Workbook
Name \a: #REF!
Name \b: #REF!
Name \c: #N/A
Name \g: #REF!
Name \O: [1]Sheet1!#REF!
Name \p: #REF!
Name \q: [2]ROCHE!#REF!
Name \r: [3]Sheet1!#REF!
Name \r: [3]Sheet1!#REF!
Name \r: [3]Sheet1!#REF!
Name \r: [3]Sheet1!#REF!
Name \r: #REF!
Name \s: [2]ROCHE!#REF!
Name \T: '[4]Noncurrent Assets'!#REF!
Name \T: '[4]Noncurrent Assets'!#REF!
Name \T: #REF!
Name \T: #REF!
Name \T: #REF!
Name \T: '[4]Noncurrent Assets'!#REF!
Name \T: '[4]Noncurrent Assets'!#REF!
Name \T: #REF!
Name \u: [2]ROCHE!#REF!
Name \v: [2]ROCHE!#REF!
Name \x: #N/A
Name \z: #N/A
Name ______DAT1: '[5]Uti per course DK'!#REF!
Name ______DAT1: '[5]Uti per course DK'!#REF!
Name ______DAT1: '[5]Uti per course DK'!#REF!
Name ______DAT1: '[5]Uti per course DK'!#REF!
Name ______DAT1: #REF!
Name ______DAT2: '[5]Uti per course DK'!#REF!
Name ______DAT2: '[5]Uti per course DK'!#REF!
Name ______DAT2: '[5]Uti per course DK'!#REF!
Name ______DAT2: '[5]Uti per course DK'!#REF!
Name ______DAT2: #REF!
Name ______EPS94: #REF!
Name ______EPS95: #REF!
Name ______EPS96: #REF!
Name ______Inc94: #REF!
Name ______Inc96: #REF!
Name ______Inc97: #REF!
Name ______Inc98: #REF!
Name ______Inc99: #REF!
Name _____Epo98: [6]Amgen!#REF!
Name _____Epo98: [6]Amgen!#REF!
Name _____Epo98: [6]Amgen!#REF!
Name _____Epo98: [6]Amgen!#REF!
Name _____Epo98: #REF!
Name _____EPS2000: [3]Sheet1!#REF!
Name _____EPS2000: [3]Sheet1!#REF!
Name _____EPS2000: [3]Sheet1!#REF!
Name _____EPS2000: [3]Sheet1!#REF!
Name _____EPS2000: #REF!
Name _____EPS93: [3]Sheet1!#REF!
Name _____EPS93: [3]Sheet1!#REF!
Name _____EPS93: [3]Sheet1!#REF!
Name _____EPS93: [3]Sheet1!#REF!
Name _____EPS93: #REF!
Name _____EPS97: [7]I!#REF!
Name _____EPS97: [7]I!#REF!

Sheet __FDSCACHE__
B1: This sheet contains FactSet XML data for use with this workbook's =FDS codes. Modifying the worksheet's contents may damage the workbook's =FDS functionality.

Sheet Income
B1: =IS!B1 -> Maplight Therapeutics, Inc. | W1: Andrew Tsai
B2: Annual and Quarterly Income Statement | W2: (415) 229-1566
W3: atsai@jefferies.com
B5: =IS!B5 -> Fiscal Year (Ending in December) | D5: =IS!D5 -> FY23 | E5: =IS!E5 -> 1Q24 | F5: =IS!F5 -> 2Q24 | G5: =IS!G5 -> 3Q24 | H5: =IS!H5 -> 4Q24 | I5: =IS!I5 -> FY24 | J5: =IS!J5 -> 1Q25 | K5: =IS!K5 -> 2Q25 | ... W5: =IS!W5 -> FY30E
B6: =IS!B6 -> ($ figures in MM, except per share) | D6: =IS!D6 -> 0 | E6: =IS!E6 -> 45352 | F6: =IS!F6 -> 45444 | G6: =IS!G6 -> 45536 | H6: =IS!H6 -> 45627 | I6: =IS!I6 -> 0 | J6: =IS!J6 -> 45717 | K6: =IS!K6 -> 45809 | ... W6: =IS!W6 -> 0
B7: =IS!B7 -> GAAP Income Statement
B8: =IS!B8 -> Revenue
B9: =IS!B9 -> Net Product Revenue | D9: =IS!D9 -> 0 | E9: =IS!E9 -> 0 | F9: =IS!F9 -> 0 | G9: =IS!G9 -> 0 | H9: =IS!H9 -> 0 | I9: =IS!I9 -> 0 | J9: =IS!J9 -> 0 | K9: =IS!K9 -> 0 | ... W9: =IS!W9 -> 35
B10: =IS!B10 -> ML-007C-MA - Total | D10: =IS!D10 -> 0 | E10: =IS!E10 -> 0 | F10: =IS!F10 -> 0 | G10: =IS!G10 -> 0 | H10: =IS!H10 -> 0 | I10: =IS!I10 -> 0 | J10: =IS!J10 -> 0 | K10: =IS!K10 -> 0 | ... W10: =IS!W10 -> 35
B11: =IS!B11 -> Schizophrenia | D11: =IS!D11 -> 0 | E11: =IS!E11 -> 0 | F11: =IS!F11 -> 0 | G11: =IS!G11 -> 0 | H11: =IS!H11 -> 0 | I11: =IS!I11 -> 0 | J11: =IS!J11 -> 0 | K11: =IS!K11 -> 0 | ... W11: =IS!W11 -> 35
B12: =IS!B12 -> Alzheimer's Disease Psychosis | D12: =IS!D12 -> 0 | E12: =IS!E12 -> 0 | F12: =IS!F12 -> 0 | G12: =IS!G12 -> 0 | H12: =IS!H12 -> 0 | I12: =IS!I12 -> 0 | J12: =IS!J12 -> 0 | K12: =IS!K12 -> 0 | ... W12: =IS!W12 -> 0
B13: =IS!B13 -> ML-004 - Autism Spectrum Disorder | D13: =IS!D13 -> 0 | E13: =IS!E13 -> 0 | F13: =IS!F13 -> 0 | G13: =IS!G13 -> 0 | H13: =IS!H13 -> 0 | I13: =IS!I13 -> 0 | J13: =IS!J13 -> 0 | K13: =IS!K13 -> 0 | ... W13: =IS!W13 -> 0
B14: =IS!B14 -> ML-021 - Parkinson's Disease | D14: =IS!D14 -> 0 | E14: =IS!E14 -> 0 | F14: =IS!F14 -> 0 | G14: =IS!G14 -> 0 | H14: =IS!H14 -> 0 | I14: =IS!I14 -> 0 | J14: =IS!J14 -> 0 | K14: =IS!K14 -> 0 | ... W14: =IS!W14 -> 0
B15: =IS!B15 -> ML-009 - Hyperactivity/Impulsivity
B16: =IS!B16 -> Other Revenue | D16: =IS!D16 -> 0 | E16: =IS!E16 -> 0 | F16: =IS!F16 -> 0 | G16: =IS!G16 -> 0 | H16: =IS!H16 -> 0 | I16: =IS!I16 -> 0 | J16: =IS!J16 -> 0 | K16: =IS!K16 -> 0 | ... W16: =IS!W16 -> 0
B17: =IS!B17 -> Licensing revenue | D17: =IS!D17 -> 0 | E17: =IS!E17 -> 0 | F17: =IS!F17 -> 0 | G17: =IS!G17 -> 0 | H17: =IS!H17 -> 0 | I17: =IS!I17 -> 0 | J17: =IS!J17 -> 0 | K17: =IS!K17 -> 0 | ... W17: =IS!W17 -> 0
B18: =IS!B18 -> Other revenue | D18: =IS!D18 -> 0 | E18: =IS!E18 -> 0 | F18: =IS!F18 -> 0 | G18: =IS!G18 -> 0 | H18: =IS!H18 -> 0 | I18: =IS!I18 -> 0 | J18: =IS!J18 -> 0 | K18: =IS!K18 -> 0 | ... W18: =IS!W18 -> 0
B19: =IS!B19 -> Total Revenues | D19: =IS!D19 -> 0 | E19: =IS!E19 -> 0 | F19: =IS!F19 -> 0 | G19: =IS!G19 -> 0 | H19: =IS!H19 -> 0 | I19: =IS!I19 -> 0 | J19: =IS!J19 -> 0 | K19: =IS!K19 -> 0 | ... W19: =IS!W19 -> 35
B20: =IS!B20 -> Cost of Sales | D20: =IS!D20 -> 0 | E20: =IS!E20 -> 0 | F20: =IS!F20 -> 0 | G20: =IS!G20 -> 0 | H20: =IS!H20 -> 0 | I20: =IS!I20 -> 0 | J20: =IS!J20 -> 0 | K20: =IS!K20 -> 0 | ... W20: =IS!W20 -> 1.75
B21: =IS!B21 -> % of Product Revenue | D21: =IS!D21 -> 0 | E21: =IS!E21 -> 0 | F21: =IS!F21 -> 0 | G21: =IS!G21 -> 0 | H21: =IS!H21 -> 0 | I21: =IS!I21 -> 0 | J21: =IS!J21 -> 0 | K21: =IS!K21 -> 0 | ... W21: =IS!W21 -> 0.05
B22: =IS!B22 -> Operating Expenses | D22: =IS!D22 -> 57.282 | E22: =IS!E22 -> 19.291 | F22: =IS!F22 -> 19.985 | G22: =IS!G22 -> 20.894 | H22: =IS!H22 -> 22.776 | I22: =IS!I22 -> 82.946 | J22: =IS!J22 -> 23.542 | K22: =IS!K22 -> 30.664 | ... W22: =IS!W22 -> 436.58528
B23: =IS!B23 -> Research and Development (R&D) | D23: =IS!D23 -> 49.675 | E23: =IS!E23 -> 15.347 | F23: =IS!F23 -> 15.642 | G23: =IS!G23 -> 16.814 | H23: =IS!H23 -> 20.72 | I23: =IS!I23 -> 68.523 | J23: =IS!J23 -> 19.786 | K23: =IS!K23 -> 26.847 | ... W23: =IS!W23 -> 385.04466
B24: =IS!B24 -> Sales, General, and Administrative (SG&A) | D24: =IS!D24 -> 7.607 | E24: =IS!E24 -> 3.944 | F24: =IS!F24 -> 4.343 | G24: =IS!G24 -> 4.08 | H24: =IS!H24 -> 2.056 | I24: =IS!I24 -> 14.423 | J24: =IS!J24 -> 3.756 | K24: =IS!K24 -> 3.817 | ... W24: =IS!W24 -> 51.540614
B25: =IS!B25 -> Other Expenses | D25: =IS!D25 -> 0 | E25: =IS!E25 -> 0 | F25: =IS!F25 -> 0 | G25: =IS!G25 -> 0 | H25: =IS!H25 -> 0 | I25: =IS!I25 -> 0 | J25: =IS!J25 -> 0 | K25: =IS!K25 -> 0 | ... W25: =IS!W25 -> 0 | AK25: C
B26: =IS!B26 -> Total Expenses | D26: =IS!D26 -> 57.282 | E26: =IS!E26 -> 19.291 | F26: =IS!F26 -> 19.985 | G26: =IS!G26 -> 20.894 | H26: =IS!H26 -> 22.776 | I26: =IS!I26 -> 82.946 | J26: =IS!J26 -> 23.542 | K26: =IS!K26 -> 30.664 | ... W26: =IS!W26 -> 438.33528
B27: =IS!B27 -> Operating Income (EBIT) | D27: =IS!D27 -> -57.282 | E27: =IS!E27 -> -19.291 | F27: =IS!F27 -> -19.985 | G27: =IS!G27 -> -20.894 | H27: =IS!H27 -> -22.776 | I27: =IS!I27 -> -82.946 | J27: =IS!J27 -> -23.542 | K27: =IS!K27 -> -30.664 | ... W27: =IS!W27 -> -403.33528
B28: =IS!B28 -> Total Other Income | D28: =IS!D28 -> 1.573 | E28: =IS!E28 -> 0.356 | F28: =IS!F28 -> 1.585 | G28: =IS!G28 -> 1.878 | H28: =IS!H28 -> 1.547 | I28: =IS!I28 -> 5.366 | J28: =IS!J28 -> 1.203 | K28: =IS!K28 -> 0.818 | ... W28: =IS!W28 -> 24.165851
B29: =IS!B29 -> Interest income | D29: =IS!D29 -> 1.099 | E29: =IS!E29 -> 0.89 | F29: =IS!F29 -> 1.634 | G29: =IS!G29 -> 1.081 | H29: =IS!H29 -> 0.899 | I29: =IS!I29 -> 4.504 | J29: =IS!J29 -> 0.811 | K29: =IS!K29 -> 0.688 | ... W29: =IS!W29 -> 24.165851
B30: =IS!B30 -> Interest expense | D30: =IS!D30 -> 0 | E30: =IS!E30 -> 0 | F30: =IS!F30 -> 0 | G30: =IS!G30 -> 0 | H30: =IS!H30 -> 0 | I30: =IS!I30 -> 0 | J30: =IS!J30 -> 0 | K30: =IS!K30 -> 0 | ... W30: =IS!W30 -> 0
B31: =IS!B31 -> Other income, net | D31: =IS!D31 -> 0.474 | E31: =IS!E31 -> -0.534 | F31: =IS!F31 -> -0.049 | G31: =IS!G31 -> 0.797 | H31: =IS!H31 -> 0.648 | I31: =IS!I31 -> 0.862 | J31: =IS!J31 -> 0.392 | K31: =IS!K31 -> 0.13 | ... W31: =IS!W31 -> 0
B32: =IS!B32 -> Pre-Tax Income | D32: =IS!D32 -> -55.709 | E32: =IS!E32 -> -18.935 | F32: =IS!F32 -> -18.4 | G32: =IS!G32 -> -19.016 | H32: =IS!H32 -> -21.229 | I32: =IS!I32 -> -77.58 | J32: =IS!J32 -> -22.339 | K32: =IS!K32 -> -29.846 | ... W32: =IS!W32 -> -379.16943
B33: =IS!B33 -> Provision for taxes (benefit) | D33: =IS!D33 -> 0 | E33: =IS!E33 -> 0 | F33: =IS!F33 -> 0 | G33: =IS!G33 -> 0 | H33: =IS!H33 -> 0 | I33: =IS!I33 -> 0 | J33: =IS!J33 -> 0 | K33: =IS!K33 -> 0 | ... W33: =IS!W33 -> 0
B34: =IS!B34 -> Tax rate | D34: =IS!D34 -> 0 | E34: =IS!E34 -> 0 | F34: =IS!F34 -> 0 | G34: =IS!G34 -> 0 | H34: =IS!H34 -> 0 | I34: =IS!I34 -> 0 | J34: =IS!J34 -> 0 | K34: =IS!K34 -> 0 | ... W34: =IS!W34 -> 0
B35: =IS!B35 -> Net Income | D35: =IS!D35 -> -55.709 | E35: =IS!E35 -> -18.935 | F35: =IS!F35 -> -18.4 | G35: =IS!G35 -> -19.016 | H35: =IS!H35 -> -21.229 | I35: =IS!I35 -> -77.58 | J35: =IS!J35 -> -22.339 | K35: =IS!K35 -> -29.846 | ... W35: =IS!W35 -> -379.16943
B36: =IS!B36 -> Other | D36: =IS!D36 -> 0 | E36: =IS!E36 -> 0 | F36: =IS!F36 -> 0 | G36: =IS!G36 -> 0 | H36: =IS!H36 -> 0 | I36: =IS!I36 -> 0 | J36: =IS!J36 -> 0 | K36: =IS!K36 -> 0 | ... W36: =IS!W36 -> 0
B37: =IS!B37 -> Net Income attributable to common stockholders | D37: =IS!D37 -> -55.709 | E37: =IS!E37 -> -18.935 | F37: =IS!F37 -> -18.4 | G37: =IS!G37 -> -19.016 | H37: =IS!H37 -> -21.229 | I37: =IS!I37 -> -77.58 | J37: =IS!J37 -> -22.339 | K37: =IS!K37 -> -29.846 | ... W37: =IS!W37 -> -379.16943
... B43: =IS!B43 -> Shares Outstanding - Fully Diluted + Options/Warrants, etc | D43: =IS!D43 -> 11.082459 | E43: =IS!E43 -> 3.9 | F43: =IS!F43 -> 18.089366 | G43: =IS!G43 -> 18.044291 | H43: =IS!H43 -> 18.046087 | I43: =IS!I43 -> 14.519936 | J43: =IS!J43 -> 18.056087 | K43: =IS!K43 -> 18.04934 | ... W43: =IS!W43 -> 66.915365

Sheet IS
B1: Maplight Therapeutics, Inc. | W1: Andrew Tsai
B2: Annual and Quarterly Income Statement | W2: (415) 229-1566
W3: atsai@jefferies.com
B5: Fiscal Year (Ending in December) | D5: FY23 | E5: 1Q24 | F5: 2Q24 | G5: 3Q24 | H5: 4Q24 | I5: FY24 | J5: 1Q25 | K5: 2Q25 | L5: 3Q25E | M5: 4Q25E | N5: FY25E | O5: 1Q26E | P5: 2Q26E | Q5: 3Q26E | R5: 4Q26E | S5: FY26E | T5: FY27E | U5: FY28E | V5: FY29E | W5: FY30E
B6: ($ figures in MM, except per share) | E6: 45352 | F6: 45444 | G6: 45536 | H6: 45627 | J6: 45717 | K6: 45809 | L6: 45901 | M6: 45992 | O6: 46082 | P6: 46174 | Q6: 46266 | R6: 46357
B7: GAAP Income Statement
B8: Revenue
B9: Net Product Revenue | D9: =SUM(D10,D13,D14,D15) -> 0 | E9: =SUM(E10,E13,E14,E15) -> 0 | F9: =SUM(F10,F13,F14,F15) -> 0 | G9: =SUM(G10,G13,G14,G15) -> 0 | H9: =SUM(H10,H13,H14,H15) -> 0 | I9: =SUM(I10,I13,I14,I15) -> 0 | J9: =SUM(J10,J13,J14,J15) -> 0 | K9: =SUM(K10,K13,K14,K15) -> 0 | ... W9: =SUM(W10,W13,W14,W15) -> 35
B10: ML-007C-MA - Total | D10: =D11+D12 -> 0 | E10: =E11+E12 -> 0 | F10: =F11+F12 -> 0 | G10: =G11+G12 -> 0 | H10: =H11+H12 -> 0 | I10: =I11+I12 -> 0 | J10: =J11+J12 -> 0 | K10: =K11+K12 -> 0 | ... W10: =W11+W12 -> 35
B11: Schizophrenia | D11: 0 | E11: 0 | F11: 0 | G11: 0 | H11: 0 | I11: =SUM(E11:H11) -> 0 | J11: 0 | K11: 0 | L11: 0 | M11: 0 | N11: =SUM(J11:M11) -> 0 | O11: 0 | P11: 0 | Q11: 0 | R11: 0 | S11: =SUM(O11:R11) -> 0 | T11: 0 | U11: 0 | V11: 0 | W11: 35
B12: Alzheimer's Disease Psychosis | D12: 0 | E12: 0 | F12: 0 | G12: 0 | H12: 0 | I12: =SUM(E12:H12) -> 0 | J12: 0 | K12: 0 | L12: 0 | M12: 0 | N12: =SUM(J12:M12) -> 0 | O12: 0 | P12: 0 | Q12: 0 | R12: 0 | S12: =SUM(O12:R12) -> 0 | T12: 0 | U12: 0 | V12: 0 | W12: 0
B13: ML-004 - Autism Spectrum Disorder | D13: 0 | E13: 0 | F13: 0 | G13: 0 | H13: 0 | I13: =SUM(E13:H13) -> 0 | J13: 0 | K13: 0 | L13: 0 | M13: 0 | N13: =SUM(J13:M13) -> 0 | O13: 0 | P13: 0 | Q13: 0 | R13: 0 | S13: =SUM(O13:R13) -> 0 | T13: 0 | U13: 0 | V13: 0 | W13: 0
B14: ML-021 - Parkinson's Disease | D14: 0 | E14: 0 | F14: 0 | G14: 0 | H14: 0 | I14: =SUM(E14:H14) -> 0 | J14: 0 | K14: 0 | L14: 0 | M14: 0 | N14: =SUM(J14:M14) -> 0 | O14: 0 | P14: 0 | Q14: 0 | R14: 0 | S14: =SUM(O14:R14) -> 0 | T14: 0 | U14: 0 | V14: 0 | W14: 0
B15: ML-009 - Hyperactivity/Impulsivity | D15: 0 | E15: 0 | F15: 0 | G15: 0 | H15: 0 | I15: =SUM(E15:H15) -> 0 | J15: 0 | K15: 0 | L15: 0 | M15: 0 | N15: =SUM(J15:M15) -> 0 | O15: 0 | P15: 0 | Q15: 0 | R15: 0 | S15: =SUM(O15:R15) -> 0
B16: Other Revenue | D16: =SUM(D17:D18) -> 0 | E16: =SUM(E17:E18) -> 0 | F16: =SUM(F17:F18) -> 0 | G16: =SUM(G17:G18) -> 0 | H16: =SUM(H17:H18) -> 0 | I16: =SUM(I17:I18) -> 0 | J16: =SUM(J17:J18) -> 0 | K16: =SUM(K17:K18) -> 0 | ... W16: =SUM(W17:W18) -> 0
B17: Licensing revenue | D17: 0 | E17: 0 | F17: 0 | G17: 0 | H17: 0 | I17: =SUM(E17:H17) -> 0 | J17: 0 | K17: 0 | L17: 0 | M17: 0 | N17: =SUM(J17:M17) -> 0 | O17: 0 | P17: 0 | Q17: 0 | R17: 0 | S17: =SUM(O17:R17) -> 0 | T17: 0 | U17: 0 | V17: 0 | W17: 0
B18: Other revenue | D18: 0 | E18: 0 | F18: 0 | G18: 0 | H18: 0 | I18: =SUM(E18:H18) -> 0 | J18: 0 | K18: 0 | L18: 0 | M18: 0 | N18: =SUM(J18:M18) -> 0 | O18: 0 | P18: 0 | Q18: 0 | R18: 0 | S18: =SUM(O18:R18) -> 0 | T18: 0 | U18: 0 | V18: 0 | W18: 0
B19: Total Revenues | D19: =D9+D16 -> 0 | E19: =E9+E16 -> 0 | F19: =F9+F16 -> 0 | G19: =G9+G16 -> 0 | H19: =H9+H16 -> 0 | I19: =I9+I16 -> 0 | J19: =J9+J16 -> 0 | K19: =K9+K16 -> 0 | ... W19: =W9+W16 -> 35
B20: Cost of Sales | D20: 0 | E20: 0 | F20: =F21*F9 -> 0 | G20: =G21*G9 -> 0 | H20: =H21*H9 -> 0 | I20: =SUM(E20:H20) -> 0 | J20: =J21*J9 -> 0 | K20: =K21*K9 -> 0 | L20: =L21*L9 -> 0 | M20: =M21*M9 -> 0 | N20: =SUM(J20:M20) -> 0 | O20: =O21*O9 -> 0 | P20: =P21*P9 -> 0 | Q20: =Q21*Q9 -> 0 | R20: =R21*R9 -> 0 | S20: =SUM(O20:R20) -> 0 | T20: =T21*T9 -> 0 | U20: =U21*U9 -> 0 | V20: =V21*V9 -> 0 | W20: =W21*W9 -> 1.75
B21: % of Product Revenue | D21: =IFERROR(D20/D9,0) -> 0 | E21: =IFERROR(E20/E9,0) -> 0 | F21: 0 | G21: 0 | H21: 0 | I21: =IFERROR(I20/I9,0) -> 0 | J21: 0 | K21: 0 | L21: 0 | M21: =IF(M9>0,5%,0%) -> 0 | N21: =IFERROR(N20/N9,0) -> 0 | O21: =IF(O9>0,5%,0%) -> 0 | P21: =IF(P9>0,5%,0%) -> 0 | Q21: =IF(Q9>0,5%,0%) -> 0 | R21: =IF(R9>0,5%,0%) -> 0 | S21: =IFERROR(S20/S9,0) -> 0 | T21: =IF(T9>0,5%,0%) -> 0 | U21: =IF(U9>0,5%,0%) -> 0 | V21: =IF(V9>0,5%,0%) -> 0 | W21: =IF(W9>0,5%,0%) -> 0.05
B22: Operating Expenses | D22: =SUM(D23:D25) -> 57.282 | E22: =SUM(E23:E25) -> 19.291 | F22: =SUM(F23:F25) -> 19.985 | G22: =SUM(G23:G25) -> 20.894 | H22: =SUM(H23:H25) -> 22.776 | I22: =SUM(I23:I25) -> 82.946 | J22: =SUM(J23:J25) -> 23.542 | K22: =SUM(K23:K25) -> 30.664 | ... W22: =SUM(W23:W25) -> 436.58528
B23: Research and Development (R&D) | D23: 49.675 | E23: 15.347 | F23: =30.989-E23 -> 15.642 | G23: 16.814 | H23: =68.523-SUM(E23:G23) -> 20.72 | I23: =SUM(E23:H23) -> 68.523 | J23: 19.786 | K23: =46.633-J23 -> 26.847 | L23: 27.094 | M23: =M75 -> 34 | N23: =SUM(J23:M23) -> 107.727 | O23: =O75 -> 38 | P23: =P75 -> 42 | Q23: =Q75 -> 47 | R23: =R75 -> 53 | S23: =SUM(O23:R23) -> 180 | T23: =T75 -> 271.9 | U23: =U75 -> 305.185 | V23: =V75 -> 342.71275 | W23: =W75 -> 385.04466
B24: Sales, General, and Administrative (SG&A) | D24: 7.607 | E24: 3.944 | F24: =8.287-E24 -> 4.343 | G24: 4.08 | H24: =14.423-SUM(E24:G24) -> 2.056 | I24: =SUM(E24:H24) -> 14.423 | J24: 3.756 | K24: =7.573-J24 -> 3.817 | L24: 4.404 | M24: =M78 -> 4.8 | N24: =SUM(J24:M24) -> 16.777 | O24: =O78 -> 5.4 | P24: =P78 -> 6 | Q24: =Q78 -> 6.6 | R24: =R78 -> 7.2 | S24: =SUM(O24:R24) -> 25.2 | T24: =T78 -> 30.13 | U24: =U78 -> 36.0295 | V24: =V78 -> 43.089925 | W24: =W78 -> 51.540614
B25: Other Expenses | D25: 0 | E25: 0 | F25: 0 | G25: 0 | H25: 0 | I25: =SUM(E25:H25) -> 0 | J25: 0 | K25: 0 | L25: 0 | M25: 0 | N25: =SUM(J25:M25) -> 0 | O25: 0 | P25: 0 | Q25: 0 | R25: 0 | S25: =SUM(O25:R25) -> 0 | T25: 0 | U25: 0 | V25: 0 | W25: 0
B26: Total Expenses | D26: =SUM(D22,D20) -> 57.282 | E26: =SUM(E22,E20) -> 19.291 | F26: =SUM(F22,F20) -> 19.985 | G26: =SUM(G22,G20) -> 20.894 | H26: =SUM(H22,H20) -> 22.776 | I26: =SUM(I22,I20) -> 82.946 | J26: =SUM(J22,J20) -> 23.542 | K26: =SUM(K22,K20) -> 30.664 | ... W26: =SUM(W22,W20) -> 438.33528
B27: Operating Income (EBIT) | D27: =SUM(-D26,D19) -> -57.282 | E27: =SUM(-E26,E19) -> -19.291 | F27: =SUM(-F26,F19) -> -19.985 | G27: =SUM(-G26,G19) -> -20.894 | H27: =SUM(-H26,H19) -> -22.776 | I27: =SUM(-I26,I19) -> -82.946 | J27: =SUM(-J26,J19) -> -23.542 | K27: =SUM(-K26,K19) -> -30.664 | ... W27: =SUM(-W26,W19) -> -403.33528
B28: Total Other Income | D28: =SUM(D29:D31) -> 1.573 | E28: =SUM(E29:E31) -> 0.356 | F28: =SUM(F29:F31) -> 1.585 | G28: =SUM(G29:G31) -> 1.878 | H28: =SUM(H29:H31) -> 1.547 | I28: =SUM(I29:I31) -> 5.366 | J28: =SUM(J29:J31) -> 1.203 | K28: =SUM(K29:K31) -> 0.818 | ... W28: =SUM(W29:W31) -> 24.165851
B29: Interest income | D29: 1.099 | E29: 0.89 | F29: =2.524-E29 -> 1.634 | G29: 1.081 | H29: =4.504-SUM(E29:G29) -> 0.899 | I29: =SUM(E29:H29) -> 4.504 | J29: 0.811 | K29: =1.499-J29 -> 0.688 | L29: 1.549 | M29: =AVERAGE(K67,L67)*5%/4 -> 1.79775 | N29: =SUM(J29:M29) -> 4.84575 | O29: =AVERAGE(M67,M59)*5%/4 -> 4.4627081 | P29: =AVERAGE(N67,O67)*5%/4 -> 5.8468332 | Q29: =AVERAGE(O67,P67)*5%/4 -> 5.3500178 | R29: =AVERAGE(P67,Q67)*5%/4 -> 6.0099981 | S29: =SUM(O29:R29) -> 21.669557 | T29: =AVERAGE(N67,S67)*5% -> 24.702504 | U29: =AVERAGE(O67,T67)*5% -> 26.070384 | V29: =AVERAGE(P67,U67)*5% -> 17.35319 | W29: =AVERAGE(Q67,V67)*5% -> 24.165851
B30: Interest expense | D30: 0 | E30: 0 | F30: 0 | G30: 0 | H30: 0 | I30: =SUM(E30:H30) -> 0 | J30: 0 | K30: 0 | L30: 0 | M30: =-M70*6.7%/4 -> 0 | N30: =SUM(J30:M30) -> 0 | O30: =-O70*6.7%/4 -> 0 | P30: =-P70*6.7%/4 -> 0 | Q30: =-Q70*6.7%/4 -> 0 | R30: =-R70*6.7%/4 -> 0 | S30: =SUM(O30:R30) -> 0 | T30: =-T70*6.7% -> 0 | U30: =-U70*6.7% -> 0 | V30: =-V70*6.7% -> 0 | W30: =-W70*6.7% -> 0
B31: Other income, net | D31: =-0.514+0.986+0.002 -> 0.474 | E31: -0.534 | F31: =0.403-0.986-E31 -> -0.049 | G31: 0.797 | H31: =SUM(1.848-0.986-SUM(E31:G31)) -> 0.648 | I31: =SUM(E31:H31) -> 0.862 | J31: 0.392 | K31: =0.522-J31 -> 0.13 | L31: 0.531 | M31: 0 | N31: =SUM(J31:M31) -> 1.053 | O31: 0 | P31: 0 | Q31: 0 | R31: 0 | S31: =SUM(O31:R31) -> 0 | T31: 0 | U31: 0 | V31: 0 | W31: 0
B32: Pre-Tax Income | D32: =D28+D27 -> -55.709 | E32: =E28+E27 -> -18.935 | F32: =F28+F27 -> -18.4 | G32: =G28+G27 -> -19.016 | H32: =H28+H27 -> -21.229 | I32: =I28+I27 -> -77.58 | J32: =J28+J27 -> -22.339 | K32: =K28+K27 -> -29.846 | ... W32: =W28+W27 -> -379.16943
B33: Provision for taxes (benefit) | D33: 0 | E33: 0 | F33: 0 | G33: 0 | H33: 0 | I33: =SUM(E33:H33) -> 0 | J33: 0 | K33: 0 | L33: 0 | M33: 0 | N33: =SUM(J33:M33) -> 0 | O33: 0 | P33: 0 | Q33: 0 | R33: 0 | S33: =SUM(O33:R33) -> 0 | T33: 0 | U33: 0 | V33: 0 | W33: 0
B34: Tax rate | D34: =IFERROR(D33/D32,0%) -> 0 | E34: =IFERROR(E33/E32,0%) -> 0 | F34: =IFERROR(F33/F32,0%) -> 0 | G34: =IFERROR(G33/G32,0%) -> 0 | H34: =IFERROR(H33/H32,0%) -> 0 | I34: =IFERROR(I33/I32,0%) -> 0 | J34: =IFERROR(J33/J32,0%) -> 0 | K34: =IFERROR(K33/K32,0%) -> 0 | ... W34: =IFERROR(W33/W32,0%) -> 0
B35: Net Income | D35: =D32-D33 -> -55.709 | E35: =E32-E33 -> -18.935 | F35: =F32-F33 -> -18.4 | G35: =G32-G33 -> -19.016 | H35: =H32-H33 -> -21.229 | I35: =I32-I33 -> -77.58 | J35: =J32-J33 -> -22.339 | K35: =K32-K33 -> -29.846 | ... W35: =W32-W33 -> -379.16943
B36: Other | D36: 0 | E36: 0 | F36: 0 | G36: 0 | H36: 0 | I36: =SUM(E36:H36) -> 0 | J36: 0 | K36: 0 | L36: 0 | M36: 0 | N36: =SUM(J36:M36) -> 0 | O36: 0 | P36: 0 | Q36: 0 | R36: 0 | S36: =SUM(O36:R36) -> 0 | T36: 0 | U36: 0 | V36: 0 | W36: 0
B37: Net Income attributable to common stockholders | D37: =D35+D36 -> -55.709 | E37: =E35+E36 -> -18.935 | F37: =F35+F36 -> -18.4 | G37: =G35+G36 -> -19.016 | H37: =H35+H36 -> -21.229 | I37: =I35+I36 -> -77.58 | J37: =J35+J36 -> -22.339 | K37: =K35+K36 -> -29.846 | ... W37: =W35+W36 -> -379.16943
B38: EPS (Basic) | D38: =D35/D40 -> -5.0267725 | E38: =E35/E40 -> -27.05 | F38: =F35/F40 -> -25.315585 | G38: =G35/G40 -> -25.080321 | H38: =H35/H40 -> -27.932895 | I38: =I35/I40 -> -105.37078 | J38: =J35/J40 -> -29.011688 | K38: =K35/K40 -> -39.532906 | ... W38: =W35/W40 -> -6.2381496
B39: EPS (Diluted, as reported) | D39: =D35/D41 -> -5.0267725 | E39: =E35/E41 -> -27.05 | F39: =F35/F41 -> -25.315585 | G39: =G35/G41 -> -25.080321 | H39: =H35/H41 -> -27.932895 | I39: =I35/I41 -> -105.37078 | J39: =J35/J41 -> -29.011688 | K39: =K35/K41 -> -39.532906 | ... W39: =W35/W41 -> -6.2381496
B40: Shares Outstanding - Basic | D40: 11.082459 | E40: 0.7 | F40: =0.728343*3-G40-E40 -> 0.726825 | G40: 0.758204 | H40: =0.76 -> 0.76 | I40: =AVERAGE(E40:H40) -> 0.73625725 | J40: 0.77 | K40: =0.772031*3-L40-J40 -> 0.754966 | L40: 0.791127 | M40: =45.373033 -> 45.373033 | N40: =AVERAGE(J40:M40) -> 11.922282 | O40: =M40*1.001+O53 -> 45.418406 | P40: =O40*1.001+P53 -> 45.463824 | Q40: =P40*1.001+Q53 -> 50.509288 | R40: =Q40*1.001+R53 -> 50.559798 | S40: =AVERAGE(O40:R40) -> 47.987829 | T40: =R40*1.001+T53 -> 55.610357 | U40: =T40*1.001+U53 -> 55.665968 | V40: =U40*1.001+V53 -> 60.721634 | W40: =V40*1.001+W53 -> 60.782355
B41: Shares Outstanding - Diluted (as reported) | D41: =D40 -> 11.082459 | E41: =IF(E37<0,E40,E40+E50) -> 0.7 | F41: =IF(F37<0,F40,F40+F50) -> 0.726825 | G41: =IF(G37<0,G40,G40+G50) -> 0.758204 | H41: =IF(H37<0,H40,H40+H50) -> 0.76 | I41: =I40 -> 0.73625725 | J41: =IF(J37<0,J40,J40+J50) -> 0.77 | K41: =IF(K37<0,K40,K40+K50) -> 0.754966 | L41: =IF(L37<0,L40,L40+L50) -> 0.791127 | M41: =IF(M37<0,M40,M40+M50) -> 45.373033 | N41: =AVERAGE(J41:M41) -> 11.922282 | O41: =IF(O37<0,O40,O40+O50) -> 45.418406 | P41: =IF(P37<0,P40,P40+P50) -> 45.463824 | Q41: =IF(Q37<0,Q40,Q40+Q50) -> 50.509288 | R41: =IF(R37<0,R40,R40+R50) -> 50.559798 | S41: =AVERAGE(O41:R41) -> 47.987829 | T41: =IF(T37<0,T40,T40+T50) -> 55.610357 | U41: =IF(U37<0,U40,U40+U50) -> 55.665968 | V41: =IF(V37<0,V40,V40+V50) -> 60.721634 | W41: =IF(W37<0,W40,W40+W50) -> 60.782355
B42: Shares Outstanding - Fully Diluted + Preferred/Warrants | D42: =D41+D46+D47+D48 -> 11.082459 | E42: =E41+E46+E47+E48 -> 2.7 | F42: =F41+F46+F47+F48 -> 17.088419 | G42: =G41+G46+G47+G48 -> 17.079746 | H42: =H41+H46+H47+H48 -> 17.081542 | I42: =AVERAGE(E42:H42) -> 13.487427 | J42: =J41+J46+J47+J48 -> 17.091542 | K42: =K41+K46+K47+K48 -> 17.097178 | L42: =L41+L46+L47+L48 -> 32.416337 | M42: =M41+M46+M47+M48 -> 50.573033 | N42: =AVERAGE(J42:M42) -> 29.294522 | O42: =O41+O46+O47+O48 -> 50.618406 | P42: =P41+P46+P47+P48 -> 50.663824 | Q42: =Q41+Q46+Q47+Q48 -> 55.709288 | R42: =R41+R46+R47+R48 -> 55.759798 | S42: =AVERAGE(O42:R42) -> 53.187829 | T42: =T41+T46+T47+T48 -> 60.810357 | U42: =U41+U46+U47+U48 -> 60.865968 | V42: =V41+V46+V47+V48 -> 65.921634 | W42: =W41+W46+W47+W48 -> 65.982355
B43: Shares Outstanding - Fully Diluted + Options/Warrants, etc | D43: =IF(D38<0,D41+D50,D41) -> 11.082459 | E43: =IF(E38<0,E41+E50,E41) -> 3.9 | F43: =IF(F38<0,F41+F50,F41) -> 18.089366 | G43: =IF(G38<0,G41+G50,G41) -> 18.044291 | H43: =IF(H38<0,H41+H50,H41) -> 18.046087 | I43: =AVERAGE(E43:H43) -> 14.519936 | J43: =IF(J38<0,J41+J50,J41) -> 18.056087 | K43: =IF(K38<0,K41+K50,K41) -> 18.04934 | L43: =IF(L38<0,L41+L50,L41) -> 33.349347 | M43: =IF(M38<0,M41+M50,M41) -> 51.506043 | N43: =AVERAGE(J43:M43) -> 30.240204 | O43: =IF(O38<0,O41+O50,O41) -> 51.551416 | P43: =IF(P38<0,P41+P50,P41) -> 51.596834 | Q43: =IF(Q38<0,Q41+Q50,Q41) -> 56.642298 | R43: =IF(R38<0,R41+R50,R41) -> 56.692808 | S43: =AVERAGE(O43:R43) -> 54.120839 | T43: =IF(T38<0,T41+T50,T41) -> 61.743367 | U43: =IF(U38<0,U41+U50,U41) -> 61.798978 | V43: =IF(V38<0,V41+V50,V41) -> 66.854644 | W43: =IF(W38<0,W41+W50,W41) -> 66.915365
B45: Dilutive Securities
B46: Convertible Preferred Stock | E46: 1 | F46: 12.911004 | G46: 12.911004 | H46: =G46 -> 12.911004 | I46: =H46 -> 12.911004 | J46: =I46 -> 12.911004 | K46: =12.911004 -> 12.911004 | L46: 25.412974 | M46: 0 | N46: =M46 -> 0 | O46: =M46 -> 0 | P46: =O46 -> 0 | Q46: =P46 -> 0 | R46: =Q46 -> 0 | S46: =R46 -> 0 | T46: =S46 -> 0 | U46: =T46 -> 0 | V46: =U46 -> 0 | W46: =V46 -> 0
B47: Preferred Stock Warrants | E47: 0 | F47: 0 | G47: 0 | H47: =G47 -> 0 | I47: =H47 -> 0 | J47: =I47 -> 0 | K47: 0 | L47: 0 | M47: =L47 -> 0 | N47: =M47 -> 0 | O47: =M47 -> 0 | P47: =O47 -> 0 | Q47: =P47 -> 0 | R47: =Q47 -> 0 | S47: =R47 -> 0 | T47: =S47 -> 0 | U47: =T47 -> 0 | V47: =U47 -> 0 | W47: =V47 -> 0
B48: Restricted Common Stock (RSU) | E48: 1 | F48: 3.45059 | G48: =3.410538 -> 3.410538 | H48: =G48 -> 3.410538 | I48: =H48 -> 3.410538 | J48: =I48 -> 3.410538 | K48: 3.431208 | L48: =6.212236 -> 6.212236 | M48: 5.2 | N48: =M48 -> 5.2 | O48: =M48 -> 5.2 | P48: =O48 -> 5.2 | Q48: =P48 -> 5.2 | R48: =Q48 -> 5.2 | S48: =R48 -> 5.2 | T48: =S48 -> 5.2 | U48: =T48 -> 5.2 | V48: =U48 -> 5.2 | W48: =V48 -> 5.2
B49: Stock options issued and outstanding | E49: 1.2 | F49: 1.0009468 | G49: =0.964545 -> 0.964545 | H49: =G49 -> 0.964545 | I49: =H49 -> 0.964545 | J49: =I49 -> 0.964545 | K49: 0.952162 | L49: =0.93301 -> 0.93301 | M49: =L49 -> 0.93301 | N49: =M49 -> 0.93301 | O49: =M49 -> 0.93301 | P49: =O49 -> 0.93301 | Q49: =P49 -> 0.93301 | R49: =Q49 -> 0.93301 | S49: =R49 -> 0.93301 | T49: =S49 -> 0.93301 | U49: =T49 -> 0.93301 | V49: =U49 -> 0.93301 | W49: =V49 -> 0.93301
B50: Total dilutive securities | D50: =SUM(D46:D49) -> 0 | E50: =SUM(E46:E49) -> 3.2 | F50: =SUM(F46:F49) -> 17.362541 | G50: =SUM(G46:G49) -> 17.286087 | H50: =SUM(H46:H49) -> 17.286087 | I50: =H50 -> 17.286087 | J50: =SUM(J46:J49) -> 17.286087 | K50: =SUM(K46:K49) -> 17.294374 | L50: =SUM(L46:L49) -> 32.55822 | M50: =SUM(M46:M49) -> 6.13301 | N50: =M50 -> 6.13301 | O50: =SUM(O46:O49) -> 6.13301 | P50: =SUM(P46:P49) -> 6.13301 | Q50: =SUM(Q46:Q49) -> 6.13301 | R50: =SUM(R46:R49) -> 6.13301 | S50: =R50 -> 6.13301 | T50: =SUM(T46:T49) -> 6.13301 | U50: =SUM(U46:U49) -> 6.13301 | V50: =SUM(V46:V49) -> 6.13301 | W50: =SUM(W46:W49) -> 6.13301
B52: Public & Private Financing
B53: # of shares | D53: 0 | E53: 0 | F53: 0 | G53: 0 | H53: 0 | J53: 0 | K53: 0 | L53: =L55/L54 -> 12.470588 | M53: =14.75+2.2125+0.476707 -> 17.439207 | O53: 0 | P53: 0 | Q53: 5 | R53: 0 | T53: 5 | U53: 0 | V53: 5 | W53: 0
B54: Issue Price | D54: 0 | E54: 0 | F54: 0 | G54: 0 | H54: 0 | J54: 0 | K54: 0 | L54: =M54/1.06 -> 16.037736 | M54: 17 | O54: 0 | P54: 0 | Q54: 40 | R54: 0 | T54: 75 | U54: 0 | V54: 100 | W54: 0
B55: Proceeds (before transaction costs) | D55: =D54*D53 -> 0 | E55: =E54*E53 -> 0 | F55: =F54*F53 -> 0 | G55: 0 | H55: 0 | J55: =J54*J53 -> 0 | K55: =K54*K53 -> 0 | L55: 200 | M55: =M53*M54 -> 296.46652 | O55: =O54*O53 -> 0 | P55: =P54*P53 -> 0 | Q55: =Q54*Q53 -> 200 | R55: =R54*R53 -> 0 | T55: =T54*T53 -> 375 | U55: =U54*U53 -> 0 | V55: =V54*V53 -> 500 | W55: =W54*W53 -> 0
B56: Proceeds (after transaction costs) | D56: =D55*(1-5.9555%) -> 0 | E56: =E55*(1-3%) -> 0 | F56: =F55*(1-3%) -> 0 | G56: 0 | H56: 0 | J56: =J55*(1-5.9555%) -> 0 | K56: =K55*(1-5.9555%) -> 0 | L56: =L55*(1-5.9555%) -> 188.089 | M56: =M55*(1-0.0900505902192243%) -> 296.19955 | O56: =O55*(1-5.9555%) -> 0 | P56: =P55*(1-5.9555%) -> 0 | Q56: =Q55*(1-3%) -> 194 | R56: =R55*(1-5.9555%) -> 0 | T56: =T55*(1-3%) -> 363.75 | U56: =U55*(1-3%) -> 0 | V56: =V55*(1-3%) -> 485 | W56: =W55*(1-3%) -> 0
B58: CASH ANALYSIS
B59: Cash at beginning of period | D59: =CF!I52 -> 27.899 | E59: =D67 -> 79.769 | F59: =E67 -> 179.788 | G59: =F67 -> 160.558 | H59: =G67 -> 141.804 | I59: =D67 -> 79.769 | J59: =I67 -> 118.159 | K59: =J67 -> 94.757 | L59: =K67 -> 60.472 | M59: =L67 -> 227.168 | N59: =I67 -> 118.159 | O59: =N67 -> 486.8653 | P59: =O67 -> 448.62801 | Q59: =P67 -> 407.37484 | R59: =Q67 -> 554.22486 | S59: =N67 -> 486.8653 | T59: =S67 -> 501.23486 | U59: =T67 -> 594.18736 | V59: =U67 -> 286.75274 | W59: =V67 -> 412.40918
B60: Net income | D60: =D35 -> -55.709 | E60: =E35 -> -18.935 | F60: =F35 -> -18.4 | G60: =G35 -> -19.016 | H60: =H35 -> -21.229 | I60: =I35 -> -77.58 | J60: =J35 -> -22.339 | K60: =K35 -> -29.846 | ... W60: =W35 -> -379.16943
B61: Stock Comp | D61: 1.045 | E61: =CF!J13 -> 0.267 | F61: =CF!K13 -> 0.245 | G61: =G76+G79 -> 0.262 | H61: =H76+H79 -> 0.306 | I61: =SUM(E61:H61) -> 1.08 | J61: =CF!O13 -> 0.212 | K61: =CF!P13 -> 0.148 | L61: =CF!Q13 -> 0.125 | M61: =M76+M79 -> 0.5 | N61: =SUM(J61:M61) -> 0.985 | O61: =O76+O79 -> 0.7 | P61: =P76+P79 -> 0.9 | Q61: =Q76+Q79 -> 1.1 | R61: =R76+R79 -> 1.2 | S61: =SUM(O61:R61) -> 3.9 | T61: =T76+T79 -> 6.53 | U61: =U76+U79 -> 7.7095 | V61: =V76+V79 -> 9.105925 | W61: =W76+W79 -> 10.759814
B62: Working Capital | D62: =BS!I15-BS!I30 -> 68.906 | E62: =SUM(CF!J20:J29) -> -2.093 | F62: =SUM(CF!K20:K29) -> 0.218 | G62: =SUM(CF!L20:L29) -> 0 | H62: =SUM(CF!M20:M29) -> -2.722 | I62: =SUM(E62:H62) -> -4.597 | J62: =SUM(CF!O20:O29) -> -3.544 | K62: =SUM(CF!P20:P29) -> -5.177 | L62: =SUM(CF!Q20:Q29) -> -2.393 | M62: =SUM(CF!R20:R29) -> 0 | N62: =SUM(J62:M62) -> -11.114 | O62: =SUM(CF!T20:T29) -> 0 | P62: =SUM(CF!U20:U29) -> 0 | Q62: =SUM(CF!V20:V29) -> 0 | R62: =SUM(CF!W20:W29) -> 0 | S62: =SUM(O62:R62) -> 0 | T62: =SUM(CF!Y20:Y29) -> 0 | U62: =SUM(CF!Z20:Z29) -> 0 | V62: =SUM(CF!AA20:AA29) -> 0 | W62: =SUM(CF!AB20:AB29) -> 0
B63: CapEx | D63: =CF!I35 -> -0.462 | E63: =CF!J35 -> -0.002 | F63: =CF!K35 -> -0.288 | G63: 0 | H63: 0 | I63: =SUM(E63:H63) -> -0.29 | J63: =CF!O35 -> 0 | K63: =CF!P35 -> -0.066 | L63: =CF!Q35 -> -0.031 | M63: 0 | N63: =SUM(J63:M63) -> -0.097 | O63: 0 | P63: 0 | Q63: 0 | R63: 0 | S63: =SUM(O63:R63) -> 0 | T63: 0 | U63: 0 | V63: 0 | W63: 0
B64: Debt | D64: =CF!I43+CF!I44 -> 0 | E64: =CF!J43+CF!J44 -> 0 | F64: =CF!K43+CF!K44 -> 0 | G64: =CF!L43+CF!L44 -> 0 | H64: =CF!M43+CF!M44 -> 0 | I64: =SUM(E64:H64) -> 0 | J64: =CF!O43+CF!O44 -> 0 | K64: =CF!P43+CF!P44 -> 0 | L64: =CF!Q43+CF!Q44 -> 0 | M64: =CF!R43+CF!R44 -> 0 | N64: =SUM(J64:M64) -> 0 | O64: =CF!T43+CF!T44 -> 0 | P64: =CF!U43+CF!U44 -> 0 | Q64: =CF!V43+CF!V44 -> 0 | R64: =CF!W43+CF!W44 -> 0 | S64: =SUM(O64:R64) -> 0 | T64: =CF!Y43+CF!Y44 -> 0 | U64: =CF!Z43+CF!Z44 -> 0 | V64: =CF!AA43+CF!AA44 -> 0 | W64: =CF!AB43+CF!AB44 -> 0
B65: Financing activities | D65: =CF!I46 -> 104.572 | E65: =CF!J40+CF!J41+CF!J42 -> 119.96 | F65: =CF!K40+CF!K41+CF!K42 -> 0.261 | G65: =G56 -> 0 | H65: =H56 -> 0 | I65: =SUM(E65:H65) -> 120.221 | J65: =CF!O40+CF!O41+CF!O42 -> 0.005 | K65: =CF!P40+CF!P41+CF!P42 -> 0.003 | L65: =CF!Q40+CF!Q41+CF!Q42 -> 198.974 | M65: =M56 -> 296.19955 | N65: =SUM(J65:M65) -> 495.18155 | O65: =O56 -> 0 | P65: =P56 -> 0 | Q65: =Q56 -> 194 | R65: =R56 -> 0 | S65: =SUM(O65:R65) -> 194 | T65: =T56 -> 363.75 | U65: =U56 -> 0 | V65: =V56 -> 485 | W65: =W56 -> 0
B66: Other | D66: =D67-SUM(D59:D65) -> -66.482 | E66: =E67-SUM(E59:E65) -> 0.822 | F66: =F67-SUM(F59:F65) -> -1.266 | H66: 0 | I66: =SUM(E66:H66) -> -0.444 | J66: =J67-SUM(J59:J65) -> 2.264 | K66: =K67-SUM(K59:K65) -> 0.653 | L66: =L67-SUM(L59:L65) -> -0.561 | M66: 0 | N66: =SUM(J66:M66) -> 2.356 | O66: 0 | P66: 0 | R66: 0 | S66: =SUM(O66:R66) -> 0 | T66: 0 | U66: 0 | V66: 0 | W66: 0
B67: Cash at end | D67: =BS!I8 -> 79.769 | E67: =BS!J51 -> 179.788 | F67: =BS!K51 -> 160.558 | G67: =SUM(G59:G66) -> 141.804 | H67: =SUM(H59:H66) -> 118.159 | I67: =SUM(I59:I66) -> 118.159 | J67: =BS!O51 -> 94.757 | K67: =BS!P51 -> 60.472 | L67: =BS!Q51 -> 227.168 | M67: =SUM(M59:M66) -> 486.8653 | N67: =SUM(N59:N66) -> 486.8653 | O67: =SUM(O59:O66) -> 448.62801 | P67: =SUM(P59:P66) -> 407.37484 | Q67: =SUM(Q59:Q66) -> 554.22486 | R67: =SUM(R59:R66) -> 501.23486 | S67: =SUM(S59:S66) -> 501.23486 | T67: =SUM(T59:T66) -> 594.18736 | ... W67: =SUM(W59:W66) -> 43.999573
B68: Cash/share | D68: =D67/D42 -> 7.1977708 | E68: =E67/E42 -> 66.588148 | F68: =F67/F42 -> 9.39572 | G68: =G67/G42 -> 8.3024654 | H68: =H67/H42 -> 6.9173497 | I68: =I67/I42 -> 8.7606778 | J68: =J67/J42 -> 5.5440872 | K68: =K67/K42 -> 3.536958 | ... W68: =W67/W42 -> 0.66683847
B69: Cash Burn | D69: =D59-D67+D65 -> 52.702 | E69: =E59-E67+E65 -> 19.941 | F69: =F59-F67+F65 -> 19.491 | G69: =G59-G67+G65 -> 18.754 | H69: =H59-H67+H65 -> 23.645 | I69: =I59-I67+I65 -> 81.831 | J69: =J59-J67+J65 -> 23.407 | K69: =K59-K67+K65 -> 34.288 | ... W69: =W59-W67+W65 -> 368.40961
B70: Debt | D70: =BS!I52 -> 0 | E70: =BS!J52 -> 0 | F70: =BS!K52 -> 0 | G70: =BS!P52 -> 0 | H70: =BS!Q52 -> 0 | I70: =H70 -> 0 | J70: =BS!O52 -> 0 | K70: =BS!T52 -> 0 | L70: =BS!U52 -> 0 | M70: =BS!R52 -> 0 | N70: =M70 -> 0 | O70: =BS!X52 -> 0 | P70: =BS!Y52 -> 0 | Q70: =BS!Z52 -> 0 | R70: =BS!AA52 -> 0 | S70: =R70 -> 0 | T70: =BS!Y52 -> 0 | U70: =BS!Z52 -> 0 | V70: =BS!AA52 -> 0 | W70: =BS!AB52 -> 0
B71: Net Debt | D71: =D70-D67 -> -79.769 | E71: =E70-E67 -> -179.788 | F71: =F70-F67 -> -160.558 | G71: =G70-G67 -> -141.804 | H71: =H70-H67 -> -118.159 | I71: =I70-I67 -> -118.159 | J71: =J70-J67 -> -94.757 | K71: =K70-K67 -> -60.472 | ... W71: =W70-W67 -> -43.999573
B73: Expense Analysis
B74: Operating Expenses (GAAP)
B75: GAAP R&D | D75: =D23 -> 49.675 | E75: =E23 -> 15.347 | F75: =F23 -> 15.642 | G75: =G23 -> 16.814 | H75: =H23 -> 20.72 | I75: =SUM(E75:H75) -> 68.523 | J75: =J23 -> 19.786 | K75: =K76+K77 -> 26.847 | L75: =L76+L77 -> 30 | M75: =M76+M77 -> 34 | N75: =SUM(J75:M75) -> 110.633 | O75: =O76+O77 -> 38 | P75: =P76+P77 -> 42 | Q75: =Q76+Q77 -> 47 | R75: =R76+R77 -> 53 | S75: =SUM(O75:R75) -> 180 | T75: =T76+T77 -> 271.9 | U75: =U76+U77 -> 305.185 | V75: =V76+V77 -> 342.71275 | W75: =W76+W77 -> 385.04466
B76: Stock-based Comp (R&D) | D76: 0.696 | E76: 0.155 | F76: =0.302-E76 -> 0.147 | G76: 0.15 | H76: =0.597-SUM(E76:G76) -> 0.145 | I76: =SUM(E76:H76) -> 0.597 | J76: 0.147 | K76: =0.247-J76 -> 0.1 | L76: 0.2 | M76: 0.2 | N76: =SUM(J76:M76) -> 0.647 | O76: 0.3 | P76: 0.4 | Q76: 0.5 | R76: 0.5 | S76: =SUM(O76:R76) -> 1.7 | T76: =R76*4*2 -> 4 | U76: =T76*1.2 -> 4.8 | V76: =U76*1.2 -> 5.76 | W76: =V76*1.2 -> 6.912
B77: Non-GAAP R&D | D77: =D75-D76 -> 48.979 | E77: =E75-E76 -> 15.192 | F77: =F75-F76 -> 15.495 | G77: =G90-G76 -> 17.25 | H77: =H90-H76 -> 19.989 | I77: =SUM(E77:H77) -> 67.926 | J77: =J90-J76 -> 19.639 | K77: =K90-K76 -> 26.747 | L77: =L90-L76 -> 29.8 | M77: =M90-M76 -> 33.8 | N77: =SUM(J77:M77) -> 109.986 | O77: =O90-O76 -> 37.7 | P77: =P90-P76 -> 41.6 | Q77: =Q90-Q76 -> 46.5 | R77: =R90-R76 -> 52.5 | S77: =SUM(O77:R77) -> 178.3 | T77: =T90-T76 -> 267.9 | U77: =U90-U76 -> 300.385 | V77: =V90-V76 -> 336.95275 | W77: =W90-W76 -> 378.13266
B78: GAAP SG&A | D78: =D24 -> 7.607 | E78: =E24 -> 3.944 | F78: =F24 -> 4.343 | G78: =G24 -> 4.08 | H78: =H24 -> 2.056 | I78: =SUM(E78:H78) -> 14.423 | J78: =J24 -> 3.756 | K78: =K24 -> 3.817 | L78: =L79+L80 -> 4.2 | M78: =M79+M80 -> 4.8 | N78: =SUM(J78:M78) -> 16.573 | O78: =O79+O80 -> 5.4 | P78: =P79+P80 -> 6 | Q78: =Q79+Q80 -> 6.6 | R78: =R79+R80 -> 7.2 | S78: =SUM(O78:R78) -> 25.2 | T78: =T79+T80 -> 30.13 | U78: =U79+U80 -> 36.0295 | V78: =V79+V80 -> 43.089925 | W78: =W79+W80 -> 51.540614
B79: Stock-based Comp (SG&A) | D79: 0.359 | E79: 0.112 | F79: =0.21-E79 -> 0.098 | G79: 0.112 | H79: =0.483-SUM(E79:G79) -> 0.161 | I79: =SUM(E79:H79) -> 0.483 | J79: 0.065 | K79: =0.113-J79 -> 0.048 | L79: 0.2 | M79: 0.3 | N79: =SUM(J79:M79) -> 0.613 | O79: 0.4 | P79: 0.5 | Q79: 0.6 | R79: 0.7 | S79: =SUM(O79:R79) -> 2.2 | T79: =S79*1.15 -> 2.53 | U79: =T79*1.15 -> 2.9095 | V79: =U79*1.15 -> 3.345925 | W79: =V79*1.15 -> 3.8478137
B80: Non-GAAP SG&A | D80: =D78-D79 -> 7.248 | E80: =E78-E79 -> 3.832 | F80: =F78-F79 -> 4.245 | G80: =G78-G79 -> 3.968 | H80: =H78-H79 -> 1.895 | I80: =SUM(E80:H80) -> 13.94 | J80: =J78-J79 -> 3.691 | K80: =K78-K79 -> 3.769 | L80: 4 | M80: 4.5 | N80: =SUM(J80:M80) -> 15.96 | O80: 5 | P80: 5.5 | Q80: 6 | R80: 6.5 | S80: =SUM(O80:R80) -> 23 | T80: =S80*1.2 -> 27.6 | U80: =T80*1.2 -> 33.12 | V80: =U80*1.2 -> 39.744 | W80: =V80*1.2 -> 47.6928
B81: Operating Expense (non-GAAP) | D81: =D80+D77 -> 56.227 | E81: =E80+E77 -> 19.024 | F81: =F80+F77 -> 19.74 | G81: =G80+G77 -> 21.218 | H81: =H80+H77 -> 21.884 | I81: =SUM(E81:H81) -> 81.866 | J81: =J80+J77 -> 23.33 | K81: =K80+K77 -> 30.516 | L81: =L80+L77 -> 33.8 | M81: =M80+M77 -> 38.3 | N81: =SUM(J81:M81) -> 125.946 | O81: =O80+O77 -> 42.7 | P81: =P80+P77 -> 47.1 | Q81: =Q80+Q77 -> 52.5 | R81: =R80+R77 -> 59 | S81: =SUM(O81:R81) -> 201.3 | T81: =T80+T77 -> 295.5 | U81: =U80+U77 -> 333.505 | V81: =V80+V77 -> 376.69675 | W81: =W80+W77 -> 425.82546
B83: R&D Expenses
B84: Program and Internal/unallocated expenses
B85: Employee related expenses | D85: 11.867 | E85: 4.528 | F85: =9.683-E85 -> 5.155 | G85: 5.5 | H85: =21.337-SUM(E85:G85) -> 6.154 | I85: =SUM(E85:H85) -> 21.337 | J85: 7.05 | K85: =14.008-J85 -> 6.958 | L85: 8 | M85: 9 | N85: =SUM(J85:M85) -> 31.008 | O85: 10 | P85: 11 | Q85: 12 | R85: 13 | S85: =SUM(O85:R85) -> 46 | T85: =S85*1.15 -> 52.9 | U85: =T85*1.15 -> 60.835 | V85: =U85*1.15 -> 69.96025 | W85: =V85*1.15 -> 80.454287
B86: Clinical trial expenses | D86: 13.307 | E86: 3.457 | F86: =9.404-E86 -> 5.947 | G86: 5 | H86: =18.18-SUM(E86:G86) -> 3.776 | I86: =SUM(E86:H86) -> 18.18 | J86: 6.081 | K86: =7.926-J86 -> 1.845 | L86: 7 | M86: 10 | N86: =SUM(J86:M86) -> 24.926 | O86: 13 | P86: 16 | Q86: 20 | R86: 25 | S86: =SUM(O86:R86) -> 74 | T86: =30+35+40+45 -> 150 | U86: =T86*1.1 -> 165 | V86: =U86*1.1 -> 181.5 | W86: =V86*1.1 -> 199.65
B87: Preclinical program expenses | D87: 14.315 | E87: 2.233 | F87: =5.701-E87 -> 3.468 | G87: 4 | H87: =13.972-SUM(E87:G87) -> 4.271 | I87: =SUM(E87:H87) -> 13.972 | J87: 3.956 | K87: =15.808-J87 -> 11.852 | L87: 12 | M87: 12 | N87: =SUM(J87:M87) -> 39.808 | O87: 12 | P87: 12 | Q87: 12 | R87: 12 | S87: =SUM(O87:R87) -> 48 | T87: =S87*1.15 -> 55.2 | U87: =T87*1.15 -> 63.48 | V87: =U87*1.15 -> 73.002 | W87: =V87*1.15 -> 83.9523
B88: Formulation and CMC expenses | D88: 7.709 | E88: 4.74 | F88: =5.354-E88 -> 0.614 | G88: 2 | H88: =11.473-SUM(E88:G88) -> 4.119 | I88: =SUM(E88:H88) -> 11.473 | J88: 1.939 | K88: =7.36-J88 -> 5.421 | L88: 2 | M88: 2 | N88: =SUM(J88:M88) -> 11.36 | O88: 2 | P88: 2 | Q88: 2 | R88: 2 | S88: =SUM(O88:R88) -> 8 | T88: =S88*1.15 -> 9.2 | U88: =T88*1.15 -> 10.58 | V88: =U88*1.15 -> 12.167 | W88: =V88*1.15 -> 13.99205
B89: Other expenses | D89: 2.477 | E89: 0.389 | F89: =0.847-E89 -> 0.458 | G89: 0.9 | H89: =3.561-SUM(E89:G89) -> 1.814 | I89: =SUM(E89:H89) -> 3.561 | J89: 0.76 | K89: =1.531-J89 -> 0.771 | L89: 1 | M89: 1 | N89: =SUM(J89:M89) -> 3.531 | O89: 1 | P89: 1 | Q89: 1 | R89: 1 | S89: =SUM(O89:R89) -> 4 | T89: =S89*1.15 -> 4.6 | U89: =T89*1.15 -> 5.29 | V89: =U89*1.15 -> 6.0835 | W89: =V89*1.15 -> 6.996025
B90: Total R&D | D90: =SUM(D85:D89) -> 49.675 | E90: =SUM(E85:E89) -> 15.347 | F90: =SUM(F85:F89) -> 15.642 | G90: =SUM(G85:G89) -> 17.4 | H90: =SUM(H85:H89) -> 20.134 | I90: =SUM(I85:I89) -> 68.523 | J90: =SUM(J85:J89) -> 19.786 | K90: =SUM(K85:K89) -> 26.847 | ... W90: =SUM(W85:W89) -> 385.04466
B92: Non-GAAP Income Statement
B93: Total Revenue | D93: =D19 -> 0 | E93: =E19 -> 0 | F93: =F19 -> 0 | G93: =G19 -> 0 | H93: =H19 -> 0 | I93: =I19 -> 0 | J93: =J19 -> 0 | K93: =K19 -> 0 | ... W93: =W19 -> 35
B94: Cost of Sales | D94: =D20 -> 0 | E94: =E20 -> 0 | F94: =F20 -> 0 | G94: =G20 -> 0 | H94: =H20 -> 0 | I94: =I20 -> 0 | J94: =J20 -> 0 | K94: =K20 -> 0 | ... W94: =W20 -> 1.75
B95: % of total revenue | D95: =D94/D93 -> #DIV/0! | E95: =E94/E93 -> #DIV/0! | F95: =F94/F93 -> #DIV/0! | G95: =G94/G93 -> #DIV/0! | H95: =H94/H93 -> #DIV/0! | I95: =I94/I93 -> #DIV/0! | J95: =J94/J93 -> #DIV/0! | K95: =K94/K93 -> #DIV/0! | ... W95: =W94/W93 -> 0.05
B96: Operating Expenses | D96: =SUM(D97:D99) -> 56.227 | E96: =SUM(E97:E99) -> 19.024 | F96: =SUM(F97:F99) -> 19.74 | G96: =SUM(G97:G99) -> 21.218 | H96: =SUM(H97:H99) -> 21.884 | I96: =SUM(I97:I99) -> 81.866 | J96: =SUM(J97:J99) -> 23.33 | K96: =SUM(K97:K99) -> 30.516 | ... W96: =SUM(W97:W99) -> 425.82546
B97: Research and Development (R&D) | D97: =D77 -> 48.979 | E97: =E77 -> 15.192 | F97: =F77 -> 15.495 | G97: =G77 -> 17.25 | H97: =H77 -> 19.989 | I97: =I77 -> 67.926 | J97: =J77 -> 19.639 | K97: =K77 -> 26.747 | ... W97: =W77 -> 378.13266
B98: Sales, General and Administrative (SG&A) | D98: =D80 -> 7.248 | E98: =E80 -> 3.832 | F98: =F80 -> 4.245 | G98: =G80 -> 3.968 | H98: =H80 -> 1.895 | I98: =I80 -> 13.94 | J98: =J80 -> 3.691 | K98: =K80 -> 3.769 | ... W98: =W80 -> 47.6928
B99: Other Expenses | D99: =D25 -> 0 | E99: =E25 -> 0 | F99: =F25 -> 0 | G99: =G25 -> 0 | H99: =H25 -> 0 | I99: =I25 -> 0 | J99: =J25 -> 0 | K99: =K25 -> 0 | ... W99: =W25 -> 0
B100: Total Expenses | D100: =D96+D94 -> 56.227 | E100: =E96+E94 -> 19.024 | F100: =F96+F94 -> 19.74 | G100: =G96+G94 -> 21.218 | H100: =H96+H94 -> 21.884 | I100: =I96+I94 -> 81.866 | J100: =J96+J94 -> 23.33 | K100: =K96+K94 -> 30.516 | ... W100: =W96+W94 -> 427.57546
B101: Operating Income (EBIT) | D101: =D93-D100 -> -56.227 | E101: =E93-E100 -> -19.024 | F101: =F93-F100 -> -19.74 | G101: =G93-G100 -> -21.218 | H101: =H93-H100 -> -21.884 | I101: =I93-I100 -> -81.866 | J101: =J93-J100 -> -23.33 | K101: =K93-K100 -> -30.516 | ... W101: =W93-W100 -> -392.57546
B102: Total Other Income | D102: =D28 -> 1.573 | E102: =E28 -> 0.356 | F102: =F28 -> 1.585 | G102: =G28 -> 1.878 | H102: =H28 -> 1.547 | I102: =I28 -> 5.366 | J102: =J28 -> 1.203 | K102: =K28 -> 0.818 | ... W102: =W28 -> 24.165851
B103: Pre-tax income | D103: =D102+D101 -> -54.654 | E103: =E102+E101 -> -18.668 | F103: =F102+F101 -> -18.155 | G103: =G102+G101 -> -19.34 | H103: =H102+H101 -> -20.337 | I103: =I102+I101 -> -76.5 | J103: =J102+J101 -> -22.127 | K103: =K102+K101 -> -29.698 | ... W103: =W102+W101 -> -368.40961
B104: Provision for taxes (benefit) | D104: =D33 -> 0 | E104: =E33 -> 0 | F104: =F33 -> 0 | G104: =G33 -> 0 | H104: =H33 -> 0 | I104: =I33 -> 0 | J104: =J33 -> 0 | K104: =K33 -> 0 | ... W104: =W33 -> 0
B105: Tax Rate | D105: =IFERROR(D104/D103,0%) -> 0 | E105: =IFERROR(E104/E103,0%) -> 0 | F105: =IFERROR(F104/F103,0%) -> 0 | G105: =IFERROR(G104/G103,0%) -> 0 | H105: =IFERROR(H104/H103,0%) -> 0 | I105: =IFERROR(I104/I103,0%) -> 0 | J105: =IFERROR(J104/J103,0%) -> 0 | K105: =IFERROR(K104/K103,0%) -> 0 | ... W105: =IFERROR(W104/W103,0%) -> 0
B106: Net Income | D106: =D103-D104 -> -54.654 | E106: =E103-E104 -> -18.668 | F106: =F103-F104 -> -18.155 | G106: =G103-G104 -> -19.34 | H106: =H103-H104 -> -20.337 | I106: =I103-I104 -> -76.5 | J106: =J103-J104 -> -22.127 | K106: =K103-K104 -> -29.698 | ... W106: =W103-W104 -> -368.40961
B107: Other (Preferred stock) | D107: =D36 -> 0 | E107: =E36 -> 0 | F107: =F36 -> 0 | G107: =G36 -> 0 | H107: =H36 -> 0 | I107: =I36 -> 0 | J107: =J36 -> 0 | K107: =K36 -> 0 | ... W107: =W36 -> 0
...

Sheet BS
B1: =IS!B1 -> Maplight Therapeutics, Inc. | AB1: Andrew Tsai
B2: Annual and Quarterly Balance Sheet | AB2: (415) 229-1566
AB3: atsai@jefferies.com
B5: Fiscal Year (Ending in December) | D5: =IS!#REF! -> #REF! | E5: =IS!#REF! -> #REF! | F5: =IS!#REF! -> #REF! | G5: =IS!#REF! -> #REF! | H5: =IS!#REF! -> #REF! | I5: =IS!D5 -> FY23 | J5: =IS!E5 -> 1Q24 | K5: =IS!F5 -> 2Q24 | L5: =IS!G5 -> 3Q24 | M5: =IS!H5 -> 4Q24 | N5: =IS!I5 -> FY24 | O5: =IS!J5 -> 1Q25 | P5: =IS!K5 -> 2Q25 | ... AB5: =IS!W5 -> FY30E
B6: ($ figures in MM, except per share) | D6: =IS!#REF! -> #REF! | E6: =IS!#REF! -> #REF! | F6: =IS!#REF! -> #REF! | G6: =IS!#REF! -> #REF! | H6: =IS!#REF! -> #REF! | I6: =IS!D6 -> 0 | J6: =IS!E6 -> 45352 | K6: =IS!F6 -> 45444 | L6: =IS!G6 -> 45536 | M6: =IS!H6 -> 45627 | N6: =IS!I6 -> 0 | O6: =IS!J6 -> 45717 | P6: =IS!K6 -> 45809 | ... AB6: =IS!W6 -> 0
B7: Current assets:
B8: Cash and cash equivalents | I8: 79.769 | J8: =I8+CF!J50 -> 179.786 | K8: =J8+CF!K50 -> 38.736 | L8: =K8+CF!L50 -> 19.736 | M8: 38.253 | N8: =M8 -> 38.253 | O8: 50.156 | P8: 33.467 | Q8: 64.146 | R8: =Q8+CF!R50 -> 324.3923 | S8: =R8 -> 324.3923 | T8: =S8+CF!T50 -> 286.70401 | U8: =T8+CF!U50 -> 245.99984 | V8: =U8+CF!V50 -> 393.39886 | W8: =V8+CF!W50 -> 340.95786 | X8: =W8 -> 340.95786 | Y8: =X8+CF!Y50 -> 436.10636 | Z8: =Y8+CF!Z50 -> 130.86774 | AA8: =Z8+CF!AA50 -> 258.72018 | AB8: =AA8+CF!AB50 -> -87.493427
B9: Marketable securities | I9: 0 | J9: =I9-CF!J33-CF!J34-CF!J36 -> 0 | K9: =J9-CF!K33-CF!K34-CF!K36 -> 121.532 | L9: =K9-CF!L33-CF!L34-CF!L36 -> 121.532 | M9: 70.542 | N9: =M9 -> 70.542 | O9: 42.108 | P9: 27.005 | Q9: 163.022 | R9: =Q9-CF!R33-CF!R34-CF!R36 -> 163.022 | S9: =R9 -> 163.022 | T9: =S9-CF!T33-CF!T34-CF!T36 -> 163.022 | U9: =T9-CF!U33-CF!U34-CF!U36 -> 163.022 | V9: =U9-CF!V33-CF!V34-CF!V36 -> 163.022 | W9: =V9-CF!W33-CF!W34-CF!W36 -> 163.022 | X9: =W9 -> 163.022 | Y9: =X9-CF!Y33-CF!Y34-CF!Y36 -> 163.022 | Z9: =Y9-CF!Z33-CF!Z34-CF!Z36 -> 163.022 | AA9: =Z9-CF!AA33-CF!AA34-CF!AA36 -> 163.022 | AB9: =AA9-CF!AB33-CF!AB34-CF!AB36 -> 143.022
B10: Prepaid expenses & other current assets | I10: 3.835 | J10: =I10 -> 3.835 | K10: =J10 -> 3.835 | L10: =K10 -> 3.835 | M10: 5.807 | N10: =M10 -> 5.807 | O10: 6 | P10: 12.729 | Q10: 18.138 | R10: =Q10 -> 18.138 | S10: =R10 -> 18.138 | T10: =S10 -> 18.138 | U10: =T10 -> 18.138 | V10: =U10 -> 18.138 | W10: =V10 -> 18.138 | X10: =W10 -> 18.138 | Y10: =X10 -> 18.138 | ... AB10: =AA10 -> 18.138
B11: Restricted cash | I11: 0 | J11: 0 | K11: 0 | L11: 0 | M11: 0 | N11: =M11 -> 0 | O11: 0 | P11: 0 | Q11: 0 | R11: 0 | S11: =R11 -> 0 | T11: 0 | U11: 0 | V11: 0 | W11: 0 | X11: =W11 -> 0 | Y11: 0 | Z11: 0 | AA11: 0 | AB11: 0
B12: Accounts receivable | I12: 0 | J12: =I12 -> 0 | K12: =J12 -> 0 | L12: =K12 -> 0 | M12: 0 | N12: =M12 -> 0 | O12: 0 | P12: 0 | Q12: 0 | R12: =Q12 -> 0 | S12: =R12 -> 0 | T12: =S12 -> 0 | U12: =T12 -> 0 | V12: =U12 -> 0 | W12: =V12 -> 0 | X12: =W12 -> 0 | Y12: =X12 -> 0 | ... AB12: =AA12 -> 0
B13: Inventory | I13: 0 | J13: =I13 -> 0 | K13: =J13 -> 0 | L13: =K13 -> 0 | M13: 0 | N13: =M13 -> 0 | O13: 0 | P13: 0 | Q13: 0 | R13: =Q13 -> 0 | S13: =R13 -> 0 | T13: =S13 -> 0 | U13: =T13 -> 0 | V13: =U13 -> 0 | W13: =V13 -> 0 | X13: =W13 -> 0 | Y13: =X13 -> 0 | ... AB13: =AA13 -> 0
B14: Other current assets | I14: 0 | J14: =I14 -> 0 | K14: =J14 -> 0 | L14: =K14 -> 0 | M14: 0 | N14: =M14 -> 0 | O14: 0 | P14: 0 | Q14: 0 | R14: =Q14 -> 0 | S14: =R14 -> 0 | T14: =S14 -> 0 | U14: =T14 -> 0 | V14: =U14 -> 0 | W14: =V14 -> 0 | X14: =W14 -> 0 | Y14: =X14 -> 0 | ... AB14: =AA14 -> 0
B15: Total current assets | I15: =SUM(I8:I14) -> 83.604 | J15: =SUM(J8:J14) -> 183.621 | K15: =SUM(K8:K14) -> 164.103 | L15: =SUM(L8:L14) -> 145.103 | M15: =SUM(M8:M14) -> 114.602 | N15: =SUM(N8:N14) -> 114.602 | O15: =SUM(O8:O14) -> 98.264 | P15: =SUM(P8:P14) -> 73.201 | ... AB15: =SUM(AB8:AB14) -> 73.666573
B17: Marketable securities - long-term | I17: 0 | J17: =I17-CF!J35 -> 0.002 | K17: =J17-CF!K35 -> 0.29 | L17: =K17-CF!L35 -> 0.29 | M17: 11.38 | N17: =M17 -> 11.38 | O17: 2.493 | P17: 0 | Q17: 0 | R17: =Q17-CF!R35 -> 0 | S17: =R17 -> 0 | T17: =S17-CF!T35 -> 0 | U17: =T17-CF!U35 -> 0 | V17: =U17-CF!V35 -> 0 | W17: =V17-CF!W35 -> 0 | X17: =W17 -> 0 | Y17: =X17-CF!Y35 -> 0 | Z17: =Y17-CF!Z35 -> 0 | AA17: =Z17-CF!AA35 -> 0 | AB17: =AA17-CF!AB35 -> 0
B18: Restricted cash - long-term | I18: 0.234 | J18: =I18 -> 0.234 | K18: =J18 -> 0.234 | L18: =K18 -> 0.234 | M18: 0.207 | N18: =M18 -> 0.207 | O18: 0.207 | P18: 0.207 | Q18: 0.207 | R18: =Q18 -> 0.207 | S18: =R18 -> 0.207 | T18: =S18 -> 0.207 | U18: =T18 -> 0.207 | V18: =U18 -> 0.207 | W18: =V18 -> 0.207 | X18: =W18 -> 0.207 | Y18: =X18 -> 0.207 | ... AB18: =AA18 -> 0.207
B19: Other intangible assets (Right-of-use) | I19: 5.614 | J19: =I19 -> 5.614 | K19: =J19 -> 5.614 | L19: =K19 -> 5.614 | M19: 6.354 | N19: =M19 -> 6.354 | O19: 6.142 | P19: 5.927 | Q19: 5.71 | R19: =Q19 -> 5.71 | S19: =R19 -> 5.71 | T19: =S19 -> 5.71 | U19: =T19 -> 5.71 | V19: =U19 -> 5.71 | W19: =V19 -> 5.71 | X19: =W19 -> 5.71 | Y19: =X19 -> 5.71 | ... AB19: =AA19 -> 5.71
B20: Property and equipment, net | I20: 0.971 | J20: =I20 -> 0.971 | K20: =J20 -> 0.971 | L20: =K20 -> 0.971 | M20: 1.207 | N20: =M20 -> 1.207 | O20: 1.041 | P20: 0.971 | Q20: 0.859 | R20: =Q20 -> 0.859 | S20: =R20 -> 0.859 | T20: =S20 -> 0.859 | U20: =T20 -> 0.859 | V20: =U20 -> 0.859 | W20: =V20 -> 0.859 | X20: =W20 -> 0.859 | Y20: =X20 -> 0.859 | ... AB20: =AA20 -> 0.859
B21: Other long-term assets | I21: 0.986 | J21: =I21 -> 0.986 | K21: =J21 -> 0.986 | L21: =K21 -> 0.986 | M21: 3.166 | N21: =M21 -> 3.166 | O21: 3.42 | P21: 3.811 | Q21: 5.14 | R21: =Q21 -> 5.14 | S21: =R21 -> 5.14 | T21: =S21 -> 5.14 | U21: =T21 -> 5.14 | V21: =U21 -> 5.14 | W21: =V21 -> 5.14 | X21: =W21 -> 5.14 | Y21: =X21 -> 5.14 | ... AB21: =AA21 -> 5.14
B22: Total assets | I22: =SUM(I17:I21)+I15 -> 91.409 | J22: =SUM(J17:J21)+J15 -> 191.428 | K22: =SUM(K17:K21)+K15 -> 172.198 | L22: =SUM(L17:L21)+L15 -> 153.198 | M22: =SUM(M17:M21)+M15 -> 136.916 | N22: =SUM(N17:N21)+N15 -> 136.916 | O22: =SUM(O17:O21)+O15 -> 111.567 | P22: =SUM(P17:P21)+P15 -> 84.117 | ... AB22: =SUM(AB17:AB21)+AB15 -> 85.582573
B24: Current liabilities:
B25: Accounts payable | I25: 3.25 | J25: =I25 -> 3.25 | K25: =J25 -> 3.25 | L25: =K25 -> 3.25 | M25: 1.912 | N25: =M25 -> 1.912 | O25: 0.862 | P25: 2.102 | Q25: 2.446 | R25: =Q25 -> 2.446 | S25: =R25 -> 2.446 | T25: =S25 -> 2.446 | U25: =T25 -> 2.446 | V25: =U25 -> 2.446 | W25: =V25 -> 2.446 | X25: =W25 -> 2.446 | Y25: =X25 -> 2.446 | ... AB25: =AA25 -> 2.446
B26: Accrued expenses | I26: 6.755 | J26: =I26 -> 6.755 | K26: =J26 -> 6.755 | L26: =K26 -> 6.755 | M26: 9.991 | N26: =M26 -> 9.991 | O26: 8.076 | P26: 9.643 | Q26: 14.048 | R26: =Q26 -> 14.048 | S26: =R26 -> 14.048 | T26: =S26 -> 14.048 | U26: =T26 -> 14.048 | V26: =U26 -> 14.048 | W26: =V26 -> 14.048 | X26: =W26 -> 14.048 | Y26: =X26 -> 14.048 | ... AB26: =AA26 -> 14.048
B27: Lease liability - current | I27: 0.495 | J27: =I27-IS!E17 -> 0.495 | K27: =J27 -> 0.495 | L27: =K27 -> 0.495 | M27: 0.778 | N27: =M27 -> 0.778 | O27: 0.805 | P27: 0.833 | Q27: 0.862 | R27: =Q27-IS!M17 -> 0.862 | S27: =R27 -> 0.862 | T27: =S27-IS!O17 -> 0.862 | U27: =T27 -> 0.862 | V27: =U27 -> 0.862 | W27: =V27 -> 0.862 | X27: =W27 -> 0.862 | Y27: =X27 -> 0.862 | Z27: =Y27 -> 0.862 | AA27: =Z27 -> 0.862 | AB27: =AA27 -> 0.862
B28: Deferred grant earnings | I28: 4.198 | J28: =I28-IS!E18 -> 4.198 | K28: =J28 -> 4.198 | L28: =K28 -> 4.198 | M28: 3.239 | N28: =M28 -> 3.239 | O28: 3.239 | P28: 2.406 | Q28: 1.206 | R28: =Q28-IS!M18 -> 1.206 | S28: =R28 -> 1.206 | T28: =S28-IS!O18 -> 1.206 | U28: =T28 -> 1.206 | V28: =U28 -> 1.206 | W28: =V28 -> 1.206 | X28: =W28 -> 1.206 | Y28: =X28 -> 1.206 | Z28: =Y28 -> 1.206 | AA28: =Z28 -> 1.206 | AB28: =AA28 -> 1.206
B29: Current portion of long-term debt | I29: 0 | J29: =I29 -> 0 | K29: =J29 -> 0 | L29: =K29 -> 0 | M29: 0 | N29: =M29 -> 0 | O29: 0 | P29: 0 | Q29: 0 | R29: =Q29 -> 0 | S29: =R29 -> 0 | T29: =S29 -> 0 | U29: =T29 -> 0 | V29: =U29 -> 0 | W29: =V29 -> 0 | X29: =W29 -> 0 | Y29: =X29 -> 0 | ... AB29: =AA29 -> 0
B30: Total current liabilities | I30: =SUM(I25:I29) -> 14.698 | J30: =SUM(J25:J29) -> 14.698 | K30: =SUM(K25:K29) -> 14.698 | L30: =SUM(L25:L29) -> 14.698 | M30: =SUM(M25:M29) -> 15.92 | N30: =SUM(N25:N29) -> 15.92 | O30: =SUM(O25:O29) -> 12.982 | P30: =SUM(P25:P29) -> 14.984 | ... AB30: =SUM(AB25:AB29) -> 18.562
B32: Deferred revenue, net of current portion | I32: 0 | J32: =I32 -> 0 | K32: =J32 -> 0 | L32: =K32 -> 0 | M32: 0 | N32: =M32 -> 0 | O32: 0 | P32: 0 | Q32: 0 | R32: =Q32 -> 0 | S32: =R32 -> 0 | T32: =S32 -> 0 | U32: =T32 -> 0 | V32: =U32 -> 0 | W32: =V32 -> 0 | X32: =W32 -> 0 | Y32: =X32 -> 0 | ... AB32: =AA32 -> 0
B33: Long-term debt | I33: 0 | J33: =I33 -> 0 | K33: =J33 -> 0 | L33: =K33 -> 0 | M33: 0 | N33: =M33 -> 0 | O33: 0 | P33: 0 | Q33: 0 | R33: =Q33 -> 0 | S33: =R33 -> 0 | T33: =S33 -> 0 | U33: =T33 -> 0 | V33: =U33 -> 0 | W33: =V33 -> 0 | X33: =W33 -> 0 | Y33: =X33 -> 0 | ... AB33: =AA33 -> 0
B34: Preferred stock warrant liability | I34: 0 | J34: =H34*1.05 -> 0 | K34: =J34*1.05 -> 0 | L34: =K34*1.05 -> 0 | M34: 0 | N34: =M34 -> 0 | O34: 0 | P34: 0 | Q34: 0 | R34: =Q34*1.05 -> 0 | S34: =R34 -> 0 | T34: =R34*1.05 -> 0 | U34: =T34*1.05 -> 0 | V34: =U34*1.05 -> 0 | W34: =V34*1.05 -> 0 | X34: =W34 -> 0 | Y34: =X34*1.2 -> 0 | Z34: =Y34*1.2 -> 0 | AA34: =Z34*1.2 -> 0 | AB34: =AA34*1.2 -> 0
B35: Deferred tax liabilities | I35: 0 | J35: 0 | K35: 0 | L35: 0 | M35: 0 | N35: =M35 -> 0 | O35: 0 | P35: 0 | Q35: 0 | R35: 0 | S35: =R35 -> 0 | T35: 0 | U35: 0 | V35: 0 | W35: 0 | X35: =W35 -> 0 | Y35: 0 | Z35: 0 | AA35: 0 | AB35: 0
B36: Other long-term liabilities | I36: 5.429 | J36: =I36 -> 5.429 | K36: =J36 -> 5.429 | L36: =K36 -> 5.429 | M36: 5.801 | N36: =M36 -> 5.801 | O36: 5.59 | P36: 5.372 | Q36: =5.144 -> 5.144 | R36: =Q36 -> 5.144 | S36: =R36 -> 5.144 | T36: =S36 -> 5.144 | U36: =T36 -> 5.144 | V36: =U36 -> 5.144 | W36: =V36 -> 5.144 | X36: =W36 -> 5.144 | Y36: =X36 -> 5.144 | ... AB36: =AA36 -> 5.144
B37: Total liabilities | I37: =SUM(I32:I36)+I30 -> 20.127 | J37: =SUM(J32:J36)+J30 -> 20.127 | K37: =SUM(K32:K36)+K30 -> 20.127 | L37: =SUM(L32:L36)+L30 -> 20.127 | M37: =SUM(M32:M36)+M30 -> 21.721 | N37: =SUM(N32:N36)+N30 -> 21.721 | O37: =SUM(O32:O36)+O30 -> 18.572 | P37: =SUM(P32:P36)+P30 -> 20.356 | ... AB37: =SUM(AB32:AB36)+AB30 -> 23.706
B39: Stockholders' Equity:
B40: Convertible preferred stock | I40: =105.036+11.981+51.094+15.963+4.793 -> 188.867 | J40: =I40 -> 188.867 | K40: =J40 -> 188.867 | L40: =K40 -> 188.867 | M40: =224.992+11.981+51.094+15.963+4.793 -> 308.823 | N40: =M40 -> 308.823 | O40: =224.992+11.981+51.094+15.963+4.793 -> 308.823 | P40: =224.992+11.981+51.094+15.963+4.793 -> 308.823 | Q40: =198.87+224.992+11.981+51.094+15.963+4.793 -> 507.693 | R40: =Q40 -> 507.693 | S40: =R40 -> 507.693 | T40: =S40 -> 507.693 | U40: =T40 -> 507.693 | V40: =U40 -> 507.693 | W40: =V40 -> 507.693 | X40: =W40 -> 507.693 | Y40: =X40 -> 507.693 | ... AB40: =AA40 -> 507.693
B41: Common stock | I41: 0 | J41: =I41 -> 0 | K41: =J41 -> 0 | L41: =K41 -> 0 | M41: 0 | N41: =M41 -> 0 | O41: 0 | P41: 0 | Q41: 0 | R41: =Q41 -> 0 | S41: =R41 -> 0 | T41: =S41 -> 0 | U41: =T41 -> 0 | V41: =U41 -> 0 | W41: =V41 -> 0 | X41: =W41 -> 0 | Y41: =X41 -> 0 | ... AB41: =AA41 -> 0
B42: Additional paid-in capital | I42: 4.203 | J42: =I42 -> 4.203 | K42: =J42 -> 4.203 | L42: =K42 -> 4.203 | M42: 5.577 | N42: =M42 -> 5.577 | O42: 5.794 | P42: =6.441 -> 6.441 | Q42: 6.794 | R42: =Q42 -> 6.794 | S42: =R42 -> 6.794 | T42: =S42 -> 6.794 | U42: =T42 -> 6.794 | V42: =U42 -> 6.794 | W42: =V42 -> 6.794 | X42: =W42 -> 6.794 | Y42: =X42 -> 6.794 | ... AB42: =AA42 -> 6.794
B43: Accumulated deficit and other | I43: -121.788 | J43: =J22-J37-J40-J41-J42-J44 -> -21.769 | K43: =K22-K37-K40-K41-K42-K44 -> -40.999 | L43: =L22-L37-L40-L41-L42-L44 -> -59.999 | M43: =-199.368+0.163 -> -199.205 | N43: =M43 -> -199.205 | O43: =0.085-221.707 -> -221.622 | P43: =0.05-251.553 -> -251.503 | Q43: -280.971 | R43: =R22-R37-R40-R41-R42-R44 -> -20.724701 | S43: =R43 -> -20.724701 | T43: =T22-T37-T40-T41-T42-T44 -> -58.412993 | U43: =U22-U37-U40-U41-U42-U44 -> -99.11716 | V43: =V22-V37-V40-V41-V42-V44 -> 48.281858 | W43: =W22-W37-W40-W41-W42-W44 -> -4.1591437 | X43: =W43 -> -4.1591437 | Y43: =Y22-Y37-Y40-Y41-Y42-Y44 -> 90.98936 | Z43: =Z22-Z37-Z40-Z41-Z42-Z44 -> -214.24926 | AA43: =AA22-AA37-AA40-AA41-AA42-AA44 -> -86.396816 | AB43: =AB22-AB37-AB40-AB41-AB42-AB44 -> -452.61043
B44: Treasury stock | I44: 0 | J44: =I44 -> 0 | K44: =J44 -> 0 | L44: =K44 -> 0 | N44: =M44 -> 0 | O44: 0 | P44: =O44 -> 0 | Q44: =P44 -> 0 | R44: =Q44 -> 0 | S44: =R44 -> 0 | T44: =S44 -> 0 | U44: =T44 -> 0 | V44: =U44 -> 0 | W44: =V44 -> 0 | ... AB44: =AA44 -> 0
B45: Total stockholders' equity | I45: =SUM(I40:I44) -> 71.282 | J45: =SUM(J40:J44) -> 171.301 | K45: =SUM(K40:K44) -> 152.071 | L45: =SUM(L40:L44) -> 133.071 | M45: =SUM(M40:M44) -> 115.195 | N45: =SUM(N40:N44) -> 115.195 | O45: =SUM(O40:O44) -> 92.995 | P45: =SUM(P40:P44) -> 63.761 | ... AB45: =SUM(AB40:AB44) -> 61.876573
B47: Total liabilities and stockholders' equity | I47: =I45+I37 -> 91.409 | J47: =J45+J37 -> 191.428 | K47: =K45+K37 -> 172.198 | L47: =L45+L37 -> 153.198 | M47: =M45+M37 -> 136.916 | N47: =N45+N37 -> 136.916 | O47: =O45+O37 -> 111.567 | P47: =P45+P37 -> 84.117 | ... AB47: =AB45+AB37 -> 85.582573
B48: Check | D48: =D47-D22 -> 0 | E48: =E47-E22 -> 0 | F48: =F47-F22 -> 0 | G48: =G47-G22 -> 0 | H48: =H47-H22 -> 0 | I48: =I47-I22 -> 0 | J48: =J47-J22 -> 0 | K48: =K47-K22 -> 0 | ... AB48: =AB47-AB22 -> 0
B50: CASH /DEBT
B51: Total Cash + Marketable Securities | D51: =D8+D9+D17 -> 0 | E51: =E8+E9+E17 -> 0 | F51: =F8+F9+F17 -> 0 | G51: =G8+G9+G17 -> 0 | H51: =H8+H9+H17 -> 0 | J51: =J8+J9+J17 -> 179.788 | K51: =K8+K9+K17 -> 160.558 | L51: =L8+L9+L17 -> 141.558 | M51: =M8+M9+M17 -> 120.175 | O51: =O8+O9+O17 -> 94.757 | P51: =P8+P9+P17 -> 60.472 | Q51: =Q8+Q9+Q17 -> 227.168 | R51: =R8+R9+R17 -> 487.4143 | T51: =T8+T9+T17 -> 449.72601 | U51: =U8+U9+U17 -> 409.02184 | V51: =V8+V9+V17 -> 556.42086 | W51: =W8+W9+W17 -> 503.97986 | Y51: =Y8+Y9+Y17 -> 599.12836 | Z51: =Z8+Z9+Z17 -> 293.88974 | AA51: =AA8+AA9+AA17 -> 421.74218 | AB51: =AB8+AB9+AB17 -> 55.528573
B52: Total Debt | D52: =D33+D29 -> 0 | E52: =E33+E29 -> 0 | F52: =F33+F29 -> 0 | G52: =G33+G29 -> 0 | H52: =H33+H29 -> 0 | J52: =J33+J29 -> 0 | K52: =K33+K29 -> 0 | L52: =L33+L29 -> 0 | M52: =M33+M29 -> 0 | O52: =O33+O29 -> 0 | P52: =P33+P29 -> 0 | Q52: =Q33+Q29 -> 0 | R52: =R33+R29 -> 0 | T52: =T33+T29 -> 0 | U52: =U33+U29 -> 0 | V52: =V33+V29 -> 0 | W52: =W33+W29 -> 0 | Y52: =Y33+Y29 -> 0 | Z52: =Z33+Z29 -> 0 | AA52: =AA33+AA29 -> 0 | AB52: =AB33+AB29 -> 0
B53: Net Debt | D53: =D52-D51 -> 0 | E53: =E52-E51 -> 0 | F53: =F52-F51 -> 0 | G53: =G52-G51 -> 0 | H53: =H52-H51 -> 0 | J53: =J52-J51 -> -179.788 | K53: =K52-K51 -> -160.558 | L53: =L52-L51 -> -141.558 | M53: =M52-M51 -> -120.175 | O53: =O52-O51 -> -94.757 | P53: =P52-P51 -> -60.472 | Q53: =Q52-Q51 -> -227.168 | R53: =R52-R51 -> -487.4143 | T53: =T52-T51 -> -449.72601 | U53: =U52-U51 -> -409.02184 | V53: =V52-V51 -> -556.42086 | W53: =W52-W51 -> -503.97986 | Y53: =Y52-Y51 -> -599.12836 | Z53: =Z52-Z51 -> -293.88974 | AA53: =AA52-AA51 -> -421.74218 | AB53: =AB52-AB51 -> -55.528573
B54: Cash/Share | D54: =D51/IS!#REF! -> #REF! | E54: =E51/IS!#REF! -> #REF! | F54: =F51/IS!#REF! -> #REF! | G54: =G51/IS!#REF! -> #REF! | H54: =H51/IS!#REF! -> #REF! | J54: =J51/IS!E41 -> 256.84 | K54: =K51/IS!F41 -> 220.90324 | L54: =L51/IS!G41 -> 186.70173 | M54: =M51/IS!H41 -> 158.125 | O54: =O51/IS!J41 -> 123.06104 | P54: =P51/IS!K41 -> 80.098971 | Q54: =Q51/IS!L41 -> 287.14479 | R54: =R51/IS!M41 -> 10.742379 | T54: =T51/IS!O41 -> 9.9018448 | U54: =U51/IS!P41 -> 8.9966439 | V54: =V51/IS!Q41 -> 11.016209 | W54: =W51/IS!R41 -> 9.9679959 | Y54: =Y51/IS!T41 -> 10.773683 | Z54: =Z51/IS!U41 -> 5.2795228 | AA54: =AA51/IS!V41 -> 6.9455013 | AB54: =AB51/IS!W41 -> 0.91356402
B56: INCOME STATEMENT ITEMS
B57: Total Revenue | D57: =IS!#REF! -> #REF! | E57: =IS!#REF! -> #REF! | F57: =IS!#REF! -> #REF! | G57: =IS!#REF! -> #REF! | H57: =IS!#REF! -> #REF! | J57: =IS!E19 -> 0 | K57: =IS!F19 -> 0 | L57: =IS!G19 -> 0 | M57: =IS!H19 -> 0 | O57: =IS!J19 -> 0 | P57: =IS!K19 -> 0 | Q57: =IS!L19 -> 0 | R57: =IS!M19 -> 0 | T57: =IS!O19 -> 0 | U57: =IS!P19 -> 0 | V57: =IS!Q19 -> 0 | W57: =IS!R19 -> 0 | Y57: =IS!T19 -> 0 | Z57: =IS!U19 -> 0 | AA57: =IS!V19 -> 0 | AB57: =IS!W19 -> 35
B58: Product Revenue | D58: =IS!#REF! -> #REF! | E58: =IS!#REF! -> #REF! | F58: =IS!#REF! -> #REF! | G58: =IS!#REF! -> #REF! | H58: =IS!#REF! -> #REF! | J58: =IS!E9 -> 0 | K58: =IS!F9 -> 0 | L58: =IS!G9 -> 0 | M58: =IS!H9 -> 0 | O58: =IS!J9 -> 0 | P58: =IS!K9 -> 0 | Q58: =IS!L9 -> 0 | R58: =IS!M9 -> 0 | T58: =IS!O9 -> 0 | U58: =IS!P9 -> 0 | V58: =IS!Q9 -> 0 | W58: =IS!R9 -> 0 | Y58: =IS!T9 -> 0 | Z58: =IS!U9 -> 0 | AA58: =IS!V9 -> 0 | AB58: =IS!W9 -> 35
B59: Net Income | D59: =IS!#REF! -> #REF! | E59: =IS!#REF! -> #REF! | F59: =IS!#REF! -> #REF! | G59: =IS!#REF! -> #REF! | H59: =IS!#REF! -> #REF! | J59: =IS!E35 -> -18.935 | K59: =IS!F35 -> -18.4 | L59: =IS!G35 -> -19.016 | M59: =IS!H35 -> -21.229 | O59: =IS!J35 -> -22.339 | P59: =IS!K35 -> -29.846 | Q59: =IS!L35 -> -29.418 | R59: =IS!M35 -> -37.00225 | T59: =IS!O35 -> -38.937292 | U59: =IS!P35 -> -42.153167 | V59: =IS!Q35 -> -48.249982 | W59: =IS!R35 -> -54.190002 | Y59: =IS!T35 -> -277.3275 | Z59: =IS!U35 -> -315.14412 | AA59: =IS!V35 -> -368.44949 | AB59: =IS!W35 -> -379.16943
B60: Diluted Shares | D60: =IS!#REF! -> #REF! | E60: =IS!#REF! -> #REF! | F60: =IS!#REF! -> #REF! | G60: =IS!#REF! -> #REF! | H60: =IS!#REF! -> #REF! | J60: =IS!E41 -> 0.7 | K60: =IS!F41 -> 0.726825 | L60: =IS!G41 -> 0.758204 | M60: =IS!H41 -> 0.76 | O60: =IS!J41 -> 0.77 | P60: =IS!K41 -> 0.754966 | Q60: =IS!L41 -> 0.791127 | R60: =IS!M41 -> 45.373033 | T60: =IS!O41 -> 45.418406 | U60: =IS!P41 -> 45.463824 | V60: =IS!Q41 -> 50.509288 | W60: =IS!R41 -> 50.559798 | Y60: =IS!T41 -> 55.610357 | Z60: =IS!U41 -> 55.665968 | AA60: =IS!V41 -> 60.721634 | AB60: =IS!W41 -> 60.782355
B62: LIQUIDITY & LEVERAGE
B63: Current Ratio | D63: =D15/D30 -> #DIV/0! | E63: =E15/E30 -> #DIV/0! | F63: =F15/F30 -> #DIV/0! | G63: =G15/G30 -> #DIV/0! | H63: =H15/H30 -> #DIV/0! | J63: =J15/J30 -> 12.492924 | K63: =K15/K30 -> 11.164988 | L63: =L15/L30 -> 9.8722956 | M63: =M15/M30 -> 7.1986181 | O63: =O15/O30 -> 7.5692497 | P63: =P15/P30 -> 4.8852776 | Q63: =Q15/Q30 -> 13.215494 | R63: =R15/R30 -> 27.235874 | T63: =T15/T30 -> 25.205474 | U63: =U15/U30 -> 23.012598 | V63: =V15/V30 -> 30.9535 | W63: =W15/W30 -> 28.128319 | Y63: =Y15/Y30 -> 33.254302 | Z63: =Z15/Z30 -> 16.810028 | AA63: =AA15/AA30 -> 23.697887 | AB63: =AB15/AB30 -> 3.9686765
B64: Long Term Debt/Equity | D64: =D33/D45 -> #DIV/0! | E64: =E33/E45 -> #DIV/0! | F64: =F33/F45 -> #DIV/0! | G64: =G33/G45 -> #DIV/0! | H64: =H33/H45 -> #DIV/0! | J64: =J33/J45 -> 0 | K64: =K33/K45 -> 0 | L64: =L33/L45 -> 0 | M64: =M33/M45 -> 0 | O64: =O33/O45 -> 0 | P64: =P33/P45 -> 0 | Q64: =Q33/Q45 -> 0 | R64: =R33/R45 -> 0 | T64: =T33/T45 -> 0 | U64: =U33/U45 -> 0 | V64: =V33/V45 -> 0 | W64: =W33/W45 -> 0 | Y64: =Y33/Y45 -> 0 | Z64: =Z33/Z45 -> 0 | AA64: =AA33/AA45 -> 0 | AB64: =AB33/AB45 -> 0
B65: Long Term Debt/Capitalization | D65: =D33/(D45+D33+D29) -> #DIV/0! | E65: =E33/(E45+E33+E29) -> #DIV/0! | F65: =F33/(F45+F33+F29) -> #DIV/0! | G65: =G33/(G45+G33+G29) -> #DIV/0! | H65: =H33/(H45+H33+H29) -> #DIV/0! | J65: =J33/(J45+J33+J29) -> 0 | K65: =K33/(K45+K33+K29) -> 0 | L65: =L33/(L45+L33+L29) -> 0 | M65: =M33/(M45+M33+M29) -> 0 | O65: =O33/(O45+O33+O29) -> 0 | P65: =P33/(P45+P33+P29) -> 0 | Q65: =Q33/(Q45+Q33+Q29) -> 0 | R65: =R33/(R45+R33+R29) -> 0 | T65: =T33/(T45+T33+T29) -> 0 | U65: =U33/(U45+U33+U29) -> 0 | V65: =V33/(V45+V33+V29) -> 0 | W65: =W33/(W45+W33+W29) -> 0 | Y65: =Y33/(Y45+Y33+Y29) -> 0 | Z65: =Z33/(Z45+Z33+Z29) -> 0 | AA65: =AA33/(AA45+AA33+AA29) -> 0 | AB65: =AB33/(AB45+AB33+AB29) -> 0
B67: MANAGEMENT & PROFITABILITY
B68: Sales/Capital | D68: =D57/D45 -> #REF! | E68: =E57/E45 -> #REF! | F68: =F57/F45 -> #REF! | G68: =G57/G45 -> #REF! | H68: =H57/H45 -> #REF! | J68: =J57/J45 -> 0 | K68: =K57/K45 -> 0 | L68: =L57/L45 -> 0 | M68: =M57/M45 -> 0 | O68: =O57/O45 -> 0 | P68: =P57/P45 -> 0 | Q68: =Q57/Q45 -> 0 | R68: =R57/R45 -> 0 | T68: =T57/T45 -> 0 | U68: =U57/U45 -> 0 | V68: =V57/V45 -> 0 | W68: =W57/W45 -> 0 | Y68: =Y57/Y45 -> 0 | Z68: =Z57/Z45 -> 0 | AA68: =AA57/AA45 -> 0 | AB68: =AB57/AB45 -> 0.56564219
B69: DSO | D69: =IFERROR(D12/D58*91.25,0) -> 0 | E69: =IFERROR(E12/E58*91.25,0) -> 0 | F69: =IFERROR(F12/F58*91.25,0) -> 0 | G69: =IFERROR(G12/G58*91.25,0) -> 0 | H69: =IFERROR(H12/H58*91.25,0) -> 0 | J69: =IFERROR(J12/J58*91.25,0) -> 0 | K69: =IFERROR(K12/K58*91.25,0) -> 0 | L69: =IFERROR(L12/L58*91.25,0) -> 0 | M69: =IFERROR(M12/M58*91.25,0) -> 0 | O69: =IFERROR(O12/O58*91.25,0) -> 0 | P69: =IFERROR(P12/P58*91.25,0) -> 0 | Q69: =IFERROR(Q12/Q58*91.25,0) -> 0 | R69: =IFERROR(R12/R58*91.25,0) -> 0 | T69: =IFERROR(T12/T58*91.25,0) -> 0 | U69: =IFERROR(U12/U58*91.25,0) -> 0 | V69: =IFERROR(V12/V58*91.25,0) -> 0 | W69: =IFERROR(W12/W58*91.25,0) -> 0 | Y69: =IFERROR(Y12/Y58*91.25,0) -> 0 | Z69: =IFERROR(Z12/Z58*91.25,0) -> 0 | AA69: =IFERROR(AA12/AA58*91.25,0) -> 0 | AB69: =IFERROR(AB12/AB58*91.25,0) -> 0
B70: Inventory Turnover | D70: =IFERROR(D58/D13,0) -> 0 | E70: =IFERROR(E58/E13,0) -> 0 | F70: =IFERROR(F58/F13,0) -> 0 | G70: =IFERROR(G58/G13,0) -> 0 | H70: =IFERROR(H58/H13,0) -> 0 | J70: =IFERROR(J58/J13,0) -> 0 | K70: =IFERROR(K58/K13,0) -> 0 | L70: =IFERROR(L58/L13,0) -> 0 | M70: =IFERROR(M58/M13,0) -> 0 | O70: =IFERROR(O58/O13,0) -> 0 | P70: =IFERROR(P58/P13,0) -> 0 | Q70: =IFERROR(Q58/Q13,0) -> 0 | R70: =IFERROR(R58/R13,0) -> 0 | T70: =IFERROR(T58/T13,0) -> 0 | U70: =IFERROR(U58/U13,0) -> 0 | V70: =IFERROR(V58/V13,0) -> 0 | W70: =IFERROR(W58/W13,0) -> 0 | Y70: =IFERROR(Y58/Y13,0) -> 0 | Z70: =IFERROR(Z58/Z13,0) -> 0 | AA70: =IFERROR(AA58/AA13,0) -> 0 | AB70: =IFERROR(AB58/AB13,0) -> 0
B71: Return on Assets | D71: =D59/D22 -> #REF! | E71: =E59/E22 -> #REF! | F71: =F59/F22 -> #REF! | G71: =G59/G22 -> #REF! | H71: =H59/H22 -> #REF! | J71: =J59/J22 -> -0.098914474 | K71: =K59/K22 -> -0.10685374 | L71: =L59/L22 -> -0.12412695 | M71: =M59/M22 -> -0.15505127 | O71: =O59/O22 -> -0.20022946 | P71: =P59/P22 -> -0.35481532 | Q71: =Q59/Q22 -> -0.11436813 | R71: =R59/R22 -> -0.071506313 | T71: =T59/T22 -> -0.081156554 | U71: =U59/U22 -> -0.096004296 | V71: =V59/V22 -> -0.082271186 | W71: =W59/W22 -> -0.10147297 | Y71: =Y59/Y22 -> -0.44077443 | Z71: =Z59/Z22 -> -0.97283594 | AA71: =AA59/AA22 -> -0.81552146 | AB71: =AB59/AB22 -> -4.4304514
B72: Return on Capital | D72: =D59/D45 -> #REF! | E72: =E59/E45 -> #REF! | F72: =F59/F45 -> #REF! | G72: =G59/G45 -> #REF! | H72: =H59/H45 -> #REF! | J72: =J59/J45 -> -0.11053642 | K72: =K59/K45 -> -0.12099611 | L72: =L59/L45 -> -0.14290116 | M72: =M59/M45 -> -0.18428751 | O72: =O59/O45 -> -0.24021722 | P72: =P59/P45 -> -0.46809178 | Q72: =Q59/Q45 -> -0.12597852 | R72: =R59/R45 -> -0.074939399 | T72: =T59/T45 -> -0.085374942 | U72: =U59/U45 -> -0.10148346 | V72: =V59/V45 -> -0.085736767 | W72: =W59/W45 -> -0.10618664 | Y72: =Y59/Y45 -> -0.45803191 | Z72: =Z59/Z45 -> -1.0496486 | AA72: =AA59/AA45 -> -0.86068193 | AB72: =AB59/AB45 -> -6.127835
B74: PER SHARE DATA
B75: Book Value | D75: =D45/D60 -> #REF! | E75: =E45/E60 -> #REF! | F75: =F45/F60 -> #REF! | G75: =G45/G60 -> #REF! | H75: =H45/H60 -> #REF! | J75: =J45/J60 -> 244.71571 | K75: =K45/K60 -> 209.22643 | L75: =L45/L60 -> 175.50817 | M75: =M45/M60 -> 151.57237 | O75: =O45/O60 -> 120.77273 | P75: =P45/P60 -> 84.455459 | Q75: =Q45/Q60 -> 295.16879 | R75: =R45/R60 -> 10.882286 | T75: =T45/T60 -> 10.041612 | U75: =U45/U60 -> 9.1362714 | V75: =V45/V60 -> 11.141889 | W75: =W45/W60 -> 10.09355 | Y75: =Y45/Y60 -> 10.887834 | Z75: =Z45/Z60 -> 5.3935601 | AA75: =AA45/AA60 -> 7.0500439 | AB75: =AB45/AB60 -> 1.0180022
B76: Free Cash Flow | D76: =(CF!D30+CF!D35)/D60 -> #REF! | E76: =(CF!E30+CF!E35)/E60 -> #REF! | F76: =(CF!F30+CF!F35)/F60 -> #REF! | G76: =(CF!G30+CF!G35)/G60 -> #REF! | H76: =(CF!H30+CF!H35)/H60 -> #REF! | J76: =(CF!J30+CF!J35)/J60 -> -28.49 | K76: =(CF!K30+CF!K35)/K60 -> -24.517594 | L76: =(CF!L30+CF!L35)/L60 -> -25.059219 | M76: =(CF!M30+CF!M35)/M60 -> -31.435526 | O76: =(CF!O30+CF!O35)/O60 -> -33.181818 | P76: =(CF!P30+CF!P35)/P60 -> -45.078851 | Q76: =(CF!Q30+CF!Q35)/Q60 -> -40.22363 | R76: =(CF!R30+CF!R35)/R60 -> -0.79239248 | T76: =(CF!T30+CF!T35)/T60 -> -0.82980217 | U76: =(CF!U30+CF!U35)/U60 -> -0.8953089 | V76: =(CF!V30+CF!V35)/V60 -> -0.92262203 | W76: =(CF!W30+CF!W35)/W60 -> -1.0372075 | Y76: =(CF!Y30+CF!Y35)/Y60 -> -4.8300624 | Z76: =(CF!Z30+CF!Z35)/Z60 -> -5.4833973 | AA76: =(CF!AA30+CF!AA35)/AA60 -> -5.8817186 | AB76: =(CF!AB30+CF!AB35)/AB60 -> -6.0249987
B77: Net Cash | D77: =CF!D53/BS!D60 -> #REF! | E77: =CF!E53/BS!E60 -> #REF! | F77: =CF!F53/BS!F60 -> #REF! | G77: =CF!G53/BS!G60 -> #REF! | H77: =CF!H53/BS!H60 -> #REF! | J77: =CF!J53/BS!J60 -> 257.17143 | K77: =CF!K53/BS!K60 -> 53.616758 | L77: =CF!L53/BS!L60 -> 26.338558 | M77: =CF!M53/BS!M60 -> -5.1592105 | O77: =CF!O53/BS!O60 -> 65.406494 | P77: =CF!P53/BS!P60 -> 44.603333 | Q77: =CF!Q53/BS!Q60 -> 81.343451 | R77: =CF!R53/BS!R60 -> 7.1540137 | T77: =CF!T53/BS!T60 -> 6.3170647 | U77: =CF!U53/BS!U60 -> 5.415445 | V77: =CF!V53/BS!V60 -> 7.7927421 | W77: =CF!W53/BS!W60 -> 6.7477497 | Y77: =CF!Y53/BS!Y60 -> 7.845901 | Z77: =CF!Z53/BS!Z60 -> 2.3546657 | AA77: =CF!AA53/BS!AA60 -> 4.264167 | AB77: =CF!AB53/BS!AB60 -> -1.4360488
B78: Earnings (GAAP) | D78: =D59/D60 -> #REF! | E78: =E59/E60 -> #REF! | F78: =F59/F60 -> #REF! | G78: =G59/G60 -> #REF! | H78: =H59/H60 -> #REF! | J78: =J59/J60 -> -27.05 | K78: =K59/K60 -> -25.315585 | L78: =L59/L60 -> -25.080321 | M78: =M59/M60 -> -27.932895 | O78: =O59/O60 -> -29.011688 | P78: =P59/P60 -> -39.532906 | Q78: =Q59/Q60 -> -37.184927 | R78: =R59/R60 -> -0.81551194 | T78: =T59/T60 -> -0.85730203 | U78: =U59/U60 -> -0.9271804 | V78: =V59/V60 -> -0.95526949 | W78: =W59/W60 -> -1.0718002 | Y78: =Y59/Y60 -> -4.9869756 | Z78: =Z59/Z60 -> -5.6613426 | AA78: =AA59/AA60 -> -6.0678454 | AB78: =AB59/AB60 -> -6.2381496

Sheet CF
B1: =IS!B1 -> Maplight Therapeutics, Inc. | AB1: Andrew Tsai
B2: Annual and Quarterly Cash Flow Statement | AB2: (415) 229-1566
AB3: atsai@jefferies.com
B4: CF Statement
B5: Fiscal Year (Ending in December) | I5: =IS!D5 -> FY23 | J5: =IS!E5 -> 1Q24 | K5: =IS!F5 -> 2Q24 | L5: =IS!G5 -> 3Q24 | M5: =IS!H5 -> 4Q24 | N5: =IS!I5 -> FY24 | O5: =IS!J5 -> 1Q25 | P5: =IS!K5 -> 2Q25 | ... AB5: =IS!W5 -> FY30E | AC5: 1Q22 | AD5: 2Q22 | AE5: 3Q22 | AF5: 4Q22 | AH5: =E5 -> 0 | AI5: =F5 -> 0 | AJ5: =G5 -> 0 | AK5: =H5 -> 0 | AM5: =J5 -> 1Q24 | AN5: =K5 -> 2Q24 | AO5: =L5 -> 3Q24 | AP5: =M5 -> 4Q24 | AR5: =O5 -> 1Q25 | AS5: =P5 -> 2Q25 | AT5: =Q5 -> 3Q25E | AU5: =R5 -> 4Q25E
B6: ($ figures in MM, except per share) | I6: =IS!D6 -> 0 | J6: =IS!E6 -> 45352 | K6: =IS!F6 -> 45444 | L6: =IS!G6 -> 45536 | M6: =IS!H6 -> 45627 | N6: =IS!I6 -> 0 | O6: =IS!J6 -> 45717 | P6: =IS!K6 -> 45809 | ... AB6: =IS!W6 -> 0 | AC6: 44621 | AD6: 44713 | AE6: 44805 | AF6: 44896 | AH6: =E6 -> 0 | AI6: =F6 -> 0 | AJ6: =G6 -> 0 | AK6: =H6 -> 0 | AM6: =J6 -> 45352 | AN6: =K6 -> 45444 | AO6: =L6 -> 45536 | AP6: =M6 -> 45627 | AR6: =O6 -> 45717 | AS6: =P6 -> 45809 | AT6: =Q6 -> 45901 | AU6: =R6 -> 45992
B7: Cash flows from operating activities:
B8: Net income | I8: -55.709 | J8: =AM8 -> -18.935 | K8: =AN8-AM8 -> -18.4 | L8: =IS!G35 -> -19.016 | M8: =IS!H35 -> -21.229 | N8: -77.58 | O8: =AR8 -> -22.339 | P8: =AS8-AR8 -> -29.846 | Q8: =AT8-AS8 -> -29.419 | R8: =IS!M35 -> -37.00225 | S8: =SUM(O8:R8) -> -118.60625 | T8: =IS!O35 -> -38.937292 | U8: =IS!P35 -> -42.153167 | V8: =IS!Q35 -> -48.249982 | W8: =IS!R35 -> -54.190002 | X8: =SUM(T8:W8) -> -183.53044 | Y8: =IS!T35 -> -277.3275 | Z8: =IS!U35 -> -315.14412 | AA8: =IS!V35 -> -368.44949 | AB8: =IS!W35 -> -379.16943 | AM8: -18.935 | AN8: -37.335 | AR8: -22.339 | AS8: -52.185 | AT8: -81.604
B9: Adjustments to reconcile net income to net cash provided by operating activities | C9: -
B10: Depreciation and amortization | I10: 0.556 | J10: =AM10 -> 0.147 | K10: =AN10-AM10 -> -0.246 | L10: =K10 -> -0.246 | M10: =L10 -> -0.246 | N10: =0.701-1.741 -> -1.04 | O10: =AR10 -> -0.091 | P10: =AS10-AR10 -> 0.197 | Q10: =AT10-AS10 -> 0.332 | R10: =Q10 -> 0.332 | S10: =SUM(O10:R10) -> 0.77 | T10: =R10 -> 0.332 | U10: =T10 -> 0.332 | V10: =U10 -> 0.332 | W10: =V10 -> 0.332 | X10: =SUM(T10:W10) -> 1.328 | Y10: =X10 -> 1.328 | Z10: =Y10 -> 1.328 | AA10: =Z10 -> 1.328 | AB10: =AA10 -> 1.328 | AM10: =0.147+0 -> 0.147 | AN10: =0.32-0.419 -> -0.099 | AR10: =0.166+-0.257 -> -0.091 | AS10: =0.302-0.196 -> 0.106 | AT10: 0.438
B11: Non-cash lease expense | I11: 0.533 | J11: =AM11 -> 0.139 | K11: =AN11-AM11 -> 0.199 | L11: 0 | M11: 0 | N11: 0.745 | O11: =AR11 -> 0.212 | P11: =AS11-AR11 -> 0.215 | Q11: =AT11-AS11 -> 0.217 | R11: =Q11 -> 0.217 | S11: =SUM(O11:R11) -> 0.861 | T11: =R11 -> 0.217 | U11: =T11 -> 0.217 | V11: =U11 -> 0.217 | W11: =V11 -> 0.217 | X11: =SUM(T11:W11) -> 0.868 | Y11: =X11 -> 0.868 | Z11: =Y11 -> 0.868 | AA11: =Z11 -> 0.868 | AB11: =AA11 -> 0.868 | AM11: 0.139 | AN11: 0.338 | AR11: 0.212 | AS11: 0.427 | AT11: 0.644
B12: Loss (gain) from equity method investment | I12: -0.986 | J12: =AM12 -> 0.534 | K12: =AN12-AM12 -> 0.452 | L12: 0 | M12: 0 | N12: 0.986 | O12: =AR12 -> 0 | P12: =AS12-AR12 -> 0 | Q12: =AT12-AS12 -> 0 | R12: =Q12 -> 0 | S12: =SUM(O12:R12) -> 0 | T12: =R12 -> 0 | U12: =T12 -> 0 | V12: =U12 -> 0 | W12: =V12 -> 0 | X12: =SUM(T12:W12) -> 0 | Y12: =X12 -> 0 | Z12: =Y12 -> 0 | AA12: =Z12 -> 0 | AB12: =AA12 -> 0 | AM12: 0.534 | AN12: 0.986 | AR12: 0 | AS12: 0 | AT12: 0
B13: Stock-based compensation | I13: 1.045 | J13: =AM13 -> 0.267 | K13: =AN13-AM13 -> 0.245 | L13: =IS!G61 -> 0.262 | M13: =IS!H61 -> 0.306 | N13: 1.08 | O13: =AR13 -> 0.212 | P13: =AS13-AR13 -> 0.148 | Q13: =AT13-AS13 -> 0.125 | R13: =IS!M61 -> 0.5 | S13: =SUM(O13:R13) -> 0.985 | T13: =IS!O61 -> 0.7 | U13: =IS!P61 -> 0.9 | V13: =IS!Q61 -> 1.1 | W13: =IS!R61 -> 1.2 | X13: =SUM(T13:W13) -> 3.9 | Y13: =IS!T61 -> 6.53 | Z13: =IS!U61 -> 7.7095 | AA13: =IS!V61 -> 9.105925 | AB13: =IS!W61 -> 10.759814 | AM13: 0.267 | AN13: 0.512 | AR13: 0.212 | AS13: 0.36 | AT13: 0.485
B14: Loss from revaluation of preferred stock purchase right | I14: 0.514 | J14: =AM14 -> 0 | K14: =AN14-AM14 -> 0 | L14: 0 | M14: 0 | N14: 0 | O14: =AR14 -> 0 | P14: =AS14-AR14 -> 0 | Q14: =AT14-AS14 -> 0 | R14: =Q14 -> 0 | S14: =SUM(O14:R14) -> 0 | T14: =R14 -> 0 | U14: =T14 -> 0 | V14: =U14 -> 0 | W14: =V14 -> 0 | X14: =SUM(T14:W14) -> 0 | Y14: =X14 -> 0 | Z14: =Y14 -> 0 | AA14: =Z14 -> 0 | AB14: =AA14 -> 0 | AM14: 0 | AN14: 0 | AR14: 0 | AS14: 0 | AT14: 0
B15: Loss on disposal of property and equipment | I15: =SUM(E15:H15) -> 0 | J15: =AM15 -> 0 | K15: =AN15-AM15 -> 0 | L15: 0 | M15: 0 | N15: 0.059 | O15: =AR15 -> 0 | P15: =AS15-AR15 -> 0 | Q15: =AT15-AS15 -> 0 | R15: =Q15 -> 0 | S15: =SUM(O15:R15) -> 0 | T15: =R15 -> 0 | U15: =T15 -> 0 | V15: =U15 -> 0 | W15: =V15 -> 0 | X15: =SUM(T15:W15) -> 0 | Y15: =X15 -> 0 | Z15: =Y15 -> 0 | AA15: =Z15 -> 0 | AB15: =AA15 -> 0 | AM15: 0 | AN15: 0 | AR15: 0 | AS15: 0 | AT15: 0
B16: Non-cash interest expense (income) | I16: =SUM(E16:H16) -> 0 | J16: =AM16 -> 0 | K16: =AN16-AM16 -> 0 | L16: 0 | M16: 0 | N16: 0 | O16: =AR16 -> 0 | P16: =AS16-AR16 -> 0.496 | Q16: =AT16-AS16 -> -0.496 | R16: 0 | S16: =SUM(O16:R16) -> 0 | T16: =R16 -> 0 | U16: =T16 -> 0 | V16: =U16 -> 0 | W16: =V16 -> 0 | X16: =SUM(T16:W16) -> 0 | Y16: =X16 -> 0 | Z16: =Y16 -> 0 | AA16: =Z16 -> 0 | AB16: =AA16 -> 0 | AM16: 0 | AN16: 0 | AR16: 0 | AS16: 0.496 | AT16: 0
B17: Change in deferred tax, other | I17: =SUM(E17:H17) -> 0 | J17: =AM17 -> 0 | K17: =AN17-AM17 -> 0 | L17: 0 | M17: 0 | N17: 0 | O17: =AR17 -> 0 | P17: =AS17-AR17 -> 0 | Q17: =AT17-AS17 -> -0.157 | R17: 0 | S17: =SUM(O17:R17) -> -0.157 | T17: =R17 -> 0 | U17: =T17 -> 0 | V17: =U17 -> 0 | W17: =V17 -> 0 | X17: =SUM(T17:W17) -> 0 | Y17: =X17 -> 0 | Z17: =Y17 -> 0 | AA17: =Z17 -> 0 | AB17: =AA17 -> 0 | AM17: 0 | AN17: 0 | AR17: 0 | AS17: 0 | AT17: =-0.66+0.496+0.007 -> -0.157
B19: Changes in operating assets and liabilities
B20: (Increase) decrease in receivables | I20: =SUM(E20:H20) -> 0 | J20: =AM20 -> 0 | K20: =AN20-AM20 -> 0 | L20: =BS!K10-BS!L10 -> 0 | M20: =BS!L10-BS!M10 -> -1.972 | O20: =AR20 -> 0 | P20: =AS20-AR20 -> 0 | Q20: =AT20-AS20 -> 0 | R20: =BS!Q10-BS!R10 -> 0 | S20: =SUM(O20:R20) -> 0 | T20: =BS!R10-BS!T10 -> 0 | U20: =BS!T10-BS!U10 -> 0 | V20: =BS!U10-BS!V10 -> 0 | W20: =BS!V10-BS!W10 -> 0 | X20: =SUM(T20:W20) -> 0 | Y20: =BS!X10-BS!Y10 -> 0 | Z20: =BS!Y10-BS!Z10 -> 0 | AA20: =BS!Z10-BS!AA10 -> 0 | AB20: =BS!AA10-BS!AB10 -> 0
B21: Increase in inventory | I21: =SUM(E21:H21) -> 0 | J21: =AM21 -> 0 | K21: =AN21-AM21 -> 0 | L21: =BS!K13-BS!L13 -> 0 | M21: =BS!L13-BS!M13 -> 0 | N21: 0 | O21: =AR21 -> 0 | P21: =AS21-AR21 -> 0 | Q21: =AT21-AS21 -> 0 | R21: =BS!Q13-BS!R13 -> 0 | S21: =SUM(O21:R21) -> 0 | T21: =BS!S13-BS!T13 -> 0 | U21: =BS!T13-BS!U13 -> 0 | V21: =BS!U13-BS!V13 -> 0 | W21: =BS!V13-BS!W13 -> 0 | X21: =SUM(T21:W21) -> 0 | Y21: =BS!X13-BS!Y13 -> 0 | Z21: =BS!Y13-BS!Z13 -> 0 | AA21: =BS!Z13-BS!AA13 -> 0 | AB21: =BS!AA13-BS!AB13 -> 0 | AM21: 0 | AN21: 0 | AR21: 0 | AS21: 0 | AT21: 0
B22: (Increase) decrease in prepaid expenses | I22: 0.532 | J22: =AM22 -> 0.012 | K22: =AN22-AM22 -> 0.232 | L22: =BS!K10-BS!L10 -> 0 | M22: =BS!L10-BS!M10 -> -1.972 | N22: -2.277 | O22: =AR22 -> -0.193 | P22: =AS22-AR22 -> -6.673 | Q22: =AT22-AS22 -> -3.908 | R22: =BS!Q10-BS!R10 -> 0 | S22: =SUM(O22:R22) -> -10.774 | T22: =BS!S10-BS!T10 -> 0 | U22: =BS!T10-BS!U10 -> 0 | V22: =BS!U10-BS!V10 -> 0 | W22: =BS!V10-BS!W10 -> 0 | X22: =SUM(T22:W22) -> 0 | Y22: =BS!X10-BS!Y10 -> 0 | Z22: =BS!Y10-BS!Z10 -> 0 | AA22: =BS!Z10-BS!AA10 -> 0 | AB22: =BS!AA10-BS!AB10 -> 0 | AM22: 0.012 | AN22: 0.244 | AR22: -0.193 | AS22: -6.866 | AT22: -10.774
B23: (Increase) decrease in receivables | I23: =SUM(E23:H23) -> 0 | J23: =AM23 -> 0 | K23: =AN23-AM23 -> 0 | L23: =BS!K12-BS!L12 -> 0 | M23: =BS!L12-BS!M12 -> 0 | N23: 0 | O23: =AR23 -> 0 | P23: =AS23-AR23 -> 0 | Q23: =AT23-AS23 -> 0 | R23: =BS!Q12-BS!R12 -> 0 | S23: =SUM(O23:R23) -> 0 | T23: =BS!S12-BS!T12 -> 0 | U23: =BS!T12-BS!U12 -> 0 | V23: =BS!U12-BS!V12 -> 0 | W23: =BS!V12-BS!W12 -> 0 | X23: =SUM(T23:W23) -> 0 | Y23: =BS!X12-BS!Y12 -> 0 | Z23: =BS!Y12-BS!Z12 -> 0 | AA23: =BS!Z12-BS!AA12 -> 0 | AB23: =BS!AA12-BS!AB12 -> 0 | AM23: 0 | AN23: 0 | AR23: 0 | AS23: 0 | AT23: 0
B24: (Increase) decrease in other assets | I24: =SUM(E24:H24) -> 0 | J24: =AM24 -> 0 | K24: =AN24-AM24 -> 0 | L24: =BS!K14-BS!L14 -> 0 | M24: =BS!L14-BS!M14 -> 0 | N24: 0 | O24: =AR24 -> 0 | P24: =AS24-AR24 -> 0 | Q24: =AT24-AS24 -> 0 | R24: =BS!Q14-BS!R14 -> 0 | S24: =SUM(O24:R24) -> 0 | T24: =BS!S14-BS!T14 -> 0 | U24: =BS!T14-BS!U14 -> 0 | V24: =BS!U14-BS!V14 -> 0 | W24: =BS!V14-BS!W14 -> 0 | X24: =SUM(T24:W24) -> 0 | Y24: =BS!X14-BS!Y14 -> 0 | Z24: =BS!Y14-BS!Z14 -> 0 | AA24: =BS!Z14-BS!AA14 -> 0 | AB24: =BS!AA14-BS!AB14 -> 0 | AM24: 0 | AN24: 0 | AR24: 0 | AS24: 0 | AT24: 0
B25: Deferred revenue | I25: =SUM(E25:H25) -> 0 | J25: =AM25 -> 0 | K25: =AN25-AM25 -> 0 | L25: =BS!L32-BS!K32 -> 0 | M25: =BS!M32-BS!L32 -> 0 | N25: 0 | O25: =AR25 -> 0 | P25: =AS25-AR25 -> 0 | Q25: =AT25-AS25 -> 0 | R25: =BS!R32-BS!Q32 -> 0 | S25: =SUM(O25:R25) -> 0 | T25: =BS!T32-BS!S32 -> 0 | U25: =BS!U32-BS!T32 -> 0 | V25: =BS!V32-BS!U32 -> 0 | W25: =BS!W32-BS!V32 -> 0 | X25: =SUM(T25:W25) -> 0 | Y25: =BS!Y32-BS!X32 -> 0 | Z25: =BS!Z32-BS!Y32 -> 0 | AA25: =BS!AA32-BS!Z32 -> 0 | AB25: =BS!AB32-BS!AA32 -> 0 | AM25: 0 | AN25: 0 | AR25: 0 | AS25: 0 | AT25: 0
B26: Increase (decrease) in accounts payable | I26: -0.405 | J26: =AM26 -> 0.802 | K26: =AN26-AM26 -> -2.02 | L26: =BS!L25-BS!K25 -> 0 | M26: =BS!M25-BS!L25 -> -1.338 | N26: -1.345 | O26: =AR26 -> -1.05 | P26: =AS26-AR26 -> 1.24 | Q26: =AT26-AS26 -> 0.301 | R26: =BS!R25-BS!Q25 -> 0 | S26: =SUM(O26:R26) -> 0.491 | T26: =BS!T25-BS!S25 -> 0 | U26: =BS!U25-BS!T25 -> 0 | V26: =BS!V25-BS!U25 -> 0 | W26: =BS!W25-BS!V25 -> 0 | X26: =SUM(T26:W26) -> 0 | Y26: =BS!Y25-BS!X25 -> 0 | Z26: =BS!Z25-BS!Y25 -> 0 | AA26: =BS!AA25-BS!Z25 -> 0 | AB26: =BS!AB25-BS!AA25 -> 0 | AM26: 0.802 | AN26: -1.218 | AR26: -1.05 | AS26: 0.19 | AT26: 0.491
B27: Accrued expenses | I27: 3.922 | J27: =AM27 -> -2.555 | K27: =AN27-AM27 -> 2.369 | L27: =BS!L26-BS!K26 -> 0 | M27: =BS!M26-BS!L26 -> 3.236 | N27: 2.169 | O27: =AR27 -> -2.117 | P27: =AS27-AR27 -> 1.279 | Q27: =AT27-AS27 -> 2.613 | R27: =BS!R26-BS!Q26 -> 0 | S27: =SUM(O27:R27) -> 1.775 | T27: =BS!T26-BS!S26 -> 0 | U27: =BS!U26-BS!T26 -> 0 | V27: =BS!V26-BS!U26 -> 0 | W27: =BS!W26-BS!V26 -> 0 | X27: =SUM(T27:W27) -> 0 | Y27: =BS!Y26-BS!X26 -> 0 | Z27: =BS!Z26-BS!Y26 -> 0 | AA27: =BS!AA26-BS!Z26 -> 0 | AB27: =BS!AB26-BS!AA26 -> 0 | AM27: -2.555 | AN27: -0.186 | AR27: -2.117 | AS27: -0.838 | AT27: 1.775
B28: Operating lease liability | I28: -0.347 | J28: =AM28 -> -0.116 | K28: =AN28-AM28 -> -0.187 | L28: =BS!L27-BS!K27 -> 0 | M28: =BS!M27-BS!L27 -> 0.283 | N28: -0.653 | O28: =AR28 -> -0.184 | P28: =AS28-AR28 -> -0.19 | Q28: =AT28-AS28 -> -0.199 | R28: =BS!R27-BS!Q27 -> 0 | S28: =SUM(O28:R28) -> -0.573 | T28: =BS!T27-BS!S27 -> 0 | U28: =BS!U27-BS!T27 -> 0 | V28: =BS!V27-BS!U27 -> 0 | W28: =BS!W27-BS!V27 -> 0 | X28: =SUM(T28:W28) -> 0 | Y28: =BS!Y27-BS!X27 -> 0 | Z28: =BS!Z27-BS!Y27 -> 0 | AA28: =BS!AA27-BS!Z27 -> 0 | AB28: =BS!AB27-BS!AA27 -> 0 | AM28: -0.116 | AN28: -0.303 | AR28: -0.184 | AS28: -0.374 | AT28: -0.573
B29: Increase (decrease) in other liabilities | I29: -1.661 | J29: =AM29 -> -0.236 | K29: =AN29-AM29 -> -0.176 | L29: =BS!L28-BS!K28 -> 0 | M29: =BS!M28-BS!L28 -> -0.959 | N29: -0.959 | O29: =AR29 -> 0 | P29: =AS29-AR29 -> -0.833 | Q29: =AT29-AS29 -> -1.2 | R29: =BS!R28-BS!Q28 -> 0 | S29: =SUM(O29:R29) -> -2.033 | T29: =BS!T28-BS!S28 -> 0 | U29: =BS!U28-BS!T28 -> 0 | V29: =BS!V28-BS!U28 -> 0 | W29: =BS!W28-BS!V28 -> 0 | X29: =SUM(T29:W29) -> 0 | Y29: =BS!Y28-BS!X28 -> 0 | Z29: =BS!Z28-BS!Y28 -> 0 | AA29: =BS!AA28-BS!Z28 -> 0 | AB29: =BS!AB28-BS!AA28 -> 0 | AM29: -0.236 | AN29: -0.412 | AR29: 0 | AS29: -0.833 | AT29: -2.033
B30: Net cash provided by operating activities | I30: =SUM(I8:I29) -> -52.006 | J30: =SUM(J8:J29) -> -19.941 | K30: =SUM(K8:K29) -> -17.532 | L30: =SUM(L8:L29) -> -19 | M30: =SUM(M8:M29) -> -23.891 | N30: =SUM(N8:N29) -> -78.815 | O30: =SUM(O8:O29) -> -25.55 | P30: =SUM(P8:P29) -> -33.967 | ... AB30: =SUM(AB8:AB29) -> -366.21361 | AM30: =SUM(AM8:AM29) -> -19.941 | AN30: =SUM(AN8:AN29) -> -37.473 | AR30: =SUM(AR8:AR29) -> -25.55 | AS30: =SUM(AS8:AS29) -> -59.517 | AT30: =SUM(AT8:AT29) -> -91.308
K31: =AN31-AM31 -> 0
B32: Cash flows from investing activities: | K32: =AN32-AM32 -> 0
B33: Maturities/sale of marketable securities | I33: 0 | J33: =AM33 -> 0 | K33: =AN33-AM33 -> 0 | L33: 0 | M33: 0 | N33: 45 | O33: =AR33 -> 37.5 | P33: =AS33-AR33 -> 17.5 | Q33: =AT33-AS33 -> 6.5 | R33: 0 | S33: =SUM(O33:R33) -> 61.5 | T33: 0 | U33: 0 | V33: 0 | W33: 0 | X33: =SUM(T33:W33) -> 0 | Y33: 0 | Z33: 0 | AA33: 0 | AB33: 20 | AM33: 0 | AN33: 0 | AR33: 37.5 | AS33: 55 | AT33: 61.5
B34: Purchases of marketable securities | I34: 0 | J34: =AM34 -> 0 | K34: =AN34-AM34 -> -121.532 | L34: 0 | M34: 0 | N34: -125.018 | O34: =AR34 -> 0 | P34: =AS34-AR34 -> 0 | Q34: =AT34-AS34 -> -142.057 | R34: 0 | S34: =SUM(O34:R34) -> -142.057 | T34: 0 | U34: 0 | V34: 0 | W34: 0 | X34: =SUM(T34:W34) -> 0 | Y34: 0 | Z34: 0 | AA34: 0 | AB34: 0 | AM34: 0 | AN34: -121.532 | AR34: 0 | AS34: 0 | AT34: -142.057
B35: Capital expenditures | I35: -0.462 | J35: =AM35 -> -0.002 | K35: =AN35-AM35 -> -0.288 | L35: =IS!G63 -> 0 | M35: =IS!H63 -> 0 | N35: -0.77 | O35: =AR35 -> 0 | P35: =AS35-AR35 -> -0.066 | Q35: =AT35-AS35 -> -0.031 | R35: =IS!M63 -> 0 | S35: =SUM(O35:R35) -> -0.097 | T35: =IS!O63 -> 0 | U35: =IS!P63 -> 0 | V35: =IS!Q63 -> 0 | W35: =IS!R63 -> 0 | X35: =SUM(T35:W35) -> 0 | Y35: =IS!T63 -> 0 | Z35: =IS!U63 -> 0 | AA35: =IS!V63 -> 0 | AB35: =IS!W63 -> 0 | AM35: -0.002 | AN35: -0.29 | AR35: 0 | AS35: -0.066 | AT35: -0.097
B36: Purchases of other securities | I36: 0 | J36: =AM36 -> 0 | K36: =AN36-AM36 -> 0 | L36: 0 | M36: 0 | N36: =SUM(J36:M36) -> 0 | O36: =AR36 -> 0 | P36: =AS36-AR36 -> 0 | Q36: =AT36-AS36 -> 0 | R36: 0 | S36: =SUM(O36:R36) -> 0 | T36: 0 | U36: 0 | V36: 0 | W36: 0 | X36: =SUM(T36:W36) -> 0 | Y36: 0 | Z36: 0 | AA36: 0 | AB36: 0 | AM36: 0 | AN36: 0 | AR36: 0 | AS36: 0 | AT36: 0
B37: Net cash used in investing activities | I37: =SUM(I33:I36) -> -0.462 | J37: =SUM(J33:J36) -> -0.002 | K37: =SUM(K33:K36) -> -121.82 | L37: =SUM(L33:L36) -> 0 | M37: =SUM(M33:M36) -> 0 | N37: =SUM(N33:N36) -> -80.788 | O37: =SUM(O33:O36) -> 37.5 | P37: =SUM(P33:P36) -> 17.434 | ... AB37: =SUM(AB33:AB36) -> 20 | AM37: =SUM(AM33:AM36) -> -0.002 | AN37: =SUM(AN33:AN36) -> -121.822 | AR37: =SUM(AR33:AR36) -> 37.5 | AS37: =SUM(AS33:AS36) -> 54.934 | AT37: =SUM(AT33:AT36) -> -80.654
K38: =AN38-AM38 -> 0
B39: Cash flows from financing activities: | K39: =AN39-AM39 -> 0
B40: Proceeds from issuance of common stock/series D, net of fees | I40: 104.532 | J40: =AM40 -> 119.956 | K40: =AN40-AM40 -> 0 | L40: =IS!G65 -> 0 | M40: =IS!H65 -> 0 | N40: 119.956 | O40: =AR40 -> 0 | P40: =AS40-AR40 -> 0 | Q40: =AT40-AS40 -> 0 | R40: =IS!M65 -> 296.19955 | S40: =SUM(O40:R40) -> 296.19955 | T40: =IS!O65 -> 0 | U40: =IS!P65 -> 0 | V40: =IS!Q65 -> 194 | W40: =IS!R65 -> 0 | X40: =SUM(T40:W40) -> 194 | Y40: =IS!T65 -> 363.75 | Z40: =IS!U65 -> 0 | AA40: =IS!V65 -> 485 | AB40: =IS!W65 -> 0 | AM40: 119.956 | AN40: 119.956 | AR40: 0 | AS40: 0 | AT40: 0
B41: Proceeds from the exercise of stock options | I41: 0.04 | J41: =AM41 -> 0.004 | K41: =AN41-AM41 -> 0.261 | L41: 0 | M41: 0 | N41: 0.294 | O41: =AR41 -> 0.005 | P41: =AS41-AR41 -> 0.003 | Q41: =AT41-AS41 -> 0.104 | R41: 0 | S41: =SUM(O41:R41) -> 0.112 | T41: 0 | U41: 0 | V41: 0 | W41: 0 | X41: =SUM(T41:W41) -> 0 | Y41: 0 | Z41: 0 | AA41: 0 | AB41: 0 | AM41: 0.004 | AN41: 0.265 | AR41: 0.005 | AS41: 0.008 | AT41: 0.112
B42: Proceeds from issuance of convertible preferred stock | I42: =SUM(E42:H42) -> 0 | J42: =AM42 -> 0 | K42: =AN42-AM42 -> 0 | L42: 0 | M42: 0 | N42: =SUM(J42:M42) -> 0 | O42: =AR42 -> 0 | P42: =AS42-AR42 -> 0 | Q42: =AT42-AS42 -> 198.87 | R42: 0 | S42: =SUM(O42:R42) -> 198.87 | T42: 0 | U42: 0 | V42: 0 | W42: 0 | X42: =SUM(T42:W42) -> 0 | Y42: 0 | Z42: 0 | AA42: 0 | AB42: 0 | AM42: 0 | AN42: 0 | AR42: 0 | AS42: 0 | AT42: 198.87
B43: Proceeds from debt borrowings | I43: =SUM(E43:H43) -> 0 | J43: =AM43 -> 0 | K43: =AN43-AM43 -> 0 | L43: =IF(BS!L52>BS!K52,BS!L52-BS!K52,0) -> 0 | M43: =IF(BS!M52>BS!L52,BS!M52-BS!L52,0) -> 0 | N43: =SUM(J43:M43) -> 0 | O43: =AR43 -> 0 | P43: =AS43-AR43 -> 0 | Q43: =AT43-AS43 -> 0 | R43: =IF(BS!R52>BS!Q52,BS!R52-BS!Q52,0) -> 0 | S43: =SUM(O43:R43) -> 0 | T43: =IF(BS!T52>BS!R52,BS!T52-BS!R52,0) -> 0 | U43: =IF(BS!U52>BS!T52,BS!U52-BS!T52,0) -> 0 | V43: =IF(BS!V52>BS!U52,BS!V52-BS!U52,0) -> 0 | W43: =IF(BS!W52>BS!V52,BS!W52-BS!V52,0) -> 0 | X43: =SUM(T43:W43) -> 0 | Y43: =IF(BS!Y52>BS!X52,BS!Y52-BS!X52,0) -> 0 | Z43: =IF(BS!Z52>BS!Y52,BS!Z52-BS!Y52,0) -> 0 | AA43: =IF(BS!AA52>BS!Z52,BS!AA52-BS!Z52,0) -> 0 | AB43: =IF(BS!AB52>BS!AA52,BS!AB52-BS!AA52,0) -> 0 | AM43: 0 | AN43: 0 | AR43: 0 | AS43: 0 | AT43: 0
B44: Repayment of debt borrowings | I44: =SUM(E44:H44) -> 0 | J44: =AM44 -> 0 | K44: =AN44-AM44 -> 0 | L44: =IF(BS!L52<BS!K52,BS!L52-BS!K52,0) -> 0 | M44: =IF(BS!M52<BS!L52,BS!M52-BS!L52,0) -> 0 | N44: =SUM(J44:M44) -> 0 | O44: =AR44 -> 0 | P44: =AS44-AR44 -> 0 | Q44: =AT44-AS44 -> 0 | R44: =IF(BS!R52<BS!Q52,BS!R52-BS!Q52,0) -> 0 | S44: =SUM(O44:R44) -> 0 | T44: =IF(BS!T52<BS!R52,BS!T52-BS!R52,0) -> 0 | U44: =IF(BS!U52<BS!T52,BS!U52-BS!T52,0) -> 0 | V44: =IF(BS!V52<BS!U52,BS!V52-BS!U52,0) -> 0 | W44: =IF(BS!W52<BS!V52,BS!W52-BS!V52,0) -> 0 | X44: =SUM(T44:W44) -> 0 | Y44: =IF(BS!Y52<BS!X52,BS!Y52-BS!X52,0) -> 0 | Z44: =IF(BS!Z52<BS!Y52,BS!Z52-BS!Y52,0) -> 0 | AA44: =IF(BS!AA52<BS!Z52,BS!AA52-BS!Z52,0) -> 0 | AB44: =IF(BS!AB52<BS!AA52,BS!AB52-BS!AA52,0) -> 0 | AM44: 0 | AN44: 0 | AR44: 0 | AS44: 0 | AT44: 0
B45: Other financing activities | I45: 0 | J45: =AM45 -> 0 | K45: =AN45-AM45 -> -1.959 | L45: 0 | M45: 0 | N45: -2.19 | O45: =AR45 -> -0.052 | P45: =AS45-AR45 -> -0.159 | Q45: =AT45-AS45 -> -0.916 | R45: 0 | S45: =SUM(O45:R45) -> -1.127 | T45: 0 | U45: 0 | V45: 0 | W45: 0 | X45: =SUM(T45:W45) -> 0 | Y45: 0 | Z45: 0 | AA45: 0 | AB45: 0 | AM45: 0 | AN45: -1.959 | AR45: -0.052 | AS45: -0.211 | AT45: -1.127
B46: Net cash provided by (used in) financing activities | I46: =SUM(I40:I45) -> 104.572 | J46: =SUM(J40:J45) -> 119.96 | K46: =SUM(K40:K45) -> -1.698 | L46: =SUM(L40:L45) -> 0 | M46: =SUM(M40:M45) -> 0 | N46: =SUM(N40:N45) -> 118.06 | O46: =SUM(O40:O45) -> -0.047 | P46: =SUM(P40:P45) -> -0.156 | ... AB46: =SUM(AB40:AB45) -> 0 | AM46: =SUM(AM40:AM45) -> 119.96 | AN46: =SUM(AN40:AN45) -> 118.262 | AR46: =SUM(AR40:AR45) -> -0.047 | AS46: =SUM(AS40:AS45) -> -0.203 | AT46: =SUM(AT40:AT45) -> 197.855
K47: =AN47-AM47 -> 0
B48: Effect of foreign currency exchange rate changes on cash and cash equivalents | I48: =SUM(E48:H48) -> 0 | J48: =AM48 -> 0 | K48: =AN48-AM48 -> 0 | L48: 0 | M48: 0 | N48: =SUM(J48:M48) -> 0 | O48: =AR48 -> 0 | P48: =AS48-AR48 -> 0 | Q48: =AT48-AS48 -> 0 | R48: 0 | S48: =(SUM(O48:R48))-(SUM(O48:R48)) -> 0 | T48: 0 | U48: 0 | V48: 0 | W48: 0 | X48: =(SUM(T48:W48))-(SUM(T48:W48)) -> 0 | Y48: 0 | Z48: 0 | AA48: 0 | AB48: 0 | AM48: 0 | AN48: 0
B50: Net increase in cash and cash equivalents | I50: =I46+I37+I30+I48 -> 52.104 | J50: =J46+J37+J30+J48 -> 100.017 | K50: =K46+K37+K30+K48 -> -141.05 | L50: =L46+L37+L30+L48 -> -19 | M50: =M46+M37+M30+M48 -> -23.891 | N50: =N46+N37+N30+N48 -> -41.543 | O50: =O46+O37+O30+O48 -> 11.903 | P50: =P46+P37+P30+P48 -> -16.689 | ... AB50: =AB46+AB37+AB30+AB48 -> -346.21361 | AM50: =AM46+AM37+AM30+AM48 -> 100.017 | AN50: =AN46+AN37+AN30+AN48 -> -41.033 | AR50: =AR46+AR37+AR30+AR48 -> 11.903 | AS50: =AS46+AS37+AS30+AS48 -> -4.786 | AT50: =AT46+AT37+AT30+AT48 -> 25.893
B52: Cash and cash equivalents at beginning of period | I52: 27.899 | J52: =I53 -> 80.003 | K52: =J53 -> 180.02 | L52: =K53 -> 38.97 | M52: =L53 -> 19.97 | N52: =I53 -> 80.003 | O52: =N53 -> 38.46 | P52: =O53 -> 50.363 | Q52: =P53 -> 33.674 | R52: =Q53 -> 64.353 | S52: =N53 -> 38.46 | T52: =S53 -> 324.5993 | U52: =T53 -> 286.91101 | V52: =U53 -> 246.20684 | W52: =V53 -> 393.60586 | X52: =S53 -> 324.5993 | Y52: =X53 -> 341.16486 | Z52: =Y53 -> 436.31336 | AA52: =Z53 -> 131.07474 | AB52: =AA53 -> 258.92718
B53: Cash and cash equivalents at end of period | I53: =SUM(I50:I52) -> 80.003 | J53: =SUM(J50:J52) -> 180.02 | K53: =SUM(K50:K52) -> 38.97 | L53: =SUM(L50:L52) -> 19.97 | M53: =SUM(M50:M52) -> -3.921 | N53: =SUM(N50:N52) -> 38.46 | O53: =SUM(O50:O52) -> 50.363 | P53: =SUM(P50:P52) -> 33.674 | ... AB53: =SUM(AB50:AB52) -> -87.286427
B54: Check | I54: =I53-BS!I8-BS!I11-BS!I18 -> -1.9567681e-14 | J54: =J53-BS!J9-BS!J8-BS!J11-BS!J18 -> -1.9567681e-14 | K54: =K53-BS!K8-BS!K11-BS!K18 -> -1.9567681e-14 | L54: =L53-BS!L8-BS!L11-BS!L18 -> -1.9567681e-14 | M54: =M53-BS!M8-BS!M11-BS!M18 -> -42.381 | N54: =N53-BS!N8-BS!N11-BS!N18 -> -2.0566882e-14 | O54: =O53-BS!O8-BS!O11-BS!O18 -> -2.0566882e-14 | P54: =P53-BS!P8-BS!P11-BS!P18 -> -2.0566882e-14 | Q54: =Q53-BS!Q8-BS!Q11-BS!Q18 -> 7.8548279e-15 | R54: =R53-BS!R8-BS!R11-BS!R18 -> -6.3560268e-15 | ... AB54: =AB53-BS!AB8-BS!AB11-BS!AB18 -> -6.3560268e-15
I57: Values hardcoded | N57: Values hardcoded

Sheet SOTP
B1: MPLT Sum-Of-The-Parts Worksheet | L1: MPLT Pipeline Analysis - NPV ($M)
B2: NPV ($M) | D2: Bear | E2: % | F2: Base | G2: % | H2: Bull | I2: % | L2: Drug | M2: Licensing Partner | N2: Indication | O2: Phase | P2: Status | Q2: Rev. Pot'l | R2: Bear PoS | S2: Base PoS | T2: Bull PoS | U2: Peak Year | V2: P/S Multiple | W2: Partner | X2: Bear | Y2: Base | Z2: Bull
D3: Case | F3: Case | H3: Case
L4: ML-007C-MA | M4: n/a | N4: Alzheimer's Disease Cognition | O4: n/a | P4: Pot'l Phase II initation H2:26 | Q4: 1000 | R4: 0 | S4: 0 | T4: 0.05 | U4: 2045 | V4: 3 | W4: 1 | X4: =(($Q4*R4*$V4)/(1+$M$11)^($U4-$M$10)/$D$38)*W4 -> 0 | Y4: =(($Q4*S4*$V4)/(1+$M$11)^($U4-$M$10)/$D$38)*W4 -> 0 | Z4: =(($Q4*T4*$V4)/(1+$M$11)^($U4-$M$10)/$D$38)*W4 -> 0.54849861
B5: ML-007C-MA - Schizophrenia | D5: ='SCZ DCF'!O96 -> 2.0644184 | E5: =D5/D$32 -> 0.35386204 | F5: ='SCZ DCF'!C99 -> 16.515347 | G5: =F5/F$32 -> 0.52708005 | H5: ='SCZ DCF'!Q96 -> 24.77302 | I5: =H5/H$32 -> 0.4859726 | L5: ML-021 | M5: n/a | N5: Parkinson's Disease | O5: Preclin. | P5: Phase II initation 2026 | Q5: 1000 | R5: 0 | S5: 0 | T5: 0.05 | U5: 2045 | V5: 3 | W5: 1 | X5: =(($Q5*R5*$V5)/(1+$M$11)^($U5-$M$10)/$D$38)*W5 -> 0 | Y5: =(($Q5*S5*$V5)/(1+$M$11)^($U5-$M$10)/$D$38)*W5 -> 0 | Z5: =(($Q5*T5*$V5)/(1+$M$11)^($U5-$M$10)/$D$38)*W5 -> 0.54849861
B6: Probability | D6: ='SCZ DCF'!O95 -> 0.05 | F6: ='SCZ DCF'!P95 -> 0.4 | H6: ='SCZ DCF'!Q95 -> 0.6 | L6: ML-009 | M6: n/a | N6: Hyperactivity/Impulsivity | O6: Preclin. | P6: IND enabling studies YE:25 | Q6: 1000 | R6: 0 | S6: 0 | T6: 0.05 | U6: 2044 | V6: 3 | W6: 1 | X6: =(($Q6*R6*$V6)/(1+$M$11)^($U6-$M$10)/$D$38)*W6 -> 0 | Y6: =(($Q6*S6*$V6)/(1+$M$11)^($U6-$M$10)/$D$38)*W6 -> 0 | Z6: =(($Q6*T6*$V6)/(1+$M$11)^($U6-$M$10)/$D$38)*W6 -> 0.59786349
B7: NPV | D7: ='SCZ DCF'!O94 -> 109.80193 | F7: ='SCZ DCF'!P94 -> 878.41545 | H7: ='SCZ DCF'!Q94 -> 1317.6232 | L7: Total | X7: =SUM(X4:X6) -> 0 | Y7: =SUM(Y4:Y6) -> 0 | Z7: =SUM(Z4:Z6) -> 1.6948607
B9: ML-007C-MA - Alzheimer's Disease Psychosis | D9: ='ADP DCF'!K98 -> 0 | E9: =D9/D$32 -> 0 | F9: ='ADP DCF'!L98 -> 9.5511695 | G9: =F9/F$32 -> 0.30482138 | H9: ='ADP DCF'!M98 -> 19.102339 | I9: =H9/H$32 -> 0.37473079
B10: Probability | D10: ='ADP DCF'!K97 -> 0 | F10: ='ADP DCF'!L97 -> 0.15 | H10: ='ADP DCF'!M97 -> 0.3 | L10: Current Year: | M10: 2026
B11: NPV | D11: ='ADP DCF'!K96 -> 0 | F11: ='ADP DCF'!L96 -> 508.00597 | H11: ='ADP DCF'!M96 -> 1016.0119 | L11: Discount Rate: | M11: 0.09
B13: =IS!B13 -> ML-004 - Autism Spectrum Disorder | D13: ='ASD DCF'!O96 -> 0 | E13: =D13/D$32 -> 0 | F13: ='ASD DCF'!P96 -> 4.324757 | G13: =F13/F$32 -> 0.13802272 | H13: ='ASD DCF'!Q96 -> 5.4059462 | I13: =H13/H$32 -> 0.1060485
B14: Probability | D14: ='ASD DCF'!O95 -> 0 | F14: ='ASD DCF'!P95 -> 0.2 | H14: ='ASD DCF'!Q95 -> 0.25
B15: NPV | D15: ='ASD DCF'!O94 -> 0 | F15: ='ASD DCF'!P94 -> 230.02443 | H15: ='ASD DCF'!Q94 -> 287.53054
B17: ML-007C-MA - Alzheimer's Disease Cognition | D17: =X4 -> 0 | E17: =D17/D$32 -> 0 | F17: =Y4 -> 0 | G17: =F17/F$32 -> 0 | H17: =Z4 -> 0.54849861 | I17: =H17/H$32 -> 0.010759903
B18: Probability | D18: =R4 -> 0 | F18: =S4 -> 0 | H18: =T4 -> 0.05
B19: NPV | D19: =D17*D38 -> 0 | F19: =F17*D38 -> 0 | H19: =H17*D38 -> 29.17345
B21: =IS!B14 -> ML-021 - Parkinson's Disease | D21: =X5 -> 0 | E21: =D21/D$32 -> 0 | F21: =Y5 -> 0 | G21: =F21/F$32 -> 0 | H21: =Z5 -> 0.54849861 | I21: =H21/H$32 -> 0.010759903
B22: Probability | D22: =R5 -> 0 | F22: =S5 -> 0 | H22: =T5 -> 0.05
B23: NPV | D23: =D21*D38 -> 0 | F23: =F21*D38 -> 0 | H23: =H21*D38 -> 29.17345
B25: =IS!B15 -> ML-009 - Hyperactivity/Impulsivity | D25: =X6 -> 0 | E25: =D25/D$32 -> 0 | F25: =Y6 -> 0 | G25: =F25/F$32 -> 0 | H25: =Z6 -> 0.59786349 | I25: =H25/H$32 -> 0.011728294
B26: Probability | D26: =R6 -> 0 | F26: =S6 -> 0 | H26: =T6 -> 0.05
B27: NPV | D27: =D25*D38 -> 0 | F27: =F25*D38 -> 0 | H27: =H25*D38 -> 31.799061
B29: Cash | D29: =D40*D30 -> 3.7695455 | E29: =D29/D$32 -> 0.64613796 | F29: =D40*F30 -> 0.94238638 | G29: =F29/F$32 -> 0.030075848 | H29: =D40*H30 -> 0 | I29: =H29/H$32 -> 0
B30: Weight | D30: 0.4 | F30: 0.1 | H30: 0
B32: $/Share | D32: =D29+D9+D13+D5+D25+D21+D17 -> 5.8339639 | F32: =F29+F9+F13+F5+F25+F21+F17 -> 31.33366 | H32: =H29+H9+H13+H5+H25+H21+H17 -> 50.976166
B33: Implied Market Cap ($M) | D33: =D32*$D38 -> 310.29587 | F33: =F32*$D38 -> 1666.5693 | H33: =H32*$D38 -> 2711.3116
B35: Upside/downside | D35: =D32/D37-1 -> -0.56102604 | F35: =F32/D37-1 -> 1.357687 | H35: =H32/D37-1 -> 2.8356784
B37: Stock Price | D37: 13.29
B38: Share Count (in M) - YE:26 | D38: =IS!S42 -> 53.187829
B39: Cash (Q4:26) | D39: =IS!S67 -> 501.23486
B40: Cash/Share | D40: =D39/D38 -> 9.4238638
B41: Debt (Q4:26) | D41: =IS!S70 -> 0
J69: =MAX(#REF!) -> #REF!

Sheet Pipeline
B1: MPLT Pipeline | M1: Sep 2025
B2: Program | C2: Target | D2: Modality | E2: Indication | F2: Designation | G2: Stage | H2: Milestone | I2: Partner | K2: IP
B3: ML-007C-MA | C3: M1/M4 Agonist | D3: Oral small molecule | E3: Schizophrenia | F3: N/A | G3: Phase II (ZEPHYR) | H3: - Phase II data expected H2:26 | I3: N/A | K3: 2045
E4: Alzheimer's Disease Psychosis (ADP) | F4: N/A | G4: Phase II (VISTA) | H4: - Phase II data expected H2:27 | I4: N/A | K4: 2045
B5: ML-004 | C5: 5-HT1B/1D Agonist | D5: Oral small molecule | E5: Autism Spectrum Disorder (ASD) | F5: N/A | G5: Phase II (IRIS) | H5: - Phase II data expected H2:26 | I5: N/A | K5: 2045
B6: ML-021 | C6: M4 Antagonist | D6: Oral small molecule | E6: Parkinson's Disease | F6: N/A | G6: Preclinical | H6: - Complete IND-enabling studies in 2026 | I6: N/A | K6: 2045
B7: ML-009 | C7: GPR52 Positive Allosteric Modulator (PAM) | D7: Oral small molecule | E7: Hyperactivity/Impulsivity | F7: N/A | G7: Preclinical | H7: - Initiate IND enabling studies in 2026 | I7: N/A | K7: 2045

Sheet Newsflow
B1: MPLT Expected Newsflow | G1: Dec 2025
B2: Timing | C2: Expected Newsflow | D2: Drug | E2: Indication
B3: H2:26 | C3: Phase II data (N=300) in schizophrenia (Study 211; ZEPHYR) | D3: ML-007C-MA (M1/M4 Agonist) | E3: Schizophrenia
B4: H2:26 | C4: Phase II data (N=160) in autism spectrum disorder (IRIS) | D4: ML-004 (5-HT1B/1D Agonist) | E4: Autism Spectrum Disorder (ASD)
B5: H2:26 | C5: Complete IND-enabling studies for ML-021 in Parkinson's | D5: ML-021 (M4 Antagonist) | E5: Parkinson's Disease
B6: 2026 | C6: Initiate IND-enabling studies for hyperactivity/agitation | D6: ML-009 (GPR52 PAM) | E6: Hyperactivity/Impulsivity
B7: H2:27 | C7: Phase II data (N=300) in ADP Alzheimer's psychosis (Study 221; VISTA) | D7: ML-007C-MA | E7: Alzheimer's Disease Psychosis (ADP)
B10: Old

Sheet SCZ DCF
B1: ML-007C-MA Model Analysis for Schizophrenia (SCZ): Change Assumptions in Blue
B3: ML-007C-MA Sales Summary ($M) | E3: 2018 | F3: =E3+1 -> 2019 | G3: =F3+1 -> 2020 | H3: =G3+1 -> 2021 | I3: =H3+1 -> 2022 | J3: =I3+1 -> 2023 | K3: =J3+1 -> 2024 | L3: =K3+1 -> 2025 | M3: =L3+1 -> 2026 | ... AF3: =AE3+1 -> 2045
B4: US | E4: =E36 -> 0 | F4: =F36 -> 0 | G4: =G36 -> 0 | H4: =H36 -> 0 | I4: =I36 -> 0 | J4: =J36 -> 0 | K4: =K36 -> 0 | L4: =L36 -> 0 | ... AF4: =AF36 -> 1335.0132
B5: EU5 (Before royalties) | E5: =E62 -> 0 | F5: =F62 -> 0 | G5: =G62 -> 0 | H5: =H62 -> 0 | I5: =I62 -> 0 | J5: =J62 -> 0 | K5: =K62 -> 0 | L5: =L62 -> 0 | ... AF5: =AF62 -> 0
B6: Total Sales ($M) | E6: =E4+E5 -> 0 | F6: =F4+F5 -> 0 | G6: =G4+G5 -> 0 | H6: =H4+H5 -> 0 | I6: =I4+I5 -> 0 | J6: =J4+J5 -> 0 | K6: =K4+K5 -> 0 | L6: =L4+L5 -> 0 | ... AF6: =AF4+AF5 -> 1335.0132
B8: ML-007C-MA Patient Summary | E8: 2018 | F8: =E8+1 -> 2019 | G8: =F8+1 -> 2020 | H8: =G8+1 -> 2021 | I8: =H8+1 -> 2022 | J8: =I8+1 -> 2023 | K8: =J8+1 -> 2024 | L8: =K8+1 -> 2025 | M8: =L8+1 -> 2026 | ... AF8: =AE8+1 -> 2045
B9: US | E9: =E29 -> 0 | F9: =F29 -> 0 | G9: =G29 -> 0 | H9: =H29 -> 0 | I9: =I29 -> 0 | J9: =J29 -> 0 | K9: =K29 -> 0 | L9: =L29 -> 0 | ... AF9: =AF29 -> 82920.073
B10: EU5 | E10: =E55 -> 0 | F10: =F55 -> 0 | G10: =G55 -> 0 | H10: =H55 -> 0 | I10: =I55 -> 0 | J10: =J55 -> 0 | K10: =K55 -> 0 | L10: =L55 -> 0 | ... AF10: =AF55 -> 0
B11: Total Patients | E11: =E9+E10 -> 0 | F11: =F9+F10 -> 0 | G11: =G9+G10 -> 0 | H11: =H9+H10 -> 0 | I11: =I9+I10 -> 0 | J11: =J9+J10 -> 0 | K11: =K9+K10 -> 0 | L11: =L9+L10 -> 0 | ... AF11: =AF9+AF10 -> 82920.073
B13: ML-007C-MA for Schizophrenia - US Market Model | E13: 2018 | F13: =E13+1 -> 2019 | G13: =F13+1 -> 2020 | H13: =G13+1 -> 2021 | I13: =H13+1 -> 2022 | J13: =I13+1 -> 2023 | K13: =J13+1 -> 2024 | L13: =K13+1 -> 2025 | M13: =L13+1 -> 2026 | ... AF13: =AE13+1 -> 2045
B14: US Population (000s) | E14: =327.2*1000 -> 327200 | F14: =E14*(1+F$15) -> 329654 | G14: =F14*(1+G$15) -> 332126.41 | H14: =G14*(1+H$15) -> 334617.35 | I14: =H14*(1+I$15) -> 337126.98 | J14: =I14*(1+J$15) -> 339655.44 | K14: =J14*(1+K$15) -> 342202.85 | L14: =K14*(1+L$15) -> 344769.37 | M14: =L14*(1+M$15) -> 347355.14 | ... AF14: =AE14*(1+AF$15) -> 400340.73
B15: Annual Growth Rate | C15: 0.0075 | E15: =C15 -> 0.0075 | F15: =E15 -> 0.0075 | G15: =F15 -> 0.0075 | H15: =G15 -> 0.0075 | I15: =H15 -> 0.0075 | J15: =I15 -> 0.0075 | K15: =J15 -> 0.0075 | L15: =K15 -> 0.0075 | M15: =L15 -> 0.0075 | ... AF15: =AE15 -> 0.0075
B17: Total SCZ Adult Prevalence (000s) | E17: =E14*$C18 -> 2454 | F17: =F14*$C18 -> 2472.405 | G17: =G14*$C18 -> 2490.948 | H17: =H14*$C18 -> 2509.6301 | I17: =I14*$C18 -> 2528.4524 | J17: =J14*$C18 -> 2547.4158 | K17: =K14*$C18 -> 2566.5214 | L17: =L14*$C18 -> 2585.7703 | ... AF17: =AF14*$C18 -> 3002.5555
B18: Prevalence | C18: =7.5/1000 -> 0.0075 | E18: =C18 -> 0.0075 | F18: =C18 -> 0.0075 | G18: =F18 -> 0.0075 | H18: =G18 -> 0.0075 | I18: =H18 -> 0.0075 | J18: =I18 -> 0.0075 | K18: =J18 -> 0.0075 | L18: =K18 -> 0.0075 | M18: =L18 -> 0.0075 | N18: =M18 -> 0.0075 | ... AF18: =AE18 -> 0.0075
B20: Total Diagnosed SCZ Patients (000s) | E20: =E17*E21 -> 2331.3 | F20: =F17*F21 -> 2348.7847 | G20: =G17*G21 -> 2366.4006 | H20: =H17*H21 -> 2384.1486 | I20: =I17*I21 -> 2402.0298 | J20: =J17*J21 -> 2420.045 | K20: =K17*K21 -> 2438.1953 | L20: =L17*L21 -> 2456.4818 | ... AF20: =AF17*AF21 -> 2852.4277
B21: Diagnosis Rate | C21: 0.95 | E21: =C21 -> 0.95 | F21: =E21 -> 0.95 | G21: =F21 -> 0.95 | H21: =G21 -> 0.95 | I21: =H21 -> 0.95 | J21: =I21 -> 0.95 | K21: =J21 -> 0.95 | L21: =K21 -> 0.95 | M21: =L21 -> 0.95 | ... AF21: =AE21 -> 0.95
B23: Patients Requiring Treatment (000s) | E23: =E20*(1-E24) -> 1981.605 | F23: =F20*(1-F24) -> 1996.467 | G23: =G20*(1-G24) -> 2011.4405 | H23: =H20*(1-H24) -> 2026.5263 | I23: =I20*(1-I24) -> 2041.7253 | J23: =J20*(1-J24) -> 2057.0382 | K23: =K20*(1-K24) -> 2072.466 | L23: =L20*(1-L24) -> 2088.0095 | ... AF23: =AF20*(1-AF24) -> 2424.5635
B24: % Not requiring treatment at all | C24: 0.15 | E24: =C24 -> 0.15 | F24: =C24 -> 0.15 | G24: =F24 -> 0.15 | H24: =G24 -> 0.15 | I24: =H24 -> 0.15 | J24: =I24 -> 0.15 | K24: =J24 -> 0.15 | L24: =K24 -> 0.15 | M24: =L24 -> 0.15 | N24: =M24 -> 0.15 | ... AF24: =AE24 -> 0.15
B26: Tx Discontinuation Rate | E26: =E23*(E27)*1000 -> 792642 | F26: =F23*(F27)*1000 -> 798586.81 | G26: =G23*(G27)*1000 -> 804576.22 | H26: =H23*(H27)*1000 -> 810610.54 | I26: =I23*(I27)*1000 -> 816690.12 | J26: =J23*(J27)*1000 -> 822815.29 | K26: =K23*(K27)*1000 -> 828986.41 | L26: =L23*(L27)*1000 -> 835203.81 | M26: =M23*(1-M27)*1000 -> 1262201.8 | N26: =N23*(1-N27)*1000 -> 1271668.3 | O26: =O23*(1-O27)*1000 -> 1281205.8 | P26: =P23*(1-P27)*1000 -> 1290814.8 | Q26: =Q23*(1-Q27)*1000 -> 1300495.9 | R26: =R23*(1-R27)*1000 -> 1310249.6 | S26: =S23*(1-S27)*1000 -> 1320076.5 | T26: =T23*(1-T27)*1000 -> 1329977.1 | ... AF26: =AF23*(1-AF27)*1000 -> 1454738.1
B27: Prevalence | C27: 0.4 | E27: =C27 -> 0.4 | F27: =C27 -> 0.4 | G27: =F27 -> 0.4 | H27: =G27 -> 0.4 | I27: =H27 -> 0.4 | J27: =I27 -> 0.4 | K27: =J27 -> 0.4 | L27: =K27 -> 0.4 | M27: =C27 -> 0.4 | N27: =M27 -> 0.4 | O27: =N27 -> 0.4 | P27: =O27 -> 0.4 | Q27: =P27 -> 0.4 | R27: =Q27 -> 0.4 | S27: =R27 -> 0.4 | T27: =S27 -> 0.4 | U27: =T27 -> 0.4 | ... AF27: =AE27 -> 0.4
B29: Total ML-007C-MA Patients Treated | E29: =E30*E26 -> 0 | F29: =F30*F26 -> 0 | G29: =G30*G26 -> 0 | H29: =H30*H26 -> 0 | I29: =I30*I26 -> 0 | J29: =J30*J26 -> 0 | K29: =K30*K26 -> 0 | L29: =L30*L26 -> 0 | ... AF29: =AF30*AF26 -> 82920.073
B30: % penetration | P30: 0 | Q30: 0.0015 | R30: =Q30+0.37% -> 0.0052 | S30: =R30+0.37% -> 0.0089 | T30: =S30+0.37% -> 0.0126 | U30: =T30+0.37% -> 0.0163 | V30: =U30+0.37% -> 0.02 | W30: =V30+0.37% -> 0.0237 | X30: =W30+0.37% -> 0.0274 | Y30: =X30+0.37% -> 0.0311 | ... AF30: =AE30+0.37% -> 0.057
B32: Annual Gross Price | C32: 23000 | E32: 0 | F32: 0 | G32: 0 | H32: 0 | I32: 0 | J32: 0 | K32: 0 | L32: 0 | M32: 0 | N32: 0 | O32: 0 | P32: 0 | Q32: =C32 -> 23000 | R32: =Q32*(1+R33) -> 23000 | S32: =R32*(1+S33) -> 23000 | T32: =S32*(1+T33) -> 23000 | U32: =T32*(1+U33) -> 23000 | V32: =U32*(1+V33) -> 23000 | W32: =V32*(1+W33) -> 23000 | X32: =W32*(1+X33) -> 23000 | Y32: =X32*(1+Y33) -> 23000 | ... AF32: =AE32*(1+AF33) -> 23000
B33: % Price increase | E33: 0 | F33: 0 | G33: 0 | H33: 0 | I33: 0 | J33: 0 | K33: 0 | L33: 0 | M33: 0 | N33: 0 | O33: 0 | Q33: 0 | R33: 0 | S33: 0 | T33: 0 | U33: 0 | V33: 0 | W33: 0 | X33: 0 | Y33: 0 | Z33: 0 | AA33: 0 | AB33: 0 | AC33: 0 | AD33: 0 | AE33: 0 | AF33: 0
B34: Annual Net Price | E34: =E27*E32/1000000 -> 0 | F34: =F27*F32/1000000 -> 0 | G34: =G27*G32/1000000 -> 0 | H34: =H27*H32/1000000 -> 0 | I34: =I27*I32/1000000 -> 0 | J34: =J27*J32/1000000 -> 0 | K34: =K27*K32/1000000 -> 0 | L34: =L27*L32/1000000 -> 0 | ... O34: =O27*O32/1000000 -> 0 | P34: =P32*(1-P35) -> 0 | Q34: =Q32*(1-Q35) -> 17250 | R34: =R32*(1-R35) -> 17020 | S34: =S32*(1-S35) -> 16790 | T34: =T32*(1-T35) -> 16560 | U34: =U32*(1-U35) -> 16330 | V34: =V32*(1-V35) -> 16100 | W34: =W32*(1-W35) -> 16100 | ... AF34: =AF32*(1-AF35) -> 16100
B35: Gross to net | E35: 0 | F35: 0 | G35: 0 | H35: 0 | I35: 0 | J35: 0 | K35: 0 | L35: 0 | M35: 0 | N35: 0 | O35: 0 | P35: 0 | Q35: 0.25 | R35: 0.26 | S35: 0.27 | T35: 0.28 | U35: 0.29 | V35: 0.3 | W35: 0.3 | X35: 0.3 | Y35: 0.3 | Z35: 0.3 | AA35: 0.3 | AB35: 0.3 | AC35: 0.3 | AD35: 0.3 | AE35: 0.3 | AF35: 0.3
B36: US Revenue ($M) | E36: =E34*E35 -> 0 | F36: =F34*F35 -> 0 | G36: =G34*G35 -> 0 | H36: =H34*H35 -> 0 | I36: =I34*I35 -> 0 | J36: =J34*J35 -> 0 | K36: =K34*K35 -> 0 | L36: =L34*L35 -> 0 | ... O36: =O34*O35 -> 0 | P36: =P29*P34/1000000 -> 0 | Q36: =Q29*Q34/1000000 -> 33.650332 | R36: =R29*R34/1000000 -> 115.96234 | S36: =S29*S34/1000000 -> 197.26035 | T36: =T29*T34/1000000 -> 277.5077 | U36: =U29*U34/1000000 -> 356.66706 | V36: =V29*V34/1000000 -> 434.7005 | W36: =W29*W34/1000000 -> 518.9835 | ... AF36: =AF29*AF34/1000000 -> 1335.0132
B37: Reported/Projected in Income Statement | E37: 0 | F37: 0 | G37: 0 | H37: 0 | I37: 0 | J37: 0 | K37: 0 | L37: 0 | M37: 0 | N37: 0 | O37: 0 | P37: =IS!V11 -> 0 | Q37: =IS!W11 -> 35 | R37: 0 | S37: 0 | T37: 0 | U37: 0 | V37: 0 | W37: 0 | X37: 0 | Y37: 0 | Z37: 0 | AA37: 0 | AB37: 0 | AC37: 0 | AD37: 0 | AE37: 0 | AF37: 0
B39: ML-007C-MA for Schizophrenia - EU Market Model | E39: 2018 | F39: =E39+1 -> 2019 | G39: =F39+1 -> 2020 | H39: =G39+1 -> 2021 | I39: =H39+1 -> 2022 | J39: =I39+1 -> 2023 | K39: =J39+1 -> 2024 | L39: =K39+1 -> 2025 | M39: =L39+1 -> 2026 | ... AF39: =AE39+1 -> 2045
B40: EU5 Population (000s) | E40: 320549.95 | F40: =E40*(1+F$15) -> 322954.07 | G40: =F40*(1+G$15) -> 325376.23 | H40: =G40*(1+H$15) -> 327816.55 | I40: =H40*(1+I$15) -> 330275.18 | J40: =I40*(1+J$15) -> 332752.24 | K40: =J40*(1+K$15) -> 335247.88 | L40: =K40*(1+L$15) -> 337762.24 | M40: =L40*(1+M$15) -> 340295.46 | ... AF40: =AE40*(1+AF$15) -> 392204.16
B41: Annual Growth Rate | C41: 0.001 | E41: =C41 -> 0.001 | F41: =E41 -> 0.001 | G41: =F41 -> 0.001 | H41: =G41 -> 0.001 | I41: =H41 -> 0.001 | J41: =I41 -> 0.001 | K41: =J41 -> 0.001 | L41: =K41 -> 0.001 | M41: =L41 -> 0.001 | ... AF41: =AE41 -> 0.001
B43: Total SCZ Adult Prevalence (000s) | E43: =E40*$C44 -> 2404.1246 | F43: =F40*$C44 -> 2422.1556 | G43: =G40*$C44 -> 2440.3217 | H43: =H40*$C44 -> 2458.6241 | I43: =I40*$C44 -> 2477.0638 | J43: =J40*$C44 -> 2495.6418 | K43: =K40*$C44 -> 2514.3591 | L43: =L40*$C44 -> 2533.2168 | ... AF43: =AF40*$C44 -> 2941.5312
B44: Prevalence | C44: =7.5/1000 -> 0.0075 | E44: =C44 -> 0.0075 | F44: =C44 -> 0.0075 | G44: =F44 -> 0.0075 | H44: =G44 -> 0.0075 | I44: =H44 -> 0.0075 | J44: =I44 -> 0.0075 | K44: =J44 -> 0.0075 | L44: =K44 -> 0.0075 | M44: =L44 -> 0.0075 | N44: =M44 -> 0.0075 | ... AF44: =AE44 -> 0.0075
B46: Total Diagnosed SCZ Patients (000s) | E46: =E43*E47 -> 2283.9184 | F46: =F43*F47 -> 2301.0478 | G46: =G43*G47 -> 2318.3056 | H46: =H43*H47 -> 2335.6929 | I46: =I43*I47 -> 2353.2106 | J46: =J43*J47 -> 2370.8597 | K46: =K43*K47 -> 2388.6412 | L46: =L43*L47 -> 2406.556 | ... AF46: =AF43*AF47 -> 2794.4546
B47: Diagnosis Rate | C47: 0.95 | E47: =C47 -> 0.95 | F47: =E47 -> 0.95 | G47: =F47 -> 0.95 | H47: =G47 -> 0.95 | I47: =H47 -> 0.95 | J47: =I47 -> 0.95 | K47: =J47 -> 0.95 | L47: =K47 -> 0.95 | M47: =L47 -> 0.95 | ... AF47: =AE47 -> 0.95
B49: Patients Requiring Treatment (000s) | E49: =E46*(1-E50) -> 1941.3306 | F49: =F46*(1-F50) -> 1955.8906 | G49: =G46*(1-G50) -> 1970.5598 | H49: =H46*(1-H50) -> 1985.339 | I49: =I46*(1-I50) -> 2000.229 | J49: =J46*(1-J50) -> 2015.2307 | K49: =K46*(1-K50) -> 2030.345 | L49: =L46*(1-L50) -> 2045.5726 | ... AF49: =AF46*(1-AF50) -> 2375.2864
B50: % Not requiring treatment at all | C50: 0.15 | E50: =C50 -> 0.15 | F50: =C50 -> 0.15 | G50: =F50 -> 0.15 | H50: =G50 -> 0.15 | I50: =H50 -> 0.15 | J50: =I50 -> 0.15 | K50: =J50 -> 0.15 | L50: =K50 -> 0.15 | M50: =L50 -> 0.15 | N50: =M50 -> 0.15 | ... AF50: =AE50 -> 0.15
B52: Discontinuation Rate | E52: =E49*(E53)*1000 -> 776532.25 | F52: =F49*(F53)*1000 -> 782356.24 | G52: =G49*(G53)*1000 -> 788223.92 | H52: =H49*(H53)*1000 -> 794135.6 | I52: =I49*(I53)*1000 -> 800091.61 | J52: =J49*(J53)*1000 -> 806092.3 | K52: =K49*(K53)*1000 -> 812137.99 | L52: =L49*(L53)*1000 -> 818229.03 | ... AF52: =AF49*(AF53)*1000 -> 1425171.9
B53: Prevalence | C53: 0.4 | E53: =C53 -> 0.4 | F53: =C53 -> 0.4 | G53: =F53 -> 0.4 | H53: =G53 -> 0.4 | I53: =H53 -> 0.4 | J53: =I53 -> 0.4 | K53: =J53 -> 0.4 | L53: =K53 -> 0.4 | M53: =1-C53 -> 0.6 | N53: =M53 -> 0.6 | O53: =N53 -> 0.6 | P53: =O53 -> 0.6 | Q53: =P53 -> 0.6 | R53: =Q53 -> 0.6 | S53: =R53 -> 0.6 | T53: =S53 -> 0.6 | U53: =T53 -> 0.6 | ... AF53: =AE53 -> 0.6
B55: Total ML-007C-MA Patients Treated | E55: =E56*E52 -> 0 | F55: =F56*F52 -> 0 | G55: =G56*G52 -> 0 | H55: =H56*H52 -> 0 | I55: =I56*I52 -> 0 | J55: =J56*J52 -> 0 | K55: =K56*K52 -> 0 | L55: =L56*L52 -> 0 | ... AF55: =AF56*AF52 -> 0
B56: % penetration | E56: =C56 -> 0 | F56: =E56 -> 0 | G56: 0 | H56: 0 | I56: =H56 -> 0 | J56: 0 | K56: 0 | L56: 0 | M56: 0 | N56: 0 | O56: 0 | P56: 0 | Q56: 0 | R56: 0 | S56: 0 | T56: 0 | U56: 0 | V56: 0 | W56: 0 | X56: 0 | Y56: 0 | Z56: 0 | AA56: 0 | AB56: 0 | AC56: 0 | AD56: 0 | AE56: 0 | AF56: 0
B58: Annual Gross Price | C58: 23000 | E58: 0 | F58: 0 | G58: 0 | H58: 0 | I58: 0 | J58: 0 | K58: 0 | L58: 0 | M58: 0 | N58: 0 | O58: 0 | P58: =C58 -> 23000 | Q58: =P58*(1+Q59) -> 23000 | R58: =Q58*(1+R59) -> 23000 | S58: =R58*(1+S59) -> 23000 | T58: =S58*(1+T59) -> 23000 | U58: =T58*(1+U59) -> 23000 | V58: =U58*(1+V59) -> 23000 | W58: =V58*(1+W59) -> 23000 | X58: =W58*(1+X59) -> 23000 | ... AF58: =AE58*(1+AF59) -> 23000
B59: % Price increase | C59: 0 | P59: =$C59 -> 0 | Q59: =$C59 -> 0 | R59: =$C59 -> 0 | S59: =$C59 -> 0 | T59: =$C59 -> 0 | U59: =$C59 -> 0 | V59: =$C59 -> 0 | W59: =$C59 -> 0 | ... AF59: =$C59 -> 0
B60: Annual Net Price | E60: 0 | F60: 0 | G60: 0 | H60: 0 | I60: 0 | J60: =J58*(1-J61) -> 0 | K60: =K58*(1-K61) -> 0 | L60: =L58*(1-L61) -> 0 | M60: =M58*(1-M61) -> 0 | N60: =N58*(1-N61) -> 0 | O60: =O58*(1-O61) -> 0 | P60: =P58*(1-P61) -> 23000 | Q60: =Q58*(1-Q61) -> 23000 | ... AF60: =AF58*(1-AF61) -> 23000
B61: Gross to net | C61: 0 | E61: 0 | F61: 0 | G61: 0 | H61: 0 | I61: 0 | J61: 0 | K61: 0 | L61: 0 | M61: 0 | N61: 0 | O61: 0 | P61: =C61 -> 0 | Q61: =P61 -> 0 | R61: =Q61 -> 0 | S61: =R61 -> 0 | T61: =S61 -> 0 | U61: =T61 -> 0 | V61: =U61 -> 0 | W61: =V61 -> 0 | X61: =W61 -> 0 | ... AF61: =AE61 -> 0
B62: EU5 Revenue ($M) | E62: =E55*E60/1000000 -> 0 | F62: =F55*F60/1000000 -> 0 | G62: =G55*G60/1000000 -> 0 | H62: =H55*H60/1000000 -> 0 | I62: =I55*I60/1000000 -> 0 | J62: =J55*J60/1000000 -> 0 | K62: =K55*K60/1000000 -> 0 | L62: =L55*L60/1000000 -> 0 | ... AF62: =AF55*AF60/1000000 -> 0
B63: Royalty Rate | C63: 0.25 | E63: 0 | F63: 0 | G63: 0 | H63: 0 | I63: 0 | J63: 0 | K63: 0 | L63: 0 | M63: 0 | N63: 0 | O63: 0 | P63: =$C63 -> 0.25 | Q63: =$C63 -> 0.25 | R63: =$C63 -> 0.25 | S63: =$C63 -> 0.25 | T63: =$C63 -> 0.25 | U63: =$C63 -> 0.25 | V63: =$C63 -> 0.25 | W63: =$C63 -> 0.25 | ... AF63: =$C63 -> 0.25
B64: EU5 Royalties ($M) | E64: =E62*E63 -> 0 | F64: =F62*F63 -> 0 | G64: =G62*G63 -> 0 | H64: =H62*H63 -> 0 | I64: =I62*I63 -> 0 | J64: =J62*J63 -> 0 | K64: =K62*K63 -> 0 | L64: =L62*L63 -> 0 | ... AF64: =AF62*AF63 -> 0
B65: Reported/Projected in Income Statement | E65: 0 | F65: 0 | G65: 0 | H65: 0 | I65: 0
B67: TRADITIONAL DCF VALUATION
B68: DCF | E68: 2018 | F68: =E68+1 -> 2019 | G68: =F68+1 -> 2020 | H68: =G68+1 -> 2021 | I68: =H68+1 -> 2022 | J68: =I68+1 -> 2023 | K68: =J68+1 -> 2024 | L68: =K68+1 -> 2025 | M68: =L68+1 -> 2026 | ... AF68: =AE68+1 -> 2045
B69: Revenue (in $M) | E69: =SUM(E70,E71) -> 0 | F69: =SUM(F70,F71) -> 0 | G69: =SUM(G70,G71) -> 0 | H69: =SUM(H70,H71) -> 0 | I69: =SUM(I70,I71) -> 0 | J69: =SUM(J70,J71) -> 0 | K69: =SUM(K70,K71) -> 0 | L69: =SUM(L70,L71) -> 0 | ... AF69: =SUM(AF70,AF71) -> 1335.0132
B70: US | E70: =E36 -> 0 | F70: =F36 -> 0 | G70: =G36 -> 0 | H70: =H36 -> 0 | I70: =I36 -> 0 | J70: =J36 -> 0 | K70: =K36 -> 0 | L70: =L36 -> 0 | ... AF70: =AF36 -> 1335.0132
B71: EU5 | E71: =E64 -> 0 | F71: =F64 -> 0 | G71: =G64 -> 0 | H71: =H64 -> 0 | I71: =I64 -> 0 | J71: =J64 -> 0 | K71: =K64 -> 0 | L71: =L64 -> 0 | ... AF71: =AF64 -> 0
B72: Milestone Payments | E72: 0 | F72: 0 | G72: 0 | H72: 0 | I72: 0 | J72: 0 | K72: 0 | L72: 0 | M72: 0 | N72: 0 | O72: 0 | P72: 0 | Q72: 0 | R72: 0 | S72: 0 | T72: 0 | U72: 0 | V72: 0 | W72: 0 | X72: 0 | Y72: 0 | Z72: 0 | AA72: 0 | AB72: 0 | AC72: 0 | AD72: 0 | AE72: 0 | AF72: 0
B73: Royalties | C73: 0 | E73: =E69*$C73 -> 0 | F73: =F69*$C73 -> 0 | G73: =G69*$C73 -> 0 | H73: =H69*$C73 -> 0 | I73: =I69*$C73 -> 0 | J73: =J69*$C73 -> 0 | K73: =K69*$C73 -> 0 | L73: =L69*$C73 -> 0 | ... AF73: =AF69*$C73 -> 0
B74: Cost of Goods sold | E74: 0 | F74: =F69*F75 -> 0 | G74: =G69*G75 -> 0 | H74: =H69*H75 -> 0 | I74: =I69*I75 -> 0 | J74: =J69*J75 -> 0 | K74: =K69*K75 -> 0 | L74: =L69*L75 -> 0 | M74: =M69*M75 -> 0 | ... AF74: =AF69*AF75 -> 66.750659
B75: % of Revenue | E75: =IF(E69=0,0,5%) -> 0 | F75: =IF(F69=0,0,5%) -> 0 | G75: =IF(G69=0,0,5%) -> 0 | H75: =IF(H69=0,0,5%) -> 0 | I75: =IF(I69=0,0,5%) -> 0 | J75: =IF(J69=0,0,5%) -> 0 | K75: =IF(K69=0,0,5%) -> 0 | L75: =IF(L69=0,0,5%) -> 0 | ... AF75: =IF(AF69=0,0,5%) -> 0.05
B76: R&D | E76: 0 | F76: 0 | G76: 0 | H76: 0 | I76: 0 | J76: =IS!D23*0.4 -> 19.87 | K76: =IS!I23*0.4 -> 27.4092 | L76: =IS!N23*0.4 -> 43.0908 | M76: =IS!S23*0.4 -> 72 | N76: =IS!T23*0.4 -> 108.76 | O76: =IS!U23*0.4 -> 122.074 | P76: =IS!V23*0.4 -> 137.0851 | Q76: 50 | R76: 25 | S76: 10 | T76: 10 | U76: 10 | V76: 10 | W76: 10 | X76: 10 | Y76: 10 | Z76: 10 | AA76: 10 | AB76: 10 | AC76: 10 | AD76: 10 | AE76: 10 | AF76: 10
B77: % of Revenue | E77: =IFERROR(E76/E69,"-") -> - | F77: =IFERROR(F76/F69,"-") -> - | G77: =IFERROR(G76/G69,"-") -> - | H77: =IFERROR(H76/H69,"-") -> - | I77: =IFERROR(I76/I69,"-") -> - | P77: =IFERROR(P76/P69,"-") -> - | Q77: =IFERROR(Q76/Q69,"-") -> 1.4858694 | R77: =IFERROR(R76/R69,"-") -> 0.21558724 | S77: =IFERROR(S76/S69,"-") -> 0.050694424 | T77: =IFERROR(T76/T69,"-") -> 0.036035036 | U77: =IFERROR(U76/U69,"-") -> 0.028037352 | V77: =IFERROR(V76/V69,"-") -> 0.023004344 | W77: =IFERROR(W76/W69,"-") -> 0.019268435 | ... AF77: =IFERROR(AF76/AF69,"-") -> 0.0074905628
B78: SG&A | E78: 0 | F78: 0 | G78: 0 | H78: 0 | I78: 0 | J78: =IS!D24*0.4 -> 3.0428 | K78: =IS!I24*0.4 -> 5.7692 | L78: =IS!N24*0.4 -> 6.7108 | M78: =IS!S24*0.4 -> 10.08 | N78: =IS!T24*0.4 -> 12.052 | O78: =IS!U24*0.4 -> 14.4118 | P78: 50 | Q78: 100 | R78: 100 | S78: 100 | T78: 100 | U78: 100 | V78: 100 | W78: 100 | X78: 100 | Y78: 100 | Z78: 100 | AA78: 100 | AB78: 100 | AC78: 100 | AD78: 100 | AE78: 100 | AF78: 100
B79: % of Revenue | E79: =IFERROR(E78/E69,"-") -> - | F79: =IFERROR(F78/F69,"-") -> - | G79: =IFERROR(G78/G69,"-") -> - | H79: =IFERROR(H78/H69,"-") -> - | I79: =IFERROR(I78/I69,"-") -> - | P79: =IFERROR(P78/P69,"-") -> - | Q79: =IFERROR(Q78/Q69,"-") -> 2.9717389 | R79: =IFERROR(R78/R69,"-") -> 0.86234897 | S79: =IFERROR(S78/S69,"-") -> 0.50694424 | T79: =IFERROR(T78/T69,"-") -> 0.36035036 | U79: =IFERROR(U78/U69,"-") -> 0.28037352 | V79: =IFERROR(V78/V69,"-") -> 0.23004344 | W79: =IFERROR(W78/W69,"-") -> 0.19268435 | ... AF79: =IFERROR(AF78/AF69,"-") -> 0.074905628
B80: Total EBIT | E80: =E69-E74-E76-E78-E72 -> 0 | F80: =F69-F74-F76-F78-F72 -> 0 | G80: =G69-G74-G76-G78-G72 -> 0 | H80: =H69-H74-H76-H78-H72 -> 0 | I80: =I69-I74-I76-I78-I72 -> 0 | J80: =J69-J74-J76-J78-J72 -> -22.9128 | K80: =K69-K74-K76-K78-K72 -> -33.1784 | L80: =L69-L74-L76-L78-L72 -> -49.8016 | ... AF80: =AF69-AF74-AF76-AF78-AF72 -> 1158.2625
B81: Tax rate | E81: =IF(E80>0, 20%, 0%) -> 0 | F81: =IF(F80>0, 20%, 0%) -> 0 | G81: =IF(G80>0, 20%, 0%) -> 0 | H81: 0 | I81: 0 | J81: 0 | K81: =IF(K80>0, 15%, 0%) -> 0 | L81: =IF(L80>0, 15%, 0%) -> 0 | M81: =IF(M80>0, 15%, 0%) -> 0 | N81: =IF(N80>0, 15%, 0%) -> 0 | O81: =IF(O80>0, 15%, 0%) -> 0 | P81: =IF(P80>0, 15%, 0%) -> 0 | Q81: =IF(Q80>0, 15%, 0%) -> 0 | R81: =IF(R80>0, 15%, 0%) -> 0 | ... AF81: =IF(AF80>0, 15%, 0%) -> 0.15
B82: Profit | E82: =E80*(1-E81) -> 0 | F82: =F80*(1-F81) -> 0 | G82: =G80*(1-G81) -> 0 | H82: =H80*(1-H81) -> 0 | I82: =I80*(1-I81) -> 0 | J82: =J80*(1-J81) -> -22.9128 | K82: =K80*(1-K81) -> -33.1784 | L82: =L80*(1-L81) -> -49.8016 | ... AF82: =AF80*(1-AF81) -> 984.52314
B84: D&A | E84: 0 | F84: 0 | G84: 0 | H84: 0 | I84: 0 | J84: 0 | K84: =J84 -> 0 | L84: =K84 -> 0 | M84: =L84 -> 0 | N84: =M84 -> 0 | O84: =N84 -> 0 | P84: =O84 -> 0 | Q84: =P84 -> 0 | R84: =Q84 -> 0 | ... AF84: =AE84 -> 0
B85: Stock Option Expense | E85: 0 | F85: 0 | G85: 0 | H85: 0 | I85: 0 | J85: =J78*30% -> 0.91284 | K85: =K78*30% -> 1.73076 | L85: =L78*30% -> 2.01324 | M85: =M78*30% -> 3.024 | N85: =N78*30% -> 3.6156 | O85: =O78*30% -> 4.32354 | P85: =P78*30% -> 15 | Q85: =Q78*30% -> 30 | ... AF85: =AF78*30% -> 30
B86: Capex | E86: 0 | F86: 0 | G86: 0 | H86: 0 | I86: 0 | J86: 0 | K86: =J86 -> 0 | L86: =K86 -> 0 | M86: =L86 -> 0 | N86: =M86 -> 0 | O86: =N86 -> 0 | P86: =O86 -> 0 | Q86: =P86 -> 0 | R86: =Q86 -> 0 | ... AF86: =AE86 -> 0
B87: Working Capital | E87: 0 | F87: 0 | G87: 0 | H87: 0 | I87: 0 | J87: 0 | K87: 0 | L87: 0 | M87: =L87 -> 0 | N87: =M87 -> 0 | O87: =N87 -> 0 | P87: =O87 -> 0 | Q87: =P87 -> 0 | R87: =Q87 -> 0 | S87: =R87 -> 0 | T87: =S87 -> 0 | ... AF87: =AE87 -> 0
B88: FCF (in $M) | E88: =E82+SUM(E84:E87) -> 0 | F88: =F82+SUM(F84:F87) -> 0 | G88: =G82+SUM(G84:G87) -> 0 | H88: =H82+SUM(H84:H87) -> 0 | I88: =I82+SUM(I84:I87) -> 0 | J88: =J82+SUM(J84:J87) -> -21.99996 | K88: =K82+SUM(K84:K87) -> -31.44764 | L88: =L82+SUM(L84:L87) -> -47.78836 | ... AF88: =AF82+SUM(AF84:AF87) -> 1014.5231 | AG88: =AF88*(1+C94)/(C95-C94) -> 2237.9187
B90: Discount period | C90: 2026 | M90: =M68-$C$90 -> 0 | N90: =N68-$C$90 -> 1 | O90: =O68-$C$90 -> 2 | P90: =P68-$C$90 -> 3 | Q90: =Q68-$C$90 -> 4 | R90: =R68-$C$90 -> 5 | S90: =S68-$C$90 -> 6 | T90: =T68-$C$90 -> 7 | ... AF90: =AF68-$C$90 -> 19 | AG90: =AF90 -> 19
B91: NPV | M91: =M88/(1+$C$95)^M90 -> -79.056 | N91: =N88/(1+$C$95)^N90 -> -107.51963 | O91: =O88/(1+$C$95)^O90 -> -111.23833 | P91: =P88/(1+$C$95)^P90 -> -132.88127 | Q91: =Q88/(1+$C$95)^Q90 -> -62.364219 | R91: =R88/(1+$C$95)^R90 -> 9.8557014 | S91: =S88/(1+$C$95)^S90 -> 57.115098 | T91: =T88/(1+$C$95)^T90 -> 87.846845 | ... AG91: =AG88/(1+$C$95)^AG90 -> 435.25207
B93: NPV Sum (in $M) | C93: =IF(C90=F68,SUM(F91:AG91),(SUM(G91:AG91))) -> 2196.0386 | M93: $/share | O93: Downside | P93: Base Case | Q93: Upside
B94: Terminal Growth (%) | C94: -0.25 | M94: Probability adjusted NPV | O94: =C93*O95 -> 109.80193 | P94: =C98 -> 878.41545 | Q94: =C93*Q95 -> 1317.6232
B95: Discount Rate | C95: 0.09 | M95: Assumed PoS | O95: 0.05 | P95: =C97 -> 0.4 | Q95: 0.6
B96: Share count (in M) | C96: =SOTP!D38 -> 53.187829 | M96: ML-007C-MA | O96: =P96/P95*O95 -> 2.0644184 | P96: =C99 -> 16.515347 | Q96: =P96/P95*Q95 -> 24.77302
B97: Probability of Success | C97: 0.4
B98: Probability adjusted NPV | C98: =C93*C97 -> 878.41545
B99: Price Per Share | C99: =C98/C96 -> 16.515347
M101: Peak Sales Calculator | O101: Downside | P101: Base Case | Q101: Upside
M102: Peak sales ($M) | O102: 500 | P102: =MAX(Q69:AF69) -> 1335.0132 | Q102: 2500
M103: Multiple | O103: 2 | P103: 2 | Q103: 2.5
M104: Valuation | O104: =O102*O103 -> 1000 | P104: =P102*P103 -> 2670.0263 | Q104: =Q102*Q103 -> 6250
M105: Assumed PoS | O105: =O95 -> 0.05 | P105: =P95 -> 0.4 | Q105: =Q95 -> 0.6
M106: $/Share | O106: =O104/$C96*O105 -> 0.94006469 | P106: =P104/$C96*P105 -> 20.07998 | Q106: =Q104/$C96*Q105 -> 70.504852

Sheet ADP DCF
B1: ML-007C-MA Model Analysis for Alzheimer's Disease Psychosis (ADP): Change Assumptions in Blue
B3: ML-007C-MA Sales Summary ($M) | F3: 2023 | G3: =F3+1 -> 2024 | H3: =G3+1 -> 2025 | I3: =H3+1 -> 2026 | J3: =I3+1 -> 2027 | K3: =J3+1 -> 2028 | L3: =K3+1 -> 2029 | M3: =L3+1 -> 2030 | N3: =M3+1 -> 2031 | ... AB3: =AA3+1 -> 2045
B4: ML-007C-MA (US) | F4: =F36 -> 0 | G4: =G36 -> 0 | H4: =H36 -> 0 | I4: =I36 -> 0 | J4: =J36 -> 0 | K4: =K36 -> 0 | L4: =L36 -> 0 | M4: =M36 -> 0 | ... AB4: =AB36 -> 2070.5346
B5: EU5 (Before royalties) | F5: =F64 -> 0 | G5: =G64 -> 0 | H5: =H64 -> 0 | I5: =I64 -> 0 | J5: =J64 -> 0 | K5: =K64 -> 0 | L5: =L64 -> 0 | M5: =M64 -> 0 | ... AB5: =AB64 -> 0
B6: Total Sales ($M) | F6: =F4+F5 -> 0 | G6: =G4+G5 -> 0 | H6: =H4+H5 -> 0 | I6: =I4+I5 -> 0 | J6: =J4+J5 -> 0 | K6: =K4+K5 -> 0 | L6: =L4+L5 -> 0 | M6: =M4+M5 -> 0 | ... AB6: =AB4+AB5 -> 2070.5346
B8: ML-007C-MA Patient Summary | F8: 2023 | G8: =F8+1 -> 2024 | H8: =G8+1 -> 2025 | I8: =H8+1 -> 2026 | J8: =I8+1 -> 2027 | K8: =J8+1 -> 2028 | L8: =K8+1 -> 2029 | M8: =L8+1 -> 2030 | N8: =M8+1 -> 2031 | ... AB8: =AA8+1 -> 2045
B9: US | F9: =F26 -> 0 | G9: =G26 -> 0 | H9: =H26 -> 0 | I9: =I26 -> 0 | J9: =J26 -> 0 | K9: =K26 -> 0 | L9: =L26 -> 0 | M9: =M26 -> 0 | ... AB9: =AB26 -> 128604.63
B10: EU5 | F10: =F54 -> 0 | G10: =G54 -> 0 | H10: =H54 -> 0 | I10: =I54 -> 0 | J10: =J54 -> 0 | K10: =K54 -> 0 | L10: =L54 -> 0 | M10: =M54 -> 0 | ... AB10: =AB54 -> 0
B11: Total Patients | F11: =F9+F10 -> 0 | G11: =G9+G10 -> 0 | H11: =H9+H10 -> 0 | I11: =I9+I10 -> 0 | J11: =J9+J10 -> 0 | K11: =K9+K10 -> 0 | L11: =L9+L10 -> 0 | M11: =M9+M10 -> 0 | ... AB11: =AB9+AB10 -> 128604.63
B13: ML-007C-MA for ADP - US Market Model | F13: 2023 | G13: =F13+1 -> 2024 | H13: =G13+1 -> 2025 | I13: =H13+1 -> 2026 | J13: =I13+1 -> 2027 | K13: =J13+1 -> 2028 | L13: =K13+1 -> 2029 | M13: =L13+1 -> 2030 | N13: =M13+1 -> 2031 | ... AB13: =AA13+1 -> 2045
B14: US Population (000s) | F14: =339.996563*1000 -> 339996.56 | G14: =F14*(1+D15) -> 341696.55 | H14: =G14*(1+H$15) -> 343405.03 | I14: =H14*(1+I$15) -> 345122.05 | J14: =I14*(1+J$15) -> 346847.66 | K14: =J14*(1+K$15) -> 348581.9 | L14: =K14*(1+L$15) -> 350324.81 | M14: =L14*(1+M$15) -> 352076.44 | N14: =M14*(1+N$15) -> 353836.82 | O14: =N14*(1+O$15) -> 355606 | ... AB14: =AA14*(1+AB$15) -> 379426.7
B15: Annual Growth Rate | D15: 0.005 | G15: =D15 -> 0.005 | H15: =G15 -> 0.005 | I15: =H15 -> 0.005 | J15: =I15 -> 0.005 | K15: =J15 -> 0.005 | L15: =K15 -> 0.005 | M15: =L15 -> 0.005 | N15: =M15 -> 0.005 | O15: =N15 -> 0.005 | ... AB15: =AA15 -> 0.005
B17: Alzheimer's Disease Population (000s) | F17: =F14*F18 -> 6700 | G17: =G14*G18 -> 6733.5 | H17: =H14*H18 -> 6767.1675 | I17: =I14*I18 -> 6801.0033 | J17: =J14*J18 -> 6835.0084 | K17: =K14*K18 -> 6869.1834 | L17: =L14*L18 -> 6903.5293 | M17: =M14*M18 -> 6938.047 | ... AB17: =AB14*AB18 -> 7477.0134
B18: Prevalence | D18: 0.019706082 | F18: =D18 -> 0.019706082 | G18: =F18 -> 0.019706082 | H18: =G18 -> 0.019706082 | I18: =H18 -> 0.019706082 | J18: =I18 -> 0.019706082 | K18: =J18 -> 0.019706082 | L18: =K18 -> 0.019706082 | M18: =L18 -> 0.019706082 | N18: =M18 -> 0.019706082 | ... AB18: =AA18 -> 0.019706082
B20: (1) Alzheimer's with psychosis | F20: =(F17)*F21*1000 -> 2680000 | G20: =(G17)*G21*1000 -> 2693400 | H20: =(H17)*H21*1000 -> 2706867 | I20: =(I17)*I21*1000 -> 2720401.3 | J20: =(J17)*J21*1000 -> 2734003.3 | K20: =(K17)*K21*1000 -> 2747673.4 | L20: =(L17)*L21*1000 -> 2761411.7 | M20: =(M17)*M21*1000 -> 2775218.8 | ... AB20: =(AB17)*AB21*1000 -> 2990805.4
B21: Prevalence | D21: 0.4 | F21: =D21 -> 0.4 | G21: =F21 -> 0.4 | H21: =G21 -> 0.4 | I21: =H21 -> 0.4 | J21: =I21 -> 0.4 | K21: =J21 -> 0.4 | L21: =K21 -> 0.4 | M21: =L21 -> 0.4 | N21: =M21 -> 0.4 | ... AB21: =AA21 -> 0.4
B23: (2) Alzheimer's without psychosis | F23: =(F17)*F24*1000 -> 4020000 | G23: =(G17)*G24*1000 -> 4040100 | H23: =(H17)*H24*1000 -> 4060300.5 | I23: =(I17)*I24*1000 -> 4080602 | J23: =(J17)*J24*1000 -> 4101005 | K23: =(K17)*K24*1000 -> 4121510 | L23: =(L17)*L24*1000 -> 4142117.6 | M23: =(M17)*M24*1000 -> 4162828.2 | ... AB23: =(AB17)*AB24*1000 -> 4486208.1
B24: Prevalence | D24: =1-D21 -> 0.6 | F24: =D24 -> 0.6 | G24: =D24 -> 0.6 | H24: =D24 -> 0.6 | I24: =H24 -> 0.6 | J24: =I24 -> 0.6 | K24: =J24 -> 0.6 | L24: =K24 -> 0.6 | M24: =L24 -> 0.6 | N24: =M24 -> 0.6 | O24: =N24 -> 0.6 | P24: =O24 -> 0.6 | ... AB24: =AA24 -> 0.6
B26: Total ML-007C-MA Patients Treated | F26: =F27+F29 -> 0 | G26: =G27+G29 -> 0 | H26: =H27+H29 -> 0 | I26: =I27+I29 -> 0 | J26: =J27+J29 -> 0 | K26: =K27+K29 -> 0 | L26: =L27+L29 -> 0 | M26: =M27+M29 -> 0 | ... AB26: =AB27+AB29 -> 128604.63
B27: Alzheimer's with psychosis | F27: =F28*F20 -> 0 | G27: =G28*G20 -> 0 | H27: =H28*H20 -> 0 | I27: =I28*I20 -> 0 | J27: =J28*J20 -> 0 | K27: =K28*K20 -> 0 | L27: =L28*L20 -> 0 | M27: =M28*M20 -> 0 | ... AB27: =AB28*AB20 -> 128604.63
B28: % penetration (overall subgroup) | F28: 0 | G28: 0 | H28: 0 | I28: 0 | J28: 0 | K28: 0 | L28: 0 | M28: 0 | N28: 0.001 | O28: =N28+0.3% -> 0.004 | P28: =O28+0.3% -> 0.007 | Q28: =P28+0.3% -> 0.01 | R28: =Q28+0.3% -> 0.013 | S28: =R28+0.3% -> 0.016 | T28: =S28+0.3% -> 0.019 | U28: =T28+0.3% -> 0.022 | V28: =U28+0.3% -> 0.025 | ... AB28: =AA28+0.3% -> 0.043
B29: Alzheimer's without psychosis | F29: =F30*F23 -> 0 | G29: =G30*G23 -> 0 | H29: =H30*H23 -> 0 | I29: =I30*I23 -> 0 | J29: =J30*J23 -> 0 | K29: =K30*K23 -> 0 | L29: =L30*L23 -> 0 | M29: =M30*M23 -> 0 | ... AB29: =AB30*AB23 -> 0
B30: % penetration (overall subgroup) | F30: 0 | G30: 0 | H30: 0 | I30: 0 | J30: 0 | K30: 0 | L30: 0 | M30: 0 | N30: 0 | O30: 0 | P30: 0 | Q30: 0 | R30: 0 | S30: 0 | T30: 0 | U30: 0 | V30: 0 | W30: 0 | X30: 0 | Y30: 0 | Z30: 0 | AA30: 0 | AB30: 0
B32: Annual Gross Price | D32: ='SCZ DCF'!C32 -> 23000 | F32: 0 | G32: 0 | H32: 0 | I32: 0 | J32: 0 | K32: 0 | L32: ='SCZ DCF'!P32 -> 0 | M32: ='SCZ DCF'!Q32 -> 23000 | N32: ='SCZ DCF'!R32 -> 23000 | O32: ='SCZ DCF'!S32 -> 23000 | P32: ='SCZ DCF'!T32 -> 23000 | Q32: ='SCZ DCF'!U32 -> 23000 | R32: ='SCZ DCF'!V32 -> 23000 | S32: ='SCZ DCF'!W32 -> 23000 | ... AB32: ='SCZ DCF'!AF32 -> 23000
B33: % Price increase | F33: 0 | G33: 0 | H33: 0 | I33: 0 | J33: 0 | K33: 0 | L33: 0 | M33: 0 | N33: ='SCZ DCF'!R33 -> 0 | O33: ='SCZ DCF'!S33 -> 0 | P33: ='SCZ DCF'!T33 -> 0 | Q33: ='SCZ DCF'!U33 -> 0 | R33: ='SCZ DCF'!V33 -> 0 | S33: ='SCZ DCF'!W33 -> 0 | T33: ='SCZ DCF'!X33 -> 0 | U33: ='SCZ DCF'!Y33 -> 0 | ... AB33: ='SCZ DCF'!AF33 -> 0
B34: Annual Net Price | F34: =F27*F32/1000000 -> 0 | G34: =G27*G32/1000000 -> 0 | H34: =H27*H32/1000000 -> 0 | I34: =I27*I32/1000000 -> 0 | J34: =J27*J32/1000000 -> 0 | K34: =K27*K32/1000000 -> 0 | L34: =L32*(1-L35) -> 0 | M34: =M32*(1-M35) -> 17250 | N34: =N32*(1-N35) -> 17020 | O34: =O32*(1-O35) -> 16790 | P34: =P32*(1-P35) -> 16560 | Q34: =Q32*(1-Q35) -> 16330 | R34: =R32*(1-R35) -> 16100 | S34: =S32*(1-S35) -> 16100 | ... AB34: =AB32*(1-AB35) -> 16100
B35: Gross to net | F35: 0 | G35: 0 | H35: 0 | I35: 0 | J35: 0 | K35: 0 | L35: 0 | M35: ='SCZ DCF'!Q35 -> 0.25 | N35: ='SCZ DCF'!R35 -> 0.26 | O35: ='SCZ DCF'!S35 -> 0.27 | P35: ='SCZ DCF'!T35 -> 0.28 | Q35: ='SCZ DCF'!U35 -> 0.29 | R35: ='SCZ DCF'!V35 -> 0.3 | S35: ='SCZ DCF'!W35 -> 0.3 | T35: ='SCZ DCF'!X35 -> 0.3 | ... AB35: ='SCZ DCF'!AF35 -> 0.3
B36: US Revenue ($M) | F36: =F34*F35 -> 0 | G36: =G34*G35 -> 0 | H36: =H34*H35 -> 0 | I36: =I34*I35 -> 0 | J36: =J34*J35 -> 0 | K36: =K34*K35 -> 0 | L36: =L26*L34/1000000 -> 0 | M36: =M26*M34/1000000 -> 0 | N36: =N26*N34/1000000 -> 47.470395 | O36: =O26*O34/1000000 -> 188.25219 | P36: =P26*P34/1000000 -> 326.55308 | Q36: =Q26*Q34/1000000 -> 462.3253 | R36: =R26*R34/1000000 -> 595.52056 | S36: =S26*S34/1000000 -> 736.61313 | ... AB36: =AB26*AB34/1000000 -> 2070.5346
B37: Revenue - Alzheimer's with psychosis | F37: =F27*F34/1000000 -> 0 | G37: =G27*G34/1000000 -> 0 | H37: =H27*H34/1000000 -> 0 | I37: =I27*I34/1000000 -> 0 | J37: =J27*J34/1000000 -> 0 | K37: =K27*K34/1000000 -> 0 | L37: =L27*L34/1000000 -> 0 | M37: =M27*M34/1000000 -> 0 | ... AB37: =AB27*AB34/1000000 -> 2070.5346
B38: Revenue - Alzheimer's without psychosis | F38: =F29*F34/1000000 -> 0 | G38: =G29*G34/1000000 -> 0 | H38: =H29*H34/1000000 -> 0 | I38: =I29*I34/1000000 -> 0 | J38: =J29*J34/1000000 -> 0 | K38: =K29*K34/1000000 -> 0 | L38: =L29*L34/1000000 -> 0 | M38: =M29*M34/1000000 -> 0 | ... AB38: =AB29*AB34/1000000 -> 0
B39: Reported/Projected in Income Statement | F39: =IS!D12 -> 0 | G39: =IS!I12 -> 0 | H39: =IS!N12 -> 0 | I39: =IS!S12 -> 0 | J39: =IS!T12 -> 0 | K39: =IS!U12 -> 0 | L39: =IS!V12 -> 0 | M39: =IS!W12 -> 0
B41: ML-007C-MA for ADP - EU Market Model | F41: 2023 | G41: =F41+1 -> 2024 | H41: =G41+1 -> 2025 | I41: =H41+1 -> 2026 | J41: =I41+1 -> 2027 | K41: =J41+1 -> 2028 | L41: =K41+1 -> 2029 | M41: =L41+1 -> 2030 | N41: =M41+1 -> 2031 | ... AB41: =AA41+1 -> 2045
B42: EU Population (000s) | F42: 330000 | G42: =F42*(1+D43) -> 331650 | H42: =G42*(1+H$15) -> 333308.25 | I42: =H42*(1+I$15) -> 334974.79 | J42: =I42*(1+J$15) -> 336649.67 | K42: =J42*(1+K$15) -> 338332.91 | L42: =K42*(1+L$15) -> 340024.58 | M42: =L42*(1+M$15) -> 341724.7 | N42: =M42*(1+N$15) -> 343433.32 | O42: =N42*(1+O$15) -> 345150.49 | ... AB42: =AA42*(1+AB$15) -> 368270.81
B43: Annual Growth Rate | D43: 0.005 | G43: =D43 -> 0.005 | H43: =G43 -> 0.005 | I43: =H43 -> 0.005 | J43: =I43 -> 0.005 | K43: =J43 -> 0.005 | L43: =K43 -> 0.005 | M43: =L43 -> 0.005 | N43: =M43 -> 0.005 | O43: =N43 -> 0.005 | ... AB43: =AA43 -> 0.005
B45: Alzheimer's Disease Population | F45: =F42*F46 -> 6503.0069 | G45: =G42*G46 -> 6535.5219 | H45: =H42*H46 -> 6568.1996 | I45: =I42*I46 -> 6601.0406 | J45: =J42*J46 -> 6634.0458 | K45: =K42*K46 -> 6667.216 | L45: =L42*L46 -> 6700.5521 | M45: =M42*M46 -> 6734.0548 | ... AB45: =AB42*AB46 -> 7257.1746
B46: Prevalence | D46: =D18 -> 0.019706082 | F46: =D46 -> 0.019706082 | G46: =F46 -> 0.019706082 | H46: =G46 -> 0.019706082 | I46: =H46 -> 0.019706082 | J46: =I46 -> 0.019706082 | K46: =J46 -> 0.019706082 | L46: =K46 -> 0.019706082 | M46: =L46 -> 0.019706082 | N46: =M46 -> 0.019706082 | ... AB46: =AA46 -> 0.019706082
B48: (1) Alzheimer's with psychosis | F48: =(F45)*F49*1000 -> 1820841.9 | G48: =(G45)*G49*1000 -> 1829946.1 | H48: =(H45)*H49*1000 -> 1839095.9 | I48: =(I45)*I49*1000 -> 1848291.4 | J48: =(J45)*J49*1000 -> 1857532.8 | K48: =(K45)*K49*1000 -> 1866820.5 | L48: =(L45)*L49*1000 -> 1876154.6 | M48: =(M45)*M49*1000 -> 1885535.4 | ... AB48: =(AB45)*AB49*1000 -> 2032008.9
B49: Prevalence | D49: =0.7*0.4 -> 0.28 | F49: =D49 -> 0.28 | G49: =F49 -> 0.28 | H49: =G49 -> 0.28 | I49: =H49 -> 0.28 | J49: =I49 -> 0.28 | K49: =J49 -> 0.28 | L49: =K49 -> 0.28 | M49: =L49 -> 0.28 | N49: =M49 -> 0.28 | ... AB49: =AA49 -> 0.28
B51: (2) Alzheimer's without psychosis | F51: =(F45)*F52*1000 -> 3901804.1 | G51: =(G45)*G52*1000 -> 3921313.2 | H51: =(H45)*H52*1000 -> 3940919.7 | I51: =(I45)*I52*1000 -> 3960624.3 | J51: =(J45)*J52*1000 -> 3980427.5 | K51: =(K45)*K52*1000 -> 4000329.6 | L51: =(L45)*L52*1000 -> 4020331.2 | M51: =(M45)*M52*1000 -> 4040432.9 | ... AB51: =(AB45)*AB52*1000 -> 4354304.8
B52: Prevalence | D52: =D24 -> 0.6 | F52: =D52 -> 0.6 | G52: =D52 -> 0.6 | H52: =D52 -> 0.6 | I52: =H52 -> 0.6 | J52: =I52 -> 0.6 | K52: =J52 -> 0.6 | L52: =K52 -> 0.6 | M52: =L52 -> 0.6 | N52: =M52 -> 0.6 | O52: =N52 -> 0.6 | P52: =O52 -> 0.6 | ... AB52: =AA52 -> 0.6
B54: Total ML-007C-MA Patients Treated | F54: =F55+F57 -> 0 | G54: =G55+G57 -> 0 | H54: =H55+H57 -> 0 | I54: =I55+I57 -> 0 | J54: =J55+J57 -> 0 | K54: =K55+K57 -> 0 | L54: =L55+L57 -> 0 | M54: =M55+M57 -> 0 | ... AB54: =AB55+AB57 -> 0
B55: Alzheimer's with psychosis | F55: =F56*F48 -> 0 | G55: =G56*G48 -> 0 | H55: =H56*H48 -> 0 | I55: =I56*I48 -> 0 | J55: =J56*J48 -> 0 | K55: =K56*K48 -> 0 | L55: =L56*L48 -> 0 | M55: =M56*M48 -> 0 | ... AB55: =AB56*AB48 -> 0
B56: % penetration (overall subgroup) | F56: 0 | G56: 0 | H56: 0 | I56: 0 | J56: 0 | K56: 0 | L56: 0 | M56: 0 | N56: 0 | O56: 0 | P56: 0 | Q56: 0 | R56: 0 | S56: 0 | T56: 0 | U56: 0 | V56: 0 | W56: 0 | X56: 0 | Y56: 0 | Z56: 0 | AA56: 0 | AB56: 0
B57: Alzheimer's without psychosis | F57: =F58*F51 -> 0 | G57: =G58*G51 -> 0 | H57: =H58*H51 -> 0 | I57: =I58*I51 -> 0 | J57: =J58*J51 -> 0 | K57: =K58*K51 -> 0 | L57: =L58*L51 -> 0 | M57: =M58*M51 -> 0 | ... AB57: =AB58*AB51 -> 0
B58: % penetration (overall subgroup) | F58: 0 | G58: 0 | H58: 0 | I58: 0 | J58: 0 | K58: 0 | L58: 0 | M58: 0 | N58: 0 | O58: 0 | P58: 0 | Q58: 0 | R58: 0 | S58: 0 | T58: 0 | U58: 0 | V58: 0 | W58: 0 | X58: 0 | Y58: 0 | Z58: 0 | AA58: 0 | AB58: 0
B60: Annual Gross Price | D60: ='SCZ DCF'!C58 -> 23000 | F60: =F32*66% -> 0 | G60: =G32*66% -> 0 | H60: =H32*66% -> 0 | I60: =I32*66% -> 0 | J60: =J32*66% -> 0 | K60: =K32*66% -> 0 | L60: =L32*66% -> 0 | M60: =D60 -> 23000 | N60: =M60 -> 23000 | O60: =N60 -> 23000 | P60: =O60 -> 23000 | Q60: =P60 -> 23000 | R60: =Q60 -> 23000 | S60: =R60 -> 23000 | T60: =S60 -> 23000 | U60: =T60 -> 23000 | ... AB60: =AA60 -> 23000
B61: % Price increase | D61: ='SCZ DCF'!C59 -> 0 | M61: =L61 -> 0 | N61: =M61 -> 0 | O61: =N61 -> 0 | P61: =O61 -> 0 | Q61: =P61 -> 0 | R61: =Q61 -> 0 | S61: =R61 -> 0 | T61: =S61 -> 0 | ... AB61: =AA61 -> 0
B62: Annual Net Price | F62: 0 | G62: 0 | H62: 0 | I62: 0 | J62: 0 | K62: 0 | L62: 0 | M62: =M60*(1-M63) -> 23000 | N62: =N60*(1-N63) -> 23000 | O62: =O60*(1-O63) -> 23000 | P62: =P60*(1-P63) -> 23000 | Q62: =Q60*(1-Q63) -> 23000 | R62: =R60*(1-R63) -> 23000 | S62: =S60*(1-S63) -> 23000 | T62: =T60*(1-T63) -> 23000 | ... AB62: =AB60*(1-AB63) -> 23000
B63: Gross to net | D63: 0 | F63: 0 | G63: 0 | H63: 0 | I63: 0 | J63: 0 | K63: 0 | L63: 0 | M63: =$D63 -> 0 | N63: =$D63 -> 0 | O63: =$D63 -> 0 | P63: =$D63 -> 0 | Q63: =$D63 -> 0 | R63: =$D63 -> 0 | S63: =$D63 -> 0 | T63: =$D63 -> 0 | ... AB63: =$D63 -> 0
B64: EU5 Revenue ($M) | F64: =F54*F62/1000000 -> 0 | G64: =G54*G62/1000000 -> 0 | H64: =H54*H62/1000000 -> 0 | I64: =I54*I62/1000000 -> 0 | J64: =J54*J62/1000000 -> 0 | K64: =K54*K62/1000000 -> 0 | L64: =L54*L62/1000000 -> 0 | M64: =M54*M62/1000000 -> 0 | ... AB64: =AB54*AB62/1000000 -> 0
B65: Royalty Rate | D65: 0.25 | F65: 0 | G65: 0 | H65: 0 | I65: 0 | J65: 0 | K65: 0 | L65: 0 | M65: =L65 -> 0 | N65: =M65 -> 0 | O65: =N65 -> 0 | P65: =O65 -> 0 | Q65: =P65 -> 0 | R65: =Q65 -> 0 | S65: =R65 -> 0 | T65: =S65 -> 0 | ... AB65: =AA65 -> 0
B66: EU5 Royalties ($M) | F66: =F65*F64 -> 0 | G66: =G65*G64 -> 0 | H66: =H65*H64 -> 0 | I66: =I65*I64 -> 0 | J66: =J65*J64 -> 0 | K66: =K65*K64 -> 0 | L66: =L65*L64 -> 0 | M66: =M65*M64 -> 0 | ... AB66: =AB65*AB64 -> 0
B68: TRADITIONAL DCF VALUATION
B69: DCF | F69: 2023 | G69: =F69+1 -> 2024 | H69: =G69+1 -> 2025 | I69: =H69+1 -> 2026 | J69: =I69+1 -> 2027 | K69: =J69+1 -> 2028 | L69: =K69+1 -> 2029 | M69: =L69+1 -> 2030 | N69: =M69+1 -> 2031 | ... AB69: =AA69+1 -> 2045
B70: Revenue (in $M) | F70: =SUM(F71,F72) -> 0 | G70: =SUM(G71,G72) -> 0 | H70: =SUM(H71,H72) -> 0 | I70: =SUM(I71,I72) -> 0 | J70: =SUM(J71,J72) -> 0 | K70: =SUM(K71,K72) -> 0 | L70: =SUM(L71,L72) -> 0 | M70: =SUM(M71,M72) -> 0 | ... AB70: =SUM(AB71,AB72) -> 2070.5346
B71: US | F71: =F36 -> 0 | G71: =G36 -> 0 | H71: =H36 -> 0 | I71: =I36 -> 0 | J71: =J36 -> 0 | K71: =K36 -> 0 | L71: =L36 -> 0 | M71: =M36 -> 0 | ... AB71: =AB36 -> 2070.5346
B72: EU5 (Royalties) | F72: =F66 -> 0 | G72: =G66 -> 0 | H72: =H66 -> 0 | I72: =I66 -> 0 | J72: =J66 -> 0 | K72: =K66 -> 0 | L72: =L66 -> 0 | M72: =M66 -> 0 | ... AB72: =AB66 -> 0
B73: Milestone Payments | F73: 0 | G73: 0 | H73: 0 | I73: 0 | J73: 0 | K73: 0 | L73: 0 | M73: 0 | N73: 0 | O73: 0 | P73: 0 | Q73: 0 | R73: 0 | S73: 0 | T73: 0 | U73: 0 | V73: 0 | W73: 0 | X73: 0 | Y73: 0 | Z73: 0 | AA73: 0 | AB73: 0
B74: Royalties Owed | F74: =F70*F75 -> 0 | G74: =G70*G75 -> 0 | H74: =H70*H75 -> 0 | I74: =I70*I75 -> 0 | J74: =J70*J75 -> 0 | K74: =K70*K75 -> 0 | L74: =L70*L75 -> 0 | M74: =M70*M75 -> 0 | ... AB74: =AB70*AB75 -> 0
B75: % Royalty rate | D75: 0 | F75: 0 | G75: =F75 -> 0 | H75: =G75 -> 0 | I75: =H75 -> 0 | J75: =I75 -> 0 | K75: =J75 -> 0 | L75: =K75 -> 0 | M75: =L75 -> 0 | N75: =M75 -> 0 | ... AB75: =AA75 -> 0
B76: Cost of Goods sold | F76: =IF(F70=5, 0, F77*F70) -> 0 | G76: =IF(G70=5, 0, G77*G70) -> 0 | H76: =IF(H70=5, 0, H77*H70) -> 0 | I76: =IF(I70=5, 0, I77*I70) -> 0 | J76: =IF(J70=5, 0, J77*J70) -> 0 | K76: =IF(K70=5, 0, K77*K70) -> 0 | L76: =IF(L70=5, 0, L77*L70) -> 0 | M76: =IF(M70=5, 0, M77*M70) -> 0 | ... AB76: =IF(AB70=5, 0, AB77*AB70) -> 103.52673
B77: % of Revenue | D77: 0.05 | F77: =D77 -> 0.05 | G77: =F77 -> 0.05 | H77: =G77 -> 0.05 | I77: =H77 -> 0.05 | J77: =I77 -> 0.05 | K77: =J77 -> 0.05 | L77: =K77 -> 0.05 | M77: =L77 -> 0.05 | N77: =M77 -> 0.05 | ... AB77: =AA77 -> 0.05
B78: R&D | F78: =IS!D23*0.4 -> 19.87 | G78: =IS!I23*0.4 -> 27.4092 | H78: =IS!N23*0.4 -> 43.0908 | I78: =IS!S23*0.4 -> 72 | J78: =IS!T23*0.4 -> 108.76 | K78: =IS!U23*0.45 -> 137.33325 | L78: =IS!V23*0.45 -> 154.22074 | M78: =IS!W23*0.45 -> 173.2701 | N78: 50 | O78: 25 | P78: 15 | Q78: 10 | R78: 10 | S78: 10 | T78: 10 | U78: 10 | V78: 10 | W78: 10 | X78: 10 | Y78: 10 | Z78: 10 | AA78: 10 | AB78: 11
B79: % of Revenue | F79: =IFERROR(F78/F70,"-") -> - | G79: =IFERROR(G78/G70,"-") -> - | H79: =IFERROR(H78/H70,"-") -> - | I79: =IFERROR(I78/I70,"-") -> - | J79: =IFERROR(J78/J70,"-") -> - | K79: =IFERROR(K78/K70,"-") -> - | L79: =IFERROR(L78/L70,"-") -> - | M79: =IFERROR(M78/M70,"-") -> - | ... AB79: =IFERROR(AB78/AB70,"-") -> 0.0053126377
B80: SG&A | F80: =IS!D24*0.3 -> 2.2821 | G80: =IS!I24*0.3 -> 4.3269 | H80: =IS!N24*0.3 -> 5.0331 | I80: =IS!S24*0.3 -> 7.56 | J80: =IS!T24*0.3 -> 9.039 | K80: =IS!U24*0.3 -> 10.80885 | L80: =IS!V24*0.3 -> 12.926977 | M80: 50 | N80: 100 | O80: 100 | P80: 100 | Q80: 100 | R80: 100 | S80: 100 | T80: 100 | U80: 100 | V80: 100 | W80: 100 | X80: 100 | Y80: 100 | Z80: 100 | AA80: 100 | AB80: 100
B81: % of Revenue | F81: =IFERROR(F80/F70,"-") -> - | G81: =IFERROR(G80/G70,"-") -> - | H81: =IFERROR(H80/H70,"-") -> - | I81: =IFERROR(I80/I70,"-") -> - | J81: =IFERROR(J80/J70,"-") -> - | K81: =IFERROR(K80/K70,"-") -> - | L81: =IFERROR(L80/L70,"-") -> - | M81: =IFERROR(M80/M70,"-") -> - | ... AB81: =IFERROR(AB80/AB70,"-") -> 0.048296706
B82: Total EBIT | F82: =F70-F76-F78-F80-F73-F74 -> -22.1521 | G82: =G70-G76-G78-G80-G73-G74 -> -31.7361 | H82: =H70-H76-H78-H80-H73-H74 -> -48.1239 | I82: =I70-I76-I78-I80-I73-I74 -> -79.56 | J82: =J70-J76-J78-J80-J73-J74 -> -117.799 | K82: =K70-K76-K78-K80-K73-K74 -> -148.1421 | L82: =L70-L76-L78-L80-L73-L74 -> -167.14772 | M82: =M70-M76-M78-M80-M73-M74 -> -223.2701 | ... AB82: =AB70-AB76-AB78-AB80-AB73-AB74 -> 1856.0078
B83: Tax rate | F83: =IF(F82<0,0%,15%) -> 0 | G83: =IF(G82<0,0%,15%) -> 0 | H83: =IF(H82<0,0%,15%) -> 0 | I83: =IF(I82<0,0%,15%) -> 0 | J83: =IF(J82<0,0%,15%) -> 0 | K83: =IF(K82<0,0%,15%) -> 0 | L83: =IF(L82<0,0%,15%) -> 0 | M83: =IF(M82<0,0%,15%) -> 0 | ... AB83: =IF(AB82<0,0%,15%) -> 0.15
B84: Profit | F84: =F82*(1-F83) -> -22.1521 | G84: =G82*(1-G83) -> -31.7361 | H84: =H82*(1-H83) -> -48.1239 | I84: =I82*(1-I83) -> -79.56 | J84: =J82*(1-J83) -> -117.799 | K84: =K82*(1-K83) -> -148.1421 | L84: =L82*(1-L83) -> -167.14772 | M84: =M82*(1-M83) -> -223.2701 | ... AB84: =AB82*(1-AB83) -> 1577.6067
B86: D&A | F86: 0 | G86: 0 | H86: 0 | I86: 0 | J86: 0 | K86: 0 | L86: 0 | M86: 0 | N86: 0 | O86: 0 | P86: 0 | Q86: 0 | R86: 0 | S86: 0 | T86: 0 | U86: 0 | V86: 0 | W86: 0 | X86: 0 | Y86: 0 | Z86: 0 | AA86: 0 | AB86: 0
B87: Stock Option Expense | F87: =F80*20% -> 0.45642 | G87: =G80*20% -> 0.86538 | H87: =H80*20% -> 1.00662 | I87: =I80*20% -> 1.512 | J87: =J80*20% -> 1.8078 | K87: =K80*20% -> 2.16177 | L87: =L80*20% -> 2.5853955 | M87: =M80*20% -> 10 | ... AB87: =AB80*20% -> 20
B88: Capex | F88: 0 | G88: 0 | H88: 0 | I88: 0 | J88: 0 | K88: 0 | L88: 0 | M88: 0 | N88: 0 | O88: 0 | P88: 0 | Q88: 0 | R88: 0 | S88: 0 | T88: 0 | U88: 0 | V88: 0 | W88: 0 | X88: 0 | Y88: 0 | Z88: 0 | AA88: 0 | AB88: 0
B89: Working Capital | F89: 0 | G89: 0 | H89: 0 | I89: 0 | J89: 0 | K89: 0 | L89: 0 | M89: 0 | N89: 0 | O89: 0 | P89: 0 | Q89: 0 | R89: 0 | S89: 0 | T89: 0 | U89: 0 | V89: 0 | W89: 0 | X89: 0 | Y89: 0 | Z89: 0 | AA89: 0 | AB89: 0
B90: FCF (in $M) | G90: =G84+SUM(G86:G89) -> -30.87072 | H90: =H84+SUM(H86:H89) -> -47.11728 | I90: =I84+SUM(I86:I89) -> -78.048 | J90: =J84+SUM(J86:J89) -> -115.9912 | K90: =K84+SUM(K86:K89) -> -145.98033 | L90: =L84+SUM(L86:L89) -> -164.56232 | M90: =M84+SUM(M86:M89) -> -213.2701 | N90: =N84+SUM(N86:N89) -> -84.903125 | ... AB90: =AB84+SUM(AB86:AB89) -> 1597.6067 | AC90: =AB90*(1+D96)/(D97-D96) -> 3524.1323
B92: Discount period | D92: 2026 | I92: =I69-$D$92 -> 0 | J92: =J69-$D$92 -> 1 | K92: =K69-$D$92 -> 2 | L92: =L69-$D$92 -> 3 | M92: =M69-$D$92 -> 4 | N92: =N69-$D$92 -> 5 | O92: =O69-$D$92 -> 6 | P92: =P69-$D$92 -> 7 | ... AB92: =AB69-$D$92 -> 19 | AC92: =AB92 -> 19
B93: NPV | I93: =I90/(1+$D$97)^I92 -> -78.048 | J93: =J90/(1+$D$97)^J92 -> -106.41394 | K93: =K90/(1+$D$97)^K92 -> -122.86872 | L93: =L90/(1+$D$97)^L92 -> -127.0723 | M93: =M90/(1+$D$97)^M92 -> -151.08591 | N93: =N90/(1+$D$97)^N92 -> -55.181206 | O93: =O90/(1+$D$97)^O92 -> 39.212712 | P93: =P90/(1+$D$97)^P92 -> 101.71643 | ... AC93: =AC90/(1+$D$97)^AC92 -> 685.40733
B95: NPV Sum (in $M) | D95: =IF(D92=I69,SUM(F93:AC93),(SUM(F93:AC93))) -> 3386.7065 | I95: $/share | K95: Downside | L95: Base Case | M95: Upside
B96: Terminal Growth (%) | D96: -0.25 | I96: ML-007C-MA NPV ($M) | K96: =$D$95*K97 -> 0 | L96: =$D$95*L97 -> 508.00597 | M96: =$D$95*M97 -> 1016.0119
B97: Discount Rate | D97: 0.09 | I97: Assumed PoS | K97: 0 | L97: =D99 -> 0.15 | M97: 0.3
B98: Share count (in M) | D98: =SOTP!D38 -> 53.187829 | I98: ML-007C-MA ($/share) | K98: =IFERROR($L$98/$L$97*K97,0) -> 0 | L98: =D101 -> 9.5511695 | M98: =D95*M97/D98 -> 19.102339
B99: Probability of Success | D99: 0.15
B100: Probability adjusted NPV | D100: =D95*D99 -> 508.00597
B101: Price Per Share | D101: =D100/D98 -> 9.5511695
I103: Peak Sales Calculator | K103: Downside | L103: Base Case | M103: Upside
I104: Peak sales ($M) | K104: 500 | L104: =MAX(C70:AC70) -> 2070.5346 | M104: 2000
I105: Multiple | K105: 2 | L105: 2 | M105: 2.5
I106: Valuation | K106: =K104*K105 -> 1000 | L106: =L104*L105 -> 4141.0691 | M106: =M104*M105 -> 5000
I107: Assumed PoS | K107: =K97 -> 0 | L107: =L97 -> 0.15 | M107: =M97 -> 0.3
I108: $/Share (adjusted) | K108: =K106/$D98*K107 -> 0 | L108: =L106/$D98*L107 -> 11.678619 | M108: =M106/$D98*M107 -> 28.201941

Sheet ASD DCF
B1: ML-004 Model Analysis for Autism Spectrum Disorder (ASD): Change Assumptions in Blue
B3: ML-004 Sales Summary ($M) | E3: 2018 | F3: =E3+1 -> 2019 | G3: =F3+1 -> 2020 | H3: =G3+1 -> 2021 | I3: =H3+1 -> 2022 | J3: =I3+1 -> 2023 | K3: =J3+1 -> 2024 | L3: =K3+1 -> 2025 | M3: =L3+1 -> 2026 | ... AC3: =AB3+1 -> 2042
B4: US | E4: =E36 -> 0 | F4: =F36 -> 0 | G4: =G36 -> 0 | H4: =H36 -> 0 | I4: =I36 -> 0 | J4: =J36 -> 0 | K4: =K36 -> 0 | L4: =L36 -> 0 | ... AC4: =AC36 -> 890.89801
B5: EU5 (Before royalties) | E5: =E62 -> 0 | F5: =F62 -> 0 | G5: =G62 -> 0 | H5: =H62 -> 0 | I5: =I62 -> 0 | J5: =J62 -> 0 | K5: =K62 -> 0 | L5: =L62 -> 0 | ... AC5: =AC62 -> 0
B6: Total Sales ($M) | E6: =E4+E5 -> 0 | F6: =F4+F5 -> 0 | G6: =G4+G5 -> 0 | H6: =H4+H5 -> 0 | I6: =I4+I5 -> 0 | J6: =J4+J5 -> 0 | K6: =K4+K5 -> 0 | L6: =L4+L5 -> 0 | ... AC6: =AC4+AC5 -> 890.89801
B8: ML-004 Patient Summary | E8: 2018 | F8: =E8+1 -> 2019 | G8: =F8+1 -> 2020 | H8: =G8+1 -> 2021 | I8: =H8+1 -> 2022 | J8: =I8+1 -> 2023 | K8: =J8+1 -> 2024 | L8: =K8+1 -> 2025 | M8: =L8+1 -> 2026 | ... AC8: =AB8+1 -> 2042
B9: US | E9: =E29 -> 0 | F9: =F29 -> 0 | G9: =G29 -> 0 | H9: =H29 -> 0 | I9: =I29 -> 0 | J9: =J29 -> 0 | K9: =K29 -> 0 | L9: =L29 -> 0 | ... AC9: =AC29 -> 62519.158
B10: EU5 | E10: =E55 -> 0 | F10: =F55 -> 0 | G10: =G55 -> 0 | H10: =H55 -> 0 | I10: =I55 -> 0 | J10: =J55 -> 0 | K10: =K55 -> 0 | L10: =L55 -> 0 | ... AC10: =AC55 -> 0
B11: Total Patients | E11: =E9+E10 -> 0 | F11: =F9+F10 -> 0 | G11: =G9+G10 -> 0 | H11: =H9+H10 -> 0 | I11: =I9+I10 -> 0 | J11: =J9+J10 -> 0 | K11: =K9+K10 -> 0 | L11: =L9+L10 -> 0 | ... AC11: =AC9+AC10 -> 62519.158
B13: ML-004 for Autism Spectrum Disorder - US Market Model | E13: 2018 | F13: =E13+1 -> 2019 | G13: =F13+1 -> 2020 | H13: =G13+1 -> 2021 | I13: =H13+1 -> 2022 | J13: =I13+1 -> 2023 | K13: =J13+1 -> 2024 | L13: =K13+1 -> 2025 | M13: =L13+1 -> 2026 | ... AC13: =AB13+1 -> 2042
B14: US Population (000s) | E14: =327.2*1000 -> 327200 | F14: =E14*(1+F$15) -> 329654 | G14: =F14*(1+G$15) -> 332126.41 | H14: =G14*(1+H$15) -> 334617.35 | I14: =H14*(1+I$15) -> 337126.98 | J14: =I14*(1+J$15) -> 339655.44 | K14: =J14*(1+K$15) -> 342202.85 | L14: =K14*(1+L$15) -> 344769.37 | M14: =L14*(1+M$15) -> 347355.14 | ... AC14: =AB14*(1+AC$15) -> 391466.51
B15: Annual Growth Rate | C15: 0.0075 | E15: =C15 -> 0.0075 | F15: =E15 -> 0.0075 | G15: =F15 -> 0.0075 | H15: =G15 -> 0.0075 | I15: =H15 -> 0.0075 | J15: =I15 -> 0.0075 | K15: =J15 -> 0.0075 | L15: =K15 -> 0.0075 | M15: =L15 -> 0.0075 | ... AC15: =AB15 -> 0.0075
B17: Total ASD Prevalence (000s) | E17: =E14*$C18 -> 7927.8566 | F17: =F14*$C18 -> 7987.3156 | G17: =G14*$C18 -> 8047.2204 | H17: =H14*$C18 -> 8107.5746 | I17: =I14*$C18 -> 8168.3814 | J17: =J14*$C18 -> 8229.6442 | K17: =K14*$C18 -> 8291.3666 | L17: =L14*$C18 -> 8353.5518 | ... AC17: =AC14*$C18 -> 9484.9949
B18: Prevalence | C18: =1/31*0.2+1/45*0.8 -> 0.024229391 | E18: =C18 -> 0.024229391 | F18: =C18 -> 0.024229391 | G18: =F18 -> 0.024229391 | H18: =G18 -> 0.024229391 | I18: =H18 -> 0.024229391 | J18: =I18 -> 0.024229391 | K18: =J18 -> 0.024229391 | L18: =K18 -> 0.024229391 | M18: =L18 -> 0.024229391 | N18: =M18 -> 0.024229391 | ... AC18: =AB18 -> 0.024229391
B20: Total Diagnosed ASD Patients (000s) | E20: =E17*E21 -> 7135.071 | F20: =F17*F21 -> 7188.584 | G20: =G17*G21 -> 7242.4984 | H20: =H17*H21 -> 7296.8171 | I20: =I17*I21 -> 7351.5432 | J20: =J17*J21 -> 7406.6798 | K20: =K17*K21 -> 7462.2299 | L20: =L17*L21 -> 7518.1966 | ... AC20: =AC17*AC21 -> 8536.4954
B21: Diagnosis Rate | C21: 0.9 | E21: =C21 -> 0.9 | F21: =E21 -> 0.9 | G21: =F21 -> 0.9 | H21: =G21 -> 0.9 | I21: =H21 -> 0.9 | J21: =I21 -> 0.9 | K21: =J21 -> 0.9 | L21: =K21 -> 0.9 | M21: =L21 -> 0.9 | ... AC21: =AB21 -> 0.9
B23: Moderate to Severe (000s) | E23: =E20*(1-E24) -> 3317.808 | F23: =F20*(1-F24) -> 3342.6916 | G23: =G20*(1-G24) -> 3367.7617 | H23: =H20*(1-H24) -> 3393.02 | I23: =I20*(1-I24) -> 3418.4676 | J23: =J20*(1-J24) -> 3444.1061 | K23: =K20*(1-K24) -> 3469.9369 | L23: =L20*(1-L24) -> 3495.9614 | ... AC23: =AC20*(1-AC24) -> 3969.4704
B24: % Not requiring treatment at all | C24: =1-AVERAGE(25%,68%) -> 0.535 | E24: =C24 -> 0.535 | F24: =C24 -> 0.535 | G24: =F24 -> 0.535 | H24: =G24 -> 0.535 | I24: =H24 -> 0.535 | J24: =I24 -> 0.535 | K24: =J24 -> 0.535 | L24: =K24 -> 0.535 | M24: =L24 -> 0.535 | N24: =M24 -> 0.535 | ... AC24: =AB24 -> 0.535
B26: Tx Discontinuation Rate | E26: =E23*(E27)*1000 -> 1658904 | F26: =F23*(F27)*1000 -> 1671345.8 | G26: =G23*(G27)*1000 -> 1683880.9 | H26: =H23*(H27)*1000 -> 1696510 | I26: =I23*(I27)*1000 -> 1709233.8 | J26: =J23*(J27)*1000 -> 1722053.1 | K26: =K23*(K27)*1000 -> 1734968.5 | L26: =L23*(L27)*1000 -> 1747980.7 | ... AC26: =AC23*(AC27)*1000 -> 1984735.2
B27: Prevalence | C27: 0.5 | E27: =C27 -> 0.5 | F27: =C27 -> 0.5 | G27: =F27 -> 0.5 | H27: =G27 -> 0.5 | I27: =H27 -> 0.5 | J27: =I27 -> 0.5 | K27: =J27 -> 0.5 | L27: =K27 -> 0.5 | M27: =L27 -> 0.5 | N27: =M27 -> 0.5 | ... AC27: =AB27 -> 0.5
B29: Total ML-004 Patients Treated | E29: =E30*E26 -> 0 | F29: =F30*F26 -> 0 | G29: =G30*G26 -> 0 | H29: =H30*H26 -> 0 | I29: =I30*I26 -> 0 | J29: =J30*J26 -> 0 | K29: =K30*K26 -> 0 | L29: =L30*L26 -> 0 | ... AC29: =AC30*AC26 -> 62519.158
B30: % penetration | E30: =C30 -> 0 | F30: 0 | G30: 0 | H30: 0 | I30: 0 | J30: 0 | K30: 0 | L30: 0 | M30: 0 | N30: 0 | O30: 0 | P30: 0 | Q30: 0 | R30: 0 | S30: 0.0015 | T30: =S30+0.3% -> 0.0045 | U30: =T30+0.3% -> 0.0075 | V30: =U30+0.3% -> 0.0105 | W30: =V30+0.3% -> 0.0135 | X30: =W30+0.3% -> 0.0165 | Y30: =X30+0.3% -> 0.0195 | Z30: =Y30+0.3% -> 0.0225 | AA30: =Z30+0.3% -> 0.0255 | ... AC30: =AB30+0.3% -> 0.0315
B32: Annual Gross Price | C32: 19000 | E32: 0 | F32: 0 | G32: 0 | H32: 0 | I32: 0 | J32: 0 | K32: 0 | L32: 0 | M32: 0 | N32: 0 | O32: 0 | P32: 0 | Q32: 0 | R32: 0 | S32: =C32 -> 19000 | T32: =S32*(1+T33) -> 19000 | U32: =T32*(1+U33) -> 19000 | V32: =U32*(1+V33) -> 19000 | W32: =V32*(1+W33) -> 19000 | X32: =W32*(1+X33) -> 19000 | Y32: =X32*(1+Y33) -> 19000 | Z32: =Y32*(1+Z33) -> 19000 | AA32: =Z32*(1+AA33) -> 19000 | ... AC32: =AB32*(1+AC33) -> 19000
B33: % Price increase | S33: 0 | T33: 0 | U33: 0 | V33: 0 | W33: 0 | X33: 0 | Y33: 0 | Z33: 0 | AA33: 0 | AB33: 0 | AC33: 0
B34: Annual Net Price | E34: 0 | F34: =F32*(1-F35) -> 0 | G34: =G32*(1-G35) -> 0 | H34: =H32*(1-H35) -> 0 | I34: =I32*(1-I35) -> 0 | J34: =J32*(1-J35) -> 0 | K34: =K32*(1-K35) -> 0 | L34: =L32*(1-L35) -> 0 | M34: =M32*(1-M35) -> 0 | ... AC34: =AC32*(1-AC35) -> 14250
B35: Gross to net | C35: 0.25 | S35: =C35 -> 0.25 | T35: =S35 -> 0.25 | U35: =T35 -> 0.25 | V35: =U35 -> 0.25 | W35: =V35 -> 0.25 | X35: =W35 -> 0.25 | Y35: =X35 -> 0.25 | Z35: =Y35 -> 0.25 | AA35: =Z35 -> 0.25 | ... AC35: =AB35 -> 0.25
B36: US Revenue ($M) | E36: =E29*E34/1000000 -> 0 | F36: =F29*F34/1000000 -> 0 | G36: =G29*G34/1000000 -> 0 | H36: =H29*H34/1000000 -> 0 | I36: =I29*I34/1000000 -> 0 | J36: =J29*J34/1000000 -> 0 | K36: =K29*K34/1000000 -> 0 | L36: =L29*L34/1000000 -> 0 | ... AC36: =AC29*AC34/1000000 -> 890.89801
B37: Reported/Projected in Income Statement | J37: =IS!D13 -> 0 | K37: =IS!I13 -> 0 | L37: =IS!N13 -> 0 | M37: =IS!S13 -> 0 | N37: =IS!T13 -> 0 | O37: =IS!U13 -> 0 | P37: =IS!V13 -> 0 | Q37: =IS!W13 -> 0
B39: ML-004 for Autism Spectrum Disorder - EU Market Model | E39: 2018 | F39: =E39+1 -> 2019 | G39: =F39+1 -> 2020 | H39: =G39+1 -> 2021 | I39: =H39+1 -> 2022 | J39: =I39+1 -> 2023 | K39: =J39+1 -> 2024 | L39: =K39+1 -> 2025 | M39: =L39+1 -> 2026 | ... AC39: =AB39+1 -> 2042
B40: EU5 Population (000s) | E40: 320549.95 | F40: =E40*(1+F$15) -> 322954.07 | G40: =F40*(1+G$15) -> 325376.23 | H40: =G40*(1+H$15) -> 327816.55 | I40: =H40*(1+I$15) -> 330275.18 | J40: =I40*(1+J$15) -> 332752.24 | K40: =J40*(1+K$15) -> 335247.88 | L40: =K40*(1+L$15) -> 337762.24 | M40: =L40*(1+M$15) -> 340295.46 | ... AC40: =AB40*(1+AC$15) -> 383510.3
B41: Annual Growth Rate | C41: 0.001 | E41: =C41 -> 0.001 | F41: =E41 -> 0.001 | G41: =F41 -> 0.001 | H41: =G41 -> 0.001 | I41: =H41 -> 0.001 | J41: =I41 -> 0.001 | K41: =J41 -> 0.001 | L41: =K41 -> 0.001 | M41: =L41 -> 0.001 | ... AC41: =AB41 -> 0.001
B43: Total ASD Adult Prevalence (000s) | E43: =E40*$C44 -> 7766.73 | F43: =F40*$C44 -> 7824.9804 | G43: =G40*$C44 -> 7883.6678 | H43: =H40*$C44 -> 7942.7953 | I43: =I40*$C44 -> 8002.3663 | J43: =J40*$C44 -> 8062.384 | K43: =K40*$C44 -> 8122.8519 | L43: =L40*$C44 -> 8183.7733 | ... AC43: =AC40*$C44 -> 9292.2208
B44: Prevalence | C44: =C18 -> 0.024229391 | E44: =C44 -> 0.024229391 | F44: =C44 -> 0.024229391 | G44: =F44 -> 0.024229391 | H44: =G44 -> 0.024229391 | I44: =H44 -> 0.024229391 | J44: =I44 -> 0.024229391 | K44: =J44 -> 0.024229391 | L44: =K44 -> 0.024229391 | M44: =L44 -> 0.024229391 | N44: =M44 -> 0.024229391 | ... AC44: =AB44 -> 0.024229391
B46: Total Diagnosed ASD Patients (000s) | E46: =E43*E47 -> 6990.057 | F46: =F43*F47 -> 7042.4824 | G46: =G43*G47 -> 7095.301 | H46: =H43*H47 -> 7148.5158 | I46: =I43*I47 -> 7202.1296 | J46: =J43*J47 -> 7256.1456 | K46: =K43*K47 -> 7310.5667 | L46: =L43*L47 -> 7365.3959 | ... AC46: =AC43*AC47 -> 8362.9987
B47: Diagnosis Rate | C47: =C21 -> 0.9 | E47: =C47 -> 0.9 | F47: =E47 -> 0.9 | G47: =F47 -> 0.9 | H47: =G47 -> 0.9 | I47: =H47 -> 0.9 | J47: =I47 -> 0.9 | K47: =J47 -> 0.9 | L47: =K47 -> 0.9 | M47: =L47 -> 0.9 | ... AC47: =AB47 -> 0.9
B49: Patients Requiring Treatment (000s) | E49: =E46*(1-E50) -> 3250.3765 | F49: =F46*(1-F50) -> 3274.7543 | G49: =G46*(1-G50) -> 3299.315 | H49: =H46*(1-H50) -> 3324.0598 | I49: =I46*(1-I50) -> 3348.9903 | J49: =J46*(1-J50) -> 3374.1077 | K49: =K46*(1-K50) -> 3399.4135 | L49: =L46*(1-L50) -> 3424.9091 | ... AC49: =AC46*(1-AC50) -> 3888.7944
B50: % Not requiring treatment at all | C50: =C24 -> 0.535 | E50: =C50 -> 0.535 | F50: =C50 -> 0.535 | G50: =F50 -> 0.535 | H50: =G50 -> 0.535 | I50: =H50 -> 0.535 | J50: =I50 -> 0.535 | K50: =J50 -> 0.535 | L50: =K50 -> 0.535 | M50: =L50 -> 0.535 | N50: =M50 -> 0.535 | ... AC50: =AB50 -> 0.535
B52: Discontinuation Rate | E52: =E49*(E53)*1000 -> 1625188.2 | F52: =F49*(F53)*1000 -> 1637377.2 | G52: =G49*(G53)*1000 -> 1649657.5 | H52: =H49*(H53)*1000 -> 1662029.9 | I52: =I49*(I53)*1000 -> 1674495.1 | J52: =J49*(J53)*1000 -> 1687053.9 | K52: =K49*(K53)*1000 -> 1699706.8 | L52: =L49*(L53)*1000 -> 1712454.6 | ... AC52: =AC49*(AC53)*1000 -> 1944397.2
B53: Prevalence | C53: =C27 -> 0.5 | E53: =C53 -> 0.5 | F53: =C53 -> 0.5 | G53: =F53 -> 0.5 | H53: =G53 -> 0.5 | I53: =H53 -> 0.5 | J53: =I53 -> 0.5 | K53: =J53 -> 0.5 | L53: =K53 -> 0.5 | M53: =L53 -> 0.5 | N53: =M53 -> 0.5 | ... AC53: =AB53 -> 0.5
B55: Total ML-004 Patients Treated | E55: =E56*E52 -> 0 | F55: =F56*F52 -> 0 | G55: =G56*G52 -> 0 | H55: =H56*H52 -> 0 | I55: =I56*I52 -> 0 | J55: =J56*J52 -> 0 | K55: =K56*K52 -> 0 | L55: =L56*L52 -> 0 | ... AC55: =AC56*AC52 -> 0
B56: % penetration | E56: =C56 -> 0 | F56: =E56 -> 0 | G56: 0 | H56: 0 | I56: =H56 -> 0 | J56: 0 | K56: 0 | L56: 0 | M56: 0 | N56: 0 | O56: 0 | P56: 0 | Q56: 0 | R56: 0 | S56: 0 | T56: 0 | U56: 0 | V56: 0 | W56: 0 | X56: 0 | Y56: 0 | Z56: 0 | AA56: 0 | AB56: 0 | AC56: 0
B58: Annual Gross Price | C58: =C32*66% -> 12540 | E58: 0 | F58: 0 | G58: 0 | H58: 0 | I58: 0 | J58: 0 | K58: 0 | L58: 0 | M58: 0 | N58: 0 | O58: 0 | P58: 0 | Q58: 0 | R58: 0 | S58: =C58 -> 12540 | T58: =S58*(1+T59) -> 12540 | U58: =T58*(1+U59) -> 12540 | V58: =U58*(1+V59) -> 12540 | W58: =V58*(1+W59) -> 12540 | X58: =W58*(1+X59) -> 12540 | Y58: =X58*(1+Y59) -> 12540 | Z58: =Y58*(1+Z59) -> 12540 | AA58: =Z58*(1+AA59) -> 12540 | ... AC58: =AB58*(1+AC59) -> 12540
B59: % Price increase | C59: 0 | S59: =$C59 -> 0 | T59: =$C59 -> 0 | U59: =$C59 -> 0 | V59: =$C59 -> 0 | W59: =$C59 -> 0 | X59: =$C59 -> 0 | Y59: =$C59 -> 0 | Z59: =$C59 -> 0 | ... AC59: =$C59 -> 0
B60: Annual Net Price | E60: 0 | F60: 0 | G60: 0 | H60: 0 | I60: 0 | J60: =J58*(1-J61) -> 0 | K60: =K58*(1-K61) -> 0 | L60: =L58*(1-L61) -> 0 | M60: =M58*(1-M61) -> 0 | N60: =N58*(1-N61) -> 0 | O60: =O58*(1-O61) -> 0 | P60: =P58*(1-P61) -> 0 | Q60: =Q58*(1-Q61) -> 0 | ... AC60: =AC58*(1-AC61) -> 12540
B61: Gross to net | C61: 0 | E61: 0 | F61: 0 | G61: 0 | H61: 0 | I61: 0 | J61: 0 | K61: 0 | L61: 0 | M61: 0 | N61: 0 | O61: 0 | P61: 0 | Q61: 0 | R61: 0 | S61: =C61 -> 0 | T61: =S61 -> 0 | U61: =T61 -> 0 | V61: =U61 -> 0 | W61: =V61 -> 0 | X61: =W61 -> 0 | Y61: =X61 -> 0 | Z61: =Y61 -> 0 | AA61: =Z61 -> 0 | ... AC61: =AB61 -> 0
B62: EU5 Revenue ($M) | E62: =E55*E60/1000000 -> 0 | F62: =F55*F60/1000000 -> 0 | G62: =G55*G60/1000000 -> 0 | H62: =H55*H60/1000000 -> 0 | I62: =I55*I60/1000000 -> 0 | J62: =J55*J60/1000000 -> 0 | K62: =K55*K60/1000000 -> 0 | L62: =L55*L60/1000000 -> 0 | ... AC62: =AC55*AC60/1000000 -> 0
B63: Royalty Rate | C63: 0.25 | E63: 0 | F63: 0 | G63: 0 | H63: 0 | I63: 0 | J63: 0 | K63: 0 | L63: 0 | M63: 0 | N63: 0 | O63: 0 | P63: 0 | Q63: 0 | R63: 0 | S63: =$C63 -> 0.25 | T63: =$C63 -> 0.25 | U63: =$C63 -> 0.25 | V63: =$C63 -> 0.25 | W63: =$C63 -> 0.25 | X63: =$C63 -> 0.25 | Y63: =$C63 -> 0.25 | Z63: =$C63 -> 0.25 | ... AC63: =$C63 -> 0.25
B64: EU5 Royalties ($M) | E64: =E62*E63 -> 0 | F64: =F62*F63 -> 0 | G64: =G62*G63 -> 0 | H64: =H62*H63 -> 0 | I64: =I62*I63 -> 0 | J64: =J62*J63 -> 0 | K64: =K62*K63 -> 0 | L64: =L62*L63 -> 0 | ... AC64: =AC62*AC63 -> 0
B65: Reported/Projected in Income Statement | E65: 0 | F65: 0 | G65: 0 | H65: 0 | I65: 0
B67: TRADITIONAL DCF VALUATION
B68: DCF | E68: 2018 | F68: =E68+1 -> 2019 | G68: =F68+1 -> 2020 | H68: =G68+1 -> 2021 | I68: =H68+1 -> 2022 | J68: =I68+1 -> 2023 | K68: =J68+1 -> 2024 | L68: =K68+1 -> 2025 | M68: =L68+1 -> 2026 | ... AC68: =AB68+1 -> 2042
B69: Revenue (in $M) | E69: =SUM(E70,E71) -> 0 | F69: =SUM(F70,F71) -> 0 | G69: =SUM(G70,G71) -> 0 | H69: =SUM(H70,H71) -> 0 | I69: =SUM(I70,I71) -> 0 | J69: =SUM(J70,J71) -> 0 | K69: =SUM(K70,K71) -> 0 | L69: =SUM(L70,L71) -> 0 | ... AC69: =SUM(AC70,AC71) -> 890.89801
B70: US | E70: =E36 -> 0 | F70: =F36 -> 0 | G70: =G36 -> 0 | H70: =H36 -> 0 | I70: =I36 -> 0 | J70: =J36 -> 0 | K70: =K36 -> 0 | L70: =L36 -> 0 | ... AC70: =AC36 -> 890.89801
B71: EU5 | E71: =E64 -> 0 | F71: =F64 -> 0 | G71: =G64 -> 0 | H71: =H64 -> 0 | I71: =I64 -> 0 | J71: =J64 -> 0 | K71: =K64 -> 0 | L71: =L64 -> 0 | ... AC71: =AC64 -> 0
B72: Milestone Payments | E72: 0 | F72: 0 | G72: 0 | H72: 0 | I72: 0 | J72: 0 | K72: 0 | L72: 0 | M72: 0 | N72: 0 | O72: 0 | P72: 0 | Q72: 0 | R72: 0 | S72: 0 | T72: 0 | U72: 0 | V72: 0 | W72: 0 | X72: 0 | Y72: 0 | Z72: 0 | AA72: 0 | AB72: 0 | AC72: 0
B73: Royalties | C73: 0 | E73: =E69*$C73 -> 0 | F73: =F69*$C73 -> 0 | G73: =G69*$C73 -> 0 | H73: =H69*$C73 -> 0 | I73: =I69*$C73 -> 0 | J73: =J69*$C73 -> 0 | K73: =K69*$C73 -> 0 | L73: =L69*$C73 -> 0 | ... AC73: =AC69*$C73 -> 0
B74: Cost of Goods sold | E74: 0 | F74: =F69*F75 -> 0 | G74: =G69*G75 -> 0 | H74: =H69*H75 -> 0 | I74: =I69*I75 -> 0 | J74: =J69*J75 -> 0 | K74: =K69*K75 -> 0 | L74: =L69*L75 -> 0 | M74: =M69*M75 -> 0 | ... AC74: =AC69*AC75 -> 44.5449
B75: % of Revenue | E75: =IF(E69=0,0,5%) -> 0 | F75: =IF(F69=0,0,5%) -> 0 | G75: =IF(G69=0,0,5%) -> 0 | H75: =IF(H69=0,0,5%) -> 0 | I75: =IF(I69=0,0,5%) -> 0 | J75: =IF(J69=0,0,5%) -> 0 | K75: =IF(K69=0,0,5%) -> 0 | L75: =IF(L69=0,0,5%) -> 0 | ... AC75: =IF(AC69=0,0,5%) -> 0.05
B76: R&D | E76: 0 | F76: 0 | G76: 0 | H76: 0 | I76: 0 | J76: =IS!D23*0.15 -> 7.45125 | K76: =IS!I23*0.15 -> 10.27845 | L76: =IS!N23*0.15 -> 16.15905 | M76: =IS!S23*0.15 -> 27 | N76: =IS!T23*0.15 -> 40.785 | O76: =IS!U23*0.15 -> 45.77775 | P76: =IS!V23*0.15 -> 51.406913 | Q76: 35 | R76: 35 | S76: 20 | T76: 10 | U76: 10 | V76: 10 | W76: 10 | X76: 10 | Y76: 10 | Z76: 10 | AA76: 10 | AB76: 10 | AC76: 10
B77: % of Revenue | E77: =IFERROR(E76/E69,"-") -> - | F77: =IFERROR(F76/F69,"-") -> - | G77: =IFERROR(G76/G69,"-") -> - | H77: =IFERROR(H76/H69,"-") -> - | I77: =IFERROR(I76/I69,"-") -> - | P77: =IFERROR(P76/P69,"-") -> - | Q77: =IFERROR(Q76/Q69,"-") -> - | R77: =IFERROR(R76/R69,"-") -> - | S77: =IFERROR(S76/S69,"-") -> 0.50800952 | T77: =IFERROR(T76/T69,"-") -> 0.084037968 | U77: =IFERROR(U76/U69,"-") -> 0.050047425 | V77: =IFERROR(V76/V69,"-") -> 0.035482046 | W77: =IFERROR(W76/W69,"-") -> 0.027391709 | ... AC77: =IFERROR(AC76/AC69,"-") -> 0.011224629
B78: SG&A | E78: 0 | F78: 0 | G78: 0 | H78: 0 | I78: 0 | J78: =IS!D24*0.15 -> 1.14105 | K78: =IS!I24*0.15 -> 2.16345 | L78: =IS!N24*0.15 -> 2.51655 | M78: =IS!S24*0.15 -> 3.78 | N78: =IS!T24*0.15 -> 4.5195 | O78: =IS!U24*0.15 -> 5.404425 | P78: =IS!V24*0.15 -> 6.4634887 | Q78: 20 | R78: 50 | S78: 100 | T78: 100 | U78: 100 | V78: 100 | W78: 100 | X78: 100 | Y78: 100 | Z78: 100 | AA78: 100 | AB78: 100 | AC78: 100
B79: % of Revenue | E79: =IFERROR(E78/E69,"-") -> - | F79: =IFERROR(F78/F69,"-") -> - | G79: =IFERROR(G78/G69,"-") -> - | H79: =IFERROR(H78/H69,"-") -> - | I79: =IFERROR(I78/I69,"-") -> - | P79: =IFERROR(P78/P69,"-") -> - | Q79: =IFERROR(Q78/Q69,"-") -> - | R79: =IFERROR(R78/R69,"-") -> - | S79: =IFERROR(S78/S69,"-") -> 2.5400476 | T79: =IFERROR(T78/T69,"-") -> 0.84037968 | U79: =IFERROR(U78/U69,"-") -> 0.50047425 | V79: =IFERROR(V78/V69,"-") -> 0.35482046 | W79: =IFERROR(W78/W69,"-") -> 0.27391709 | ... AC79: =IFERROR(AC78/AC69,"-") -> 0.11224629
B80: Total EBIT | E80: =E69-E74-E76-E78-E72 -> 0 | F80: =F69-F74-F76-F78-F72 -> 0 | G80: =G69-G74-G76-G78-G72 -> 0 | H80: =H69-H74-H76-H78-H72 -> 0 | I80: =I69-I74-I76-I78-I72 -> 0 | J80: =J69-J74-J76-J78-J72 -> -8.5923 | K80: =K69-K74-K76-K78-K72 -> -12.4419 | L80: =L69-L74-L76-L78-L72 -> -18.6756 | ... AC80: =AC69-AC74-AC76-AC78-AC72 -> 736.35311
B81: Tax rate | E81: =IF(E80>0, 15%, 0%) -> 0 | F81: =IF(F80>0, 15%, 0%) -> 0 | G81: =IF(G80>0, 15%, 0%) -> 0 | H81: =IF(H80>0, 15%, 0%) -> 0 | I81: =IF(I80>0, 15%, 0%) -> 0 | J81: =IF(J80>0, 15%, 0%) -> 0 | K81: =IF(K80>0, 15%, 0%) -> 0 | L81: =IF(L80>0, 15%, 0%) -> 0 | ... AC81: =IF(AC80>0, 15%, 0%) -> 0.15
B82: Profit | E82: =E80*(1-E81) -> 0 | F82: =F80*(1-F81) -> 0 | G82: =G80*(1-G81) -> 0 | H82: =H80*(1-H81) -> 0 | I82: =I80*(1-I81) -> 0 | J82: =J80*(1-J81) -> -8.5923 | K82: =K80*(1-K81) -> -12.4419 | L82: =L80*(1-L81) -> -18.6756 | ... AC82: =AC80*(1-AC81) -> 625.90014
B84: D&A | E84: 0 | F84: 0 | G84: 0 | H84: 0 | I84: 0 | J84: 0 | K84: =J84 -> 0 | L84: =K84 -> 0 | M84: =L84 -> 0 | N84: =M84 -> 0 | O84: =N84 -> 0 | P84: =O84 -> 0 | Q84: =P84 -> 0 | R84: =Q84 -> 0 | ... AC84: =AB84 -> 0
B85: Stock Option Expense | E85: 0 | F85: 0 | G85: 0 | H85: 0 | I85: 0 | J85: 0 | K85: =K78*20% -> 0.43269 | L85: =L78*20% -> 0.50331 | M85: =M78*20% -> 0.756 | N85: =N78*20% -> 0.9039 | O85: =O78*20% -> 1.080885 | P85: =P78*20% -> 1.2926977 | Q85: =Q78*20% -> 4 | R85: =R78*20% -> 10 | ... AC85: =AC78*20% -> 20
B86: Capex | E86: 0 | F86: 0 | G86: 0 | H86: 0 | I86: 0 | J86: 0 | K86: =J86 -> 0 | L86: =K86 -> 0 | M86: =L86 -> 0 | N86: =M86 -> 0 | O86: =N86 -> 0 | P86: =O86 -> 0 | Q86: =P86 -> 0 | R86: =Q86 -> 0 | ... AC86: =AB86 -> 0
B87: Working Capital | E87: 0 | F87: 0 | G87: 0 | H87: 0 | I87: 0 | J87: 0 | K87: 0 | L87: 0 | M87: =L87 -> 0 | N87: =M87 -> 0 | O87: =N87 -> 0 | P87: =O87 -> 0 | Q87: =P87 -> 0 | R87: =Q87 -> 0 | S87: =R87 -> 0 | T87: =S87 -> 0 | ... AC87: =AB87 -> 0
B88: FCF (in $M) | E88: =E82+SUM(E84:E87) -> 0 | F88: =F82+SUM(F84:F87) -> 0 | G88: =G82+SUM(G84:G87) -> 0 | H88: =H82+SUM(H84:H87) -> 0 | I88: =I82+SUM(I84:I87) -> 0 | J88: =J82+SUM(J84:J87) -> -8.5923 | K88: =K82+SUM(K84:K87) -> -12.00921 | L88: =L82+SUM(L84:L87) -> -18.17229 | ... AC88: =AC82+SUM(AC84:AC87) -> 645.90014 | AD88: =AC88*(1+C94)/(C95-C94) -> 1424.7797
B90: Discount period | C90: 2026 | M90: =M68-$C$90 -> 0 | N90: =N68-$C$90 -> 1 | O90: =O68-$C$90 -> 2 | P90: =P68-$C$90 -> 3 | Q90: =Q68-$C$90 -> 4 | R90: =R68-$C$90 -> 5 | S90: =S68-$C$90 -> 6 | T90: =T68-$C$90 -> 7 | ... AC90: =AC68-$C$90 -> 16 | AD90: =AC90 -> 16
B91: NPV | M91: =M88/(1+$C$95)^M90 -> -30.024 | N91: =N88/(1+$C$95)^N90 -> -40.734495 | O91: =O88/(1+$C$95)^O90 -> -42.169253 | P91: =P88/(1+$C$95)^P90 -> -43.688368 | Q91: =Q88/(1+$C$95)^Q90 -> -36.129686 | R91: =R88/(1+$C$95)^R90 -> -48.744854 | S91: =S88/(1+$C$95)^S90 -> -37.325814 | T91: =T88/(1+$C$95)^T90 -> 12.356147 | ... AD91: =AD88/(1+$C$95)^AD90 -> 358.85893
B93: NPV Sum (in $M) | C93: =IF(C90=F68,SUM(F91:AD91),(SUM(G91:AD91))) -> 1150.1222 | M93: $/share | O93: Downside | P93: Base Case | Q93: Upside
B94: Terminal Growth (%) | C94: -0.25 | M94: Probability adjusted NPV | O94: =C93*O95 -> 0 | P94: =C98 -> 230.02443 | Q94: =C93*Q95 -> 287.53054
B95: Discount Rate | C95: 0.09 | M95: Assumed PoS | O95: 0 | P95: =C97 -> 0.2 | Q95: 0.25
B96: Share count (in M) | C96: =SOTP!D38 -> 53.187829 | M96: ML-004 | O96: =P96/P95*O95 -> 0 | P96: =C99 -> 4.324757 | Q96: =P96/P95*Q95 -> 5.4059462
B97: Probability of Success | C97: 0.2
B98: Probability adjusted NPV | C98: =C93*C97 -> 230.02443
B99: Price Per Share | C99: =C98/C96 -> 4.324757
M100: Peak Sales Calculator | O100: Downside | P100: Base Case | Q100: Upside
M101: Peak sales ($M) | O101: 500 | P101: =MAX(Q69:AC69) -> 890.89801 | Q101: 1500
M102: Multiple | O102: 2 | P102: 2 | Q102: 2.5
M103: Valuation | O103: =O101*O102 -> 1000 | P103: =P101*P102 -> 1781.796 | Q103: =Q101*Q102 -> 3750
M104: Assumed PoS | O104: =O95 -> 0 | P104: =P95 -> 0.2 | Q104: =Q95 -> 0.25
M105: $/Share | O105: =O103/$C96*O104 -> 0 | P105: =P103/$C96*P104 -> 6.7000141 | Q105: =Q103/$C96*Q104 -> 17.626213

Sheet Schizophrenia Drug Peak Sales
B2: Comparison of Selected Atypical Antipsychotics (Second-generation antipsychotics)
B3: Company | C3: Branded | D3: Generic | E3: Mode | F3: Indication** | G3: Approved | H3: Peak Sales | I3: Peak Year | J3: Blackbox? | K3: Safety Notes | L3: Label
B4: Novartis (NVS) | C4: Clozaril | D4: clozapine | E4: Oral | F4: TR-SCZ, Reducing Suicide Risk | G4: 1989 | H4: 0.3909 | I4: ~2012 | J4: Neutropenia, Hypotension, Bradycardia, Syncope, Mortality, Seizure, Myocarditis, Cardiomyopathy | K4: White blood cell decrease, heart inflammation | L4: https://www.accessdata.fda.gov/drugsatfda_docs/label/2017/019758s084lbl.pdf | M4: x
B5: Janssen (JNJ) | C5: Risperdal | D5: risperidone | E5: Oral | F5: SCZ, BP1 (Manic/Mixed)*, ASD (Irritability) | G5: 1993 | H5: 4.5 | I5: 2007 | J5: Mortality | K5: Less sedating but more extrapyramidal side effects | L5: http://www.janssenlabels.com/package-insert/product-monograph/prescribing-information/RISPERDAL-pi.pdf | M5: x
B6: Eli Lilly (LLY) | C6: Zyprexa | D6: olanzapine | E6: Oral, IM | F6: SCZ, BP1 (Manic/Mixed), BP1 depression*, TRD* | G6: 1996 | H6: 5.026 | I6: 2010 | J6: Mortality | K6: Less extrapyramidal side effects but increases weight and blood sugar | L6: https://www.accessdata.fda.gov/drugsatfda_docs/label/2014/020592s062021086s040021253s048lbl.pdf | M6: x
B7: AstraZeneca (AZN) | C7: Seroquel | D7: quetiapine | E7: Oral | F7: SCZ, BP1 (Manic), Bipolar depression | G7: 1997 | H7: 6.177 | I7: 2011 | J7: Mortality, Suicidality | K7: Less motor side effects but more weight gain and hypertension | L7: https://www.accessdata.fda.gov/drugsatfda_docs/label/2013/020639s061lbl.pdf | M7: x
B8: Pfizer (PFE) | C8: Geodon | D8: ziprasidone | E8: Oral , IM | F8: SCZ, BP1 (Manic/Mixed)* | G8: 2001 | H8: 1.35 | I8: 2011 | J8: Mortality | K8: Heart arrhythmia, hypertension, dizziness | L8: http://labeling.pfizer.com/ShowLabeling.aspx?format=PDF&id=584 | M8: x
B9: Otsuka/ Bristol Myers (BMY) | C9: Abilify | D9: aripiprazole | E9: Oral , IM | F9: SCZ, BP1 (Manic/Mixed), MDD*, ASD (Irritability), TS | G9: 2002 | H9: 7.363 | I9: 2011 | J9: Mortality, Suicidality | K9: Weight gain, headache, agitation, anxiety, insomnia, nausea | L9: https://www.accessdata.fda.gov/drugsatfda_docs/label/2014/021436s038,021713s030,021729s022,021866s023lbl.pdf | M9: x
B10: Johnson & Johnson (JNJ) | C10: Invega/ Invega Sustenna | D10: paliperidone | E10: IM | F10: SCZ, SZA | G10: 2006 | H10: 4.2 | I10: 2024 | J10: Mortality | K10: Restlessness, weight gain, sedation | L10: https://www.accessdata.fda.gov/drugsatfda_docs/label/2017/022264s023lbl.pdf | M10: x
B11: Allergan (AGN) | C11: Saphris | D11: asenapine | E11: Oral | F11: SCZ, BP1 (Manic/Mixed) | G11: 2009 | H11: 0.167 | I11: 2016 | J11: Mortality | K11: Stroke, ischemic attacks, QT prolongation, seizures, hypotension | L11: https://www.accessdata.fda.gov/drugsatfda_docs/label/2017/022117s020s021lbl.pdf | M11: x
B12: Vanda (VNDA) | C12: Fanapt/ Zomaril | D12: Iloperidone | E12: Oral | F12: SCZ, BP1 (Manic/Mixed) | G12: 2009 | H12: 0.2 | I12: 2027 | J12: Mortality | K12: Weight gain, seizures, hypotension, suicide, cognitive impairment | L12: https://www.accessdata.fda.gov/drugsatfda_docs/label/2016/022192s017lbl.pdf | M12: x
B13: Sunovion | C13: Latuda | D13: Lurasidone | E13: Oral | F13: SCZ, BP1 depression | G13: 2010 | H13: 1.829 | I13: 2021 | J13: Mortality, Suicidality | K13: Stroke, ischemic attack, neuroleptic malignant syndrome, weight gain | L13: https://www.latuda.com/LatudaPrescribingInformation.pdf | M13: x
B14: Otsuka/ Lundbeck | C14: Rexulti | D14: brexpiprazole | E14: Oral | F14: SCZ, MDD, ADA* | G14: 2015 | H14: 2.6 | I14: 2028 | J14: Mortality, Suicidality | K14: Stroke, ischemic attacks, weight gain, hypotension, seizures | L14: https://www.otsuka-us.com/media/static/Rexulti-PI.pdf | M14: x | AE14: -
B15: Allergan (AGN)/ AbbVie (ABBV) | C15: Vraylar | D15: cariprazine | E15: Oral | F15: SCZ, BP1 (Manic/Mixed), BP1 depression, MDD | G15: 2015 | H15: 4.5 | I15: 2029 | J15: Mortality, Suicidality | K15: Stroke, ischemic attacks, weight gain, hypotension, seizures | L15: https://www.allergan.com/assets/pdf/vraylar_pi | M15: x | AE15: -
B16: Intracellular (ITCI)/ Johnson & Johnson (JNJ) | C16: Caplyta | D16: lumateperone | E16: Oral | F16: SCZ, Bipolar depression, MDD | G16: 2019 | H16: 5 | I16: 2040 | J16: Mortality | K16: Stroke, ischemic attacks, weight gain, metabolic changes, hypotension, seizures
B17: Alkermes (ALKS) | C17: Lybalvi | D17: olanzapine and samidorphan | E17: Oral | F17: SCZ, BP1 (Manic/Mixed) | G17: 2021 | H17: 0.6235 | I17: 2031 | J17: Mortality | K17: Stroke, ischemic attacks, weight gain, metabolic changes, hypotension, seizures | M17: x | AE17: -
B18: * Efficacy Comparison of Approved Second-Generation Antipsychotics (Positive, Placebo-Controlled Datasets Mentioned in Their Respective FDA Labels)
B19: ** Schizophrenia (SCZ); Treatment-resistant schizophrenia (TR-SCZ); Schizoaffective disorder (SZA); Bipolar 1 disorder (BP1); Major depressive disorder (MDD); Tourettes syndrome (TS);
B20: Autism spectrum disorder (ASD); Treatment-Resistant Depression (TRD); Alzheimer's Disease Agitation (ADA)
C23: All | D23: SCZ | E23: ADP
B24: Abilify (2011) | C24: 7.363
B25: Seroquel (2011) | C25: 6.177
B26: Cobenfy (2035E) | C26: =D26+E26 -> 5.5119 | D26: 3.5139 | E26: 1.998
B27: Zyprexa (2010) | C27: 5.026
B28: Caplyta (2040E) | C28: 5
B29: Risperdal (2007) | C29: 4.5
B30: Vraylar (2029E) | C30: 4.5
B31: Invega* (2024) | C31: 4.2
B32: ML-007C-MA (2045E) | C32: =D32+E32 -> 3.4055477 | D32: ='SCZ DCF'!P102/1000 -> 1.3350132 | E32: ='ADP DCF'!L104/1000 -> 2.0705346
B33: Rexulti (2028E) | C33: 2.6
B34: Latuda (2021) | C34: 1.829
B35: Geodon (2011) | C35: 1.35
B36: Lybalvi (2031E) | C36: 0.6235
B37: Clozaril (2012) | C37: 0.3909
B38: Fanapt (2027E) | C38: 0.2
B39: Saphris (2016) | C39: 0.167
I55: Risperidal
B56: https://www.forbes.com/sites/simonking/2013/01/28/the-best-selling-drugs-of-all-time-humira-joins-the-elite/#4d1e81f35110 | C56: x | I56: It can cause strokes among the elderly. And it can cause boys to grow large, pendulous breasts; one boy developed a 46DD bust.
I57: https://www.justice.gov/sites/default/files/usao-edpa/legacy/2014/02/11/JanssenPharma_information.pdf
B68: * Scores were determined by taking the average scores from all positive trials (mentioned in the label)
B74: ******* Single trial evaluating efficacy using the BPRS endpoint - no PANSS data available

Sheet Cobenfy Launch
L1: Source: Factset
O2: Launch Aligned
C3: Q4:24 | D3: Q1:25 | E3: Q2:25 | F3: Q3:25E | G3: Q4:25E | H3: Q1:26E | I3: Q2:26E | J3: Q3:26E | K3: Q4:26E | P3: Q1 | Q3: Q2 | R3: Q3 | S3: Q4 | T3: Q5 | U3: Q6 | V3: Q7 | W3: Q8 | X3: Q9
B4: Total | C4: =C5+C7 -> 10 | D4: =D5+D7 -> 27 | E4: =E5+E7 -> 35 | F4: 43 | G4: 53 | H4: 69.2 | I4: 89.5 | J4: 109.5 | K4: 128.8 | O4: Latuda (2011) | P4: =O22 -> 35 | Q4: =P22 -> 6 | R4: =Q22 -> 7 | S4: =R22 -> 38 | T4: =S22 -> 39 | U4: =T22 -> 41 | V4: =U22 -> 60 | W4: =V22 -> 62 | X4: =W22 -> 50
B5: US | C5: 10 | D5: 27 | E5: 35 | F5: 43 | O5: Lybalvi (2021) | P5: =BF24*0.5 -> 4.1 | Q5: =BG24*0.5 -> 7 | R5: =BH24*0.5 -> 10 | S5: =BI24*0.5 -> 13.5 | T5: =BJ24*0.5 -> 17.5 | U5: =BK24*0.5 -> 19 | V5: =BL24*0.5 -> 23.5 | W5: =BM24*0.5 -> 25.35 | X5: =BN24*0.5 -> 28.1
B6: % | C6: =C5/C4 -> 1 | D6: =D5/D4 -> 1 | E6: =E5/E4 -> 1 | F6: =F5/F4 -> 1 | G6: =G5/G4 -> 0 | H6: =H5/H4 -> 0 | I6: =I5/I4 -> 0 | J6: =J5/J4 -> 0 | K6: =K5/K4 -> 0 | O6: Caplyta (2019) | P6: =AY23 -> 0.882516 | Q6: =AZ23 -> 1.875889 | R6: =BA23 -> 7.368594 | S6: =BB23 -> 12.403754 | T6: =BC23 -> 15.578905 | U6: =BD23 -> 19.00678 | V6: =BE23 -> 21.606163 | W6: =BF23 -> 25.516026
B7: Int'l | C7: 0 | D7: 0 | E7: 0 | F7: 0 | O7: Cobenfy (2024) | P7: =C4 -> 10 | Q7: =D4 -> 27 | R7: =E4 -> 35 | S7: =F4 -> 43 | T7: =G4 -> 53 | U7: =H4 -> 69.2 | V7: =I4 -> 89.5 | W7: =J4 -> 109.5 | X7: =K4 -> 128.8
B8: % | C8: =C7/C4 -> 0 | D8: =D7/D4 -> 0 | E8: =E7/E4 -> 0 | F8: =F7/F4 -> 0 | G8: =G7/G4 -> 0 | H8: =H7/H4 -> 0 | I8: =I7/I4 -> 0 | J8: =J7/J4 -> 0 | K8: =K7/K4 -> 0
C9: Blue = Cons estimate
N21: Drug | O21: 1Q11 | P21: 2Q11 | Q21: 3Q11 | R21: 4Q11 | S21: 1Q12 | T21: 2Q12 | U21: 3Q12 | V21: 4Q12 | W21: 1Q13 | X21: 2Q13 | Y21: 3Q13 | Z21: 4Q13 | AA21: 1Q14 | AB21: 2Q14 | AC21: 3Q14 | AD21: 4Q14 | AE21: 1Q15 | AF21: 2Q15 | AG21: 3Q15 | AH21: 4Q15 | AI21: 1Q16 | AJ21: 2Q16 | AK21: 3Q16 | AL21: 4Q16 | AM21: 1Q17 | AN21: 2Q17 | AO21: 3Q17 | AP21: 4Q17 | AQ21: 1Q18 | AR21: 2Q18 | AS21: 3Q18 | AT21: 4Q18 | AU21: 1Q19 | AV21: 2Q19 | AW21: 3Q19 | AX21: 4Q19 | AY21: 1Q20 | AZ21: 2Q20 | BA21: 3Q20 | BB21: 4Q20 | BC21: 1Q21 | BD21: 2Q21 | BE21: 3Q21 | BF21: 4Q21 | BG21: 1Q22 | BH21: 2Q22 | BI21: 3Q22 | BJ21: 4Q22 | BK21: 1Q23 | BL21: 2Q23 | BM21: 3Q23 | BN21: 4Q23 | BO21: 1Q24 | BP21: 2Q24 | BQ21: 3Q24 | BR21: 4Q24 | BS21: 1Q25 | BT21: 2Q25 | BU21: 3Q25 | BV21: 4Q25
N22: Latuda (Sumitomo) | O22: 35 | P22: =41-O22 -> 6 | Q22: =48-P22-O22 -> 7 | R22: 38 | S22: 39 | T22: =80-S22 -> 41 | U22: =140-T22-S22 -> 60 | V22: 62 | W22: 50 | X22: 68 | Y22: 94 | Z22: 127 | AA22: =421-Z22-Y22-X22 -> 132 | AB22: 180 | AC22: =354-AB22 -> 174 | AD22: =555-AC22-AB22 -> 201 | AE22: =752-AD22-AC22-AB22 -> 197 | AF22: 218 | AG22: =472-AF22 -> 254 | AH22: =729-AG22-AF22 -> 257 | AI22: =1002-AH22-AG22-AF22 -> 273 | AJ22: 291 | AK22: =584-AJ22 -> 293 | AL22: =911-AK22-AJ22 -> 327 | AM22: =1254-AL22-AK22-AJ22 -> 343 | AN22: 395 | AO22: =779-AN22 -> 384 | AP22: =1210-AO22-AN22 -> 431 | AQ22: =1611-AP22-AO22-AN22 -> 401 | AR22: 402 | AS22: =813-AR22 -> 411 | AT22: =1256-AS22-AR22 -> 443 | AU22: =1663-AT22-AS22-AR22 -> 407 | AV22: 445 | AW22: =873-AV22 -> 428 | AX22: =1308-AW22-AV22 -> 435 | AY22: =1743-AX22-AW22-AV22 -> 435 | AZ22: 493 | BA22: =978-AZ22 -> 485 | BB22: =1513-BA22-AZ22 -> 535 | BC22: =1946-BB22-BA22-AZ22 -> 433 | BD22: 469 | BE22: =920-BD22 -> 451 | BF22: =1413-BE22-BD22 -> 493 | BG22: =1816-BF22-BE22-BD22 -> 403 | BH22: 482 | BI22: =952-BH22 -> 470 | BJ22: =1313-BI22-BH22 -> 361 | BK22: =1465-BJ22-BI22-BH22 -> 152 | BL22: 8 | BM22: =29-BL22 -> 21 | BN22: =36-BM22-BL22 -> 7 | BO22: =47-BN22-BM22-BL22 -> 11 | BP22: 3.4 | BQ22: 3.3 | BR22: 3.5
N23: Caplyta (ITCI/JNJ) | AY23: 0.882516 | AZ23: 1.875889 | BA23: 7.368594 | BB23: 12.403754 | BC23: 15.578905 | BD23: 19.00678 | BE23: 21.606163 | BF23: 25.516026 | BG23: 34.755 | BH23: 55.074 | BI23: 71.87 | BJ23: 87.433 | BK23: 94.731 | BL23: 110.128 | BM23: 125.81 | BN23: 131.506 | BO23: 144.843 | BP23: 161.276 | BQ23: 175.159 | BR23: 199.223 | BS23: =AVERAGE(BR23,BT23) -> 205.1115 | BT23: 211 | BU23: 240
N24: Lybalvi (ALKS) | BF24: 8.2 | BG24: 14 | BH24: 20 | BI24: 27 | BJ24: 35 | BK24: 38 | BL24: 47 | BM24: 50.7 | BN24: 56.2 | BO24: 57 | BP24: 71.4 | BQ24: 74.7 | BR24: 77 | BS24: 70 | BT24: 84.28 | BU24: 98.2
C25: 2024 | D25: 2025 | E25: 2026 | F25: 2027 | G25: 2028 | H25: 2029 | I25: 2030 | J25: 2031 | K25: 2032 | L25: 2033
B26: Total | C26: =C4 -> 10 | D26: 173.3 | E26: 494.4 | F26: 1023.5 | G26: 1688.8 | H26: 2448.6 | I26: 3189.2 | J26: 3864.9 | K26: 4531 | L26: 4807
C28: Blue = Cons estimate

Sheet Cobenfy Launch Commentary
B2: Date | C2: Venue | D2: Comments
B3: 45869 | C3: Q2:25 Call | D3: Cobenfy has delivered strong performance since launch and we have consistently received positive feedback from physicians. They are seeing firsthand the medicine's differentiated profile with robust efficacy on both positive and negative symptoms and improved cognition. Now moving to discuss Cobenfy on slide 13. Cobenfy sales were $35 million in the quarter and $62 million year-to-date. The launch of Cobenfy is tracking as we expected. Weekly total prescriptions continued to grow, and we expect continued steady growth with sales in the second half of the year higher than the first half. No, thanks, Chris, Cobenfy is performing in line with expectations, and we're now tracking over 2,000 TRx-es on a weekly basis. We expect to see steady TRx growth as we continue to execute our plan. And we're still in the early stages of launch. And as we previously communicated, we knew it was going to take time to change what's been decades of entrenched prescribing behavior, and indeed, I think that's been the case. Physician feedback continues to be very positive regarding Cobenfy's differentiated profile. And what's encouraging is that the vast majority of physicians have indicated an intent to prescribe Cobenfy. So we're making steady progress with adding a number of new trialists as we're growing trialists each week. But we definitely have an opportunity to continue to accelerate breadth and depth of prescribing. So let me talk a little bit about what we're doing and also some of what we're hearing. First, we're increasing the size of our community field force to increase reach and frequency as we know it takes multiple calls to change physician behavior. For your question, the most common question that we receive from physicians is how to switch. And we're focused on clarifying switching approaches from D2s to Cobenfy through peer-to-peer initiatives, introducing real-world data. And we also have a Phase 4 switch study that reads out at the end of the year, I think all of which will help build physician confidence. And then finally, we're expanding into the hospital setting. So this is a planned sequence launch first into the community, then into the hospital, and that opportunity to drive new patient starts, patients are typically maintained on treatment from the hospital and then moved into the community. So in the hospitals, around 20% to 25% of NRx is initiated there. So based on all leading indicators we're seeing, we're confident that Cobenfy is going to be a big drug in schizophrenia and longer term will be fueled by additional indications such as our Alzheimer's program. So I'll turn it over to Samit to talk about the Alzheimer's program.
D4: Yeah, Seamus, thanks for the question. And as I said, previously, we expect to see continued, steady TRx growth as we execute the plan that I outlined. Cobenfy is tracking far ahead of all branded schizophrenia launch benchmarks. So, we've now achieved over 45,000 TRx-es since launch. And I think the big opportunity is to continue to change the treatment paradigm and unlock this entrenched prescribing behavior that has existed now for decades. And so that's why we are, in fact, focusing on driving number of – increasing number of trial depth and breadth of prescribing. What I look at on a weekly basis is how are we doing in adding number of writers? What's our depth and breadth of prescribing? What's the intent to prescribe? All those leading indicators we see are very, very positive. There's not a great analog, to be frank, since there's been nothing in this space for so long, but we're very pleased with what we're seeing thus far. And based on everything that we continue to see and hear from physicians, we're confident that Cobenfy is going to be a big drug in schizophrenia. The last thing that I'll mention is just every week, we get feedback from physicians and patients. And just last week, we received a feedback from a physician that said he stopped the medicine for the patient and started them on Cobenfy. And now the patient's thinking about his future. He is including signing up for a class with improvements in attention, judgment and insight. And that's just a small sample of what we hear every single week from physicians and patients. So, again, increasing our confidence that this is going to be a big drug in schizophrenia. As you heard from Chris, Samit, David and myself, longer term, this product is going to be multibillion dollars [ph] if you buy (00:49:10) additional indications. Got it. I'll start off. And there's a lot of questions in there and I'll try and address as much as I can. Keeping in mind, we are at a place where we are totally blinded to the data, so cannot comment on the specificities. As you know, the trial is designed with four dose escalations on week one, two, three and four. Of course, the fourth one, the 200-milligram of Cobenfy or KarXT with 20 milligrams of trospium is an optionality, but of course, dependent on the tolerability. Remember, there's a huge difference between AD psychosis trial that we are conducting versus a 30-year ago xanomeline-only study that was conducted because there was a tolerability issue where patients did go off treatment much more and the number of completers was limited because of the toxicity. So I would not necessarily draw true conclusions directly from that trial. Also, over there, when we talk about the impact on some of the endpoints, much attention was paid to the cognition endpoint, ADAS-Cog, where the analysis is conducted and that significance was seen only in the ADAS-Cog highest dose level.
D5: For the psychosis-related symptomatology, we did see dose-dependent improvements, but of course, the pairwise analysis was not conducted. We did see hallucinations, delusions, aggression, suspiciousness, all of those endpoints, quite meaningfully impacted. So, overall, we are really looking forward to the data from ADEPT-2, and that will help us guide in terms of the future discussions around this once the data are available.
B6: 45771 | C6: Q1:25 Call | D6: Sure. As Chris stated in his opening remarks, we don't expect these data to have a meaningful impact on Cobenfy sales, Chris. Recall, about 70% to 80% of patients are treated with monotherapy, and clearly, that's the most significant commercial opportunity. And it's also the treatment goal for psychiatrists. What happens in the real world, psychiatrists exhaust monotherapy options before trying adjunctive use, and that's after several failed monotherapy treatments happening later in line, third line, fourth line plus. Our focus is moving Cobenfy earlier in treatment. That's exactly what we've been seeing in the market. In fact, roughly 40% to 50% of the Cobenfy prescribing today is now in second line and third line. And so physicians have also told us, both in research and through advisory boards, that missing the endpoint of the study will have no impact on monotherapy usage or their willingness to use Cobenfy, particularly when you look at the safety of the study results. There's a significant unmet need that still exists for patients with schizophrenia, and Cobenfy fills the need with its efficacy and safety profile. And that's why we're seeing strong uptake in the market since launch with positive feedback from both physicians and for patients. So, we're going to continue to execute our plan for Cobenfy to come to foundational monotherapy treatment, and we have a clear opportunity to continue to drive significant growth. Now moving to slide 12. In its first full quarter on the market, Cobenfy is off to a solid start with sales of approximately $27 million, driven primarily by demand. During the quarter, weekly total prescriptions remained strong, tracking ahead of all branded schizophrenia launch benchmarks. We expect several of these opportunities to come this year, such as the first look at one of the Phase 3 trials for Cobenfy in Alzheimer's disease psychosis, where there is significant unmet need. We also plan to initiate several new pivotal studies this year, including seven Phase 3 studies for Cobenfy across three indications, Alzheimer's agitation, Alzheimer's cognition impairment and Bipolar I, all expected to be underway by midyear.
D8: Yeah. Thanks, Luisa, for the question. ARISE data has no impact as we think about Alzheimer's disease psychosis. There are a few reasons for that. One, obviously, the disease is very different. Two, Alzheimer's disease overall plan in psychosis as well as future-looking cognition impairment and agitation, those are based on the data that have already been generated many years ago, a couple decades ago for xanomeline, where it showed statistically significant benefits in the behavioral patterns in patients with Alzheimer's disease. Also, from a design perspective, in Alzheimer's disease psychosis, there is a longer duration of treatment of up to 12 weeks, which is obviously going to be beneficial as we think about observation of output for primary and secondary endpoints. So, overall, confident in the conduct of our studies. And as you know, we are also initiating several studies, as Chris spoke about earlier, seven different Phase 3 trials this year. So, really looking forward to initiation of that program.
D9: Yeah. Thanks, Terrance. So, we're very pleased with these Cobenfy's launch performance. The launch is off to a strong start. We're now over 1,600 TRxs per week, and it's tracking ahead of all branded schizophrenia launch benchmarks. We've made very good progress achieving Medicaid and Medicare access. We're now at virtually 100% access across both channels, and we're making good progress with commercial payers. I mentioned earlier that because of this access, it's allowing us to move Cobenfy up earlier in treatment, which is critical. And I think, most importantly, we are hearing very encouraging feedback from both patients and physicians around Cobenfy's efficacy and safety profile, physicians noting efficacy and positive symptoms, negative symptoms and improvement in cognition and clarity of thought. We're also – I think, a critical metric for us is growing number of new trialists, and we're seeing consistent growth week-over-week in new trialists since launch. And we've got an opportunity to continue to expand and reach the 30,000 psychiatrists that are on our target list. And so, as we've said, we expect to see strong uptake over the course of 2025, with a ramp in the back half of the year after we continue to increase the frequency of calls to our customers and try to break those reflexive habits. But we know the work we need to do to maximize this launch, and we will make this a very big product for the company over time. Now, as it relates to gross-to-net, as you saw in the slides, we delivered $27 million in net sales for the quarter, and that was inclusive of $9 million in gross-to-net benefit. So, the underlying demand for Cobenfy is strong. And at launch, we made assumptions around payer mix and discount. So, Q1 essentially was a true-up for favorable gross-to-nets in Q4. So, we've been very disciplined in discretionary gross-to-net spend. As you know, there are mandatory discounts in Medicaid. We now have very strong access. So, we expect to see increases this year in gross-to-nets for the full year. But again, we expect to see strong uptake over the course of the year with a ramp taking place in the back half of 2025. Yeah. So, related to the gross-to-net, we don't share specific discounting rates. But as I mentioned, we've been very disciplined in discretionary gross-to-net spend. And so when you look at the gross-to-net impact for the first quarter, we saw this was just a true-up for a projection that we made was favorable in Q4. So, we will have increase in gross-to-nets for the full year, because we have now 100% access virtually in both Medicaid and Medicare.
B10: 45694 | C10: Q4:24 Call | D10: Yeah, Seamus, thanks for the questions. We've been really pleased with what we're hearing from both physicians and patients. The feedback has been very positive with a lot of enthusiasm on the efficacy and the safety profile. So, what we're hearing is, patients are seeing improvements in positive symptoms as early as the first week of treatment, and on really the lowest dose of 50 milligrams. And we're also hearing good successes on negative symptoms and what we were really excited about this asset for, improvement in clarity of thought, improvement of cognition, patients being able to reengage with their families and even start thinking about going back to work. The AEs, what we've heard from physicians, they're manageable, including the nausea and vomiting, because what we're seeing is the majority of physicians in the real world are treating patients at the lowest dose. Just starting with 50 milligrams, they're taking a week or two before they titrate up to the next dose at 100 milligrams unlike what you saw in the clinical trials, which moved to 125 milligrams within the first eight days of the trial. So that has been incredibly positively received, and so we're not hearing a lot of the GI tolerability issues from physicians. But our teams are out there making sure that we're educating on what to expect. As it relates to BID, we know that on average, patients are on seven pills per day. And so, we're not hearing this as a major objection to prescribing. And last thing I'll mention is we've got an ongoing study looking at taking COBENFY with food that will readout this year. So that will also improve the ease of prescribing for physicians and make it easier for patients as well. Yeah. I'll just answer the question around COBENFY. Courtney, thanks for the question. As it relates to gross-to-net, the brand is going to continue to lean heavily towards the public sector of Medicare and Medicaid. And you think about the evolution of schizophrenia indications or our Alzheimer's indications, whether it be Alzheimer's psychosis or Alzheimer's cognition. These are patients who are going to be in Medicare and Medicaid. Commercial patients are less than 10%, you will see that more commonly in some of the indications such as autism and in bipolar disorder, but the majority of the brand will largely be in the public sector where there are Medicaid best price. I'll just add, Samit. Our focus has been on ensuring a successful launch where generics atypical have about 80% market share, and COBENFY has significant safety and efficacy advantages there.
D12: As Samit just mentioned, we see the unique efficacy advantages around the three domains of schizophrenia, hitting on positive symptoms, negative symptoms, and cognition due to its unique mechanism of action. So, we didn't expect competition from other muscarinics in schizophrenia until late 2026, early 2027. And the failure of emraclidine, we have a clear path forward in schizophrenia and we're excited about the opportunity with COBENFY. And we believe that we're going to drive meaningful growth for COBENFY really into the middle of the next decade. I will wrap up reviewing our performance for the quarter on slide 16 with Neuroscience and COBENFY. COBENFY sales in the fourth quarter were approximately $10 million and represent roughly two months of sales and initial stocking. And we've seen strong prescription uptake during these early months of launch. Feedback from both patients and physicians has been favorable, highlighting the benefits of COBENFY's differentiated efficacy and safety profile. Great. Thanks, Chris. So, regards to COBENFY, we're very pleased with what we're seeing with COBENFY with three months postlaunch, and the launch is really off to a strong start. We're now at approximately 1,000 TRxs per week. And we made very good progress achieving our access goals. So, for Medicaid and Medicare, we're tracking ahead of our expectations. We've achieved over 90% Medicaid access and over 80% Medicare access, recall those two payers represent over 80% of the covered lives in this category. And as expected, the majority have one-step edit post-generic. We're also making very good progress with commercial payers. The feedback over the last several months has been very positive. There's been a lot of enthusiasm around the efficacy and safety profile. I'm also pleased with the number of trialists that we're seeing since launch, and we have an opportunity to further expand and increase adoption with the roughly 30,000 psychiatrists. So, as you say, this is the first new mechanism of action in decades in the treatment of schizophrenia. And so, we're out with our teams educating customers on COBENFY's differentiated profile and we're breaking reflexive prescribing habits, and that's going to take some time.
D13: So, we would expect to see continued strong uptake through 2025, and as we said, with the ramp in the back half of this year. But taken together, we are really pleased with what we're seeing so far, and we plan to make this a very big product for the company over time.
B14: 45596 | C14: Q3:24 Call | D14: We're very excited about the approval of COBENFY. As you heard from Chris, is the first innovative therapy approved in schizophrenia in decades. And we're very pleased with the label does not carry the atypical antipsychotic class warnings and precautions or a box warning. And so, how we think about this addresses a large market. Remember, there are 1.6 million people treated for schizophrenia each year in the U.S. We do see this as a 2025 launch with the launch picking up after attaining broad access. We expect to see sales ramp in the second half of the year, and I'll describe those dynamics. First and foremost, we're really excited that product is available this week. Our field teams are out now selling. They're engaging with customers. And so, we'll see stocking this year. Now, access is a gating factor to sales uptake as over 80% of patients are either Medicare or Medicaid. And just remember, schizophrenia is a fundamentally different market than markets that are highly PBM-driven. So, we expect to take about a year to achieve 80% to 85% access. It could move a bit faster in Medicaid and we're certainly going to work to accelerate that. So, the way to think about is really in a stepwise fashion. In Medicaid, recall, roughly half of the states have zero to one step access. And so, deep Medicaid P&T meetings will take place over the course of the next several months. We've already seen a few states come online this week. Physicians can prescribe once P&T reviews are completed, and we are working to expand access across the remaining states. Now, in Medicare, recall this is a protected class. So, payers have 90 days to make a coverage decision, and we expect to see mandatory coverage determinations in Q1, but in the meantime, physicians can push through medical exemptions before any of these formulary reviews take place. Our asset teams have been meeting with payers for some time, and our team without immediately post approval, with payers to review the approved label, and the response has been very, very positive. So, again, we know the work that we need to do to maximize this important launch, and we plan to make this a very big product for our company over time. COBENFY, delivers compelling efficacy without the notable side effects associated with atypicals. The BMS team has been laying the groundwork for a successful launch. We built an experienced sales and medical team engaged with payers to secure access and develop sophisticated patient support services.
D16: And what are your comments to those that are looking at the BID regimen and GI adverse effects as potential barriers on ease of use in this patient population where compliance or lack thereof is a significant variable when thinking about your competitors that are coming up behind you. Yes. Thank you. Remember, the differentiating feature for COBENFY is that it's a dual direct agonist as opposed to some of the other therapies in development that target the M4 through indirect ways because they are allosteric modulators, which require a ligand such as acetylcholine to be present in the brain. And M1 is a very important component because from a biological perspective, that is associated with cognition function in the brain. And so having a direct impact on M1 as well as M4 gives us that opportunity to really impact the cognition and during the overall life cycle, as we think about the Alzheimer's disease patients as they go through it, cognition does become important in terms of the impact on the patient and patient life and quality of life. So there's a large proportion of patients who will have cognitive impairment and will be eligible if the data reads out positive to be treated with the drug. So overall, that's why we've developed a program in all three parts of AD that impact from a psychosis perspective, agitation perspective as well as the cognition perspective So it relates to the dosing regimen for that step back and just talk about the leading cause of discontinuation. Number one is efficacy and COBENFY delivers unsurpassed efficacy, efficacy that's at least as good as Zyprexa. And the other areas of high-level discontinuation include areas like weight gain, include infectious dysfunction, trouble concentrating, excessive sedation. And so now physicians don't need to trade that off. People living with schizophrenia commonly manage multiple medications at significantly higher rates than the general population. In fact, when you look at patients with schizophrenia, they're on average 7 pills a day which includes antipsychotic. It could include different psychotropic medications, including anti-depressants, anti-anxiety medications as well as medicines to combat the adverse events of their existing products. So yes, we're going to need to manage this, but we don't believe that this will impact uptake based on the unprecedented efficacy that COBENFY has shown. Last thing I'd mention is we saw very low discontinuation rates in our clinical trial due to the fact that patients that robust efficacy that the product is well tolerated and we will provide support to both patients and caregivers to maximize compliance with this medicine.

Sheet SCZ Pricing
B3: Caplyta
B4: 1709.94 | C4: 30 x 42mg
B5: =B4*365/30 -> 20804.27 | C5: per year
B7: Cobenfy
B8: 1850 | C8: 60 x 100mg/20mg
B9: =B8/60*365*2 -> 22508.333 | C9: per year
B11: Vraylar
B12: 1518.88 | C12: 30 x 6mg
B13: =B12*365/30 -> 18479.707 | C13: per year
B15: Rexulti
B16: 1515.69 | C16: 30 x 4mg
B17: =B16*365/30 -> 18440.895 | C17: per year

Sheet ASD
B1: ABC-I Subscale - Percent Reduction (or Improvement) Achieved by Drugs for Irritability in Autism Spectrum Disorder (ASD)
B2: Company | C2: Drug | D2: Status | E2: Study | F2: Design | G2: Duration | H2: Age | I2: N | J2: Dose | K2: Baseline ABC-I | L2: Efficacy Change | M2: Pbo Δ Change | N2: % | O2: Pbo Δ Change
B3: Otsuka/ BMY | C3: Abilify | D3: Approved | E3: Study 1 | F3: Pbo-Controlled | G3: 8 Weeks | H3: 6-17 | I3: 98 | J3: 2-15mg QD | K3: 29.6 | L3: -12.9 | M3: =L3-L4 -> -7.9 | N3: =(K3+L3)/K3-1 -> -0.43581081 | O3: =N3-N4 -> -0.2702479 | Q3: https://www.accessdata.fda.gov/drugsatfda_docs/label/2014/021436s038,021713s030,021729s022,021866s023lbl.pdf | R3: x | S3: met the DSM-IV criteria for autistic disorder
J4: Placebo | K4: 30.2 | L4: -5 | M4: - | N4: =(K4+L4)/K4-1 -> -0.16556291 | O4: - | S4: Over 75% of these subjects were under 13 years of a
E5: Study 2 | F5: Pbo-Controlled | G5: 8 Weeks | H5: 6-17 | I5: 218 | J5: 15mg QD | K5: 28.9 | L5: -14.4 | M5: =L5-L$8 -> -6 | N5: =(K5+L5)/K5-1 -> -0.4982699 | O5: =N5-N8 -> -0.1982699
J6: 10mg QD | K6: 28.2 | L6: -13.2 | M6: =L6-L$8 -> -4.8 | N6: =(K6+L6)/K6-1 -> -0.46808511 | O6: =N6-N8 -> -0.16808511
J7: 5mg QD | K7: 28.6 | L7: -12.4 | M7: =L7-L$8 -> -4 | N7: =(K7+L7)/K7-1 -> -0.43356643 | O7: =N7-N8 -> -0.13356643
J8: Placebo | K8: 28 | L8: -8.4 | M8: - | N8: =(K8+L8)/K8-1 -> -0.3 | O8: -
B9: JNJ | C9: Risperdal | D9: Approved | E9: Study 1 | F9: Pbo-Controlled | G9: 8 Weeks | H9: 5-16 | I9: 101 | J9: 0.5-3.5mg BID | K9: 26.2 | L9: =11.3-K9 -> -14.9 | M9: =L9-L$10 -> -11.3 | N9: =(K9+L9)/K9-1 -> -0.56870229 | O9: =N9-N10 -> -0.42752582 | Q9: https://www.accessdata.fda.gov/drugsatfda_docs/label/2009/020272s056,020588s044,021346s033,021444s03lbl.pdf | R9: x | S9: met the DSM-IV criteria for autistic disorder
J10: Placebo | K10: 25.5 | L10: =21.9-K10 -> -3.6 | M10: - | N10: =(K10+L10)/K10-1 -> -0.14117647 | O10: - | Q10: https://www.nejm.org/doi/10.1056/NEJMoa013171?url_ver=Z39.88-2003&rfr_id=ori:rid:crossref.org&rfr_dat=cr_pub%3dwww.ncbi.nlm.nih.gov | R10: x | S10: Over 90% of these subjects were under 12 years of age and most weighed over 20 kg (16-104.3 kg)
E11: Study 2 | F11: Pbo-Controlled | G11: 8 Weeks | H11: 5-12 | I11: 55 | J11: 0.02-0.06mg/kg QD | K11: 18.9 | L11: -12.1 | M11: =L11-L$12 -> -5.6 | N11: =(K11+L11)/K11-1 -> -0.64021164 | O11: =N11-N12 -> -0.33360787 | Q11: https://pediatrics.aappublications.org/content/pediatrics/114/5/e634.full.pdf?download=true | R11: x
J12: Placebo | K12: 21.2 | L12: -6.5 | M12: - | N12: =(K12+L12)/K12-1 -> -0.30660377 | O12: -
B13: ZYNE* | C13: Zygel | D13: Start Phase III in H2:22 | E13: Phase II (BRIGHT) | F13: Open-Label | G13: 14 Weeks | H13: 4-17 | I13: 37 | J13: 250mg or 500mg QD | K13: 30.3 | L13: =18.2-K13 -> -12.1 | M13: - | N13: -0.391 | O13: - | Q13: https://zynerba.com/zynerba-pharmaceuticals-announces-achievement-of-enrollment-target-in-phase-2-trial-of-zygel-in-autism-spectrum-disorder/ | R13: x | S13: ASD as confirmed by DSM-5 diagnostic criteria for ASD
B14: *Mean improvement

Sheet Disclaimer
