Workbook
Name IPS: #REF!
Name NDTI: #REF!
Name Notes: ML007MA_ME!$C$62,ML007MA_ME!$C$63:$C$65
Name Notes: '[3]VA Consensus'!$C$172,'[3]VA Consensus'!$C$173:$C$175
Name NPA: #REF!
Name RP_PP: #REF!

Sheet __FDSCACHE__
B1: This sheet contains FactSet XML data for use with this workbook's =FDS codes. Modifying the worksheet's contents may damage the workbook's =FDS functionality.

Sheet Variance
A1: COGT Variance Analysis
B3: 3Q24A | C3: 3Q25E | E3: 3Q25A | N3: 44768
B4: Value | C4: Amount | D4: % Change | E4: Amount | F4: % Change | G4: Variance | I4: Consensus | J4: Actual vs Cons | N4: Consensus
A5: Products
A6: Royalties and Contract Revenue | B6: 0 | C6: 0 | D6: =IFERROR(C6/B6-1,"NA") -> NA | E6: 0 | F6: =IFERROR(E6/B6-1,"NA") -> NA | G6: =E6-C6 -> 0
A7: Total Revenues | B7: =B6 -> 0 | C7: =C6 -> 0 | D7: =IFERROR(C7/B7-1,"NA") -> NA | E7: =E6 -> 0 | F7: =IFERROR(E7/B7-1,"NA") -> NA | G7: =E7-C7 -> 0 | I7: =FactSet!#REF! -> #REF! | J7: =E7-I7 -> #REF! | N7: 10.191705
A9: COGS | B9: 0 | C9: 0 | D9: =IFERROR(C9/B9-1,"NA") -> NA | E9: 0 | F9: =IFERROR(E9/B9-1,"NA") -> NA | G9: =-(E9-C9) -> 0 | N9: 0
A10: Gross Profit | B10: =B7-B9 -> 0 | C10: =C7-C9 -> 0 | D10: =IFERROR(C10/B10-1,"NA") -> NA | E10: =E7-E9 -> 0 | F10: =IFERROR(E10/B10-1,"NA") -> NA | G10: =E10-C10 -> 0
A11: SG&A | B11: 11.8 | C11: 13.5 | D11: =IFERROR(C11/B11-1,"NA") -> 0.1440678 | E11: 14.366 | F11: =IFERROR(E11/B11-1,"NA") -> 0.21745763 | G11: =-(E11-C11) -> -0.866 | I11: =FactSet!#REF! -> #REF! | J11: =-(E11-I11) -> #REF! | N11: 12.76223
A12: R&D | B12: 63.614 | C12: 65.604709 | D12: =IFERROR(C12/B12-1,"NA") -> 0.031293565 | E12: 68.989 | F12: =IFERROR(E12/B12-1,"NA") -> 0.084493979 | G12: =-(E12-C12) -> -3.3842911 | I12: =FactSet!#REF! -> #REF! | J12: =-(E12-I12) -> #REF! | N12: 26.507185
A13: Operating Income | B13: =B10-B11-B12 -> -75.414 | C13: =C10-C11-C12 -> -79.104709 | D13: =IFERROR(C13/B13-1,"NA") -> 0.048939307 | E13: =E10-E11-E12 -> -83.355 | F13: =IFERROR(E13/B13-1,"NA") -> 0.10529875 | G13: =E13-C13 -> -4.2502911 | I13: =FactSet!#REF! -> #REF! | J13: =E13-I13 -> #REF! | N13: -28.511639
A15: Interest income | B15: 4.779 | C15: 4 | D15: =IFERROR(C15/B15-1,"NA") -> -0.16300481 | E15: 3.887 | F15: =IFERROR(E15/B15-1,"NA") -> -0.18664993 | G15: =E15-C15 -> -0.113
A16: Gain on disposal of long-lived assets | B16: 0 | C16: 0 | D16: =IFERROR(C16/B16-1,"NA") -> NA | E16: 0
A17: Other income, net | B17: 0.044 | C17: 1.5687931 | D17: =IFERROR(C17/B17-1,"NA") -> 34.65439 | E17: =-1.459-0.003 -> -1.462 | F17: =IFERROR(E17/B17-1,"NA") -> -34.227273 | G17: =E17-C17 -> -3.0307931
A18: Non-Operating Items | B18: =SUM(B15:B17) -> 4.823 | C18: =SUM(C15:C17) -> 5.5687931 | D18: =IFERROR(C18/B18-1,"NA") -> 0.15463262 | E18: =SUM(E15:E17) -> 2.425 | F18: =IFERROR(E18/B18-1,"NA") -> -0.49720091 | G18: =E18-C18 -> -3.1437931
A19: Pre-tax Income | B19: =B13+B18 -> -70.591 | C19: =C13+C18 -> -73.535916 | D19: =IFERROR(C19/B19-1,"NA") -> 0.041718005 | E19: =E13+E18 -> -80.93 | F19: =IFERROR(E19/B19-1,"NA") -> 0.14646343 | G19: =E19-C19 -> -7.3940843
A20: Tax Rate | B20: =B21/B19 -> 0 | C20: =C21/C19 -> 0 | D20: =IFERROR(C20/B20-1,"NA") -> NA | E20: =E21/E19 -> 0 | F20: =IFERROR(E20/B20-1,"NA") -> NA | G20: =E20-C20 -> 0
A21: Taxes | B21: 0 | C21: 0 | D21: =IFERROR(C21/B21-1,"NA") -> NA | E21: 0 | F21: =IFERROR(E21/B21-1,"NA") -> NA | G21: =-(E21-C21) -> 0 | N21: -0.033018783
A23: Net Income (GAAP) | B23: =B19-B21 -> -70.591 | C23: =C19-C21 -> -73.535916 | D23: =IFERROR(C23/B23-1,"NA") -> 0.041718005 | E23: =E19-E21 -> -80.93 | F23: =IFERROR(E23/B23-1,"NA") -> 0.14646343 | G23: =E23-C23 -> -7.3940843 | I23: =FactSet!#REF! -> #REF! | J23: =E23-I23 -> #REF! | N23: -27.79529
A25: Average Basic & Diluted Shares | B25: 99.24003 | C25: 113.80794 | D25: =IFERROR(C25/B25-1,"NA") -> 0.1467947 | E25: 114.46608 | F25: =IFERROR(E25/B25-1,"NA") -> 0.1534265 | G25: =E25-C25 -> 0.65814
A26: GAAP EPS | B26: =B23/B25 -> -0.71131579 | C26: =C23/C25 -> -0.64614047 | D26: =IFERROR(C26/B26-1,"NA") -> -0.091626418 | E26: =E23/E25 -> -0.70702168 | F26: =IFERROR(E26/B26-1,"NA") -> -0.0060368521 | G26: =E26-C26 -> -0.060881209 | I26: =FactSet!#REF! -> #REF! | J26: =E26-I26 -> #REF! | N26: -0.6016666
A27: Source: Company reports; Team Research estimates

Sheet IS
A1: MapLight Therapeutics | AU1: =SOTP!R14 -> 37.175346
A2: Income Statement
A3: ($ Millions, except EPS)
B4: 1Q19A | C4: 2Q19A | D4: 3Q19A | E4: 4Q19A | F4: 2019A | G4: 1Q20A | H4: 2Q20A | I4: 3Q20A | J4: 4Q20A | K4: 2020A | L4: 1Q21A | M4: 2Q21A | N4: 3Q21A | O4: 4Q21A | P4: 2021A | Q4: 1Q22A | R4: 2Q22A | S4: 3Q22A | T4: 4Q22A | U4: 2022A | V4: 1Q23A | W4: 2Q23A | X4: 3Q23A | Y4: 4Q23A | Z4: 2023A | AA4: 1Q25A | AB4: 2Q25A | AC4: 3Q25A | AD4: 4Q25A | AE4: 2025A | AF4: 1Q26E | AG4: 2Q26E | AH4: 3Q26E | AI4: 4Q26E | AJ4: 2026E | AK4: 2027E | AL4: 2028E | AM4: 2029E | AN4: 2030E | AO4: 2031E | AP4: 2032E | AQ4: 2033E | AR4: 2034E | AS4: 2035E | AV4: Check
A6: Product Revenue | F6: 0 | G6: 0 | H6: 0 | I6: 0 | J6: =K6-SUM(G6:I6) -> 0 | K6: 0 | L6: 0 | M6: 0 | N6: 0 | O6: =P6-SUM(L6:N6) -> 0 | P6: 0 | Q6: 0 | R6: 0 | S6: 0 | T6: 0 | U6: =SUM(Q6:T6) -> 0 | V6: 0 | W6: 0 | X6: 0 | Y6: 0 | Z6: =REVENUE!Z19 -> #REF! | AC6: 0 | AD6: =REVENUE!AH19 -> 0 | AE6: =REVENUE!AI19 -> 0 | AF6: =REVENUE!AJ19 -> 0 | AG6: =REVENUE!AK19 -> 0 | AH6: =REVENUE!AL19 -> 0 | AI6: =REVENUE!AM19 -> 0 | AJ6: =REVENUE!AN19 -> 0 | AK6: =REVENUE!AO19 -> 0 | AL6: =REVENUE!AP19 -> 0 | AM6: =REVENUE!AQ19+REVENUE!AQ25 -> 16.880566 | AN6: =REVENUE!AR19+REVENUE!AR25 -> 128.13327 | AO6: =REVENUE!AS19+REVENUE!AS25 -> 348.00111 | AP6: =REVENUE!AT19+REVENUE!AT25 -> 670.96672 | AQ6: =REVENUE!AU19+REVENUE!AU25 -> 969.33752 | AR6: =REVENUE!AV19+REVENUE!AV25 -> 1235.6197 | AS6: =REVENUE!AW19+REVENUE!AW25 -> 1475.7246
A7: Collaboration revenue | F7: 22.499 | G7: 7.031 | H7: 0.528 | I7: 0.312 | J7: =K7-SUM(G7:I7) -> 0 | K7: 7.871 | L7: 0 | M7: 0 | N7: 0 | O7: =P7-SUM(L7:N7) -> 0 | P7: 0 | Q7: 0 | R7: 0 | S7: 0 | T7: 0 | U7: =SUM(Q7:T7) -> 0 | V7: 0 | W7: 0 | X7: 0 | Y7: 0 | Z7: =REVENUE!Z34 -> 0 | AC7: 0 | AD7: =REVENUE!AH34 -> 0 | AE7: =REVENUE!AI34 -> 0 | AF7: =REVENUE!AJ34 -> 0 | AG7: =REVENUE!AK34 -> 0 | AH7: =REVENUE!AL34 -> 0 | AI7: =REVENUE!AM34 -> 0 | AJ7: =REVENUE!AN34 -> 0 | AK7: =REVENUE!AO34 -> 0 | ... AS7: =REVENUE!AW34 -> 0
A8: Total Revenues | F8: =SUM(F6:F7) -> 22.499 | G8: =SUM(G6:G7) -> 7.031 | H8: =SUM(H6:H7) -> 0.528 | I8: =SUM(I6:I7) -> 0.312 | J8: =SUM(J6:J7) -> 0 | K8: =SUM(K6:K7) -> 7.871 | L8: =SUM(L6:L7) -> 0 | M8: =SUM(M6:M7) -> 0 | ... Z8: =SUM(Z6:Z7) -> #REF! | AC8: =SUM(AC6:AC7) -> 0 | AD8: =SUM(AD6:AD7) -> 0 | AE8: =SUM(AE6:AE7) -> 0 | AF8: =SUM(AF6:AF7) -> 0 | AG8: =SUM(AG6:AG7) -> 0 | AH8: =SUM(AH6:AH7) -> 0 | AI8: =SUM(AI6:AI7) -> 0 | AJ8: =SUM(AJ6:AJ7) -> 0 | ... AS8: =SUM(AS6:AS7) -> 1475.7246 | AV8: =AJ8-SUM(AF8:AI8) -> 0
A9: Consensus | Y9: =FactSet!#REF! -> #REF! | Z9: =FactSet!#REF! -> #REF! | AC9: =FactSet!P17 -> 0 | AD9: =FactSet!Q17 -> 0 | AE9: =FactSet!R17 -> 0 | AF9: =FactSet!S17 -> 0 | AG9: =FactSet!T17 -> 0 | AH9: =FactSet!U17 -> 0 | AI9: =FactSet!V17 -> 0 | AJ9: =FactSet!W17 -> 0 | AK9: =FactSet!X17 -> 0
A13: COGS | F13: 0 | G13: 0 | H13: 0 | I13: 0 | J13: =K13-SUM(G13:I13) -> 0 | K13: 0 | L13: 0 | M13: 0 | N13: 0 | O13: =P13-SUM(L13:N13) -> 0 | P13: 0 | Q13: 0 | R13: 0 | S13: 0 | T13: 0 | U13: =SUM(Q13:T13) -> 0 | V13: 0 | W13: 0 | X13: 0 | Y13: 0 | Z13: =OPEX!#REF! -> #REF! | AC13: 0 | AD13: 0 | AE13: =OPEX!O94 -> 0 | AF13: =OPEX!P94 -> 0 | AG13: =OPEX!Q94 -> 0 | AH13: =OPEX!R94 -> 0 | AI13: =OPEX!S94 -> 0 | AJ13: =OPEX!T94 -> 0 | AK13: =OPEX!U94 -> 0 | AL13: =OPEX!V94 -> 0 | ... AS13: =OPEX!AC94 -> 110.67934 | AV13: =AJ13-SUM(AF13:AI13) -> 0
A14: Gross Profit | F14: =F8-F13 -> 22.499 | G14: =G8-G13 -> 7.031 | H14: =H8-H13 -> 0.528 | I14: =I8-I13 -> 0.312 | J14: =J8-J13 -> 0 | K14: =K8-K13 -> 7.871 | L14: =L8-L13 -> 0 | M14: =M8-M13 -> 0 | ... Z14: =Z8-Z13 -> #REF! | AC14: =AC8-AC13 -> 0 | AD14: =AD8-AD13 -> 0 | AE14: =AE8-AE13 -> 0 | AF14: =AF8-AF13 -> 0 | AG14: =AG8-AG13 -> 0 | AH14: =AH8-AH13 -> 0 | AI14: =AI8-AI13 -> 0 | AJ14: =AJ8-AJ13 -> 0 | ... AS14: =AS8-AS13 -> 1365.0453
A16: SG&A | F16: 10.968 | G16: 3.674 | H16: 2.802 | I16: 5.598 | J16: =K16-SUM(G16:I16) -> 5.348 | K16: 17.422 | L16: 4.587 | M16: 4.904 | N16: 5.021 | O16: =P16-SUM(L16:N16) -> 5.126 | P16: 19.638 | Q16: 5.948 | R16: 6.376 | S16: 6.885 | T16: 7.003 | U16: =SUM(Q16:T16) -> 26.212 | V16: 7.199 | W16: 8.214 | X16: 9.453 | Y16: 9.508 | Z16: =OPEX!#REF! -> #REF! | AC16: 4.404 | AD16: 18.755 | AE16: 30.734 | AF16: =OPEX!P68 -> 13 | AG16: =OPEX!Q68 -> 14.1 | AH16: =OPEX!R68 -> 15 | AI16: =OPEX!S68 -> 15.2 | AJ16: =OPEX!T68 -> 57.3 | AK16: =OPEX!U68 -> 59.019 | AL16: =OPEX!V68 -> 81.646819 | AM16: =OPEX!W68 -> 116.54432 | ... AS16: =OPEX!AC68 -> 183.35219 | AV16: =AJ16-SUM(AF16:AI16) -> 0
A17: Consensus | Y17: =FactSet!#REF! -> #REF! | Z17: =FactSet!#REF! -> #REF! | AC17: =FactSet!P20 -> 4.4 | AD17: =FactSet!Q20 -> 18.8 | AE17: =FactSet!R20 -> 30.7 | AF17: =FactSet!S20 -> 8.5 | AG17: =FactSet!T20 -> 9.033334 | AH17: =FactSet!U20 -> 9.733334 | AI17: =FactSet!V20 -> 10.166667 | AJ17: =FactSet!W20 -> 37.433334 | AK17: =FactSet!X20 -> 42.1
A18: R&D | F18: 43.709 | G18: 9.498 | H18: 5.129 | I18: 5.003 | J18: =K18-SUM(G18:I18) -> 6.108 | K18: 25.738 | L18: 8.213 | M18: 12.388 | N18: 14.798 | O18: =P18-SUM(L18:N18) -> 20.514 | P18: 55.913 | Q18: 25.47 | R18: 29.479 | S18: 29.936 | T18: 36.742 | U18: =SUM(Q18:T18) -> 121.627 | V18: 36.038 | W18: 38.871 | X18: 50.127 | Y18: 48.719 | Z18: =OPEX!#REF! -> #REF! | AC18: 27.094 | AD18: 64.623 | AE18: 138.349 | AF18: =OPEX!P13 -> 42 | AG18: =OPEX!Q13 -> 40.5 | AH18: =OPEX!R13 -> 37.05 | AI18: =OPEX!S13 -> 39.55 | AJ18: =OPEX!T13 -> 159.1 | AK18: =OPEX!U13 -> 165.373 | AL18: =OPEX!V13 -> 182.04209 | AM18: =OPEX!W13 -> 164.86335 | ... AS18: =OPEX!AC13 -> 158.65991 | AV18: =AJ18-SUM(AF18:AI18) -> 0
A19: Consensus | Y19: =FactSet!#REF! -> #REF! | Z19: =FactSet!#REF! -> #REF! | AC19: =FactSet!P21 -> 27.1 | AD19: =FactSet!Q21 -> 64.6 | AE19: =FactSet!R21 -> 138.3 | AF19: =FactSet!S21 -> 35.1 | AG19: =FactSet!T21 -> 36.766666 | AH19: =FactSet!U21 -> 38.1 | AI19: =FactSet!V21 -> 40.766666 | AJ19: =FactSet!W21 -> 150.66667
A20: Acquired in-process research and development | F20: 0 | G20: 0 | H20: 0 | I20: 46.91 | J20: =K20-SUM(G20:I20) -> 0 | K20: 46.91 | L20: 0 | M20: 0 | N20: 0 | O20: =P20-SUM(L20:N20) -> 0 | P20: 0 | Q20: 0 | R20: 0 | S20: 0 | T20: 0 | U20: =SUM(Q20:T20) -> 0 | V20: 0 | W20: 0 | X20: 0 | Y20: =Z20-SUM(V20:X20) -> 0 | Z20: 0 | AC20: 0 | AD20: 0 | AE20: 0 | AF20: 0 | AG20: 0 | AH20: 0 | AI20: =AJ20-SUM(AF20:AH20) -> 0 | AJ20: 0 | AK20: 0 | AL20: =AK20 -> 0 | AM20: =AL20 -> 0 | AN20: =AM20 -> 0 | AO20: =AN20 -> 0 | AP20: =AO20 -> 0 | AQ20: =AP20 -> 0 | AR20: =AQ20 -> 0 | AS20: =AR20 -> 0
A22: Total Expenses | F22: =F16+F18+F20 -> 54.677 | G22: =G16+G18+G20 -> 13.172 | H22: =H16+H18+H20 -> 7.931 | I22: =I16+I18+I20 -> 57.511 | J22: =J16+J18+J20 -> 11.456 | K22: =K16+K18+K20 -> 90.07 | L22: =L16+L18+L20 -> 12.8 | M22: =M16+M18+M20 -> 17.292 | ... Z22: =Z16+Z18+Z20 -> #REF! | AC22: =AC16+AC18+AC20 -> 31.498 | AD22: =AD16+AD18+AD20 -> 83.378 | AE22: =AE16+AE18+AE20 -> 169.083 | AF22: =AF16+AF18+AF20 -> 55 | AG22: =AG16+AG18+AG20 -> 54.6 | AH22: =AH16+AH18+AH20 -> 52.05 | AI22: =AI16+AI18+AI20 -> 54.75 | AJ22: =AJ16+AJ18+AJ20 -> 216.4 | ... AS22: =AS16+AS18+AS20 -> 342.01209 | AV22: =AJ22-SUM(AF22:AI22) -> 0
A24: Operating Income | F24: =F8-F13-F16-F18-F20 -> -32.178 | G24: =G8-G13-G16-G18-G20 -> -6.141 | H24: =H8-H13-H16-H18-H20 -> -7.403 | I24: =I8-I13-I16-I18-I20 -> -57.199 | J24: =J8-J13-J16-J18-J20 -> -11.456 | K24: =K8-K13-K16-K18-K20 -> -82.199 | L24: =L8-L13-L16-L18-L20 -> -12.8 | M24: =M8-M13-M16-M18-M20 -> -17.292 | ... Z24: =Z8-Z13-Z16-Z18-Z20 -> #REF! | AC24: =AC8-AC13-AC16-AC18-AC20 -> -31.498 | AD24: =AD8-AD13-AD16-AD18-AD20 -> -83.378 | AE24: =AE8-AE13-AE16-AE18-AE20 -> -169.083 | AF24: =AF8-AF13-AF16-AF18-AF20 -> -55 | AG24: =AG8-AG13-AG16-AG18-AG20 -> -54.6 | AH24: =AH8-AH13-AH16-AH18-AH20 -> -52.05 | AI24: =AI8-AI13-AI16-AI18-AI20 -> -54.75 | AJ24: =AJ8-AJ13-AJ16-AJ18-AJ20 -> -216.4 | ... AS24: =AS8-AS13-AS16-AS18-AS20 -> 1023.0332
A26: Interest income | F26: 0.267 | G26: 0.047 | H26: 0.003 | I26: 0.023 | J26: =K26-SUM(G26:I26) -> 0.071 | K26: 0.144 | L26: 0.125 | M26: 0.12 | N26: 0.115 | O26: =P26-SUM(L26:N26) -> 0.107 | P26: 0.467 | Q26: 0.107 | R26: 0.272 | S26: 1.5 | T26: 2.11 | U26: =SUM(Q26:T26) -> 3.989 | V26: 2.268 | W26: 2.741 | X26: 4.198 | Y26: 3.87 | Z26: =SUM(V26:Y26) -> 13.077 | AC26: 1.549 | AD26: 2.471 | AE26: 5.518 | AF26: 2.5 | AG26: 2.5 | AH26: 2.5 | AI26: =AJ26-AH26-AG26-AF26 -> 2.5 | AJ26: 10 | AK26: 10 | AL26: =AK26*1.03 -> 10.3 | AM26: =AL26*1.03 -> 10.609 | AN26: =AM26*1.03 -> 10.92727 | AO26: =AN26*1.03 -> 11.255088 | AP26: =AO26*1.03 -> 11.592741 | AQ26: =AP26*1.03 -> 11.940523 | AR26: =AQ26*1.03 -> 12.298739 | AS26: =AR26*1.03 -> 12.667701
A27: Loss from equity method investment | F27: 0 | G27: 0 | H27: 0.007 | I27: 0.239 | J27: =K27-SUM(G27:I27) -> 0.533 | K27: 0.779 | L27: 0.604 | M27: 0.623 | N27: 0.62 | O27: =P27-SUM(L27:N27) -> 0.621 | P27: 2.468 | Q27: 0.677 | R27: 0.656 | S27: 0.259 | T27: 0.657 | U27: =SUM(Q27:T27) -> 2.249 | V27: 0.682 | W27: 0.268 | X27: 0 | Y27: -0.007 | Z27: =SUM(V27:Y27) -> 0.943 | AC27: 0 | AD27: 0 | AE27: 0 | AF27: 0 | AG27: 0 | AH27: 0 | AI27: =AJ27-AH27-AG27-AF27 -> 0 | AJ27: 0 | AK27: 0 | AL27: =AK27*1.03 -> 0 | AM27: =AL27*1.03 -> 0 | AN27: =AM27*1.03 -> 0 | AO27: =AN27*1.03 -> 0 | AP27: =AO27*1.03 -> 0 | AQ27: =AP27*1.03 -> 0 | AR27: =AQ27*1.03 -> 0 | AS27: =AR27*1.03 -> 0
A28: Other income, net | F28: 0 | G28: 0 | H28: 0 | I28: -0.509 | J28: =K28-SUM(G28:I28) -> -0.516 | K28: -1.025 | L28: 0.343 | M28: 0 | N28: 0 | O28: =P28-SUM(L28:N28) -> 0 | P28: 0.343 | Q28: 0 | R28: 0 | S28: 0 | T28: 1.36 | U28: =SUM(Q28:T28) -> 1.36 | V28: 1.7 | W28: 0 | X28: 0 | Y28: 0 | Z28: =SUM(V28:Y28) -> 1.7 | AC28: 0.531 | AD28: 1.359 | AE28: 2.413 | AF28: 0 | AG28: 0 | AH28: 0 | AI28: =AJ28-AH28-AG28-AF28 -> 0 | AJ28: 0 | AK28: 0 | AL28: =AK28 -> 0 | AM28: =AL28 -> 0 | AN28: =AM28 -> 0 | AO28: =AN28 -> 0 | AP28: =AO28 -> 0 | AQ28: =AP28 -> 0 | AR28: =AQ28 -> 0 | AS28: =AR28 -> 0
A29: Non-Operating Income | F29: =SUM(F26:F28) -> 0.267 | G29: =SUM(G26:G28) -> 0.047 | H29: =SUM(H26:H28) -> 0.01 | I29: =SUM(I26:I28) -> -0.247 | J29: =SUM(J26:J28) -> 0.088 | K29: =SUM(K26:K28) -> -0.102 | L29: =SUM(L26:L28) -> 1.072 | M29: =SUM(M26:M28) -> 0.743 | ... Z29: =SUM(Z26:Z28) -> 15.72 | AC29: =SUM(AC26:AC28) -> 2.08 | AD29: =SUM(AD26:AD28) -> 3.83 | AE29: =SUM(AE26:AE28) -> 7.931 | AF29: =SUM(AF26:AF28) -> 2.5 | AG29: =SUM(AG26:AG28) -> 2.5 | AH29: =SUM(AH26:AH28) -> 2.5 | AI29: =SUM(AI26:AI28) -> 2.5 | AJ29: =SUM(AJ26:AJ28) -> 10 | ... AS29: =SUM(AS26:AS28) -> 12.667701
A31: Pretax Income | F31: =F24+F29 -> -31.911 | G31: =G24+G29 -> -6.094 | H31: =H24+H29 -> -7.393 | I31: =I24+I29 -> -57.446 | J31: =J24+J29 -> -11.368 | K31: =K24+K29 -> -82.301 | L31: =L24+L29 -> -11.728 | M31: =M24+M29 -> -16.549 | ... T31: =T24+T29 -> -39.618 | U31: =SUM(Q31:T31) -> -140.241 | V31: =V24+V29 -> -38.587 | W31: =W24+W29 -> -44.076 | X31: =X24+X29 -> -55.382 | Y31: =Y24+Y29 -> -54.364 | Z31: =Z24+Z29 -> #REF! | AC31: =AC24+AC29 -> -29.418 | AD31: =AD24+AD29 -> -79.548 | AE31: =AE24+AE29 -> -161.152 | AF31: =AF24+AF29 -> -52.5 | AG31: =AG24+AG29 -> -52.1 | AH31: =AH24+AH29 -> -49.55 | AI31: =AI24+AI29 -> -52.25 | AJ31: =AJ24+AJ29 -> -206.4 | ... AS31: =AS24+AS29 -> 1035.7009 | AV31: =AJ31-SUM(AF31:AI31) -> 0
A32: Taxes | F32: 0 | G32: 0 | H32: 0 | I32: 0 | J32: =K32-SUM(G32:I32) -> 0 | K32: 0 | L32: 0 | M32: 0 | N32: 0 | O32: =P32-SUM(L32:N32) -> 0 | P32: 0 | Q32: 0 | R32: 0 | S32: 0 | T32: 0 | U32: =SUM(Q32:T32) -> 0 | V32: 0 | W32: 0 | X32: 0 | Y32: 0 | Z32: =SUM(V32:Y32) -> 0 | AC32: 0 | AD32: 0 | AE32: 0 | AF32: =AF31*AF33 -> 0 | AG32: =AG31*AG33 -> 0 | AH32: =AH31*AH33 -> 0 | AI32: =AI31*AI33 -> 0 | AJ32: =SUM(AF32:AI32) -> 0 | AK32: =AK31*AK33 -> 0 | AL32: =AL31*AL33 -> 0 | AM32: =AM31*AM33 -> 0 | AN32: =AN31*AN33 -> 0 | AO32: =AO31*AO33 -> 0 | AP32: =AP31*AP33 -> 15.877365 | AQ32: =AQ31*AQ33 -> 58.508113 | AR32: =AR31*AR33 -> 172.75574 | AS32: =AS31*AS33 -> 217.49718
A33: Tax Rate | F33: =F32/F31 -> 0 | G33: =G32/G31 -> 0 | H33: =H32/H31 -> 0 | I33: =I32/I31 -> 0 | J33: =J32/J31 -> 0 | K33: =K32/K31 -> 0 | L33: =L32/L31 -> 0 | M33: =M32/M31 -> 0 | ... Z33: =Z32/Z31 -> #REF! | AC33: =AC32/AC31 -> 0 | AD33: =AD32/AD31 -> 0 | AE33: =AE32/AE31 -> 0 | AF33: 0 | AG33: 0 | AH33: 0 | AI33: 0 | AJ33: =AJ32/AJ31 -> 0 | AK33: 0 | AL33: 0 | AM33: 0 | AN33: 0 | AO33: 0 | AP33: 0.05 | AQ33: 0.1 | AR33: 0.21 | AS33: =AR33 -> 0.21
A35: Net loss | F35: =F31-F32 -> -31.911 | G35: =G31-G32 -> -6.094 | H35: =H31-H32 -> -7.393 | I35: =I31-I32 -> -57.446 | J35: =J31-J32 -> -11.368 | K35: =K31-K32 -> -82.301 | L35: =L31-L32 -> -11.728 | M35: =M31-M32 -> -16.549 | ... T35: =T31-T32 -> -39.618 | U35: =SUM(Q35:T35) -> -140.241 | V35: =V31-V32 -> -38.587 | W35: =W31-W32 -> -44.076 | X35: =X31-X32 -> -55.382 | Y35: =Y31-Y32 -> -54.364 | Z35: =Z31-Z32 -> #REF! | AC35: =AC31-AC32 -> -29.418 | AD35: =AD31-AD32 -> -79.548 | AE35: =AE31-AE32 -> -161.152 | AF35: =AF31-AF32 -> -52.5 | AG35: =AG31-AG32 -> -52.1 | AH35: =AH31-AH32 -> -49.55 | AI35: =AI31-AI32 -> -52.25 | AJ35: =AJ31-AJ32 -> -206.4 | ... AS35: =AS31-AS32 -> 818.20368
A36: Unrealized (loss) gain on available-for-sale invesments | AC36: -0.004 | AD36: 0 | AE36: -0.391
A37: Comprehensive loss | AC37: =AC35+AC36 -> -29.422 | AD37: =AD35+AD36 -> -79.548 | AE37: =AE35+AE36 -> -161.543
A39: Shares - Weighted average | F39: 7.620082 | G39: 7.534187 | H39: 7.777487 | I39: 9.85053 | J39: =K39*4-SUM(G39:I39) -> 19.162824 | K39: 11.081257 | L39: 34.879296 | M39: 38.441729 | N39: 39.848943 | O39: =P39*4-SUM(L39:N39) -> 41.753284 | P39: 38.730813 | Q39: 45.105923 | R39: 49.388936 | S39: 69.576359 | T39: 70.489607 | U39: =#REF!/U40 -> #REF! | V39: 70.73495 | W39: 74.753269 | X39: 86.165951 | Y39: 86.730309 | Z39: 79.657942 | AC39: 0.791127 | AD39: 32.148977 | AE39: 8.680741 | AF39: =AD39+0.5 -> 32.648977 | AG39: =AF39+0.5 -> 33.148977 | AH39: =AG39+0.5 -> 33.648977 | AI39: =AH39+CF!D47 -> 47.648977 | AJ39: =AVERAGE(AF39:AI39) -> 36.773977 | AK39: =AI39+2+CF!E47 -> 56.605499 | AL39: =AK39+2+CF!F47 -> 58.605499 | AM39: =AL39+2+CF!G47 -> 66.915269 | AN39: =AM39+2+CF!H47 -> 68.915269 | AO39: =AN39+2+CF!I47 -> 70.915269 | AP39: =AO39+2+CF!J47 -> 72.915269 | AQ39: =AP39+2+CF!K47 -> 74.915269 | AR39: =AQ39+2+CF!L47 -> 76.915269 | AS39: =AR39+2+CF!M47 -> 78.915269
A40: EPS - Basic & diluted | F40: =#REF!/F39 -> #REF! | G40: =#REF!/G39 -> #REF! | H40: =#REF!/H39 -> #REF! | I40: =#REF!/I39 -> #REF! | J40: =#REF!/J39 -> #REF! | K40: =SUM(G40:J40) -> #REF! | L40: =#REF!/L39 -> #REF! | M40: =#REF!/M39 -> #REF! | N40: =#REF!/N39 -> #REF! | O40: =#REF!/O39 -> #REF! | P40: =SUM(L40:O40) -> #REF! | Q40: =#REF!/Q39 -> #REF! | R40: =#REF!/R39 -> #REF! | S40: =#REF!/S39 -> #REF! | T40: =#REF!/T39 -> #REF! | U40: =SUM(Q40:T40) -> #REF! | V40: =#REF!/V39 -> #REF! | W40: =#REF!/W39 -> #REF! | X40: =#REF!/X39 -> #REF! | Y40: =#REF!/Y39 -> #REF! | Z40: =#REF!/Z39 -> #REF! | AC40: =AC35/AC39 -> -37.184927 | AD40: =AD35/AD39 -> -2.4743556 | AE40: =AE35/AE39 -> -18.564314 | AF40: =AF35/AF39 -> -1.6080136 | AG40: =AG35/AG39 -> -1.5716925 | AH40: =AH35/AH39 -> -1.4725559 | AI40: =AI35/AI39 -> -1.0965608 | AJ40: =SUM(AF40:AI40) -> -5.7488229 | AK40: =AK35/AK39 -> -3.7874766 | AL40: =AL35/AL39 -> -4.3236371 | AM40: =AM35/AM39 -> -3.8135413 | AN40: =AN35/AN39 -> -2.369021 | AO40: =AO35/AO39 -> 0.3805463 | AP40: =AP35/AP39 -> 4.1372669 | AQ40: =AQ35/AQ39 -> 7.0289144 | AR40: =AR35/AR39 -> 8.449436 | AS40: =AS35/AS39 -> 10.368129 | AV40: =AJ40-SUM(AF40:AI40) -> 0
A41: Consensus | Y41: =FactSet!#REF! -> #REF! | Z41: =FactSet!#REF! -> #REF! | AC41: =FactSet!P8 -> -37.18 | AD41: =FactSet!Q8 -> -2.47 | AE41: =FactSet!R8 -> -18.56 | AF41: =FactSet!S8 -> -0.948 | AG41: =FactSet!T8 -> -0.99 | AH41: =FactSet!U8 -> -0.98 | AI41: =FactSet!V8 -> -1.028 | AJ41: =FactSet!W8 -> -3.946 | AK41: =FactSet!X8 -> -4.1
A42: Source: Company reports; Needham & Company, LLC estimates
A45: Margin Analysis | B45: =B4 -> 1Q19A | C45: =C4 -> 2Q19A | D45: =D4 -> 3Q19A | E45: =E4 -> 4Q19A | F45: =F4 -> 2019A | G45: =G4 -> 1Q20A | H45: =H4 -> 2Q20A | I45: =I4 -> 3Q20A | ... AS45: =AS4 -> 2035E
A47: Revenues | AJ47: 1 | AK47: 1 | AL47: 1 | AM47: 1 | AN47: 1 | AO47: 1 | AP47: 1 | AQ47: 1 | AR47: 1 | AS47: 1
A48: COGS | AJ48: =IFERROR(AJ13/AJ$8,"NM") -> NM | AK48: =IFERROR(AK13/AK$8,"NM") -> NM | AL48: =IFERROR(AL13/AL$8,"NM") -> NM | AM48: =IFERROR(AM13/AM$8,"NM") -> 0.075 | AN48: =IFERROR(AN13/AN$8,"NM") -> 0.075 | AO48: =IFERROR(AO13/AO$8,"NM") -> 0.075 | AP48: =IFERROR(AP13/AP$8,"NM") -> 0.075 | AQ48: =IFERROR(AQ13/AQ$8,"NM") -> 0.075 | ... AS48: =IFERROR(AS13/AS$8,"NM") -> 0.075
A49: Gross Margin | AJ49: =IFERROR(AJ14/AJ$8,"NM") -> NM | AK49: =IFERROR(AK14/AK$8,"NM") -> NM | AL49: =IFERROR(AL14/AL$8,"NM") -> NM | AM49: =IFERROR(AM14/AM$8,"NM") -> 0.925 | AN49: =IFERROR(AN14/AN$8,"NM") -> 0.925 | AO49: =IFERROR(AO14/AO$8,"NM") -> 0.925 | AP49: =IFERROR(AP14/AP$8,"NM") -> 0.925 | AQ49: =IFERROR(AQ14/AQ$8,"NM") -> 0.925 | ... AS49: =IFERROR(AS14/AS$8,"NM") -> 0.925
A51: SG&A | AJ51: =IFERROR(AJ16/AJ$8,"NM") -> NM | AK51: =IFERROR(AK16/AK$8,"NM") -> NM | AL51: =IFERROR(AL16/AL$8,"NM") -> NM | AM51: =IFERROR(AM16/AM$8,"NM") -> 6.9040526 | AN51: =IFERROR(AN16/AN$8,"NM") -> 1.0921676 | AO51: =IFERROR(AO16/AO$8,"NM") -> 0.46093888 | AP51: =IFERROR(AP16/AP$8,"NM") -> 0.24717241 | AQ51: =IFERROR(AQ16/AQ$8,"NM") -> 0.17690024 | ... AS51: =IFERROR(AS16/AS$8,"NM") -> 0.12424553
A52: R&D | AJ52: =IFERROR(AJ18/AJ$8,"NM") -> NM | AK52: =IFERROR(AK18/AK$8,"NM") -> NM | AL52: =IFERROR(AL18/AL$8,"NM") -> NM | AM52: =IFERROR(AM18/AM$8,"NM") -> 9.7664588 | AN52: =IFERROR(AN18/AN$8,"NM") -> 1.1922684 | AO52: =IFERROR(AO18/AO$8,"NM") -> 0.41885593 | AP52: =IFERROR(AP18/AP$8,"NM") -> 0.22183694 | AQ52: =IFERROR(AQ18/AQ$8,"NM") -> 0.15682933 | ... AS52: =IFERROR(AS18/AS$8,"NM") -> 0.10751322
A53: Operating Margin | AJ53: =IFERROR(AJ24/AJ$8,"NM") -> NM | AK53: =IFERROR(AK24/AK$8,"NM") -> NM | AL53: =IFERROR(AL24/AL$8,"NM") -> NM | AM53: =IFERROR(AM24/AM$8,"NM") -> -15.745511 | AN53: =IFERROR(AN24/AN$8,"NM") -> -1.359436 | AO53: =IFERROR(AO24/AO$8,"NM") -> 0.045205186 | AP53: =IFERROR(AP24/AP$8,"NM") -> 0.45599065 | AQ53: =IFERROR(AQ24/AQ$8,"NM") -> 0.59127042 | ... AS53: =IFERROR(AS24/AS$8,"NM") -> 0.69324125
A55: Pretax Margin | AJ55: =IFERROR(AJ31/AJ$8, "NM") -> NM | AK55: =IFERROR(AK31/AK$8, "NM") -> NM | AL55: =IFERROR(AL31/AL$8, "NM") -> NM | AM55: =IFERROR(AM31/AM$8, "NM") -> -15.117037 | AN55: =IFERROR(AN31/AN$8, "NM") -> -1.2741555 | AO55: =IFERROR(AO31/AO$8, "NM") -> 0.077547289 | AP55: =IFERROR(AP31/AP$8, "NM") -> 0.47326832 | AQ55: =IFERROR(AQ31/AQ$8, "NM") -> 0.60358865 | ... AS55: =IFERROR(AS31/AS$8, "NM") -> 0.7018253
A56: Net Margin | AJ56: =IFERROR(AJ35/AJ$8, "NM") -> NM | AK56: =IFERROR(AK35/AK$8, "NM") -> NM | AL56: =IFERROR(AL35/AL$8, "NM") -> NM | AM56: =IFERROR(AM35/AM$8, "NM") -> -15.117037 | AN56: =IFERROR(AN35/AN$8, "NM") -> -1.2741555 | AO56: =IFERROR(AO35/AO$8, "NM") -> 0.077547289 | AP56: =IFERROR(AP35/AP$8, "NM") -> 0.44960491 | AQ56: =IFERROR(AQ35/AQ$8, "NM") -> 0.54322979 | ... AS56: =IFERROR(AS35/AS$8, "NM") -> 0.55444199
A58: % Change | Z58: =Z4 -> 2023A | AA58: =AA4 -> 1Q25A | AB58: =AB4 -> 2Q25A | AC58: =AC4 -> 3Q25A | AD58: =AD4 -> 4Q25A | AE58: =AE4 -> 2025A | AF58: =AF4 -> 1Q26E | AG58: =AG4 -> 2Q26E | ... AS58: =AS4 -> 2035E
A60: Revenues | AK60: =IFERROR(AK8/AJ8-1,"NM") -> NM | AL60: =IFERROR(AL8/AK8-1,"NM") -> NM | AM60: =IFERROR(AM8/AL8-1,"NM") -> NM | AN60: =IFERROR(AN8/AM8-1,"NM") -> 6.5905793 | AO60: =IFERROR(AO8/AN8-1,"NM") -> 1.7159309 | AP60: =IFERROR(AP8/AO8-1,"NM") -> 0.92805912 | AQ60: =IFERROR(AQ8/AP8-1,"NM") -> 0.44468793 | AR60: =IFERROR(AR8/AQ8-1,"NM") -> 0.27470531 | AS60: =IFERROR(AS8/AR8-1,"NM") -> 0.19431943
A61: COGS | AK61: =IFERROR(AK13/AJ13-1, "NM") -> NM | AL61: =IFERROR(AL13/AK13-1, "NM") -> NM | AM61: =IFERROR(AM13/AL13-1, "NM") -> NM | AN61: =IFERROR(AN13/AM13-1, "NM") -> 6.5905793 | AO61: =IFERROR(AO13/AN13-1, "NM") -> 1.7159309 | AP61: =IFERROR(AP13/AO13-1, "NM") -> 0.92805912 | AQ61: =IFERROR(AQ13/AP13-1, "NM") -> 0.44468793 | AR61: =IFERROR(AR13/AQ13-1, "NM") -> 0.27470531 | AS61: =IFERROR(AS13/AR13-1, "NM") -> 0.19431943
A62: Gross Profit | AK62: =IFERROR(AK14/AJ14-1, "NM") -> NM | AL62: =IFERROR(AL14/AK14-1, "NM") -> NM | AM62: =IFERROR(AM14/AL14-1, "NM") -> NM | AN62: =IFERROR(AN14/AM14-1, "NM") -> 6.5905793 | AO62: =IFERROR(AO14/AN14-1, "NM") -> 1.7159309 | AP62: =IFERROR(AP14/AO14-1, "NM") -> 0.92805912 | AQ62: =IFERROR(AQ14/AP14-1, "NM") -> 0.44468793 | AR62: =IFERROR(AR14/AQ14-1, "NM") -> 0.27470531 | AS62: =IFERROR(AS14/AR14-1, "NM") -> 0.19431943
A64: SG&A | AK64: =AK16/AJ16-1 -> 0.03 | AL64: =AL16/AK16-1 -> 0.38339889 | AM64: =AM16/AL16-1 -> 0.42742016 | AN64: =AN16/AM16-1 -> 0.20077082 | AO64: =AO16/AN16-1 -> 0.14623259 | AP64: =AP16/AO16-1 -> 0.033896333 | AQ64: =AQ16/AP16-1 -> 0.033957021 | AR64: =AR16/AQ16-1 -> 0.034018418 | AS64: =AS16/AR16-1 -> 0.034080526
A65: R&D | AK65: =AK18/AJ18-1 -> 0.039428033 | AL65: =AL18/AK18-1 -> 0.10079693 | AM65: =AM18/AL18-1 -> -0.094366843 | AN65: =AN18/AM18-1 -> -0.073358325 | AO65: =AO18/AN18-1 -> -0.045866051 | AP65: =AP18/AO18-1 -> 0.021149977 | AQ65: =AQ18/AP18-1 -> 0.021333278 | AR65: =AR18/AQ18-1 -> 0.021514306 | AS65: =AS18/AR18-1 -> 0.021693024
A66: Operating Income | AK66: =AK24/AJ24-1 -> 0.036931608 | AL66: =AL24/AK24-1 -> 0.17512616 | AM66: =AM24/AL24-1 -> 0.0079799925 | AN66: =AN24/AM24-1 -> -0.34464454 | AO66: =AO24/AN24-1 -> -1.0903126 | AP66: =AP24/AO24-1 -> 18.448586 | AQ66: =AQ24/AP24-1 -> 0.87328673 | AR66: =AR24/AQ24-1 -> 0.41387233 | AS66: =AS24/AR24-1 -> 0.26246206
A68: Pretax Income | AK68: =AK31/AJ31-1 -> 0.03872093 | AL68: =AL31/AK31-1 -> 0.18189535 | AM68: =AM31/AL31-1 -> 0.0070849017 | AN68: =AN31/AM31-1 -> -0.36021998 | AO68: =AO31/AN31-1 -> -1.1652962 | AP68: =AP31/AO31-1 -> 10.766876 | AQ68: =AQ31/AP31-1 -> 0.84250075 | AR68: =AR31/AQ31-1 -> 0.40603814 | AS68: =AS31/AR31-1 -> 0.2589867
A69: Net Income | AK69: =AK35/AJ35-1 -> 0.03872093 | AL69: =AL35/AK35-1 -> 0.18189535 | AM69: =AM35/AL35-1 -> 0.0070849017 | AN69: =AN35/AM35-1 -> -0.36021998 | AO69: =AO35/AN35-1 -> -1.1652962 | AP69: =AP35/AO35-1 -> 10.178532 | AQ69: =AQ35/AP35-1 -> 0.74552703 | AR69: =AR35/AQ35-1 -> 0.23418904 | AS69: =AS35/AR35-1 -> 0.2589867
A70: Source: Company reports; Needham & Company, LLC estimates

Sheet OPEX
A1: MapLight Therapeutics - Operating Cost | AE1: =SOTP!R14 -> 37.175346
A2: ($ Millions, except EPS)
B3: =IS!B4 -> 1Q19A | C3: =IS!C4 -> 2Q19A | D3: =IS!D4 -> 3Q19A | E3: =IS!E4 -> 4Q19A | F3: =IS!F4 -> 2019A | G3: =IS!G4 -> 1Q20A | H3: =IS!H4 -> 2Q20A | I3: =IS!I4 -> 3Q20A | J3: =IS!J4 -> 4Q20A | K3: =IS!AA4 -> 1Q25A | L3: =IS!AB4 -> 2Q25A | M3: =IS!AC4 -> 3Q25A | N3: =IS!AD4 -> 4Q25A | O3: =IS!AE4 -> 2025A | P3: =IS!AF4 -> 1Q26E | Q3: =IS!AG4 -> 2Q26E | R3: =IS!AH4 -> 3Q26E | ... AC3: =IS!AS4 -> 2035E
A5: R&D - GAAP
A7: Clinical trial expenses | F7: 13.895 | G7: 1.668 | H7: 1.728 | I7: 0.794 | J7: 1.3 | M7: 11.915 | N7: 20 | O7: 53.461 | P7: 15 | Q7: 16 | R7: 18 | S7: 20 | T7: =SUM(P7:S7) -> 69 | U7: =T7*1.03 -> 71.07 | V7: 85 | W7: 65 | X7: 50 | Y7: 40 | Z7: =Y7 -> 40 | AA7: =Z7 -> 40 | AB7: =AA7 -> 40 | AC7: =AB7 -> 40
A8: Formulation and CMC expenses | F8: =F7-#REF!-#REF! -> #REF! | G8: =G7-#REF!-#REF! -> #REF! | H8: =H7-#REF!-#REF! -> #REF! | I8: =I7-#REF!-#REF! -> #REF! | J8: =J7-#REF!-#REF! -> #REF! | M8: 4.175 | N8: 8 | O8: 18.266 | P8: 5 | Q8: 4 | R8: 3 | S8: 3 | T8: =SUM(P8:S8) -> 15 | U8: 3 | V8: 3 | W8: =V8 -> 3 | X8: =W8 -> 3 | Y8: =X8 -> 3 | Z8: =Y8 -> 3 | AA8: =Z8 -> 3 | AB8: =AA8 -> 3 | AC8: =AB8 -> 3
A9: Preclinical research and discovery | F9: 2.443 | G9: 0.505 | H9: 0.351 | I9: -0.444 | J9: 0.3 | M9: 2.792 | N9: 5 | O9: 10.421 | P9: 12 | Q9: 10 | R9: 5 | S9: 5 | T9: =SUM(P9:S9) -> 32 | U9: =S9*4*1.03 -> 20.6 | V9: =U9*1.03 -> 21.218 | W9: =V9*1.03 -> 21.85454 | X9: =W9*1.03 -> 22.510176 | Y9: =X9*1.03 -> 23.185481 | Z9: =Y9*1.03 -> 23.881046 | AA9: =Z9*1.03 -> 24.597477 | AB9: =AA9*1.03 -> 25.335402 | AC9: =AB9*1.03 -> 26.095464
A11: Employee related expenses | G11: 0.237 | H11: 0.466 | I11: 1.876 | J11: =#REF!-G11-H11-I11 -> #REF! | M11: 7.043 | N11: 30 | O11: 51.062 | P11: 5 | Q11: 5 | R11: 5.05 | S11: 5.05 | T11: =SUM(P11:S11) -> 20.1 | U11: =T11*1.03 -> 20.703 | V11: =U11*1.03 -> 21.32409 | W11: =V11*1.03 -> 21.963813 | X11: =W11*1.03 -> 22.622727 | Y11: =X11*1.03 -> 23.301409 | Z11: =Y11*1.03 -> 24.000451 | AA11: =Z11*1.03 -> 24.720465 | AB11: =AA11*1.03 -> 25.462079 | AC11: =AB11*1.03 -> 26.225941
A12: Other expenses | F12: 12.197 | G12: 2.736 | H12: 1.102 | I12: 0.975 | J12: 1.2 | M12: 1.169 | N12: =N13-SUM(N7:N11) -> 1.623 | O12: 5.139 | P12: 5 | Q12: 5.5 | R12: 6 | S12: 6.5 | T12: =SUM(P12:S12) -> 23 | U12: 50 | V12: =U12*1.03 -> 51.5 | W12: =V12*1.03 -> 53.045 | X12: =W12*1.03 -> 54.63635 | Y12: =X12*1.03 -> 56.275441 | Z12: =Y12*1.03 -> 57.963704 | AA12: =Z12*1.03 -> 59.702615 | AB12: =AA12*1.03 -> 61.493693 | AC12: =AB12*1.03 -> 63.338504
A13: Total R&D - GAAP per IS | B13: =IS!B18 -> 0 | C13: =IS!C18 -> 0 | D13: =IS!D18 -> 0 | E13: =IS!E18 -> 0 | F13: =IS!F18 -> 43.709 | G13: =IS!G18 -> 9.498 | H13: =IS!H18 -> 5.129 | I13: =IS!I18 -> 5.003 | J13: =IS!J18 -> 6.108 | M13: =SUM(M7,M8,M9,M11:M12) -> 27.094 | N13: =IS!AD18 -> 64.623 | O13: =SUM(O7,O8,O9,O11:O12) -> 138.349 | P13: =SUM(P7,P8,P9,P11:P12) -> 42 | Q13: =SUM(Q7,Q8,Q9,Q11:Q12) -> 40.5 | R13: =SUM(R7,R8,R9,R11:R12) -> 37.05 | S13: =SUM(S7,S8,S9,S11:S12) -> 39.55 | T13: =SUM(T7,T8,T9,T11:T12) -> 159.1 | U13: =SUM(U7,U8,U9,U11:U12) -> 165.373 | V13: =SUM(V7,V8,V9,V11:V12) -> 182.04209 | ... AC13: =SUM(AC7,AC8,AC9,AC11:AC12) -> 158.65991
A14: Consensus | M14: =FactSet!P21 -> 27.1 | N14: =FactSet!Q21 -> 64.6 | O14: =FactSet!R21 -> 138.3 | P14: =FactSet!S21 -> 35.1 | Q14: =FactSet!T21 -> 36.766666 | R14: =FactSet!U21 -> 38.1 | S14: =FactSet!V21 -> 40.766666 | T14: =FactSet!W21 -> 150.66667 | U14: =FactSet!X21 -> 175
A15: Check | F15: =SUM(F7,F9,F11,#REF!,F12) - F13 -> #REF! | G15: =SUM(G7,G9,G11,#REF!,G12) - G13 -> #REF! | H15: =SUM(H7,H9,H11,#REF!,H12) - H13 -> #REF! | I15: =SUM(I7,I9,I11,#REF!,I12) - I13 -> #REF! | J15: =SUM(J7,J9,J11,#REF!,J12) - J13 -> #REF! | M15: =SUM(M7,M9,M11,M8,M12) - M13 -> 0 | N15: =SUM(N7,N9,N11,N8,N12) - N13 -> 0 | O15: =SUM(O7,O9,O11,O8,O12) - O13 -> 0 | P15: =SUM(P7,P9,P11,P8,P12) - P13 -> 0 | Q15: =SUM(Q7,Q9,Q11,Q8,Q12) - Q13 -> 0 | R15: =SUM(R7,R9,R11,R8,R12) - R13 -> 0 | S15: =SUM(S7,S9,S11,S8,S12) - S13 -> 0 | T15: =SUM(T7,T9,T11,T8,T12) - T13 -> 0 | ... AC15: =SUM(AC7,AC9,AC11,AC8,AC12) - AC13 -> 0
A17: Rep - Sales - ML-007 - Schizophrenia | P17: 0.55 | Q17: =P17 -> 0.55 | R17: =Q17 -> 0.55 | S17: =R17 -> 0.55 | U17: 0.45 | V17: =U17 -> 0.45 | W17: 0.2 | X17: =W17 -> 0.2 | Y17: =X17 -> 0.2 | Z17: =Y17 -> 0.2 | AA17: =Z17 -> 0.2 | AB17: =AA17 -> 0.2 | AC17: =AB17 -> 0.2
A18: Rep - Sales - ML-007 - AD Psychosis | P18: 0.35 | Q18: =P18 -> 0.35 | R18: =Q18 -> 0.35 | S18: =R18 -> 0.35 | U18: 0.45 | V18: =U18 -> 0.45 | W18: 0.55 | X18: =W18 -> 0.55 | Y18: =X18 -> 0.55 | Z18: =Y18 -> 0.55 | AA18: =Z18 -> 0.55 | AB18: =AA18 -> 0.55 | AC18: =AB18 -> 0.55
A19: Rep - Sales - ML-004- ASD | P19: =P20-P18-P17 -> 0.1 | Q19: =Q20-Q18-Q17 -> 0.1 | R19: =R20-R18-R17 -> 0.1 | S19: =S20-S18-S17 -> 0.1 | U19: =U20-U18-U17 -> 0.1 | V19: =V20-V18-V17 -> 0.1 | W19: =W20-W18-W17 -> 0.25 | X19: =X20-X18-X17 -> 0.25 | Y19: =Y20-Y18-Y17 -> 0.25 | Z19: =Z20-Z18-Z17 -> 0.25 | AA19: =AA20-AA18-AA17 -> 0.25 | AB19: =AB20-AB18-AB17 -> 0.25 | AC19: =AC20-AC18-AC17 -> 0.25
P20: 1 | Q20: 1 | R20: 1 | S20: 1 | U20: 1 | V20: 1 | W20: 1 | X20: 1 | Y20: 1 | Z20: 1 | AA20: 1 | AB20: 1 | AC20: 1
A22: Rep - Sales - ML-007 - Schizophrenia | P22: =P17*P$7 -> 8.25 | Q22: =Q17*Q$7 -> 8.8 | R22: =R17*R$7 -> 9.9 | S22: =S17*S$7 -> 11 | T22: =SUM(P22:S22) -> 37.95 | U22: =U17*U$7 -> 31.9815 | V22: =V17*V$7 -> 38.25 | W22: =W17*W$7 -> 13 | X22: =X17*X$7 -> 10 | Y22: =Y17*Y$7 -> 8 | Z22: =Z17*Z$7 -> 8 | AA22: =AA17*AA$7 -> 8 | AB22: =AB17*AB$7 -> 8 | AC22: =AC17*AC$7 -> 8
A23: Rep - Sales - ML-007 - AD Psychosis | P23: =P18*P$7 -> 5.25 | Q23: =Q18*Q$7 -> 5.6 | R23: =R18*R$7 -> 6.3 | S23: =S18*S$7 -> 7 | T23: =SUM(P23:S23) -> 24.15 | U23: =U18*U$7 -> 31.9815 | V23: =V18*V$7 -> 38.25 | W23: =W18*W$7 -> 35.75 | X23: =X18*X$7 -> 27.5 | Y23: =Y18*Y$7 -> 22 | Z23: =Z18*Z$7 -> 22 | AA23: =AA18*AA$7 -> 22 | AB23: =AB18*AB$7 -> 22 | AC23: =AC18*AC$7 -> 22
A24: Rep - Sales - ML-004- ASD | P24: =P19*P$7 -> 1.5 | Q24: =Q19*Q$7 -> 1.6 | R24: =R19*R$7 -> 1.8 | S24: =S19*S$7 -> 2 | T24: =SUM(P24:S24) -> 6.9 | U24: =U19*U$7 -> 7.107 | V24: =V19*V$7 -> 8.5 | W24: =W19*W$7 -> 16.25 | X24: =X19*X$7 -> 12.5 | Y24: =Y19*Y$7 -> 10 | Z24: =Z19*Z$7 -> 10 | AA24: =AA19*AA$7 -> 10 | AB24: =AB19*AB$7 -> 10 | AC24: =AC19*AC$7 -> 10
P25: =SUM(P22:P24) -> 15 | Q25: =SUM(Q22:Q24) -> 16 | R25: =SUM(R22:R24) -> 18 | S25: =SUM(S22:S24) -> 20 | T25: =SUM(T22:T24) -> 69 | U25: =SUM(U22:U24) -> 71.07 | V25: =SUM(V22:V24) -> 85 | W25: =SUM(W22:W24) -> 65 | ... AC25: =SUM(AC22:AC24) -> 40
B27: =B3 -> 1Q19A | C27: =C3 -> 2Q19A | D27: =D3 -> 3Q19A | E27: =E3 -> 4Q19A | F27: =F3 -> 2019A | G27: =G3 -> 1Q20A | H27: =H3 -> 2Q20A | I27: =I3 -> 3Q20A | J27: =J3 -> 4Q20A | M27: =M3 -> 3Q25A | N27: =N3 -> 4Q25A | O27: =O3 -> 2025A | P27: =P3 -> 1Q26E | Q27: =Q3 -> 2Q26E | R27: =R3 -> 3Q26E | S27: =S3 -> 4Q26E | T27: =T3 -> 2026E | ... AC27: =AC3 -> 2035E
A29: G&A - GAAP
A31: Professional and other fees | B31: =B33-B32 -> -0.432 | C31: =C33-C32 -> -1.103 | D31: =D33-D32 -> -1.302 | E31: =E33-E32 -> 2.837 | G31: =G33-G32 -> 3.142 | H31: =H33-H32 -> 2.398 | I31: =I33-I32 -> 3.962 | J31: =J33-J32 -> #REF! | M31: 2 | N31: 7 | O31: 9.046 | P31: 8 | Q31: 9 | R31: 10 | S31: 10 | T31: =SUM(P31:S31) -> 37 | U31: =T31*1.03 -> 38.11 | V31: =U31*1.03 -> 39.2533 | W31: =V31*1.03 -> 40.430899 | X31: =W31*1.03 -> 41.643826 | Y31: =X31*1.03 -> 42.893141 | Z31: =Y31*1.03 -> 44.179935 | AA31: =Z31*1.03 -> 45.505333 | AB31: =AA31*1.03 -> 46.870493 | AC31: =AB31*1.03 -> 48.276608
A32: Employee related expenses | B32: 0.432 | C32: 1.103 | D32: 1.302 | E32: =F32-D32-C32-B32 -> -2.837 | G32: 0.532 | H32: 0.404 | I32: 1.636 | J32: =#REF!-G32-H32-I32 -> #REF! | M32: 1.904 | N32: =N33-N31 -> 11.755 | O32: 21.688 | P32: 5 | Q32: 5.1 | R32: 5 | S32: 5.2 | T32: =SUM(P32:S32) -> 20.3 | U32: =T32*1.03 -> 20.909 | V32: =U32*1.03 -> 21.53627 | W32: =V32*1.03 -> 22.182358 | X32: =W32*1.03 -> 22.847829 | Y32: =X32*1.03 -> 23.533264 | Z32: =Y32*1.03 -> 24.239262 | AA32: =Z32*1.03 -> 24.966439 | AB32: =AA32*1.03 -> 25.715433 | AC32: =AB32*1.03 -> 26.486896
A33: Total G&A - GAAP per IS | B33: =B68-B66 -> 0 | C33: =C68-C66 -> 0 | D33: =D68-D66 -> 0 | E33: =E68-E66 -> 0 | F33: =F68-F66 -> 10.968 | G33: =G68-G66 -> 3.674 | H33: =H68-H66 -> 2.802 | I33: =I68-I66 -> 5.598 | J33: =J68-J66 -> 5.348 | M33: =M68-M66 -> 4.404 | N33: =N68 -> 18.755 | O33: =SUM(O31:O32) -> 30.734 | P33: =SUM(P31:P32) -> 13 | Q33: =SUM(Q31:Q32) -> 14.1 | R33: =SUM(R31:R32) -> 15 | S33: =SUM(S31:S32) -> 15.2 | T33: =SUM(T31:T32) -> 57.3 | U33: =SUM(U31:U32) -> 59.019 | V33: =SUM(V31:V32) -> 60.78957 | ... AC33: =SUM(AC31:AC32) -> 74.763503
A35: S&M - GAAP
A37: Sales & Marketing
A39: Rep - Sales - ML-007 - Schizophrenia | V39: 25 | W39: 60 | X39: =W39 -> 60 | Y39: =X39 -> 60 | Z39: =Y39 -> 60 | AA39: =Z39 -> 60 | AB39: =AA39 -> 60 | AC39: =AB39 -> 60
A40: Rep - Sales - ML-007 - AD Psychosis | W40: 100 | X40: 150 | Y40: 200 | Z40: =Y40 -> 200 | AA40: =Z40 -> 200 | AB40: =AA40 -> 200 | AC40: =AB40 -> 200
A41: Rep - Sales - ML-004- ASD | W41: 0 | X41: 0 | Y41: =X41 -> 0 | Z41: =Y41 -> 0 | AA41: =Z41 -> 0 | AB41: =AA41 -> 0 | AC41: =AB41 -> 0
A42: Rep - Sales - Unallocated
A43: Total Reps | O43: =SUM(O39:O42) -> 0 | U43: =SUM(U39:U42) -> 0 | V43: =SUM(V39:V42) -> 25 | W43: =SUM(W39:W42) -> 160 | X43: =SUM(X39:X42) -> 210 | Y43: =SUM(Y39:Y42) -> 260 | Z43: =SUM(Z39:Z42) -> 260 | AA43: =SUM(AA39:AA42) -> 260 | AB43: =SUM(AB39:AB42) -> 260 | AC43: =SUM(AC39:AC42) -> 260
A45: Cost per Rep | O45: 290000 | P45: =O45*1.03 -> 298700 | Q45: =P45 -> 298700 | R45: =Q45 -> 298700 | S45: =R45 -> 298700 | T45: =O45*1.03 -> 298700 | U45: =T45*1.03 -> 307661 | V45: =U45*1.03 -> 316890.83 | W45: =V45*1.03 -> 326397.55 | X45: =W45*1.03 -> 336189.48 | Y45: =X45*1.03 -> 346275.17 | Z45: =Y45*1.03 -> 356663.42 | AA45: =Z45*1.03 -> 367363.32 | AB45: =AA45*1.03 -> 378384.22 | AC45: =AB45*1.03 -> 389735.75
A47: Cost - Sales - ML-007 - Schizophrenia | O47: =O39*O$45/10^6 -> 0 | P47: =P39*P$45/10^6 -> 0 | Q47: =Q39*Q$45/10^6 -> 0 | R47: =R39*R$45/10^6 -> 0 | S47: =S39*S$45/10^6 -> 0 | T47: =SUM(P47:S47) -> 0 | U47: =U39*U$45/10^6 -> 0 | V47: =V39*V$45/10^6 -> 7.9222708 | W47: =W39*W$45/10^6 -> 19.583853 | X47: =X39*X$45/10^6 -> 20.171369 | Y47: =Y39*Y$45/10^6 -> 20.77651 | Z47: =Z39*Z$45/10^6 -> 21.399805 | AA47: =AA39*AA$45/10^6 -> 22.041799 | AB47: =AB39*AB$45/10^6 -> 22.703053 | AC47: =AC39*AC$45/10^6 -> 23.384145
A48: Cost - Sales - ML-007 - AD Psychosis | O48: =O40*O$45/10^6 -> 0 | P48: =P40*P$45/10^6 -> 0 | Q48: =Q40*Q$45/10^6 -> 0 | R48: =R40*R$45/10^6/4 -> 0 | S48: =S40*S$45/10^6/4 -> 0 | T48: =SUM(P48:S48) -> 0 | U48: =U40*U$45/10^6 -> 0 | V48: =V40*V$45/10^6 -> 0 | W48: =W40*W$45/10^6 -> 32.639755 | X48: =X40*X$45/10^6 -> 50.428422 | Y48: =Y40*Y$45/10^6 -> 69.255033 | Z48: =Z40*Z$45/10^6 -> 71.332684 | AA48: =AA40*AA$45/10^6 -> 73.472665 | AB48: =AB40*AB$45/10^6 -> 75.676845 | AC48: =AC40*AC$45/10^6 -> 77.94715
A49: Cost - Sales - ML-004 - ASD | O49: =O41*O$45/10^6 -> 0 | P49: =P41*P$45/10^6 -> 0 | Q49: =Q41*Q$45/10^6 -> 0 | R49: =R41*R$45/10^6/4 -> 0 | S49: =S41*S$45/10^6/4 -> 0 | T49: =SUM(P49:S49) -> 0 | U49: =U41*U$45/10^6 -> 0 | V49: =V41*V$45/10^6 -> 0 | W49: =W41*W$45/10^6 -> 0 | X49: =X41*X$45/10^6 -> 0 | Y49: =Y41*Y$45/10^6 -> 0 | Z49: =Z41*Z$45/10^6 -> 0 | AA49: =AA41*AA$45/10^6 -> 0 | AB49: =AB41*AB$45/10^6 -> 0 | AC49: =AC41*AC$45/10^6 -> 0
A50: Cost - Sales - Unallocated | O50: =O42*O$45 -> 0 | P50: =P42*P$45 -> 0 | Q50: =Q42*Q$45 -> 0 | R50: =R42*R$45 -> 0 | S50: =S42*S$45 -> 0 | T50: =SUM(P50:S50) -> 0 | U50: =U42*U$45 -> 0 | V50: =V42*V$45 -> 0 | W50: =W42*W$45 -> 0 | X50: =X42*X$45 -> 0 | Y50: =Y42*Y$45 -> 0 | Z50: =Z42*Z$45 -> 0 | AA50: =AA42*AA$45 -> 0 | AB50: =AB42*AB$45 -> 0 | AC50: =AC42*AC$45 -> 0
A51: Total Salesforce Costs | O51: =SUM(O47:O50) -> 0 | P51: =SUM(P47:P50) -> 0 | Q51: =SUM(Q47:Q50) -> 0 | R51: =SUM(R47:R50) -> 0 | S51: =SUM(S47:S50) -> 0 | T51: =SUM(P51:S51) -> 0 | U51: =SUM(U47:U50) -> 0 | V51: =SUM(V47:V50) -> 7.9222708 | W51: =SUM(W47:W50) -> 52.223609 | X51: =SUM(X47:X50) -> 70.599791 | Y51: =SUM(Y47:Y50) -> 90.031543 | Z51: =SUM(Z47:Z50) -> 92.732489 | AA51: =SUM(AA47:AA50) -> 95.514464 | AB51: =SUM(AB47:AB50) -> 98.379898 | AC51: =SUM(AC47:AC50) -> 101.3313
A53: A&P
A54: A&P Cost - Sales - ML-007 - Schizophrenia | V54: 30 | W54: 50 | X54: =W54+10 -> 60 | Y54: =X54*1.03 -> 61.8 | Z54: =Y54*1.03 -> 63.654 | AA54: =Z54*1.03 -> 65.56362 | AB54: =AA54*1.03 -> 67.530529 | AC54: =AB54*1.03 -> 69.556444
A55: A&P Cost - Sales - ML-007 - AD Psychosis | W55: 30 | X55: 75 | Y55: 125 | Z55: =Y55*1.05 -> 131.25 | AA55: =Z55*1.05 -> 137.8125 | AB55: =AA55*1.05 -> 144.70312 | AC55: =AB55*1.05 -> 151.93828
A56: A&P Cost - Sales - ML-004 - ASD | X56: =W56*1.03 -> 0 | Y56: =X56*1.03 -> 0 | Z56: =Y56*1.03 -> 0 | AA56: =Z56*1.03 -> 0 | AB56: =AA56*1.03 -> 0 | AC56: =AB56*1.03 -> 0
A57: A&P Cost - Sales - Unallocated
A58: Total A&P | O58: =SUM(O54:O57) -> 0 | P58: =SUM(P54:P57) -> 0 | Q58: =SUM(Q54:Q57) -> 0 | R58: =SUM(R54:R57) -> 0 | S58: =SUM(S54:S57) -> 0 | T58: =SUM(T54:T57) -> 0 | U58: =SUM(U54:U57) -> 0 | V58: =SUM(V54:V57) -> 30 | ... AC58: =SUM(AC54:AC57) -> 221.49473
A60: PoS Adj. SG&A | AE60: PoS
A61: Cost - ML-007 - Schizophrenia | O61: =(O47+O54)*$AE61 -> 0 | P61: =(P47+P54)*$AE61 -> 0 | Q61: =(Q47+Q54)*$AE61 -> 0 | R61: =(R47+R54)*$AE61 -> 0 | S61: =(S47+S54)*$AE61 -> 0 | T61: =(T47+T54)*$AE61 -> 0 | U61: =(U47+U54)*$AE61 -> 0 | V61: =(V47+V54)*$AE61 -> 20.857249 | ... AC61: =(AC47+AC54)*$AE61 -> 51.117324 | AE61: =REVENUE!AY7 -> 0.55
A62: Cost - ML-007 - AD Psychosis | O62: =(O48+O55)*$AE62 -> 0 | P62: =(P48+P55)*$AE62 -> 0 | Q62: =(Q48+Q55)*$AE62 -> 0 | R62: =(R48+R55)*$AE62 -> 0 | S62: =(S48+S55)*$AE62 -> 0 | T62: =(T48+T55)*$AE62 -> 0 | U62: =(U48+U55)*$AE62 -> 0 | V62: =(V48+V55)*$AE62 -> 0 | ... AC62: =(AC48+AC55)*$AE62 -> 57.471358 | AE62: =REVENUE!AY12 -> 0.25
A63: Cost - ML-004 - ASD | O63: =(O49+O56)*$AE63 -> 0 | P63: =(P49+P56)*$AE63 -> 0 | Q63: =(Q49+Q56)*$AE63 -> 0 | R63: =(R49+R56)*$AE63 -> 0 | S63: =(S49+S56)*$AE63 -> 0 | T63: =(T49+T56)*$AE63 -> 0 | U63: =(U49+U56)*$AE63 -> 0 | V63: =(V49+V56)*$AE63 -> 0 | ... AC63: =(AC49+AC56)*$AE63 -> 0 | AE63: =REVENUE!AY24 -> 0.05
A64: Unallocated | O64: =(O50+O57)*$AE64 -> 0 | P64: =(P50+P57)*$AE64 -> 0 | Q64: =(Q50+Q57)*$AE64 -> 0 | R64: =(R50+R57)*$AE64 -> 0 | S64: =(S50+S57)*$AE64 -> 0 | T64: =(T50+T57)*$AE64 -> 0 | U64: =(U50+U57)*$AE64 -> 0 | V64: =(V50+V57)*$AE64 -> 0 | ... AC64: =(AC50+AC57)*$AE64 -> 0 | AE64: 1
A66: Total PoS Adj. S&M - GAAP per IS | M66: =SUM(M61:M64) -> 0 | N66: =SUM(N61:N64) -> 0 | O66: =SUM(O61:O64) -> 0 | P66: =SUM(P61:P64) -> 0 | Q66: =SUM(Q61:Q64) -> 0 | R66: =SUM(R61:R64) -> 0 | S66: =SUM(S61:S64) -> 0 | T66: =SUM(T61:T64) -> 0 | ... AC66: =SUM(AC61:AC64) -> 108.58868
A68: Total SG&A | B68: =IS!B16 -> 0 | C68: =IS!C16 -> 0 | D68: =IS!D16 -> 0 | E68: =IS!E16 -> 0 | F68: =IS!F16 -> 10.968 | G68: =IS!G16 -> 3.674 | H68: =IS!H16 -> 2.802 | I68: =IS!I16 -> 5.598 | J68: =IS!J16 -> 5.348 | M68: =IS!AC16 -> 4.404 | N68: =IS!AD16 -> 18.755 | O68: =SUM(O33,O66) -> 30.734 | P68: =SUM(P33,P66) -> 13 | Q68: =SUM(Q33,Q66) -> 14.1 | R68: =SUM(R33,R66) -> 15 | S68: =SUM(S33,S66) -> 15.2 | T68: =SUM(T33,T66) -> 57.3 | U68: =SUM(U33,U66) -> 59.019 | V68: =SUM(V33,V66) -> 81.646819 | ... AC68: =SUM(AC33,AC66) -> 183.35219
A69: Consensus | M69: =FactSet!P20 -> 4.4 | N69: =FactSet!Q20 -> 18.8 | O69: =FactSet!R20 -> 30.7 | P69: =FactSet!S20 -> 8.5 | Q69: =FactSet!T20 -> 9.033334 | R69: =FactSet!U20 -> 9.733334 | S69: =FactSet!V20 -> 10.166667 | T69: =FactSet!W20 -> 37.433334 | U69: =FactSet!X20 -> 42.1
B71: =B3 -> 1Q19A | C71: =C3 -> 2Q19A | D71: =D3 -> 3Q19A | E71: =E3 -> 4Q19A | F71: =F3 -> 2019A | G71: =G3 -> 1Q20A | H71: =H3 -> 2Q20A | I71: =I3 -> 3Q20A | J71: =J3 -> 4Q20A | M71: =M3 -> 3Q25A | N71: =N3 -> 4Q25A | O71: =O3 -> 2025A | P71: =P3 -> 1Q26E | Q71: =Q3 -> 2Q26E | R71: =R3 -> 3Q26E | S71: =S3 -> 4Q26E | T71: =T3 -> 2026E | ... AC71: =AC3 -> 2035E
A73: GM
A75: Gross Margin
A76: ML-007 - Schizophrenia | O76: 0 | P76: 0.925 | Q76: =P76 -> 0.925 | R76: =Q76 -> 0.925 | S76: =R76 -> 0.925 | T76: =IFERROR(T83/T97,"NM") -> NM | U76: =S76 -> 0.925 | V76: =U76 -> 0.925 | W76: =V76 -> 0.925 | X76: =W76 -> 0.925 | Y76: =X76 -> 0.925 | Z76: =Y76 -> 0.925 | AA76: =Z76 -> 0.925 | AB76: =AA76 -> 0.925 | AC76: =AB76 -> 0.925
A77: ML-007 - AD Psychosis | O77: 0 | P77: 0.925 | Q77: =P77 -> 0.925 | R77: =Q77 -> 0.925 | S77: =R77 -> 0.925 | T77: =IFERROR(T84/T98,"NM") -> NM | U77: =S77 -> 0.925 | V77: =U77 -> 0.925 | W77: =V77 -> 0.925 | X77: =W77 -> 0.925 | Y77: =X77 -> 0.925 | Z77: =Y77 -> 0.925 | AA77: =Z77 -> 0.925 | AB77: =AA77 -> 0.925 | AC77: =AB77 -> 0.925
A78: ML-004 - ASD | O78: 0 | P78: 0.925 | Q78: =P78 -> 0.925 | R78: =Q78 -> 0.925 | S78: =R78 -> 0.925 | T78: =IFERROR(T85/T99,"NM") -> NM | U78: =S78 -> 0.925 | V78: =U78 -> 0.925 | W78: =V78 -> 0.925 | X78: =W78 -> 0.925 | Y78: =X78 -> 0.925 | Z78: =Y78 -> 0.925 | AA78: =Z78 -> 0.925 | AB78: =AA78 -> 0.925 | AC78: =AB78 -> 0.925
A79: Collaboration | O79: 0 | P79: 1 | Q79: =P79 -> 1 | R79: =Q79 -> 1 | S79: =R79 -> 1 | T79: =IFERROR(T86/T100,"NM") -> NM | U79: =S79 -> 1 | V79: =U79 -> 1 | W79: =V79 -> 1 | X79: =W79 -> 1 | Y79: =X79 -> 1 | Z79: =Y79 -> 1 | AA79: =Z79 -> 1 | AB79: =AA79 -> 1 | AC79: =AB79 -> 1
A80: Total GM
A82: Gross profit
A83: ML-007 - Schizophrenia | O83: 0 | P83: =P76*P97 -> 0 | Q83: =Q76*Q97 -> 0 | R83: =R76*R97 -> 0 | S83: =S76*S97 -> 0 | T83: =SUM(P83:S83) -> 0 | U83: =U76*U97 -> 0 | V83: =V76*V97 -> 0 | W83: =W76*W97 -> 15.614524 | X83: =X76*X97 -> 95.092448 | Y83: =Y76*Y97 -> 239.32095 | Z83: =Z76*Z97 -> 388.16387 | AA83: =AA76*AA97 -> 534.24727 | AB83: =AB76*AB97 -> 666.33725 | AC83: =AC76*AC97 -> 786.37899
A84: ML-007 - AD Psychosis | O84: 0 | P84: =P77*P98 -> 0 | Q84: =Q77*Q98 -> 0 | R84: =R77*R98 -> 0 | S84: =S77*S98 -> 0 | T84: =SUM(P84:S84) -> 0 | U84: =U77*U98 -> 0 | V84: =V77*V98 -> 0 | W84: =W77*W98 -> 0 | X84: =X77*X98 -> 23.43083 | Y84: =Y77*Y98 -> 79.850583 | Z84: =Z77*Z98 -> 222.98211 | AA84: =AA77*AA98 -> 346.99439 | AB84: =AB77*AB98 -> 456.03958 | AC84: =AC77*AC98 -> 553.50926
A85: ML-004 - ASD | O85: 0 | P85: =P78*P99 -> 0 | Q85: =Q78*Q99 -> 0 | R85: =R78*R99 -> 0 | S85: =S78*S99 -> 0 | T85: =SUM(P85:S85) -> 0 | U85: =U78*U99 -> 0 | V85: =V78*V99 -> 0 | W85: =W78*W99 -> 0 | X85: =X78*X99 -> 0 | Y85: =Y78*Y99 -> 2.7294977 | Z85: =Z78*Z99 -> 9.4982281 | AA85: =AA78*AA99 -> 15.395554 | AB85: =AB78*AB99 -> 20.571374 | AC85: =AC78*AC99 -> 25.157003
A86: Collaboration | B86: =REVENUE!B34 -> 0 | C86: =REVENUE!C34 -> 0 | D86: =REVENUE!D34 -> 0 | E86: =REVENUE!E34 -> 0 | F86: =REVENUE!F34 -> 22.499 | G86: =REVENUE!G34 -> 7.031 | H86: =REVENUE!H34 -> 0.528 | I86: =REVENUE!I34 -> 0.312 | J86: =REVENUE!J34 -> 0 | M86: =REVENUE!AG34 -> 0 | N86: =REVENUE!AH34 -> 0 | O86: 0 | P86: =P79*P100 -> 0 | Q86: =Q79*Q100 -> 0 | R86: =R79*R100 -> 0 | S86: =S79*S100 -> 0 | T86: =SUM(P86:S86) -> 0 | U86: =U79*U100 -> 0 | V86: =V79*V100 -> 0 | W86: =W79*W100 -> 0 | X86: =X79*X100 -> 0 | Y86: =Y79*Y100 -> 0 | Z86: =Z79*Z100 -> 0 | AA86: =AA79*AA100 -> 0 | AB86: =AB79*AB100 -> 0 | AC86: =AC79*AC100 -> 0
A87: Gross Profit | B87: =IS!B14 -> 0 | C87: =IS!C14 -> 0 | D87: =IS!D14 -> 0 | E87: =IS!E14 -> 0 | F87: =IS!F14 -> 22.499 | G87: =IS!G14 -> 7.031 | H87: =IS!H14 -> 0.528 | I87: =IS!I14 -> 0.312 | J87: =IS!J14 -> 0 | M87: =IS!AC14 -> 0 | N87: =IS!AD14 -> 0 | O87: =SUM(O83:O86) -> 0 | P87: =SUM(P83:P86) -> 0 | Q87: =SUM(Q83:Q86) -> 0 | R87: =SUM(R83:R86) -> 0 | S87: =SUM(S83:S86) -> 0 | T87: =SUM(T83:T86) -> 0 | U87: =SUM(U83:U86) -> 0 | V87: =SUM(V83:V86) -> 0 | ... AC87: =SUM(AC83:AC86) -> 1365.0453
A89: COGS
A90: ML-007 - Schizophrenia | O90: =O97-O83 -> 0 | P90: =P97-P83 -> 0 | Q90: =Q97-Q83 -> 0 | R90: =R97-R83 -> 0 | S90: =S97-S83 -> 0 | T90: =T97-T83 -> 0 | U90: =U97-U83 -> 0 | V90: =V97-V83 -> 0 | ... AC90: =AC97-AC83 -> 63.760459
A91: ML-007 - AD Psychosis | O91: =O98-O84 -> 0 | P91: =P98-P84 -> 0 | Q91: =Q98-Q84 -> 0 | R91: =R98-R84 -> 0 | S91: =S98-S84 -> 0 | T91: =T98-T84 -> 0 | U91: =U98-U84 -> 0 | V91: =V98-V84 -> 0 | ... AC91: =AC98-AC84 -> 44.879129
A92: ML-004 - ASD | O92: =O99-O85 -> 0 | P92: =P99-P85 -> 0 | Q92: =Q99-Q85 -> 0 | R92: =R99-R85 -> 0 | S92: =S99-S85 -> 0 | T92: =T99-T85 -> 0 | U92: =U99-U85 -> 0 | V92: =V99-V85 -> 0 | ... AC92: =AC99-AC85 -> 2.039757
A93: Collaboration | O93: =O100-O86 -> 0 | P93: =P100-P86 -> 0 | Q93: =Q100-Q86 -> 0 | R93: =R100-R86 -> 0 | S93: =S100-S86 -> 0 | T93: =T100-T86 -> 0 | U93: =U100-U86 -> 0 | V93: =V100-V86 -> 0 | ... AC93: =AC100-AC86 -> 0
A94: COGS | B94: =IS!B13 -> 0 | C94: =IS!C13 -> 0 | D94: =IS!D13 -> 0 | E94: =IS!E13 -> 0 | F94: =IS!F13 -> 0 | G94: =IS!G13 -> 0 | H94: =IS!H13 -> 0 | I94: =IS!I13 -> 0 | J94: =IS!J13 -> 0 | M94: =M101-M87 -> 0 | N94: =N101-N87 -> 0 | O94: =O101-O87 -> 0 | P94: =P101-P87 -> 0 | Q94: =Q101-Q87 -> 0 | R94: =R101-R87 -> 0 | S94: =S101-S87 -> 0 | T94: =T101-T87 -> 0 | ... AC94: =AC101-AC87 -> 110.67934
A95: Consensus
A96: Sales
A97: ML-007 - Schizophrenia | P97: =REVENUE!AJ9 -> 0 | Q97: =REVENUE!AK9 -> 0 | R97: =REVENUE!AL9 -> 0 | S97: =REVENUE!AM9 -> 0 | T97: =REVENUE!AN9 -> 0 | U97: =REVENUE!AO9 -> 0 | V97: =REVENUE!AP9 -> 0 | W97: =REVENUE!AQ9 -> 16.880566 | ... AC97: =REVENUE!AW9 -> 850.13945
A98: ML-007 - AD Psychosis | P98: =REVENUE!AJ14 -> 0 | Q98: =REVENUE!AK14 -> 0 | R98: =REVENUE!AL14 -> 0 | S98: =REVENUE!AM14 -> 0 | T98: =REVENUE!AN14 -> 0 | U98: =REVENUE!AO14 -> 0 | V98: =REVENUE!AP14 -> 0 | W98: =REVENUE!AQ14 -> 0 | ... AC98: =REVENUE!AW14 -> 598.38838
A99: ML-004 - ASD | P99: =REVENUE!AJ25 -> 0 | Q99: =REVENUE!AK25 -> 0 | R99: =REVENUE!AL25 -> 0 | S99: =REVENUE!AM25 -> 0 | T99: =REVENUE!AN25 -> 0 | U99: =REVENUE!AO25 -> 0 | V99: =REVENUE!AP25 -> 0 | W99: =REVENUE!AQ25 -> 0 | ... AC99: =REVENUE!AW25 -> 27.19676
A100: Collaboration | B100: =REVENUE!B34 -> 0 | C100: =REVENUE!C34 -> 0 | D100: =REVENUE!D34 -> 0 | E100: =REVENUE!E34 -> 0 | F100: =REVENUE!F34 -> 22.499 | G100: =REVENUE!G34 -> 7.031 | H100: =REVENUE!H34 -> 0.528 | I100: =REVENUE!I34 -> 0.312 | J100: =REVENUE!J34 -> 0 | P100: =REVENUE!AJ34 -> 0 | Q100: =REVENUE!AK34 -> 0 | R100: =REVENUE!AL34 -> 0 | S100: =REVENUE!AM34 -> 0 | T100: =REVENUE!AN34 -> 0 | U100: =REVENUE!AO34 -> 0 | V100: =REVENUE!AP34 -> 0 | W100: =REVENUE!AQ34 -> 0 | ... AC100: =REVENUE!AW34 -> 0
A101: Total Sales | B101: =REVENUE!B36 -> 0 | C101: =REVENUE!C36 -> 0 | D101: =REVENUE!D36 -> 0 | E101: =REVENUE!E36 -> 0 | F101: =REVENUE!F36 -> 22.499 | G101: =REVENUE!G36 -> 7.031 | H101: =REVENUE!H36 -> 0.528 | I101: =REVENUE!I36 -> 0.312 | J101: =REVENUE!J36 -> 0 | P101: =REVENUE!AJ36 -> 0 | Q101: =REVENUE!AK36 -> 0 | R101: =REVENUE!AL36 -> 0 | S101: =REVENUE!AM36 -> 0 | T101: =REVENUE!AN36 -> 0 | U101: =REVENUE!AO36 -> 0 | V101: =REVENUE!AP36 -> 0 | W101: =REVENUE!AQ36 -> 16.880566 | ... AC101: =REVENUE!AW36 -> 1475.7246
A102: Source: Company reports; Needham & Company, LLC estimates

Sheet REVENUE
A1: MapLight Therapeutics - Revenue | AZ1: =SOTP!R14 -> 37.175346
A2: ($ Millions, except EPS)
B4: =IS!B4 -> 1Q19A | C4: =IS!C4 -> 2Q19A | D4: =IS!D4 -> 3Q19A | E4: =IS!E4 -> 4Q19A | F4: =IS!F4 -> 2019A | G4: =IS!G4 -> 1Q20A | H4: =IS!H4 -> 2Q20A | I4: =IS!I4 -> 3Q20A | ... Z4: =IS!Z4 -> 2023A | AA4: =IS!#REF! -> #REF! | AB4: =IS!#REF! -> #REF! | AC4: =IS!#REF! -> #REF! | AD4: =IS!#REF! -> #REF! | AE4: =IS!AA4 -> 1Q25A | AF4: =IS!AB4 -> 2Q25A | AG4: =IS!AC4 -> 3Q25A | AH4: =IS!AD4 -> 4Q25A | AI4: =IS!AE4 -> 2025A | AJ4: =IS!AF4 -> 1Q26E | AK4: =IS!AG4 -> 2Q26E | AL4: =IS!AH4 -> 3Q26E | ... AW4: =IS!AS4 -> 2035E
A6: ML-007C-MA
A7: Schizophrenia | Z7: 0 | AP7: 0 | AQ7: 30.691938 | AR7: 186.9139 | AS7: 470.40973 | AT7: 762.97567 | AU7: 1050.1175 | AV7: 1309.7538 | AW7: 1545.7081 | AY7: 0.55 | BC7: 78 | BD7: 37
A8: VA Cons. (Unadj) | AP8: =ML007MA_ME!T19 -> 0 | AQ8: =ML007MA_ME!U19 -> 29.32648 | AR8: =ML007MA_ME!V19 -> 90.24745 | AS8: =ML007MA_ME!W19 -> 196.03091 | AT8: =ML007MA_ME!X19 -> 316.81523 | AU8: =ML007MA_ME!Y19 -> 452.42737 | AV8: =ML007MA_ME!Z19 -> 590.38147 | AW8: =ML007MA_ME!AA19 -> 724.87222
A9: Schizophrenia PoS Adj. | Z9: =Z7*$AY$7 -> 0 | AP9: =AP7*$AY$7 -> 0 | AQ9: =AQ7*$AY$7 -> 16.880566 | AR9: =AR7*$AY$7 -> 102.80265 | AS9: =AS7*$AY$7 -> 258.72535 | AT9: =AT7*$AY$7 -> 419.63662 | AU9: =AU7*$AY$7 -> 577.56461 | AV9: =AV7*$AY$7 -> 720.3646 | AW9: =AW7*$AY$7 -> 850.13945 | BC9: 36 | BD9: 21
A10: VA Cons. (Adj) | AP10: =ML007MA_ME!T21 -> 0 | AQ10: =ML007MA_ME!U21 -> 17.595888 | AR10: =ML007MA_ME!V21 -> 53.153454 | AS10: =ML007MA_ME!W21 -> 135.93035 | AT10: =ML007MA_ME!X21 -> 216.23472 | AU10: =ML007MA_ME!Y21 -> 308.20364 | AV10: =ML007MA_ME!Z21 -> 398.53516 | AW10: =ML007MA_ME!AA21 -> 485.88175
A12: Alzheimer's Disease Psychosis | Z12: 0 | AP12: 0 | AQ12: 0 | AR12: 101.32251 | AS12: 345.29982 | AT12: 964.24697 | AU12: 1500.5163 | AV12: 1972.0631 | AW12: 2393.5535 | AY12: 0.25
A13: VA Cons. (Unadj) | AP13: =ML007MA_ME!T40 -> 0 | AQ13: =ML007MA_ME!U40 -> 0 | AR13: =ML007MA_ME!V40 -> 31.333005 | AS13: =ML007MA_ME!W40 -> 72.874931 | AT13: =ML007MA_ME!X40 -> 205.38141 | AU13: =ML007MA_ME!Y40 -> 388.60215 | AV13: =ML007MA_ME!Z40 -> 592.28238 | AW13: =ML007MA_ME!AA40 -> 786.41443
A14: AD Psychosis Pos Adj. | Z14: =Z12*$AY$12 -> 0 | AP14: =AP12*$AY$12 -> 0 | AQ14: =AQ12*$AY$12 -> 0 | AR14: =AR12*$AY$12 -> 25.330627 | AS14: =AS12*$AY$12 -> 86.324955 | AT14: =AT12*$AY$12 -> 241.06174 | AU14: =AU12*$AY$12 -> 375.12907 | AV14: =AV12*$AY$12 -> 493.01577 | AW14: =AW12*$AY$12 -> 598.38838
A15: VA Cons. (Adj) | AP15: =ML007MA_ME!T42 -> 0 | AQ15: =ML007MA_ME!U42 -> 0 | AR15: =ML007MA_ME!V42 -> 15.666503 | AS15: =ML007MA_ME!W42 -> 40.671555 | AT15: =ML007MA_ME!X42 -> 87.761699 | AU15: =ML007MA_ME!Y42 -> 152.24155 | AV15: =ML007MA_ME!Z42 -> 226.1123 | AW15: =ML007MA_ME!AA42 -> 298.94417
A17: ML-007C-MA (M1 / M4 agonist) - Total | Z17: =Z7+Z12+#REF! -> #REF! | AQ17: =AQ7+AQ12 -> 30.691938 | AR17: =AR7+AR12 -> 288.23641 | AS17: =AS7+AS12 -> 815.70955 | AT17: =AT7+AT12 -> 1727.2226 | AU17: =AU7+AU12 -> 2550.6337 | AV17: =AV7+AV12 -> 3281.8169 | AW17: =AW7+AW12 -> 3939.2616 | AY17: Avg:
A18: PoS (%) | AQ18: =AQ19/AQ17 -> 0.55 | AR18: =AR19/AR17 -> 0.44454229 | AS18: =AS19/AS17 -> 0.42300633 | AT18: =AT19/AT17 -> 0.38252067 | AU18: =AU19/AU17 -> 0.37351254 | AV18: =AV19/AV17 -> 0.36972824 | AW18: =AW19/AW17 -> 0.36771557 | AY18: =AVERAGE(AQ18:AW18) -> 0.4158608
A19: ML-007C-MA (M1 / M4 agonist) PoS Adj. | Z19: =Z7*$AY$7+Z12*$AY$12+#REF!*#REF! -> #REF! | AQ19: =AQ7*$AY$7+AQ12*$AY$12 -> 16.880566 | AR19: =AR7*$AY$7+AR12*$AY$12 -> 128.13327 | AS19: =AS7*$AY$7+AS12*$AY$12 -> 345.0503 | AT19: =AT7*$AY$7+AT12*$AY$12 -> 660.69836 | AU19: =AU7*$AY$7+AU12*$AY$12 -> 952.69368 | AV19: =AV7*$AY$7+AV12*$AY$12 -> 1213.3804 | AW19: =AW7*$AY$7+AW12*$AY$12 -> 1448.5278
A20: Growth | AR20: =AR19/AQ19-1 -> 6.5905793 | AS20: =AS19/AR19-1 -> 1.6929016 | AT20: =AT19/AS19-1 -> 0.91478853 | AU20: =AU19/AT19-1 -> 0.44194951 | AV20: =AV19/AU19-1 -> 0.27363117 | AW20: =AW19/AV19-1 -> 0.19379535
A21: Consensus | Z21: ='VA Consensus'!#REF! -> #REF! | AN21: ='VA Consensus'!S14 -> 0 | AO21: ='VA Consensus'!T14 -> 0 | AP21: ='VA Consensus'!U14 -> 0 | AQ21: ='VA Consensus'!V14 -> 17.595888 | AR21: ='VA Consensus'!W14 -> 65.038297 | AS21: ='VA Consensus'!X14 -> 182.01857 | AT21: ='VA Consensus'!Y14 -> 303.99642 | AU21: ='VA Consensus'!Z14 -> 445.62785 | ... AW21: ='VA Consensus'!AB14 -> 775.64772
A23: ML-004 (5-HT 1B/ID agonist)
A24: Autism Spectrum Disorder | Z24: 0 | AS24: 59.016167 | AT24: 205.36709 | AU24: 332.87683 | AV24: 444.78646 | AW24: 543.9352 | AY24: 0.05
A25: ASD PoS Adj. | Z25: =Z24*$AY$7 -> 0 | AS25: =AS24*$AY$24 -> 2.9508083 | AT25: =AT24*$AY$24 -> 10.268355 | AU25: =AU24*$AY$24 -> 16.643842 | AV25: =AV24*$AY$24 -> 22.239323 | AW25: =AW24*$AY$24 -> 27.19676
A26: Consensus | Z26: ='VA Consensus'!#REF! -> #REF! | AN26: ='VA Consensus'!S19 -> 0 | AO26: ='VA Consensus'!T19 -> 0 | AP26: ='VA Consensus'!U19 -> 0 | AQ26: ='VA Consensus'!V19 -> 0 | AR26: ='VA Consensus'!W19 -> 0 | AS26: ='VA Consensus'!X19 -> 11.587328 | AT26: ='VA Consensus'!Y19 -> 24.220121 | AU26: ='VA Consensus'!Z19 -> 38.412156 | ... AW26: ='VA Consensus'!AB19 -> 67.195105
A28: Royalties/Collaboration Revenues | AY28: PoS | AZ28: Royalty Rate
A29: Schizophrenia | Z29: 0 | AY29: =AY7 -> 0.55 | AZ29: 0.15
A30: AD Psychosis | Z30: 0 | AY30: =AY12 -> 0.25 | AZ30: 0.15
A31: ASD | Z31: 0 | AY31: =AY24 -> 0.05 | AZ31: 0.15
A32: Collaboration Revenue | F32: =F34 -> 22.499 | G32: =G34 -> 7.031 | H32: =H34 -> 0.528 | I32: =I34 -> 0.312 | J32: =J34 -> 0 | K32: =K34 -> 7.871 | Z32: =Z29*$AY$29*$AZ$29+Z30*$AY$30*$AZ$30+Z31*$AY$31*$AZ$31 -> 0 | AN32: =AN29*$AY$29*$AZ$29+AN30*$AY$30*$AZ$30+AN31*$AY$31*$AZ$31 -> 0 | AO32: =AO29*$AY$29*$AZ$29+AO30*$AY$30*$AZ$30+AO31*$AY$31*$AZ$31 -> 0 | AP32: =AP29*$AY$29*$AZ$29+AP30*$AY$30*$AZ$30+AP31*$AY$31*$AZ$31 -> 0 | AQ32: =AQ29*$AY$29*$AZ$29+AQ30*$AY$30*$AZ$30+AQ31*$AY$31*$AZ$31 -> 0 | AR32: =AR29*$AY$29*$AZ$29+AR30*$AY$30*$AZ$30+AR31*$AY$31*$AZ$31 -> 0 | AS32: =AS29*$AY$29*$AZ$29+AS30*$AY$30*$AZ$30+AS31*$AY$31*$AZ$31 -> 0 | AT32: =AT29*$AY$29*$AZ$29+AT30*$AY$30*$AZ$30+AT31*$AY$31*$AZ$31 -> 0 | AU32: =AU29*$AY$29*$AZ$29+AU30*$AY$30*$AZ$30+AU31*$AY$31*$AZ$31 -> 0 | ... AW32: =AW29*$AY$29*$AZ$29+AW30*$AY$30*$AZ$30+AW31*$AY$31*$AZ$31 -> 0
A34: Total Royalties/Collaboration Revenues | F34: =IS!F7 -> 22.499 | G34: =IS!G7 -> 7.031 | H34: =IS!H7 -> 0.528 | I34: =IS!I7 -> 0.312 | J34: =IS!J7 -> 0 | K34: =IS!K7 -> 7.871 | L34: =IS!L7 -> 0 | M34: =IS!M7 -> 0 | ... T34: =IS!T7 -> 0 | U34: =SUM(Q34:T34) -> 0 | V34: =IS!V7 -> 0 | W34: =IS!W7 -> 0 | X34: =IS!X7 -> 0 | Y34: =IS!Y7 -> 0 | Z34: =SUM(V34:Y34) -> 0 | AN34: =AN32 -> 0 | AO34: =AO32 -> 0 | AP34: =AP32 -> 0 | AQ34: =AQ32 -> 0 | AR34: =AR32 -> 0 | AS34: =AS32 -> 0 | AT34: =AT32 -> 0 | AU34: =AU32 -> 0 | ... AW34: =AW32 -> 0
A36: Total Revenues | F36: =IS!F8 -> 22.499 | G36: =IS!G8 -> 7.031 | H36: =IS!H8 -> 0.528 | I36: =IS!I8 -> 0.312 | J36: =IS!J8 -> 0 | K36: =IS!K8 -> 7.871 | L36: =IS!L8 -> 0 | M36: =IS!M8 -> 0 | ... T36: =IS!T8 -> 0 | U36: =SUM(U19,U34) -> 0 | V36: =IS!V8 -> 0 | W36: =IS!W8 -> 0 | X36: =IS!X8 -> 0 | Y36: =IS!Y8 -> 0 | Z36: =SUM(Z19,Z34) -> #REF! | AA36: =SUM(AA19,AA34) -> 0 | AB36: =SUM(AB19,AB34) -> 0 | AC36: =SUM(AC19,AC34) -> 0 | AD36: =SUM(AD19,AD34) -> 0 | AN36: =SUM(AN19,AN34,AN25) -> 0 | AO36: =SUM(AO19,AO34,AO25) -> 0 | AP36: =SUM(AP19,AP34,AP25) -> 0 | AQ36: =SUM(AQ19,AQ34,AQ25) -> 16.880566 | AR36: =SUM(AR19,AR34,AR25) -> 128.13327 | AS36: =SUM(AS19,AS34,AS25) -> 348.00111 | AT36: =SUM(AT19,AT34,AT25) -> 670.96672 | AU36: =SUM(AU19,AU34,AU25) -> 969.33752 | ... AW36: =SUM(AW19,AW34,AW25) -> 1475.7246
A37: Consensus | Z37: ='VA Consensus'!#REF! -> #REF! | AN37: ='VA Consensus'!S27 -> 0 | AO37: ='VA Consensus'!T27 -> 0 | AP37: ='VA Consensus'!U27 -> 0 | AQ37: ='VA Consensus'!V27 -> 17.595888 | AR37: ='VA Consensus'!W27 -> 75.100797 | AS37: ='VA Consensus'!X27 -> 259.33112 | AT37: ='VA Consensus'!Y27 -> 515.18785 | AU37: ='VA Consensus'!Z27 -> 809.33262 | ... AW37: ='VA Consensus'!AB27 -> 1392.2424
A38: Source: Company reports; Needham & Company, LLC estimates

Sheet ML007MA_ME
E1: =HYPERLINK("#ML007MA_ME!Notes","See the Notes for this Sheet") -> See the Notes for this Sheet
B2: Company | C2: =_xll.VADetail("Name",$C$3) -> MapLight Therapeutics, Inc.
B3: Ticker | C3: MPLT_US
B4: IMPL or Raw | C4: IMPL
B5: Data Type | C5: CD
B6: Tab | C6: ME
B7: As Of | C7: =TODAY() -> 46119
E8: 1QFY-2025 | F8: 2QFY-2025 | G8: 3QFY-2025 | H8: 4QFY-2025 | I8: FY-2025 | J8: 1QFY-2026 | K8: 2QFY-2026 | L8: 3QFY-2026 | M8: 4QFY-2026 | N8: FY-2026 | O8: 1QFY-2027 | P8: 2QFY-2027 | Q8: 3QFY-2027 | R8: 4QFY-2027 | S8: FY-2027 | T8: FY-2028 | U8: FY-2029 | V8: FY-2030 | W8: FY-2031 | X8: FY-2032 | Y8: FY-2033 | Z8: FY-2034 | AA8: FY-2035
E9: =_xll.VADetail("ActualOrEstimate",$C$3,"Consensus",E$8) -> A | F9: =_xll.VADetail("ActualOrEstimate",$C$3,"Consensus",F$8) -> A | G9: =_xll.VADetail("ActualOrEstimate",$C$3,"Consensus",G$8) -> A | H9: =_xll.VADetail("ActualOrEstimate",$C$3,"Consensus",H$8) -> A | I9: =_xll.VADetail("ActualOrEstimate",$C$3,"Consensus",I$8) -> A | J9: =_xll.VADetail("ActualOrEstimate",$C$3,"Consensus",J$8) -> E | K9: =_xll.VADetail("ActualOrEstimate",$C$3,"Consensus",K$8) -> E | L9: =_xll.VADetail("ActualOrEstimate",$C$3,"Consensus",L$8) -> E | ... AA9: =_xll.VADetail("ActualOrEstimate",$C$3,"Consensus",AA$8) -> E
B10: Item Code | C10: Line Item | D10: Units | E10: =IF(E$9="A","VA Actuals","Consensus") -> VA Actuals | F10: =IF(F$9="A","VA Actuals","Consensus") -> VA Actuals | G10: =IF(G$9="A","VA Actuals","Consensus") -> VA Actuals | H10: =IF(H$9="A","VA Actuals","Consensus") -> VA Actuals | I10: =IF(I$9="A","VA Actuals","Consensus") -> VA Actuals | J10: =IF(J$9="A","VA Actuals","Consensus") -> Consensus | K10: =IF(K$9="A","VA Actuals","Consensus") -> Consensus | L10: =IF(L$9="A","VA Actuals","Consensus") -> Consensus | ... AA10: =IF(AA$9="A","VA Actuals","Consensus") -> Consensus
B11: H | C11: ML 007-MA
B12: H | C12: ML-007-MA Schizophrenia
B13: N_15532762 | C13: Eligible patients - ML-007-MA - Schizophrenia - US | D13: # | E13: =_xll.VAData($C$3,E$8,$C13,E$10,$C$5,$C$4,$C$7) -> - | F13: =_xll.VAData($C$3,F$8,$C13,F$10,$C$5,$C$4,$C$7) -> - | G13: =_xll.VAData($C$3,G$8,$C13,G$10,$C$5,$C$4,$C$7) -> - | H13: =_xll.VAData($C$3,H$8,$C13,H$10,$C$5,$C$4,$C$7) -> - | I13: =_xll.VAData($C$3,I$8,$C13,I$10,$C$5,$C$4,$C$7) -> 659911.42 | J13: =_xll.VAData($C$3,J$8,$C13,J$10,$C$5,$C$4,$C$7) -> - | K13: =_xll.VAData($C$3,K$8,$C13,K$10,$C$5,$C$4,$C$7) -> - | L13: =_xll.VAData($C$3,L$8,$C13,L$10,$C$5,$C$4,$C$7) -> - | ... AA13: =_xll.VAData($C$3,AA$8,$C13,AA$10,$C$5,$C$4,$C$7) -> 938712.54
B14: N_15532764 | C14: Penetration - ML-007-MA - Schizophrenia -US | D14: % | E14: =_xll.VAData($C$3,E$8,$C14,E$10,$C$5,$C$4,$C$7) -> - | F14: =_xll.VAData($C$3,F$8,$C14,F$10,$C$5,$C$4,$C$7) -> - | G14: =_xll.VAData($C$3,G$8,$C14,G$10,$C$5,$C$4,$C$7) -> - | H14: =_xll.VAData($C$3,H$8,$C14,H$10,$C$5,$C$4,$C$7) -> - | I14: =_xll.VAData($C$3,I$8,$C14,I$10,$C$5,$C$4,$C$7) -> - | J14: =_xll.VAData($C$3,J$8,$C14,J$10,$C$5,$C$4,$C$7) -> - | K14: =_xll.VAData($C$3,K$8,$C14,K$10,$C$5,$C$4,$C$7) -> - | L14: =_xll.VAData($C$3,L$8,$C14,L$10,$C$5,$C$4,$C$7) -> - | ... AA14: =_xll.VAData($C$3,AA$8,$C14,AA$10,$C$5,$C$4,$C$7) -> 9.5
B15: N_15532763 | C15: Number of patients - ML 00-MA - Schizophrenia - US | D15: # | E15: =_xll.VAData($C$3,E$8,$C15,E$10,$C$5,$C$4,$C$7) -> - | F15: =_xll.VAData($C$3,F$8,$C15,F$10,$C$5,$C$4,$C$7) -> - | G15: =_xll.VAData($C$3,G$8,$C15,G$10,$C$5,$C$4,$C$7) -> - | H15: =_xll.VAData($C$3,H$8,$C15,H$10,$C$5,$C$4,$C$7) -> - | I15: =_xll.VAData($C$3,I$8,$C15,I$10,$C$5,$C$4,$C$7) -> - | J15: =_xll.VAData($C$3,J$8,$C15,J$10,$C$5,$C$4,$C$7) -> - | K15: =_xll.VAData($C$3,K$8,$C15,K$10,$C$5,$C$4,$C$7) -> - | L15: =_xll.VAData($C$3,L$8,$C15,L$10,$C$5,$C$4,$C$7) -> - | ... AA15: =_xll.VAData($C$3,AA$8,$C15,AA$10,$C$5,$C$4,$C$7) -> 50911.832
B16: N_15532765 | C16: Gross revenue per treatment - ML-007-MA - Schizophrenia - US | D16: $Abs | E16: =_xll.VAData($C$3,E$8,$C16,E$10,$C$5,$C$4,$C$7) -> - | F16: =_xll.VAData($C$3,F$8,$C16,F$10,$C$5,$C$4,$C$7) -> - | G16: =_xll.VAData($C$3,G$8,$C16,G$10,$C$5,$C$4,$C$7) -> - | H16: =_xll.VAData($C$3,H$8,$C16,H$10,$C$5,$C$4,$C$7) -> - | I16: =_xll.VAData($C$3,I$8,$C16,I$10,$C$5,$C$4,$C$7) -> - | J16: =_xll.VAData($C$3,J$8,$C16,J$10,$C$5,$C$4,$C$7) -> - | K16: =_xll.VAData($C$3,K$8,$C16,K$10,$C$5,$C$4,$C$7) -> - | L16: =_xll.VAData($C$3,L$8,$C16,L$10,$C$5,$C$4,$C$7) -> - | ... AA16: =_xll.VAData($C$3,AA$8,$C16,AA$10,$C$5,$C$4,$C$7) -> 24489.186
B17: N_15532767 | C17: Gross-to-net adjustment rate - ML-007-MA - Schizophrenia - US | D17: % | E17: =_xll.VAData($C$3,E$8,$C17,E$10,$C$5,$C$4,$C$7) -> - | F17: =_xll.VAData($C$3,F$8,$C17,F$10,$C$5,$C$4,$C$7) -> - | G17: =_xll.VAData($C$3,G$8,$C17,G$10,$C$5,$C$4,$C$7) -> - | H17: =_xll.VAData($C$3,H$8,$C17,H$10,$C$5,$C$4,$C$7) -> - | I17: =_xll.VAData($C$3,I$8,$C17,I$10,$C$5,$C$4,$C$7) -> 40 | J17: =_xll.VAData($C$3,J$8,$C17,J$10,$C$5,$C$4,$C$7) -> - | K17: =_xll.VAData($C$3,K$8,$C17,K$10,$C$5,$C$4,$C$7) -> - | L17: =_xll.VAData($C$3,L$8,$C17,L$10,$C$5,$C$4,$C$7) -> - | ... AA17: =_xll.VAData($C$3,AA$8,$C17,AA$10,$C$5,$C$4,$C$7) -> 32.666667
B18: N_15532766 | C18: Revenue per treatment - ML-007-MA - Schizophrenia - US | D18: $Abs | E18: =_xll.VAData($C$3,E$8,$C18,E$10,$C$5,$C$4,$C$7) -> - | F18: =_xll.VAData($C$3,F$8,$C18,F$10,$C$5,$C$4,$C$7) -> - | G18: =_xll.VAData($C$3,G$8,$C18,G$10,$C$5,$C$4,$C$7) -> - | H18: =_xll.VAData($C$3,H$8,$C18,H$10,$C$5,$C$4,$C$7) -> - | I18: =_xll.VAData($C$3,I$8,$C18,I$10,$C$5,$C$4,$C$7) -> - | J18: =_xll.VAData($C$3,J$8,$C18,J$10,$C$5,$C$4,$C$7) -> - | K18: =_xll.VAData($C$3,K$8,$C18,K$10,$C$5,$C$4,$C$7) -> - | L18: =_xll.VAData($C$3,L$8,$C18,L$10,$C$5,$C$4,$C$7) -> - | ... AA18: =_xll.VAData($C$3,AA$8,$C18,AA$10,$C$5,$C$4,$C$7) -> 17440.082
B19: N_15532769 | C19: ML 007-MA - Schizophrenia - US - Unadjusted | D19: $M | E19: =_xll.VAData($C$3,E$8,$C19,E$10,$C$5,$C$4,$C$7) -> - | F19: =_xll.VAData($C$3,F$8,$C19,F$10,$C$5,$C$4,$C$7) -> - | G19: =_xll.VAData($C$3,G$8,$C19,G$10,$C$5,$C$4,$C$7) -> - | H19: =_xll.VAData($C$3,H$8,$C19,H$10,$C$5,$C$4,$C$7) -> - | I19: =_xll.VAData($C$3,I$8,$C19,I$10,$C$5,$C$4,$C$7) -> 0 | J19: =_xll.VAData($C$3,J$8,$C19,J$10,$C$5,$C$4,$C$7) -> - | K19: =_xll.VAData($C$3,K$8,$C19,K$10,$C$5,$C$4,$C$7) -> - | L19: =_xll.VAData($C$3,L$8,$C19,L$10,$C$5,$C$4,$C$7) -> - | ... AA19: =_xll.VAData($C$3,AA$8,$C19,AA$10,$C$5,$C$4,$C$7) -> 724.87222
B20: N_15532770 | C20: POS - ML 007 MA - Schizophrenia - US | D20: % | E20: =_xll.VAData($C$3,E$8,$C20,E$10,$C$5,$C$4,$C$7) -> - | F20: =_xll.VAData($C$3,F$8,$C20,F$10,$C$5,$C$4,$C$7) -> - | G20: =_xll.VAData($C$3,G$8,$C20,G$10,$C$5,$C$4,$C$7) -> - | H20: =_xll.VAData($C$3,H$8,$C20,H$10,$C$5,$C$4,$C$7) -> - | I20: =_xll.VAData($C$3,I$8,$C20,I$10,$C$5,$C$4,$C$7) -> - | J20: =_xll.VAData($C$3,J$8,$C20,J$10,$C$5,$C$4,$C$7) -> 53.75 | K20: =_xll.VAData($C$3,K$8,$C20,K$10,$C$5,$C$4,$C$7) -> 53.75 | L20: =_xll.VAData($C$3,L$8,$C20,L$10,$C$5,$C$4,$C$7) -> 53.75 | ... AA20: =_xll.VAData($C$3,AA$8,$C20,AA$10,$C$5,$C$4,$C$7) -> 53.75
B21: N_15532768 | C21: ML 007-MA - Schizophrenia - US | D21: $M | E21: =_xll.VAData($C$3,E$8,$C21,E$10,$C$5,$C$4,$C$7) -> - | F21: =_xll.VAData($C$3,F$8,$C21,F$10,$C$5,$C$4,$C$7) -> - | G21: =_xll.VAData($C$3,G$8,$C21,G$10,$C$5,$C$4,$C$7) -> - | H21: =_xll.VAData($C$3,H$8,$C21,H$10,$C$5,$C$4,$C$7) -> - | I21: =_xll.VAData($C$3,I$8,$C21,I$10,$C$5,$C$4,$C$7) -> 0 | J21: =_xll.VAData($C$3,J$8,$C21,J$10,$C$5,$C$4,$C$7) -> - | K21: =_xll.VAData($C$3,K$8,$C21,K$10,$C$5,$C$4,$C$7) -> - | L21: =_xll.VAData($C$3,L$8,$C21,L$10,$C$5,$C$4,$C$7) -> - | ... AA21: =_xll.VAData($C$3,AA$8,$C21,AA$10,$C$5,$C$4,$C$7) -> 485.88175
B22: H
B23: N_15532802 | C23: ML-007-MA - Schizophrenia - International - Unadjusted | D23: $M | E23: =_xll.VAData($C$3,E$8,$C23,E$10,$C$5,$C$4,$C$7) -> - | F23: =_xll.VAData($C$3,F$8,$C23,F$10,$C$5,$C$4,$C$7) -> - | G23: =_xll.VAData($C$3,G$8,$C23,G$10,$C$5,$C$4,$C$7) -> - | H23: =_xll.VAData($C$3,H$8,$C23,H$10,$C$5,$C$4,$C$7) -> - | I23: =_xll.VAData($C$3,I$8,$C23,I$10,$C$5,$C$4,$C$7) -> 0 | J23: =_xll.VAData($C$3,J$8,$C23,J$10,$C$5,$C$4,$C$7) -> - | K23: =_xll.VAData($C$3,K$8,$C23,K$10,$C$5,$C$4,$C$7) -> - | L23: =_xll.VAData($C$3,L$8,$C23,L$10,$C$5,$C$4,$C$7) -> - | ... AA23: =_xll.VAData($C$3,AA$8,$C23,AA$10,$C$5,$C$4,$C$7) -> 44.982236
B24: N_15532772 | C24: POS - ML 007 MA - Schizophrenia - International | D24: % | E24: =_xll.VAData($C$3,E$8,$C24,E$10,$C$5,$C$4,$C$7) -> - | F24: =_xll.VAData($C$3,F$8,$C24,F$10,$C$5,$C$4,$C$7) -> - | G24: =_xll.VAData($C$3,G$8,$C24,G$10,$C$5,$C$4,$C$7) -> - | H24: =_xll.VAData($C$3,H$8,$C24,H$10,$C$5,$C$4,$C$7) -> - | I24: =_xll.VAData($C$3,I$8,$C24,I$10,$C$5,$C$4,$C$7) -> - | J24: =_xll.VAData($C$3,J$8,$C24,J$10,$C$5,$C$4,$C$7) -> 50 | K24: =_xll.VAData($C$3,K$8,$C24,K$10,$C$5,$C$4,$C$7) -> 50 | L24: =_xll.VAData($C$3,L$8,$C24,L$10,$C$5,$C$4,$C$7) -> 50 | ... AA24: =_xll.VAData($C$3,AA$8,$C24,AA$10,$C$5,$C$4,$C$7) -> 50
B25: N_15532771 | C25: ML 007-MA - Schizophrenia - International | D25: $M | E25: =_xll.VAData($C$3,E$8,$C25,E$10,$C$5,$C$4,$C$7) -> - | F25: =_xll.VAData($C$3,F$8,$C25,F$10,$C$5,$C$4,$C$7) -> - | G25: =_xll.VAData($C$3,G$8,$C25,G$10,$C$5,$C$4,$C$7) -> - | H25: =_xll.VAData($C$3,H$8,$C25,H$10,$C$5,$C$4,$C$7) -> - | I25: =_xll.VAData($C$3,I$8,$C25,I$10,$C$5,$C$4,$C$7) -> 0 | J25: =_xll.VAData($C$3,J$8,$C25,J$10,$C$5,$C$4,$C$7) -> - | K25: =_xll.VAData($C$3,K$8,$C25,K$10,$C$5,$C$4,$C$7) -> - | L25: =_xll.VAData($C$3,L$8,$C25,L$10,$C$5,$C$4,$C$7) -> - | ... AA25: =_xll.VAData($C$3,AA$8,$C25,AA$10,$C$5,$C$4,$C$7) -> 22.491118
B26: H
B27: N_15532806 | C27: ML-007-MA - Schizophrenia - Unadjusted | D27: $M | E27: =_xll.VAData($C$3,E$8,$C27,E$10,$C$5,$C$4,$C$7) -> - | F27: =_xll.VAData($C$3,F$8,$C27,F$10,$C$5,$C$4,$C$7) -> - | G27: =_xll.VAData($C$3,G$8,$C27,G$10,$C$5,$C$4,$C$7) -> 0 | H27: =_xll.VAData($C$3,H$8,$C27,H$10,$C$5,$C$4,$C$7) -> 0 | I27: =_xll.VAData($C$3,I$8,$C27,I$10,$C$5,$C$4,$C$7) -> 0 | J27: =_xll.VAData($C$3,J$8,$C27,J$10,$C$5,$C$4,$C$7) -> 0 | K27: =_xll.VAData($C$3,K$8,$C27,K$10,$C$5,$C$4,$C$7) -> 0 | L27: =_xll.VAData($C$3,L$8,$C27,L$10,$C$5,$C$4,$C$7) -> 0 | ... AA27: =_xll.VAData($C$3,AA$8,$C27,AA$10,$C$5,$C$4,$C$7) -> 736.11778
B28: N_15532810 | C28: POS - ML-007-MA - Schizophrenia | D28: % | E28: =_xll.VAData($C$3,E$8,$C28,E$10,$C$5,$C$4,$C$7) -> - | F28: =_xll.VAData($C$3,F$8,$C28,F$10,$C$5,$C$4,$C$7) -> - | G28: =_xll.VAData($C$3,G$8,$C28,G$10,$C$5,$C$4,$C$7) -> - | H28: =_xll.VAData($C$3,H$8,$C28,H$10,$C$5,$C$4,$C$7) -> - | I28: =_xll.VAData($C$3,I$8,$C28,I$10,$C$5,$C$4,$C$7) -> - | J28: =_xll.VAData($C$3,J$8,$C28,J$10,$C$5,$C$4,$C$7) -> 53.75 | K28: =_xll.VAData($C$3,K$8,$C28,K$10,$C$5,$C$4,$C$7) -> 53.75 | L28: =_xll.VAData($C$3,L$8,$C28,L$10,$C$5,$C$4,$C$7) -> 53.75 | ... AA28: =_xll.VAData($C$3,AA$8,$C28,AA$10,$C$5,$C$4,$C$7) -> 53.75
B29: N_15532805 | C29: ML-007-MA - Schizophrenia | D29: $M | E29: =_xll.VAData($C$3,E$8,$C29,E$10,$C$5,$C$4,$C$7) -> - | F29: =_xll.VAData($C$3,F$8,$C29,F$10,$C$5,$C$4,$C$7) -> - | G29: =_xll.VAData($C$3,G$8,$C29,G$10,$C$5,$C$4,$C$7) -> 0 | H29: =_xll.VAData($C$3,H$8,$C29,H$10,$C$5,$C$4,$C$7) -> 0 | I29: =_xll.VAData($C$3,I$8,$C29,I$10,$C$5,$C$4,$C$7) -> 0 | J29: =_xll.VAData($C$3,J$8,$C29,J$10,$C$5,$C$4,$C$7) -> - | K29: =_xll.VAData($C$3,K$8,$C29,K$10,$C$5,$C$4,$C$7) -> - | L29: =_xll.VAData($C$3,L$8,$C29,L$10,$C$5,$C$4,$C$7) -> - | ... AA29: =_xll.VAData($C$3,AA$8,$C29,AA$10,$C$5,$C$4,$C$7) -> 493.37879
B30: H
B31: H | C31: ML 007-MA Alzheimer's disease psychosis
B32: N_15532801 | C32: Gross number of patients - ML-007-MA - Alzheimer's disease psychosis (ADP) - US | D32: # | E32: =_xll.VAData($C$3,E$8,$C32,E$10,$C$5,$C$4,$C$7) -> - | F32: =_xll.VAData($C$3,F$8,$C32,F$10,$C$5,$C$4,$C$7) -> - | G32: =_xll.VAData($C$3,G$8,$C32,G$10,$C$5,$C$4,$C$7) -> - | H32: =_xll.VAData($C$3,H$8,$C32,H$10,$C$5,$C$4,$C$7) -> - | I32: =_xll.VAData($C$3,I$8,$C32,I$10,$C$5,$C$4,$C$7) -> 4584783.8 | J32: =_xll.VAData($C$3,J$8,$C32,J$10,$C$5,$C$4,$C$7) -> - | K32: =_xll.VAData($C$3,K$8,$C32,K$10,$C$5,$C$4,$C$7) -> - | L32: =_xll.VAData($C$3,L$8,$C32,L$10,$C$5,$C$4,$C$7) -> - | ... AA32: =_xll.VAData($C$3,AA$8,$C32,AA$10,$C$5,$C$4,$C$7) -> 4769886.9
B33: N_15532775 | C33: Prevalence rate - ML-007-MA - Alzheimer's disease psychosis (ADP) - US | D33: % | E33: =_xll.VAData($C$3,E$8,$C33,E$10,$C$5,$C$4,$C$7) -> - | F33: =_xll.VAData($C$3,F$8,$C33,F$10,$C$5,$C$4,$C$7) -> - | G33: =_xll.VAData($C$3,G$8,$C33,G$10,$C$5,$C$4,$C$7) -> - | H33: =_xll.VAData($C$3,H$8,$C33,H$10,$C$5,$C$4,$C$7) -> - | I33: =_xll.VAData($C$3,I$8,$C33,I$10,$C$5,$C$4,$C$7) -> 35 | J33: =_xll.VAData($C$3,J$8,$C33,J$10,$C$5,$C$4,$C$7) -> - | K33: =_xll.VAData($C$3,K$8,$C33,K$10,$C$5,$C$4,$C$7) -> - | L33: =_xll.VAData($C$3,L$8,$C33,L$10,$C$5,$C$4,$C$7) -> - | ... AA33: =_xll.VAData($C$3,AA$8,$C33,AA$10,$C$5,$C$4,$C$7) -> 35
B34: N_15532774 | C34: Eligible patients - ML-007-MA - Alzheimer's disease psychosis (ADP) - US | D34: # | E34: =_xll.VAData($C$3,E$8,$C34,E$10,$C$5,$C$4,$C$7) -> - | F34: =_xll.VAData($C$3,F$8,$C34,F$10,$C$5,$C$4,$C$7) -> - | G34: =_xll.VAData($C$3,G$8,$C34,G$10,$C$5,$C$4,$C$7) -> - | H34: =_xll.VAData($C$3,H$8,$C34,H$10,$C$5,$C$4,$C$7) -> - | I34: =_xll.VAData($C$3,I$8,$C34,I$10,$C$5,$C$4,$C$7) -> 1412735.8 | J34: =_xll.VAData($C$3,J$8,$C34,J$10,$C$5,$C$4,$C$7) -> - | K34: =_xll.VAData($C$3,K$8,$C34,K$10,$C$5,$C$4,$C$7) -> - | L34: =_xll.VAData($C$3,L$8,$C34,L$10,$C$5,$C$4,$C$7) -> - | ... AA34: =_xll.VAData($C$3,AA$8,$C34,AA$10,$C$5,$C$4,$C$7) -> 1547799.7
B35: N_15532777 | C35: Penetration rate - ML-007-MA - Alzheimer's disease psychosis (ADP) - US | D35: % | E35: =_xll.VAData($C$3,E$8,$C35,E$10,$C$5,$C$4,$C$7) -> - | F35: =_xll.VAData($C$3,F$8,$C35,F$10,$C$5,$C$4,$C$7) -> - | G35: =_xll.VAData($C$3,G$8,$C35,G$10,$C$5,$C$4,$C$7) -> - | H35: =_xll.VAData($C$3,H$8,$C35,H$10,$C$5,$C$4,$C$7) -> - | I35: =_xll.VAData($C$3,I$8,$C35,I$10,$C$5,$C$4,$C$7) -> - | J35: =_xll.VAData($C$3,J$8,$C35,J$10,$C$5,$C$4,$C$7) -> - | K35: =_xll.VAData($C$3,K$8,$C35,K$10,$C$5,$C$4,$C$7) -> - | L35: =_xll.VAData($C$3,L$8,$C35,L$10,$C$5,$C$4,$C$7) -> - | ... AA35: =_xll.VAData($C$3,AA$8,$C35,AA$10,$C$5,$C$4,$C$7) -> 5.5625
B36: N_15532776 | C36: Number of patients - ML-007-MA - Alzheimer's disease psychosis (ADP) - US | D36: # | E36: =_xll.VAData($C$3,E$8,$C36,E$10,$C$5,$C$4,$C$7) -> - | F36: =_xll.VAData($C$3,F$8,$C36,F$10,$C$5,$C$4,$C$7) -> - | G36: =_xll.VAData($C$3,G$8,$C36,G$10,$C$5,$C$4,$C$7) -> - | H36: =_xll.VAData($C$3,H$8,$C36,H$10,$C$5,$C$4,$C$7) -> - | I36: =_xll.VAData($C$3,I$8,$C36,I$10,$C$5,$C$4,$C$7) -> - | J36: =_xll.VAData($C$3,J$8,$C36,J$10,$C$5,$C$4,$C$7) -> - | K36: =_xll.VAData($C$3,K$8,$C36,K$10,$C$5,$C$4,$C$7) -> - | L36: =_xll.VAData($C$3,L$8,$C36,L$10,$C$5,$C$4,$C$7) -> - | ... AA36: =_xll.VAData($C$3,AA$8,$C36,AA$10,$C$5,$C$4,$C$7) -> 60970.32
B37: N_15532778 | C37: Gross revenue per treatment - ML-007-MA - Alzheimer's disease psychosis (ADP) - US | D37: $Abs | E37: =_xll.VAData($C$3,E$8,$C37,E$10,$C$5,$C$4,$C$7) -> - | F37: =_xll.VAData($C$3,F$8,$C37,F$10,$C$5,$C$4,$C$7) -> - | G37: =_xll.VAData($C$3,G$8,$C37,G$10,$C$5,$C$4,$C$7) -> - | H37: =_xll.VAData($C$3,H$8,$C37,H$10,$C$5,$C$4,$C$7) -> - | I37: =_xll.VAData($C$3,I$8,$C37,I$10,$C$5,$C$4,$C$7) -> - | J37: =_xll.VAData($C$3,J$8,$C37,J$10,$C$5,$C$4,$C$7) -> - | K37: =_xll.VAData($C$3,K$8,$C37,K$10,$C$5,$C$4,$C$7) -> - | L37: =_xll.VAData($C$3,L$8,$C37,L$10,$C$5,$C$4,$C$7) -> - | ... AA37: =_xll.VAData($C$3,AA$8,$C37,AA$10,$C$5,$C$4,$C$7) -> 27130.693
B38: N_15532780 | C38: Gross-to-net adjustment rate - ML-007-MA - Alzheimer's disease psychosis (ADP) - US | D38: % | E38: =_xll.VAData($C$3,E$8,$C38,E$10,$C$5,$C$4,$C$7) -> - | F38: =_xll.VAData($C$3,F$8,$C38,F$10,$C$5,$C$4,$C$7) -> - | G38: =_xll.VAData($C$3,G$8,$C38,G$10,$C$5,$C$4,$C$7) -> - | H38: =_xll.VAData($C$3,H$8,$C38,H$10,$C$5,$C$4,$C$7) -> - | I38: =_xll.VAData($C$3,I$8,$C38,I$10,$C$5,$C$4,$C$7) -> 40 | J38: =_xll.VAData($C$3,J$8,$C38,J$10,$C$5,$C$4,$C$7) -> - | K38: =_xll.VAData($C$3,K$8,$C38,K$10,$C$5,$C$4,$C$7) -> - | L38: =_xll.VAData($C$3,L$8,$C38,L$10,$C$5,$C$4,$C$7) -> - | ... AA38: =_xll.VAData($C$3,AA$8,$C38,AA$10,$C$5,$C$4,$C$7) -> 32.666667
B39: N_15532779 | C39: Revenue per treatment - ML-007-MA - Alzheimer's disease psychosis (ADP) - US | D39: $Abs | E39: =_xll.VAData($C$3,E$8,$C39,E$10,$C$5,$C$4,$C$7) -> - | F39: =_xll.VAData($C$3,F$8,$C39,F$10,$C$5,$C$4,$C$7) -> - | G39: =_xll.VAData($C$3,G$8,$C39,G$10,$C$5,$C$4,$C$7) -> - | H39: =_xll.VAData($C$3,H$8,$C39,H$10,$C$5,$C$4,$C$7) -> - | I39: =_xll.VAData($C$3,I$8,$C39,I$10,$C$5,$C$4,$C$7) -> - | J39: =_xll.VAData($C$3,J$8,$C39,J$10,$C$5,$C$4,$C$7) -> - | K39: =_xll.VAData($C$3,K$8,$C39,K$10,$C$5,$C$4,$C$7) -> - | L39: =_xll.VAData($C$3,L$8,$C39,L$10,$C$5,$C$4,$C$7) -> - | ... AA39: =_xll.VAData($C$3,AA$8,$C39,AA$10,$C$5,$C$4,$C$7) -> 20852.786
B40: N_15532784 | C40: ML-007-MA - Alzheimer's disease psychosis (ADP) - US - Unadjusted | D40: $M | E40: =_xll.VAData($C$3,E$8,$C40,E$10,$C$5,$C$4,$C$7) -> - | F40: =_xll.VAData($C$3,F$8,$C40,F$10,$C$5,$C$4,$C$7) -> - | G40: =_xll.VAData($C$3,G$8,$C40,G$10,$C$5,$C$4,$C$7) -> - | H40: =_xll.VAData($C$3,H$8,$C40,H$10,$C$5,$C$4,$C$7) -> - | I40: =_xll.VAData($C$3,I$8,$C40,I$10,$C$5,$C$4,$C$7) -> 0 | J40: =_xll.VAData($C$3,J$8,$C40,J$10,$C$5,$C$4,$C$7) -> - | K40: =_xll.VAData($C$3,K$8,$C40,K$10,$C$5,$C$4,$C$7) -> - | L40: =_xll.VAData($C$3,L$8,$C40,L$10,$C$5,$C$4,$C$7) -> - | ... AA40: =_xll.VAData($C$3,AA$8,$C40,AA$10,$C$5,$C$4,$C$7) -> 786.41443
B41: N_15532782 | C41: POS - ML-007-MA - Alzheimer's disease psychosis (ADP) -US | D41: % | E41: =_xll.VAData($C$3,E$8,$C41,E$10,$C$5,$C$4,$C$7) -> - | F41: =_xll.VAData($C$3,F$8,$C41,F$10,$C$5,$C$4,$C$7) -> - | G41: =_xll.VAData($C$3,G$8,$C41,G$10,$C$5,$C$4,$C$7) -> - | H41: =_xll.VAData($C$3,H$8,$C41,H$10,$C$5,$C$4,$C$7) -> - | I41: =_xll.VAData($C$3,I$8,$C41,I$10,$C$5,$C$4,$C$7) -> - | J41: =_xll.VAData($C$3,J$8,$C41,J$10,$C$5,$C$4,$C$7) -> 30 | K41: =_xll.VAData($C$3,K$8,$C41,K$10,$C$5,$C$4,$C$7) -> 30 | L41: =_xll.VAData($C$3,L$8,$C41,L$10,$C$5,$C$4,$C$7) -> 30 | ... AA41: =_xll.VAData($C$3,AA$8,$C41,AA$10,$C$5,$C$4,$C$7) -> 30
B42: N_15532781 | C42: ML-007-MA- Alzheimer's disease psychosis (ADP) - US | D42: $M | E42: =_xll.VAData($C$3,E$8,$C42,E$10,$C$5,$C$4,$C$7) -> - | F42: =_xll.VAData($C$3,F$8,$C42,F$10,$C$5,$C$4,$C$7) -> - | G42: =_xll.VAData($C$3,G$8,$C42,G$10,$C$5,$C$4,$C$7) -> - | H42: =_xll.VAData($C$3,H$8,$C42,H$10,$C$5,$C$4,$C$7) -> - | I42: =_xll.VAData($C$3,I$8,$C42,I$10,$C$5,$C$4,$C$7) -> 0 | J42: =_xll.VAData($C$3,J$8,$C42,J$10,$C$5,$C$4,$C$7) -> - | K42: =_xll.VAData($C$3,K$8,$C42,K$10,$C$5,$C$4,$C$7) -> - | L42: =_xll.VAData($C$3,L$8,$C42,L$10,$C$5,$C$4,$C$7) -> - | ... AA42: =_xll.VAData($C$3,AA$8,$C42,AA$10,$C$5,$C$4,$C$7) -> 298.94417
B43: H
B44: N_15532785 | C44: ML-007-MA - Alzheimer's disease psychosis (ADP) - International - Unadjusted | D44: $M | E44: =_xll.VAData($C$3,E$8,$C44,E$10,$C$5,$C$4,$C$7) -> - | F44: =_xll.VAData($C$3,F$8,$C44,F$10,$C$5,$C$4,$C$7) -> - | G44: =_xll.VAData($C$3,G$8,$C44,G$10,$C$5,$C$4,$C$7) -> - | H44: =_xll.VAData($C$3,H$8,$C44,H$10,$C$5,$C$4,$C$7) -> - | I44: =_xll.VAData($C$3,I$8,$C44,I$10,$C$5,$C$4,$C$7) -> 0 | J44: =_xll.VAData($C$3,J$8,$C44,J$10,$C$5,$C$4,$C$7) -> - | K44: =_xll.VAData($C$3,K$8,$C44,K$10,$C$5,$C$4,$C$7) -> - | L44: =_xll.VAData($C$3,L$8,$C44,L$10,$C$5,$C$4,$C$7) -> - | ... AA44: =_xll.VAData($C$3,AA$8,$C44,AA$10,$C$5,$C$4,$C$7) -> 37.431478
B45: N_15532787 | C45: POS - ML-007-MA - Alzheimer's disease psychosis (ADP) - International | D45: % | E45: =_xll.VAData($C$3,E$8,$C45,E$10,$C$5,$C$4,$C$7) -> - | F45: =_xll.VAData($C$3,F$8,$C45,F$10,$C$5,$C$4,$C$7) -> - | G45: =_xll.VAData($C$3,G$8,$C45,G$10,$C$5,$C$4,$C$7) -> - | H45: =_xll.VAData($C$3,H$8,$C45,H$10,$C$5,$C$4,$C$7) -> - | I45: =_xll.VAData($C$3,I$8,$C45,I$10,$C$5,$C$4,$C$7) -> - | J45: =_xll.VAData($C$3,J$8,$C45,J$10,$C$5,$C$4,$C$7) -> 20 | K45: =_xll.VAData($C$3,K$8,$C45,K$10,$C$5,$C$4,$C$7) -> 20 | L45: =_xll.VAData($C$3,L$8,$C45,L$10,$C$5,$C$4,$C$7) -> 20 | ... AA45: =_xll.VAData($C$3,AA$8,$C45,AA$10,$C$5,$C$4,$C$7) -> 20
B46: N_15532786 | C46: ML-007-MA- Alzheimer's disease psychosis (ADP) - International | D46: $M | E46: =_xll.VAData($C$3,E$8,$C46,E$10,$C$5,$C$4,$C$7) -> - | F46: =_xll.VAData($C$3,F$8,$C46,F$10,$C$5,$C$4,$C$7) -> - | G46: =_xll.VAData($C$3,G$8,$C46,G$10,$C$5,$C$4,$C$7) -> - | H46: =_xll.VAData($C$3,H$8,$C46,H$10,$C$5,$C$4,$C$7) -> - | I46: =_xll.VAData($C$3,I$8,$C46,I$10,$C$5,$C$4,$C$7) -> 0 | J46: =_xll.VAData($C$3,J$8,$C46,J$10,$C$5,$C$4,$C$7) -> - | K46: =_xll.VAData($C$3,K$8,$C46,K$10,$C$5,$C$4,$C$7) -> - | L46: =_xll.VAData($C$3,L$8,$C46,L$10,$C$5,$C$4,$C$7) -> - | ... AA46: =_xll.VAData($C$3,AA$8,$C46,AA$10,$C$5,$C$4,$C$7) -> 7.4862955
B47: H
B48: N_15532807 | C48: ML-007-MA - Alzheimer's disease psychosis (ADP) - Unadjusted | D48: $M | E48: =_xll.VAData($C$3,E$8,$C48,E$10,$C$5,$C$4,$C$7) -> - | F48: =_xll.VAData($C$3,F$8,$C48,F$10,$C$5,$C$4,$C$7) -> - | G48: =_xll.VAData($C$3,G$8,$C48,G$10,$C$5,$C$4,$C$7) -> 0 | H48: =_xll.VAData($C$3,H$8,$C48,H$10,$C$5,$C$4,$C$7) -> 0 | I48: =_xll.VAData($C$3,I$8,$C48,I$10,$C$5,$C$4,$C$7) -> 0 | J48: =_xll.VAData($C$3,J$8,$C48,J$10,$C$5,$C$4,$C$7) -> - | K48: =_xll.VAData($C$3,K$8,$C48,K$10,$C$5,$C$4,$C$7) -> - | L48: =_xll.VAData($C$3,L$8,$C48,L$10,$C$5,$C$4,$C$7) -> - | ... AA48: =_xll.VAData($C$3,AA$8,$C48,AA$10,$C$5,$C$4,$C$7) -> 795.7723
B49: N_15532809 | C49: POS - ML-007-MA - Alzheimer's disease psychosis (ADP) | D49: % | E49: =_xll.VAData($C$3,E$8,$C49,E$10,$C$5,$C$4,$C$7) -> - | F49: =_xll.VAData($C$3,F$8,$C49,F$10,$C$5,$C$4,$C$7) -> - | G49: =_xll.VAData($C$3,G$8,$C49,G$10,$C$5,$C$4,$C$7) -> - | H49: =_xll.VAData($C$3,H$8,$C49,H$10,$C$5,$C$4,$C$7) -> - | I49: =_xll.VAData($C$3,I$8,$C49,I$10,$C$5,$C$4,$C$7) -> - | J49: =_xll.VAData($C$3,J$8,$C49,J$10,$C$5,$C$4,$C$7) -> 30 | K49: =_xll.VAData($C$3,K$8,$C49,K$10,$C$5,$C$4,$C$7) -> 30 | L49: =_xll.VAData($C$3,L$8,$C49,L$10,$C$5,$C$4,$C$7) -> 30 | ... AA49: =_xll.VAData($C$3,AA$8,$C49,AA$10,$C$5,$C$4,$C$7) -> 30
B50: N_15532804 | C50: ML-007-MA - Alzheimer's disease psychosis (ADP) | D50: $M | E50: =_xll.VAData($C$3,E$8,$C50,E$10,$C$5,$C$4,$C$7) -> - | F50: =_xll.VAData($C$3,F$8,$C50,F$10,$C$5,$C$4,$C$7) -> - | G50: =_xll.VAData($C$3,G$8,$C50,G$10,$C$5,$C$4,$C$7) -> 0 | H50: =_xll.VAData($C$3,H$8,$C50,H$10,$C$5,$C$4,$C$7) -> 0 | I50: =_xll.VAData($C$3,I$8,$C50,I$10,$C$5,$C$4,$C$7) -> 0 | J50: =_xll.VAData($C$3,J$8,$C50,J$10,$C$5,$C$4,$C$7) -> - | K50: =_xll.VAData($C$3,K$8,$C50,K$10,$C$5,$C$4,$C$7) -> - | L50: =_xll.VAData($C$3,L$8,$C50,L$10,$C$5,$C$4,$C$7) -> - | ... AA50: =_xll.VAData($C$3,AA$8,$C50,AA$10,$C$5,$C$4,$C$7) -> 301.4396
B51: H
B52: N_15532850 | C52: ML-007-MA - US - Unadjusted | D52: $M | E52: =_xll.VAData($C$3,E$8,$C52,E$10,$C$5,$C$4,$C$7) -> - | F52: =_xll.VAData($C$3,F$8,$C52,F$10,$C$5,$C$4,$C$7) -> - | G52: =_xll.VAData($C$3,G$8,$C52,G$10,$C$5,$C$4,$C$7) -> - | H52: =_xll.VAData($C$3,H$8,$C52,H$10,$C$5,$C$4,$C$7) -> - | I52: =_xll.VAData($C$3,I$8,$C52,I$10,$C$5,$C$4,$C$7) -> 0 | J52: =_xll.VAData($C$3,J$8,$C52,J$10,$C$5,$C$4,$C$7) -> - | K52: =_xll.VAData($C$3,K$8,$C52,K$10,$C$5,$C$4,$C$7) -> - | L52: =_xll.VAData($C$3,L$8,$C52,L$10,$C$5,$C$4,$C$7) -> - | ... AA52: =_xll.VAData($C$3,AA$8,$C52,AA$10,$C$5,$C$4,$C$7) -> 1511.2867
B53: N_15532851 | C53: ML-007-MA - US | D53: $M | E53: =_xll.VAData($C$3,E$8,$C53,E$10,$C$5,$C$4,$C$7) -> - | F53: =_xll.VAData($C$3,F$8,$C53,F$10,$C$5,$C$4,$C$7) -> - | G53: =_xll.VAData($C$3,G$8,$C53,G$10,$C$5,$C$4,$C$7) -> - | H53: =_xll.VAData($C$3,H$8,$C53,H$10,$C$5,$C$4,$C$7) -> - | I53: =_xll.VAData($C$3,I$8,$C53,I$10,$C$5,$C$4,$C$7) -> 0 | J53: =_xll.VAData($C$3,J$8,$C53,J$10,$C$5,$C$4,$C$7) -> - | K53: =_xll.VAData($C$3,K$8,$C53,K$10,$C$5,$C$4,$C$7) -> - | L53: =_xll.VAData($C$3,L$8,$C53,L$10,$C$5,$C$4,$C$7) -> - | ... AA53: =_xll.VAData($C$3,AA$8,$C53,AA$10,$C$5,$C$4,$C$7) -> 784.82591
B54: H
B55: N_15532847 | C55: ML-007-MA - International - Unadjusted | D55: $M | E55: =_xll.VAData($C$3,E$8,$C55,E$10,$C$5,$C$4,$C$7) -> - | F55: =_xll.VAData($C$3,F$8,$C55,F$10,$C$5,$C$4,$C$7) -> - | G55: =_xll.VAData($C$3,G$8,$C55,G$10,$C$5,$C$4,$C$7) -> - | H55: =_xll.VAData($C$3,H$8,$C55,H$10,$C$5,$C$4,$C$7) -> - | I55: =_xll.VAData($C$3,I$8,$C55,I$10,$C$5,$C$4,$C$7) -> 0 | J55: =_xll.VAData($C$3,J$8,$C55,J$10,$C$5,$C$4,$C$7) -> - | K55: =_xll.VAData($C$3,K$8,$C55,K$10,$C$5,$C$4,$C$7) -> - | L55: =_xll.VAData($C$3,L$8,$C55,L$10,$C$5,$C$4,$C$7) -> - | ... AA55: =_xll.VAData($C$3,AA$8,$C55,AA$10,$C$5,$C$4,$C$7) -> 82.413714
B56: N_15532848 | C56: ML-007-MA - International | D56: $M | E56: =_xll.VAData($C$3,E$8,$C56,E$10,$C$5,$C$4,$C$7) -> - | F56: =_xll.VAData($C$3,F$8,$C56,F$10,$C$5,$C$4,$C$7) -> - | G56: =_xll.VAData($C$3,G$8,$C56,G$10,$C$5,$C$4,$C$7) -> - | H56: =_xll.VAData($C$3,H$8,$C56,H$10,$C$5,$C$4,$C$7) -> - | I56: =_xll.VAData($C$3,I$8,$C56,I$10,$C$5,$C$4,$C$7) -> 0 | J56: =_xll.VAData($C$3,J$8,$C56,J$10,$C$5,$C$4,$C$7) -> - | K56: =_xll.VAData($C$3,K$8,$C56,K$10,$C$5,$C$4,$C$7) -> - | L56: =_xll.VAData($C$3,L$8,$C56,L$10,$C$5,$C$4,$C$7) -> - | ... AA56: =_xll.VAData($C$3,AA$8,$C56,AA$10,$C$5,$C$4,$C$7) -> 29.977414
B57: H
B58: N_15532833 | C58: ML-007-MA - Unadjusted | D58: $M | E58: =_xll.VAData($C$3,E$8,$C58,E$10,$C$5,$C$4,$C$7) -> - | F58: =_xll.VAData($C$3,F$8,$C58,F$10,$C$5,$C$4,$C$7) -> - | G58: =_xll.VAData($C$3,G$8,$C58,G$10,$C$5,$C$4,$C$7) -> 0 | H58: =_xll.VAData($C$3,H$8,$C58,H$10,$C$5,$C$4,$C$7) -> 0 | I58: =_xll.VAData($C$3,I$8,$C58,I$10,$C$5,$C$4,$C$7) -> 0 | J58: =_xll.VAData($C$3,J$8,$C58,J$10,$C$5,$C$4,$C$7) -> 0 | K58: =_xll.VAData($C$3,K$8,$C58,K$10,$C$5,$C$4,$C$7) -> 0 | L58: =_xll.VAData($C$3,L$8,$C58,L$10,$C$5,$C$4,$C$7) -> 0 | ... AA58: =_xll.VAData($C$3,AA$8,$C58,AA$10,$C$5,$C$4,$C$7) -> 1531.8901
B59: N_15532854 | C59: ML-007-MA | D59: $M | E59: =_xll.VAData($C$3,E$8,$C59,E$10,$C$5,$C$4,$C$7) -> - | F59: =_xll.VAData($C$3,F$8,$C59,F$10,$C$5,$C$4,$C$7) -> - | G59: =_xll.VAData($C$3,G$8,$C59,G$10,$C$5,$C$4,$C$7) -> 0 | H59: =_xll.VAData($C$3,H$8,$C59,H$10,$C$5,$C$4,$C$7) -> 0 | I59: =_xll.VAData($C$3,I$8,$C59,I$10,$C$5,$C$4,$C$7) -> 0 | J59: =_xll.VAData($C$3,J$8,$C59,J$10,$C$5,$C$4,$C$7) -> - | K59: =_xll.VAData($C$3,K$8,$C59,K$10,$C$5,$C$4,$C$7) -> - | L59: =_xll.VAData($C$3,L$8,$C59,L$10,$C$5,$C$4,$C$7) -> - | ... AA59: =_xll.VAData($C$3,AA$8,$C59,AA$10,$C$5,$C$4,$C$7) -> 794.81839
B60: H
C62: Notes:
C63: By default, this downloaded page includes data from 1QFY-2025 (1QFY-2025) to FY-2035 (FY-2035)
C64: It contains the same period types as those selected for the worksheet on the Visible Alpha web platform.
C65: Visible Alpha has Quarterly and Annual data for MPLT_US from Jan 2022 to Dec 2047

Sheet Ph2 Scenarios
C3: Peak Sh in Schizo | D3: Schizo POS | E3: ADP POS | F3: Our Est. PT
B4: Current PT | C4: 0.35 | D4: 0.55 | E4: 0.25 | F4: 37
B5: No Safety Differentiation | C5: 0.2 | D5: 0.6 | E5: 0.25 | F5: 25 | G5: =F5/F4-1 -> -0.32432432
B6: Safety Differentiation (Base case) | C6: 0.35 | D6: 0.65 | E6: 0.3 | F6: 47 | G6: =F6/$F$4-1 -> 0.27027027
B7: Both Safety and Efficacy Differentiation | C7: 0.4 | D7: 0.65 | E7: 0.3 | F7: 53 | G7: =F7/$F$4-1 -> 0.43243243
E11: PoS (%) | F11: Stock Move (%)
B12: Scenario 1 | C12: Base | D12: Superior on tolerability and convenience with comparable efficacy | E12: 65 | F12: +mid-to-high 20s
B13: Scenario 2 | C13: Downside | D13: Comparable on both efficacy and tolerability but superior on convenience | E13: 20 | F13: -low-30s
B14: Scenario 3 | C14: Upside | D14: Superior on tolerability, convenience, and efficacy | E14: 10 | F14: +40s

Sheet CF
A1: Maplight Therpeutics
A2: Cash Flow
A3: ($ Millions, except per-share data)
B5: =BS!B4 -> 2024A | C5: =BS!C4 -> 2025A | D5: =BS!D4 -> 2026E | E5: =BS!E4 -> 2027E | F5: =BS!F4 -> 2028E | G5: =BS!G4 -> 2029E | H5: =BS!H4 -> 2030E | I5: =BS!I4 -> 2031E | ... M5: =BS!M4 -> 2035E
A6: CASH FLOWS FROM OPERATING ACTIVITIES:
A7: Net loss | B7: -77.58 | C7: -161.152 | D7: =IS!AJ35 -> -206.4 | E7: =IS!AK35 -> -214.392 | F7: =IS!AL35 -> -253.38891 | G7: =IS!AM35 -> -255.18414 | H7: =IS!AN35 -> -163.26172 | I7: =IS!AO35 -> 26.986543 | J7: =IS!AP35 -> 301.66993 | K7: =IS!AQ35 -> 526.57302 | ... M7: =IS!AS35 -> 818.20368
A8: Adjustments to reconcile net loss to net cash used in operating activities:
A9: Depreciation | B9: 0.701 | C9: 0.578 | D9: =C9 -> 0.578 | E9: =D9 -> 0.578 | F9: =E9 -> 0.578 | G9: =F9 -> 0.578 | H9: =G9 -> 0.578 | I9: =H9 -> 0.578 | J9: =I9 -> 0.578 | K9: =J9 -> 0.578 | ... M9: =L9 -> 0.578
A10: Stock-based compensation expense | B10: 1.08 | C10: 36.006 | D10: =OPEX!T11+OPEX!T32 -> 40.4 | E10: =OPEX!U11+OPEX!U32 -> 41.612 | F10: =OPEX!V11+OPEX!V32 -> 42.86036 | G10: =OPEX!W11+OPEX!W32 -> 44.146171 | H10: =OPEX!X11+OPEX!X32 -> 45.470556 | I10: =OPEX!Y11+OPEX!Y32 -> 46.834673 | J10: =OPEX!Z11+OPEX!Z32 -> 48.239713 | K10: =OPEX!AA11+OPEX!AA32 -> 49.686904 | ... M10: =OPEX!AC11+OPEX!AC32 -> 52.712837
A11: Net amorization of premiums and accretion of discounts on investments | B11: -1.741 | C11: -2.102 | D11: =C11 -> -2.102 | E11: =D11 -> -2.102 | F11: =E11 -> -2.102 | G11: =F11 -> -2.102 | H11: =G11 -> -2.102 | I11: =H11 -> -2.102 | J11: =I11 -> -2.102 | K11: =J11 -> -2.102 | ... M11: =L11 -> -2.102
A12: Common stock issued to NeuroSolis | B12: 0 | C12: 0.496 | D12: =C12 -> 0.496 | E12: =D12 -> 0.496 | F12: =E12 -> 0.496 | G12: =F12 -> 0.496 | H12: =G12 -> 0.496 | I12: =H12 -> 0.496 | J12: =I12 -> 0.496 | K12: =J12 -> 0.496 | ... M12: =L12 -> 0.496
A13: Non-cash lease expense | B13: 0.745 | C13: 0.866 | D13: =BS!D23-BS!C23 -> 0.1 | E13: =BS!E23-BS!D23 -> 0.1 | F13: =BS!F23-BS!E23 -> 0.1 | G13: =BS!G23-BS!F23 -> 0.1 | H13: =BS!H23-BS!G23 -> 0.1 | I13: =BS!I23-BS!H23 -> 0.1 | J13: =BS!J23-BS!I23 -> 0.1 | K13: =BS!K23-BS!J23 -> 0.1 | ... M13: =BS!M23-BS!L23 -> 0.1
A14: Loss from equity method investment | B14: 0.986 | C14: 0 | D14: =C14 -> 0 | E14: =D14 -> 0 | F14: =E14 -> 0 | G14: =F14 -> 0 | H14: =G14 -> 0 | I14: =H14 -> 0 | J14: =I14 -> 0 | K14: =J14 -> 0 | ... M14: =L14 -> 0
A15: Loss from disposal and write-off of equipment | B15: 0.059 | C15: 0.007 | D15: =C15 -> 0.007 | E15: =D15 -> 0.007 | F15: =E15 -> 0.007 | G15: =F15 -> 0.007 | H15: =G15 -> 0.007 | I15: =H15 -> 0.007 | J15: =I15 -> 0.007 | K15: =J15 -> 0.007 | ... M15: =L15 -> 0.007
A16: Changes in operating assets and liabilities: | B16: =SUM(B17:B24) -> -3.065 | C16: =SUM(C17:C24) -> -12.836 | D16: =SUM(D17:D24) -> 2.511 | E16: =SUM(E17:E24) -> 2.8 | F16: =SUM(F17:F24) -> 2.8 | G16: =SUM(G17:G24) -> 1.6183604 | H16: =SUM(H17:H24) -> -4.9876896 | I16: =SUM(I17:I24) -> -8.4956972 | ... M16: =SUM(M17:M24) -> -4.4024917
A17: Accounts receivable | B17: 0 | C17: 0 | D17: =BS!C9-BS!D9 -> 0 | E17: =BS!D9-BS!E9 -> 0 | F17: =BS!E9-BS!F9 -> 0 | G17: =BS!F9-BS!G9 -> -1.1816396 | H17: =BS!G9-BS!H9 -> -7.7876896 | I17: =BS!H9-BS!I9 -> -15.390749 | J17: =BS!I9-BS!J9 -> -22.607592 | K17: =BS!J9-BS!K9 -> -20.885956 | ... M17: =BS!L9-BS!M9 -> -16.807344
A18: Prepaid expenses and other current assets | B18: -2.277 | C18: -13.103 | D18: =BS!C10-BS!D10 -> -0.5 | E18: =BS!D10-BS!E10 -> -0.5 | F18: =BS!E10-BS!F10 -> -0.5 | G18: =BS!F10-BS!G10 -> -0.5 | H18: =BS!G10-BS!H10 -> -0.5 | I18: =BS!H10-BS!I10 -> -0.5 | J18: =BS!I10-BS!J10 -> -0.5 | K18: =BS!J10-BS!K10 -> -0.5 | ... M18: =BS!L10-BS!M10 -> -0.5
A19: Operating lease, right-of-use asset | B19: 0 | C19: 0 | D19: =BS!C14-BS!D14 -> 0 | E19: =BS!D14-BS!E14 -> 0 | F19: =BS!E14-BS!F14 -> 0 | G19: =BS!F14-BS!G14 -> 0 | H19: =BS!G14-BS!H14 -> 0 | I19: =BS!H14-BS!I14 -> 0 | J19: =BS!I14-BS!J14 -> 0 | K19: =BS!J14-BS!K14 -> 0 | ... M19: =BS!L14-BS!M14 -> 0
A20: Other assets | B20: 0 | C20: 0 | D20: =BS!C16-BS!D16 -> 0 | E20: =BS!D16-BS!E16 -> 0 | F20: =BS!E16-BS!F16 -> 0 | G20: =BS!F16-BS!G16 -> 0 | H20: =BS!G16-BS!H16 -> 0 | I20: =BS!H16-BS!I16 -> 0 | J20: =BS!I16-BS!J16 -> 0 | K20: =BS!J16-BS!K16 -> 0 | ... M20: =BS!L16-BS!M16 -> 0
A21: Accounts payable | B21: -1.345 | C21: 1.384 | D21: =BS!D21-BS!C21 -> 1.211 | E21: =BS!E21-BS!D21 -> 1.5 | F21: =BS!F21-BS!E21 -> 1.5 | G21: =BS!G21-BS!F21 -> 1.5 | H21: =BS!H21-BS!G21 -> 1.5 | I21: =BS!I21-BS!H21 -> 5.5950514 | J21: =BS!J21-BS!I21 -> 14.937159 | K21: =BS!K21-BS!J21 -> 13.79965 | ... M21: =BS!M21-BS!L21 -> 11.104852
A22: Accrued expenses and other current liabilities | B22: 2.169 | C22: 2.899 | D22: =BS!D22-BS!C22 -> 2 | E22: =BS!E22-BS!D22 -> 2 | F22: =BS!F22-BS!E22 -> 2 | G22: =BS!G22-BS!F22 -> 2 | H22: =BS!H22-BS!G22 -> 2 | I22: =BS!I22-BS!H22 -> 2 | J22: =BS!J22-BS!I22 -> 2 | K22: =BS!K22-BS!J22 -> 2 | ... M22: =BS!M22-BS!L22 -> 2
A23: Operating lease liability | B23: -0.653 | C23: -0.777 | D23: =BS!D26-BS!C26 -> -0.2 | E23: =BS!E26-BS!D26 -> -0.2 | F23: =BS!F26-BS!E26 -> -0.2 | G23: =BS!G26-BS!F26 -> -0.2 | H23: =BS!H26-BS!G26 -> -0.2 | I23: =BS!I26-BS!H26 -> -0.2 | J23: =BS!J26-BS!I26 -> -0.2 | K23: =BS!K26-BS!J26 -> -0.2 | ... M23: =BS!M26-BS!L26 -> -0.2
A24: Deferred grant earnings | B24: -0.959 | C24: -3.239 | D24: =BS!D24-BS!C24 -> 0 | E24: =BS!E24-BS!D24 -> 0 | F24: =BS!F24-BS!E24 -> 0 | G24: =BS!G24-BS!F24 -> 0 | H24: =BS!H24-BS!G24 -> 0 | I24: =BS!I24-BS!H24 -> 0 | J24: =BS!J24-BS!I24 -> 0 | K24: =BS!K24-BS!J24 -> 0 | ... M24: =BS!M24-BS!L24 -> 0
A25: Net cash used in operating activities | B25: =SUM(B7,B9:B16) -> -78.815 | C25: =SUM(C7,C9:C16) -> -138.137 | D25: =SUM(D7,D9:D16) -> -164.41 | E25: =SUM(E7,E9:E16) -> -170.901 | F25: =SUM(F7,F9:F16) -> -208.64955 | G25: =SUM(G7,G9:G16) -> -210.34061 | H25: =SUM(H7,H9:H16) -> -123.69985 | I25: =SUM(I7,I9:I16) -> 64.404518 | ... M25: =SUM(M7,M9:M16) -> 865.59302
A27: CASH FLOWS FROM INVESTING ACTIVITIES:
A28: Purchases of short-term and long-term investments | B28: -125.018 | C28: -408.234 | D28: 100 | E28: 100 | F28: 50 | G28: 8.4 | H28: 0 | I28: =H28 -> 0 | J28: =I28 -> 0 | K28: =J28 -> 0 | L28: =K28 -> 0 | M28: =L28 -> 0
A29: Maturities of marketable debt securities | B29: 45 | C29: 85.5 | D29: 50 | E29: 0 | F29: =E29 -> 0 | G29: =F29 -> 0 | H29: =G29 -> 0 | I29: =H29 -> 0 | J29: =I29 -> 0 | K29: =J29 -> 0 | L29: =K29 -> 0 | M29: =L29 -> 0
A30: Purchases of property and equipment | B30: -0.77 | C30: -0.473 | D30: =C30 -> -0.473 | E30: =D30 -> -0.473 | F30: =E30 -> -0.473 | G30: =F30 -> -0.473 | H30: =G30 -> -0.473 | I30: =H30 -> -0.473 | J30: =I30 -> -0.473 | K30: =J30 -> -0.473 | ... M30: =L30 -> -0.473
A31: Net cash provided by (used in) investing activities | B31: =SUM(B28:B30) -> -80.788 | C31: =SUM(C28:C30) -> -323.207 | D31: =SUM(D28:D30) -> 149.527 | E31: =SUM(E28:E30) -> 99.527 | F31: =SUM(F28:F30) -> 49.527 | G31: =SUM(G28:G30) -> 7.927 | H31: =SUM(H28:H30) -> -0.473 | I31: =SUM(I28:I30) -> -0.473 | ... M31: =SUM(M28:M30) -> -0.473
A33: CASH FLOWS FROM FINANCING ACTIVITIES:
A34: Payments of deferred financing costs | B34: -2.19 | C34: -5.021 | D34: 0 | E34: =D34 -> 0 | F34: =E34 -> 0 | G34: =F34 -> 0 | H34: =G34 -> 0 | I34: =H34 -> 0 | J34: =I34 -> 0 | K34: =J34 -> 0 | L34: =K34 -> 0 | M34: =L34 -> 0
A35: Proceeds from issuance of Series C | B35: 119.956 | C35: 0 | D35: =C35 -> 0 | E35: =D35 -> 0 | F35: =E35 -> 0 | G35: =F35 -> 0 | H35: =G35 -> 0 | I35: =H35 -> 0 | J35: =I35 -> 0 | K35: =J35 -> 0 | ... M35: =L35 -> 0
A36: Proceeds from issuance of Series D | B36: 0 | C36: 198.84 | D36: 0 | E36: =D36 -> 0 | F36: =E36 -> 0 | G36: =F36 -> 0 | H36: =G36 -> 0 | I36: =H36 -> 0 | J36: =I36 -> 0 | K36: =J36 -> 0 | L36: =K36 -> 0 | M36: =L36 -> 0
A37: Proceeds from exercise of stock options | B37: 0.294 | C37: 0.285 | D37: =C37 -> 0.285 | E37: =D37 -> 0.285 | F37: =E37 -> 0.285 | G37: =F37 -> 0.285 | H37: =G37 -> 0.285 | I37: =H37 -> 0.285 | J37: =I37 -> 0.285 | K37: =J37 -> 0.285 | ... M37: =L37 -> 0.285
A38: Proceeds from issuance of common stock upon stock option exercises | B38: 0 | C38: 275.716 | D38: =D46 -> 350 | E38: =E46 -> 200 | F38: =F46 -> 0 | G38: =G46 -> 200 | H38: =H46 -> 0 | I38: =I46 -> 0 | J38: =J46 -> 0 | K38: =K46 -> 0 | ... M38: =M46 -> 0
A39: Proceeds from long-term debt | B39: 0 | C39: 0 | D39: =C39 -> 0 | E39: =D39 -> 0 | F39: =E39 -> 0 | G39: =F39 -> 0 | H39: =G39 -> 0 | I39: =H39 -> 0 | J39: =I39 -> 0 | K39: =J39 -> 0 | ... M39: =L39 -> 0
A40: Net cash provided by financing activities | B40: =SUM(B34:B39) -> 118.06 | C40: =SUM(C34:C39) -> 469.82 | D40: =SUM(D34:D39) -> 350.285 | E40: =SUM(E34:E39) -> 200.285 | F40: =SUM(F34:F39) -> 0.285 | G40: =SUM(G34:G39) -> 200.285 | H40: =SUM(H34:H39) -> 0.285 | I40: =SUM(I34:I39) -> 0.285 | ... M40: =SUM(M34:M39) -> 0.285
A41: Increase (decrease) in cash, cash equivalents, and restricted cash | B41: =B25+B31+B40 -> -41.543 | C41: =C25+C31+C40 -> 8.476 | D41: =D25+D31+D40 -> 335.402 | E41: =E25+E31+E40 -> 128.911 | F41: =F25+F31+F40 -> -158.83755 | G41: =G25+G31+G40 -> -2.1286132 | H41: =H25+H31+H40 -> -123.88785 | I41: =I25+I31+I40 -> 64.216518 | ... M41: =M25+M31+M40 -> 865.40502
A42: Cash, cash equivalents, and restricted cash, beginning of period | B42: 80.003 | C42: =B43 -> 38.46 | D42: =C43 -> 46.936 | E42: =D43 -> 382.338 | F42: =E43 -> 511.249 | G42: =F43 -> 352.41145 | H42: =G43 -> 350.28284 | I42: =H43 -> 226.39499 | J42: =I43 -> 290.6115 | ... M42: =L43 -> 1897.3413
A43: Cash, cash equivalents, and restricted cash, end of period | B43: =B42+B40+B31+B25 -> 38.46 | C43: =C42+C40+C31+C25 -> 46.936 | D43: =D42+D40+D31+D25 -> 382.338 | E43: =E42+E40+E31+E25 -> 511.249 | F43: =F42+F40+F31+F25 -> 352.41145 | G43: =G42+G40+G31+G25 -> 350.28284 | H43: =H42+H40+H31+H25 -> 226.39499 | I43: =I42+I40+I31+I25 -> 290.6115 | ... M43: =M42+M40+M31+M25 -> 2762.7463
A44: Source: Company reports; Needham & Company, LLC estimates
A46: Cash Raised | D46: 350 | E46: 200 | F46: =F35 -> 0 | G46: 200 | H46: =H35 -> 0 | I46: =I35 -> 0 | J46: =J35 -> 0 | K46: =K35 -> 0 | L46: =L35 -> 0 | M46: =M35 -> 0
A47: Shares Issued | D47: =D46/D48 -> 14 | E47: =E46/E48 -> 6.9565217 | F47: =F46/F48 -> 0 | G47: =G46/G48 -> 6.3097703 | H47: =H46/H48 -> 0 | I47: =I46/I48 -> 0 | J47: =J46/J48 -> 0 | K47: =K46/K48 -> 0 | ... M47: =M46/M48 -> 0
A48: Stock Price | D48: 25 | E48: =D48*1.15 -> 28.75 | F48: =E48*1.05 -> 30.1875 | G48: =F48*1.05 -> 31.696875 | H48: =G48*1.05 -> 33.281719 | I48: =H48*1.05 -> 34.945805 | J48: =I48*1.05 -> 36.693095 | K48: =J48*1.05 -> 38.52775 | L48: =K48*1.05 -> 40.454137 | M48: =L48*1.05 -> 42.476844
A51: Supplemental disclosure of noncash investing and financing information:
A52: Conversion of Series A non-voting convertible preferred stock into common stock
A53: Issuance of shares in partial settlement of CVR liability

Sheet BS
A1: Maplight Therpeutics
A2: Balance Sheet
A3: ($ Millions, except per-share data)
B4: 2024A | C4: =IS!AE4 -> 2025A | D4: =IS!AJ4 -> 2026E | E4: =IS!AK4 -> 2027E | F4: =IS!AL4 -> 2028E | G4: =IS!AM4 -> 2029E | H4: =IS!AN4 -> 2030E | I4: =IS!AO4 -> 2031E | J4: =IS!AP4 -> 2032E | K4: =IS!AQ4 -> 2033E | ... M4: =IS!AS4 -> 2035E
A5: ASSETS
A6: Current assets:
A7: Cash and cash equivalents | B7: 38.253 | C7: 46.729 | D7: =CF!D43-D13 -> 382.131 | E7: =CF!E43-E13 -> 511.042 | F7: =CF!F43-F13 -> 352.20445 | G7: =CF!G43-G13 -> 350.07584 | H7: =CF!H43-H13 -> 226.18799 | I7: =CF!I43-I13 -> 290.4045 | J7: =CF!J43-J13 -> 632.83471 | K7: =CF!K43-K13 -> 1202.1993 | ... M7: =CF!M43-M13 -> 2762.5393 | O7: =D7-C7 -> 335.402
A8: Short-term investments | B8: 70.542 | C8: 258.374 | D8: =C8-CF!D28 -> 158.374 | E8: =D8-CF!E28 -> 58.374 | F8: =E8-CF!F28 -> 8.374 | G8: =F8-CF!G28 -> -0.026 | H8: =G8-CF!H28 -> -0.026 | I8: =H8-CF!I28 -> -0.026 | J8: =I8-CF!J28 -> -0.026 | K8: =J8-CF!K28 -> -0.026 | ... M8: =L8-CF!M28 -> -0.026 | O8: =D8-C8 -> -100
A9: Accounts receivable | B9: 0 | C9: 0 | D9: =D49 -> 0 | E9: =E49 -> 0 | F9: =F49 -> 0 | G9: =G49 -> 1.1816396 | H9: =H49 -> 8.9693292 | I9: =I49 -> 24.360078 | J9: =J49 -> 46.96767 | K9: =K49 -> 67.853626 | ... M9: =M49 -> 103.30072 | O9: =D9-C9 -> 0
A10: Prepaid expenses and other current assets | B10: 5.807 | C10: 19.567 | D10: =C10+0.5 -> 20.067 | E10: =D10+0.5 -> 20.567 | F10: =E10+0.5 -> 21.067 | G10: =F10+0.5 -> 21.567 | H10: =G10+0.5 -> 22.067 | I10: =H10+0.5 -> 22.567 | J10: =I10+0.5 -> 23.067 | K10: =J10+0.5 -> 23.567 | ... M10: =L10+0.5 -> 24.567 | O10: =D10-C10 -> 0.5
A11: Total current assets | B11: =SUM(B7:B10) -> 114.602 | C11: =SUM(C7:C10) -> 324.67 | D11: =SUM(D7:D10) -> 560.572 | E11: =SUM(E7:E10) -> 589.983 | F11: =SUM(F7:F10) -> 381.64545 | G11: =SUM(G7:G10) -> 372.79848 | H11: =SUM(H7:H10) -> 257.19832 | I11: =SUM(I7:I10) -> 337.30558 | ... M11: =SUM(M7:M10) -> 2890.381
A12: Long-term investments | B12: 11.38 | C12: 147.993 | D12: =C12-CF!D29 -> 97.993 | E12: =D12-CF!E29 -> 97.993 | F12: =E12-CF!F29 -> 97.993 | G12: =F12-CF!G29 -> 97.993 | H12: =G12-CF!H29 -> 97.993 | I12: =H12-CF!I29 -> 97.993 | J12: =I12-CF!J29 -> 97.993 | K12: =J12-CF!K29 -> 97.993 | ... M12: =L12-CF!M29 -> 97.993 | O12: =D12-C12 -> -50
A13: Restricted cash | B13: 0.207 | C13: 0.207 | D13: =C13 -> 0.207 | E13: =D13 -> 0.207 | F13: =E13 -> 0.207 | G13: =F13 -> 0.207 | H13: =G13 -> 0.207 | I13: =H13 -> 0.207 | J13: =I13 -> 0.207 | K13: =J13 -> 0.207 | ... M13: =L13 -> 0.207 | O13: =D13-C13 -> 0 | P13: Not linked
A14: Operating lease, right-of-use asset | B14: 6.354 | C14: 5.488 | D14: =C14 -> 5.488 | E14: =D14 -> 5.488 | F14: =E14 -> 5.488 | G14: =F14 -> 5.488 | H14: =G14 -> 5.488 | I14: =H14 -> 5.488 | J14: =I14 -> 5.488 | K14: =J14 -> 5.488 | ... M14: =L14 -> 5.488 | O14: =D14-C14 -> 0
A15: Property and equipment, net | B15: 1.207 | C15: 1.095 | D15: =C15-CF!D30-CF!D9 -> 0.99 | E15: =D15-CF!E30-CF!E9 -> 0.885 | F15: =E15-CF!F30-CF!F9 -> 0.78 | G15: =F15-CF!G30-CF!G9 -> 0.675 | H15: =G15-CF!H30-CF!H9 -> 0.57 | I15: =H15-CF!I30-CF!I9 -> 0.465 | J15: =I15-CF!J30-CF!J9 -> 0.36 | K15: =J15-CF!K30-CF!K9 -> 0.255 | ... M15: =L15-CF!M30-CF!M9 -> 0.045 | O15: =D15-C15 -> -0.105
A16: Other assets | B16: 3.166 | C16: 0.059 | D16: =C16 -> 0.059 | E16: =D16 -> 0.059 | F16: =E16 -> 0.059 | G16: =F16 -> 0.059 | H16: =G16 -> 0.059 | I16: =H16 -> 0.059 | J16: =I16 -> 0.059 | K16: =J16 -> 0.059 | ... M16: =L16 -> 0.059 | O16: =D16-C16 -> 0
A17: Total assets | B17: =SUM(B11:B16) -> 136.916 | C17: =SUM(C11:C16) -> 479.512 | D17: =SUM(D11:D16) -> 665.309 | E17: =SUM(E11:E16) -> 694.615 | F17: =SUM(F11:F16) -> 486.17245 | G17: =SUM(G11:G16) -> 477.22048 | H17: =SUM(H11:H16) -> 361.51532 | I17: =SUM(I11:I16) -> 441.51758 | ... M17: =SUM(M11:M16) -> 2994.173
A19: LIABILITIES AND STOCKHOLDERS’ EQUITY
A20: Current liabilities:
A21: Accounts payable | B21: 1.912 | C21: 3.289 | D21: 4.5 | E21: =D21+1.5 -> 6 | F21: =E21+1.5 -> 7.5 | G21: =F21+1.5 -> 9 | H21: =G21+1.5 -> 10.5 | I21: =I53 -> 16.095051 | J21: =J53 -> 31.032211 | K21: =K53 -> 44.83186 | L21: =L53 -> 57.14741 | M21: =M53 -> 68.252263 | O21: =D21-C21 -> 1.211
A22: Accrued expenses and other current liabilities | B22: 9.991 | C22: 12.049 | D22: =C22+2 -> 14.049 | E22: =D22+2 -> 16.049 | F22: =E22+2 -> 18.049 | G22: =F22+2 -> 20.049 | H22: =G22+2 -> 22.049 | I22: =H22+2 -> 24.049 | J22: =I22+2 -> 26.049 | K22: =J22+2 -> 28.049 | ... M22: =L22+2 -> 32.049 | O22: =D22-C22 -> 2
A23: Lease liability - current | B23: 0.778 | C23: 0.891 | D23: =C23+0.1 -> 0.991 | E23: =D23+0.1 -> 1.091 | F23: =E23+0.1 -> 1.191 | G23: =F23+0.1 -> 1.291 | H23: =G23+0.1 -> 1.391 | I23: =H23+0.1 -> 1.491 | J23: =I23+0.1 -> 1.591 | K23: =J23+0.1 -> 1.691 | ... M23: =L23+0.1 -> 1.891 | O23: =D23-C23 -> 0.1
A24: Deferred grant earnings | B24: 3.239 | C24: 0 | D24: =C24 -> 0 | E24: =D24 -> 0 | F24: =E24 -> 0 | G24: =F24 -> 0 | H24: =G24 -> 0 | I24: =H24 -> 0 | J24: =I24 -> 0 | K24: =J24 -> 0 | ... M24: =L24 -> 0 | O24: =D24-C24 -> 0
A25: Total current liabilities | B25: =SUM(B21:B24) -> 15.92 | C25: =SUM(C21:C24) -> 16.229 | D25: =SUM(D21:D24) -> 19.54 | E25: =SUM(E21:E24) -> 23.14 | F25: =SUM(F21:F24) -> 26.74 | G25: =SUM(G21:G24) -> 30.34 | H25: =SUM(H21:H24) -> 33.94 | I25: =SUM(I21:I24) -> 41.635051 | ... M25: =SUM(M21:M24) -> 102.19226
A26: Operating lease liability, net of current portion | B26: 5.801 | C26: 4.911 | D26: =C26-0.2 -> 4.711 | E26: =D26-0.2 -> 4.511 | F26: =E26-0.2 -> 4.311 | G26: =F26-0.2 -> 4.111 | H26: =G26-0.2 -> 3.911 | I26: =H26-0.2 -> 3.711 | J26: =I26-0.2 -> 3.511 | K26: =J26-0.2 -> 3.311 | ... M26: =L26-0.2 -> 2.911 | O26: =D26-C26 -> -0.2
A27: Total liabilities | B27: =SUM(B25:B26) -> 21.721 | C27: =SUM(C25:C26) -> 21.14 | D27: =SUM(D25:D26) -> 24.251 | E27: =SUM(E25:E26) -> 27.651 | F27: =SUM(F25:F26) -> 31.051 | G27: =SUM(G25:G26) -> 34.451 | H27: =SUM(H25:H26) -> 37.851 | I27: =SUM(I25:I26) -> 45.346051 | ... M27: =SUM(M25:M26) -> 105.10326
A29: Stockholders’ equity:
A30: Series D | B30: 0 | C30: 0 | D30: =C30+CF!D36 -> 0 | E30: =D30+CF!E36 -> 0 | F30: =E30+CF!F36 -> 0 | G30: =F30+CF!G36 -> 0 | H30: =G30+CF!H36 -> 0 | I30: =H30+CF!I36 -> 0 | J30: =I30+CF!J36 -> 0 | K30: =J30+CF!K36 -> 0 | ... M30: =L30+CF!M36 -> 0 | O30: =D30-C30 -> 0
A31: Series C | B31: 224.992 | C31: 0 | D31: =C31+CF!D35 -> 0 | E31: =D31+CF!E35 -> 0 | F31: =E31+CF!F35 -> 0 | G31: =F31+CF!G35 -> 0 | H31: =G31+CF!H35 -> 0 | I31: =H31+CF!I35 -> 0 | J31: =I31+CF!J35 -> 0 | K31: =J31+CF!K35 -> 0 | ... M31: =L31+CF!M35 -> 0 | O31: =D31-C31 -> 0
A32: Series B-1 | B32: 11.981 | C32: 0 | D32: =C32 -> 0 | E32: =D32 -> 0 | F32: =E32 -> 0 | G32: =F32 -> 0 | H32: =G32 -> 0 | I32: =H32 -> 0 | J32: =I32 -> 0 | K32: =J32 -> 0 | ... M32: =L32 -> 0 | O32: =D32-C32 -> 0
A33: Series B | B33: 51.094 | C33: 0 | D33: =C33 -> 0 | E33: =D33 -> 0 | F33: =E33 -> 0 | G33: =F33 -> 0 | H33: =G33 -> 0 | I33: =H33 -> 0 | J33: =I33 -> 0 | K33: =J33 -> 0 | ... M33: =L33 -> 0 | O33: =D33-C33 -> 0
A34: Series A-1 | B34: 15.963 | C34: 0 | D34: =C34 -> 0 | E34: =D34 -> 0 | F34: =E34 -> 0 | G34: =F34 -> 0 | H34: =G34 -> 0 | I34: =H34 -> 0 | J34: =I34 -> 0 | K34: =J34 -> 0 | ... M34: =L34 -> 0 | O34: =D34-C34 -> 0
A35: Series A-1 | B35: 4.793 | C35: 0 | D35: =C35 -> 0 | E35: =D35 -> 0 | F35: =E35 -> 0 | G35: =F35 -> 0 | H35: =G35 -> 0 | I35: =H35 -> 0 | J35: =I35 -> 0 | K35: =J35 -> 0 | ... M35: =L35 -> 0 | O35: =D35-C35 -> 0 | R35: 9
A36: Common stock | B36: 0 | C36: 0.005 | D36: =C36 -> 0.005 | E36: =D36 -> 0.005 | F36: =E36 -> 0.005 | G36: =F36 -> 0.005 | H36: =G36 -> 0.005 | I36: =H36 -> 0.005 | J36: =I36 -> 0.005 | K36: =J36 -> 0.005 | ... M36: =L36 -> 0.005 | O36: =D36-C36 -> 0
A37: Additional paid-in capital | B37: 5.577 | C37: 819.115 | D37: =C37+CF!D38+CF!D37+CF!D39+CF!D10+CF!D11+CF!D12+CF!D14+CF!D15+CF!D34 -> 1208.201 | E37: =D37+CF!E38+CF!E37+CF!E39+CF!E10+CF!E11+CF!E12+CF!E14+CF!E15+CF!E34 -> 1448.499 | F37: =E37+CF!F38+CF!F37+CF!F39+CF!F10+CF!F11+CF!F12+CF!F14+CF!F15+CF!F34 -> 1490.0454 | G37: =F37+CF!G38+CF!G37+CF!G39+CF!G10+CF!G11+CF!G12+CF!G14+CF!G15+CF!G34 -> 1732.8775 | H37: =G37+CF!H38+CF!H37+CF!H39+CF!H10+CF!H11+CF!H12+CF!H14+CF!H15+CF!H34 -> 1777.0341 | I37: =H37+CF!I38+CF!I37+CF!I39+CF!I10+CF!I11+CF!I12+CF!I14+CF!I15+CF!I34 -> 1822.5548 | J37: =I37+CF!J38+CF!J37+CF!J39+CF!J10+CF!J11+CF!J12+CF!J14+CF!J15+CF!J34 -> 1869.4805 | K37: =J37+CF!K38+CF!K37+CF!K39+CF!K10+CF!K11+CF!K12+CF!K14+CF!K15+CF!K34 -> 1917.8534 | ... M37: =L37+CF!M38+CF!M37+CF!M39+CF!M10+CF!M11+CF!M12+CF!M14+CF!M15+CF!M34 -> 2019.1157 | O37: =D37-C37 -> 389.086
A38: Accumulated other comprehensive loss | B38: 0.163 | C38: -0.228 | D38: =C38 -> -0.228 | E38: =D38 -> -0.228 | F38: =E38 -> -0.228 | G38: =F38 -> -0.228 | H38: =G38 -> -0.228 | I38: =H38 -> -0.228 | J38: =I38 -> -0.228 | K38: =J38 -> -0.228 | ... M38: =L38 -> -0.228 | O38: =D38-C38 -> 0
A39: Accumulated deficit | B39: -199.368 | C39: -360.52 | D39: =C39+CF!D7 -> -566.92 | E39: =D39+CF!E7 -> -781.312 | F39: =E39+CF!F7 -> -1034.7009 | G39: =F39+CF!G7 -> -1289.8851 | H39: =G39+CF!H7 -> -1453.1468 | I39: =H39+CF!I7 -> -1426.1602 | J39: =I39+CF!J7 -> -1124.4903 | K39: =J39+CF!K7 -> -597.91728 | ... M39: =L39+CF!M7 -> 870.17704 | O39: =D39-C39 -> -206.4
A40: Total stockholders’ equity | B40: =SUM(B30:B39) -> 115.195 | C40: =SUM(C30:C39) -> 458.372 | D40: =SUM(D33:D39) -> 641.058 | E40: =SUM(E33:E39) -> 666.964 | F40: =SUM(F33:F39) -> 455.12145 | G40: =SUM(G33:G39) -> 442.76948 | H40: =SUM(H33:H39) -> 323.66432 | I40: =SUM(I33:I39) -> 396.17153 | J40: =SUM(J33:J39) -> 744.76717 | K40: =SUM(K33:K39) -> 1319.7131 | ... M40: =SUM(M33:M39) -> 2889.0698
A41: Total liabilities and stockholders’ equity | B41: =SUM(B40,B27) -> 136.916 | C41: =SUM(C40,C27) -> 479.512 | D41: =SUM(D40,D27) -> 665.309 | E41: =SUM(E40,E27) -> 694.615 | F41: =SUM(F40,F27) -> 486.17245 | G41: =SUM(G40,G27) -> 477.22048 | H41: =SUM(H40,H27) -> 361.51532 | I41: =SUM(I40,I27) -> 441.51758 | ... M41: =SUM(M40,M27) -> 2994.173
A42: Source: Company reports; Needham & Company, LLC estimates
A44: check | B44: =B41-B17 -> 0 | C44: =C41-C17 -> 0 | D44: =D41-D17 -> 0 | E44: =E41-E17 -> 0 | F44: =F41-F17 -> 0 | G44: =G41-G17 -> 0 | H44: =H41-H17 -> 6.8212103e-13 | I44: =I41-I17 -> 9.6633812e-13 | ... M44: =M41-M17 -> 0
A47: Sales | B47: =IS!AD8 -> 0 | C47: =IS!AE8 -> 0 | D47: =IS!AJ8 -> 0 | E47: =IS!AK8 -> 0 | F47: =IS!AL8 -> 0 | G47: =IS!AM8 -> 16.880566 | H47: =IS!AN8 -> 128.13327 | I47: =IS!AO8 -> 348.00111 | J47: =IS!AP8 -> 670.96672 | K47: =IS!AQ8 -> 969.33752 | ... M47: =IS!AS8 -> 1475.7246
A48: A/R to Sales | B48: 0.07 | C48: =B48 -> 0.07 | D48: =C48 -> 0.07 | E48: =D48 -> 0.07 | F48: =E48 -> 0.07 | G48: =F48 -> 0.07 | H48: =G48 -> 0.07 | I48: =H48 -> 0.07 | J48: =I48 -> 0.07 | ... M48: =L48 -> 0.07
A49: A/R | B49: =B47*B48 -> 0 | C49: =C47*C48 -> 0 | D49: =D47*D48 -> 0 | E49: =E47*E48 -> 0 | F49: =F47*F48 -> 0 | G49: =G47*G48 -> 1.1816396 | H49: =H47*H48 -> 8.9693292 | I49: =I47*I48 -> 24.360078 | ... M49: =M47*M48 -> 103.30072
A51: Sales | B51: =IS!AE14 -> 0 | C51: =IS!AE14 -> 0 | D51: =IS!AJ14 -> 0 | E51: =IS!AK14 -> 0 | F51: =IS!AL14 -> 0 | G51: =IS!AM14 -> 15.614524 | H51: =IS!AN14 -> 118.52328 | I51: =IS!AO14 -> 321.90103 | J51: =IS!AP14 -> 620.64421 | K51: =IS!AQ14 -> 896.63721 | ... M51: =IS!AS14 -> 1365.0453
A52: A/P to Sales | B52: 0.05 | C52: =B52 -> 0.05 | D52: =C52 -> 0.05 | E52: =D52 -> 0.05 | F52: =E52 -> 0.05 | G52: =F52 -> 0.05 | H52: =G52 -> 0.05 | I52: =H52 -> 0.05 | J52: =I52 -> 0.05 | ... M52: =L52 -> 0.05
A53: A/P | B53: =B51*B52 -> 0 | C53: =C51*C52 -> 0 | D53: =D51*D52 -> 0 | E53: =E51*E52 -> 0 | F53: =F51*F52 -> 0 | G53: =G51*G52 -> 0.78072618 | H53: =H51*H52 -> 5.9261639 | I53: =I51*I52 -> 16.095051 | ... M53: =M51*M52 -> 68.252263

Sheet SOTP
R1: =R14 -> 37.175346
J3: Peak | L3: Per Share | M3: Prob | N3: Risk-Adj | O3: Other | P3: Risk-Adj | Q3: Per Share | R3: % of Total | T3: Fraction
B4: Product | G4: Indication | H4: Region | I4: Stage | J4: Launch | K4: Revenue | L4: NPV | M4: Value | N4: of Success | O4: NPV | P4: Adj. | Q4: Net NPV | R4: Value | S4: Value/Shr
A7: 1 | B7: ML-007 | G7: Schizophrenia | H7: US | I7: Phase 2 | J7: =H35 -> 2029 | K7: =MAX(REVENUE!Z7:AW7) -> 1545.7081 | L7: =O7/N7 -> 2606.8067 | M7: =R7/N7 -> 29.162252 | N7: =REVENUE!AY7 -> 0.55 | O7: =G59 -> 1433.7437 | P7: =$O$18*U7 -> -685.52961 | Q7: =O7+P7 -> 748.21407 | R7: =Q7/$G$33 -> 16.039239 | S7: =R7/R$14 -> 0.43144826 | U7: =O7/$O$11 -> 0.63774103
A8: 2 | B8: ML-007 | G8: AD Psychosis | H8: US | I8: Phase 2 | J8: =H64 -> 2030 | K8: =MAX(REVENUE!Z12:AW12) -> 2393.5535 | L8: =O8/N8 -> 3270.6507 | M8: =R8/N8 -> 36.588651 | N8: =REVENUE!AY12 -> 0.25 | O8: =G88 -> 817.66268 | P8: =$O$18*U8 -> -390.9569 | Q8: =O8+P8 -> 426.70579 | R8: =Q8/$G$33 -> 9.1471628 | S8: =R8/R$14 -> 0.24605454 | U8: =O8/$O$11 -> 0.36370311
A9: 3 | B9: ML-004 | G9: ASD | H9: US | I9: Phase 2 | J9: =H91 -> 2031 | K9: =MAX(H93:Q93) -> 27.19676 | L9: =O9/N9 -> -64.933078 | M9: =R9/N9 -> -0.72640399 | N9: =REVENUE!AY24 -> 0.05 | O9: =G115 -> -3.2466539 | P9: =$O$18*U9 -> 1.5523538 | Q9: =O9+P9 -> -1.6943001 | R9: =Q9/$G$33 -> -0.036320199 | S9: =R9/R$14 -> -0.00097699693 | U9: =O9/$O$11 -> -0.0014441385
A10: 4 | B10: Collaboration | H10: EU | K10: =MAX(REVENUE!Z32:AW32) -> 0 | L10: =O10/N10 -> #DIV/0! | M10: =R10/N10 -> #DIV/0! | O10: =G130 -> 0 | P10: =$O$18*U10 -> 0 | Q10: =O10+P10 -> 0 | R10: =Q10/$G$33 -> 0 | S10: =R10/R$14 -> 0 | U10: =O10/$O$11 -> 0
B11: Total Pipeline | L11: =SUM(L7:L10) -> #DIV/0! | M11: =SUM(M7:M10) -> #DIV/0! | O11: =SUM(O7:O10) -> 2248.1597 | P11: =SUM(P7:P10) -> -1074.9342 | Q11: =SUM(Q7:Q10) -> 1173.2256 | R11: =SUM(R7:R10) -> 25.150081 | S11: =R11/R$14 -> 0.6765258 | U11: =SUM(U7:U10) -> 1
B12: Platform Value | L12: =M12*$G$33 -> 107.87033 | M12: =R12 -> 2.3123835 | R12: =G159 -> 2.3123835 | S12: =R12/R$14 -> 0.062202071
B13: Net Cash Value | L13: =M13*$G$33 -> 453.096 | M13: =R13 -> 9.7128818 | R13: =O19/$G$33 -> 9.7128818 | S13: =R13/R$14 -> 0.26127213
B14: Total Value | R14: =R11+R12+R13 -> 37.175346 | S14: =R14/R$14 -> 1
O15: Current Stock | Q15: =TODAY() -> 46119 | R15: =_xll.FDS($G$26,"P_PRICE("&$Q$15&")") -> #Calc
O16: Upside/Downside | R16: =R14/R15-1 -> #VALUE!
B17: Adjustments
B18: Company Unallocated Expenses | O18: =-G148 -> -1074.9342
B19: Cash/ST/LT Securities | O19: =BS!C7+BS!C8+BS!C12 -> 453.096
B20: Debt | O20: 0
B21: Net Cash | O21: =O19-O20 -> 453.096
B22: Total Adjustments | O22: =SUM(O18,O21) -> -621.83815
B24: Total
B26: Current Stock Price | G26: MPLT
B28: Assumptions
B29: Discount Rate | G29: 0.125
B30: Current Year | G30: 2026
B31: Shs at beginning of year | G31: =IS!AF39 -> 32.648977
B32: Add'l Cap Raise (Current + Next yr) | G32: =CF!D47 -> 14
B33: Diluted Shares | G33: =G31+G32 -> 46.648977
F35: Year of launch: | H35: =INDEX(C36:X36,MATCH(TRUE,INDEX(C37:X37<>0,),0)) -> 2029
A36: 1 | B36: ML-007 (Schizophrenia) | C36: 2021 | D36: =C36+1 -> 2022 | E36: =D36+1 -> 2023 | F36: =E36+1 -> 2024 | G36: =F36+1 -> 2025 | H36: =G36+1 -> 2026 | I36: =H36+1 -> 2027 | J36: =I36+1 -> 2028 | K36: =J36+1 -> 2029 | ... X36: =W36+1 -> 2042 | Y36: Terminal
B37: Revenues | E37: =REVENUE!Z9 -> 0 | H37: =REVENUE!AN9 -> 0 | I37: =REVENUE!AO9 -> 0 | J37: =REVENUE!AP9 -> 0 | K37: =REVENUE!AQ9 -> 16.880566 | L37: =REVENUE!AR9 -> 102.80265 | M37: =REVENUE!AS9 -> 258.72535 | N37: =REVENUE!AT9 -> 419.63662 | O37: =REVENUE!AU9 -> 577.56461 | ... Q37: =REVENUE!AW9 -> 850.13945
B38: COGS | E38: =OPEX!#REF! -> #REF! | H38: =OPEX!T90 -> 0 | I38: =OPEX!U90 -> 0 | J38: =OPEX!V90 -> 0 | K38: =OPEX!W90 -> 1.2660425 | L38: =OPEX!X90 -> 7.7101985 | M38: =OPEX!Y90 -> 19.404401 | N38: =OPEX!Z90 -> 31.472747 | O38: =OPEX!AA90 -> 43.317346 | ... Q38: =OPEX!AC90 -> 63.760459
B39: Gross Profit | E39: =E37-E38 -> #REF! | H39: =H37-H38 -> 0 | I39: =I37-I38 -> 0 | J39: =J37-J38 -> 0 | K39: =K37-K38 -> 15.614524 | L39: =L37-L38 -> 95.092448 | M39: =M37-M38 -> 239.32095 | N39: =N37-N38 -> 388.16387 | O39: =O37-O38 -> 534.24727 | ... Q39: =Q37-Q38 -> 786.37899
B40: Sales and Marketing | E40: =OPEX!#REF! -> #REF! | H40: =OPEX!T61 -> 0 | I40: =OPEX!U61 -> 0 | J40: =OPEX!V61 -> 20.857249 | K40: =OPEX!W61 -> 38.271119 | L40: =OPEX!X61 -> 44.094253 | M40: =OPEX!Y61 -> 45.41708 | N40: =OPEX!Z61 -> 46.779593 | O40: =OPEX!AA61 -> 48.182981 | ... Q40: =OPEX!AC61 -> 51.117324
B41: R&D | E41: =OPEX!#REF! -> #REF! | H41: =OPEX!T22 -> 37.95 | I41: =OPEX!U22 -> 31.9815 | J41: =OPEX!V22 -> 38.25 | K41: =OPEX!W22 -> 13 | L41: =OPEX!X22 -> 10 | M41: =OPEX!Y22 -> 8 | N41: =OPEX!Z22 -> 8 | O41: =OPEX!AA22 -> 8 | ... Q41: =OPEX!AC22 -> 8
B42: Operating Income | E42: =E37-E38-E40-E41 -> #REF! | H42: =H37-H38-H40-H41 -> -37.95 | I42: =I37-I38-I40-I41 -> -31.9815 | J42: =J37-J38-J40-J41 -> -59.107249 | K42: =K37-K38-K40-K41 -> -35.656596 | L42: =L37-L38-L40-L41 -> 40.998196 | M42: =M37-M38-M40-M41 -> 185.90387 | N42: =N37-N38-N40-N41 -> 333.38428 | O42: =O37-O38-O40-O41 -> 478.06429 | ... Q42: =Q37-Q38-Q40-Q41 -> 727.26167
B43: Taxes | E43: =E42*IS!Z33 -> #REF! | H43: =H42*IS!AJ33 -> 0 | I43: =I42*IS!AK33 -> 0 | J43: =J42*IS!AL33 -> 0 | K43: =K42*IS!AM33 -> 0 | L43: =L42*IS!AN33 -> 0 | M43: =M42*IS!AO33 -> 0 | N43: =N42*IS!AP33 -> 16.669214 | O43: =O42*IS!AQ33 -> 47.806429 | ... Q43: =Q42*IS!AS33 -> 152.72495
B44: EBIAT Contribution | E44: =E42-E43 -> #REF! | H44: =H42-H43 -> -37.95 | I44: =I42-I43 -> -31.9815 | J44: =J42-J43 -> -59.107249 | K44: =K42-K43 -> -35.656596 | L44: =L42-L43 -> 40.998196 | M44: =M42-M43 -> 185.90387 | N44: =N42-N43 -> 316.71507 | O44: =O42-O43 -> 430.25786 | ... Q44: =Q42-Q43 -> 574.53672
B45: FCF Adjustment | E45: =E178 -> #REF! | H45: =H178 -> 1.44265 | I45: =I178 -> 1.3104 | J45: =J178 -> 1.6259662 | K45: =K178 -> 0.59718186 | L45: =L178 -> 28.852796 | M45: =M178 -> -8.2937429 | N45: =N178 -> -4.3178423 | O45: =O178 -> -3.5899485 | ... Q45: =Q178 -> -2.5650814
B46: FCF Contribution | E46: =E44+E45 -> #REF! | H46: =H44+H45 -> -36.50735 | I46: =I44+I45 -> -30.6711 | J46: =J44+J45 -> -57.481283 | K46: =K44+K45 -> -35.059414 | L46: =L44+L45 -> 69.850991 | M46: =M44+M45 -> 177.61012 | N46: =N44+N45 -> 312.39722 | O46: =O44+O45 -> 426.66791 | ... Q46: =Q44+Q45 -> 571.97164 | R46: =Q46*(1+R47) -> 655.98428 | S46: =R46*(1+S47) -> 719.53771 | T46: =S46*(1+T47) -> 753.27147 | U46: =T46*(1+U47) -> 781.05403 | V46: =U46*(1+V47) -> 273.36891 | W46: =V46*(1+W47) -> 95.679119 | X46: =W46*(1+X47) -> 47.839559 | Y46: =(X46*(1+Y47))/($G$29-Y47) -> 382.71648
B47: Growth rate | E47: =E46/D46-1 -> #REF! | H47: =H46/G46-1 -> #DIV/0! | I47: =I46/H46-1 -> -0.15986507 | J47: =J46/I46-1 -> 0.87411872 | K47: =K46/J46-1 -> -0.39007252 | L47: =L46/K46-1 -> -2.9923605 | M47: =M46/L46-1 -> 1.5427001 | N47: =N46/M46-1 -> 0.75889311 | O47: =O46/N46-1 -> 0.36578649 | ... Q47: =Q46/P46-1 -> 0.19688254 | R47: =Q47-0.05 -> 0.14688254 | S47: =R47-0.05 -> 0.096882541 | T47: =S47-0.05 -> 0.046882541 | U47: =T47-0.01 -> 0.036882541 | V47: -0.65 | W47: -0.65 | X47: -0.5 | Y47: 0
B48: Discounted | E48: =E46/((1+$G$29)^(E36-$G$30+1)) -> #REF! | H48: =H46/((1+$G$29)^(H36-$G$30+1)) -> -32.450978 | I48: =I46/((1+$G$29)^(I36-$G$30+1)) -> -24.233956 | J48: =J46/((1+$G$29)^(J36-$G$30+1)) -> -40.370942 | K48: =K46/((1+$G$29)^(K36-$G$30+1)) -> -21.887419 | L48: =L46/((1+$G$29)^(L36-$G$30+1)) -> 38.762338 | M48: =M46/((1+$G$29)^(M36-$G$30+1)) -> 87.609779 | N48: =N46/((1+$G$29)^(N36-$G$30+1)) -> 136.97443 | O48: =O46/((1+$G$29)^(O36-$G$30+1)) -> 166.2914 | ... X48: =X46/((1+$G$29)^(X36-$G$30+1)) -> 6.4594314 | Y48: =Y46/((1+$G$29)^(X36-$G$30+1+1)) -> 45.933734
B50: Revenues | E50: 1 | H50: 1 | I50: 1 | J50: 1 | K50: 1 | L50: 1
B51: COGS | E51: =IFERROR(E38/E37,"NM") -> NM | H51: =H38/H37 -> #DIV/0! | I51: =I38/I37 -> #DIV/0! | J51: =J38/J37 -> #DIV/0! | K51: =K38/K37 -> 0.075 | L51: =L38/L37 -> 0.075
B52: Gross Margin | E52: =IFERROR(E50-E51,"NM") -> NM | H52: =H50-H51 -> #DIV/0! | I52: =I50-I51 -> #DIV/0! | J52: =J50-J51 -> #DIV/0! | K52: =K50-K51 -> 0.925 | L52: =L50-L51 -> 0.925
B53: Sales and Marketing | E53: =IFERROR(E40/E37,"NM") -> NM | H53: =H40/H37 -> #DIV/0! | I53: =I40/I37 -> #DIV/0! | J53: =J40/J37 -> #DIV/0! | K53: =K40/K37 -> 2.2671704 | L53: =L40/L37 -> 0.42892138
B54: R&D | E54: =IFERROR(E41/E37,"NM") -> NM | H54: =H41/H37 -> #DIV/0! | I54: =I41/I37 -> #DIV/0! | J54: =J41/J37 -> #DIV/0! | K54: =K41/K37 -> 0.77011636 | L54: =L41/L37 -> 0.09727376
B55: Operating Margin | E55: =IFERROR(E42/E37,"NM") -> NM | H55: =H42/H37 -> #DIV/0! | I55: =I42/I37 -> #DIV/0! | J55: =J42/J37 -> #DIV/0! | K55: =K42/K37 -> -2.1122867 | L55: =L42/L37 -> 0.39880486
B57: NPV | G57: =SUM(H48:X48) -> 1387.8099
B58: Terminal Value | G58: =Y48 -> 45.933734
B59: Total NPV | G59: =G58+G57 -> 1433.7437
B60: Per Share Value | G60: =G59/$G$33 -> 30.734729
F64: Year of launch: | H64: =INDEX(C65:Y65,MATCH(TRUE,INDEX(C66:Y66<>0,),0)) -> 2030
A65: 2 | B65: ML 007 (AD Psychosis) | C65: 2021 | D65: =C65+1 -> 2022 | E65: =D65+1 -> 2023 | F65: =E65+1 -> 2024 | G65: =F65+1 -> 2025 | H65: =G65+1 -> 2026 | I65: =H65+1 -> 2027 | J65: =I65+1 -> 2028 | K65: =J65+1 -> 2029 | ... X65: =W65+1 -> 2042 | Y65: Terminal
B66: Revenues | E66: =REVENUE!Z14 -> 0 | H66: =REVENUE!AN14 -> 0 | I66: =REVENUE!AO14 -> 0 | J66: =REVENUE!AP14 -> 0 | K66: =REVENUE!AQ14 -> 0 | L66: =REVENUE!AR14 -> 25.330627 | M66: =REVENUE!AS14 -> 86.324955 | N66: =REVENUE!AT14 -> 241.06174 | O66: =REVENUE!AU14 -> 375.12907 | ... Q66: =REVENUE!AW14 -> 598.38838
B67: COGS | E67: =OPEX!#REF! -> #REF! | H67: =OPEX!T91 -> 0 | I67: =OPEX!U91 -> 0 | J67: =OPEX!V91 -> 0 | K67: =OPEX!W91 -> 0 | L67: =OPEX!X91 -> 1.899797 | M67: =OPEX!Y91 -> 6.4743716 | N67: =OPEX!Z91 -> 18.079631 | O67: =OPEX!AA91 -> 28.13468 | ... Q67: =OPEX!AC91 -> 44.879129
B68: Gross Profit | E68: =E66-E67 -> #REF! | H68: =H66-H67 -> 0 | I68: =I66-I67 -> 0 | J68: =J66-J67 -> 0 | K68: =K66-K67 -> 0 | L68: =L66-L67 -> 23.43083 | M68: =M66-M67 -> 79.850583 | N68: =N66-N67 -> 222.98211 | O68: =O66-O67 -> 346.99439 | ... Q68: =Q66-Q67 -> 553.50926
B69: Sales and Marketing | E69: =OPEX!#REF! -> #REF! | H69: =OPEX!T62 -> 0 | I69: =OPEX!U62 -> 0 | J69: =OPEX!V62 -> 0 | K69: =OPEX!W62 -> 15.659939 | L69: =OPEX!X62 -> 31.357106 | M69: =OPEX!Y62 -> 48.563758 | N69: =OPEX!Z62 -> 50.645671 | O69: =OPEX!AA62 -> 52.821291 | ... Q69: =OPEX!AC62 -> 57.471358
B70: R&D | E70: =OPEX!#REF! -> #REF! | H70: =OPEX!T23 -> 24.15 | I70: =OPEX!U23 -> 31.9815 | J70: =OPEX!V23 -> 38.25 | K70: =OPEX!W23 -> 35.75 | L70: =OPEX!X23 -> 27.5 | M70: =OPEX!Y23 -> 22 | N70: =OPEX!Z23 -> 22 | O70: =OPEX!AA23 -> 22 | ... Q70: =OPEX!AC23 -> 22
B71: Operating Income | E71: =E66-E67-E69-E70 -> #REF! | H71: =H66-H67-H69-H70 -> -24.15 | I71: =I66-I67-I69-I70 -> -31.9815 | J71: =J66-J67-J69-J70 -> -38.25 | K71: =K66-K67-K69-K70 -> -51.409939 | L71: =L66-L67-L69-L70 -> -35.426275 | M71: =M66-M67-M69-M70 -> 9.2868249 | N71: =N66-N67-N69-N70 -> 150.33644 | O71: =O66-O67-O69-O70 -> 272.1731 | ... Q71: =Q66-Q67-Q69-Q70 -> 474.0379
B72: Taxes | E72: =E71*IS!Z33 -> #REF! | H72: =H71*IS!AJ33 -> 0 | I72: =I71*IS!AK33 -> 0 | J72: =J71*IS!AL33 -> 0 | K72: =K71*IS!AM33 -> 0 | L72: =L71*IS!AN33 -> 0 | M72: =M71*IS!AO33 -> 0 | N72: =N71*IS!AP33 -> 7.5168221 | O72: =O71*IS!AQ33 -> 27.21731 | ... Q72: =Q71*IS!AS33 -> 99.547959
B73: EBIAT Contribution | E73: =E71-E72 -> #REF! | H73: =H71-H72 -> -24.15 | I73: =I71-I72 -> -31.9815 | J73: =J71-J72 -> -38.25 | K73: =K71-K72 -> -51.409939 | L73: =L71-L72 -> -35.426275 | M73: =M71-M72 -> 9.2868249 | N73: =N71-N72 -> 142.81962 | O73: =O71-O72 -> 244.95579 | ... Q73: =Q71-Q72 -> 374.48994
B74: FCF Adjustment | E74: =E179 -> #REF! | H74: =H179 -> 0.91805 | I74: =I179 -> 1.3104 | J74: =J179 -> 1.0522095 | K74: =K179 -> 0.86102115 | L74: =L179 -> -24.931514 | M74: =M179 -> -0.4143138 | N74: =N179 -> -1.9470896 | O74: =O179 -> -2.043841 | ... Q74: =Q179 -> -1.6719509
B75: FCF Contribution | E75: =E73+E74 -> #REF! | H75: =H73+H74 -> -23.23195 | I75: =I73+I74 -> -30.6711 | J75: =J73+J74 -> -37.197791 | K75: =K73+K74 -> -50.548918 | L75: =L73+L74 -> -60.35779 | M75: =M73+M74 -> 8.8725111 | N75: =N73+N74 -> 140.87253 | O75: =O73+O74 -> 242.91195 | ... Q75: =Q73+Q74 -> 372.81799 | R75: =Q75*(1+R76) -> 448.56101 | S75: =R75*(1+S76) -> 517.26421 | T75: =S75*(1+T76) -> 570.62701 | U75: =T75*(1+U76) -> 600.96357 | V75: =U75*(1+V76) -> 210.33725 | W75: =V75*(1+W76) -> 73.618037 | X75: =W75*(1+X76) -> 36.809018 | Y75: =(X75*(1+Y76))/($G$29-Y76) -> 294.47215
B76: Growth rate | E76: =IFERROR(E75/D75-1,0) -> 0 | H76: =IFERROR(H75/G75-1,0) -> 0 | I76: =IFERROR(I75/H75-1,0) -> 0.32021204 | J76: =IFERROR(J75/I75-1,0) -> 0.2127961 | K76: =IFERROR(K75/J75-1,0) -> 0.35892259 | L76: =IFERROR(L75/K75-1,0) -> 0.19404712 | M76: =IFERROR(M75/L75-1,0) -> -1.1469986 | N76: =IFERROR(N75/M75-1,0) -> 14.877414 | O76: =IFERROR(O75/N75-1,0) -> 0.72433863 | ... Q76: =IFERROR(Q75/P75-1,0) -> 0.25316354 | R76: =Q76-0.05 -> 0.20316354 | S76: =R76-0.05 -> 0.15316354 | T76: =S76-0.05 -> 0.10316354 | U76: =T76-0.05 -> 0.053163543 | V76: -0.65 | W76: -0.65 | X76: -0.5 | Y76: 0
B77: Discounted | E77: =E75/((1+$G$29)^(E65-$G$30+1)) -> #REF! | H77: =H75/((1+$G$29)^(H65-$G$30+1)) -> -20.650622 | I77: =I75/((1+$G$29)^(I65-$G$30+1)) -> -24.233956 | J77: =J75/((1+$G$29)^(J65-$G$30+1)) -> -26.125197 | K77: =K75/((1+$G$29)^(K65-$G$30+1)) -> -31.55744 | L77: =L75/((1+$G$29)^(L65-$G$30+1)) -> -33.494285 | M77: =M75/((1+$G$29)^(M65-$G$30+1)) -> 4.3765452 | N77: =N75/((1+$G$29)^(N65-$G$30+1)) -> 61.767306 | O77: =O75/((1+$G$29)^(O65-$G$30+1)) -> 94.673557 | ... X77: =X75/((1+$G$29)^(X65-$G$30+1)) -> 4.9700568 | Y77: =Y75/((1+$G$29)^(X65-$G$30+1+1)) -> 35.342626
B79: Revenues | E79: 1 | H79: 1 | I79: 1 | J79: 1 | K79: 1 | L79: 1
B80: COGS | E80: =IFERROR(E67/E66,"NM") -> NM | H80: =H67/H66 -> #DIV/0! | I80: =I67/I66 -> #DIV/0! | J80: =J67/J66 -> #DIV/0! | K80: =K67/K66 -> #DIV/0! | L80: =L67/L66 -> 0.075
B81: Gross Margin | E81: =IFERROR(E79-E80,"NM") -> NM | H81: =H79-H80 -> #DIV/0! | I81: =I79-I80 -> #DIV/0! | J81: =J79-J80 -> #DIV/0! | K81: =K79-K80 -> #DIV/0! | L81: =L79-L80 -> 0.925
B82: Sales and Marketing | E82: =IFERROR(E69/E66,"NM") -> NM | H82: =H69/H66 -> #DIV/0! | I82: =I69/I66 -> #DIV/0! | J82: =J69/J66 -> #DIV/0! | K82: =K69/K66 -> #DIV/0! | L82: =L69/L66 -> 1.2379127
B83: R&D | E83: =IFERROR(E70/E66,"NM") -> NM | H83: =H70/H66 -> #DIV/0! | I83: =I70/I66 -> #DIV/0! | J83: =J70/J66 -> #DIV/0! | K83: =K70/K66 -> #DIV/0! | L83: =L70/L66 -> 1.0856423
B84: Operating Margin | E84: =IFERROR(E71/E66,"NM") -> NM | H84: =H71/H66 -> #DIV/0! | I84: =I71/I66 -> #DIV/0! | J84: =J71/J66 -> #DIV/0! | K84: =K71/K66 -> #DIV/0! | L84: =L71/L66 -> -1.398555
B86: NPV | G86: =SUM(H77:X77) -> 782.32005
B87: Terminal Value | G87: =Y77 -> 35.342626
B88: Total NPV | G88: =G87+G86 -> 817.66268
B89: Per Share Value | G89: =G88/$G$33 -> 17.527987
F91: Year of launch: | H91: =INDEX(C92:Y92,MATCH(TRUE,INDEX(C93:Y93<>0,),0)) -> 2031
A92: 3 | B92: =B9 -> ML-004 | C92: 2021 | D92: =C92+1 -> 2022 | E92: =D92+1 -> 2023 | F92: =E92+1 -> 2024 | G92: =F92+1 -> 2025 | H92: =G92+1 -> 2026 | I92: =H92+1 -> 2027 | J92: =I92+1 -> 2028 | K92: =J92+1 -> 2029 | ... X92: =W92+1 -> 2042 | Y92: Terminal
B93: Revenues | E93: =REVENUE!#REF! -> #REF! | F93: =REVENUE!#REF! -> #REF! | H93: =REVENUE!AN25 -> 0 | I93: =REVENUE!AO25 -> 0 | J93: =REVENUE!AP25 -> 0 | K93: =REVENUE!AQ25 -> 0 | L93: =REVENUE!AR25 -> 0 | M93: =REVENUE!AS25 -> 2.9508083 | N93: =REVENUE!AT25 -> 10.268355 | O93: =REVENUE!AU25 -> 16.643842 | ... Q93: =REVENUE!AW25 -> 27.19676
B94: COGS | E94: =OPEX!#REF! -> #REF! | H94: =OPEX!T92 -> 0 | I94: =OPEX!U92 -> 0 | J94: =OPEX!V92 -> 0 | K94: =OPEX!W92 -> 0 | L94: =OPEX!X92 -> 0 | M94: =OPEX!Y92 -> 0.22131063 | N94: =OPEX!Z92 -> 0.7701266 | O94: =OPEX!AA92 -> 1.2482881 | ... Q94: =OPEX!AC92 -> 2.039757
B95: Gross Profit | E95: =E93-E94 -> #REF! | H95: =H93-H94 -> 0 | I95: =I93-I94 -> 0 | J95: =J93-J94 -> 0 | K95: =K93-K94 -> 0 | L95: =L93-L94 -> 0 | M95: =M93-M94 -> 2.7294977 | N95: =N93-N94 -> 9.4982281 | O95: =O93-O94 -> 15.395554 | ... Q95: =Q93-Q94 -> 25.157003
B96: Sales and Marketing | E96: =OPEX!#REF! -> #REF! | H96: =OPEX!T63 -> 0 | I96: =OPEX!U63 -> 0 | J96: =OPEX!V63 -> 0 | K96: =OPEX!W63 -> 0 | L96: =OPEX!X63 -> 0 | M96: =OPEX!Y63 -> 0 | N96: =OPEX!Z63 -> 0 | O96: =OPEX!AA63 -> 0 | ... Q96: =OPEX!AC63 -> 0
B97: R&D | E97: =OPEX!#REF! -> #REF! | H97: =OPEX!T24 -> 6.9 | I97: =OPEX!U24 -> 7.107 | J97: =OPEX!V24 -> 8.5 | K97: =OPEX!W24 -> 16.25 | L97: =OPEX!X24 -> 12.5 | M97: =OPEX!Y24 -> 10 | N97: =OPEX!Z24 -> 10 | O97: =OPEX!AA24 -> 10 | ... Q97: =OPEX!AC24 -> 10
B98: Operating Income | E98: =E93-E94-E96-E97 -> #REF! | H98: =H93-H94-H96-H97 -> -6.9 | I98: =I93-I94-I96-I97 -> -7.107 | J98: =J93-J94-J96-J97 -> -8.5 | K98: =K93-K94-K96-K97 -> -16.25 | L98: =L93-L94-L96-L97 -> -12.5 | M98: =M93-M94-M96-M97 -> -7.2705023 | N98: =N93-N94-N96-N97 -> -0.5017719 | O98: =O93-O94-O96-O97 -> 5.3955536 | ... Q98: =Q93-Q94-Q96-Q97 -> 15.157003
B99: Taxes | E99: =E98*IS!Z33 -> #REF! | H99: =H98*IS!AJ33 -> 0 | I99: =I98*IS!AK33 -> 0 | J99: =J98*IS!AL33 -> 0 | K99: =K98*IS!AM33 -> 0 | L99: =L98*IS!AN33 -> 0 | M99: =M98*IS!AO33 -> 0 | N99: =N98*IS!AP33 -> -0.025088595 | O99: =O98*IS!AQ33 -> 0.53955536 | ... Q99: =Q98*IS!AS33 -> 3.1829706
B100: EBIAT Contribution | E100: =E98-E99 -> #REF! | H100: =H98-H99 -> -6.9 | I100: =I98-I99 -> -7.107 | J100: =J98-J99 -> -8.5 | K100: =K98-K99 -> -16.25 | L100: =L98-L99 -> -12.5 | M100: =M98-M99 -> -7.2705023 | N100: =N98-N99 -> -0.4766833 | O100: =O98-O99 -> 4.8559982 | ... Q100: =Q98-Q99 -> 11.974032
B101: FCF Adjustment | E101: =E180 -> #REF! | H101: =H180 -> 0.2623 | I101: =I180 -> 0.2912 | J101: =J180 -> 0.23382433 | K101: =K180 -> 0.27215737 | L101: =L180 -> -8.7969713 | M101: =M180 -> 0.32435945 | N101: =N180 -> 0.0064987225 | O101: =O180 -> -0.04051706 | ... Q101: =Q180 -> -0.053459364
B102: FCF Contribution | E102: =E100+E101 -> #REF! | H102: =H100+H101 -> -6.6377 | I102: =I100+I101 -> -6.8158 | J102: =J100+J101 -> -8.2661757 | K102: =K100+K101 -> -15.977843 | L102: =L100+L101 -> -21.296971 | M102: =M100+M101 -> -6.9461428 | N102: =N100+N101 -> -0.47018458 | O102: =O100+O101 -> 4.8154812 | ... Q102: =Q100+Q101 -> 11.920573 | R102: =Q102*(1+R103) -> 12.158984 | S102: =R102*(1+S103) -> 12.402164 | T102: =S102*(1+T103) -> 12.650207 | U102: =T102*(1+U103) -> 12.903211 | V102: =U102*(1+V103) -> 13.161276 | W102: =V102*(1+W103) -> 13.424501 | X102: =W102*(1+X103) -> 13.692991 | Y102: =(X102*(1+Y103))/($G$29-Y103) -> 109.54393
B103: Growth rate | E103: =IFERROR(E102/D102-1,0) -> 0 | H103: =IFERROR(H102/G102-1,0) -> 0 | I103: =IFERROR(I102/H102-1,0) -> 0.026831583 | J103: =IFERROR(J102/I102-1,0) -> 0.2127961 | K103: =IFERROR(K102/J102-1,0) -> 0.93291835 | L103: =IFERROR(L102/K102-1,0) -> 0.33290656 | M103: =IFERROR(M102/L102-1,0) -> -0.67384363 | N103: =IFERROR(N102/M102-1,0) -> -0.93230998 | O103: =IFERROR(O102/N102-1,0) -> -11.241683 | ... Q103: =IFERROR(Q102/P102-1,0) -> 0.43632362 | R103: 0.02 | S103: =R103 -> 0.02 | T103: =S103 -> 0.02 | U103: =T103 -> 0.02 | V103: =U103 -> 0.02 | W103: =V103 -> 0.02 | X103: =W103 -> 0.02 | Y103: 0
B104: Discounted | E104: =E102/((1+$G$29)^(E92-$G$30+1)) -> #REF! | H104: =H102/((1+$G$29)^(H92-$G$30+1)) -> -5.9001778 | I104: =I102/((1+$G$29)^(I92-$G$30+1)) -> -5.3853235 | J104: =J102/((1+$G$29)^(J92-$G$30+1)) -> -5.8055994 | K104: =K102/((1+$G$29)^(K92-$G$30+1)) -> -9.9748885 | L104: =L102/((1+$G$29)^(L92-$G$30+1)) -> -11.818306 | M104: =M102/((1+$G$29)^(M92-$G$30+1)) -> -3.4263252 | N104: =N102/((1+$G$29)^(N92-$G$30+1)) -> -0.20615825 | O104: =O102/((1+$G$29)^(O92-$G$30+1)) -> 1.8768066 | ... X104: =X102/((1+$G$29)^(X92-$G$30+1)) -> 1.848866 | Y104: =Y102/((1+$G$29)^(X92-$G$30+1+1)) -> 13.147492
B106: Revenues | E106: 1 | H106: 1 | I106: 1 | J106: 1 | K106: 1 | L106: 1
B107: COGS | E107: =IFERROR(E94/E93,"NM") -> NM | H107: =H94/H93 -> #DIV/0! | I107: =I94/I93 -> #DIV/0! | J107: =J94/J93 -> #DIV/0! | K107: =K94/K93 -> #DIV/0! | L107: =L94/L93 -> #DIV/0!
B108: Gross Margin | E108: =IFERROR(E106-E107,"NM") -> NM | H108: =H106-H107 -> #DIV/0! | I108: =I106-I107 -> #DIV/0! | J108: =J106-J107 -> #DIV/0! | K108: =K106-K107 -> #DIV/0! | L108: =L106-L107 -> #DIV/0!
B109: Sales and Marketing | E109: =IFERROR(E96/E93,"NM") -> NM | H109: =H96/H93 -> #DIV/0! | I109: =I96/I93 -> #DIV/0! | J109: =J96/J93 -> #DIV/0! | K109: =K96/K93 -> #DIV/0! | L109: =L96/L93 -> #DIV/0!
B110: R&D | E110: =IFERROR(E97/E93,"NM") -> NM | H110: =H97/H93 -> #DIV/0! | I110: =I97/I93 -> #DIV/0! | J110: =J97/J93 -> #DIV/0! | K110: =K97/K93 -> #DIV/0! | L110: =L97/L93 -> #DIV/0!
B111: Operating Margin | E111: =IFERROR(E98/E93,"NM") -> NM | H111: =H98/H93 -> #DIV/0! | I111: =I98/I93 -> #DIV/0! | J111: =J98/J93 -> #DIV/0! | K111: =K98/K93 -> #DIV/0! | L111: =L98/L93 -> #DIV/0!
B113: NPV | G113: =SUM(H104:X104) -> -16.394146
B114: Terminal Value | G114: =Y104 -> 13.147492
B115: Total NPV | G115: =G114+G113 -> -3.2466539
B116: Per Share Value | G116: =G115/$G$33 -> -0.069597537
A119: 5 | B119: Collaboration | C119: 2021 | D119: =C119+1 -> 2022 | E119: =D119+1 -> 2023 | F119: =E119+1 -> 2024 | G119: =F119+1 -> 2025 | H119: =G119+1 -> 2026 | I119: =H119+1 -> 2027 | J119: =I119+1 -> 2028 | K119: =J119+1 -> 2029 | ... Y119: =X119+1 -> 2043 | Z119: Terminal
...

Sheet SOTP-FIGURE
B1: B | C1: C | D1: D | E1: E | G1: L | H1: F | J1: H | K1: I | L1: J
G3: Non-Risk-Adjusted | K3: Risk-Adjusted
B4: Product | C4: Indication | D4: Region | E4: Stage | F4: Launch | G4: Peak Rev. ($M) | H4: NPV ($M) | I4: Value/ Share ($) | J4: POS | K4: NPV ($M) | L4: Value/ Share ($)
B5: Pipeline
B6: =SOTP!B7 -> ML-007 | C6: =SOTP!G7 -> Schizophrenia | D6: =SOTP!H7 -> US | E6: =SOTP!I7 -> Phase 2 | F6: =SOTP!J7 -> 2029 | G6: =SOTP!K7 -> 1545.7081 | H6: =SOTP!L7 -> 2606.8067 | I6: =SOTP!M7 -> 29.162252 | J6: =SOTP!N7 -> 0.55 | K6: =SOTP!Q7 -> 748.21407 | L6: =SOTP!R7 -> 16.039239
B7: =SOTP!B8 -> ML-007 | C7: =SOTP!G8 -> AD Psychosis | D7: =SOTP!H8 -> US | E7: =SOTP!I8 -> Phase 2 | F7: =SOTP!J8 -> 2030 | G7: =SOTP!K8 -> 2393.5535 | H7: =SOTP!L8 -> 3270.6507 | I7: =SOTP!M8 -> 36.588651 | J7: =SOTP!N8 -> 0.25 | K7: =SOTP!Q8 -> 426.70579 | L7: =SOTP!R8 -> 9.1471628
B8: =SOTP!B9 -> ML-004 | C8: =SOTP!G9 -> ASD | D8: =SOTP!H9 -> US | E8: =SOTP!I9 -> Phase 2 | F8: =SOTP!J9 -> 2031 | G8: =SOTP!K9 -> 27.19676 | H8: =SOTP!L9 -> -64.933078 | I8: =SOTP!M9 -> -0.72640399 | J8: =SOTP!N9 -> 0.05 | K8: =SOTP!Q9 -> -1.6943001 | L8: =SOTP!R9 -> -0.036320199
B9: =SOTP!B10 -> Collaboration | D9: =SOTP!H10 -> EU | G9: =SOTP!K10 -> 0 | H9: =SOTP!L10 -> #DIV/0! | I9: =SOTP!M10 -> #DIV/0! | J9: =SOTP!N10 -> 0 | K9: =SOTP!Q10 -> 0 | L9: =SOTP!R10 -> 0
B10: Sub-Total | G10: =SUM(G6:G9) -> 3966.4584 | H10: =SUM(H6:H8) -> 5812.5243 | I10: =SUM(I6:I8) -> 65.024499 | K10: =SUM(K6:K9) -> 1173.2256 | L10: =SUM(L6:L9) -> 25.150081
B12: Adjustments
B13: Platform Value | H13: =SOTP!L12 -> 107.87033 | I13: =SOTP!M12 -> 2.3123835 | K13: =H13 -> 107.87033 | L13: =I13 -> 2.3123835
B14: Net Cash | H14: =SOTP!L13 -> 453.096 | I14: =SOTP!M13 -> 9.7128818 | K14: =H14 -> 453.096 | L14: =I14 -> 9.7128818
B15: Total Equity Value | H15: =SUM(H10,H13,H14) -> 6373.4907 | I15: =SUM(I10,I13,I14) -> 77.049764 | K15: =SUM(K10,K13,K14) -> 1734.1919 | L15: =SUM(L10,L13,L14) -> 37.175346
B16: * This includes unallocated R&D and G&A costs.
R18: =CONCATENATE(B6," - ",C6) -> ML-007 - Schizophrenia | S18: =CONCATENATE(B7," - ",C7) -> ML-007 - AD Psychosis | T18: =B13 -> Platform Value | U18: =B14 -> Net Cash | V18: Value/ Share
Q19: Invisible | S19: =R20 -> 16.039239 | T19: =S19+S20 -> 25.186401 | U19: =T19+T20 -> 27.498785
Q20: Visible | R20: =L6 -> 16.039239 | S20: =L7 -> 9.1471628 | T20: =L13 -> 2.3123835 | U20: =L14 -> 9.7128818 | V20: =U19+U20 -> 37.211667
AE44: MPLT | AF44: Mkt Cap | AG44: Cash | AH44: EV
AF45: =TODAY() -> 46119 | AG45: =TODAY() -> 46119
AF46: =_xll.FDS(AE44,"FREF_MARKET_VALUE_COMPANY(0,,,,,0)") -> 898.37701 | AG46: -450 | AH46: =AF46+AG46 -> 448.37701
AF47: 6.746558 | AG47: -2.3405823 | AH47: 4.4059757

Sheet VA Consensus
E1: =HYPERLINK("#Revenue_RV!Notes","See the Notes for this Sheet") -> See the Notes for this Sheet
B2: Company | C2: =_xll.VADetail("Name",$C$3) -> MapLight Therapeutics, Inc.
B3: Ticker | C3: MPLT_US
B4: IMPL or Raw | C4: IMPL
B5: Data Type | C5: CD
B6: Tab | C6: RV
B7: As Of | C7: 46063
E8: 1QFY-2024 | F8: 2QFY-2024 | G8: 3QFY-2024 | H8: 4QFY-2024 | I8: FY-2024 | J8: 1QFY-2025 | K8: 2QFY-2025 | L8: 3QFY-2025 | M8: 4QFY-2025 | N8: FY-2025 | O8: 1QFY-2026 | P8: 2QFY-2026 | Q8: 3QFY-2026 | R8: 4QFY-2026 | S8: FY-2026 | T8: FY-2027 | U8: FY-2028 | V8: FY-2029 | W8: FY-2030 | X8: FY-2031 | Y8: FY-2032 | Z8: FY-2033 | AA8: FY-2034 | AB8: FY-2035
E9: =_xll.VADetail("ActualOrEstimate",$C$3,"Consensus",E$8) -> A | F9: =_xll.VADetail("ActualOrEstimate",$C$3,"Consensus",F$8) -> A | G9: =_xll.VADetail("ActualOrEstimate",$C$3,"Consensus",G$8) -> A | H9: =_xll.VADetail("ActualOrEstimate",$C$3,"Consensus",H$8) -> A | I9: =_xll.VADetail("ActualOrEstimate",$C$3,"Consensus",I$8) -> A | J9: =_xll.VADetail("ActualOrEstimate",$C$3,"Consensus",J$8) -> A | K9: =_xll.VADetail("ActualOrEstimate",$C$3,"Consensus",K$8) -> A | L9: =_xll.VADetail("ActualOrEstimate",$C$3,"Consensus",L$8) -> A | ... AB9: =_xll.VADetail("ActualOrEstimate",$C$3,"Consensus",AB$8) -> E
B10: Item Code | C10: Line Item | D10: Units | E10: =IF(E$9="A","VA Actuals","Consensus") -> VA Actuals | F10: =IF(F$9="A","VA Actuals","Consensus") -> VA Actuals | G10: =IF(G$9="A","VA Actuals","Consensus") -> VA Actuals | H10: =IF(H$9="A","VA Actuals","Consensus") -> VA Actuals | I10: =IF(I$9="A","VA Actuals","Consensus") -> VA Actuals | J10: =IF(J$9="A","VA Actuals","Consensus") -> VA Actuals | K10: =IF(K$9="A","VA Actuals","Consensus") -> VA Actuals | L10: =IF(L$9="A","VA Actuals","Consensus") -> VA Actuals | ... AB10: =IF(AB$9="A","VA Actuals","Consensus") -> Consensus
B11: H | C11: Revenue
B12: H | C12: ML-007-MA
B13: N_15532833 | C13: ML-007-MA - Unadjusted | D13: $M | E13: =_xll.VAData($C$3,E$8,$C13,E$10,$C$5,$C$4,$C$7) -> - | F13: =_xll.VAData($C$3,F$8,$C13,F$10,$C$5,$C$4,$C$7) -> - | G13: =_xll.VAData($C$3,G$8,$C13,G$10,$C$5,$C$4,$C$7) -> - | H13: =_xll.VAData($C$3,H$8,$C13,H$10,$C$5,$C$4,$C$7) -> - | I13: =_xll.VAData($C$3,I$8,$C13,I$10,$C$5,$C$4,$C$7) -> - | J13: =_xll.VAData($C$3,J$8,$C13,J$10,$C$5,$C$4,$C$7) -> - | K13: =_xll.VAData($C$3,K$8,$C13,K$10,$C$5,$C$4,$C$7) -> - | L13: =_xll.VAData($C$3,L$8,$C13,L$10,$C$5,$C$4,$C$7) -> 0 | ... AB13: =_xll.VAData($C$3,AB$8,$C13,AB$10,$C$5,$C$4,$C$7) -> 1509.7701
B14: N_15532854 | C14: ML-007-MA | D14: $M | E14: =_xll.VAData($C$3,E$8,$C14,E$10,$C$5,$C$4,$C$7) -> - | F14: =_xll.VAData($C$3,F$8,$C14,F$10,$C$5,$C$4,$C$7) -> - | G14: =_xll.VAData($C$3,G$8,$C14,G$10,$C$5,$C$4,$C$7) -> - | H14: =_xll.VAData($C$3,H$8,$C14,H$10,$C$5,$C$4,$C$7) -> - | I14: =_xll.VAData($C$3,I$8,$C14,I$10,$C$5,$C$4,$C$7) -> - | J14: =_xll.VAData($C$3,J$8,$C14,J$10,$C$5,$C$4,$C$7) -> - | K14: =_xll.VAData($C$3,K$8,$C14,K$10,$C$5,$C$4,$C$7) -> - | L14: =_xll.VAData($C$3,L$8,$C14,L$10,$C$5,$C$4,$C$7) -> 0 | ... AB14: =_xll.VAData($C$3,AB$8,$C14,AB$10,$C$5,$C$4,$C$7) -> 775.64772
B15: H
B16: H | C16: ML-004
B17: N_15532836 | C17: Revenue - ML-004 - Unadjusted | D17: $M | E17: =_xll.VAData($C$3,E$8,$C17,E$10,$C$5,$C$4,$C$7) -> - | F17: =_xll.VAData($C$3,F$8,$C17,F$10,$C$5,$C$4,$C$7) -> - | G17: =_xll.VAData($C$3,G$8,$C17,G$10,$C$5,$C$4,$C$7) -> - | H17: =_xll.VAData($C$3,H$8,$C17,H$10,$C$5,$C$4,$C$7) -> - | I17: =_xll.VAData($C$3,I$8,$C17,I$10,$C$5,$C$4,$C$7) -> - | J17: =_xll.VAData($C$3,J$8,$C17,J$10,$C$5,$C$4,$C$7) -> - | K17: =_xll.VAData($C$3,K$8,$C17,K$10,$C$5,$C$4,$C$7) -> - | L17: =_xll.VAData($C$3,L$8,$C17,L$10,$C$5,$C$4,$C$7) -> 0 | ... AB17: =_xll.VAData($C$3,AB$8,$C17,AB$10,$C$5,$C$4,$C$7) -> 537.19591
B18: N_15532838 | C18: POS - ML-004 | D18: % | E18: =_xll.VAData($C$3,E$8,$C18,E$10,$C$5,$C$4,$C$7) -> - | F18: =_xll.VAData($C$3,F$8,$C18,F$10,$C$5,$C$4,$C$7) -> - | G18: =_xll.VAData($C$3,G$8,$C18,G$10,$C$5,$C$4,$C$7) -> - | H18: =_xll.VAData($C$3,H$8,$C18,H$10,$C$5,$C$4,$C$7) -> - | I18: =_xll.VAData($C$3,I$8,$C18,I$10,$C$5,$C$4,$C$7) -> - | J18: =_xll.VAData($C$3,J$8,$C18,J$10,$C$5,$C$4,$C$7) -> - | K18: =_xll.VAData($C$3,K$8,$C18,K$10,$C$5,$C$4,$C$7) -> - | L18: =_xll.VAData($C$3,L$8,$C18,L$10,$C$5,$C$4,$C$7) -> - | ... AB18: =_xll.VAData($C$3,AB$8,$C18,AB$10,$C$5,$C$4,$C$7) -> 13.75
B19: N_15532846 | C19: Revenue - ML-004 | D19: $M | E19: =_xll.VAData($C$3,E$8,$C19,E$10,$C$5,$C$4,$C$7) -> - | F19: =_xll.VAData($C$3,F$8,$C19,F$10,$C$5,$C$4,$C$7) -> - | G19: =_xll.VAData($C$3,G$8,$C19,G$10,$C$5,$C$4,$C$7) -> - | H19: =_xll.VAData($C$3,H$8,$C19,H$10,$C$5,$C$4,$C$7) -> - | I19: =_xll.VAData($C$3,I$8,$C19,I$10,$C$5,$C$4,$C$7) -> - | J19: =_xll.VAData($C$3,J$8,$C19,J$10,$C$5,$C$4,$C$7) -> - | K19: =_xll.VAData($C$3,K$8,$C19,K$10,$C$5,$C$4,$C$7) -> - | L19: =_xll.VAData($C$3,L$8,$C19,L$10,$C$5,$C$4,$C$7) -> 0 | ... AB19: =_xll.VAData($C$3,AB$8,$C19,AB$10,$C$5,$C$4,$C$7) -> 67.195105
B20: H
B21: N_15532812 | C21: Pipeline - Unadjusted | D21: $M | E21: =_xll.VAData($C$3,E$8,$C21,E$10,$C$5,$C$4,$C$7) -> - | F21: =_xll.VAData($C$3,F$8,$C21,F$10,$C$5,$C$4,$C$7) -> - | G21: =_xll.VAData($C$3,G$8,$C21,G$10,$C$5,$C$4,$C$7) -> - | H21: =_xll.VAData($C$3,H$8,$C21,H$10,$C$5,$C$4,$C$7) -> - | I21: =_xll.VAData($C$3,I$8,$C21,I$10,$C$5,$C$4,$C$7) -> 0 | J21: =_xll.VAData($C$3,J$8,$C21,J$10,$C$5,$C$4,$C$7) -> - | K21: =_xll.VAData($C$3,K$8,$C21,K$10,$C$5,$C$4,$C$7) -> - | L21: =_xll.VAData($C$3,L$8,$C21,L$10,$C$5,$C$4,$C$7) -> 0 | ... AB21: =_xll.VAData($C$3,AB$8,$C21,AB$10,$C$5,$C$4,$C$7) -> 2046.966
B22: N_15532813 | C22: Pipeline | D22: $M | E22: =_xll.VAData($C$3,E$8,$C22,E$10,$C$5,$C$4,$C$7) -> - | F22: =_xll.VAData($C$3,F$8,$C22,F$10,$C$5,$C$4,$C$7) -> - | G22: =_xll.VAData($C$3,G$8,$C22,G$10,$C$5,$C$4,$C$7) -> - | H22: =_xll.VAData($C$3,H$8,$C22,H$10,$C$5,$C$4,$C$7) -> - | I22: =_xll.VAData($C$3,I$8,$C22,I$10,$C$5,$C$4,$C$7) -> - | J22: =_xll.VAData($C$3,J$8,$C22,J$10,$C$5,$C$4,$C$7) -> - | K22: =_xll.VAData($C$3,K$8,$C22,K$10,$C$5,$C$4,$C$7) -> - | L22: =_xll.VAData($C$3,L$8,$C22,L$10,$C$5,$C$4,$C$7) -> 0 | ... AB22: =_xll.VAData($C$3,AB$8,$C22,AB$10,$C$5,$C$4,$C$7) -> 842.84282
B23: H
B24: N_15532814 | C24: Total revenue - Risk unadjusted | D24: $M | E24: =_xll.VAData($C$3,E$8,$C24,E$10,$C$5,$C$4,$C$7) -> - | F24: =_xll.VAData($C$3,F$8,$C24,F$10,$C$5,$C$4,$C$7) -> - | G24: =_xll.VAData($C$3,G$8,$C24,G$10,$C$5,$C$4,$C$7) -> - | H24: =_xll.VAData($C$3,H$8,$C24,H$10,$C$5,$C$4,$C$7) -> - | I24: =_xll.VAData($C$3,I$8,$C24,I$10,$C$5,$C$4,$C$7) -> 0 | J24: =_xll.VAData($C$3,J$8,$C24,J$10,$C$5,$C$4,$C$7) -> - | K24: =_xll.VAData($C$3,K$8,$C24,K$10,$C$5,$C$4,$C$7) -> - | L24: =_xll.VAData($C$3,L$8,$C24,L$10,$C$5,$C$4,$C$7) -> 0 | ... AB24: =_xll.VAData($C$3,AB$8,$C24,AB$10,$C$5,$C$4,$C$7) -> 2046.966
B25: N_15532815 | C25: Total revenue - Risk adjusted | D25: $M | E25: =_xll.VAData($C$3,E$8,$C25,E$10,$C$5,$C$4,$C$7) -> - | F25: =_xll.VAData($C$3,F$8,$C25,F$10,$C$5,$C$4,$C$7) -> - | G25: =_xll.VAData($C$3,G$8,$C25,G$10,$C$5,$C$4,$C$7) -> - | H25: =_xll.VAData($C$3,H$8,$C25,H$10,$C$5,$C$4,$C$7) -> - | I25: =_xll.VAData($C$3,I$8,$C25,I$10,$C$5,$C$4,$C$7) -> - | J25: =_xll.VAData($C$3,J$8,$C25,J$10,$C$5,$C$4,$C$7) -> - | K25: =_xll.VAData($C$3,K$8,$C25,K$10,$C$5,$C$4,$C$7) -> - | L25: =_xll.VAData($C$3,L$8,$C25,L$10,$C$5,$C$4,$C$7) -> 0 | ... AB25: =_xll.VAData($C$3,AB$8,$C25,AB$10,$C$5,$C$4,$C$7) -> 842.84282
B26: H
B27: N_15532756 | C27: Total revenue | D27: $M | E27: =_xll.VAData($C$3,E$8,$C27,E$10,$C$5,$C$4,$C$7) -> 0 | F27: =_xll.VAData($C$3,F$8,$C27,F$10,$C$5,$C$4,$C$7) -> 0 | G27: =_xll.VAData($C$3,G$8,$C27,G$10,$C$5,$C$4,$C$7) -> 0 | H27: =_xll.VAData($C$3,H$8,$C27,H$10,$C$5,$C$4,$C$7) -> 0 | I27: =_xll.VAData($C$3,I$8,$C27,I$10,$C$5,$C$4,$C$7) -> 0 | J27: =_xll.VAData($C$3,J$8,$C27,J$10,$C$5,$C$4,$C$7) -> 0 | K27: =_xll.VAData($C$3,K$8,$C27,K$10,$C$5,$C$4,$C$7) -> 0 | L27: =_xll.VAData($C$3,L$8,$C27,L$10,$C$5,$C$4,$C$7) -> 0 | ... AB27: =_xll.VAData($C$3,AB$8,$C27,AB$10,$C$5,$C$4,$C$7) -> 1392.2424
B28: H
C30: Notes:
C31: By default, this downloaded page includes data from 1QFY-2024 (1QFY-2024) to FY-2035 (FY-2035)
C32: It contains the same period types as those selected for the worksheet on the Visible Alpha web platform.
C33: Visible Alpha has Quarterly and Annual data for MPLT_US from Jan 2022 to Dec 2047

Sheet TODO
A3: If-convertible share count for convcertible stocks needs to be reflected.

Sheet FactSet
A3: MPLT-US | K3: MPLT-US
A4: Earnings Per Share | K4: Earnings Per Share
A5: Ticker | B5: MPLT-US | K5: Ticker | L5: MPLT-US
B6: {=_xll.FDSRC("-",$B$5,"PROPER(CONVERT_DATE(FE_TIMESERIES_PERIOD(,2024,2030,FY,'DISPLAY=YYYYMMDD'),""MMM 'YY""))")} -> Dec '24 | C6: Dec '25 | D6: Dec '26 | E6: Dec '27 | F6: Dec '28 | G6: Dec '29 | H6: Dec '30 | L6: {=_xll.FDSRC("-",$L$5,"PROPER(CONVERT_DATE(FE_TIMESERIES_PERIOD(,2023,2024,FY,'DISPLAY=YYYYMMDD'),""MMM 'YY""))")} -> Dec '23 | M6: Dec '24 | N6: {=_xll.FDSRC("-",$L$5,"PROPER(CONVERT_DATE(FE_TIMESERIES_PERIOD(,2025/1F,2025/4F,FQ,'DISPLAY=YYYYMMDD'),""MMM 'YY""))")} -> Mar '25 | O6: Jun '25 | P6: Sep '25 | Q6: Dec '25 | R6: =_xll.FDSRC("-",$L$5,"PROPER(CONVERT_DATE(FE_TIMESERIES_PERIOD(,2025,2025,FY,'DISPLAY=YYYYMMDD'),""MMM 'YY""))") -> Dec '25 | S6: {=_xll.FDSRC("-",$L$5,"PROPER(CONVERT_DATE(FE_TIMESERIES_PERIOD(,2026/1F,2026/4F,FQ,'DISPLAY=YYYYMMDD'),""MMM 'YY""))")} -> Mar '26 | T6: Jun '26 | U6: Sep '26 | V6: Dec '26 | W6: {=_xll.FDSRC("-",$L$5,"PROPER(CONVERT_DATE(FE_TIMESERIES_PERIOD(,2026,2027,FY,'DISPLAY=YYYYMMDD'),""MMM 'YY""))")} -> Dec '26 | X6: Dec '27
A7: EPS | B7: {=_xll.FDSRC("-",$B$5,"FE_TIMESERIES(EPS,MEAN,2024,2030,FY,'BKRACTMED=1,WIN=0,UNITS=AUTO,DATE=NOW')")} -> - | C7: -18.56 | D7: -3.946 | E7: -4.1 | F7: -4.77 | G7: -4.56 | H7: -4.67 | L7: {=_xll.FDSRC("-",$L$5,"FE_TIMESERIES_PERIOD(,2023,2024,FY,'')")} -> 2023 | M7: 2024 | N7: {=_xll.FDSRC("-",$L$5,"FE_TIMESERIES_PERIOD(,2025/1F,2025/4F,FQ,'')")} -> 2025/1F | O7: 2025/2F | P7: 2025/3F | Q7: 2025/4F | R7: =_xll.FDSRC("-",$L$5,"FE_TIMESERIES_PERIOD(,2025,2025,FY,'')") -> 2025 | S7: {=_xll.FDSRC("-",$L$5,"FE_TIMESERIES_PERIOD(,2026/1F,2026/4F,FQ,'')")} -> 2026/1F | T7: 2026/2F | U7: 2026/3F | V7: 2026/4F | W7: {=_xll.FDSRC("-",$L$5,"FE_TIMESERIES_PERIOD(,2026,2027,FY,'')")} -> 2026 | X7: 2027
A8: EPS - GAAP | B8: {=_xll.FDSRC("-",$B$5,"FE_TIMESERIES(EAG,MEAN,2024,2030,FY,'BKRACTMED=1,WIN=0,UNITS=AUTO,DATE=NOW')")} -> - | C8: -18.625 | D8: -4.0866666 | E8: -4.735 | F8: -5.17 | G8: -4.995 | H8: -4.79 | K8: EPS | L8: {=_xll.FDSRC("-",$L$5,"FE_TIMESERIES(EPS,MEAN,2023,2024,FY,'BKRACTMED=1,WIN=0,UNITS=AUTO,DATE=NOW')")} -> - | M8: - | N8: {=_xll.FDSRC("-",$L$5,"FE_TIMESERIES(EPS,MEAN,2025/1F,2025/4F,FQ,'BKRACTMED=1,WIN=0,UNITS=AUTO,DATE=NOW')")} -> - | O8: -1.14 | P8: -37.18 | Q8: -2.47 | R8: =_xll.FDSRC("-",$L$5,"FE_TIMESERIES(EPS,MEAN,2025,2025,FY,'BKRACTMED=1,WIN=0,UNITS=AUTO,DATE=NOW')") -> -18.56 | S8: {=_xll.FDSRC("-",$L$5,"FE_TIMESERIES(EPS,MEAN,2026/1F,2026/4F,FQ,'BKRACTMED=1,WIN=0,UNITS=AUTO,DATE=NOW')")} -> -0.948 | T8: -0.99 | U8: -0.98 | V8: -1.028 | W8: {=_xll.FDSRC("-",$L$5,"FE_TIMESERIES(EPS,MEAN,2026,2027,FY,'BKRACTMED=1,WIN=0,UNITS=AUTO,DATE=NOW')")} -> -3.946 | X8: -4.1
K9: EPS - GAAP | L9: {=_xll.FDSRC("-",$L$5,"FE_TIMESERIES(EAG,MEAN,2023,2024,FY,'BKRACTMED=1,WIN=0,UNITS=AUTO,DATE=NOW')")} -> - | M9: - | N9: {=_xll.FDSRC("-",$L$5,"FE_TIMESERIES(EAG,MEAN,2025/1F,2025/4F,FQ,'BKRACTMED=1,WIN=0,UNITS=AUTO,DATE=NOW')")} -> - | O9: - | P9: -37.18 | Q9: -2.47 | R9: =_xll.FDSRC("-",$L$5,"FE_TIMESERIES(EAG,MEAN,2025,2025,FY,'BKRACTMED=1,WIN=0,UNITS=AUTO,DATE=NOW')") -> -18.625 | S9: {=_xll.FDSRC("-",$L$5,"FE_TIMESERIES(EAG,MEAN,2026/1F,2026/4F,FQ,'BKRACTMED=1,WIN=0,UNITS=AUTO,DATE=NOW')")} -> -1.0066667 | T9: -1.05 | U9: -0.9866667 | V9: -1.0466666 | W9: {=_xll.FDSRC("-",$L$5,"FE_TIMESERIES(EAG,MEAN,2026,2027,FY,'BKRACTMED=1,WIN=0,UNITS=AUTO,DATE=NOW')")} -> -4.0866666 | X9: -4.735
A11: MPLT-US
A12: Income Statement (M) | K12: MPLT-US
A13: Ticker | B13: MPLT-US | K13: Income Statement (M)
B14: {=_xll.FDSRC("-",$B$13,"PROPER(CONVERT_DATE(FE_TIMESERIES_PERIOD(,2024,2030,FY,'DISPLAY=YYYYMMDD'),""MMM 'YY""))")} -> Dec '24 | C14: Dec '25 | D14: Dec '26 | E14: Dec '27 | F14: Dec '28 | G14: Dec '29 | H14: Dec '30 | K14: Ticker | L14: MPLT-US
A15: Sales | B15: {=_xll.FDSRC("-",$B$13,"FE_TIMESERIES(SALES,MEAN,2024,2030,FY,'BKRACTMED=1,WIN=0,UNITS=AUTO,DATE=NOW')")} -> - | C15: 0 | D15: 0 | E15: 0 | F15: 0 | G15: 0 | H15: 49.1 | L15: {=_xll.FDSRC("-",$L$14,"PROPER(CONVERT_DATE(FE_TIMESERIES_PERIOD(,2023,2024,FY,'DISPLAY=YYYYMMDD'),""MMM 'YY""))")} -> Dec '23 | M15: Dec '24 | N15: {=_xll.FDSRC("-",$L$14,"PROPER(CONVERT_DATE(FE_TIMESERIES_PERIOD(,2025/1F,2025/4F,FQ,'DISPLAY=YYYYMMDD'),""MMM 'YY""))")} -> Mar '25 | O15: Jun '25 | P15: Sep '25 | Q15: Dec '25 | R15: =_xll.FDSRC("-",$L$14,"PROPER(CONVERT_DATE(FE_TIMESERIES_PERIOD(,2025,2025,FY,'DISPLAY=YYYYMMDD'),""MMM 'YY""))") -> Dec '25 | S15: {=_xll.FDSRC("-",$L$14,"PROPER(CONVERT_DATE(FE_TIMESERIES_PERIOD(,2026/1F,2026/4F,FQ,'DISPLAY=YYYYMMDD'),""MMM 'YY""))")} -> Mar '26 | T15: Jun '26 | U15: Sep '26 | V15: Dec '26 | W15: {=_xll.FDSRC("-",$L$14,"PROPER(CONVERT_DATE(FE_TIMESERIES_PERIOD(,2026,2027,FY,'DISPLAY=YYYYMMDD'),""MMM 'YY""))")} -> Dec '26 | X15: Dec '27
A16: Cost of Sales | B16: {=_xll.FDSRC("-",$B$13,"FE_TIMESERIES(COS,MEAN,2024,2030,FY,'BKRACTMED=1,WIN=0,UNITS=AUTO,DATE=NOW')")} -> - | C16: 0 | D16: 0 | E16: 0 | F16: 0 | G16: 0 | H16: 2.55 | L16: {=_xll.FDSRC("-",$L$14,"FE_TIMESERIES_PERIOD(,2023,2024,FY,'')")} -> 2023 | M16: 2024 | N16: {=_xll.FDSRC("-",$L$14,"FE_TIMESERIES_PERIOD(,2025/1F,2025/4F,FQ,'')")} -> 2025/1F | O16: 2025/2F | P16: 2025/3F | Q16: 2025/4F | R16: =_xll.FDSRC("-",$L$14,"FE_TIMESERIES_PERIOD(,2025,2025,FY,'')") -> 2025 | S16: {=_xll.FDSRC("-",$L$14,"FE_TIMESERIES_PERIOD(,2026/1F,2026/4F,FQ,'')")} -> 2026/1F | T16: 2026/2F | U16: 2026/3F | V16: 2026/4F | W16: {=_xll.FDSRC("-",$L$14,"FE_TIMESERIES_PERIOD(,2026,2027,FY,'')")} -> 2026 | X16: 2027
A17: Gross Income | B17: {=_xll.FDSRC("-",$B$13,"FE_TIMESERIES(GROSSINCOME,MEAN,2024,2030,FY,'BKRACTMED=1,WIN=0,UNITS=AUTO,DATE=NOW')")} -> - | C17: 0 | D17: 0 | E17: 0 | F17: 0 | G17: 0 | H17: 53.65 | K17: Sales | L17: {=_xll.FDSRC("-",$L$14,"FE_TIMESERIES(SALES,MEAN,2023,2024,FY,'BKRACTMED=1,WIN=0,UNITS=AUTO,DATE=NOW')")} -> - | M17: - | N17: {=_xll.FDSRC("-",$L$14,"FE_TIMESERIES(SALES,MEAN,2025/1F,2025/4F,FQ,'BKRACTMED=1,WIN=0,UNITS=AUTO,DATE=NOW')")} -> - | O17: 0 | P17: 0 | Q17: 0 | R17: =_xll.FDSRC("-",$L$14,"FE_TIMESERIES(SALES,MEAN,2025,2025,FY,'BKRACTMED=1,WIN=0,UNITS=AUTO,DATE=NOW')") -> 0 | S17: {=_xll.FDSRC("-",$L$14,"FE_TIMESERIES(SALES,MEAN,2026/1F,2026/4F,FQ,'BKRACTMED=1,WIN=0,UNITS=AUTO,DATE=NOW')")} -> 0 | T17: 0 | U17: 0 | V17: 0 | W17: {=_xll.FDSRC("-",$L$14,"FE_TIMESERIES(SALES,MEAN,2026,2027,FY,'BKRACTMED=1,WIN=0,UNITS=AUTO,DATE=NOW')")} -> 0 | X17: 0
A18: SG&A Expense | B18: {=_xll.FDSRC("-",$B$13,"FE_TIMESERIES(SGA,MEAN,2024,2030,FY,'BKRACTMED=1,WIN=0,UNITS=AUTO,DATE=NOW')")} -> - | C18: 30.7 | D18: 37.433334 | E18: 42.1 | F18: 47.8 | G18: 50.7 | H18: 196.6 | K18: Cost of Sales | L18: {=_xll.FDSRC("-",$L$14,"FE_TIMESERIES(COS,MEAN,2023,2024,FY,'BKRACTMED=1,WIN=0,UNITS=AUTO,DATE=NOW')")} -> - | M18: - | N18: {=_xll.FDSRC("-",$L$14,"FE_TIMESERIES(COS,MEAN,2025/1F,2025/4F,FQ,'BKRACTMED=1,WIN=0,UNITS=AUTO,DATE=NOW')")} -> - | O18: 0 | P18: 0 | Q18: 0 | R18: =_xll.FDSRC("-",$L$14,"FE_TIMESERIES(COS,MEAN,2025,2025,FY,'BKRACTMED=1,WIN=0,UNITS=AUTO,DATE=NOW')") -> 0 | S18: {=_xll.FDSRC("-",$L$14,"FE_TIMESERIES(COS,MEAN,2026/1F,2026/4F,FQ,'BKRACTMED=1,WIN=0,UNITS=AUTO,DATE=NOW')")} -> 0 | T18: 0 | U18: 0 | V18: 0 | W18: {=_xll.FDSRC("-",$L$14,"FE_TIMESERIES(COS,MEAN,2026,2027,FY,'BKRACTMED=1,WIN=0,UNITS=AUTO,DATE=NOW')")} -> 0 | X18: 0
A19: Research & Development | B19: {=_xll.FDSRC("-",$B$13,"FE_TIMESERIES(RD_EXP,MEAN,2024,2030,FY,'BKRACTMED=1,WIN=0,UNITS=AUTO,DATE=NOW')")} -> - | C19: 138.3 | D19: 150.66667 | E19: 175 | F19: 212.5 | G19: 207.5 | H19: 147.5 | K19: Gross Income | L19: {=_xll.FDSRC("-",$L$14,"FE_TIMESERIES(GROSSINCOME,MEAN,2023,2024,FY,'BKRACTMED=1,WIN=0,UNITS=AUTO,DATE=NOW')")} -> - | M19: - | N19: {=_xll.FDSRC("-",$L$14,"FE_TIMESERIES(GROSSINCOME,MEAN,2025/1F,2025/4F,FQ,'BKRACTMED=1,WIN=0,UNITS=AUTO,DATE=NOW')")} -> - | O19: 0 | P19: 0 | Q19: 0 | R19: =_xll.FDSRC("-",$L$14,"FE_TIMESERIES(GROSSINCOME,MEAN,2025,2025,FY,'BKRACTMED=1,WIN=0,UNITS=AUTO,DATE=NOW')") -> 0 | S19: {=_xll.FDSRC("-",$L$14,"FE_TIMESERIES(GROSSINCOME,MEAN,2026/1F,2026/4F,FQ,'BKRACTMED=1,WIN=0,UNITS=AUTO,DATE=NOW')")} -> 0 | T19: 0 | U19: 0 | V19: 0 | W19: {=_xll.FDSRC("-",$L$14,"FE_TIMESERIES(GROSSINCOME,MEAN,2026,2027,FY,'BKRACTMED=1,WIN=0,UNITS=AUTO,DATE=NOW')")} -> 0 | X19: 0
A20: EBITDA | B20: {=_xll.FDSRC("-",$B$13,"FE_TIMESERIES(EBITDA,MEAN,2024,2030,FY,'BKRACTMED=1,WIN=0,UNITS=AUTO,DATE=NOW')")} -> - | C20: -169.5525 | D20: -210.85167 | E20: -227.40497 | F20: -298.0468 | G20: -264 | H20: -245.1 | K20: SG&A Expense | L20: {=_xll.FDSRC("-",$L$14,"FE_TIMESERIES(SGA,MEAN,2023,2024,FY,'BKRACTMED=1,WIN=0,UNITS=AUTO,DATE=NOW')")} -> - | M20: - | N20: {=_xll.FDSRC("-",$L$14,"FE_TIMESERIES(SGA,MEAN,2025/1F,2025/4F,FQ,'BKRACTMED=1,WIN=0,UNITS=AUTO,DATE=NOW')")} -> - | O20: 4.1 | P20: 4.4 | Q20: 18.8 | R20: =_xll.FDSRC("-",$L$14,"FE_TIMESERIES(SGA,MEAN,2025,2025,FY,'BKRACTMED=1,WIN=0,UNITS=AUTO,DATE=NOW')") -> 30.7 | S20: {=_xll.FDSRC("-",$L$14,"FE_TIMESERIES(SGA,MEAN,2026/1F,2026/4F,FQ,'BKRACTMED=1,WIN=0,UNITS=AUTO,DATE=NOW')")} -> 8.5 | T20: 9.033334 | U20: 9.733334 | V20: 10.166667 | W20: {=_xll.FDSRC("-",$L$14,"FE_TIMESERIES(SGA,MEAN,2026,2027,FY,'BKRACTMED=1,WIN=0,UNITS=AUTO,DATE=NOW')")} -> 37.433334 | X20: 42.1
A21: Depr. & Amort. | B21: {=_xll.FDSRC("-",$B$13,"FE_TIMESERIES(DEPR_AMORT,MEAN,2024,2030,FY,'BKRACTMED=1,WIN=0,UNITS=AUTO,DATE=NOW')")} -> - | C21: 0.6 | D21: 1.3 | E21: 0.55 | F21: 0.8 | G21: 0.8 | H21: 0.8 | K21: Research & Development | L21: {=_xll.FDSRC("-",$L$14,"FE_TIMESERIES(RD_EXP,MEAN,2023,2024,FY,'BKRACTMED=1,WIN=0,UNITS=AUTO,DATE=NOW')")} -> - | M21: - | N21: {=_xll.FDSRC("-",$L$14,"FE_TIMESERIES(RD_EXP,MEAN,2025/1F,2025/4F,FQ,'BKRACTMED=1,WIN=0,UNITS=AUTO,DATE=NOW')")} -> - | O21: 24.6 | P21: 27.1 | Q21: 64.6 | R21: =_xll.FDSRC("-",$L$14,"FE_TIMESERIES(RD_EXP,MEAN,2025,2025,FY,'BKRACTMED=1,WIN=0,UNITS=AUTO,DATE=NOW')") -> 138.3 | S21: {=_xll.FDSRC("-",$L$14,"FE_TIMESERIES(RD_EXP,MEAN,2026/1F,2026/4F,FQ,'BKRACTMED=1,WIN=0,UNITS=AUTO,DATE=NOW')")} -> 35.1 | T21: 36.766666 | U21: 38.1 | V21: 40.766666 | W21: {=_xll.FDSRC("-",$L$14,"FE_TIMESERIES(RD_EXP,MEAN,2026,2027,FY,'BKRACTMED=1,WIN=0,UNITS=AUTO,DATE=NOW')")} -> 150.66667 | X21: 175
A22: Operating Income | B22: {=_xll.FDSRC("-",$B$13,"FE_TIMESERIES(EBIT,MEAN,2024,2030,FY,'BKRACTMED=1,WIN=0,UNITS=AUTO,DATE=NOW')")} -> - | C22: -169.1 | D22: -195.55608 | E22: -240.46242 | F22: -298.63568 | G22: -300.73334 | H22: -328.1 | K22: EBITDA | L22: {=_xll.FDSRC("-",$L$14,"FE_TIMESERIES(EBITDA,MEAN,2023,2024,FY,'BKRACTMED=1,WIN=0,UNITS=AUTO,DATE=NOW')")} -> - | M22: - | N22: {=_xll.FDSRC("-",$L$14,"FE_TIMESERIES(EBITDA,MEAN,2025/1F,2025/4F,FQ,'BKRACTMED=1,WIN=0,UNITS=AUTO,DATE=NOW')")} -> - | O22: - | P22: - | Q22: -84.7 | R22: =_xll.FDSRC("-",$L$14,"FE_TIMESERIES(EBITDA,MEAN,2025,2025,FY,'BKRACTMED=1,WIN=0,UNITS=AUTO,DATE=NOW')") -> -169.5525 | S22: {=_xll.FDSRC("-",$L$14,"FE_TIMESERIES(EBITDA,MEAN,2026/1F,2026/4F,FQ,'BKRACTMED=1,WIN=0,UNITS=AUTO,DATE=NOW')")} -> -48.9 | T22: -51.9 | U22: -54.9 | V22: -57.9 | W22: {=_xll.FDSRC("-",$L$14,"FE_TIMESERIES(EBITDA,MEAN,2026,2027,FY,'BKRACTMED=1,WIN=0,UNITS=AUTO,DATE=NOW')")} -> -210.85167 | X22: -227.40497
A23: Operating Income - GAAP | B23: {=_xll.FDSRC("-",$B$13,"FE_TIMESERIES(EBITR,MEAN,2024,2030,FY,'BKRACTMED=1,WIN=0,UNITS=AUTO,DATE=NOW')")} -> - | C23: -169.1 | D23: -205.2 | E23: -302 | F23: -341.2 | G23: - | H23: - | K23: Depr. & Amort. | L23: {=_xll.FDSRC("-",$L$14,"FE_TIMESERIES(DEPR_AMORT,MEAN,2023,2024,FY,'BKRACTMED=1,WIN=0,UNITS=AUTO,DATE=NOW')")} -> - | M23: - | N23: {=_xll.FDSRC("-",$L$14,"FE_TIMESERIES(DEPR_AMORT,MEAN,2025/1F,2025/4F,FQ,'BKRACTMED=1,WIN=0,UNITS=AUTO,DATE=NOW')")} -> - | O23: - | P23: 0.1 | Q23: 0.1 | R23: =_xll.FDSRC("-",$L$14,"FE_TIMESERIES(DEPR_AMORT,MEAN,2025,2025,FY,'BKRACTMED=1,WIN=0,UNITS=AUTO,DATE=NOW')") -> 0.6 | S23: {=_xll.FDSRC("-",$L$14,"FE_TIMESERIES(DEPR_AMORT,MEAN,2026/1F,2026/4F,FQ,'BKRACTMED=1,WIN=0,UNITS=AUTO,DATE=NOW')")} -> 0.4 | T23: 0.4 | U23: 0.4 | V23: 0.4 | W23: {=_xll.FDSRC("-",$L$14,"FE_TIMESERIES(DEPR_AMORT,MEAN,2026,2027,FY,'BKRACTMED=1,WIN=0,UNITS=AUTO,DATE=NOW')")} -> 1.3 | X23: 0.55
A24: Interest Income | B24: {=_xll.FDSRC("-",$B$13,"FE_TIMESERIES(INT_INCOME,MEAN,2024,2030,FY,'BKRACTMED=1,WIN=0,UNITS=AUTO,DATE=NOW')")} -> - | C24: - | D24: - | E24: - | F24: - | G24: - | H24: - | K24: Operating Income | L24: {=_xll.FDSRC("-",$L$14,"FE_TIMESERIES(EBIT,MEAN,2023,2024,FY,'BKRACTMED=1,WIN=0,UNITS=AUTO,DATE=NOW')")} -> - | M24: - | N24: {=_xll.FDSRC("-",$L$14,"FE_TIMESERIES(EBIT,MEAN,2025/1F,2025/4F,FQ,'BKRACTMED=1,WIN=0,UNITS=AUTO,DATE=NOW')")} -> - | O24: -29.7 | P24: -31.5 | Q24: -83.4 | R24: =_xll.FDSRC("-",$L$14,"FE_TIMESERIES(EBIT,MEAN,2025,2025,FY,'BKRACTMED=1,WIN=0,UNITS=AUTO,DATE=NOW')") -> -169.1 | S24: {=_xll.FDSRC("-",$L$14,"FE_TIMESERIES(EBIT,MEAN,2026/1F,2026/4F,FQ,'BKRACTMED=1,WIN=0,UNITS=AUTO,DATE=NOW')")} -> -43.55 | T24: -46.35 | U24: -49.275 | V24: -53.25 | W24: {=_xll.FDSRC("-",$L$14,"FE_TIMESERIES(EBIT,MEAN,2026,2027,FY,'BKRACTMED=1,WIN=0,UNITS=AUTO,DATE=NOW')")} -> -195.55608 | X24: -240.46242
A25: Pretax Income | B25: {=_xll.FDSRC("-",$B$13,"FE_TIMESERIES(PTP,MEAN,2024,2030,FY,'BKRACTMED=1,WIN=0,UNITS=AUTO,DATE=NOW')")} -> - | C25: -161.2 | D25: -186.84521 | E25: -228.53249 | F25: -286.71274 | G25: -292.96667 | H25: -318.8 | K25: Operating Income - GAAP | L25: {=_xll.FDSRC("-",$L$14,"FE_TIMESERIES(EBITR,MEAN,2023,2024,FY,'BKRACTMED=1,WIN=0,UNITS=AUTO,DATE=NOW')")} -> - | M25: - | N25: {=_xll.FDSRC("-",$L$14,"FE_TIMESERIES(EBITR,MEAN,2025/1F,2025/4F,FQ,'BKRACTMED=1,WIN=0,UNITS=AUTO,DATE=NOW')")} -> - | O25: - | P25: -31.5 | Q25: -83.4 | R25: =_xll.FDSRC("-",$L$14,"FE_TIMESERIES(EBITR,MEAN,2025,2025,FY,'BKRACTMED=1,WIN=0,UNITS=AUTO,DATE=NOW')") -> -169.1 | S25: {=_xll.FDSRC("-",$L$14,"FE_TIMESERIES(EBITR,MEAN,2026/1F,2026/4F,FQ,'BKRACTMED=1,WIN=0,UNITS=AUTO,DATE=NOW')")} -> -43.4 | T25: -48 | U25: -53.6 | V25: -60.2 | W25: {=_xll.FDSRC("-",$L$14,"FE_TIMESERIES(EBITR,MEAN,2026,2027,FY,'BKRACTMED=1,WIN=0,UNITS=AUTO,DATE=NOW')")} -> -205.2 | X25: -302
A26: Pretax Income - Non GAAP | B26: {=_xll.FDSRC("-",$B$13,"FE_TIMESERIES(PTPA,MEAN,2024,2030,FY,'BKRACTMED=1,WIN=0,UNITS=AUTO,DATE=NOW')")} -> - | C26: -161.2 | D26: -185 | E26: -279.1 | F26: -316.9 | G26: - | H26: - | K26: Interest Income | L26: {=_xll.FDSRC("-",$L$14,"FE_TIMESERIES(INT_INCOME,MEAN,2023,2024,FY,'BKRACTMED=1,WIN=0,UNITS=AUTO,DATE=NOW')")} -> - | M26: - | N26: {=_xll.FDSRC("-",$L$14,"FE_TIMESERIES(INT_INCOME,MEAN,2025/1F,2025/4F,FQ,'BKRACTMED=1,WIN=0,UNITS=AUTO,DATE=NOW')")} -> - | O26: - | P26: 1.5 | Q26: - | R26: =_xll.FDSRC("-",$L$14,"FE_TIMESERIES(INT_INCOME,MEAN,2025,2025,FY,'BKRACTMED=1,WIN=0,UNITS=AUTO,DATE=NOW')") -> - | S26: {=_xll.FDSRC("-",$L$14,"FE_TIMESERIES(INT_INCOME,MEAN,2026/1F,2026/4F,FQ,'BKRACTMED=1,WIN=0,UNITS=AUTO,DATE=NOW')")} -> - | T26: - | U26: - | V26: - | W26: {=_xll.FDSRC("-",$L$14,"FE_TIMESERIES(INT_INCOME,MEAN,2026,2027,FY,'BKRACTMED=1,WIN=0,UNITS=AUTO,DATE=NOW')")} -> - | X26: -
A27: Tax Expense | B27: {=_xll.FDSRC("-",$B$13,"FE_TIMESERIES(TAX_EXPENSE,MEAN,2024,2030,FY,'BKRACTMED=1,WIN=0,UNITS=AUTO,DATE=NOW')")} -> - | C27: 0 | D27: 0 | E27: 0 | F27: 0 | G27: 0 | H27: 0 | K27: Pretax Income | L27: {=_xll.FDSRC("-",$L$14,"FE_TIMESERIES(PTP,MEAN,2023,2024,FY,'BKRACTMED=1,WIN=0,UNITS=AUTO,DATE=NOW')")} -> - | M27: - | N27: {=_xll.FDSRC("-",$L$14,"FE_TIMESERIES(PTP,MEAN,2025/1F,2025/4F,FQ,'BKRACTMED=1,WIN=0,UNITS=AUTO,DATE=NOW')")} -> - | O27: -28.6 | P27: -29.4 | Q27: -79.5 | R27: =_xll.FDSRC("-",$L$14,"FE_TIMESERIES(PTP,MEAN,2025,2025,FY,'BKRACTMED=1,WIN=0,UNITS=AUTO,DATE=NOW')") -> -161.2 | S27: {=_xll.FDSRC("-",$L$14,"FE_TIMESERIES(PTP,MEAN,2026/1F,2026/4F,FQ,'BKRACTMED=1,WIN=0,UNITS=AUTO,DATE=NOW')")} -> -41.575 | T27: -44.175 | U27: -47.3 | V27: -51.15 | W27: {=_xll.FDSRC("-",$L$14,"FE_TIMESERIES(PTP,MEAN,2026,2027,FY,'BKRACTMED=1,WIN=0,UNITS=AUTO,DATE=NOW')")} -> -186.84521 | X27: -228.53249
A28: Net Income | B28: {=_xll.FDSRC("-",$B$13,"FE_TIMESERIES(NETPROFIT,MEAN,2024,2030,FY,'BKRACTMED=1,WIN=0,UNITS=AUTO,DATE=NOW')")} -> - | C28: -161.152 | D28: -186.84521 | E28: -228.53249 | F28: -286.71274 | G28: -292.96667 | H28: -318.8 | K28: Pretax Income - Non GAAP | L28: {=_xll.FDSRC("-",$L$14,"FE_TIMESERIES(PTPA,MEAN,2023,2024,FY,'BKRACTMED=1,WIN=0,UNITS=AUTO,DATE=NOW')")} -> - | M28: - | N28: {=_xll.FDSRC("-",$L$14,"FE_TIMESERIES(PTPA,MEAN,2025/1F,2025/4F,FQ,'BKRACTMED=1,WIN=0,UNITS=AUTO,DATE=NOW')")} -> - | O28: - | P28: -29.4 | Q28: -79.5 | R28: =_xll.FDSRC("-",$L$14,"FE_TIMESERIES(PTPA,MEAN,2025,2025,FY,'BKRACTMED=1,WIN=0,UNITS=AUTO,DATE=NOW')") -> -161.2 | S28: {=_xll.FDSRC("-",$L$14,"FE_TIMESERIES(PTPA,MEAN,2026/1F,2026/4F,FQ,'BKRACTMED=1,WIN=0,UNITS=AUTO,DATE=NOW')")} -> -39.1 | T28: -42.6 | U28: -48.7 | V28: -54.6 | W28: {=_xll.FDSRC("-",$L$14,"FE_TIMESERIES(PTPA,MEAN,2026,2027,FY,'BKRACTMED=1,WIN=0,UNITS=AUTO,DATE=NOW')")} -> -185 | X28: -279.1
A29: Net Income - GAAP | B29: {=_xll.FDSRC("-",$B$13,"FE_TIMESERIES(BFNG,MEAN,2024,2030,FY,'BKRACTMED=1,WIN=0,UNITS=AUTO,DATE=NOW')")} -> - | C29: -161.2 | D29: -199.15 | E29: -254.25 | F29: -290.7 | G29: -264.6 | H29: -245.8 | K29: Tax Expense | L29: {=_xll.FDSRC("-",$L$14,"FE_TIMESERIES(TAX_EXPENSE,MEAN,2023,2024,FY,'BKRACTMED=1,WIN=0,UNITS=AUTO,DATE=NOW')")} -> - | M29: - | N29: {=_xll.FDSRC("-",$L$14,"FE_TIMESERIES(TAX_EXPENSE,MEAN,2025/1F,2025/4F,FQ,'BKRACTMED=1,WIN=0,UNITS=AUTO,DATE=NOW')")} -> - | O29: 0 | P29: 0 | Q29: 0 | R29: =_xll.FDSRC("-",$L$14,"FE_TIMESERIES(TAX_EXPENSE,MEAN,2025,2025,FY,'BKRACTMED=1,WIN=0,UNITS=AUTO,DATE=NOW')") -> 0 | S29: {=_xll.FDSRC("-",$L$14,"FE_TIMESERIES(TAX_EXPENSE,MEAN,2026/1F,2026/4F,FQ,'BKRACTMED=1,WIN=0,UNITS=AUTO,DATE=NOW')")} -> 0 | T29: 0 | U29: 0 | V29: 0 | W29: {=_xll.FDSRC("-",$L$14,"FE_TIMESERIES(TAX_EXPENSE,MEAN,2026,2027,FY,'BKRACTMED=1,WIN=0,UNITS=AUTO,DATE=NOW')")} -> 0 | X29: 0
K30: Net Income | L30: {=_xll.FDSRC("-",$L$14,"FE_TIMESERIES(NETPROFIT,MEAN,2023,2024,FY,'BKRACTMED=1,WIN=0,UNITS=AUTO,DATE=NOW')")} -> - | M30: - | N30: {=_xll.FDSRC("-",$L$14,"FE_TIMESERIES(NETPROFIT,MEAN,2025/1F,2025/4F,FQ,'BKRACTMED=1,WIN=0,UNITS=AUTO,DATE=NOW')")} -> - | O30: -27.4 | P30: -29.418 | Q30: -79.548 | R30: =_xll.FDSRC("-",$L$14,"FE_TIMESERIES(NETPROFIT,MEAN,2025,2025,FY,'BKRACTMED=1,WIN=0,UNITS=AUTO,DATE=NOW')") -> -161.152 | S30: {=_xll.FDSRC("-",$L$14,"FE_TIMESERIES(NETPROFIT,MEAN,2026/1F,2026/4F,FQ,'BKRACTMED=1,WIN=0,UNITS=AUTO,DATE=NOW')")} -> -41.575 | T30: -44.175 | U30: -47.3 | V30: -51.15 | W30: {=_xll.FDSRC("-",$L$14,"FE_TIMESERIES(NETPROFIT,MEAN,2026,2027,FY,'BKRACTMED=1,WIN=0,UNITS=AUTO,DATE=NOW')")} -> -186.84521 | X30: -228.53249
K31: Net Income - GAAP | L31: {=_xll.FDSRC("-",$L$14,"FE_TIMESERIES(BFNG,MEAN,2023,2024,FY,'BKRACTMED=1,WIN=0,UNITS=AUTO,DATE=NOW')")} -> - | M31: - | N31: {=_xll.FDSRC("-",$L$14,"FE_TIMESERIES(BFNG,MEAN,2025/1F,2025/4F,FQ,'BKRACTMED=1,WIN=0,UNITS=AUTO,DATE=NOW')")} -> - | O31: - | P31: -29.4 | Q31: -79.5 | R31: =_xll.FDSRC("-",$L$14,"FE_TIMESERIES(BFNG,MEAN,2025,2025,FY,'BKRACTMED=1,WIN=0,UNITS=AUTO,DATE=NOW')") -> -161.2 | S31: {=_xll.FDSRC("-",$L$14,"FE_TIMESERIES(BFNG,MEAN,2026/1F,2026/4F,FQ,'BKRACTMED=1,WIN=0,UNITS=AUTO,DATE=NOW')")} -> -43.95 | T31: -47.25 | U31: -51.75 | V31: -56.2 | W31: {=_xll.FDSRC("-",$L$14,"FE_TIMESERIES(BFNG,MEAN,2026,2027,FY,'BKRACTMED=1,WIN=0,UNITS=AUTO,DATE=NOW')")} -> -199.15 | X31: -254.25
A32: MPLT-US
A33: Balance Sheet (M) | K33: MPLT-US
A34: Ticker | B34: MPLT-US | K34: Balance Sheet (M)
B35: {=_xll.FDSRC("-",$B$34,"PROPER(CONVERT_DATE(FE_TIMESERIES_PERIOD(,2024,2030,FY,'DISPLAY=YYYYMMDD'),""MMM 'YY""))")} -> Dec '24 | C35: Dec '25 | D35: Dec '26 | E35: Dec '27 | F35: Dec '28 | G35: Dec '29 | H35: Dec '30 | K35: Ticker | L35: MPLT-US
A36: Current Assets | B36: {=_xll.FDSRC("-",$B$34,"FE_TIMESERIES(CURRENTASSETS,MEAN,2024,2030,FY,'BKRACTMED=1,WIN=0,UNITS=AUTO,DATE=NOW')")} -> - | C36: 324.7 | D36: 340.3 | E36: 400.75 | F36: 256.65 | G36: 211 | H36: 161.35 | L36: {=_xll.FDSRC("-",$L$35,"PROPER(CONVERT_DATE(FE_TIMESERIES_PERIOD(,2023,2024,FY,'DISPLAY=YYYYMMDD'),""MMM 'YY""))")} -> Dec '23 | M36: Dec '24 | N36: {=_xll.FDSRC("-",$L$35,"PROPER(CONVERT_DATE(FE_TIMESERIES_PERIOD(,2025/1F,2025/4F,FQ,'DISPLAY=YYYYMMDD'),""MMM 'YY""))")} -> Mar '25 | O36: Jun '25 | P36: Sep '25 | Q36: Dec '25 | R36: =_xll.FDSRC("-",$L$35,"PROPER(CONVERT_DATE(FE_TIMESERIES_PERIOD(,2025,2025,FY,'DISPLAY=YYYYMMDD'),""MMM 'YY""))") -> Dec '25 | S36: {=_xll.FDSRC("-",$L$35,"PROPER(CONVERT_DATE(FE_TIMESERIES_PERIOD(,2026/1F,2026/4F,FQ,'DISPLAY=YYYYMMDD'),""MMM 'YY""))")} -> Mar '26 | T36: Jun '26 | U36: Sep '26 | V36: Dec '26 | W36: {=_xll.FDSRC("-",$L$35,"PROPER(CONVERT_DATE(FE_TIMESERIES_PERIOD(,2026,2027,FY,'DISPLAY=YYYYMMDD'),""MMM 'YY""))")} -> Dec '26 | X36: Dec '27
A37: Cash and Cash Equivalents | B37: {=_xll.FDSRC("-",$B$34,"FE_TIMESERIES(CASH_ST,MEAN,2024,2030,FY,'BKRACTMED=1,WIN=0,UNITS=AUTO,DATE=NOW')")} -> - | C37: 453.1 | D37: 392.23334 | E37: 430.15 | F37: 286.05 | G37: 240.5 | H37: 221.15 | L37: {=_xll.FDSRC("-",$L$35,"FE_TIMESERIES_PERIOD(,2023,2024,FY,'')")} -> 2023 | M37: 2024 | N37: {=_xll.FDSRC("-",$L$35,"FE_TIMESERIES_PERIOD(,2025/1F,2025/4F,FQ,'')")} -> 2025/1F | O37: 2025/2F | P37: 2025/3F | Q37: 2025/4F | R37: =_xll.FDSRC("-",$L$35,"FE_TIMESERIES_PERIOD(,2025,2025,FY,'')") -> 2025 | S37: {=_xll.FDSRC("-",$L$35,"FE_TIMESERIES_PERIOD(,2026/1F,2026/4F,FQ,'')")} -> 2026/1F | T37: 2026/2F | U37: 2026/3F | V37: 2026/4F | W37: {=_xll.FDSRC("-",$L$35,"FE_TIMESERIES_PERIOD(,2026,2027,FY,'')")} -> 2026 | X37: 2027
A38: Accounts Receivable | B38: {=_xll.FDSRC("-",$B$34,"FE_TIMESERIES(RECEIV_NET,MEAN,2024,2030,FY,'BKRACTMED=1,WIN=0,UNITS=AUTO,DATE=NOW')")} -> - | C38: 0 | D38: 0 | E38: 0 | F38: 0 | G38: 0 | H38: 2.75 | K38: Current Assets | L38: {=_xll.FDSRC("-",$L$35,"FE_TIMESERIES(CURRENTASSETS,MEAN,2023,2024,FY,'BKRACTMED=1,WIN=0,UNITS=AUTO,DATE=NOW')")} -> - | M38: - | N38: {=_xll.FDSRC("-",$L$35,"FE_TIMESERIES(CURRENTASSETS,MEAN,2025/1F,2025/4F,FQ,'BKRACTMED=1,WIN=0,UNITS=AUTO,DATE=NOW')")} -> - | O38: - | P38: - | Q38: 324.7 | R38: =_xll.FDSRC("-",$L$35,"FE_TIMESERIES(CURRENTASSETS,MEAN,2025,2025,FY,'BKRACTMED=1,WIN=0,UNITS=AUTO,DATE=NOW')") -> 324.7 | S38: {=_xll.FDSRC("-",$L$35,"FE_TIMESERIES(CURRENTASSETS,MEAN,2026/1F,2026/4F,FQ,'BKRACTMED=1,WIN=0,UNITS=AUTO,DATE=NOW')")} -> 277.8 | T38: 228 | U38: 325.2 | V38: 269.3 | W38: {=_xll.FDSRC("-",$L$35,"FE_TIMESERIES(CURRENTASSETS,MEAN,2026,2027,FY,'BKRACTMED=1,WIN=0,UNITS=AUTO,DATE=NOW')")} -> 340.3 | X38: 400.75
A39: Inventories | B39: {=_xll.FDSRC("-",$B$34,"FE_TIMESERIES(INVENTORIES,MEAN,2024,2030,FY,'BKRACTMED=1,WIN=0,UNITS=AUTO,DATE=NOW')")} -> - | C39: 0 | D39: 0 | E39: 0 | F39: 0 | G39: 0 | H39: 0.2 | K39: Cash and Cash Equivalents | L39: {=_xll.FDSRC("-",$L$35,"FE_TIMESERIES(CASH_ST,MEAN,2023,2024,FY,'BKRACTMED=1,WIN=0,UNITS=AUTO,DATE=NOW')")} -> - | M39: - | N39: {=_xll.FDSRC("-",$L$35,"FE_TIMESERIES(CASH_ST,MEAN,2025/1F,2025/4F,FQ,'BKRACTMED=1,WIN=0,UNITS=AUTO,DATE=NOW')")} -> - | O39: - | P39: 227.2 | Q39: 453.1 | R39: =_xll.FDSRC("-",$L$35,"FE_TIMESERIES(CASH_ST,MEAN,2025,2025,FY,'BKRACTMED=1,WIN=0,UNITS=AUTO,DATE=NOW')") -> 453.1 | S39: {=_xll.FDSRC("-",$L$35,"FE_TIMESERIES(CASH_ST,MEAN,2026/1F,2026/4F,FQ,'BKRACTMED=1,WIN=0,UNITS=AUTO,DATE=NOW')")} -> 409.15 | T39: 362.9 | U39: 540.95 | V39: 492.5 | W39: {=_xll.FDSRC("-",$L$35,"FE_TIMESERIES(CASH_ST,MEAN,2026,2027,FY,'BKRACTMED=1,WIN=0,UNITS=AUTO,DATE=NOW')")} -> 392.23334 | X39: 430.15
A40: Current Liabilities | B40: {=_xll.FDSRC("-",$B$34,"FE_TIMESERIES(CURRENTLIABILITIES,MEAN,2024,2030,FY,'BKRACTMED=1,WIN=0,UNITS=AUTO,DATE=NOW')")} -> - | C40: 16.2 | D40: 16.2 | E40: 8.1 | F40: 8.1 | G40: 8.1 | H40: 12.55 | K40: Accounts Receivable | L40: {=_xll.FDSRC("-",$L$35,"FE_TIMESERIES(RECEIV_NET,MEAN,2023,2024,FY,'BKRACTMED=1,WIN=0,UNITS=AUTO,DATE=NOW')")} -> - | M40: - | N40: {=_xll.FDSRC("-",$L$35,"FE_TIMESERIES(RECEIV_NET,MEAN,2025/1F,2025/4F,FQ,'BKRACTMED=1,WIN=0,UNITS=AUTO,DATE=NOW')")} -> - | O40: - | P40: - | Q40: 0 | R40: =_xll.FDSRC("-",$L$35,"FE_TIMESERIES(RECEIV_NET,MEAN,2025,2025,FY,'BKRACTMED=1,WIN=0,UNITS=AUTO,DATE=NOW')") -> 0 | S40: {=_xll.FDSRC("-",$L$35,"FE_TIMESERIES(RECEIV_NET,MEAN,2026/1F,2026/4F,FQ,'BKRACTMED=1,WIN=0,UNITS=AUTO,DATE=NOW')")} -> 0 | T40: 0 | U40: 0 | V40: 0 | W40: {=_xll.FDSRC("-",$L$35,"FE_TIMESERIES(RECEIV_NET,MEAN,2026,2027,FY,'BKRACTMED=1,WIN=0,UNITS=AUTO,DATE=NOW')")} -> 0 | X40: 0
A41: Total Assets | B41: {=_xll.FDSRC("-",$B$34,"FE_TIMESERIES(TOTASSET,MEAN,2024,2030,FY,'BKRACTMED=1,WIN=0,UNITS=AUTO,DATE=NOW')")} -> - | C41: 479.5 | D41: 492.8 | E41: 510.86667 | F41: 310.6 | G41: 320.4 | H41: 243.2 | K41: Inventories | L41: {=_xll.FDSRC("-",$L$35,"FE_TIMESERIES(INVENTORIES,MEAN,2023,2024,FY,'BKRACTMED=1,WIN=0,UNITS=AUTO,DATE=NOW')")} -> - | M41: - | N41: {=_xll.FDSRC("-",$L$35,"FE_TIMESERIES(INVENTORIES,MEAN,2025/1F,2025/4F,FQ,'BKRACTMED=1,WIN=0,UNITS=AUTO,DATE=NOW')")} -> - | O41: - | P41: - | Q41: 0 | R41: =_xll.FDSRC("-",$L$35,"FE_TIMESERIES(INVENTORIES,MEAN,2025,2025,FY,'BKRACTMED=1,WIN=0,UNITS=AUTO,DATE=NOW')") -> 0 | S41: {=_xll.FDSRC("-",$L$35,"FE_TIMESERIES(INVENTORIES,MEAN,2026/1F,2026/4F,FQ,'BKRACTMED=1,WIN=0,UNITS=AUTO,DATE=NOW')")} -> 0 | T41: 0 | U41: 0 | V41: 0 | W41: {=_xll.FDSRC("-",$L$35,"FE_TIMESERIES(INVENTORIES,MEAN,2026,2027,FY,'BKRACTMED=1,WIN=0,UNITS=AUTO,DATE=NOW')")} -> 0 | X41: 0
A42: Net Debt | B42: {=_xll.FDSRC("-",$B$34,"FE_TIMESERIES(NETDEBT,MEAN,2024,2030,FY,'BKRACTMED=1,WIN=0,UNITS=AUTO,DATE=NOW')")} -> - | C42: -453.1 | D42: -438.47427 | E42: -335.03198 | F42: -353.34064 | G42: -266.6 | H42: -260.5 | K42: Current Liabilities | L42: {=_xll.FDSRC("-",$L$35,"FE_TIMESERIES(CURRENTLIABILITIES,MEAN,2023,2024,FY,'BKRACTMED=1,WIN=0,UNITS=AUTO,DATE=NOW')")} -> - | M42: - | N42: {=_xll.FDSRC("-",$L$35,"FE_TIMESERIES(CURRENTLIABILITIES,MEAN,2025/1F,2025/4F,FQ,'BKRACTMED=1,WIN=0,UNITS=AUTO,DATE=NOW')")} -> - | O42: - | P42: - | Q42: 16.2 | R42: =_xll.FDSRC("-",$L$35,"FE_TIMESERIES(CURRENTLIABILITIES,MEAN,2025,2025,FY,'BKRACTMED=1,WIN=0,UNITS=AUTO,DATE=NOW')") -> 16.2 | S42: {=_xll.FDSRC("-",$L$35,"FE_TIMESERIES(CURRENTLIABILITIES,MEAN,2026/1F,2026/4F,FQ,'BKRACTMED=1,WIN=0,UNITS=AUTO,DATE=NOW')")} -> 16.2 | T42: 16.2 | U42: 16.2 | V42: 16.2 | W42: {=_xll.FDSRC("-",$L$35,"FE_TIMESERIES(CURRENTLIABILITIES,MEAN,2026,2027,FY,'BKRACTMED=1,WIN=0,UNITS=AUTO,DATE=NOW')")} -> 16.2 | X42: 8.1
A43: Shareholder Equity | B43: {=_xll.FDSRC("-",$B$34,"FE_TIMESERIES(SHEQUITY,MEAN,2024,2030,FY,'BKRACTMED=1,WIN=0,UNITS=AUTO,DATE=NOW')")} -> - | C43: 458.4 | D43: 474 | E43: 468.25 | F43: 324.65 | G43: 279.55 | H43: 225.35 | K43: Total Assets | L43: {=_xll.FDSRC("-",$L$35,"FE_TIMESERIES(TOTASSET,MEAN,2023,2024,FY,'BKRACTMED=1,WIN=0,UNITS=AUTO,DATE=NOW')")} -> - | M43: - | N43: {=_xll.FDSRC("-",$L$35,"FE_TIMESERIES(TOTASSET,MEAN,2025/1F,2025/4F,FQ,'BKRACTMED=1,WIN=0,UNITS=AUTO,DATE=NOW')")} -> - | O43: 84.1 | P43: - | Q43: 479.5 | R43: =_xll.FDSRC("-",$L$35,"FE_TIMESERIES(TOTASSET,MEAN,2025,2025,FY,'BKRACTMED=1,WIN=0,UNITS=AUTO,DATE=NOW')") -> 479.5 | S43: {=_xll.FDSRC("-",$L$35,"FE_TIMESERIES(TOTASSET,MEAN,2026/1F,2026/4F,FQ,'BKRACTMED=1,WIN=0,UNITS=AUTO,DATE=NOW')")} -> 436.35 | T43: 390 | U43: 511.3 | V43: 456.15 | W43: {=_xll.FDSRC("-",$L$35,"FE_TIMESERIES(TOTASSET,MEAN,2026,2027,FY,'BKRACTMED=1,WIN=0,UNITS=AUTO,DATE=NOW')")} -> 492.8 | X43: 510.86667
K44: Net Debt | L44: {=_xll.FDSRC("-",$L$35,"FE_TIMESERIES(NETDEBT,MEAN,2023,2024,FY,'BKRACTMED=1,WIN=0,UNITS=AUTO,DATE=NOW')")} -> - | M44: - | N44: {=_xll.FDSRC("-",$L$35,"FE_TIMESERIES(NETDEBT,MEAN,2025/1F,2025/4F,FQ,'BKRACTMED=1,WIN=0,UNITS=AUTO,DATE=NOW')")} -> - | O44: - | P44: -227.2 | Q44: -453.1 | R44: =_xll.FDSRC("-",$L$35,"FE_TIMESERIES(NETDEBT,MEAN,2025,2025,FY,'BKRACTMED=1,WIN=0,UNITS=AUTO,DATE=NOW')") -> -453.1 | S44: {=_xll.FDSRC("-",$L$35,"FE_TIMESERIES(NETDEBT,MEAN,2026/1F,2026/4F,FQ,'BKRACTMED=1,WIN=0,UNITS=AUTO,DATE=NOW')")} -> -409.15 | T44: -362.9 | U44: -540.95 | V44: -492.5 | W44: {=_xll.FDSRC("-",$L$35,"FE_TIMESERIES(NETDEBT,MEAN,2026,2027,FY,'BKRACTMED=1,WIN=0,UNITS=AUTO,DATE=NOW')")} -> -438.47427 | X44: -335.03198
K45: Shareholder Equity | L45: {=_xll.FDSRC("-",$L$35,"FE_TIMESERIES(SHEQUITY,MEAN,2023,2024,FY,'BKRACTMED=1,WIN=0,UNITS=AUTO,DATE=NOW')")} -> - | M45: - | N45: {=_xll.FDSRC("-",$L$35,"FE_TIMESERIES(SHEQUITY,MEAN,2025/1F,2025/4F,FQ,'BKRACTMED=1,WIN=0,UNITS=AUTO,DATE=NOW')")} -> - | O45: - | P45: - | Q45: 458.4 | R45: =_xll.FDSRC("-",$L$35,"FE_TIMESERIES(SHEQUITY,MEAN,2025,2025,FY,'BKRACTMED=1,WIN=0,UNITS=AUTO,DATE=NOW')") -> 458.4 | S45: {=_xll.FDSRC("-",$L$35,"FE_TIMESERIES(SHEQUITY,MEAN,2026/1F,2026/4F,FQ,'BKRACTMED=1,WIN=0,UNITS=AUTO,DATE=NOW')")} -> 411.5 | T45: 361.7 | U45: 458.9 | V45: 403 | W45: {=_xll.FDSRC("-",$L$35,"FE_TIMESERIES(SHEQUITY,MEAN,2026,2027,FY,'BKRACTMED=1,WIN=0,UNITS=AUTO,DATE=NOW')")} -> 474 | X45: 468.25

Sheet MARKETING
D2: 2020A | E2: 2021A | F2: 2025A | G2: 2026E | H2: 2027E | I2: 2028E | J2: 2029E | K2: 2030E
C4: Revenues - Needham | D4: =IS!K8 -> 7.871 | E4: =IS!P8 -> 0 | F4: =IS!AE8 -> 0 | G4: =IS!AJ8 -> 0 | H4: =IS!AK8 -> 0 | I4: =IS!AL8 -> 0 | J4: =IS!AM8 -> 16.880566 | K4: =IS!AN8 -> 128.13327
C5: % Growth Rate | E5: =IFERROR(E4/D4-1,"NM") -> -1 | F5: =IFERROR(F4/E4-1,"NM") -> NM | G5: =IFERROR(G4/F4-1,"NM") -> NM | H5: =IFERROR(H4/G4-1,"NM") -> NM | I5: =IFERROR(I4/H4-1,"NM") -> NM | J5: =IFERROR(J4/I4-1,"NM") -> NM | K5: =IFERROR(K4/J4-1,"NM") -> 6.5905793
C6: Consensus | G6: =FactSet!D15 -> 0 | H6: =FactSet!E15 -> 0 | I6: =FactSet!F15 -> 0 | J6: =FactSet!G15 -> 0 | K6: =FactSet!H15 -> 49.1
C7: Needham vs Cons. | G7: =IFERROR(G4/G6-1,"NM") -> NM | H7: =IFERROR(H4/H6-1,"NM") -> NM | I7: =IFERROR(I4/I6-1,"NM") -> NM | J7: =IFERROR(J4/J6-1,"NM") -> NM | K7: =IFERROR(K4/K6-1,"NM") -> 1.609639
C9: EPS - Needham | D9: =IS!K40 -> #REF! | E9: =IS!P40 -> #REF! | F9: =IS!AE40 -> -18.564314 | G9: =IS!AJ40 -> -5.7488229 | H9: =IS!AK40 -> -3.7874766 | I9: =IS!AL40 -> -4.3236371 | J9: =IS!AM40 -> -3.8135413 | K9: =IS!AN40 -> -2.369021
C10: % Growth Rate | E10: =1-E9/D9 -> #REF! | G10: =1-G9/F9 -> 0.69032936 | H10: =1-H9/G9 -> 0.34117355 | I10: =1-I9/H9 -> -0.14156141 | J10: =1-J9/I9 -> 0.1179784 | K10: =1-K9/J9 -> 0.37878712
C11: Consensus | G11: =FactSet!D7 -> -3.946 | H11: =FactSet!E7 -> -4.1 | I11: =FactSet!F7 -> -4.77 | J11: =FactSet!G7 -> -4.56 | K11: =FactSet!H7 -> -4.67
C12: Needham vs Cons. | G12: =IFERROR(1-G9/G11,"NM") -> -0.45687351 | H12: =IFERROR(1-H9/H11,"NM") -> 0.076225228 | I12: =IFERROR(1-I9/I11,"NM") -> 0.093577127 | J12: =IFERROR(1-J9/J11,"NM") -> 0.16369708 | K12: =IFERROR(1-K9/K11,"NM") -> 0.49271499
M16: Needham | N16: Needham | Q16: 52-week | S16: Market | T16: Average | U16: Short | V16: 2025 | W16: 2025 Cash | X16: EV/Sales-
L17: Ticker | M17: Rating | N17: PT | O17: Date | P17: Close | Q17: Low | R17: High | S17: Cap (M) | T17: Volume (k) | U17: Interest | V17: Cash/share | W17: & Equiv. (M) | X17: 2025E
L18: MPLT | M18: Buy | N18: =SOTP!R14 -> 37.175346 | O18: =TODAY()-1 -> 46118 | P18: 12.46 | Q18: =_xll.FactSetLive.RTDFunction.1.FDSLIVE(L18,"RTP_PRICE_LOW_52W") -> 12.24 | R18: =_xll.FactSetLive.RTDFunction.1.FDSLIVE(L18,"RTP_PRICE_HIGH_52W") -> 22.99 | S18: =_xll.FDS(L18,"FREF_MARKET_VALUE_COMPANY(0,0,,,1,0,,""LEGACY"")") -> 883.94865 | T18: =_xll.FDSC("-",L18,"P_VOLUME_AVG(0,-3AM,,,0)")/1000 -> 199.49047 | U18: =_xll.FDS(L18,"OS_SEC_SI_PCTFLT(0D,,D)")% -> 0.11049805 | V18: =W18/IS!AF39 -> 13.877801 | W18: =SOTP!O19 -> 453.096 | X18: =IFERROR('SOTP-FIGURE'!AH46/IS!AE8,"NM") -> NM
Z21: Close-P | AA21: EPS-2025E | AB21: P/E-2025E
Z22: =P18 -> 12.46 | AA22: 2.935 | AB22: =Z22/AA22 -> 4.2453152
AA23: EPS-2021E | AB23: P/E-2021E
AA24: -1.2122453 | AB24: N.A.
Z26: EV current | AA26: Sales-2025E | AB26: EV/Sales-2025E
Z27: 2659.1605 | AA27: =_xll.FDS(L18,"FE_ESTIMATE(SALES,MEAN,ANN,2023,NOW,,,'')") -> #Calc | AB27: =Z27/AA27 -> #VALUE!

Sheet CHANGES
B2: =IS!Q4 -> 1Q22A | C2: =IS!R4 -> 2Q22A | D2: =IS!S4 -> 3Q22A | E2: =IS!T4 -> 4Q22A | F2: =IS!U4 -> 2022A | G2: =IS!V4 -> 1Q23A | H2: =IS!W4 -> 2Q23A | I2: =IS!X4 -> 3Q23A | ... K2: =IS!Z4 -> 2023A | L2: =IS!#REF! -> #REF! | M2: =IS!#REF! -> #REF! | N2: =IS!#REF! -> #REF! | O2: =IS!#REF! -> #REF! | P2: =IS!#REF! -> #REF! | Q2: =IS!AA4 -> 1Q25A | R2: =IS!AB4 -> 2Q25A | S2: =IS!AC4 -> 3Q25A | T2: =IS!AD4 -> 4Q25A | U2: =IS!AE4 -> 2025A | V2: =IS!AJ4 -> 2026E | W2: =IS!AK4 -> 2027E | X2: =IS!AL4 -> 2028E | Y2: =IS!AM4 -> 2029E | Z2: =IS!AN4 -> 2030E
A4: Bezuclastinib - AdvSM
A5: New | K5: =REVENUE!Z9 -> 0 | L5: =REVENUE!AA9 -> 0 | M5: =REVENUE!AB9 -> 0 | N5: =REVENUE!AC9 -> 0 | O5: =REVENUE!AD9 -> 0 | P5: =REVENUE!#REF! -> #REF! | Q5: =REVENUE!AE9 -> 0 | R5: =REVENUE!AF9 -> 0 | S5: =REVENUE!AG9 -> 0 | T5: =REVENUE!AH9 -> 0 | U5: =REVENUE!AI9 -> 0 | V5: =REVENUE!AN9 -> 0 | W5: =REVENUE!AO9 -> 0 | X5: =REVENUE!AP9 -> 0 | Y5: =REVENUE!AQ9 -> 16.880566 | Z5: =REVENUE!AR9 -> 102.80265
A6: Old | K6: 0 | L6: 0 | M6: 0 | N6: 0 | O6: 0 | P6: 0 | Q6: 0 | R6: 0 | S6: 0 | T6: 0 | U6: 0 | V6: 23.971675 | W6: 58.101213 | X6: 105.99927 | Y6: 162.90106 | Z6: 206.43831
A7: Change | K7: =K5-K6 -> 0 | L7: =L5-L6 -> 0 | M7: =M5-M6 -> 0 | N7: =N5-N6 -> 0 | O7: =O5-O6 -> 0 | P7: =P5-P6 -> #REF! | Q7: =Q5-Q6 -> 0 | R7: =R5-R6 -> 0 | ... Z7: =Z5-Z6 -> -103.63566
A10: Bezuclastinib - Non-AdvSM
A11: New | K11: =REVENUE!Z14 -> 0 | L11: =REVENUE!AA14 -> 0 | M11: =REVENUE!AB14 -> 0 | N11: =REVENUE!AC14 -> 0 | O11: =REVENUE!AD14 -> 0 | P11: =REVENUE!#REF! -> #REF! | Q11: =REVENUE!AE14 -> 0 | R11: =REVENUE!AF14 -> 0 | S11: =REVENUE!AG14 -> 0 | T11: =REVENUE!AH14 -> 0 | U11: =REVENUE!AI14 -> 0 | V11: =REVENUE!AN14 -> 0 | W11: =REVENUE!AO14 -> 0 | X11: =REVENUE!AP14 -> 0 | Y11: =REVENUE!AQ14 -> 0 | Z11: =REVENUE!AR14 -> 25.330627
A12: Old | K12: 0 | L12: 0 | M12: 0 | N12: 0 | O12: 0 | P12: 0 | Q12: 0 | R12: 0 | S12: 0 | T12: 0 | U12: 0 | V12: 33.049773 | W12: 172.54628 | X12: 371.67703 | Y12: 464.89185 | Z12: 543.00733
A13: Change | K13: =K11-K12 -> 0 | L13: =L11-L12 -> 0 | M13: =M11-M12 -> 0 | N13: =N11-N12 -> 0 | O13: =O11-O12 -> 0 | P13: =P11-P12 -> #REF! | Q13: =Q11-Q12 -> 0 | R13: =R11-R12 -> 0 | ... Z13: =Z11-Z12 -> -517.6767
A15: Bezuclastinib - GIST
A16: New | K16: =REVENUE!#REF! -> #REF! | L16: =REVENUE!#REF! -> #REF! | M16: =REVENUE!#REF! -> #REF! | N16: =REVENUE!#REF! -> #REF! | O16: =REVENUE!#REF! -> #REF! | P16: =REVENUE!#REF! -> #REF! | Q16: =REVENUE!#REF! -> #REF! | R16: =REVENUE!#REF! -> #REF! | ... Z16: =REVENUE!#REF! -> #REF!
A17: Old | K17: 0 | L17: 0 | M17: 0 | N17: 0 | O17: 0 | P17: 0 | Q17: 0 | R17: 0 | S17: 0 | T17: 0 | U17: 0 | V17: 101.65168 | W17: 223.9196 | X17: 331.46594 | Y17: 463.12836 | Z17: 579.02389
A18: Change | K18: =K16-K17 -> #REF! | L18: =L16-L17 -> #REF! | M18: =M16-M17 -> #REF! | N18: =N16-N17 -> #REF! | O18: =O16-O17 -> #REF! | P18: =P16-P17 -> #REF! | Q18: =Q16-Q17 -> #REF! | R18: =R16-R17 -> #REF! | ... Z18: =Z16-Z17 -> #REF!
A20: Royalties/Collaborations
A21: New | K21: =REVENUE!Z34 -> 0 | L21: =REVENUE!AA34 -> 0 | M21: =REVENUE!AB34 -> 0 | N21: =REVENUE!AC34 -> 0 | O21: =REVENUE!AD34 -> 0 | P21: =REVENUE!#REF! -> #REF! | Q21: =REVENUE!AE34 -> 0 | R21: =REVENUE!AF34 -> 0 | S21: =REVENUE!AG34 -> 0 | T21: =REVENUE!AH34 -> 0 | U21: =REVENUE!AI34 -> 0 | V21: =REVENUE!AN34 -> 0 | W21: =REVENUE!AO34 -> 0 | X21: =REVENUE!AP34 -> 0 | Y21: =REVENUE!AQ34 -> 0 | Z21: =REVENUE!AR34 -> 0
A22: Old | K22: 0 | L22: 0 | M22: 0 | N22: 0 | O22: 0 | P22: 0 | Q22: 0 | R22: 0 | S22: 0 | T22: 0 | U22: 0 | V22: 0 | W22: 11.956466 | X22: 34.610557 | Y22: 62.340257 | Z22: 84.462949
A23: Change | K23: =K21-K22 -> 0 | L23: =L21-L22 -> 0 | M23: =M21-M22 -> 0 | N23: =N21-N22 -> 0 | O23: =O21-O22 -> 0 | P23: =P21-P22 -> #REF! | Q23: =Q21-Q22 -> 0 | R23: =R21-R22 -> 0 | ... Z23: =Z21-Z22 -> -84.462949
A25: Total Revenues
A26: New | B26: =IS!Q8 -> 0 | C26: =IS!R8 -> 0 | D26: =IS!S8 -> 0 | E26: =IS!T8 -> 0 | F26: =IS!U8 -> 0 | G26: =IS!V8 -> 0 | H26: =IS!W8 -> 0 | I26: =IS!X8 -> 0 | ... K26: =IS!Z8 -> #REF! | L26: =IS!#REF! -> #REF! | M26: =IS!#REF! -> #REF! | N26: =IS!#REF! -> #REF! | O26: =IS!#REF! -> #REF! | P26: =IS!#REF! -> #REF! | Q26: =IS!AA8 -> 0 | R26: =IS!AB8 -> 0 | S26: =IS!AC8 -> 0 | T26: =IS!AD8 -> 0 | U26: =IS!AE8 -> 0 | V26: =IS!AJ8 -> 0 | W26: =IS!AK8 -> 0 | X26: =IS!AL8 -> 0 | Y26: =IS!AM8 -> 16.880566 | Z26: =IS!AN8 -> 128.13327
A27: Old | B27: 0 | C27: 0 | D27: 0 | E27: 0 | F27: 0 | G27: 0 | H27: 0 | I27: 0 | J27: 0 | K27: 0 | L27: 0 | M27: 0 | N27: 0 | O27: 0 | P27: 0 | Q27: 0 | R27: 0 | S27: 0 | T27: 0 | U27: 0 | V27: 158.67313 | W27: 466.52356 | X27: 843.7528 | Y27: 1153.2615 | Z27: 1412.9325
A28: Change | B28: =B26-B27 -> 0 | C28: =C26-C27 -> 0 | D28: =D26-D27 -> 0 | E28: =E26-E27 -> 0 | F28: =F26-F27 -> 0 | G28: =G26-G27 -> 0 | H28: =H26-H27 -> 0 | I28: =I26-I27 -> 0 | ... Z28: =Z26-Z27 -> -1284.7992
A30: COGS
A31: New | B31: =IS!Q13 -> 0 | C31: =IS!R13 -> 0 | D31: =IS!S13 -> 0 | E31: =IS!T13 -> 0 | F31: =IS!U13 -> 0 | G31: =IS!V13 -> 0 | H31: =IS!W13 -> 0 | I31: =IS!X13 -> 0 | ... K31: =IS!Z13 -> #REF! | L31: =IS!#REF! -> #REF! | M31: =IS!#REF! -> #REF! | N31: =IS!#REF! -> #REF! | O31: =IS!#REF! -> #REF! | P31: =IS!#REF! -> #REF! | Q31: =IS!AA13 -> 0 | R31: =IS!AB13 -> 0 | S31: =IS!AC13 -> 0 | T31: =IS!AD13 -> 0 | U31: =IS!AE13 -> 0 | V31: =IS!AJ13 -> 0 | W31: =IS!AK13 -> 0 | X31: =IS!AL13 -> 0 | Y31: =IS!AM13 -> 1.2660425 | Z31: =IS!AN13 -> 9.6099956
A32: Old | B32: 0 | C32: 0 | D32: 0 | E32: 0 | F32: 0 | G32: 0 | H32: 0 | I32: 0 | J32: 0 | K32: 0 | L32: 0 | M32: 0 | N32: 0 | O32: 0 | P32: 0 | Q32: 0 | R32: 0 | S32: 0 | T32: 0 | U32: 0 | V32: 11.900485 | W32: 34.092532 | X32: 60.685668 | Y32: 81.819095 | Z32: 99.635214
A33: Change | B33: =B31-B32 -> 0 | C33: =C31-C32 -> 0 | D33: =D31-D32 -> 0 | E33: =E31-E32 -> 0 | F33: =-(F31-F32) -> 0 | G33: =-(G31-G32) -> 0 | H33: =-(H31-H32) -> 0 | I33: =-(I31-I32) -> 0 | J33: =-(J31-J32) -> 0 | K33: =-(K31-K32) -> #REF! | L33: =-(L31-L32) -> #REF! | M33: =-(M31-M32) -> #REF! | ... Z33: =-(Z31-Z32) -> 90.025218
A35: Gross Margins
A36: New | V36: =IS!AJ49 -> NM | W36: =IS!AK49 -> NM | X36: =IS!AL49 -> NM | Y36: =IS!AM49 -> 0.925 | Z36: =IS!AN49 -> 0.925
A37: Old | V37: 0.925 | W37: 0.92692216 | X37: 0.92807648 | Y37: 0.92905417 | Z37: 0.92948339
A38: Change | V38: =V36-V37 -> #VALUE! | W38: =W36-W37 -> #VALUE! | X38: =X36-X37 -> #VALUE! | Y38: =Y36-Y37 -> -0.0040541709 | Z38: =Z36-Z37 -> -0.0044833856
A40: R&D
A41: New | B41: =IS!Q18 -> 25.47 | C41: =IS!R18 -> 29.479 | D41: =IS!S18 -> 29.936 | E41: =IS!T18 -> 36.742 | F41: =IS!U18 -> 121.627 | G41: =IS!V18 -> 36.038 | H41: =IS!W18 -> 38.871 | I41: =IS!X18 -> 50.127 | ... K41: =IS!Z18 -> #REF! | L41: =IS!#REF! -> #REF! | M41: =IS!#REF! -> #REF! | N41: =IS!#REF! -> #REF! | O41: =IS!#REF! -> #REF! | P41: =IS!#REF! -> #REF! | Q41: =IS!AA18 -> 0 | R41: =IS!AB18 -> 0 | S41: =IS!AC18 -> 27.094 | T41: =IS!AD18 -> 64.623 | U41: =IS!AE18 -> 138.349 | V41: =IS!AJ18 -> 159.1 | W41: =IS!AK18 -> 165.373 | X41: =IS!AL18 -> 182.04209 | Y41: =IS!AM18 -> 164.86335 | Z41: =IS!AN18 -> 152.76925
A42: Old | B42: 25.47 | C42: 29.479 | D42: 29.936 | E42: 36.742 | F42: 121.627 | G42: 36.038 | H42: 38.871 | I42: 50.127 | J42: 48.719 | K42: 173.755 | L42: 52.705 | M42: 54.294 | N42: 63.614 | O42: 62.045 | P42: 232.658 | Q42: 63.029 | R42: 62.203 | S42: 68.989 | T42: 60.604709 | U42: 254.82571 | V42: 225.77522 | W42: 211.10047 | X42: 213.77535 | Y42: 193.05861 | Z42: 123.57102
A43: Change | B43: =-(B41-B42) -> 0 | C43: =-(C41-C42) -> 0 | D43: =-(D41-D42) -> 0 | E43: =-(E41-E42) -> 0 | F43: =-(F41-F42) -> 0 | G43: =-(G41-G42) -> 0 | H43: =-(H41-H42) -> 0 | I43: =-(I41-I42) -> 0 | ... Z43: =-(Z41-Z42) -> -29.198235
A45: SG&A
A46: New | B46: =IS!Q16 -> 5.948 | C46: =IS!R16 -> 6.376 | D46: =IS!S16 -> 6.885 | E46: =IS!T16 -> 7.003 | F46: =IS!U16 -> 26.212 | G46: =IS!V16 -> 7.199 | H46: =IS!W16 -> 8.214 | I46: =IS!X16 -> 9.453 | ... K46: =IS!Z16 -> #REF! | L46: =IS!#REF! -> #REF! | M46: =IS!#REF! -> #REF! | N46: =IS!#REF! -> #REF! | O46: =IS!#REF! -> #REF! | P46: =IS!#REF! -> #REF! | Q46: =IS!AA16 -> 0 | R46: =IS!AB16 -> 0 | S46: =IS!AC16 -> 4.404 | T46: =IS!AD16 -> 18.755 | U46: =IS!AE16 -> 30.734 | V46: =IS!AJ16 -> 57.3 | W46: =IS!AK16 -> 59.019 | X46: =IS!AL16 -> 81.646819 | Y46: =IS!AM16 -> 116.54432 | Z46: =IS!AN16 -> 139.94301
A47: Old | B47: 5.948 | C47: 6.376 | D47: 6.885 | E47: 7.003 | F47: 26.212 | G47: 7.199 | H47: 8.214 | I47: 9.453 | J47: 9.508 | K47: 34.375 | L47: 9.699 | M47: 10.093 | N47: 11.8 | O47: 11.689 | P47: 43.281 | Q47: 11.904 | R47: 13.378 | S47: 14.366 | T47: 13.5 | U47: 53.148 | V47: 105.91124 | W47: 188.24098 | X47: 194.76821 | Y47: 200.9579 | Z47: 207.36793
A48: Change | B48: =-(B46-B47) -> 0 | C48: =-(C46-C47) -> 0 | D48: =-(D46-D47) -> 0 | E48: =-(E46-E47) -> 0 | F48: =-(F46-F47) -> 0 | G48: =-(G46-G47) -> 0 | H48: =-(H46-H47) -> 0 | I48: =-(I46-I47) -> 0 | ... Z48: =-(Z46-Z47) -> 67.424919
A50: Operating Profit
A51: New | B51: =IS!Q24 -> -31.418 | C51: =IS!R24 -> -35.855 | D51: =IS!S24 -> -36.821 | E51: =IS!T24 -> -43.745 | F51: =IS!U24 -> -147.839 | G51: =IS!V24 -> -43.237 | H51: =IS!W24 -> -47.085 | I51: =IS!X24 -> -59.58 | ... K51: =IS!Z24 -> #REF! | L51: =IS!#REF! -> #REF! | M51: =IS!#REF! -> #REF! | N51: =IS!#REF! -> #REF! | O51: =IS!#REF! -> #REF! | P51: =IS!#REF! -> #REF! | Q51: =IS!AA24 -> 0 | R51: =IS!AB24 -> 0 | S51: =IS!AC24 -> -31.498 | T51: =IS!AD24 -> -83.378 | U51: =IS!AE24 -> -169.083 | V51: =IS!AJ24 -> -216.4 | W51: =IS!AK24 -> -224.392 | X51: =IS!AL24 -> -263.68891 | Y51: =IS!AM24 -> -265.79314 | Z51: =IS!AN24 -> -174.18899
A52: Old | B52: -31.418 | C52: -35.855 | D52: -36.821 | E52: -43.745 | F52: -147.839 | G52: -43.237 | H52: -47.085 | I52: -59.58 | J52: -58.227 | K52: -208.13 | L52: -62.404 | M52: -64.387 | N52: -75.414 | O52: -73.734 | P52: -275.939 | Q52: -74.933 | R52: -75.581 | S52: -83.355 | T52: -74.104709 | U52: -307.97371 | V52: -184.91381 | W52: 33.089576 | X52: 374.52357 | Y52: 677.42592 | Z52: 982.3583
A53: Change | B53: =B51-B52 -> 0 | C53: =C51-C52 -> 0 | D53: =D51-D52 -> 0 | E53: =E51-E52 -> 0 | F53: =F51-F52 -> 0 | G53: =G51-G52 -> 0 | H53: =H51-H52 -> 0 | I53: =I51-I52 -> 0 | ... Z53: =Z51-Z52 -> -1156.5473
A55: Operating Margin
A56: New | V56: =IS!AJ53 -> NM | W56: =IS!AK53 -> NM | X56: =IS!AL53 -> NM | Y56: =IS!AM53 -> -15.745511 | Z56: =IS!AN53 -> -1.359436
A57: Old | V57: -1.1653757 | W57: 0.070927984 | X57: 0.44387831 | Y57: 0.58740009 | Z57: 0.69526204
A58: Change | V58: =-(V56-V57) -> #VALUE! | W58: =-(W56-W57) -> #VALUE! | X58: =-(X56-X57) -> #VALUE! | Y58: =-(Y56-Y57) -> 16.332911 | Z58: =-(Z56-Z57) -> 2.0546981
A60: EPS
A61: New | B61: =IS!Q40 -> #REF! | C61: =IS!R40 -> #REF! | D61: =IS!S40 -> #REF! | E61: =IS!T40 -> #REF! | F61: =IS!U40 -> #REF! | G61: =IS!V40 -> #REF! | H61: =IS!W40 -> #REF! | I61: =IS!X40 -> #REF! | ... K61: =IS!Z40 -> #REF! | L61: =IS!#REF! -> #REF! | M61: =IS!#REF! -> #REF! | N61: =IS!#REF! -> #REF! | O61: =IS!#REF! -> #REF! | P61: =IS!#REF! -> #REF! | Q61: =IS!AA40 -> 0 | R61: =IS!AB40 -> 0 | S61: =IS!AC40 -> -37.184927 | T61: =IS!AD40 -> -2.4743556 | U61: =IS!AE40 -> -18.564314 | V61: =IS!AJ40 -> -5.7488229 | W61: =IS!AK40 -> -3.7874766 | X61: =IS!AL40 -> -4.3236371 | Y61: =IS!AM40 -> -3.8135413 | Z61: =IS!AN40 -> -2.369021
A62: Old | B62: -0.67915693 | C62: -0.70718268 | D62: -0.50393554 | E62: -0.5620403 | F62: -2.4523154 | G62: -0.54551534 | H62: -0.5896197 | I62: -0.64273648 | J62: -0.62681663 | K62: -2.4154528 | L62: -0.61545499 | M62: -0.59401433 | N62: -0.64116215 | O62: -0.088795096 | P62: -1.9394266 | Q62: -0.5248723 | R62: -0.533033 | S62: -0.49739091 | T62: -0.40768047 | U62: -1.9629767 | V62: -0.8781594 | W62: 0.13190215 | X62: 1.6037933 | Y62: 2.879616 | Z62: 3.9825705
A63: Change | B63: =B61-B62 -> #REF! | C63: =C61-C62 -> #REF! | D63: =D61-D62 -> #REF! | E63: =E61-E62 -> #REF! | F63: =(F61-F62) -> #REF! | G63: =(G61-G62) -> #REF! | H63: =(H61-H62) -> #REF! | I63: =(I61-I62) -> #REF! | J63: =(J61-J62) -> #REF! | K63: =(K61-K62) -> #REF! | L63: =(L61-L62) -> #REF! | M63: =(M61-M62) -> #REF! | ... Z63: =(Z61-Z62) -> -6.3515915
