Workbook
Name ____EPS94: '[1]Quarterly P&L'!$AL$31
Name ____EPS95: '[1]Quarterly P&L'!$AQ$31
Name ___auv01: '[2]Rev Drivers'!$BA$39
Name ___auv02: '[2]Rev Drivers'!$BB$39
Name ___cap01: '[2]Rev Drivers'!$BA$45
Name ___cap02: '[2]Rev Drivers'!$BB$45
Name ___cap03: '[2]Rev Drivers'!$BC$45
Name ___EPS94: '[1]Quarterly P&L'!$AL$31
Name ___EPS95: '[1]Quarterly P&L'!$AQ$31
Name ___ogq101: '[2]Rev Drivers'!$Z$44
Name ___ogq102: '[2]Rev Drivers'!$AD$44
Name ___ogq103: '[2]Rev Drivers'!$AH$44
Name ___ogq201: '[2]Rev Drivers'!$AA$44
Name ___ogq202: '[2]Rev Drivers'!$AE$44
Name ___ogq203: '[2]Rev Drivers'!$AI$44
Name ___ogq301: '[2]Rev Drivers'!$AB$44
Name ___ogq302: '[2]Rev Drivers'!$AF$44
Name ___ogq303: '[2]Rev Drivers'!$AJ$44
Name ___ogq401: '[2]Rev Drivers'!$AC$44
Name ___ogq402: '[2]Rev Drivers'!$AG$44
Name ___ogq403: '[2]Rev Drivers'!$AK$44
Name ___rlq101: '[2]Rev Drivers'!$Z$43
Name ___rlq102: '[2]Rev Drivers'!$AD$43
Name ___rlq103: '[2]Rev Drivers'!$AH$43
Name ___rlq201: '[2]Rev Drivers'!$AA$43
Name ___rlq202: '[2]Rev Drivers'!$AE$43
Name ___rlq203: '[2]Rev Drivers'!$AI$43
Name ___rlq301: '[2]Rev Drivers'!$AB$43
Name ___rlq302: '[2]Rev Drivers'!$AF$43
Name ___rlq303: '[2]Rev Drivers'!$AJ$43
Name ___rlq401: '[2]Rev Drivers'!$AC$43
Name ___rlq402: '[2]Rev Drivers'!$AG$43
Name ___rlq403: '[2]Rev Drivers'!$AK$43
Name __auv01: '[4]Rev Drivers'!$BA$39
Name __auv02: '[4]Rev Drivers'!$BB$39
Name __cap01: '[4]Rev Drivers'!$BA$45
Name __cap02: '[4]Rev Drivers'!$BB$45
Name __cap03: '[4]Rev Drivers'!$BC$45
Name __EPS94: '[1]Quarterly P&L'!$AL$31
Name __EPS95: '[1]Quarterly P&L'!$AQ$31
Name __FDS_UNIQUE_RANGE_ID_GENERATOR_COUNTER: 1
Name __ogq101: '[4]Rev Drivers'!$Z$44
Name __ogq102: '[4]Rev Drivers'!$AD$44
Name __ogq103: '[4]Rev Drivers'!$AH$44
Name __ogq201: '[4]Rev Drivers'!$AA$44
Name __ogq202: '[4]Rev Drivers'!$AE$44
Name __ogq203: '[4]Rev Drivers'!$AI$44
Name __ogq301: '[4]Rev Drivers'!$AB$44
Name __ogq302: '[4]Rev Drivers'!$AF$44
Name __ogq303: '[4]Rev Drivers'!$AJ$44
Name __ogq401: '[4]Rev Drivers'!$AC$44
Name __ogq402: '[4]Rev Drivers'!$AG$44
Name __ogq403: '[4]Rev Drivers'!$AK$44
Name __rev1: [6]Sheet1!$A$8:$G$103
Name __rev2: [6]Sheet1!$A$105:$G$155
Name __rev3: [6]Sheet1!$A$157:$G$197
Name __rlq101: '[4]Rev Drivers'!$Z$43
Name __rlq102: '[4]Rev Drivers'!$AD$43
Name __rlq103: '[4]Rev Drivers'!$AH$43
Name __rlq201: '[4]Rev Drivers'!$AA$43

Sheet __FDSCACHE__
B1: This sheet contains FactSet XML data for use with this workbook's =FDS codes. Modifying the worksheet's contents may damage the workbook's =FDS functionality.

Sheet iQ ML_Model_Summary
A1: Checksheet
A3: Security: | C3: =_xll.NextGen.Functions.XmlPart("urn:NextGen/PropertyType/DocumentMetadata","DocumentMetadata/Instruments/Instrument[@Type='Primary']/@Ticker") -> #NAME? | Q3: Key
Q4: percentage change data
A5: Analyst: | C5: =_xll.IQXL.Functions.iQ(Ticker,"AName") -> #NAME? | Q5: aiQ codes
Q6: aquarterly EPS logic
A7: Company: | C7: =_xll.IQXL.Functions.iQ(Ticker,"CoLongName") -> #NAME? | K7: Investment Opinion: | M7: =_xll.IQXL.Functions.iQ(Ticker,12948) -> #NAME? | Q7: CoLongName | R7: 12948
A8: Industry: | C8: =_xll.IQXL.Functions.iQ(Ticker,"ind") -> #NAME? | K8: Last Fiscal Year End: | M8: =_xll.IQXL.Functions.iQ(Ticker,"FiscalYearEnd") -> #NAME? | Q8: ind | R8: FiscalYearEnd
A9: Country: | C9: =_xll.IQXL.Functions.iQ(Ticker,"loc") -> #NAME? | K9: Price Objective: | M9: =_xll.IQXL.Functions.iQ(Ticker,12764) -> #NAME? | Q9: loc | R9: 12764
A10: Currency: | C10: =_xll.IQXL.Functions.iQ(Ticker,"REPCRNCY") -> #NAME? | K10: Date Established: | M10: =_xll.IQXL.Functions.iQ(Ticker,29013) -> #NAME? | Q10: REPCRNCY | R10: 29013
A11: Cusip: | C11: =_xll.IQXL.Functions.iQ(Ticker,"CUSIP") -> #NAME? | K11: aBase Price: | M11: =_xll.IQXL.Functions.iQ(Ticker,12765) -> #NAME? | Q11: CUSIP | R11: 12765
A12: Sedol: | C12: =_xll.IQXL.Functions.iQ(Ticker,"SEDOL") -> #NAME? | Q12: SEDOL
A14: Price Date: | C14: =_xll.IQXL.Functions.iQ(Ticker,"PriceDate") -> #NAME? | Q14: PriceDate
A15: Price: | C15: =_xll.IQXL.Functions.iQ(Ticker,"nprice") -> #NAME? | Q15: nprice
A16: Data: | C16: =_xll.IQXL.Functions.iQ(Ticker,"statusrelease") -> #NAME? | Q16: statusrelease
C17: Last Year | E17: =C18&D18 -> #NAME? | H17: Current Year | J17: =H18&I18 -> #NAME? | M17: Next Year | O17: =M18&N18 -> #NAME?
C18: =_xll.IQXL.Functions.iQ(Ticker,"year",0) -> #NAME? | D18: =_xll.IQXL.Functions.iQ(Ticker,18134,C18) -> #NAME? | H18: =_xll.IQXL.Functions.iQ(Ticker,"year","+1") -> #NAME? | I18: =_xll.IQXL.Functions.iQ(Ticker,18134,H18) -> #NAME? | M18: =_xll.IQXL.Functions.iQ(Ticker,"year","+2") -> #NAME? | N18: =_xll.IQXL.Functions.iQ(Ticker,18134,M18) -> #NAME?
C19: (model) | D19: iQ | E19: %Δ | H19: (model) | I19: iQ | J19: %Δ | M19: (model) | N19: iQ | O19: %Δ
A23: EPS: | C23: =#REF! -> #REF! | D23: =_xll.IQXL.Functions.iQ(Ticker,$Q$23,C18) -> #NAME? | E23: =IF(ISERROR(R23)=TRUE,"",R23) | H23: =#REF! -> #REF! | I23: =_xll.IQXL.Functions.iQ(Ticker,$Q$23,H18) -> #NAME? | J23: =IF(ISERROR(S23)=TRUE,"",S23) | M23: =#REF! -> #REF! | N23: =_xll.IQXL.Functions.iQ(Ticker,$Q$23,M18) -> #NAME? | O23: =IF(ISERROR(T23)=TRUE,"",T23) | Q23: 12569 | R23: =IF(NOT(AND(ISNUMBER(D23),ISNUMBER(C23))),NA(),(C23/D23-1)) -> #N/A | S23: =IF(NOT(AND(ISNUMBER(I23),ISNUMBER(H23))),NA(),(H23/I23-1)) -> #N/A | T23: =IF(NOT(AND(ISNUMBER(N23),ISNUMBER(M23))),NA(),(M23/N23-1)) -> #N/A
A24: GAAP EPS: | C24: =#REF! -> #REF! | D24: =_xll.IQXL.Functions.iQ(Ticker,12773,C18) -> #NAME? | E24: =IF(ISERROR(R24)=TRUE,"",R24) | H24: =#REF! -> #REF! | I24: =_xll.IQXL.Functions.iQ(Ticker,$Q$24,H18) -> #NAME? | J24: =IF(ISERROR(S24)=TRUE,"",S24) | M24: =#REF! -> #REF! | N24: =_xll.IQXL.Functions.iQ(Ticker,$Q$24,M18) -> #NAME? | O24: =IF(ISERROR(T24)=TRUE,"",T24) | Q24: 12773 | R24: =IF(NOT(AND(ISNUMBER(D24),ISNUMBER(C24))),NA(),(C24/D24-1)) -> #N/A | S24: =IF(NOT(AND(ISNUMBER(I24),ISNUMBER(H24))),NA(),(H24/I24-1)) -> #N/A | T24: =IF(NOT(AND(ISNUMBER(N24),ISNUMBER(M24))),NA(),(M24/N24-1)) -> #N/A
A25: CFPS: | C25: ='BAL-CF'!AK114 -> 0 | D25: =_xll.IQXL.Functions.iQ(Ticker,$Q$25,C18) -> #NAME? | E25: =IF(ISERROR(R25)=TRUE,"",R25) | H25: ='BAL-CF'!AP114 -> 0 | I25: =_xll.IQXL.Functions.iQ(Ticker,$Q$25,H18) -> #NAME? | J25: =IF(ISERROR(S25)=TRUE,"",S25) | M25: ='BAL-CF'!AU114 -> 0 | N25: =_xll.IQXL.Functions.iQ(Ticker,$Q$25,M18) -> #NAME? | O25: =IF(ISERROR(T25)=TRUE,"",T25) | Q25: 12570 | R25: =IF(NOT(AND(ISNUMBER(D25),ISNUMBER(C25))),NA(),(C25/D25-1)) -> #N/A | S25: =IF(NOT(AND(ISNUMBER(I25),ISNUMBER(H25))),NA(),(H25/I25-1)) -> #N/A | T25: =IF(NOT(AND(ISNUMBER(N25),ISNUMBER(M25))),NA(),(M25/N25-1)) -> #N/A
A26: DPS: | C26: 0 | D26: =_xll.IQXL.Functions.iQ(Ticker,$Q$26,C18) -> #NAME? | E26: =IF(ISERROR(R26)=TRUE,"",R26) | H26: 0 | I26: =_xll.IQXL.Functions.iQ(Ticker,$Q$26,H18) -> #NAME? | J26: =IF(ISERROR(S26)=TRUE,"",S26) | M26: 0 | N26: =_xll.IQXL.Functions.iQ(Ticker,$Q$26,M18) -> #NAME? | O26: =IF(ISERROR(T26)=TRUE,"",T26) | Q26: 12571 | R26: =IF(NOT(AND(ISNUMBER(D26),ISNUMBER(C26))),NA(),(C26/D26-1)) -> #N/A | S26: =IF(NOT(AND(ISNUMBER(I26),ISNUMBER(H26))),NA(),(H26/I26-1)) -> #N/A | T26: =IF(NOT(AND(ISNUMBER(N26),ISNUMBER(M26))),NA(),(M26/N26-1)) -> #N/A
F28: Est 5 Year EPS Growth Rate: | I28: =_xll.IQXL.Functions.iQ(Ticker,Q28) -> #NAME? | J28: =IF(ISERROR(R28)=TRUE,"",R28) | Q28: 12612 | R28: =IF(NOT(AND(ISNUMBER(I28),ISNUMBER(H28))),NA(),(H28/I28-1)) -> #N/A
F29: Current Qtr. EPS Est.: | H29: ='QTR-EPS'!AU32 -> 0 | I29: =VLOOKUP("E",S32:T38,2,FALSE) -> #N/A | J29: =IF(ISERROR(R29)=TRUE,"",R29) | R29: =IF(NOT(AND(ISNUMBER(I29),ISNUMBER(H29))),NA(),(H29/I29-1)) -> #N/A
F30: Curr. Qtr. Date: | H30: Q1 | I30: =Q32 -> #NAME?
Q31: Logic | S31: =_xll.IQXL.Functions.iQ(Ticker,"year","+1") -> #NAME? | T31: EPS
Q32: =IF(S32="E",R32,Q34) -> #NAME? | R32: Q1 | S32: =_xll.IQXL.Functions.iQ(Ticker,18134,S$31&$R32) -> #NAME? | T32: =_xll.IQXL.Functions.iQ(Ticker,$Q$23,S$31&$R32) -> #NAME?
Q33: =IF(S33="E",R33,Q34) -> #NAME? | R33: Q2 | S33: =_xll.IQXL.Functions.iQ(Ticker,18134,S$31&$R33) -> #NAME? | T33: =_xll.IQXL.Functions.iQ(Ticker,$Q$23,S$31&$R33) -> #NAME?
Q34: =IF(S34="E",R34,Q35) -> #NAME? | R34: Q2 | S34: =_xll.IQXL.Functions.iQ(Ticker,18134,S$31&$R34) -> #NAME? | T34: =_xll.IQXL.Functions.iQ(Ticker,$Q$23,S$31&$R34) -> #NAME?
Q35: =IF(S35="E",R35,Q36) -> #NAME? | R35: Q3 | S35: =_xll.IQXL.Functions.iQ(Ticker,18134,S$31&$R35) -> #NAME? | T35: =_xll.IQXL.Functions.iQ(Ticker,$Q$23,S$31&$R35) -> #NAME?
Q36: =IF(S36="E",R36,Q38) -> #NAME? | R36: Q4 | S36: =_xll.IQXL.Functions.iQ(Ticker,18134,S$31&$R36) -> #NAME? | T36: =_xll.IQXL.Functions.iQ(Ticker,$Q$23,S$31&$R36) -> #NAME?
S37: =_xll.IQXL.Functions.iQ(Ticker,"year","+2") -> #NAME? | T37: EPS
Q38: =IF(S38="E",R38,"NA") -> #NAME? | R38: Q1 | S38: =_xll.IQXL.Functions.iQ(Ticker,18134,S$37&$R38) -> #NAME? | T38: =_xll.IQXL.Functions.iQ(Ticker,$Q$23,S$37&$R38) -> #NAME?

Sheet Cover
A4: Company Model
B5: US Equity Research
A8: MapLight | H8: MPLT | L8: 46107
A15: Sumant Kulkarni
A16: Analyst
A17: SKulkarni@cgf.com
A18: 212.389.8037
A22: Canaccord Genuity LLC, Member FINRA (CRD# 1020) and SIPC, is a wholly owned subsidiary of Canaccord Genuity Group Inc. (together with its affiliates"Canaccord Group"). The following important disclosures and disclaimers apply to the information presented in the attached model (this "Model") and the provision of this Model by Canaccord Genuity LLC, Canaccord Group, or any of their respective affiliates, officers, directors, or employees (collectively "Canaccord Genuity") and such disclosures and disclaimers should be reviewed carefully. Models are the basis, but not substitutes, for Canaccord Genuity LLC published research reports and do not constitute research reports and should not be relied upon to make an investment decision. Models, including this Model, present a view only as of the date thereof and any opinions estimates and assumptions expressed therein are made as of the date thereof. The information contained may be subject to change or withdrawal without notice or become incorrect due to passage of time or as a result of legal, political, economic, or other changes. This Model may present non-substantive changes from a recently published model. Canaccord Genuity LLC does not assume responsibility to indicate any changes or to furnish an updated Model.
A23: This Model is intended for intended recipients who are institutional investors only and not for retail or private investors and should not be reproduced or redistributed to third parties outside of the intended recipient's organization or republished absent the prior written consent of Canaccord Genuity LLC. Any such reproduction without permission is a violation of Canaccord Genuity's copyright. This Model is provided to such institutional investors, for informational purposes only, and on the basis that any intended recipient is a sophisticated investment professional familiar with its limitations. In providing this model, Canaccord Genuity LLC is not acting as an investment adviser or fiduciary in any respect. The opinions and recommendations herein do not take into account individual client circumstances, objectives or needs and are not intended as recommendations of investment products or other financial products or strategies to particular clients. Securities, investment products, other financial products or strategies discussed herein are not suitable for all investors. The recipient of this report must make its own independent decisions regarding any securities, investment products, other financial products mentioned herein. By making this material available, Canaccord Genuity LLC is not providing investment, legal, regulatory, tax, financial, or accounting advice to the recipient of this model or any other party.
A24: This Model does not constitute an offer or solicitation to buy or sell any securities, investment products or other financial product or services. This Model does not constitute an official confirmation of any transaction. This Model is not an official statement of Canaccord Genuity and opinions expressed in this Model may differ or be contrary to opinions expressed, or actions taken by other business units, of Canaccord Genuity. Sources for the information herein are believed to be reliable, but Canaccord Genuity LLC makes no representation and gives no warranty as to the completeness or accuracy of the information contained herein, except with respect to any disclosures related to Canaccord Genuity and its research analyst's involvement with or interests in a particular issuer. Any forward looking statements incorporated herein are uncertain and may involve risks, assumptions and uncertainties. Past performance is not indicative of future results. Nothing herein shall be relied on as a representation as to future performance. No liability is accepted by Canaccord Genuity for any losses that may arise from any use of or reliance on the information contained herein. Periods beyond our published forecast are scenario analysis for the purpose of supporting our valuation framework predicated on historical trends or guidance but are not studied estimates.
A25: The preparation of this Model is subject to regulation by U.S. law. The distribution of this Model in other jurisdictions may be restricted by law, and persons into whose possession this Model comes should inform themselves about, and observe, any such restrictions. This Model has been prepared exclusively by Canaccord Genuity LLC. Although affiliates of Canaccord Genuity LLC may distribute this document ton a third-party basis, such affiliates do not provide input into its contents.
A26: This Model was last updated on the date noted above and shall constitute an addendum to, and part of, the research report published on that date which contains company-specific disclosures applicable at the time of publication and which may be obtained by visiting:
A27: https://research.canaccordgenuity.com.
A28: All conflict of interest and company-specific disclosures may be obtained at:
A29: https://canaccordgenuity.bluematrix.com/sellside/Disclosures.action
... A32: Copyright © Canaccord Genuity LLC 2026 – Member FINRA/SIPC Copyright © Canaccord Genuity Corp. 2026 – Member CIRO/Canadian Investor Protection Fund Copyright © Canaccord Genuity Limited. 2026 – Member LSE, authorized and regulated by the Financial Conduct Authority Copyright © Canaccord Genuity (Australia) Limited. 2026 – Participant of ASX Group, Cboe Australia and of the NSX. Authorized and regulated by ASIC All rights reserved. All material presented in this document, unless specifically indicated otherwise, is under copyright of Canaccord Group. None of the material, nor its content, nor any copy of it, may be altered in any way, or transmitted to or distributed to any other party, without the prior express written permission of Canaccord Group. Source: Company reports and Canaccord Genuity LLC Please contact your Canaccord Genuity LLC salesperson for a copy of the most recent research report on this company.

Sheet QTR-EPS
BJ1: `
A4: MPLT Quarterly Earnings Model
A6: ($mn) [FY - DEC] | B6: Mar-08A | C6: Jun-08A | D6: Sep-08A | E6: Dec-08A | F6: 2008A | G6: Mar-09A | H6: Jun-09A | I6: Sep-09A | J6: Dec-09A | K6: 2009A | L6: Mar-10A | M6: Jun-10A | N6: Sep-10A | O6: Dec-10A | P6: 2010A | Q6: Mar-11A | R6: Jun-11A | S6: Sep-11A | T6: Dec-11A | U6: 2011A | V6: Mar-12A | W6: Jun-12A | X6: Sep-12A | Y6: Dec-12A | Z6: 2012A | AA6: Mar-13A | AB6: Jun-13A | AC6: Sep-13A | AD6: Dec-13A | AE6: 2013A | AF6: Mar-14A | AG6: Jun-14A | AH6: Sep-14A | AI6: Dec-14A | AJ6: 2014A | AK6: Mar-15A | AL6: Jun-15A | AM6: Sep-15A | AN6: Dec-15A | AO6: 2015A | AP6: Mar-16A | AQ6: Jun-16A | AR6: Sep-16A | AS6: Dec-16A | AT6: 2016A | AU6: Mar-17A | AV6: Jun-17A | AW6: Sep-17A | AX6: Dec-17A | AY6: 2017A | AZ6: Mar-18A | BA6: Jun-18A | BB6: Sep-18A | BC6: Dec-18A | BD6: 2018A | BE6: Mar-19A | BF6: Jun-19A | BG6: Sep-19A | BH6: Dec-19A | BI6: 2019A | BJ6: Mar-20A | BK6: Jun-20A | BL6: Sep-20A | BM6: Dec-20A | BN6: 2020A | BO6: Mar-21A | BP6: Jun-21A | BQ6: Sep-21A | BR6: Dec-21A | BS6: 2021A | BT6: Mar-22A | BU6: Jun-22A | BV6: Sep-22A | BW6: Dec-22A | BX6: 2022A | BY6: Mar-23A | BZ6: Jun-23A | CA6: Sep-23A | CB6: Dec-23A | CC6: 2023A | CD6: Mar-24A | CE6: Jun-24A | CF6: Sep-24A | CG6: Dec-24A | CH6: 2024A | CI6: Mar-25A | CJ6: Jun-25A | CK6: Sep-25A | CL6: Dec-25A | CM6: 2025A | CN6: Mar-26E | CO6: Jun-26E | CP6: Sep-26E | CQ6: Dec-26E | CR6: 2026E | CS6: 2027E | CT6: 2028E | CU6: 2029E | CV6: 2030E | CW6: 2031E | CX6: 2032E | CY6: 2033E | CZ6: 2034E | DA6: 2035E | DB6: 2036E
A8: Revenue | CC8: 0 | CD8: 0 | CE8: 0 | CF8: 0 | CG8: 0 | CH8: 0 | CI8: 0 | CJ8: 0 | CK8: 0 | CL8: 0 | CM8: 0 | CN8: 0 | CO8: 0 | CP8: 0 | CQ8: 0 | CR8: 0 | CS8: 0 | CT8: 0 | CU8: 0 | CV8: 57.31451 | CW8: 374.48993 | CX8: 662.96906 | CY8: 1130.0803 | CZ8: 1958.9362 | DA8: 2876.6971 | DB8: 3716.9758
A9: COGS | CC9: 0 | CD9: 0 | CE9: 0 | CF9: 0 | CG9: 0 | CH9: 0 | CI9: 0 | CJ9: 0 | CK9: 0 | CL9: 0 | CM9: 0 | CN9: 0 | CO9: 0 | CP9: 0 | CQ9: 0 | CR9: 0 | CS9: 0 | CT9: 0 | CU9: 0 | CV9: 3.4388706 | CW9: 22.469396 | CX9: 39.778143 | CY9: 67.804821 | CZ9: 117.53617 | DA9: 172.60182 | DB9: 223.01855
A10: Gross Profit | CC10: 0 | CD10: 0 | CE10: 0 | CF10: 0 | CG10: 0 | CH10: 0 | CI10: 0 | CJ10: 0 | CK10: 0 | CL10: 0 | CM10: 0 | CN10: 0 | CO10: 0 | CP10: 0 | CQ10: 0 | CR10: 0 | CS10: 0 | CT10: 0 | CU10: 0 | CV10: 53.87564 | CW10: 352.02053 | CX10: 623.19091 | CY10: 1062.2755 | CZ10: 1841.4 | DA10: 2704.0952 | DB10: 3493.9572
A12: SG&A | CC12: 7.607 | CD12: 4.1435 | CE12: 4.1435 | CF12: 4.08 | CG12: 2.064 | CH12: 14.423 | CI12: 3.2865 | CJ12: 4.2885 | CK12: 4.404 | CL12: 18.755 | CM12: 30.734 | CN12: 11 | CO12: 12 | CP12: 13 | CQ12: 14 | CR12: 50 | CS12: 55 | CT12: 65 | CU12: 65 | CV12: 200 | CW12: 300 | CX12: 500 | CY12: 515 | CZ12: 530.45 | DA12: 546.3635 | DB12: 562.75441
A13: R&D | CC13: 49.675 | CD13: 15.4945 | CE13: 15.4945 | CF13: 16.814 | CG13: 20.714 | CH13: 68.523 | CI13: 22.3155 | CJ13: 24.3165 | CK13: 27.094 | CL13: 64.623 | CM13: 138.349 | CN13: 38 | CO13: 40 | CP13: 42 | CQ13: 44 | CR13: 164 | CS13: 175 | CT13: 200 | CU13: 200 | CV13: 100 | CW13: 50 | CX13: 50 | CY13: 50 | CZ13: 50 | DA13: 50 | DB13: 50
A14: EBITDA | CC14: -57.282 | CD14: -19.638 | CE14: -19.737 | CF14: -21.62 | CG14: -22.993 | CH14: -83.986 | CI14: -25.602 | CJ14: -28.499 | CK14: -31.826 | CL14: -84.68 | CM14: -170.607 | CN14: -48.9 | CO14: -51.9 | CP14: -54.9 | CQ14: -57.9 | CR14: -213.6 | CS14: -229.5 | CT14: -264 | CU14: -264 | CV14: -245.12436 | CW14: 3.0205348 | CX14: 74.190915 | CY14: 498.27553 | CZ14: 1261.95 | DA14: 2108.7317 | DB14: 2882.2028
A15: Depreciation | CC15: 0 | CD15: 0 | CE15: 0.32 | CF15: 0.187 | CG15: 0.194 | CH15: 0.701 | CI15: 0 | CJ15: 0.302 | CK15: 0.136 | CL15: 0.14 | CM15: 0.578 | CN15: 0.1 | CO15: 0.1 | CP15: 0.1 | CQ15: 0.1 | CR15: 0.4 | CS15: 0.5 | CT15: 1 | CU15: 1 | CV15: 1 | CW15: 1 | CX15: 1 | CY15: 1 | CZ15: 1 | DA15: 1 | DB15: 1
A16: Amortization | CC16: 0 | CD16: 0 | CE16: -0.419 | CF16: -0.913 | CG16: -0.409 | CH16: -1.741 | CI16: 0 | CJ16: -0.196 | CK16: -0.464 | CL16: -1.442 | CM16: -2.102 | CN16: 0 | CO16: 0 | CP16: 0 | CQ16: 0 | CR16: 0 | CS16: 0 | CT16: 0 | CU16: 0 | CV16: 0 | CW16: 0 | CX16: 0 | CY16: 0 | CZ16: 0 | DA16: 0 | DB16: 0
A17: Operating Income | CC17: -57.282 | CD17: -19.638 | CE17: -19.638 | CF17: -20.894 | CG17: -22.778 | CH17: -82.946 | CI17: -25.602 | CJ17: -28.605 | CK17: -31.498 | CL17: -83.378 | CM17: -169.083 | CN17: -49 | CO17: -52 | CP17: -55 | CQ17: -58 | CR17: -214 | CS17: -230 | CT17: -265 | CU17: -265 | CV17: -246.12436 | CW17: 2.0205348 | CX17: 73.190915 | CY17: 497.27553 | CZ17: 1260.95 | DA17: 2107.7317 | DB17: 2881.2028
A19: Interest Income | CC19: 1.099 | CD19: 1.2625 | CE19: 1.2625 | CF19: 1.081 | CG19: 0.899 | CH19: 4.504 | CI19: 0.698 | CJ19: 0.8 | CK19: 1.549 | CL19: 2.471 | CM19: 5.518 | CN19: 0.17605689 | CO19: 0.14584499 | CP19: 0.16062826 | CQ19: 0.17354519 | CR19: 0.65607533 | CS19: 0.58063223 | CT19: 0.47370891 | CU19: 0.35349291 | CV19: 0.28889 | CW19: 0.31654339 | CX19: 0.47072008 | CY19: 1.1867763 | CZ19: 3.1730173 | DA19: 6.6986033 | DB19: 11.738145
A20: Interest Expense | CC20: 0 | CD20: 0 | CE20: 0 | CF20: 0 | CG20: 0 | CH20: 0 | CI20: 0 | CJ20: 0 | CK20: 0 | CL20: 0 | CM20: 0 | CN20: 0 | CO20: 0 | CP20: 0 | CQ20: 0 | CR20: 0 | CS20: 0 | CT20: 0 | CU20: 0 | CV20: 0 | CW20: 0 | CX20: 0 | CY20: 0 | CZ20: 0 | DA20: 0 | DB20: 0
A21: Other | CC21: 0.474 | CD21: -0.2915 | CE21: -0.2915 | CF21: 0.797 | CG21: 0.65 | CH21: 0.862 | CI21: 0.32333333 | CJ21: 0.2 | CK21: 0.531 | CL21: 1.359 | CM21: 2.4133333 | CN21: 0 | CO21: 0 | CP21: 0 | CQ21: 0 | CR21: 0 | CS21: 0 | CT21: 0 | CU21: 0 | CV21: 0 | CW21: 0 | CX21: 0 | CY21: 0 | CZ21: 0 | DA21: 0 | DB21: 0
... A34: Adjusted Net Income | CC34: -55.709 | CD34: -18.667 | CE34: -18.667 | CF34: -19.016 | CG34: -21.229 | CH34: -77.58 | CI34: -24.580667 | CJ34: -27.605 | CK34: -29.418 | CL34: -79.548 | CM34: -161.15167 | CN34: -48.823943 | CO34: -51.854155 | CP34: -54.839372 | CQ34: -57.826455 | CR34: -213.34392 | CS34: -229.41937 | CT34: -264.52629 | CU34: -264.64651 | CV34: -245.83547 | CW34: 2.3370782 | CX34: 69.978553 | CY34: 448.61607 | CZ34: 1074.5046 | DA34: 1670.4 | DB34: 2285.4234
A35: GAAP EPS
A37: YEAR-OVER-YEAR % CHANGE
A38: Revenue | CC38: NM | CD38: NM | CE38: NM | CF38: NM | CG38: NM | CH38: NM | CI38: NM | CJ38: NM | CK38: NM | CL38: NM | CM38: NM | CN38: NM | CO38: NM | CP38: NM | CQ38: NM | CR38: NM | CS38: NM | CT38: NM | CU38: NM | CV38: NM | CW38: 5.5339463 | CX38: 0.77032546 | CY38: 0.7045748 | CZ38: 0.73344858 | DA38: 0.46849964 | DB38: 0.29209843
A39: COGS | CC39: NM | CD39: NM | CE39: NM | CF39: NM | CG39: NM | CH39: NM | CI39: NM | CJ39: NM | CK39: NM | CL39: NM | CM39: NM | CN39: NM | CO39: NM | CP39: NM | CQ39: NM | CR39: NM | CS39: NM | CT39: NM | CU39: NM | CV39: NM | CW39: NM | CX39: NM | CY39: NM | CZ39: NM | DA39: NM | DB39: NM
A40: Gross Profit | CC40: NM | CD40: NM | CE40: NM | CF40: NM | CG40: NM | CH40: NM | CI40: NM | CJ40: NM | CK40: NM | CL40: NM | CM40: NM | CN40: NM | CO40: NM | CP40: NM | CQ40: NM | CR40: NM | CS40: NM | CT40: NM | CU40: NM | CV40: NM | CW40: 5.5339463 | CX40: 0.77032546 | CY40: 0.7045748 | CZ40: 0.73344858 | DA40: 0.46849964 | DB40: 0.29209843
A41: SG&A | CC41: NM | CD41: NM | CE41: NM | CF41: NM | CG41: NM | CH41: 0.89601683 | CI41: -0.20682997 | CJ41: 0.03499457 | CK41: 0.079411765 | CL41: 8.0867248 | CM41: 1.130902 | CN41: 2.3470257 | CO41: 1.7981812 | CP41: 1.9518619 | CQ41: -0.25353239 | CR41: 0.62686276 | CS41: 0.1 | CT41: 0.18181818 | CU41: 0 | CV41: 2.0769231 | CW41: 0.5 | CX41: 0.66666667 | CY41: 0.03 | CZ41: 0.03 | DA41: 0.03 | DB41: 0.03
A42: R&D | CC42: NM | CD42: NM | CE42: NM | CF42: NM | CG42: NM | CH42: 0.37942627 | CI42: 0.44022072 | CJ42: 0.56936332 | CK42: 0.61139527 | CL42: 2.1197741 | CM42: 1.0190155 | CN42: 0.70285228 | CO42: 0.64497358 | CP42: 0.55015871 | CQ42: -0.31912786 | CR42: 0.18540792 | CS42: 0.067073171 | CT42: 0.14285714 | CU42: 0 | CV42: -0.5 | CW42: -0.5 | CX42: 0 | CY42: 0 | CZ42: 0 | DA42: 0 | DB42: 0
A43: EBITDA | CC43: NM | CD43: NM | CE43: NM | CF43: NM | CG43: NM | CH43: NM | CI43: NM | CJ43: NM | CK43: NM | CL43: NM | CM43: NM | CN43: NM | CO43: NM | CP43: NM | CQ43: NM | CR43: NM | CS43: NM | CT43: NM | CU43: NM | CV43: NM | CW43: NM | CX43: NM | CY43: NM | CZ43: 1.5326349 | DA43: 0.67101053 | DB43: 0.36679444
A44: Operating Income | CC44: NM | CD44: NM | CE44: NM | CF44: NM | CG44: NM | CH44: NM | CI44: NM | CJ44: NM | CK44: NM | CL44: NM | CM44: NM | CN44: NM | CO44: NM | CP44: NM | CQ44: NM | CR44: NM | CS44: NM | CT44: NM | CU44: NM | CV44: NM | CW44: NM | CX44: NM | CY44: NM | CZ44: 1.535717 | DA44: 0.67154267 | DB44: 0.36696846
A45: Pre-Tax Income | CC45: NM | CD45: NM | CE45: NM | CF45: NM | CG45: NM | CH45: NM | CI45: NM | CJ45: NM | CK45: NM | CL45: NM | CM45: NM | CN45: NM | CO45: NM | CP45: NM | CQ45: NM | CR45: NM | CS45: NM | CT45: NM | CU45: NM | CV45: NM | CW45: NM | CX45: NM | CY45: NM | CZ45: 1.5360454 | DA45: 0.67264602 | DB45: 0.3681893
A46: Net Income | CC46: NM | CD46: NM | CE46: NM | CF46: NM | CG46: NM | CH46: NM | CI46: NM | CJ46: NM | CK46: NM | CL46: NM | CM46: NM | CN46: NM | CO46: NM | CP46: NM | CQ46: NM | CR46: NM | CS46: NM | CT46: NM | CU46: NM | CV46: NM | CW46: NM | CX46: NM | CY46: NM | CZ46: 1.395154 | DA46: 0.55457689 | DB46: 0.3681893
A47: EPS | CC47: NM | CD47: NM | CE47: NM | CF47: NM | CG47: NM | CH47: NM | CI47: NM | CJ47: NM | CK47: NM | CL47: NM | CM47: NM | CN47: NM | CO47: NM | CP47: NM | CQ47: NM | CR47: NM | CS47: NM | CT47: NM | CU47: NM | CV47: NM | CW47: NM | CX47: NM | CY47: NM | CZ47: 1.379322 | DA47: 0.5443686 | DB47: 0.35926355
A48: GAAP EPS
A50: MARGIN ANALYSIS
A51: Gross Profit | CC51: NM | CD51: NM | CE51: NM | CF51: NM | CG51: NM | CH51: NM | CI51: NM | CJ51: NM | CK51: NM | CL51: NM | CM51: NM | CN51: NM | CO51: NM | CP51: NM | CQ51: NM | CR51: NM | CS51: NM | CT51: NM | CU51: NM | CV51: 0.94 | CW51: 0.94 | CX51: 0.94 | CY51: 0.94 | CZ51: 0.94 | DA51: 0.94 | DB51: 0.94
A52: SG&A | CC52: NM | CD52: NM | CE52: NM | CF52: NM | CG52: NM | CH52: NM | CI52: NM | CJ52: NM | CK52: NM | CL52: NM | CM52: NM | CN52: NM | CO52: NM | CP52: NM | CQ52: NM | CR52: NM | CS52: NM | CT52: NM | CU52: NM | CV52: NM | CW52: 0.80108963 | CX52: 0.75418301 | CY52: 0.45571981 | CZ52: 0.27078473 | DA52: 0.18992737 | DB52: 0.15140115
A53: R&D | CC53: NM | CD53: NM | CE53: NM | CF53: NM | CG53: NM | CH53: NM | CI53: NM | CJ53: NM | CK53: NM | CL53: NM | CM53: NM | CN53: NM | CO53: NM | CP53: NM | CQ53: NM | CR53: NM | CS53: NM | CT53: NM | CU53: NM | CV53: NM | CW53: 0.13351494 | CX53: 0.075418301 | CY53: 0.044244642 | CZ53: 0.025524058 | DA53: 0.017381045 | DB53: 0.013451796
A54: EBITDA | CC54: NM | CD54: NM | CE54: NM | CF54: NM | CG54: NM | CH54: NM | CI54: NM | CJ54: NM | CK54: NM | CL54: NM | CM54: NM | CN54: NM | CO54: NM | CP54: NM | CQ54: NM | CR54: NM | CS54: NM | CT54: NM | CU54: NM | CV54: NM | CW54: 0.0080657303 | CX54: 0.11190705 | CY54: 0.44092044 | CZ54: 0.6442017 | DA54: 0.73303921 | DB54: 0.77541609
A55: Operating Income | CC55: NM | CD55: NM | CE55: NM | CF55: NM | CG55: NM | CH55: NM | CI55: NM | CJ55: NM | CK55: NM | CL55: NM | CM55: NM | CN55: NM | CO55: NM | CP55: NM | CQ55: NM | CR55: NM | CS55: NM | CT55: NM | CU55: NM | CV55: NM | CW55: 0.0053954315 | CX55: 0.11039869 | CY55: 0.44003555 | CZ55: 0.64369121 | DA55: 0.73269159 | DB55: 0.77514705
A56: Pre-Tax Income | CC56: NM | CD56: NM | CE56: NM | CF56: NM | CG56: NM | CH56: NM | CI56: NM | CJ56: NM | CK56: NM | CL56: NM | CM56: NM | CN56: NM | CO56: NM | CP56: NM | CQ56: NM | CR56: NM | CS56: NM | CT56: NM | CU56: NM | CV56: NM | CW56: 0.0062406969 | CX56: 0.11110871 | CY56: 0.44108572 | CZ56: 0.64531098 | DA56: 0.73502016 | DB56: 0.77830504
A57: Net Income | CC57: NM | CD57: NM | CE57: NM | CF57: NM | CG57: NM | CH57: NM | CI57: NM | CJ57: NM | CK57: NM | CL57: NM | CM57: NM | CN57: NM | CO57: NM | CP57: NM | CQ57: NM | CR57: NM | CS57: NM | CT57: NM | CU57: NM | CV57: NM | CW57: 0.0062406969 | CX57: 0.10555327 | CY57: 0.39697715 | CZ57: 0.54851433 | DA57: 0.58066593 | DB57: 0.61486098
A60: Source: Company Reports and Canaccord Genuity

Sheet YR-EPS
A4: MPLT Annual Earnings Model
A6: ($mn) [FY - DEC] | B6: 2008A | C6: 2009A | D6: 2010A | E6: 2011A | F6: 2012A | G6: 2013A | H6: 2014A | I6: 2015A | J6: 2016A | K6: 2017A | L6: 2018A | M6: 2019A | N6: 2020A | O6: 2021A | P6: 2022A | Q6: 2023A | R6: 2024A | S6: 2025A | T6: 2026E | U6: 2027E | V6: 2028E | W6: 2029E | X6: 2030E | Y6: 2031E | Z6: 2032E | AA6: 2033E | AB6: 2034E | AC6: 2035E | AD6: 2036E
A8: Revenue | H8: 0 | I8: 0 | J8: 0 | K8: 0 | L8: 0 | M8: 0 | N8: 0 | O8: 0 | P8: 0 | Q8: 0 | R8: 0 | S8: 0 | T8: 0 | U8: 0 | V8: 0 | W8: 0 | X8: 57.31451 | Y8: 374.48993 | Z8: 662.96906 | AA8: 1130.0803 | AB8: 1958.9362 | AC8: 2876.6971 | AD8: 3716.9758
A9: COGS | H9: 0 | I9: 0 | J9: 0 | K9: 0 | L9: 0 | M9: 0 | N9: 0 | O9: 0 | P9: 0 | Q9: 0 | R9: 0 | S9: 0 | T9: 0 | U9: 0 | V9: 0 | W9: 0 | X9: 3.4388706 | Y9: 22.469396 | Z9: 39.778143 | AA9: 67.804821 | AB9: 117.53617 | AC9: 172.60182 | AD9: 223.01855
A10: Gross Profit | H10: 0 | I10: 0 | J10: 0 | K10: 0 | L10: 0 | M10: 0 | N10: 0 | O10: 0 | P10: 0 | Q10: 0 | R10: 0 | S10: 0 | T10: 0 | U10: 0 | V10: 0 | W10: 0 | X10: 53.87564 | Y10: 352.02053 | Z10: 623.19091 | AA10: 1062.2755 | AB10: 1841.4 | AC10: 2704.0952 | AD10: 3493.9572
A12: SG&A | H12: 0 | I12: 0 | J12: 0 | K12: 0 | L12: 0 | M12: 0 | N12: 0 | O12: 0 | P12: 0 | Q12: 7.607 | R12: 14.423 | S12: 30.734 | T12: 50 | U12: 55 | V12: 65 | W12: 65 | X12: 200 | Y12: 300 | Z12: 500 | AA12: 515 | AB12: 530.45 | AC12: 546.3635 | AD12: 562.75441
A13: R&D | H13: 0 | I13: 0 | J13: 0 | K13: 0 | L13: 0 | M13: 0 | N13: 0 | O13: 0 | P13: 0 | Q13: 49.675 | R13: 68.523 | S13: 138.349 | T13: 164 | U13: 175 | V13: 200 | W13: 200 | X13: 100 | Y13: 50 | Z13: 50 | AA13: 50 | AB13: 50 | AC13: 50 | AD13: 50
A14: EBITDA | H14: 0 | I14: 0 | J14: 0 | K14: 0 | L14: 0 | M14: 0 | N14: 0 | O14: 0 | P14: 0 | Q14: -57.282 | R14: -83.986 | S14: -170.607 | T14: -213.6 | U14: -229.5 | V14: -264 | W14: -264 | X14: -245.12436 | Y14: 3.0205348 | Z14: 74.190915 | AA14: 498.27553 | AB14: 1261.95 | AC14: 2108.7317 | AD14: 2882.2028
A15: Depreciation | H15: 0 | I15: 0 | J15: 0 | K15: 0 | L15: 0 | M15: 0 | N15: 0 | O15: 0 | P15: 0 | Q15: 0 | R15: 0.701 | S15: 0.578 | T15: 0.4 | U15: 0.5 | V15: 1 | W15: 1 | X15: 1 | Y15: 1 | Z15: 1 | AA15: 1 | AB15: 1 | AC15: 1 | AD15: 1
A16: Amortization | H16: 0 | I16: 0 | J16: 0 | K16: 0 | L16: 0 | M16: 0 | N16: 0 | O16: 0 | P16: 0 | Q16: 0 | R16: -1.741 | S16: -2.102 | T16: 0 | U16: 0 | V16: 0 | W16: 0 | X16: 0 | Y16: 0 | Z16: 0 | AA16: 0 | AB16: 0 | AC16: 0 | AD16: 0
A17: Operating Income | H17: 0 | I17: 0 | J17: 0 | K17: 0 | L17: 0 | M17: 0 | N17: 0 | O17: 0 | P17: 0 | Q17: -57.282 | R17: -82.946 | S17: -169.083 | T17: -214 | U17: -230 | V17: -265 | W17: -265 | X17: -246.12436 | Y17: 2.0205348 | Z17: 73.190915 | AA17: 497.27553 | AB17: 1260.95 | AC17: 2107.7317 | AD17: 2881.2028
A19: Interest Income | H19: 0 | I19: 0 | J19: 0 | K19: 0 | L19: 0 | M19: 0 | N19: 0 | O19: 0 | P19: 0 | Q19: 1.099 | R19: 4.504 | S19: 5.518 | T19: 0.65607533 | U19: 0.58063223 | V19: 0.47370891 | W19: 0.35349291 | X19: 0.28889 | Y19: 0.31654339 | Z19: 0.47072008 | AA19: 1.1867763 | AB19: 3.1730173 | AC19: 6.6986033 | AD19: 11.738145
A20: Interest Expense | H20: 0 | I20: 0 | J20: 0 | K20: 0 | L20: 0 | M20: 0 | N20: 0 | O20: 0 | P20: 0 | Q20: 0 | R20: 0 | S20: 0 | T20: 0 | U20: 0 | V20: 0 | W20: 0 | X20: 0 | Y20: 0 | Z20: 0 | AA20: 0 | AB20: 0 | AC20: 0 | AD20: 0
A21: Other | H21: 0 | I21: 0 | J21: 0 | K21: 0 | L21: 0 | M21: 0 | N21: 0 | O21: 0 | P21: 0 | Q21: 0.474 | R21: 0.862 | S21: 2.4133333 | T21: 0 | U21: 0 | V21: 0 | W21: 0 | X21: 0 | Y21: 0 | Z21: 0 | AA21: 0 | AB21: 0 | AC21: 0 | AD21: 0
... A35: GAAP EPS | H35: 0 | I35: 0 | J35: 0 | K35: 0 | L35: 0 | M35: 0 | N35: 0 | O35: 0 | P35: 0 | Q35: 0 | R35: 0 | S35: 0 | T35: 0 | U35: 0 | V35: 0 | W35: 0 | X35: 0 | Y35: 0 | Z35: 0 | AA35: 0 | AB35: 0 | AC35: 0 | AD35: 0
A37: YEAR-OVER-YEAR % CHANGE
A38: Revenue | H38: 0 | I38: 0 | J38: 0 | K38: 0 | L38: 0 | M38: 0 | N38: 0 | O38: 0 | P38: 0 | Q38: 0 | R38: NM | S38: NM | T38: NM | U38: NM | V38: NM | W38: NM | X38: NM | Y38: 5.5339463 | Z38: 0.77032546 | AA38: 0.7045748 | AB38: 0.73344858 | AC38: 0.46849964 | AD38: 0.29209843
A39: COGS | H39: 0 | I39: 0 | J39: 0 | K39: 0 | L39: 0 | M39: 0 | N39: 0 | O39: 0 | P39: 0 | Q39: 0 | R39: NM | S39: NM | T39: NM | U39: NM | V39: NM | W39: NM | X39: NM | Y39: NM | Z39: NM | AA39: NM | AB39: NM | AC39: NM | AD39: NM
A40: Gross Profit | H40: 0 | I40: 0 | J40: 0 | K40: 0 | L40: 0 | M40: 0 | N40: 0 | O40: 0 | P40: 0 | Q40: 0 | R40: NM | S40: NM | T40: NM | U40: NM | V40: NM | W40: NM | X40: NM | Y40: 5.5339463 | Z40: 0.77032546 | AA40: 0.7045748 | AB40: 0.73344858 | AC40: 0.46849964 | AD40: 0.29209843
A41: SG&A | H41: 0 | I41: 0 | J41: 0 | K41: 0 | L41: 0 | M41: 0 | N41: 0 | O41: 0 | P41: 0 | Q41: NM | R41: 0.89601683 | S41: 1.130902 | T41: 0.62686276 | U41: 0.1 | V41: 0.18181818 | W41: 0 | X41: 2.0769231 | Y41: 0.5 | Z41: 0.66666667 | AA41: 0.03 | AB41: 0.03 | AC41: 0.03 | AD41: 0.03
A42: R&D | H42: 0 | I42: 0 | J42: 0 | K42: 0 | L42: 0 | M42: 0 | N42: 0 | O42: 0 | P42: 0 | Q42: NM | R42: 0.37942627 | S42: 1.0190155 | T42: 0.18540792 | U42: 0.067073171 | V42: 0.14285714 | W42: 0 | X42: -0.5 | Y42: -0.5 | Z42: 0 | AA42: 0 | AB42: 0 | AC42: 0 | AD42: 0
A43: EBITDA | H43: 0 | I43: 0 | J43: 0 | K43: 0 | L43: 0 | M43: 0 | N43: 0 | O43: 0 | P43: 0 | Q43: NM | R43: NM | S43: NM | T43: NM | U43: NM | V43: NM | W43: NM | X43: NM | Y43: NM | Z43: NM | AA43: NM | AB43: 1.5326349 | AC43: 0.67101053 | AD43: 0.36679444
A44: Operating Income | H44: 0 | I44: 0 | J44: 0 | K44: 0 | L44: 0 | M44: 0 | N44: 0 | O44: 0 | P44: 0 | Q44: NM | R44: NM | S44: NM | T44: NM | U44: NM | V44: NM | W44: NM | X44: NM | Y44: NM | Z44: NM | AA44: NM | AB44: 1.535717 | AC44: 0.67154267 | AD44: 0.36696846
A45: Pre-Tax Income | H45: 0 | I45: 0 | J45: 0 | K45: 0 | L45: 0 | M45: 0 | N45: 0 | O45: 0 | P45: 0 | Q45: NM | R45: NM | S45: NM | T45: NM | U45: NM | V45: NM | W45: NM | X45: NM | Y45: NM | Z45: NM | AA45: NM | AB45: 1.5360454 | AC45: 0.67264602 | AD45: 0.3681893
A46: Net Income | H46: 0 | I46: 0 | J46: 0 | K46: 0 | L46: 0 | M46: 0 | N46: 0 | O46: 0 | P46: 0 | Q46: NM | R46: NM | S46: NM | T46: NM | U46: NM | V46: NM | W46: NM | X46: NM | Y46: NM | Z46: NM | AA46: NM | AB46: 1.395154 | AC46: 0.55457689 | AD46: 0.3681893
A47: EPS | H47: 0 | I47: 0 | J47: 0 | K47: 0 | L47: 0 | M47: 0 | N47: 0 | O47: 0 | P47: 0 | Q47: NM | R47: NM | S47: NM | T47: NM | U47: NM | V47: NM | W47: NM | X47: NM | Y47: NM | Z47: NM | AA47: NM | AB47: 1.379322 | AC47: 0.5443686 | AD47: 0.35926355
A48: GAAP EPS | H48: 0 | I48: 0 | J48: 0 | K48: 0 | L48: 0 | M48: 0 | N48: 0 | O48: 0 | P48: 0 | Q48: 0 | R48: 0 | S48: 0 | T48: 0 | U48: 0 | V48: 0 | W48: 0 | X48: 0 | Y48: 0 | Z48: 0 | AA48: 0 | AB48: 0 | AC48: 0 | AD48: 0
A50: MARGIN ANALYSIS
A51: Gross Profit | H51: 0 | I51: 0 | J51: 0 | K51: 0 | L51: 0 | M51: 0 | N51: 0 | O51: 0 | P51: 0 | Q51: NM | R51: NM | S51: NM | T51: NM | U51: NM | V51: NM | W51: NM | X51: 0.94 | Y51: 0.94 | Z51: 0.94 | AA51: 0.94 | AB51: 0.94 | AC51: 0.94 | AD51: 0.94
A52: SG&A | H52: 0 | I52: 0 | J52: 0 | K52: 0 | L52: 0 | M52: 0 | N52: 0 | O52: 0 | P52: 0 | Q52: NM | R52: NM | S52: NM | T52: NM | U52: NM | V52: NM | W52: NM | X52: NM | Y52: 0.80108963 | Z52: 0.75418301 | AA52: 0.45571981 | AB52: 0.27078473 | AC52: 0.18992737 | AD52: 0.15140115
A53: R&D | H53: 0 | I53: 0 | J53: 0 | K53: 0 | L53: 0 | M53: 0 | N53: 0 | O53: 0 | P53: 0 | Q53: NM | R53: NM | S53: NM | T53: NM | U53: NM | V53: NM | W53: NM | X53: NM | Y53: 0.13351494 | Z53: 0.075418301 | AA53: 0.044244642 | AB53: 0.025524058 | AC53: 0.017381045 | AD53: 0.013451796
A54: EBITDA | H54: 0 | I54: 0 | J54: 0 | K54: 0 | L54: 0 | M54: 0 | N54: 0 | O54: 0 | P54: 0 | Q54: NM | R54: NM | S54: NM | T54: NM | U54: NM | V54: NM | W54: NM | X54: NM | Y54: 0.0080657303 | Z54: 0.11190705 | AA54: 0.44092044 | AB54: 0.6442017 | AC54: 0.73303921 | AD54: 0.77541609
A55: Operating Income | H55: 0 | I55: 0 | J55: 0 | K55: 0 | L55: 0 | M55: 0 | N55: 0 | O55: 0 | P55: 0 | Q55: NM | R55: NM | S55: NM | T55: NM | U55: NM | V55: NM | W55: NM | X55: NM | Y55: 0.0053954315 | Z55: 0.11039869 | AA55: 0.44003555 | AB55: 0.64369121 | AC55: 0.73269159 | AD55: 0.77514705
A56: Pre-Tax Income | H56: 0 | I56: 0 | J56: 0 | K56: 0 | L56: 0 | M56: 0 | N56: 0 | O56: 0 | P56: 0 | Q56: NM | R56: NM | S56: NM | T56: NM | U56: NM | V56: NM | W56: NM | X56: NM | Y56: 0.0062406969 | Z56: 0.11110871 | AA56: 0.44108572 | AB56: 0.64531098 | AC56: 0.73502016 | AD56: 0.77830504
A57: Net Income | H57: 0 | I57: 0 | J57: 0 | K57: 0 | L57: 0 | M57: 0 | N57: 0 | O57: 0 | P57: 0 | Q57: NM | R57: NM | S57: NM | T57: NM | U57: NM | V57: NM | W57: NM | X57: NM | Y57: 0.0062406969 | Z57: 0.10555327 | AA57: 0.39697715 | AB57: 0.54851433 | AC57: 0.58066593 | AD57: 0.61486098
A60: Source: Company Reports and Canaccord Genuity

Sheet QTR-REV
A4: MPLT Quarterly Revenue and Gross Profit Model
A6: ($mn) [FY - DEC] | B6: Mar-08A | C6: Jun-08A | D6: Sep-08A | E6: Dec-08A | F6: 2008A | G6: Mar-09A | H6: Jun-09A | I6: Sep-09A | J6: Dec-09A | K6: 2009A | L6: Mar-10A | M6: Jun-10A | N6: Sep-10A | O6: Dec-10A | P6: 2010A | Q6: Mar-11A | R6: Jun-11A | S6: Sep-11A | T6: Dec-11A | U6: 2011A | V6: Mar-12A | W6: Jun-12A | X6: Sep-12A | Y6: Dec-12A | Z6: 2012A | AA6: Mar-13A | AB6: Jun-13A | AC6: Sep-13A | AD6: Dec-13A | AE6: 2013A | AF6: Mar-14A | AG6: Jun-14A | AH6: Sep-14A | AI6: Dec-14A | AJ6: 2014A | AK6: Mar-15A | AL6: Jun-15A | AM6: Sep-15A | AN6: Dec-15A | AO6: 2015A | AP6: Mar-16A | AQ6: Jun-16A | AR6: Sep-16A | AS6: Dec-16A | AT6: 2016A | AU6: Mar-17A | AV6: Jun-17A | AW6: Sep-17A | AX6: Dec-17A | AY6: 2017A | AZ6: Mar-18A | BA6: Jun-18A | BB6: Sep-18A | BC6: Dec-18A | BD6: 2018A | BE6: Mar-19A | BF6: Jun-19A | BG6: Sep-19A | BH6: Dec-19A | BI6: 2019A | BJ6: Mar-20A | BK6: Jun-20A | BL6: Sep-20A | BM6: Dec-20A | BN6: 2020A | BO6: Mar-21A | BP6: Jun-21A | BQ6: Sep-21A | BR6: Dec-21A | BS6: 2021A | BT6: Mar-22A | BU6: Jun-22A | BV6: Sep-22A | BW6: Dec-22A | BX6: 2022A | BY6: Mar-23A | BZ6: Jun-23A | CA6: Sep-23A | CB6: Dec-23A | CC6: 2023A | CD6: Mar-24A | CE6: Jun-24A | CF6: Sep-24A | CG6: Dec-24A | CH6: 2024A | CI6: Mar-25A | CJ6: Jun-25A | CK6: Sep-25A | CL6: Dec-25A | CM6: 2025A | CN6: Mar-26E | CO6: Jun-26E | CP6: Sep-26E | CQ6: Dec-26E | CR6: 2026E | CS6: 2027E | CT6: 2028E | CU6: 2029E | CV6: 2030E | CW6: 2031E | CX6: 2032E | CY6: 2033E | CZ6: 2034E | DA6: 2035E | DB6: 2036E
A8: ML-007C-MA - Schizophrenia | CC8: 0 | CD8: 0 | CE8: 0 | CF8: 0 | CG8: 0 | CH8: 0 | CI8: 0 | CJ8: 0 | CK8: 0 | CL8: 0 | CM8: 0 | CN8: 0 | CO8: 0 | CP8: 0 | CQ8: 0 | CR8: 0 | CS8: 0 | CT8: 0 | CU8: 0 | CV8: 57.31451 | CW8: 242.03918 | CX8: 383.29929 | CY8: 539.55764 | CZ8: 712.04747 | DA8: 902.09294 | DB8: 1111.1154
A9: ML-007C-MA - ADP | CC9: 0 | CD9: 0 | CE9: 0 | CF9: 0 | CG9: 0 | CH9: 0 | CI9: 0 | CJ9: 0 | CK9: 0 | CL9: 0 | CM9: 0 | CN9: 0 | CO9: 0 | CP9: 0 | CQ9: 0 | CR9: 0 | CS9: 0 | CT9: 0 | CU9: 0 | CV9: 0 | CW9: 132.45075 | CX9: 279.66977 | CY9: 590.52271 | CZ9: 1246.8887 | DA9: 1974.6041 | DB9: 2605.8604
A10: ML-004 - ASD
A11: Total Product Revenue | CC11: 0 | CD11: 0 | CE11: 0 | CF11: 0 | CG11: 0 | CH11: 0 | CI11: 0 | CJ11: 0 | CK11: 0 | CL11: 0 | CM11: 0 | CN11: 0 | CO11: 0 | CP11: 0 | CQ11: 0 | CR11: 0 | CS11: 0 | CT11: 0 | CU11: 0 | CV11: 57.31451 | CW11: 374.48993 | CX11: 662.96906 | CY11: 1130.0803 | CZ11: 1958.9362 | DA11: 2876.6971 | DB11: 3716.9758
A12: Collaboration revenue | CC12: 0 | CD12: 0 | CE12: 0 | CF12: 0 | CG12: 0 | CH12: 0 | CI12: 0 | CJ12: 0 | CK12: 0 | CL12: 0 | CM12: 0 | CN12: 0 | CO12: 0 | CP12: 0 | CQ12: 0 | CR12: 0 | CS12: 0 | CT12: 0 | CU12: 0 | CV12: 0 | CW12: 0 | CX12: 0 | CY12: 0 | CZ12: 0 | DA12: 0 | DB12: 0
A13: Other | CC13: 0 | CD13: 0 | CE13: 0 | CF13: 0 | CG13: 0 | CH13: 0 | CI13: 0 | CJ13: 0 | CK13: 0 | CL13: 0 | CM13: 0 | CN13: 0 | CO13: 0 | CP13: 0 | CQ13: 0 | CR13: 0 | CS13: 0 | CT13: 0 | CU13: 0 | CV13: 0 | CW13: 0 | CX13: 0 | CY13: 0 | CZ13: 0 | DA13: 0 | DB13: 0
A14: Total Revenue | CC14: 0 | CD14: 0 | CE14: 0 | CF14: 0 | CG14: 0 | CH14: 0 | CI14: 0 | CJ14: 0 | CK14: 0 | CL14: 0 | CM14: 0 | CN14: 0 | CO14: 0 | CP14: 0 | CQ14: 0 | CR14: 0 | CS14: 0 | CT14: 0 | CU14: 0 | CV14: 57.31451 | CW14: 374.48993 | CX14: 662.96906 | CY14: 1130.0803 | CZ14: 1958.9362 | DA14: 2876.6971 | DB14: 3716.9758
A16: YEAR-OVER-YEAR CHANGE
A17: ML-007C-MA - Schizophrenia | CC17: NM | CD17: NM | CE17: NM | CF17: NM | CG17: NM | CH17: NM | CI17: NM | CJ17: NM | CK17: NM | CL17: NM | CM17: NM | CN17: NM | CO17: NM | CP17: NM | CQ17: NM | CR17: NM | CS17: NM | CT17: NM | CU17: NM | CV17: NM | CW17: 3.223 | CX17: 0.583625 | CY17: 0.40766667 | CZ17: 0.3196875 | DA17: 0.2669 | DB17: 0.23170833
A18: ML-007C-MA - ADP | CC18: NM | CD18: NM | CE18: NM | CF18: NM | CG18: NM | CH18: NM | CI18: NM | CJ18: NM | CK18: NM | CL18: NM | CM18: NM | CN18: NM | CO18: NM | CP18: NM | CQ18: NM | CR18: NM | CS18: NM | CT18: NM | CU18: NM | CV18: NM | CW18: NM | CX18: 1.1115 | CY18: 1.1115 | CZ18: 1.1115 | DA18: 0.583625 | DB18: 0.3196875
A19: ML-004 - ASD
A20: Total Product Revenue | CC20: NM | CD20: NM | CE20: NM | CF20: NM | CG20: NM | CH20: NM | CI20: NM | CJ20: NM | CK20: NM | CL20: NM | CM20: NM | CN20: NM | CO20: NM | CP20: NM | CQ20: NM | CR20: NM | CS20: NM | CT20: NM | CU20: NM | CV20: NM | CW20: 5.5339463 | CX20: 0.77032546 | CY20: 0.7045748 | CZ20: 0.73344858 | DA20: 0.46849964 | DB20: 0.29209843
A21: Collaboration revenue | CC21: 0 | CD21: 0 | CE21: 0 | CF21: 0 | CG21: 0 | CH21: 0 | CI21: 0 | CJ21: 0 | CK21: 0 | CL21: 0 | CM21: 0 | CN21: NM | CO21: NM | CP21: NM | CQ21: NM | CR21: NM | CS21: 0 | CT21: 0 | CU21: 0 | CV21: 0 | CW21: 0 | CX21: 0 | CY21: 0 | CZ21: 0 | DA21: 0 | DB21: 0
A22: Other | CC22: 0 | CD22: NM | CE22: NM | CF22: NM | CG22: NM | CH22: 0 | CI22: NM | CJ22: NM | CK22: NM | CL22: NM | CM22: 0 | CN22: NM | CO22: NM | CP22: NM | CQ22: NM | CR22: NM | CS22: 0 | CT22: 0 | CU22: 0 | CV22: 0 | CW22: 0 | CX22: 0 | CY22: 0 | CZ22: 0 | DA22: 0 | DB22: 0
A23: Total Revenue | CC23: 0 | CD23: 0 | CE23: 0 | CF23: 0 | CG23: 0 | CH23: 0 | CI23: 0 | CJ23: 0 | CK23: 0 | CL23: 0 | CM23: 0 | CN23: NM | CO23: NM | CP23: NM | CQ23: NM | CR23: NM | CS23: 0 | CT23: 0 | CU23: 0 | CV23: 0 | CW23: 5.5339463 | CX23: 0.77032546 | CY23: 0.7045748 | CZ23: 0.73344858 | DA23: 0.46849964 | DB23: 0.29209843
A25: % OF TOTAL REVENUE
A26: ML-007C-MA - Schizophrenia | CC26: NM | CD26: NM | CE26: NM | CF26: NM | CG26: NM | CH26: NM | CI26: NM | CJ26: NM | CK26: NM | CL26: NM | CM26: NM | CN26: NM | CO26: NM | CP26: NM | CQ26: NM | CR26: NM | CS26: NM | CT26: NM | CU26: NM | CV26: 1 | CW26: 0.64631692 | CX26: 0.57815563 | CY26: 0.47745068 | CZ26: 0.36348681 | DA26: 0.31358635 | DB26: 0.29892995
A27: ML-007C-MA - ADP | CC27: NM | CD27: NM | CE27: NM | CF27: NM | CG27: NM | CH27: NM | CI27: NM | CJ27: NM | CK27: NM | CL27: NM | CM27: NM | CN27: NM | CO27: NM | CP27: NM | CQ27: NM | CR27: NM | CS27: NM | CT27: NM | CU27: NM | CV27: 0 | CW27: 0.35368308 | CX27: 0.42184437 | CY27: 0.52254932 | CZ27: 0.63651319 | DA27: 0.68641365 | DB27: 0.70107005
A28: ML-004 - ASD
A29: Total Product Revenue | CC29: NM | CD29: NM | CE29: NM | CF29: NM | CG29: NM | CH29: NM | CI29: NM | CJ29: NM | CK29: NM | CL29: NM | CM29: NM | CN29: NM | CO29: NM | CP29: NM | CQ29: NM | CR29: NM | CS29: NM | CT29: NM | CU29: NM | CV29: 1 | CW29: 1 | CX29: 1 | CY29: 1 | CZ29: 1 | DA29: 1 | DB29: 1
A30: Collaboration revenue | CC30: NM | CD30: NM | CE30: NM | CF30: NM | CG30: NM | CH30: NM | CI30: NM | CJ30: NM | CK30: NM | CL30: NM | CM30: NM | CN30: NM | CO30: NM | CP30: NM | CQ30: NM | CR30: NM | CS30: NM | CT30: NM | CU30: NM | CV30: 0 | CW30: 0 | CX30: 0 | CY30: 0 | CZ30: 0 | DA30: 0 | DB30: 0
A31: Other | CC31: NM | CD31: NM | CE31: NM | CF31: NM | CG31: NM | CH31: NM | CI31: NM | CJ31: NM | CK31: NM | CL31: NM | CM31: NM | CN31: NM | CO31: NM | CP31: NM | CQ31: NM | CR31: NM | CS31: NM | CT31: NM | CU31: NM | CV31: 0 | CW31: 0 | CX31: 0 | CY31: 0 | CZ31: 0 | DA31: 0 | DB31: 0
A32: Total Revenue | CC32: NM | CD32: NM | CE32: NM | CF32: NM | CG32: NM | CH32: NM | CI32: NM | CJ32: NM | CK32: NM | CL32: NM | CM32: NM | CN32: NM | CO32: NM | CP32: NM | CQ32: NM | CR32: NM | CS32: NM | CT32: NM | CU32: NM | CV32: 1 | CW32: 1 | CX32: 1 | CY32: 1 | CZ32: 1 | DA32: 1 | DB32: 1
A34: GROSS PROFIT
A35: ML-007C-MA - Schizophrenia | CC35: 0 | CD35: 0 | CE35: 0 | CF35: 0 | CG35: 0 | CH35: 0 | CI35: 0 | CJ35: 0 | CK35: 0 | CL35: 0 | CM35: 0 | CN35: 0 | CO35: 0 | CP35: 0 | CQ35: 0 | CR35: 0 | CS35: 0 | CT35: 0 | CU35: 0 | CV35: 53.87564 | CW35: 227.51683 | CX35: 360.30133 | CY35: 507.18418 | CZ35: 669.32462 | DA35: 847.96736 | DB35: 1044.4485
A36: ML-007C-MA - ADP | CC36: 0 | CD36: 0 | CE36: 0 | CF36: 0 | CG36: 0 | CH36: 0 | CI36: 0 | CJ36: 0 | CK36: 0 | CL36: 0 | CM36: 0 | CN36: 0 | CO36: 0 | CP36: 0 | CQ36: 0 | CR36: 0 | CS36: 0 | CT36: 0 | CU36: 0 | CV36: 0 | CW36: 124.50371 | CX36: 262.88958 | CY36: 555.09135 | CZ36: 1172.0754 | DA36: 1856.1279 | DB36: 2449.5088
A37: ML-004 - ASD
A38: Total Product Revenue | CC38: 0 | CD38: 0 | CE38: 0 | CF38: 0 | CG38: 0 | CH38: 0 | CI38: 0 | CJ38: 0 | CK38: 0 | CL38: 0 | CM38: 0 | CN38: 0 | CO38: 0 | CP38: 0 | CQ38: 0 | CR38: 0 | CS38: 0 | CT38: 0 | CU38: 0 | CV38: 53.87564 | CW38: 352.02053 | CX38: 623.19091 | CY38: 1062.2755 | CZ38: 1841.4 | DA38: 2704.0952 | DB38: 3493.9572
A39: Collaboration revenue | CC39: 0 | CD39: 0 | CE39: 0 | CF39: 0 | CG39: 0 | CH39: 0 | CI39: 0 | CJ39: 0 | CK39: 0 | CL39: 0 | CM39: 0 | CN39: 0 | CO39: 0 | CP39: 0 | CQ39: 0 | CR39: 0 | CS39: 0 | CT39: 0 | CU39: 0 | CV39: 0 | CW39: 0 | CX39: 0 | CY39: 0 | CZ39: 0 | DA39: 0 | DB39: 0
A40: Other | CC40: 0 | CD40: 0 | CE40: 0 | CF40: 0 | CG40: 0 | CH40: 0 | CI40: 0 | CJ40: 0 | CK40: 0 | CL40: 0 | CM40: 0 | CN40: 0 | CO40: 0 | CP40: 0 | CQ40: 0 | CR40: 0 | CS40: 0 | CT40: 0 | CU40: 0 | CV40: 0 | CW40: 0 | CX40: 0 | CY40: 0 | CZ40: 0 | DA40: 0 | DB40: 0
A41: Total Revenue | CC41: 0 | CD41: 0 | CE41: 0 | CF41: 0 | CG41: 0 | CH41: 0 | CI41: 0 | CJ41: 0 | CK41: 0 | CL41: 0 | CM41: 0 | CN41: 0 | CO41: 0 | CP41: 0 | CQ41: 0 | CR41: 0 | CS41: 0 | CT41: 0 | CU41: 0 | CV41: 53.87564 | CW41: 352.02053 | CX41: 623.19091 | CY41: 1062.2755 | CZ41: 1841.4 | DA41: 2704.0952 | DB41: 3493.9572
A43: GROSS MARGIN
A44: ML-007C-MA - Schizophrenia | CC44: 0 | CD44: 0 | CE44: 0 | CF44: 0 | CG44: 0 | CH44: 0 | CI44: 0 | CJ44: 0 | CK44: 0 | CL44: 0 | CM44: 0 | CN44: 0 | CO44: 0 | CP44: 0 | CQ44: 0 | CR44: 0 | CS44: 0 | CT44: 0 | CU44: 0 | CV44: 0.94 | CW44: 0.94 | CX44: 0.94 | CY44: 0.94 | CZ44: 0.94 | DA44: 0.94 | DB44: 0.94
A45: ML-007C-MA - ADP | CC45: 0 | CD45: 0 | CE45: 0 | CF45: 0 | CG45: 0 | CH45: 0 | CI45: 0 | CJ45: 0 | CK45: 0 | CL45: 0 | CM45: 0 | CN45: 0 | CO45: 0 | CP45: 0 | CQ45: 0 | CR45: 0 | CS45: 0 | CT45: 0 | CU45: 0 | CV45: 0 | CW45: 0.94 | CX45: 0.94 | CY45: 0.94 | CZ45: 0.94 | DA45: 0.94 | DB45: 0.94
A46: ML-004 - ASD
A47: Total Product Revenue | CC47: 0 | CD47: 0 | CE47: 0 | CF47: 0 | CG47: 0 | CH47: 0 | CI47: 0 | CJ47: 0 | CK47: 0 | CL47: 0 | CM47: 0 | CN47: 0 | CO47: 0 | CP47: 0 | CQ47: 0 | CR47: 0 | CS47: 0 | CT47: 0 | CU47: 0 | CV47: 0.94 | CW47: 0.94 | CX47: 0.94 | CY47: 0.94 | CZ47: 0.94 | DA47: 0.94 | DB47: 0.94
A48: Collaboration revenue | CC48: 0 | CD48: 0 | CE48: 0 | CF48: 0 | CG48: 0 | CH48: 0 | CI48: 0 | CJ48: 0 | CK48: 0 | CL48: 0 | CM48: 0 | CN48: 0 | CO48: 0 | CP48: 0 | CQ48: 0 | CR48: 0 | CS48: 0 | CT48: 0 | CU48: 0 | CV48: 0 | CW48: 0 | CX48: 0 | CY48: 0 | CZ48: 0 | DA48: 0 | DB48: 0
A49: Other | CC49: 0 | CD49: 0 | CE49: 0 | CF49: 0 | CG49: 0 | CH49: 0 | CI49: 0 | CJ49: 0 | CK49: 0 | CL49: 0 | CM49: 0 | CN49: 0 | CO49: 0 | CP49: 0 | CQ49: 0 | CR49: 0 | CS49: 0 | CT49: 0 | CU49: 0 | CV49: 0 | CW49: 0 | CX49: 0 | CY49: 0 | CZ49: 0 | DA49: 0 | DB49: 0
A50: Total Revenue | CC50: NM | CD50: NM | CE50: NM | CF50: NM | CG50: NM | CH50: NM | CI50: NM | CJ50: NM | CK50: NM | CL50: NM | CM50: NM | CN50: NM | CO50: NM | CP50: NM | CQ50: NM | CR50: NM | CS50: NM | CT50: NM | CU50: NM | CV50: 0.94 | CW50: 0.94 | CX50: 0.94 | CY50: 0.94 | CZ50: 0.94 | DA50: 0.94 | DB50: 0.94
A52: Source: Company Reports and Canaccord Genuity

Sheet YR-REV
A4: MPLT Annual Revenue and Gross Profit Model
A6: ($mn) [FY - DEC] | B6: 2008A | C6: 2009A | D6: 2010A | E6: 2011A | F6: 2012A | G6: 2013A | H6: 2014A | I6: 2015A | J6: 2016A | K6: 2017A | L6: 2018A | M6: 2019A | N6: 2020A | O6: 2021A | P6: 2022A | Q6: 2023A | R6: 2024A | S6: 2025A | T6: 2026E | U6: 2027E | V6: 2028E | W6: 2029E | X6: 2030E | Y6: 2031E | Z6: 2032E | AA6: 2033E | AB6: 2034E | AC6: 2035E | AD6: 2036E
A8: ML-007C-MA - Schizophrenia | H8: 0 | I8: 0 | J8: 0 | K8: 0 | L8: 0 | M8: 0 | N8: 0 | O8: 0 | P8: 0 | Q8: 0 | R8: 0 | S8: 0 | T8: 0 | U8: 0 | V8: 0 | W8: 0 | X8: 57.31451 | Y8: 242.03918 | Z8: 383.29929 | AA8: 539.55764 | AB8: 712.04747 | AC8: 902.09294 | AD8: 1111.1154
A9: ML-007C-MA - ADP | H9: 0 | I9: 0 | J9: 0 | K9: 0 | L9: 0 | M9: 0 | N9: 0 | O9: 0 | P9: 0 | Q9: 0 | R9: 0 | S9: 0 | T9: 0 | U9: 0 | V9: 0 | W9: 0 | X9: 0 | Y9: 132.45075 | Z9: 279.66977 | AA9: 590.52271 | AB9: 1246.8887 | AC9: 1974.6041 | AD9: 2605.8604
A10: ML-004 - ASD | H10: 0 | I10: 0 | J10: 0 | K10: 0 | L10: 0 | M10: 0 | N10: 0 | O10: 0 | P10: 0
A11: Total Product Revenue | H11: 0 | I11: 0 | J11: 0 | K11: 0 | L11: 0 | M11: 0 | N11: 0 | O11: 0 | P11: 0 | Q11: 0 | R11: 0 | S11: 0 | T11: 0 | U11: 0 | V11: 0 | W11: 0 | X11: 57.31451 | Y11: 374.48993 | Z11: 662.96906 | AA11: 1130.0803 | AB11: 1958.9362 | AC11: 2876.6971 | AD11: 3716.9758
A12: Collaboration revenue | H12: 0 | I12: 0 | J12: 0 | K12: 0 | L12: 0 | M12: 0 | N12: 0 | O12: 0 | P12: 0 | Q12: 0 | R12: 0 | S12: 0 | T12: 0 | U12: 0 | V12: 0 | W12: 0 | X12: 0 | Y12: 0 | Z12: 0 | AA12: 0 | AB12: 0 | AC12: 0 | AD12: 0
A13: Other | H13: 0 | I13: 0 | J13: 0 | K13: 0 | L13: 0 | M13: 0 | N13: 0 | O13: 0 | P13: 0 | Q13: 0 | R13: 0 | S13: 0 | T13: 0 | U13: 0 | V13: 0 | W13: 0 | X13: 0 | Y13: 0 | Z13: 0 | AA13: 0 | AB13: 0 | AC13: 0 | AD13: 0
A14: Total Revenue | H14: 0 | I14: 0 | J14: 0 | K14: 0 | L14: 0 | M14: 0 | N14: 0 | O14: 0 | P14: 0 | Q14: 0 | R14: 0 | S14: 0 | T14: 0 | U14: 0 | V14: 0 | W14: 0 | X14: 57.31451 | Y14: 374.48993 | Z14: 662.96906 | AA14: 1130.0803 | AB14: 1958.9362 | AC14: 2876.6971 | AD14: 3716.9758
A16: YEAR-OVER-YEAR CHANGE
A17: ML-007C-MA - Schizophrenia | H17: 0 | I17: 0 | J17: 0 | K17: 0 | L17: 0 | M17: 0 | N17: 0 | O17: 0 | P17: 0 | Q17: NM | R17: NM | S17: NM | T17: NM | U17: NM | V17: NM | W17: NM | X17: NM | Y17: 3.223 | Z17: 0.583625 | AA17: 0.40766667 | AB17: 0.3196875 | AC17: 0.2669 | AD17: 0.23170833
A18: ML-007C-MA - ADP | H18: 0 | I18: 0 | J18: 0 | K18: 0 | L18: 0 | M18: 0 | N18: 0 | O18: 0 | P18: 0 | Q18: NM | R18: NM | S18: NM | T18: NM | U18: NM | V18: NM | W18: NM | X18: NM | Y18: NM | Z18: 1.1115 | AA18: 1.1115 | AB18: 1.1115 | AC18: 0.583625 | AD18: 0.3196875
A19: ML-004 - ASD | H19: 0 | I19: 0 | J19: 0 | K19: 0 | L19: 0 | M19: 0 | N19: 0 | O19: 0 | P19: 0
A20: Total Product Revenue | H20: 0 | I20: 0 | J20: 0 | K20: 0 | L20: 0 | M20: 0 | N20: 0 | O20: 0 | P20: 0 | Q20: NM | R20: NM | S20: NM | T20: NM | U20: NM | V20: NM | W20: NM | X20: NM | Y20: 5.5339463 | Z20: 0.77032546 | AA20: 0.7045748 | AB20: 0.73344858 | AC20: 0.46849964 | AD20: 0.29209843
A21: Collaboration revenue | H21: 0 | I21: 0 | J21: 0 | K21: 0 | L21: 0 | M21: 0 | N21: 0 | O21: 0 | P21: 0 | Q21: 0 | R21: 0 | S21: 0 | T21: NM | U21: 0 | V21: 0 | W21: 0 | X21: 0 | Y21: 0 | Z21: 0 | AA21: 0 | AB21: 0 | AC21: 0 | AD21: 0
A22: Other | H22: 0 | I22: 0 | J22: 0 | K22: 0 | L22: 0 | M22: 0 | N22: 0 | O22: 0 | P22: 0 | Q22: 0 | R22: 0 | S22: 0 | T22: NM | U22: 0 | V22: 0 | W22: 0 | X22: 0 | Y22: 0 | Z22: 0 | AA22: 0 | AB22: 0 | AC22: 0 | AD22: 0
A23: Total Revenue | H23: 0 | I23: 0 | J23: 0 | K23: 0 | L23: 0 | M23: 0 | N23: 0 | O23: 0 | P23: 0 | Q23: 0 | R23: 0 | S23: 0 | T23: NM | U23: 0 | V23: 0 | W23: 0 | X23: 0 | Y23: 5.5339463 | Z23: 0.77032546 | AA23: 0.7045748 | AB23: 0.73344858 | AC23: 0.46849964 | AD23: 0.29209843
A25: % OF TOTAL REVENUE
A26: ML-007C-MA - Schizophrenia | H26: 0 | I26: 0 | J26: 0 | K26: 0 | L26: 0 | M26: 0 | N26: 0 | O26: 0 | P26: 0 | Q26: NM | R26: NM | S26: NM | T26: NM | U26: NM | V26: NM | W26: NM | X26: 1 | Y26: 0.64631692 | Z26: 0.57815563 | AA26: 0.47745068 | AB26: 0.36348681 | AC26: 0.31358635 | AD26: 0.29892995
A27: ML-007C-MA - ADP | H27: 0 | I27: 0 | J27: 0 | K27: 0 | L27: 0 | M27: 0 | N27: 0 | O27: 0 | P27: 0 | Q27: NM | R27: NM | S27: NM | T27: NM | U27: NM | V27: NM | W27: NM | X27: 0 | Y27: 0.35368308 | Z27: 0.42184437 | AA27: 0.52254932 | AB27: 0.63651319 | AC27: 0.68641365 | AD27: 0.70107005
A28: ML-004 - ASD | H28: 0 | I28: 0 | J28: 0 | K28: 0 | L28: 0 | M28: 0 | N28: 0 | O28: 0 | P28: 0
A29: Total Product Revenue | H29: 0 | I29: 0 | J29: 0 | K29: 0 | L29: 0 | M29: 0 | N29: 0 | O29: 0 | P29: 0 | Q29: NM | R29: NM | S29: NM | T29: NM | U29: NM | V29: NM | W29: NM | X29: 1 | Y29: 1 | Z29: 1 | AA29: 1 | AB29: 1 | AC29: 1 | AD29: 1
A30: Collaboration revenue | H30: 0 | I30: 0 | J30: 0 | K30: 0 | L30: 0 | M30: 0 | N30: 0 | O30: 0 | P30: 0 | Q30: NM | R30: NM | S30: NM | T30: NM | U30: NM | V30: NM | W30: NM | X30: 0 | Y30: 0 | Z30: 0 | AA30: 0 | AB30: 0 | AC30: 0 | AD30: 0
A31: Other | H31: 0 | I31: 0 | J31: 0 | K31: 0 | L31: 0 | M31: 0 | N31: 0 | O31: 0 | P31: 0 | Q31: NM | R31: NM | S31: NM | T31: NM | U31: NM | V31: NM | W31: NM | X31: 0 | Y31: 0 | Z31: 0 | AA31: 0 | AB31: 0 | AC31: 0 | AD31: 0
A32: Total Revenue | H32: 0 | I32: 0 | J32: 0 | K32: 0 | L32: 0 | M32: 0 | N32: 0 | O32: 0 | P32: 0 | Q32: NM | R32: NM | S32: NM | T32: NM | U32: NM | V32: NM | W32: NM | X32: 1 | Y32: 1 | Z32: 1 | AA32: 1 | AB32: 1 | AC32: 1 | AD32: 1
A34: GROSS PROFIT
A35: ML-007C-MA - Schizophrenia | H35: 0 | I35: 0 | J35: 0 | K35: 0 | L35: 0 | M35: 0 | N35: 0 | O35: 0 | P35: 0 | Q35: 0 | R35: 0 | S35: 0 | T35: 0 | U35: 0 | V35: 0 | W35: 0 | X35: 53.87564 | Y35: 227.51683 | Z35: 360.30133 | AA35: 507.18418 | AB35: 669.32462 | AC35: 847.96736 | AD35: 1044.4485
A36: ML-007C-MA - ADP | H36: 0 | I36: 0 | J36: 0 | K36: 0 | L36: 0 | M36: 0 | N36: 0 | O36: 0 | P36: 0 | Q36: 0 | R36: 0 | S36: 0 | T36: 0 | U36: 0 | V36: 0 | W36: 0 | X36: 0 | Y36: 124.50371 | Z36: 262.88958 | AA36: 555.09135 | AB36: 1172.0754 | AC36: 1856.1279 | AD36: 2449.5088
A37: ML-004 - ASD | H37: 0 | I37: 0 | J37: 0 | K37: 0 | L37: 0 | M37: 0 | N37: 0 | O37: 0 | P37: 0
A38: Total Product Revenue | H38: 0 | I38: 0 | J38: 0 | K38: 0 | L38: 0 | M38: 0 | N38: 0 | O38: 0 | P38: 0 | Q38: 0 | R38: 0 | S38: 0 | T38: 0 | U38: 0 | V38: 0 | W38: 0 | X38: 53.87564 | Y38: 352.02053 | Z38: 623.19091 | AA38: 1062.2755 | AB38: 1841.4 | AC38: 2704.0952 | AD38: 3493.9572
A39: Collaboration revenue | H39: 0 | I39: 0 | J39: 0 | K39: 0 | L39: 0 | M39: 0 | N39: 0 | O39: 0 | P39: 0 | Q39: 0 | R39: 0 | S39: 0 | T39: 0 | U39: 0 | V39: 0 | W39: 0 | X39: 0 | Y39: 0 | Z39: 0 | AA39: 0 | AB39: 0 | AC39: 0 | AD39: 0
A40: Other | H40: 0 | I40: 0 | J40: 0 | K40: 0 | L40: 0 | M40: 0 | N40: 0 | O40: 0 | P40: 0 | Q40: 0 | R40: 0 | S40: 0 | T40: 0 | U40: 0 | V40: 0 | W40: 0 | X40: 0 | Y40: 0 | Z40: 0 | AA40: 0 | AB40: 0 | AC40: 0 | AD40: 0
A41: Total Revenue | H41: 0 | I41: 0 | J41: 0 | K41: 0 | L41: 0 | M41: 0 | N41: 0 | O41: 0 | P41: 0 | Q41: 0 | R41: 0 | S41: 0 | T41: 0 | U41: 0 | V41: 0 | W41: 0 | X41: 53.87564 | Y41: 352.02053 | Z41: 623.19091 | AA41: 1062.2755 | AB41: 1841.4 | AC41: 2704.0952 | AD41: 3493.9572
A43: GROSS MARGIN
A44: ML-007C-MA - Schizophrenia | H44: 0 | I44: 0 | J44: 0 | K44: 0 | L44: 0 | M44: 0 | N44: 0 | O44: 0 | P44: 0 | Q44: 0 | R44: 0 | S44: 0 | T44: 0 | U44: 0 | V44: 0 | W44: 0 | X44: 0.94 | Y44: 0.94 | Z44: 0.94 | AA44: 0.94 | AB44: 0.94 | AC44: 0.94 | AD44: 0.94
A45: ML-007C-MA - ADP | H45: 0 | I45: 0 | J45: 0 | K45: 0 | L45: 0 | M45: 0 | N45: 0 | O45: 0 | P45: 0 | Q45: 0 | R45: 0 | S45: 0 | T45: 0 | U45: 0 | V45: 0 | W45: 0 | X45: 0 | Y45: 0.94 | Z45: 0.94 | AA45: 0.94 | AB45: 0.94 | AC45: 0.94 | AD45: 0.94
A46: ML-004 - ASD | H46: 0 | I46: 0 | J46: 0 | K46: 0 | L46: 0 | M46: 0 | N46: 0 | O46: 0 | P46: 0
A47: Total Product Revenue | H47: 0 | I47: 0 | J47: 0 | K47: 0 | L47: 0 | M47: 0 | N47: 0 | O47: 0 | P47: 0 | Q47: 0 | R47: 0 | S47: 0 | T47: 0 | U47: 0 | V47: 0 | W47: 0 | X47: 0.94 | Y47: 0.94 | Z47: 0.94 | AA47: 0.94 | AB47: 0.94 | AC47: 0.94 | AD47: 0.94
A48: Collaboration revenue | H48: 0 | I48: 0 | J48: 0 | K48: 0 | L48: 0 | M48: 0 | N48: 0 | O48: 0 | P48: 0 | Q48: 0 | R48: 0 | S48: 0 | T48: 0 | U48: 0 | V48: 0 | W48: 0 | X48: 0 | Y48: 0 | Z48: 0 | AA48: 0 | AB48: 0 | AC48: 0 | AD48: 0
A49: Other | H49: 0 | I49: 0 | J49: 0 | K49: 0 | L49: 0 | M49: 0 | N49: 0 | O49: 0 | P49: 0 | Q49: 0 | R49: 0 | S49: 0 | T49: 0 | U49: 0 | V49: 0 | W49: 0 | X49: 0 | Y49: 0 | Z49: 0 | AA49: 0 | AB49: 0 | AC49: 0 | AD49: 0
A50: Total Revenue | H50: 0 | I50: 0 | J50: 0 | K50: 0 | L50: 0 | M50: 0 | N50: 0 | O50: 0 | P50: 0 | Q50: NM | R50: NM | S50: NM | T50: NM | U50: NM | V50: NM | W50: NM | X50: 0.94 | Y50: 0.94 | Z50: 0.94 | AA50: 0.94 | AB50: 0.94 | AC50: 0.94 | AD50: 0.94
A52: Source: Company Reports and Canaccord Genuity

Sheet Schizophrenia
A4: ML-007C-MA Schizophrenia revenue model
A6: ($mn, except patient numbers) [FY - DEC] | B6: 2017A | C6: Mar-18A | D6: Jun-18A | E6: Sep-18A | F6: Dec-18A | G6: 2018A | H6: Mar-19A | I6: Jun-19A | J6: Sep-19A | K6: Dec-19A | L6: 2019A | M6: Mar-20A | N6: Jun-20A | O6: Sep-20A | P6: Dec-20A | Q6: 2020A | R6: Mar-21A | S6: Jun-21A | T6: Sep-21A | U6: Dec-21A | V6: 2021A | W6: Mar-22A | X6: Jun-22A | Y6: Sep-22A | Z6: Dec-22A | AA6: 2022A | AB6: Mar-23A | AC6: Jun-23A | AD6: Sep-23A | AE6: Dec-23A | AF6: 2023A | AG6: Mar-24A | AH6: Jun-24A | AI6: Sep-24A | AJ6: Dec-24A | AK6: 2024A | AL6: Mar-25A | AM6: Jun-25A | AN6: Sep-25A | AO6: Dec-25A | AP6: 2025A | AQ6: Mar-26E | AR6: Jun-26E | AS6: Sep-26E | AT6: Dec-26E | AU6: 2026E | AV6: 2027E | AW6: 2028E | AX6: 2029E | AY6: 2030E | AZ6: 2031E | BA6: 2032E | BB6: 2033E | BC6: 2034E | BD6: 2035E | BE6: 2036E
A7: US Market (patients in '000)
A9: Prevalence | AK9: 3000 | AL9: 3090 | AM9: 3090 | AN9: 3090 | AO9: 3090 | AP9: 3090 | AQ9: 3182.7 | AR9: 3182.7 | AS9: 3182.7 | AT9: 3182.7 | AU9: 3182.7 | AV9: 3278.181 | AW9: 3376.5264 | AX9: 3477.8222 | AY9: 3582.1569 | AZ9: 3689.6216 | BA9: 3800.3102 | BB9: 3914.3196 | BC9: 4031.7491 | BD9: 4152.7016 | BE9: 4277.2827
A10: % growth | AK10: 0.03 | AP10: 0.03 | AU10: 0.03 | AV10: 0.03 | AW10: 0.03 | AX10: 0.03 | AY10: 0.03 | AZ10: 0.03 | BA10: 0.03 | BB10: 0.03 | BC10: 0.03 | BD10: 0.03 | BE10: 0.03
A12: Patients receiving Rx treatment | AK12: 2400 | AL12: 2472 | AM12: 2472 | AN12: 2472 | AO12: 2472 | AP12: 2472 | AQ12: 2546.16 | AR12: 2546.16 | AS12: 2546.16 | AT12: 2546.16 | AU12: 2546.16 | AV12: 2622.5448 | AW12: 2701.2211 | AX12: 2782.2578 | AY12: 2865.7255 | AZ12: 2951.6973 | BA12: 3040.2482 | BB12: 3131.4556 | BC12: 3225.3993 | BD12: 3322.1613 | BE12: 3421.8261
A13: % receiving Rx treatment | AK13: 0.8 | AL13: 0.8 | AM13: 0.8 | AN13: 0.8 | AO13: 0.8 | AP13: 0.8 | AQ13: 0.8 | AR13: 0.8 | AS13: 0.8 | AT13: 0.8 | AU13: 0.8 | AV13: 0.8 | AW13: 0.8 | AX13: 0.8 | AY13: 0.8 | AZ13: 0.8 | BA13: 0.8 | BB13: 0.8 | BC13: 0.8 | BD13: 0.8 | BE13: 0.8
A15: Annual treatment fraction % | AK15: 0.5 | AL15: 0.5 | AM15: 0.5 | AN15: 0.5 | AO15: 0.5 | AP15: 0.5 | AQ15: 0.5 | AR15: 0.5 | AS15: 0.5 | AT15: 0.5 | AU15: 0.5 | AV15: 0.5 | AW15: 0.5 | AX15: 0.5 | AY15: 0.5 | AZ15: 0.5 | BA15: 0.5 | BB15: 0.5 | BC15: 0.5 | BD15: 0.5 | BE15: 0.5
A17: Patients treated with ML-007C-MA | AY17: 3.5821569 | AZ17: 14.758486 | BA17: 22.801861 | BB17: 31.314556 | BC17: 40.317491 | BD17: 49.832419 | BE17: 59.881957
A18: % of patients receiving treatment | AY18: 0.0025 | AZ18: 0.01 | BA18: 0.015 | BB18: 0.02 | BC18: 0.025 | BD18: 0.03 | BE18: 0.035
A20: Annual cost of therapy | AY20: 16000 | AZ20: 16400 | BA20: 16810 | BB20: 17230.25 | BC20: 17661.006 | BD20: 18102.531 | BE20: 18555.095
A21: % growth | AZ21: 0.025 | BA21: 0.025 | BB21: 0.025 | BC21: 0.025 | BD21: 0.025 | BE21: 0.025
A23: Sales of ML-007C-MA in schizophrenia | AY23: 57.31451 | AZ23: 242.03918 | BA23: 383.29929 | BB23: 539.55764 | BC23: 712.04747 | BD23: 902.09294 | BE23: 1111.1154
A24: % growth | AZ24: 3.223 | BA24: 0.583625 | BB24: 0.40766667 | BC24: 0.3196875 | BD24: 0.2669 | BE24: 0.23170833
A28: Source: Company Reports and Canaccord Genuity

Sheet ADP
A4: ML-007C-MA Alzheimer's disease psychosis (ADP) revenue model
A6: ($mn, except patient numbers) [FY - DEC] | B6: 2017A | C6: Mar-18A | D6: Jun-18A | E6: Sep-18A | F6: Dec-18A | G6: 2018A | H6: Mar-19A | I6: Jun-19A | J6: Sep-19A | K6: Dec-19A | L6: 2019A | M6: Mar-20A | N6: Jun-20A | O6: Sep-20A | P6: Dec-20A | Q6: 2020A | R6: Mar-21A | S6: Jun-21A | T6: Sep-21A | U6: Dec-21A | V6: 2021A | W6: Mar-22A | X6: Jun-22A | Y6: Sep-22A | Z6: Dec-22A | AA6: 2022A | AB6: Mar-23A | AC6: Jun-23A | AD6: Sep-23A | AE6: Dec-23A | AF6: 2023A | AG6: Mar-24A | AH6: Jun-24A | AI6: Sep-24A | AJ6: Dec-24A | AK6: 2024A | AL6: Mar-25A | AM6: Jun-25A | AN6: Sep-25A | AO6: Dec-25A | AP6: 2025A | AQ6: Mar-26E | AR6: Jun-26E | AS6: Sep-26E | AT6: Dec-26E | AU6: 2026E | AV6: 2027E | AW6: 2028E | AX6: 2029E | AY6: 2030E | AZ6: 2031E | BA6: 2032E | BB6: 2033E | BC6: 2034E | BD6: 2035E | BE6: 2036E
A8: People suffering from Alzheimer's - US (in '000) | AK8: 7000 | AL8: 7070 | AM8: 7070 | AN8: 7070 | AO8: 7070 | AP8: 7070 | AQ8: 7282.1 | AR8: 7500.563 | AS8: 7725.5799 | AT8: 7957.3473 | AU8: 8196.0677 | AV8: 8441.9497 | AW8: 8695.2082 | AX8: 8956.0645 | AY8: 9224.7464 | AZ8: 9501.4888 | BA8: 9786.5335 | BB8: 10080.129 | BC8: 10382.533 | BD8: 10694.009 | BE8: 11014.83
A9: % growth | AK9: 0.01 | AL9: 0.03 | AM9: 0.03 | AN9: 0.03 | AO9: 0.03 | AP9: 0.01 | AQ9: 0.03 | AR9: 0.03 | AS9: 0.03 | AT9: 0.03 | AU9: 0.03 | AV9: 0.03 | AW9: 0.03 | AX9: 0.03 | AY9: 0.03 | AZ9: 0.03 | BA9: 0.03 | BB9: 0.03 | BC9: 0.03 | BD9: 0.03 | BE9: 0.03
A11: People diagnosed with Alzheimer's-related psychosis | AK11: 2800 | AL11: 2828 | AM11: 2828 | AN11: 2828 | AO11: 2828 | AP11: 2828 | AQ11: 3278.4271 | AR11: 3278.4271 | AS11: 3278.4271 | AT11: 3278.4271 | AU11: 3278.4271 | AV11: 3376.7799 | AW11: 3478.0833 | AX11: 3582.4258 | AY11: 3689.8986 | AZ11: 3800.5955 | BA11: 3914.6134 | BB11: 4032.0518 | BC11: 4153.0133 | BD11: 4277.6037 | BE11: 4405.9319
A12: % of people diagnosed with Alzheimer's | AK12: 0.4 | AL12: 0.4 | AM12: 0.4 | AN12: 0.4 | AO12: 0.4 | AP12: 0.4 | AQ12: 0.4 | AR12: 0.4 | AS12: 0.4 | AT12: 0.4 | AU12: 0.4 | AV12: 0.4 | AW12: 0.4 | AX12: 0.4 | AY12: 0.4 | AZ12: 0.4 | BA12: 0.4 | BB12: 0.4 | BC12: 0.4 | BD12: 0.4 | BE12: 0.4
A14: ADP patients treated with ML-007C-MA | AZ14: 9.5014888 | BA14: 19.573067 | BB14: 40.320518 | BC14: 83.060267 | BD14: 128.32811 | BE14: 165.22244
A15: % of diagnosed treated with ML-007C-MA | AZ15: 0.0025 | BA15: 0.005 | BB15: 0.01 | BC15: 0.02 | BD15: 0.03 | BE15: 0.0375
A17: Price of ML-007C-MA | AZ17: 16400 | BA17: 16810 | BB17: 17230.25 | BC17: 17661.006 | BD17: 18102.531 | BE17: 18555.095
A18: % growth | AZ18: 0.025 | BA18: 0.025 | BB18: 0.025 | BC18: 0.025 | BD18: 0.025 | BE18: 0.025
A20: Compliance rate | AZ20: 0.85 | BA20: 0.85 | BB20: 0.85 | BC20: 0.85 | BD20: 0.85 | BE20: 0.85
A22: Sales of ML-007C-MA in ADP | AZ22: 132.45075 | BA22: 279.66977 | BB22: 590.52271 | BC22: 1246.8887 | BD22: 1974.6041 | BE22: 2605.8604
A23: % growth | BA23: 1.1115 | BB23: 1.1115 | BC23: 1.1115 | BD23: 0.583625 | BE23: 0.3196875
A25: Source: Company Reports and Canaccord Genuity

Sheet BAL-CF
A4: MPLT Statement of Cash Flows | CZ4: Cash Flow Actuals
A6: ($mn) | B6: 2009A | C6: Mar-10A | D6: Jun-10A | E6: Sep-10A | F6: Dec-10A | G6: 2010A | H6: Mar-11A | I6: Jun-11A | J6: Sep-11A | K6: Dec-11A | L6: 2011A | M6: Mar-12A | N6: Jun-12A | O6: Sep-12A | P6: Dec-12A | Q6: 2012A | R6: Mar-13A | S6: Jun-13A | T6: Sep-13A | U6: Dec-13A | V6: 2013A | W6: Mar-14A | X6: Jun-14A | Y6: Sep-14A | Z6: Dec-14A | AA6: 2014A | AB6: Mar-15A | AC6: Jun-15A | AD6: Sep-15A | AE6: Dec-15A | AF6: 2015A | AG6: Mar-16A | AH6: Jun-16A | AI6: Sep-16A | AJ6: Dec-16A | AK6: 2016A | AL6: Mar-17A | AM6: Jun-17A | AN6: Sep-17A | AO6: Dec-17A | AP6: 2017A | AQ6: Mar-18A | AR6: Jun-18A | AS6: Sep-18A | AT6: Dec-18A | AU6: 2018A | AV6: Mar-19A | AW6: Jun-19A | AX6: Sep-19A | AY6: Dec-19A | AZ6: 2019A | BA6: Mar-20A | BB6: Jun-20A | BC6: Sep-20A | BD6: Dec-20A | BE6: 2020A | BF6: Mar-21A | BG6: Jun-21A | BH6: Sep-21A | BI6: Dec-21A | BJ6: 2021A | BK6: Mar-22A | BL6: Jun-22A | BM6: Sep-22A | BN6: Dec-22A | BO6: 2022A | BP6: Mar-23A | BQ6: Jun-23A | BR6: Sep-23A | BS6: Dec-23A | BT6: 2023A | BU6: Mar-24A | BV6: Jun-24A | BW6: Sep-24A | BX6: Dec-24A | BY6: 2024A | BZ6: Mar-25A | CA6: Jun-25A | CB6: Sep-25A | CC6: Dec-25A | CD6: 2025A | CE6: Mar-26E | CF6: Jun-26E | CG6: Sep-26E | CH6: Dec-26E | CI6: 2026E | CJ6: 2027E | CK6: 2028E | CL6: 2029E | CM6: 2030E | CN6: 2031E | CO6: 2032E | CP6: 2033E | CQ6: 2034E | CR6: 2035E | CS6: 2036E | CV6: Mar-22A | CW6: Jun-22A | CX6: Sep-22A | CY6: Dec-22A | CZ6: 2022A | DA6: Mar-23A | DB6: Jun-23A | DC6: Sep-23A | DD6: Dec-23A | DE6: 2023A | DF6: Mar-24A | DG6: Jun-24A | DH6: Sep-24A | DI6: Dec-24A | DJ6: 2024A | DK6: Mar-25A | DL6: Jun-25A | DM6: Sep-25A | DN6: Dec-25A | DO6: 2025A
A8: Net Income - GAAP | BR8: 0 | BS8: -55.709 | BT8: -55.709 | BV8: -37.335 | BW8: -19.016 | BX8: -21.229 | BY8: -77.58 | CA8: -52.185 | CB8: -29.419 | CC8: -79.548 | CD8: -161.152 | CE8: -48.823943 | CF8: -51.854155 | CG8: -54.839372 | CH8: -57.826455 | CI8: -213.34392 | CJ8: -229.41937 | CK8: -264.52629 | CL8: -264.64651 | CM8: -245.83547 | CN8: 2.3370782 | CO8: 69.978553 | CP8: 448.61607 | CQ8: 1074.5046 | CR8: 1670.4 | CS8: 2285.4234 | CZ8: 0 | DC8: 0 | DD8: -55.709 | DE8: -55.709 | DF8: 0 | DG8: -37.335 | DH8: -56.351 | DI8: -77.58 | DJ8: -77.58 | DK8: 0 | DL8: -52.185 | DM8: -81.604 | DN8: -161.152 | DO8: -161.152
A9: Depreciation | BR9: 0 | BS9: 0.556 | BT9: 0.556 | BV9: 0.32 | BW9: 0.187 | BX9: 0.194 | BY9: 0.701 | CA9: 0.302 | CB9: 0.136 | CC9: 0.14 | CD9: 0.578 | CE9: 0.1 | CF9: 0.1 | CG9: 0.1 | CH9: 0.1 | CI9: 0.4 | CJ9: 0.5 | CK9: 1 | CL9: 1 | CM9: 1 | CN9: 1 | CO9: 1 | CP9: 1 | CQ9: 1 | CR9: 1 | CS9: 1 | CZ9: 0 | DC9: 0 | DD9: 0.556 | DE9: 0.556 | DF9: 0 | DG9: 0.32 | DH9: 0.507 | DI9: 0.701 | DJ9: 0.701 | DK9: 0 | DL9: 0.302 | DM9: 0.438 | DN9: 0.578 | DO9: 0.578
A10: Amortization | BR10: 0 | BS10: 0 | BT10: 0 | BV10: -0.419 | BW10: -0.913 | BX10: -0.409 | BY10: -1.741 | CA10: -0.196 | CB10: -0.464 | CC10: -1.442 | CD10: -2.102 | CE10: 0 | CF10: 0 | CG10: 0 | CH10: 0 | CI10: 0 | CJ10: 0 | CK10: 0 | CL10: 0 | CM10: 0 | CN10: 0 | CO10: 0 | CP10: 0 | CQ10: 0 | CR10: 0 | CS10: 0 | CZ10: 0 | DC10: 0 | DD10: 0 | DE10: 0 | DF10: 0 | DG10: -0.419 | DH10: -1.332 | DI10: -1.741 | DJ10: -1.741 | DK10: 0 | DL10: -0.196 | DM10: -0.66 | DN10: -2.102 | DO10: -2.102
A11: Stock Based Compensation | BR11: 0 | BS11: 1.045 | BT11: 1.045 | BV11: 0.512 | BW11: 0.354 | BX11: 0.214 | BY11: 1.08 | CA11: 0.36 | CB11: 0.125 | CC11: 36.017 | CD11: 36.502 | CE11: 2 | CF11: 2 | CG11: 2 | CH11: 2 | CI11: 8 | CJ11: 10 | CK11: 15 | CL11: 20 | CM11: 20 | CN11: 20 | CO11: 20 | CP11: 20 | CQ11: 20 | CR11: 20 | CS11: 20 | CZ11: 0 | DC11: 0 | DD11: 1.045 | DE11: 1.045 | DF11: 0 | DG11: 0.512 | DH11: 0.866 | DI11: 1.08 | DJ11: 1.08 | DK11: 0 | DL11: 0.36 | DM11: 0.485 | DN11: 36.502 | DO11: 36.502
A12: Deferred Rent | BR12: 0 | BS12: 0 | BT12: 0 | BV12: 0 | BW12: 0 | BX12: 0 | BY12: 0 | CA12: 0 | CB12: 0 | CC12: 0 | CD12: 0 | CE12: 0 | CF12: 0 | CG12: 0 | CH12: 0 | CI12: 0 | CJ12: 0 | CK12: 0 | CL12: 0 | CM12: 0 | CN12: 0 | CO12: 0 | CP12: 0 | CQ12: 0 | CR12: 0 | CS12: 0 | CZ12: 0 | DC12: 0 | DD12: 0 | DE12: 0 | DF12: 0 | DG12: 0 | DH12: 0 | DI12: 0 | DJ12: 0 | DK12: 0 | DL12: 0 | DM12: 0 | DN12: 0 | DO12: 0
A13: Other | BR13: 0 | BS13: -0.173 | BT13: -0.173 | BV13: 1.324 | BW13: 0.201 | BX13: 0.292 | BY13: 1.817 | CA13: 0.923 | CB13: 0.224 | CC13: -0.274 | CD13: 0.873 | CE13: 0 | CF13: 0 | CG13: 0 | CH13: 0 | CI13: 0 | CJ13: -0.255 | CK13: 0 | CL13: 0 | CM13: 3.4388706 | CN13: 19.030525 | CO13: 17.308748 | CP13: 28.026677 | CQ13: 49.73135 | CR13: 55.065653 | CS13: 50.416723 | CZ13: 0 | DC13: 0 | DD13: 0.061 | DE13: 0.061 | DF13: 0 | DG13: 1.324 | DH13: 1.525 | DI13: 1.79 | DJ13: 1.79 | DK13: 0 | DL13: 0.923 | DM13: 1.147 | DN13: 0.873 | DO13: 0.873
A14: Accounts Receivable | BR14: 0 | BS14: 0 | BT14: 0 | BV14: 0 | BW14: 0 | BX14: 0 | BY14: 0 | CA14: 0 | CB14: 0 | CC14: 0 | CD14: 0 | CE14: 0 | CF14: 0 | CG14: 0 | CH14: 0 | CI14: 0 | CJ14: 0 | CK14: 0 | CL14: 0 | CM14: -5.4959119 | CN14: -30.414081 | CO14: -27.662382 | CP14: -44.791494 | CQ14: -79.479326 | CR14: -88.004469 | CS14: -80.574671 | CZ14: 0 | DC14: 0 | DD14: 0 | DE14: 0 | DF14: 0 | DG14: 0 | DH14: 0 | DI14: 0 | DJ14: 0 | DK14: 0 | DL14: 0 | DM14: 0 | DN14: 0 | DO14: 0
A15: Inventory | BR15: 0 | BS15: 0 | BT15: 0 | BV15: 0 | BW15: 0 | BX15: 0 | BY15: 0 | CA15: 0 | CB15: 0 | CC15: 0 | CD15: 0 | CE15: 0 | CF15: 0 | CG15: 0 | CH15: 0 | CI15: 0 | CJ15: 0 | CK15: 0 | CL15: 0 | CM15: -0.42397035 | CN15: -2.3462291 | CO15: -2.1339552 | CP15: -3.4553438 | CQ15: -6.1312623 | CR15: -6.7889162 | CS15: -6.2157603 | CZ15: 0 | DC15: 0 | DD15: 0 | DE15: 0 | DF15: 0 | DG15: 0 | DH15: 0 | DI15: 0 | DJ15: 0 | DK15: 0 | DL15: 0 | DM15: 0 | DN15: 0 | DO15: 0
A16: Other Assets | BR16: 0 | BS16: 0.532 | BT16: 0.532 | BV16: 0.244 | BW16: -1.126 | BX16: -1.395 | BY16: -2.277 | CA16: -6.866 | CB16: -3.908 | CC16: -2.329 | CD16: -13.103 | CE16: 0 | CF16: 0 | CG16: 0 | CH16: 0 | CI16: 0 | CJ16: 0 | CK16: 0 | CL16: 0 | CM16: 16.701274 | CN16: -15.858771 | CO16: -14.423956 | CP16: -23.355565 | CQ16: -41.442791 | CR16: -45.888045 | CS16: -42.013935 | CZ16: 0 | DC16: 0 | DD16: 0.532 | DE16: 0.532 | DF16: 0 | DG16: 0.244 | DH16: -0.882 | DI16: -2.277 | DJ16: -2.277 | DK16: 0 | DL16: -6.866 | DM16: -10.774 | DN16: -13.103 | DO16: -13.103
A17: Deferred revenue | BR17: 0 | BS17: -1.661 | BT17: -1.661 | BV17: -0.412 | BW17: -0.547 | BX17: 0 | BY17: -0.959 | CA17: -0.833 | CB17: -1.2 | CC17: -1.206 | CD17: -3.239 | CE17: 0 | CF17: 0 | CG17: 0 | CH17: 0 | CI17: 0 | CJ17: 0 | CK17: 0 | CL17: 0 | CM17: 0 | CN17: 0 | CO17: 0 | CP17: 0 | CQ17: 0 | CR17: 0 | CS17: 0 | CZ17: 0 | DC17: 0 | DD17: -1.661 | DE17: -1.661 | DF17: 0 | DG17: -0.412 | DH17: -0.959 | DI17: -0.959 | DJ17: -0.959 | DK17: 0 | DL17: -0.833 | DM17: -2.033 | DN17: -3.239 | DO17: -3.239
A18: Accounts Payable | BR18: 0 | BS18: -0.405 | BT18: -0.405 | BV18: -1.218 | BW18: 0.03 | BX18: -0.157 | BY18: -1.345 | CA18: 0.19 | CB18: 0.301 | CC18: 0.893 | CD18: 1.384 | CE18: 0 | CF18: 0 | CG18: 0 | CH18: 0 | CI18: 0 | CJ18: -3.289 | CK18: 0 | CL18: 0 | CM18: 0.8479407 | CN18: 4.6924583 | CO18: 4.2679104 | CP18: 6.9106876 | CQ18: 12.262525 | CR18: 13.577832 | CS18: 12.431521 | CZ18: 0 | DC18: 0 | DD18: -0.405 | DE18: -0.405 | DF18: 0 | DG18: -1.218 | DH18: -1.188 | DI18: -1.345 | DJ18: -1.345 | DK18: 0 | DL18: 0.19 | DM18: 0.491 | DN18: 1.384 | DO18: 1.384
A19: Accrued Liabilities | BR19: 0 | BS19: 3.922 | BT19: 3.922 | BV19: -0.186 | BW19: 1.15 | BX19: 1.205 | BY19: 2.169 | CA19: -0.838 | CB19: 2.613 | CC19: 1.124 | CD19: 2.899 | CE19: 0 | CF19: 0 | CG19: 0 | CH19: 0 | CI19: 0 | CJ19: -12.049 | CK19: 0 | CL19: 0 | CM19: 5.731451 | CN19: 31.717542 | CO19: 28.847913 | CP19: 46.711129 | CQ19: 82.885583 | CR19: 91.776089 | CS19: 84.027871 | CZ19: 0 | DC19: 0 | DD19: 3.922 | DE19: 3.922 | DF19: 0 | DG19: -0.186 | DH19: 0.964 | DI19: 2.169 | DJ19: 2.169 | DK19: 0 | DL19: -0.838 | DM19: 1.775 | DN19: 2.899 | DO19: 2.899
A20: Other | BR20: 0 | BS20: -0.347 | BT20: -0.347 | BV20: -0.303 | BW20: -0.174 | BX20: -0.176 | BY20: -0.653 | CA20: -0.374 | CB20: -0.199 | CC20: -0.204 | CD20: -0.777 | CE20: 0 | CF20: 0 | CG20: 0 | CH20: 0 | CI20: 0 | CJ20: 0 | CK20: 0 | CL20: 0 | CM20: 0 | CN20: 0 | CO20: 0 | CP20: 0 | CQ20: 0 | CR20: 0 | CS20: 0 | CZ20: 0 | DC20: 0 | DD20: -0.347 | DE20: -0.347 | DF20: 0 | DG20: -0.303 | DH20: -0.477 | DI20: -0.653 | DJ20: -0.653 | DK20: 0 | DL20: -0.374 | DM20: -0.573 | DN20: -0.777 | DO20: -0.777
A21: Change in Working Capital | BR21: 0 | BS21: 2.041 | BT21: 2.041 | BV21: -1.875 | BW21: -0.667 | BX21: -0.523 | BY21: -3.065 | CA21: -8.721 | CB21: -2.393 | CC21: -1.722 | CD21: -12.836 | CE21: 0 | CF21: 0 | CG21: 0 | CH21: 0 | CI21: 0 | CJ21: -15.338 | CK21: 0 | CL21: 0 | CM21: 17.360784 | CN21: -12.209081 | CO21: -11.104471 | CP21: -17.980585 | CQ21: -31.905272 | CR21: -35.327508 | CS21: -32.344975 | CV21: 0 | CW21: 0 | CX21: 0 | CY21: 0 | CZ21: 0 | DA21: 0 | DB21: 0 | DC21: 0 | DD21: 2.041 | DE21: 2.041 | DF21: 0 | DG21: -1.875 | DH21: -2.542 | DI21: -3.065 | DJ21: -3.065 | DK21: 0 | DL21: -8.721 | DM21: -11.114 | DN21: -12.836 | DO21: -12.836
A22: Cash Flow from Operations | BR22: 0 | BS22: -52.24 | BT22: -52.24 | BU22: 0 | BV22: -37.473 | BW22: -19.854 | BX22: -21.461 | BY22: -78.788 | BZ22: 0 | CA22: -59.517 | CB22: -31.791 | CC22: -46.829 | CD22: -138.137 | CE22: -46.723943 | CF22: -49.754155 | CG22: -52.739372 | CH22: -55.726455 | CI22: -204.94392 | CJ22: -234.51237 | CK22: -248.52629 | CL22: -243.64651 | CM22: -204.03582 | CN22: 30.158522 | CO22: 97.18283 | CP22: 479.66217 | CQ22: 1113.3306 | CR22: 1711.1381 | CS22: 2324.4951 | CV22: 0 | CW22: 0 | CX22: 0 | CY22: 0 | CZ22: 0 | DA22: 0 | DB22: 0 | DC22: 0 | DD22: -52.006 | DE22: -52.006 | DF22: 0 | DG22: -37.473 | DH22: -57.327 | DI22: -78.815 | DJ22: -78.815 | DK22: 0 | DL22: -59.517 | DM22: -91.308 | DN22: -138.137 | DO22: -138.137
A24: Purchase of PPE (Cap-Ex) | BR24: 0 | BS24: -0.462 | BT24: -0.462 | BV24: -0.29 | BW24: -0.374 | BX24: -0.106 | BY24: -0.77 | CA24: -0.066 | CB24: -0.031 | CC24: -0.376 | CD24: -0.473 | CE24: -0.1 | CF24: -0.1 | CG24: -0.1 | CH24: -0.1 | CI24: -0.4 | CJ24: -0.5 | CK24: -2 | CL24: -2 | CM24: -2 | CN24: -2 | CO24: -2 | CP24: -2 | CQ24: -2 | CR24: -2 | CS24: -2 | CZ24: 0 | DC24: 0 | DD24: -0.462 | DE24: -0.462 | DF24: 0 | DG24: -0.29 | DH24: -0.664 | DI24: -0.77 | DJ24: -0.77 | DK24: 0 | DL24: -0.066 | DM24: -0.097 | DN24: -0.473 | DO24: -0.473
A25: Purchase of marketable securities | BR25: 0 | BS25: 0 | BT25: 0 | BV25: -121.532 | BW25: 9.014 | BX25: 32.5 | BY25: -80.018 | CA25: 55 | CB25: -135.557 | CC25: -242.177 | CD25: -322.734 | CE25: 200 | CF25: 0 | CG25: 0 | CH25: 0 | CI25: 200 | CJ25: 0 | CK25: 0 | CL25: 0 | CM25: 0 | CN25: 0 | CO25: 0 | CP25: 0 | CQ25: 0 | CR25: 0 | CS25: 0 | CZ25: 0 | DC25: 0 | DD25: 0 | DE25: 0 | DF25: 0 | DG25: -121.532 | DH25: -112.518 | DI25: -80.018 | DJ25: -80.018 | DK25: 0 | DL25: 55 | DM25: -80.557 | DN25: -322.734 | DO25: -322.734
A26: Purchase of Intangibles | BR26: 0 | BS26: 0 | BT26: 0 | BV26: 0 | BW26: 0 | BX26: 0 | BY26: 0 | CA26: 0 | CB26: 0 | CC26: 0 | CD26: 0 | CE26: 0 | CF26: 0 | CG26: 0 | CH26: 0 | CI26: 0 | CJ26: 0 | CK26: 0 | CL26: 0 | CM26: 0 | CN26: 0 | CO26: 0 | CP26: 0 | CQ26: 0 | CR26: 0 | CS26: 0 | CZ26: 0 | DC26: 0 | DD26: 0 | DE26: 0 | DF26: 0 | DG26: 0 | DH26: 0 | DI26: 0 | DJ26: 0 | DK26: 0 | DL26: 0 | DM26: 0 | DN26: 0 | DO26: 0
A27: Purchase of Product Rights | BR27: 0 | BS27: 0 | BT27: 0 | BV27: 0 | BW27: 0 | BX27: 0 | BY27: 0 | CA27: 0 | CB27: 0 | CC27: 0 | CD27: 0 | CE27: 0 | CF27: 0 | CG27: 0 | CH27: 0 | CI27: 0 | CJ27: 0 | CK27: 0 | CL27: 0 | CM27: 0 | CN27: 0 | CO27: 0 | CP27: 0 | CQ27: 0 | CR27: 0 | CS27: 0 | CZ27: 0 | DC27: 0 | DD27: 0 | DE27: 0 | DF27: 0 | DG27: 0 | DH27: 0 | DI27: 0 | DJ27: 0 | DK27: 0 | DL27: 0 | DM27: 0 | DN27: 0 | DO27: 0
A28: Change in Restricted Cash | BR28: 0 | BS28: 0 | BT28: 0 | BV28: 0 | BW28: 0 | BX28: 0 | BY28: 0 | CA28: 0 | CB28: 0 | CC28: 0 | CD28: 0 | CE28: 0 | CF28: 0 | CG28: 0 | CH28: 0 | CI28: 0 | CJ28: 0 | CK28: 0 | CL28: 0 | CM28: 0 | CN28: 0 | CO28: 0 | CP28: 0 | CQ28: 0 | CR28: 0 | CS28: 0 | CZ28: 0 | DC28: 0 | DD28: 0 | DE28: 0 | DF28: 0 | DG28: 0 | DH28: 0 | DI28: 0 | DJ28: 0 | DK28: 0 | DL28: 0 | DM28: 0 | DN28: 0 | DO28: 0
A29: Other | BR29: 0 | BS29: 0 | BT29: 0 | BV29: 0 | BW29: 0 | BX29: 0 | BY29: 0 | CA29: 0 | CB29: 0 | CC29: 0 | CD29: 0 | CE29: 0 | CF29: 0 | CG29: 0 | CH29: 0 | CI29: 0 | CJ29: 0 | CK29: 0 | CL29: 0 | CM29: 0 | CN29: 0 | CO29: 0 | CP29: 0 | CQ29: 0 | CR29: 0 | CS29: 0 | CZ29: 0 | DC29: 0 | DD29: 0 | DE29: 0 | DF29: 0 | DG29: 0 | DH29: 0 | DI29: 0 | DJ29: 0 | DK29: 0 | DL29: 0 | DM29: 0 | DN29: 0 | DO29: 0
A30: Cash Flow from Investing | BR30: 0 | BS30: -0.462 | BT30: -0.462 | BU30: 0 | BV30: -121.822 | BW30: 8.64 | BX30: 32.394 | BY30: -80.788 | BZ30: 0 | CA30: 54.934 | CB30: -135.588 | CC30: -242.553 | CD30: -323.207 | CE30: 199.9 | CF30: -0.1 | CG30: -0.1 | CH30: -0.1 | CI30: 199.6 | CJ30: -0.5 | CK30: -2 | CL30: -2 | CM30: -2 | CN30: -2 | CO30: -2 | CP30: -2 | CQ30: -2 | CR30: -2 | CS30: -2 | CV30: 0 | CW30: 0 | CX30: 0 | CY30: 0 | CZ30: 0 | DA30: 0 | DB30: 0 | DC30: 0 | DD30: -0.462 | DE30: -0.462 | DF30: 0 | DG30: -121.822 | DH30: -113.182 | DI30: -80.788 | DJ30: -80.788 | DK30: 0 | DL30: 54.934 | DM30: -80.654 | DN30: -323.207 | DO30: -323.207
A32: Proceeds from issuance of debt | BR32: 0 | BS32: 0 | BT32: 0 | BV32: 0 | BW32: 0 | BX32: 0 | BY32: 0 | CA32: 0 | CB32: 0 | CC32: 0 | CD32: 0 | CE32: 0 | CF32: 0 | CG32: 0 | CH32: 0 | CI32: 0 | CJ32: 0 | CK32: 0 | CL32: 0 | CM32: 0 | CN32: 0 | CO32: 0 | CP32: 0 | CQ32: 0 | CR32: 0 | CS32: 0 | CZ32: 0 | DC32: 0 | DD32: 0 | DE32: 0 | DF32: 0 | DG32: 0 | DH32: 0 | DI32: 0 | DJ32: 0 | DK32: 0 | DL32: 0 | DM32: 0 | DN32: 0 | DO32: 0
A33: Proceeds from convertible notes payable | BR33: 0 | BS33: 0 | BT33: 0 | BV33: 0 | BW33: 0 | BX33: 0 | BY33: 0 | CA33: 0 | CB33: 0 | CC33: 0 | CD33: 0 | CE33: 0 | CF33: 0 | CG33: 0 | CH33: 0 | CI33: 0 | CJ33: 0 | CK33: 0 | CL33: 0 | CM33: 0 | CN33: 0 | CO33: 0 | CP33: 0 | CQ33: 0 | CR33: 0 | CS33: 0 | CZ33: 0 | DC33: 0 | DD33: 0 | DE33: 0 | DF33: 0 | DG33: 0 | DH33: 0 | DI33: 0 | DJ33: 0 | DK33: 0 | DL33: 0 | DM33: 0 | DN33: 0 | DO33: 0
A34: Proceeds from convertible preferred stock | BR34: 0 | BS34: 104.532 | BT34: 104.532 | BV34: 119.956 | BW34: 0 | BX34: 0 | BY34: 119.956 | CA34: 0 | CB34: 198.87 | CC34: -0.03 | CD34: 198.84 | CE34: 0 | CF34: 0 | CG34: 0 | CH34: 0 | CI34: 0 | CJ34: 0 | CK34: 0 | CL34: 0 | CM34: 0 | CN34: 0 | CO34: 0 | CP34: 0 | CQ34: 0 | CR34: 0 | CS34: 0 | CZ34: 0 | DC34: 0 | DD34: 104.532 | DE34: 104.532 | DF34: 0 | DG34: 119.956 | DH34: 119.956 | DI34: 119.956 | DJ34: 119.956 | DK34: 0 | DL34: 0 | DM34: 198.87 | DN34: 198.84 | DO34: 198.84
A35: Proceeds from issuance of common stock | BR35: 0 | BS35: 0 | BT35: 0 | BV35: 0 | BW35: 0 | BX35: 0 | BY35: 0 | CA35: 0 | CB35: 0 | CC35: 275.716 | CD35: 275.716 | CE35: 0 | CF35: 0 | CG35: 150 | CH35: 0 | CI35: 150 | CJ35: 200 | CK35: 200 | CL35: 200 | CM35: 200 | CN35: 0 | CO35: 0 | CP35: 0 | CQ35: 0 | CR35: 0 | CS35: 0 | CZ35: 0 | DC35: 0 | DD35: 0 | DE35: 0 | DF35: 0 | DG35: 0 | DH35: 0 | DI35: 0 | DJ35: 0 | DK35: 0 | DL35: 0 | DM35: 0 | DN35: 275.716 | DO35: 275.716
A36: Other | BR36: 0 | BS36: 0.04 | BT36: 0.04 | BV36: -1.694 | BW36: -0.207 | BX36: 0.005 | BY36: -1.896 | CA36: -0.203 | CB36: -0.812 | CC36: -3.721 | CD36: -4.736 | CE36: 0 | CF36: 0 | CG36: 0 | CH36: 0 | CI36: 0 | CJ36: 0 | CK36: 0 | CL36: 0 | CM36: 0 | CN36: 0 | CO36: 0 | CP36: 0 | CQ36: 0 | CR36: 0 | CS36: 0 | CZ36: 0 | DC36: 0 | DD36: 0.04 | DE36: 0.04 | DF36: 0 | DG36: -1.694 | DH36: -1.901 | DI36: -1.896 | DJ36: -1.896 | DK36: 0 | DL36: -0.203 | DM36: -1.015 | DN36: -4.736 | DO36: -4.736
A37: Cash Flow from Financing | BR37: 0 | BS37: 104.572 | BT37: 104.572 | BU37: 0 | BV37: 118.262 | BW37: -0.207 | BX37: 0.005 | BY37: 118.06 | BZ37: 0 | CA37: -0.203 | CB37: 198.058 | CC37: 271.965 | CD37: 469.82 | CE37: 0 | CF37: 0 | CG37: 150 | CH37: 0 | CI37: 150 | CJ37: 200 | CK37: 200 | CL37: 200 | CM37: 200 | CN37: 0 | CO37: 0 | CP37: 0 | CQ37: 0 | CR37: 0 | CS37: 0 | CV37: 0 | CW37: 0 | CX37: 0 | CY37: 0 | CZ37: 0 | DA37: 0 | DB37: 0 | DC37: 0 | DD37: 104.572 | DE37: 104.572 | DF37: 0 | DG37: 118.262 | DH37: 118.055 | DI37: 118.06 | DJ37: 118.06 | DK37: 0 | DL37: -0.203 | DM37: 197.855 | DN37: 469.82 | DO37: 469.82
A39: Net Increase (Decrease) in Cash | BR39: 0 | BS39: 51.87 | BT39: 51.87 | BV39: -41.033 | BW39: -11.421 | BX39: 10.938 | BY39: -41.516 | CA39: -4.786 | CB39: 30.679 | CC39: -17.417 | CD39: 8.476 | CE39: 153.17606 | CF39: -49.854155 | CG39: 97.160628 | CH39: -55.826455 | CI39: 144.65608 | CJ39: -35.012368 | CK39: -50.526291 | CL39: -45.646507 | CM39: -6.0358158 | CN39: 28.158522 | CO39: 95.18283 | CP39: 477.66217 | CQ39: 1111.3306 | CR39: 1709.1381 | CS39: 2322.4951 | CZ39: 0 | DA39: 0 | DB39: 0 | DC39: 0 | DD39: 52.104 | DE39: 52.104 | DF39: 0 | DG39: -41.033 | DH39: -52.454 | DI39: -41.543 | DJ39: -41.543 | DK39: 0 | DL39: -4.786 | DM39: 25.893 | DN39: 8.476 | DO39: 8.476
A40: Cash & Equivalents at Beginning | BR40: 0 | BS40: 27.899 | BT40: 27.899 | BV40: 79.769 | BW40: 38.736 | BX40: 27.315 | BY40: 79.769 | CA40: 38.253 | CB40: 33.467 | CC40: 64.146 | CD40: 38.253 | CE40: 46.729 | CF40: 199.90506 | CG40: 150.0509 | CH40: 247.21153 | CI40: 46.729 | CJ40: 191.38508 | CK40: 156.37271 | CL40: 105.84642 | CM40: 60.199909 | CN40: 54.164094 | CO40: 82.322616 | CP40: 177.50545 | CQ40: 655.16761 | CR40: 1766.4983 | CS40: 3475.6364 | CZ40: 0 | DA40: 27.899 | DB40: 27.899 | DC40: 27.899 | DD40: 27.899 | DE40: 27.899 | DF40: 80.003 | DG40: 80.003 | DH40: 80.003 | DI40: 80.003 | DJ40: 80.003 | DK40: 38.46 | DL40: 38.46 | DM40: 38.46 | DN40: 38.46 | DO40: 38.46
A41: Cash & Equivalents at End | BR41: 27.899 | BS41: 79.769 | BT41: 79.769 | BU41: 0 | BV41: 38.736 | BW41: 27.315 | BX41: 38.253 | BY41: 38.253 | BZ41: 0 | CA41: 33.467 | CB41: 64.146 | CC41: 46.729 | CD41: 46.729 | CE41: 199.90506 | CF41: 150.0509 | CG41: 247.21153 | CH41: 191.38508 | CI41: 191.38508 | CJ41: 156.37271 | CK41: 105.84642 | CL41: 60.199909 | CM41: 54.164094 | CN41: 82.322616 | CO41: 177.50545 | CP41: 655.16761 | CQ41: 1766.4983 | CR41: 3475.6364 | CS41: 5798.1315 | CZ41: 27.899 | DA41: 27.899 | DB41: 27.899 | DC41: 27.899 | DD41: 80.003 | DE41: 80.003 | DF41: 80.003 | DG41: 38.97 | DH41: 27.549 | DI41: 38.46 | DJ41: 38.46 | DK41: 38.46 | DL41: 33.674 | DM41: 64.353 | DN41: 46.936 | DO41: 46.936
A45: MPLT Balance Sheet
A47: ($mn) | B47: 2009A | C47: Mar-10A | D47: Jun-10A | E47: Sep-10A | F47: Dec-10A | G47: 2010A | H47: Mar-11A | I47: Jun-11A | J47: Sep-11A | K47: Dec-11A | L47: 2011A | M47: Mar-12A | N47: Jun-12A | O47: Sep-12A | P47: Dec-12A | Q47: 2012A | R47: Mar-13A | S47: Jun-13A | T47: Sep-13A | U47: Dec-13A | V47: 2013A | W47: Mar-14A | X47: Jun-14A | Y47: Sep-14A | Z47: Dec-14A | AA47: 2014A | AB47: Mar-15A | AC47: Jun-15A | AD47: Sep-15A | AE47: Dec-15A | AF47: 2015A | AG47: Mar-16A | AH47: Jun-16A | AI47: Sep-16A | AJ47: Dec-16A | AK47: 2016A | AL47: Mar-17A | AM47: Jun-17A | AN47: Sep-17A | AO47: Dec-17A | AP47: 2017A | AQ47: Mar-18A | AR47: Jun-18A | AS47: Sep-18A | AT47: Dec-18A | AU47: 2018A | AV47: Mar-19A | AW47: Jun-19A | AX47: Sep-19A | AY47: Dec-19A | AZ47: 2019A | BA47: Mar-20A | BB47: Jun-20A | BC47: Sep-20A | BD47: Dec-20A | BE47: 2020A | BF47: Mar-21A | BG47: Jun-21A | BH47: Sep-21A | BI47: Dec-21A | BJ47: 2021A | BK47: Mar-22A | BL47: Jun-22A | BM47: Sep-22A | BN47: Dec-22A | BO47: 2022A | BT47: 2023A | BU47: Mar-24A | BV47: Jun-24A | BW47: Sep-24A | BX47: Dec-24A | BY47: 2024A | BZ47: Mar-25A | CA47: Jun-25A | CB47: Sep-25A | CC47: Dec-25A | CD47: 2025A | CE47: Mar-26E | CF47: Jun-26E | CG47: Sep-26E | CH47: Dec-26E | CI47: 2026E | CJ47: 2027E | CK47: 2028E | CL47: 2029E | CM47: 2030E | CN47: 2031E | CO47: 2032E | CP47: 2033E | CQ47: 2034E | CR47: 2035E | CS47: 2036E
A49: ASSETS
A50: Cash & Equivalents | BS50: 79.769 | BT50: 79.769 | BU50: 0 | BV50: 0 | BW50: 0 | BX50: 38.253 | BY50: 38.253 | BZ50: 0 | CA50: 33.467 | CB50: 64.146 | CC50: 46.729 | CD50: 46.729 | CE50: 199.90506 | CF50: 150.0509 | CG50: 247.21153 | CH50: 191.38508 | CI50: 191.38508 | CJ50: 156.37271 | CK50: 105.84642 | CL50: 60.199909 | CM50: 54.164094 | CN50: 82.322616 | CO50: 177.50545 | CP50: 655.16761 | CQ50: 1766.4983 | CR50: 3475.6364 | CS50: 5798.1315
A51: Restricted cash | BS51: 0 | BT51: 0 | BX51: 0 | BY51: 0 | CA51: 0 | CB51: 0 | CC51: 0 | CD51: 0 | CE51: 0 | CF51: 0 | CG51: 0 | CH51: 0 | CI51: 0 | CJ51: 0 | CK51: 0 | CL51: 0 | CM51: 0 | CN51: 0 | CO51: 0 | CP51: 0 | CQ51: 0 | CR51: 0 | CS51: 0
A52: Marketable Securities | BS52: 0 | BT52: 0 | BX52: 70.542 | BY52: 70.542 | CA52: 27.005 | CB52: 163.022 | CC52: 258.374 | CD52: 258.374 | CE52: 58.374 | CF52: 58.374 | CG52: 58.374 | CH52: 58.374 | CI52: 58.374 | CJ52: 58.374 | CK52: 58.374 | CL52: 58.374 | CM52: 58.374 | CN52: 58.374 | CO52: 58.374 | CP52: 58.374 | CQ52: 58.374 | CR52: 58.374 | CS52: 58.374
A53: Accounts Receivable | BS53: 0 | BT53: 0 | BX53: 0 | BY53: 0 | CA53: 0 | CB53: 0 | CC53: 0 | CD53: 0 | CE53: 0 | CF53: 0 | CG53: 0 | CH53: 0 | CI53: 0 | CJ53: 0 | CK53: 0 | CL53: 0 | CM53: 5.4959119 | CN53: 35.909993 | CO53: 63.572375 | CP53: 108.36387 | CQ53: 187.84319 | CR53: 275.84766 | CS53: 356.42233
A54: Inventories | BS54: 0 | BT54: 0 | BX54: 0 | BY54: 0 | CA54: 0 | CB54: 0 | CC54: 0 | CD54: 0 | CE54: 0 | CF54: 0 | CG54: 0 | CH54: 0 | CI54: 0 | CJ54: 0 | CK54: 0 | CL54: 0 | CM54: 0.42397035 | CN54: 2.7701995 | CO54: 4.9041547 | CP54: 8.3594985 | CQ54: 14.490761 | CR54: 21.279677 | CS54: 27.495437
A55: Prepaid & Other Current Assets | BS55: 3.835 | BT55: 3.835 | BX55: 5.807 | BY55: 5.807 | CA55: 12.729 | CB55: 18.138 | CC55: 19.567 | CD55: 19.567 | CE55: 19.567 | CF55: 19.567 | CG55: 19.567 | CH55: 19.567 | CI55: 19.567 | CJ55: 19.567 | CK55: 19.567 | CL55: 19.567 | CM55: 2.8657255 | CN55: 18.724497 | CO55: 33.148453 | CP55: 56.504017 | CQ55: 97.946809 | CR55: 143.83485 | CS55: 185.84879
A56: Total Current Assets | BS56: 83.604 | BT56: 83.604 | BU56: 0 | BV56: 0 | BW56: 0 | BX56: 114.602 | BY56: 114.602 | BZ56: 0 | CA56: 73.201 | CB56: 245.306 | CC56: 324.67 | CD56: 324.67 | CE56: 277.84606 | CF56: 227.9919 | CG56: 325.15253 | CH56: 269.32608 | CI56: 269.32608 | CJ56: 234.31371 | CK56: 183.78742 | CL56: 138.14091 | CM56: 121.3237 | CN56: 198.10131 | CO56: 337.50443 | CP56: 886.769 | CQ56: 2125.153 | CR56: 3974.9726 | CS56: 6426.272
A58: PPE | BS58: 0.971 | BT58: 0.971 | BX58: 1.207 | BY58: 1.207 | CA58: 0.971 | CB58: 0.859 | CC58: 1.095 | CD58: 1.095 | CE58: 1.095 | CF58: 1.095 | CG58: 1.095 | CH58: 1.095 | CI58: 1.095 | CJ58: 1.095 | CK58: 2.095 | CL58: 3.095 | CM58: 4.095 | CN58: 5.095 | CO58: 6.095 | CP58: 7.095 | CQ58: 8.095 | CR58: 9.095 | CS58: 10.095
A59: Intangibles | BS59: 0 | BT59: 0 | BX59: 0 | BY59: 0 | CA59: 0 | CB59: 0 | CC59: 0 | CD59: 0 | CE59: 0 | CF59: 0 | CG59: 0 | CH59: 0 | CI59: 0 | CJ59: 0 | CK59: 0 | CL59: 0 | CM59: 0 | CN59: 0 | CO59: 0 | CP59: 0 | CQ59: 0 | CR59: 0 | CS59: 0
A60: Goodwill | BS60: 0 | BT60: 0 | BX60: 0 | BY60: 0 | CA60: 0 | CB60: 0 | CC60: 0 | CD60: 0 | CE60: 0 | CF60: 0 | CG60: 0 | CH60: 0 | CI60: 0 | CJ60: 0 | CK60: 0 | CL60: 0 | CM60: 0 | CN60: 0 | CO60: 0 | CP60: 0 | CQ60: 0 | CR60: 0 | CS60: 0
A61: Restricted cash | BS61: 0.234 | BT61: 0.234 | BX61: 0.207 | BY61: 0.207 | CA61: 0.207 | CB61: 0.207 | CC61: 0.207 | CD61: 0.207 | CE61: 0.207 | CF61: 0.207 | CG61: 0.207 | CH61: 0.207 | CI61: 0.207 | CJ61: 0.207 | CK61: 0.207 | CL61: 0.207 | CM61: 0.207 | CN61: 0.207 | CO61: 0.207 | CP61: 0.207 | CQ61: 0.207 | CR61: 0.207 | CS61: 0.207
A62: Marketable Investment | BS62: 0 | BT62: 0 | BX62: 11.38 | BY62: 11.38 | CA62: 0 | CB62: 0 | CC62: 147.993 | CD62: 147.993 | CE62: 147.993 | CF62: 147.993 | CG62: 147.993 | CH62: 147.993 | CI62: 147.993 | CJ62: 147.993 | CK62: 147.993 | CL62: 147.993 | CM62: 147.993 | CN62: 147.993 | CO62: 147.993 | CP62: 147.993 | CQ62: 147.993 | CR62: 147.993 | CS62: 147.993
A63: Other Assets | BS63: 6.6 | BT63: 6.6 | BX63: 9.52 | BY63: 9.52 | CA63: 9.738 | CB63: 10.85 | CC63: 5.547 | CD63: 5.547 | CE63: 5.547 | CF63: 5.547 | CG63: 5.547 | CH63: 5.547 | CI63: 5.547 | CJ63: 0 | CK63: 0 | CL63: 0 | CM63: 4.5851608 | CN63: 29.959194 | CO63: 53.037525 | CP63: 90.406428 | CQ63: 156.71489 | CR63: 230.13577 | CS63: 297.35806
A64: Total Assets | BS64: 91.409 | BT64: 91.409 | BU64: 0 | BV64: 0 | BW64: 0 | BX64: 136.916 | BY64: 136.916 | BZ64: 0 | CA64: 84.117 | CB64: 257.222 | CC64: 479.512 | CD64: 479.512 | CE64: 432.68806 | CF64: 382.8339 | CG64: 479.99453 | CH64: 424.16808 | CI64: 424.16808 | CJ64: 383.60871 | CK64: 334.08242 | CL64: 289.43591 | CM64: 278.20386 | CN64: 381.3555 | CO64: 544.83695 | CP64: 1132.4704 | CQ64: 2438.1629 | CR64: 4362.4033 | CS64: 6881.9251
A66: LIABILITIES
A67: Accounts Payable | BS67: 3.25 | BT67: 3.25 | BX67: 1.912 | BY67: 1.912 | CA67: 2.102 | CB67: 2.446 | CC67: 3.289 | CD67: 3.289 | CE67: 3.289 | CF67: 3.289 | CG67: 3.289 | CH67: 3.289 | CI67: 3.289 | CJ67: 0 | CK67: 0 | CL67: 0 | CM67: 0.8479407 | CN67: 5.540399 | CO67: 9.8083094 | CP67: 16.718997 | CQ67: 28.981521 | CR67: 42.559354 | CS67: 54.990874
A68: Accrued Liabilities | BS68: 6.755 | BT68: 6.755 | BX68: 9.991 | BY68: 9.991 | CA68: 9.643 | CB68: 14.048 | CC68: 12.049 | CD68: 12.049 | CE68: 12.049 | CF68: 12.049 | CG68: 12.049 | CH68: 12.049 | CI68: 12.049 | CJ68: 0 | CK68: 0 | CL68: 0 | CM68: 5.731451 | CN68: 37.448993 | CO68: 66.296906 | CP68: 113.00803 | CQ68: 195.89362 | CR68: 287.66971 | CS68: 371.69758
A69: Deferred rent | BS69: 0 | BT69: 0 | BX69: 0 | BY69: 0 | CA69: 0 | CB69: 0 | CC69: 0 | CD69: 0 | CE69: 0 | CF69: 0 | CG69: 0 | CH69: 0 | CI69: 0 | CJ69: 0 | CK69: 0 | CL69: 0 | CM69: 0 | CN69: 0 | CO69: 0 | CP69: 0 | CQ69: 0 | CR69: 0 | CS69: 0
A70: Note payable | BS70: 0 | BT70: 0 | BX70: 0 | BY70: 0 | CA70: 0 | CB70: 0 | CC70: 0 | CD70: 0 | CE70: 0 | CF70: 0 | CG70: 0 | CH70: 0 | CI70: 0 | CJ70: 0 | CK70: 0 | CL70: 0 | CM70: 0 | CN70: 0 | CO70: 0 | CP70: 0 | CQ70: 0 | CR70: 0 | CS70: 0
A71: Deferred revenue | BS71: 4.198 | BT71: 4.198 | BX71: 3.239 | BY71: 3.239 | CA71: 2.406 | CB71: 1.206 | CC71: 0 | CD71: 0 | CE71: 0 | CF71: 0 | CG71: 0 | CH71: 0 | CI71: 0 | CJ71: 0 | CK71: 0 | CL71: 0 | CM71: 0 | CN71: 0 | CO71: 0 | CP71: 0 | CQ71: 0 | CR71: 0 | CS71: 0
A72: Other Current Liabilities | BS72: 0.495 | BT72: 0.495 | BX72: 0.778 | BY72: 0.778 | CA72: 0.833 | CB72: 0.862 | CC72: 0.891 | CD72: 0.891 | CE72: 0.891 | CF72: 0.891 | CG72: 0.891 | CH72: 0.891 | CI72: 0.891 | CJ72: 0 | CK72: 0 | CL72: 0 | CM72: 2.2925804 | CN72: 14.979597 | CO72: 26.518762 | CP72: 45.203214 | CQ72: 78.357447 | CR72: 115.06788 | CS72: 148.67903
A73: Total Current Liabilities | BS73: 14.698 | BT73: 14.698 | BU73: 0 | BV73: 0 | BW73: 0 | BX73: 15.92 | BY73: 15.92 | BZ73: 0 | CA73: 14.984 | CB73: 18.562 | CC73: 16.229 | CD73: 16.229 | CE73: 16.229 | CF73: 16.229 | CG73: 16.229 | CH73: 16.229 | CI73: 16.229 | CJ73: 0 | CK73: 0 | CL73: 0 | CM73: 8.8719721 | CN73: 57.968989 | CO73: 102.62398 | CP73: 174.93025 | CQ73: 303.23259 | CR73: 445.29694 | CS73: 575.36748
A75: Convertible preferred stock | BS75: 0 | BT75: 0 | BX75: 0 | BY75: 0 | CA75: 0 | CB75: 0 | CC75: 0 | CD75: 0 | CE75: 0 | CF75: 0 | CG75: 0 | CH75: 0 | CI75: 0 | CJ75: 0 | CK75: 0 | CL75: 0 | CM75: 0 | CN75: 0 | CO75: 0 | CP75: 0 | CQ75: 0 | CR75: 0 | CS75: 0
A76: Note payable | BS76: 0 | BT76: 0 | BX76: 0 | BY76: 0 | CA76: 0 | CB76: 0 | CC76: 0 | CD76: 0 | CE76: 0 | CF76: 0 | CG76: 0 | CH76: 0 | CI76: 0 | CJ76: 0 | CK76: 0 | CL76: 0 | CM76: 0 | CN76: 0 | CO76: 0 | CP76: 0 | CQ76: 0 | CR76: 0 | CS76: 0
A77: Convertible preferred stock warrant liability | BS77: 0 | BT77: 0 | BX77: 0 | BY77: 0 | CA77: 0 | CB77: 0 | CC77: 0 | CD77: 0 | CE77: 0 | CF77: 0 | CG77: 0 | CH77: 0 | CI77: 0 | CJ77: 0 | CK77: 0 | CL77: 0 | CM77: 0 | CN77: 0 | CO77: 0 | CP77: 0 | CQ77: 0 | CR77: 0 | CS77: 0
A78: Deferred rent | BS78: 0 | BT78: 0 | BX78: 0 | BY78: 0 | CA78: 0 | CB78: 0 | CC78: 0 | CD78: 0 | CE78: 0 | CF78: 0 | CG78: 0 | CH78: 0 | CI78: 0 | CJ78: 0 | CK78: 0 | CL78: 0 | CM78: 0 | CN78: 0 | CO78: 0 | CP78: 0 | CQ78: 0 | CR78: 0 | CS78: 0
A79: Deferred revenue | BS79: 0 | BT79: 0 | BX79: 0 | BY79: 0 | CA79: 0 | CB79: 0 | CC79: 0 | CD79: 0 | CE79: 0 | CF79: 0 | CG79: 0 | CH79: 0 | CI79: 0 | CJ79: 0 | CK79: 0 | CL79: 0 | CM79: 0 | CN79: 0 | CO79: 0 | CP79: 0 | CQ79: 0 | CR79: 0 | CS79: 0
A80: Other Liabilities | BS80: 5.429 | BT80: 5.429 | BX80: 5.801 | BY80: 5.801 | CA80: 5.372 | CB80: 5.144 | CC80: 4.911 | CD80: 4.911 | CE80: 4.911 | CF80: 4.911 | CG80: 4.911 | CH80: 4.911 | CI80: 4.911 | CJ80: 0 | CK80: 0 | CL80: 0 | CM80: 5.731451 | CN80: 37.448993 | CO80: 66.296906 | CP80: 113.00803 | CQ80: 195.89362 | CR80: 287.66971 | CS80: 371.69758
A81: Total Liabilities | BS81: 20.127 | BT81: 20.127 | BU81: 0 | BV81: 0 | BW81: 0 | BX81: 21.721 | BY81: 21.721 | BZ81: 0 | CA81: 20.356 | CB81: 23.706 | CC81: 21.14 | CD81: 21.14 | CE81: 21.14 | CF81: 21.14 | CG81: 21.14 | CH81: 21.14 | CI81: 21.14 | CJ81: 0 | CK81: 0 | CL81: 0 | CM81: 14.603423 | CN81: 95.417982 | CO81: 168.92088 | CP81: 287.93828 | CQ81: 499.1262 | CR81: 732.96665 | CS81: 947.06506
A83: Convertible preferred shares | BS83: 188.867 | BT83: 188.867 | BX83: 308.823 | BY83: 308.823 | CA83: 308.823 | CB83: 507.693 | CC83: 0 | CD83: 0 | CE83: 0 | CF83: 0 | CG83: 0 | CH83: 0 | CI83: 0 | CJ83: 0 | CK83: 0 | CL83: 0 | CM83: 0 | CN83: 0 | CO83: 0 | CP83: 0 | CQ83: 0 | CR83: 0 | CS83: 0
A85: SHAREHOLDERS EQUITY
A86: Common Stock Par value | BS86: 0 | BT86: 0 | BX86: 0 | BY86: 0 | CA86: 0 | CB86: 0 | CC86: 0.005 | CD86: 0.005 | CE86: 0.005 | CF86: 0.005 | CG86: 0.005 | CH86: 0.005 | CI86: 0.005 | CJ86: 0.005 | CK86: 0.005 | CL86: 0.005 | CM86: 0.005 | CN86: 0.005 | CO86: 0.005 | CP86: 0.005 | CQ86: 0.005 | CR86: 0.005 | CS86: 0.005
A87: Additional Paid In Capital | BS87: 4.203 | BT87: 4.203 | BX87: 5.577 | BY87: 5.577 | CA87: 6.441 | CB87: 6.749 | CC87: 819.115 | CD87: 819.115 | CE87: 821.115 | CF87: 823.115 | CG87: 975.115 | CH87: 977.115 | CI87: 977.115 | CJ87: 1187.115 | CK87: 1402.115 | CL87: 1622.115 | CM87: 1842.115 | CN87: 1862.115 | CO87: 1882.115 | CP87: 1902.115 | CQ87: 1922.115 | CR87: 1942.115 | CS87: 1962.115
A88: Accumulated other comprehensive income | BS88: 0 | BT88: 0 | BX88: 0.163 | BY88: 0.163 | CA88: 0.05 | CB88: 0.046 | CC88: -0.228 | CD88: -0.228 | CE88: -0.228 | CF88: -0.228 | CG88: -0.228 | CH88: -0.228 | CI88: -0.228 | CJ88: -0.228 | CK88: -0.228 | CL88: -0.228 | CM88: -0.228 | CN88: -0.228 | CO88: -0.228 | CP88: -0.228 | CQ88: -0.228 | CR88: -0.228 | CS88: -0.228
A89: Accumulated Deficit | BS89: -121.788 | BT89: -121.788 | BX89: -199.368 | BY89: -199.368 | CA89: -251.553 | CB89: -280.972 | CC89: -360.52 | CD89: -360.52 | CE89: -409.34394 | CF89: -461.1981 | CG89: -516.03747 | CH89: -573.86392 | CI89: -573.86392 | CJ89: -803.28329 | CK89: -1067.8096 | CL89: -1332.4561 | CM89: -1578.2916 | CN89: -1575.9545 | CO89: -1505.9759 | CP89: -1057.3599 | CQ89: 17.144712 | CR89: 1687.5447 | CS89: 3972.9681
A90: Total Shareholders' Equity | BS90: -117.585 | BT90: -117.585 | BU90: 0 | BV90: 0 | BW90: 0 | BX90: -193.628 | BY90: -193.628 | BZ90: 0 | CA90: -245.062 | CB90: -274.177 | CC90: 458.372 | CD90: 458.372 | CE90: 411.54806 | CF90: 361.6939 | CG90: 458.85453 | CH90: 403.02808 | CI90: 403.02808 | CJ90: 383.60871 | CK90: 334.08242 | CL90: 289.43591 | CM90: 263.60044 | CN90: 285.93752 | CO90: 375.91607 | CP90: 844.53214 | CQ90: 1939.0367 | CR90: 3629.4367 | CS90: 5934.8601
A92: TOTAL LIABILITIES AND EQUITY | BS92: 91.409 | BT92: 91.409 | BU92: 0 | BV92: 0 | BW92: 0 | BX92: 136.916 | BY92: 136.916 | BZ92: 0 | CA92: 84.117 | CB92: 257.222 | CC92: 479.512 | CD92: 479.512 | CE92: 432.68806 | CF92: 382.8339 | CG92: 479.99453 | CH92: 424.16808 | CI92: 424.16808 | CJ92: 383.60871 | CK92: 334.08242 | CL92: 289.43591 | CM92: 278.20386 | CN92: 381.3555 | CO92: 544.83695 | CP92: 1132.4704 | CQ92: 2438.1629 | CR92: 4362.4033 | CS92: 6881.9251
A93: Check | BS93: 0 | BT93: 0 | BU93: 0 | BV93: 0 | BW93: 0 | BX93: 0 | BY93: 0 | BZ93: 0 | CA93: 0 | CB93: 0 | CC93: 0 | CD93: 0 | CE93: 0 | CF93: 0 | CG93: 0 | CH93: 0 | CI93: 0 | CJ93: 0 | CK93: 0 | CL93: 0 | CM93: 0 | CN93: 0 | CO93: 0 | CP93: 0 | CQ93: 0 | CR93: 0 | CS93: 0
A97: MPLT Financial Analysis
A99: ($mn) | B99: 2009A | C99: Mar-10A | D99: Jun-10A | E99: Sep-10A | F99: Dec-10A | G99: 2010A | H99: Mar-11A | I99: Jun-11A | J99: Sep-11A | K99: Dec-11A | L99: 2011A | M99: Mar-12A | N99: Jun-12A | O99: Sep-12A | P99: Dec-12A | Q99: 2012A | R99: Mar-13A | S99: Jun-13A | T99: Sep-13A | U99: Dec-13A | V99: 2013A | W99: Mar-14A | X99: Jun-14A | Y99: Sep-14A | Z99: Dec-14A | BO99: 2022A | BT99: 2023A | BU99: Mar-24A | BV99: Jun-24A | BW99: Sep-24A | BX99: Dec-24A | BY99: 2024A | BZ99: Mar-25A | CA99: Jun-25A | CB99: Sep-25A | CC99: Dec-25A | CD99: 2025A | CE99: Mar-26E | CF99: Jun-26E | CG99: Sep-26E | CH99: Dec-26E | CI99: 2026E | CJ99: 2027E | CK99: 2028E | CL99: 2029E | CM99: 2030E | CN99: 2031E | CO99: 2032E | CP99: 2033E | CQ99: 2034E | CR99: 2035E | CS99: 2036E
A101: Total Cash & Equivalents | BS101: 80.003 | BT101: 80.003 | BU101: 0 | BV101: 0 | BW101: 0 | BX101: 109.002 | BY101: 109.002 | BZ101: 0 | CA101: 60.679 | CB101: 227.375 | CC101: 453.096 | CD101: 453.096 | CE101: 406.27206 | CF101: 356.4179 | CG101: 453.57853 | CH101: 397.75208 | CI101: 397.75208 | CJ101: 362.73971 | CK101: 312.21342 | CL101: 266.56691 | CM101: 260.53109 | CN101: 288.68962 | CO101: 383.87245 | CP101: 861.53461 | CQ101: 1972.8653 | CR101: 3682.0034 | CS101: 6004.4985
A102: Total Debt | BS102: 0 | BT102: 0 | BU102: 0 | BV102: 0 | BW102: 0 | BX102: 0 | BY102: 0 | BZ102: 0 | CA102: 0 | CB102: 0 | CC102: 0 | CD102: 0 | CE102: 0 | CF102: 0 | CG102: 0 | CH102: 0 | CI102: 0 | CJ102: 0 | CK102: 0 | CL102: 0 | CM102: 0 | CN102: 0 | CO102: 0 | CP102: 0 | CQ102: 0 | CR102: 0 | CS102: 0
A103: Total Debt / Capital | BS103: 0 | BT103: 0 | BU103: NM | BV103: NM | BW103: NM | BX103: NM | BY103: 0 | BZ103: NM | CA103: NM | CB103: 0 | CC103: 0 | CD103: 0 | CE103: 0 | CF103: 0 | CG103: 0 | CH103: 0 | CI103: 0 | CJ103: 0 | CK103: 0 | CL103: 0 | CM103: 0 | CN103: 0 | CO103: 0 | CP103: 0 | CQ103: 0 | CR103: 0 | CS103: 0
A104: Total Debt / EBITDA | BS104: #DIV/0! | BT104: 0 | BU104: 0 | BV104: 0 | BW104: 0 | BX104: 0 | BY104: 0 | BZ104: 0 | CA104: 0 | CB104: 0 | CC104: 0 | CD104: 0 | CE104: 0 | CF104: 0 | CG104: 0 | CH104: 0 | CI104: 0 | CJ104: 0 | CK104: 0 | CL104: 0 | CM104: 0 | CN104: 0 | CO104: 0 | CP104: 0 | CQ104: 0 | CR104: 0 | CS104: 0
A105: Net Debt | BS105: -80.003 | BT105: -80.003 | BU105: 0 | BV105: 0 | BW105: 0 | BX105: -109.002 | BY105: -109.002 | BZ105: 0 | CA105: -60.679 | CB105: -227.375 | CC105: -453.096 | CD105: -453.096 | CE105: -406.27206 | CF105: -356.4179 | CG105: -453.57853 | CH105: -397.75208 | CI105: -397.75208 | CJ105: -362.73971 | CK105: -312.21342 | CL105: -266.56691 | CM105: -260.53109 | CN105: -288.68962 | CO105: -383.87245 | CP105: -861.53461 | CQ105: -1972.8653 | CR105: -3682.0034 | CS105: -6004.4985
A106: Net Debt / Capital | BS106: NM | BT106: NM | BU106: NM | BV106: NM | BW106: NM | BX106: NM | BY106: NM | BZ106: NM | CA106: NM | CB106: NM | CC106: NM | CD106: NM | CE106: NM | CF106: NM | CG106: NM | CH106: NM | CI106: NM | CJ106: NM | CK106: NM | CL106: NM | CM106: NM | CN106: NM | CO106: NM | CP106: NM | CQ106: NM | CR106: NM | CS106: NM
A108: Cash per share | BS108: 0 | BT108: 121.27727 | BU108: 0 | BV108: 0 | BW108: 0 | BX108: 141.892 | BY108: 148.06473 | BZ108: 0 | CA108: 79.592114 | CB108: 287.40645 | CC108: 14.093637 | CD108: 52.562301 | CE108: 9.5593425 | CF108: 8.1004069 | CG108: 9.345253 | CH108: 8.153044 | CI108: 8.6551841 | CJ108: 6.5952674 | CK108: 5.1003359 | CL108: 3.9533228 | CM108: 3.5377646 | CN108: 3.8936942 | CO108: 5.1427887 | CP108: 11.46529 | CQ108: 26.081316 | CR108: 48.356517 | CS108: 78.343876
A109: Earnings per Share | BS109: 0 | BT109: -84.449778 | BU109: -27.874916 | BV109: -26.17084 | BW109: -25.080321 | BX109: -27.634587 | BY109: -105.38212 | BZ109: -31.586405 | CA109: -36.209237 | CB109: -37.184927 | CC109: -2.4743556 | CD109: -18.694719 | CE109: -1.1487987 | CF109: -1.1785035 | CG109: -1.1298767 | CH109: -1.1853153 | CI109: -4.6424169 | CJ109: -4.1712612 | CK109: -4.3213163 | CL109: -3.9248423 | CM109: -3.338212 | CN109: 0.031521285 | CO109: 0.93751171 | CP109: 5.9701759 | CQ109: 14.204971 | CR109: 21.937711 | CS109: 29.819131
A110: Cash Earnings per Share (1) | BS110: #DIV/0! | BT110: -83.606932 | BU110: -27.874916 | BV110: -25.722205 | BW110: -24.833686 | BX110: -27.38205 | BY110: -104.42991 | BZ110: -31.586405 | CA110: -35.813106 | CB110: -37.013021 | CC110: -2.4700008 | CD110: -18.627667 | CE110: -1.1464457 | CF110: -1.1762308 | CG110: -1.1278163 | CH110: -1.1832655 | CI110: -4.6337128 | CJ110: -4.1621703 | CK110: -4.3049803 | CL110: -3.9100118 | CM110: -3.324633 | CN110: 0.045008761 | CO110: 0.95090884 | CP110: 5.9834839 | CQ110: 14.218191 | CR110: 21.950844 | CS110: 29.832178
A111: Book Value per Share | BS111: #DIV/0! | BT111: -178.24817 | BU111: 0 | BV111: 0 | BW111: 0 | BX111: -252.05284 | BY111: -263.01791 | BZ111: 0 | CA111: -321.44568 | CB111: -346.56509 | CC111: 14.257748 | CD111: 53.174353 | CE111: 9.6834837 | CF111: 8.220316 | CG111: 9.4539565 | CH111: 8.2611904 | CI111: 8.7699911 | CJ111: 6.9747038 | CK111: 5.4575891 | CL111: 4.2924817 | CM111: 3.5794434 | CN111: 3.8565754 | CO111: 5.0361962 | CP111: 11.239021 | CQ111: 25.634102 | CR111: 47.666148 | CS111: 77.435266
A113: Cash Flow from Operations (CFO) | BS113: -52.24 | BT113: -52.24 | BU113: 0 | BV113: -37.473 | BW113: -19.854 | BX113: -21.461 | BY113: -78.788 | BZ113: 0 | CA113: -59.517 | CB113: -31.791 | CC113: -46.829 | CD113: -138.137 | CE113: -46.723943 | CF113: -49.754155 | CG113: -52.739372 | CH113: -55.726455 | CI113: -204.94392 | CJ113: -234.51237 | CK113: -248.52629 | CL113: -243.64651 | CM113: -204.03582 | CN113: 30.158522 | CO113: 97.18283 | CP113: 479.66217 | CQ113: 1113.3306 | CR113: 1711.1381 | CS113: 2324.4951
A114: Cash Flow from Operations / Share | BS114: #DIV/0! | BT114: -79.191089 | BU114: 0 | BV114: -52.536557 | BW114: -26.185565 | BX114: -27.93659 | BY114: -107.02303 | BZ114: 0 | CA114: -78.067929 | CB114: -40.184446 | CC114: -1.4566249 | CD114: -16.024857 | CE114: -1.0993869 | CF114: -1.1307763 | CG114: -1.0866096 | CH114: -1.1422699 | CI114: -4.4596308 | CJ114: -4.2638612 | CK114: -4.0599394 | CL114: -3.6134016 | CM114: -2.7706124 | CN114: 0.40676234 | CO114: 1.3019709 | CP114: 6.3833368 | CQ114: 14.718252 | CR114: 22.472733 | CS114: 30.32892
A115: Cash Realization Ratio (CFO / NI) | BS115: #DIV/0! | BT115: NM | BU115: NM | BV115: NM | BW115: NM | BX115: NM | BY115: NM | BZ115: NM | CA115: NM | CB115: NM | CC115: NM | CD115: NM | CE115: NM | CF115: NM | CG115: NM | CH115: NM | CI115: NM | CJ115: NM | CK115: NM | CL115: NM | CM115: NM | CN115: 12.90437 | CO115: 1.3887516 | CP115: 1.0692041 | CQ115: 1.0361339 | CR115: 1.0243883 | CS115: 1.0170961
A117: Free Cash Flow (FCF) (2) | BS117: -52.702 | BT117: -52.702 | BU117: 0 | BV117: -37.763 | BW117: -20.228 | BX117: -21.567 | BY117: -79.558 | BZ117: 0 | CA117: -59.583 | CB117: -31.822 | CC117: -47.205 | CD117: -138.61 | CE117: -46.823943 | CF117: -49.854155 | CG117: -52.839372 | CH117: -55.826455 | CI117: -205.34392 | CJ117: -235.01237 | CK117: -250.52629 | CL117: -245.64651 | CM117: -206.03582 | CN117: 28.158522 | CO117: 95.18283 | CP117: 477.66217 | CQ117: 1111.3306 | CR117: 1709.1381 | CS117: 2322.4951
A118: Free Cash Flow (FCF) per Share | BS118: #DIV/0! | BT118: -79.891439 | BU118: 0 | BV118: -52.943132 | BW118: -26.678836 | BX118: -28.074574 | BY118: -108.06897 | BZ118: 0 | CA118: -78.1545 | CB118: -40.22363 | CC118: -1.4683204 | CD118: -16.079728 | CE118: -1.1017398 | CF118: -1.133049 | CG118: -1.0886699 | CH118: -1.1443197 | CI118: -4.4683349 | CJ118: -4.2729521 | CK118: -4.0926115 | CL118: -3.6430626 | CM118: -2.7977705 | CN118: 0.37978739 | CO118: 1.2751767 | CP118: 6.3567208 | CQ118: 14.691812 | CR118: 22.446467 | CS118: 30.302825
A119: FCF / Net Income | BS119: #DIV/0! | BT119: NM | BU119: NM | BV119: NM | BW119: NM | BX119: NM | BY119: NM | BZ119: NM | CA119: NM | CB119: NM | CC119: NM | CD119: NM | CE119: NM | CF119: NM | CG119: NM | CH119: NM | CI119: NM | CJ119: NM | CK119: NM | CL119: NM | CM119: NM | CN119: 12.048601 | CO119: 1.3601715 | CP119: 1.064746 | CQ119: 1.0342726 | CR119: 1.0231909 | CS119: 1.016221
A121: DSOs (3) | BT121: #DIV/0! | CM121: 35 | CN121: 35 | CO121: 35 | CP121: 35 | CQ121: 35 | CR121: 35 | CS121: 35
A122: Inventory Turnover (4)
A123: ROE (5) | BT123: 0.94755283 | BY123: 0.49856529 | CD123: -1.2174151 | CI123: -0.49534225 | CJ123: -0.58329174 | CK123: -0.73715915 | CL123: -0.84888125 | CM123: -0.88903911 | CN123: 0.0085056114 | CO123: 0.21146234 | CP123: 0.73516609 | CQ123: 0.77203376 | CR123: 0.59994898 | CS123: 0.47790725
A125: (1) Cash Earnings per Share = (NI + D&A) / FD Shares
A126: (2) FCF = CFO - Cap-ex
A127: (3) DSOs = Average Accounts Receivable / Sales * Days per Period (year = 365 days, quarter = 91.25 days)
A128: (4) Inventory Turnover = COGS / Average Inventory
A129: (5) ROE = Net Income / Average Shareholders' Equity
...

Sheet QTR_GAAP
A4: MPLT GAAP Earnings Reconciliation
A6: ($MM) | B6: Mar-08A | C6: Jun-08A | D6: Sep-08A | E6: Dec-08A | F6: 2008A | G6: Mar-09A | H6: Jun-09A | I6: Sep-09A | J6: Dec-09A | K6: 2009A | L6: Mar-10A | M6: Jun-10A | N6: Sep-10A | O6: Dec-10A | P6: 2010A | Q6: Mar-11A | R6: Jun-11A | S6: Sep-11A | T6: Dec-11A | U6: 2011A | V6: Mar-12A | W6: Jun-12A | X6: Sep-12A | Y6: Dec-12A | Z6: 2012A | AA6: Mar-13A | AB6: Jun-13A | AC6: Sep-13A | AD6: Dec-13A | AE6: 2013A | AF6: Mar-14A | AG6: Jun-14A | AH6: Sep-14A | AI6: Dec-14A | AJ6: 2014A | AK6: Mar-15A | AL6: Jun-15A | AM6: Sep-15A | AN6: Dec-15A | AO6: 2015A | AP6: Mar-16A | AQ6: Jun-16A | AR6: Sep-16A | AS6: Dec-16A | AT6: 2016A | AU6: Mar-17A | AV6: Jun-17A | AW6: Sep-17A | AX6: Dec-17A | AY6: 2017A | AZ6: Mar-18A | BA6: Jun-18A | BB6: Sep-18A | BC6: Dec-18A | BD6: 2018A | BE6: Mar-19A | BF6: Jun-19A | BG6: Sep-19A | BH6: Dec-19A | BI6: 2019A | BJ6: Mar-20A | BK6: Jun-20A | BL6: Sep-20A | BM6: Dec-20A | BN6: 2020A | BO6: Mar-21A | BP6: Jun-21A | BQ6: Sep-21A | BR6: Dec-21A | BS6: 2021A | BT6: Mar-22A | BU6: Jun-22A | BV6: Sep-22A | BW6: Dec-22A | BX6: 2022A | BY6: Mar-23A | BZ6: Jun-23A | CA6: Sep-23A | CB6: Dec-23A | CC6: 2023A | CD6: Mar-24A | CE6: Jun-24A | CF6: Sep-24A | CG6: Dec-24A | CH6: 2024A | CI6: Mar-25A | CJ6: Jun-25A | CK6: Sep-25A | CL6: Dec-25A | CM6: 2025A | CN6: Mar-26E | CO6: Jun-26E | CP6: Sep-26E | CQ6: Dec-26E | CR6: 2026E | CS6: 2027E | CT6: 2028E | CU6: 2029E | CV6: 2030E | CW6: 2031E | CX6: 2032E | CY6: 2033E | CZ6: 2034E | DA6: 2035E | DB6: 2036E
A8: Net Income | AE8: 0 | AF8: 0 | AG8: 0 | AH8: 0 | AI8: 0 | AJ8: 0 | AK8: 0 | AL8: 0 | AM8: 0 | AN8: 0 | AO8: 0 | AP8: 0 | AQ8: 0 | AR8: 0 | AS8: 0 | AT8: 0 | AU8: 0 | AV8: 0 | AW8: 0 | AX8: 0 | AY8: 0 | AZ8: 0 | BA8: 0 | BB8: 0 | BC8: 0 | BD8: 0 | BE8: 0 | BF8: 0 | BG8: 0 | BH8: 0 | BI8: 0 | BJ8: 0 | BK8: 0 | BL8: 0 | BM8: 0 | BN8: 0 | BO8: 0 | BP8: 0 | BQ8: 0 | BR8: 0 | BS8: 0 | BT8: 0 | BU8: 0 | BV8: 0 | BW8: 0 | BX8: 0 | BY8: 0 | BZ8: 0 | CA8: 0 | CB8: 0 | CC8: -55.709 | CD8: -18.667 | CE8: -18.667 | CF8: -19.016 | CG8: -21.229 | CH8: -77.58 | CI8: -24.580667 | CJ8: -27.605 | CK8: -29.418 | CL8: -79.548 | CM8: -161.15167 | CN8: -48.823943 | CO8: -51.854155 | CP8: -54.839372 | CQ8: -57.826455 | CR8: -213.34392 | CS8: -229.41937 | CT8: -264.52629 | CU8: -264.64651 | CV8: -245.83547 | CW8: 2.3370782 | CX8: 69.978553 | CY8: 448.61607 | CZ8: 1074.5046 | DA8: 1670.4 | DB8: 2285.4234
A9: EPS | AE9: 0 | AF9: 0 | AG9: 0 | AH9: 0 | AI9: 0 | AJ9: 0 | AK9: 0 | AL9: 0 | AM9: 0 | AN9: 0 | AO9: 0 | AP9: 0 | AQ9: 0 | AR9: 0 | AS9: 0 | AT9: 0 | AU9: 0 | AV9: 0 | AW9: 0 | AX9: 0 | AY9: 0 | AZ9: 0 | BA9: 0 | BB9: 0 | BC9: 0 | BD9: 0 | BE9: 0 | BF9: 0 | BG9: 0 | BH9: 0 | BI9: 0 | BJ9: 0 | BK9: 0 | BL9: 0 | BM9: 0 | BN9: 0 | BO9: 0 | BP9: 0 | BQ9: 0 | BR9: 0 | BS9: 0 | BT9: 0 | BU9: 0 | BV9: 0 | BW9: 0 | BX9: 0 | BY9: 0 | BZ9: 0 | CA9: 0 | CB9: 0 | CC9: -84.449778 | CD9: -27.874916 | CE9: -26.17084 | CF9: -25.080321 | CG9: -27.634587 | CH9: -105.38212 | CI9: -31.586405 | CJ9: -36.209237 | CK9: -37.184927 | CL9: -2.4743556 | CM9: -18.694719 | CN9: -1.1487987 | CO9: -1.1785035 | CP9: -1.1298767 | CQ9: -1.1853153 | CR9: -4.6424169 | CS9: -4.1712612 | CT9: -4.3213163 | CU9: -3.9248423 | CV9: -3.338212 | CW9: 0.031521285 | CX9: 0.93751171 | CY9: 5.9701759 | CZ9: 14.204971 | DA9: 21.937711 | DB9: 29.819131
A10: Interest add-back
A12: Special Items
A13: Amortization of intangibles | AE13: 0 | AF13: 0 | AG13: 0 | AH13: 0 | AI13: 0 | AJ13: 0 | AK13: 0 | AL13: 0 | AM13: 0 | AN13: 0 | AO13: 0 | AP13: 0 | AQ13: 0 | AR13: 0 | AS13: 0 | AT13: 0 | AU13: 0 | AV13: 0 | AW13: 0 | AX13: 0 | AY13: 0 | AZ13: 0 | BA13: 0 | BB13: 0 | BC13: 0 | BD13: 0 | BE13: 0 | BF13: 0 | BG13: 0 | BH13: 0 | BI13: 0 | BJ13: 0 | BK13: 0 | BL13: 0 | BM13: 0 | BN13: 0 | BO13: 0 | BP13: 0 | BQ13: 0 | BR13: 0 | BS13: 0 | BT13: 0 | BU13: 0 | BV13: 0 | BW13: 0 | BX13: 0 | BY13: 0 | BZ13: 0 | CA13: 0 | CB13: 0 | CC13: 0 | CD13: 0 | CE13: 0 | CF13: 0 | CG13: 0 | CH13: 0 | CI13: 0 | CJ13: 0 | CK13: 0 | CL13: 0 | CM13: 0 | CN13: 0 | CO13: 0 | CP13: 0 | CQ13: 0 | CR13: 0 | CS13: 0 | CT13: 0 | CU13: 0 | CV13: 0 | CW13: 0 | CX13: 0 | CY13: 0 | CZ13: 0 | DA13: 0 | DB13: 0
A14: Deferred financing costs | AE14: 0 | AF14: 0 | AG14: 0 | AH14: 0 | AI14: 0 | AJ14: 0 | AK14: 0 | AL14: 0 | AM14: 0 | AN14: 0 | AO14: 0 | AP14: 0 | AQ14: 0 | AR14: 0 | AS14: 0 | AT14: 0 | AU14: 0 | AV14: 0 | AW14: 0 | AX14: 0 | AY14: 0 | AZ14: 0 | BA14: 0 | BB14: 0 | BC14: 0 | BD14: 0 | BE14: 0 | BF14: 0 | BG14: 0 | BH14: 0 | BI14: 0 | BJ14: 0 | BK14: 0 | BL14: 0 | BM14: 0 | BN14: 0 | BO14: 0 | BP14: 0 | BQ14: 0 | BR14: 0 | BS14: 0 | BT14: 0 | BU14: 0 | BV14: 0 | BW14: 0 | BX14: 0 | BY14: 0 | BZ14: 0 | CA14: 0 | CB14: 0 | CC14: 0 | CD14: 0 | CE14: 0 | CF14: 0 | CG14: 0 | CH14: 0 | CI14: 0 | CJ14: 0 | CK14: 0 | CL14: 0 | CM14: 0 | CN14: 0 | CO14: 0 | CP14: 0 | CQ14: 0 | CR14: 0 | CS14: 0 | CT14: 0 | CU14: 0 | CV14: 0 | CW14: 0 | CX14: 0 | CY14: 0 | CZ14: 0 | DA14: 0 | DB14: 0
A15: R&D payments | AE15: 0 | AF15: 0 | AG15: 0 | AH15: 0 | AI15: 0 | AJ15: 0 | AK15: 0 | AL15: 0 | AM15: 0 | AN15: 0 | AO15: 0 | AP15: 0 | AQ15: 0 | AR15: 0 | AS15: 0 | AT15: 0 | AU15: 0 | AV15: 0 | AW15: 0 | AX15: 0 | AY15: 0 | AZ15: 0 | BA15: 0 | BB15: 0 | BC15: 0 | BD15: 0 | BE15: 0 | BF15: 0 | BG15: 0 | BH15: 0 | BI15: 0 | BJ15: 0 | BK15: 0 | BL15: 0 | BM15: 0 | BN15: 0 | BO15: 0 | BP15: 0 | BQ15: 0 | BR15: 0 | BS15: 0 | BT15: 0 | BU15: 0 | BV15: 0 | BW15: 0 | BX15: 0 | BY15: 0 | BZ15: 0 | CA15: 0 | CB15: 0 | CC15: 0 | CD15: 0 | CE15: 0 | CF15: 0 | CG15: 0 | CH15: 0 | CI15: 0 | CJ15: 0 | CK15: 0 | CL15: 0 | CM15: 0 | CN15: 0 | CO15: 0 | CP15: 0 | CQ15: 0 | CR15: 0 | CS15: 0 | CT15: 0 | CU15: 0 | CV15: 0 | CW15: 0 | CX15: 0 | CY15: 0 | CZ15: 0 | DA15: 0 | DB15: 0
A16: Other | AE16: 0 | AF16: 0 | AG16: 0 | AH16: 0 | AI16: 0 | AJ16: 0 | AK16: 0 | AL16: 0 | AM16: 0 | AN16: 0 | AO16: 0 | AP16: 0 | AQ16: 0 | AR16: 0 | AS16: 0 | AT16: 0 | AU16: 0 | AV16: 0 | AW16: 0 | AX16: 0 | AY16: 0 | AZ16: 0 | BA16: 0 | BB16: 0 | BC16: 0 | BD16: 0 | BE16: 0 | BF16: 0 | BG16: 0 | BH16: 0 | BI16: 0 | BJ16: 0 | BK16: 0 | BL16: 0 | BM16: 0 | BN16: 0 | BO16: 0 | BP16: 0 | BQ16: 0 | BR16: 0 | BS16: 0 | BT16: 0 | BU16: 0 | BV16: 0 | BW16: 0 | BX16: 0 | BY16: 0 | BZ16: 0 | CA16: 0 | CB16: 0 | CC16: 0 | CD16: 0 | CE16: 0 | CF16: 0 | CG16: 0 | CH16: 0 | CI16: 0 | CJ16: 0 | CK16: 0 | CL16: 0 | CM16: 0 | CN16: 0 | CO16: 0 | CP16: 0 | CQ16: 0 | CR16: 0 | CS16: 0 | CT16: 0 | CU16: 0 | CV16: 0 | CW16: 0 | CX16: 0 | CY16: 0 | CZ16: 0 | DA16: 0 | DB16: 0
A17: Income tax benefit (expense) | AE17: 0 | AF17: 0 | AG17: 0 | AH17: 0 | AI17: 0 | AJ17: 0 | AK17: 0 | AL17: 0 | AM17: 0 | AN17: 0 | AO17: 0 | AP17: 0 | AQ17: 0 | AR17: 0 | AS17: 0 | AT17: 0 | AU17: 0 | AV17: 0 | AW17: 0 | AX17: 0 | AY17: 0 | AZ17: 0 | BA17: 0 | BB17: 0 | BC17: 0 | BD17: 0 | BE17: 0 | BF17: 0 | BG17: 0 | BH17: 0 | BI17: 0 | BJ17: 0 | BK17: 0 | BL17: 0 | BM17: 0 | BN17: 0 | BO17: 0 | BP17: 0 | BQ17: 0 | BR17: 0 | BS17: 0 | BT17: 0 | BU17: 0 | BV17: 0 | BW17: 0 | BX17: 0 | BY17: 0 | BZ17: 0 | CA17: 0 | CB17: 0 | CC17: 0 | CD17: 0 | CE17: 0 | CF17: 0 | CG17: 0 | CH17: 0 | CI17: 0 | CJ17: 0 | CK17: 0 | CL17: 0 | CM17: 0 | CN17: 0 | CO17: 0 | CP17: 0 | CQ17: 0 | CR17: 0 | CS17: 0 | CT17: 0 | CU17: 0 | CV17: 0 | CW17: 0 | CX17: 0 | CY17: 0 | CZ17: 0 | DA17: 0 | DB17: 0
A18: Net Income - GAAP | AE18: 0 | AF18: 0 | AG18: 0 | AH18: 0 | AI18: 0 | AJ18: 0 | AK18: 0 | AL18: 0 | AM18: 0 | AN18: 0 | AO18: 0 | AP18: 0 | AQ18: 0 | AR18: 0 | AS18: 0 | AT18: 0 | AU18: 0 | AV18: 0 | AW18: 0 | AX18: 0 | AY18: 0 | AZ18: 0 | BA18: 0 | BB18: 0 | BC18: 0 | BD18: 0 | BE18: 0 | BF18: 0 | BG18: 0 | BH18: 0 | BI18: 0 | BJ18: 0 | BK18: 0 | BL18: 0 | BM18: 0 | BN18: 0 | BO18: 0 | BP18: 0 | BQ18: 0 | BR18: 0 | BS18: 0 | BT18: 0 | BU18: 0 | BV18: 0 | BW18: 0 | BX18: 0 | BY18: 0 | BZ18: 0 | CA18: 0 | CB18: 0 | CC18: -55.709 | CD18: -18.667 | CE18: -18.667 | CF18: -19.016 | CG18: -21.229 | CH18: -77.58 | CI18: -24.580667 | CJ18: -27.605 | CK18: -29.418 | CL18: -79.548 | CM18: -161.15167 | CN18: -48.823943 | CO18: -51.854155 | CP18: -54.839372 | CQ18: -57.826455 | CR18: -213.34392 | CS18: -229.41937 | CT18: -264.52629 | CU18: -264.64651 | CV18: -245.83547 | CW18: 2.3370782 | CX18: 69.978553 | CY18: 448.61607 | CZ18: 1074.5046 | DA18: 1670.4 | DB18: 2285.4234
A20: Diluted Net Income (GAAP) | AE20: 0 | AF20: 0 | AG20: 0 | AH20: 0 | AI20: 0 | AJ20: 0 | AK20: 0 | AL20: 0 | AM20: 0 | AN20: 0 | AO20: 0 | AP20: 0 | AQ20: 0 | AR20: 0 | AS20: 0 | AT20: 0 | AU20: 0 | AV20: 0 | AW20: 0 | AX20: 0 | AY20: 0 | AZ20: 0 | BA20: 0 | BB20: 0 | BC20: 0 | BD20: 0 | BE20: 0 | BF20: 0 | BG20: 0 | BH20: 0 | BI20: 0 | BJ20: 0 | BK20: 0 | BL20: 0 | BM20: 0 | BN20: 0 | BO20: 0 | BP20: 0 | BQ20: 0 | BR20: 0 | BS20: 0 | BT20: 0 | BU20: 0 | BV20: 0 | BW20: 0 | BX20: 0 | BY20: 0 | BZ20: 0 | CA20: 0 | CB20: 0 | CC20: -55.709 | CD20: -18.667 | CE20: -18.667 | CF20: -19.016 | CG20: -21.229 | CH20: -77.58 | CI20: -24.580667 | CJ20: -27.605 | CK20: -29.418 | CL20: -79.548 | CM20: -161.15167 | CN20: -48.823943 | CO20: -51.854155 | CP20: -54.839372 | CQ20: -57.826455 | CR20: -213.34392 | CS20: -229.41937 | CT20: -264.52629 | CU20: -264.64651 | CV20: -245.83547 | CW20: 2.3370782 | CX20: 69.978553 | CY20: 448.61607 | CZ20: 1074.5046 | DA20: 1670.4 | DB20: 2285.4234
A21: GAAP EPS | AE21: #DIV/0! | AF21: #DIV/0! | AG21: #DIV/0! | AH21: #DIV/0! | AI21: #DIV/0! | AJ21: #DIV/0! | AK21: #DIV/0! | AL21: #DIV/0! | AM21: #DIV/0! | AN21: #DIV/0! | AO21: #DIV/0! | AP21: #DIV/0! | AQ21: #DIV/0! | AR21: #DIV/0! | AS21: #DIV/0! | AT21: #DIV/0! | AU21: #DIV/0! | AV21: #DIV/0! | AW21: #DIV/0! | AX21: #DIV/0! | AY21: #DIV/0! | AZ21: #DIV/0! | BA21: #DIV/0! | BB21: #DIV/0! | BC21: #DIV/0! | BD21: #DIV/0! | BE21: #DIV/0! | BF21: #DIV/0! | BG21: #DIV/0! | BH21: #DIV/0! | BI21: #DIV/0! | BJ21: #DIV/0! | BK21: #DIV/0! | BL21: #DIV/0! | BM21: #DIV/0! | BN21: #DIV/0! | BO21: #DIV/0! | BP21: #DIV/0! | BQ21: #DIV/0! | BR21: #DIV/0! | BS21: #DIV/0! | BT21: #DIV/0! | BU21: #DIV/0! | BV21: #DIV/0! | BW21: #DIV/0! | BX21: #DIV/0! | BY21: #DIV/0! | BZ21: #DIV/0! | CA21: #DIV/0! | CB21: #DIV/0! | CC21: -84.449778 | CD21: -27.874916 | CE21: -26.17084 | CF21: -25.080321 | CG21: -27.634587 | CH21: -105.38212 | CI21: -31.586405 | CJ21: -36.209237 | CK21: -37.184927 | CL21: -2.4743556 | CM21: -18.694719 | CN21: -1.1487987 | CO21: -1.1785035 | CP21: -1.1298767 | CQ21: -1.1853153 | CR21: -4.6424169 | CS21: -4.1712612 | CT21: -4.3213163 | CU21: -3.9248423 | CV21: -3.338212 | CW21: 0.031521285 | CX21: 0.93751171 | CY21: 5.9701759 | CZ21: 14.204971 | DA21: 21.937711 | DB21: 29.819131
A23: Diluted Shares Outstanding | AE23: 0 | AF23: 0 | AG23: 0 | AH23: 0 | AI23: 0 | AJ23: 0 | AK23: 0 | AL23: 0 | AM23: 0 | AN23: 0 | AO23: 0 | AP23: 0 | AQ23: 0 | AR23: 0 | AS23: 0 | AT23: 0 | AU23: 0 | AV23: 0 | AW23: 0 | AX23: 0 | AY23: 0 | AZ23: 0 | BA23: 0 | BB23: 0 | BC23: 0 | BD23: 0 | BE23: 0 | BF23: 0 | BG23: 0 | BH23: 0 | BI23: 0 | BJ23: 0 | BK23: 0 | BL23: 0 | BM23: 0 | BN23: 0 | BO23: 0 | BP23: 0 | BQ23: 0 | BR23: 0 | BS23: 0 | BT23: 0 | BU23: 0 | BV23: 0 | BW23: 0 | BX23: 0 | BY23: 0 | BZ23: 0 | CA23: 0 | CB23: 0 | CC23: 0.65967018 | CD23: 0.66967018 | CE23: 0.71327476 | CF23: 0.758204 | CG23: 0.768204 | CH23: 0.736178 | CI23: 0.778204 | CJ23: 0.76237452 | CK23: 0.791127 | CL23: 32.148977 | CM23: 8.6201706 | CN23: 42.5 | CO23: 44 | CP23: 48.535714 | CQ23: 48.785714 | CR23: 45.955357 | CS23: 55 | CT23: 61.214286 | CU23: 67.428571 | CV23: 73.642857 | CW23: 74.142857 | CX23: 74.642857 | CY23: 75.142857 | CZ23: 75.642857 | DA23: 76.142857 | DB23: 76.642857

Sheet Product NPV-old
A4: Product NPV Analysis
C7: 2005E | D7: 2006E | E7: 2007E | F7: 2008E | G7: 2009E | H7: 2010E | I7: 2011E | J7: 2012E | K7: 2013E | L7: 2014E | M7: 2014E
A8: Years | C8: 1 | D8: =C8+1 -> 2 | E8: =D8+1 -> 3 | F8: =E8+1 -> 4 | G8: =F8+1 -> 5 | H8: =G8+1 -> 6 | I8: =H8+1 -> 7 | J8: =I8+1 -> 8 | K8: =J8+1 -> 9 | ... M8: =L8+1 -> 11
A9: Provigil Franchise:
A10: Provigil sales | C10: ='QTR-REV'!#REF! -> #REF! | D10: ='QTR-REV'!#REF! -> #REF! | E10: ='QTR-REV'!#REF! -> #REF! | F10: ='QTR-REV'!#REF! -> #REF! | G10: ='QTR-REV'!#REF! -> #REF! | H10: =#REF! -> #REF! | I10: =#REF! -> #REF! | J10: =#REF! -> #REF! | K10: =#REF! -> #REF! | L10: =#REF! -> #REF! | M10: =#REF! -> #REF!
A11: Attenace sales | C11: ='QTR-REV'!#REF! -> #REF! | D11: ='QTR-REV'!#REF! -> #REF! | E11: ='QTR-REV'!#REF! -> #REF! | F11: ='QTR-REV'!#REF! -> #REF! | G11: ='QTR-REV'!#REF! -> #REF! | H11: =#REF! -> #REF! | I11: =#REF! -> #REF! | J11: =#REF! -> #REF! | K11: =#REF! -> #REF! | L11: =#REF! -> #REF! | M11: =#REF! -> #REF!
A12: Nuvigil sales | C12: ='QTR-REV'!#REF! -> #REF! | D12: ='QTR-REV'!#REF! -> #REF! | E12: ='QTR-REV'!#REF! -> #REF! | F12: ='QTR-REV'!#REF! -> #REF! | G12: ='QTR-REV'!#REF! -> #REF! | H12: =#REF! -> #REF! | I12: =#REF! -> #REF! | J12: =#REF! -> #REF! | K12: =#REF! -> #REF! | L12: =#REF! -> #REF! | M12: =#REF! -> #REF!
A13: Total Provigil Franchise | C13: =SUM(C10:C12) -> #REF! | D13: =SUM(D10:D12) -> #REF! | E13: =SUM(E10:E12) -> #REF! | F13: =SUM(F10:F12) -> #REF! | G13: =SUM(G10:G12) -> #REF! | H13: =SUM(H10:H12) -> #REF! | I13: =SUM(I10:I12) -> #REF! | J13: =SUM(J10:J12) -> #REF! | ... M13: =SUM(M10:M12) -> #REF!
A15: Gross profit | B15: ='QTR-REV'!#REF! -> #REF! | C15: =C13*$B$15 -> #REF! | D15: =D13*$B$15 -> #REF! | E15: =E13*$B$15 -> #REF! | F15: =F13*$B$15 -> #REF! | G15: =G13*$B$15 -> #REF! | H15: =H13*$B$15 -> #REF! | I15: =I13*$B$15 -> #REF! | J15: =J13*$B$15 -> #REF! | ... M15: =M13*$B$15 -> #REF!
A16: SG&A expense | B16: 0.45 | C16: ='QTR-EPS'!#REF!*$B$16 -> #REF! | D16: ='QTR-EPS'!#REF!*$B$16 -> #REF! | E16: ='QTR-EPS'!#REF!*$B$16 -> #REF! | F16: ='QTR-EPS'!F12*$B$16 -> 0 | G16: ='QTR-EPS'!K12*$B$16 -> 0 | H16: =G16*1.03 -> 0 | I16: =H16*1.03 -> 0 | J16: =I16*1.03 -> 0 | K16: =J16*1.03 -> 0 | L16: =K16*1.03 -> 0 | M16: =L16*1.03 -> 0
A17: R&D expense | B17: 0.5 | C17: ='QTR-EPS'!#REF!*$B$17 -> #REF! | D17: ='QTR-EPS'!#REF!*$B$17 -> #REF! | E17: ='QTR-EPS'!#REF!*$B$17 -> #REF! | F17: ='QTR-EPS'!F13*$B$17 -> 0 | G17: ='QTR-EPS'!K13*$B$17 -> 0 | H17: =G17*1.03 -> 0 | I17: =H17*1.03 -> 0 | J17: =I17*1.03 -> 0 | K17: =J17*1.03 -> 0 | L17: =K17*1.03 -> 0 | M17: =L17*1.03 -> 0
A18: Other expense | C18: 0 | D18: =C18*1.03 -> 0 | E18: =D18*1.03 -> 0 | F18: =E18*1.03 -> 0 | G18: =F18*1.03 -> 0 | H18: =G18*1.03 -> 0 | I18: =H18*1.03 -> 0 | J18: =I18*1.03 -> 0 | K18: =J18*1.03 -> 0 | ... M18: =L18*1.03 -> 0
A19: Operating profit | C19: =C15-SUM(C16:C18) -> #REF! | D19: =D15-SUM(D16:D18) -> #REF! | E19: =E15-SUM(E16:E18) -> #REF! | F19: =F15-SUM(F16:F18) -> #REF! | G19: =G15-SUM(G16:G18) -> #REF! | H19: =H15-SUM(H16:H18) -> #REF! | I19: =I15-SUM(I16:I18) -> #REF! | J19: =J15-SUM(J16:J18) -> #REF! | ... M19: =M15-SUM(M16:M18) -> #REF!
A21: Taxes | B21: ='QTR-EPS'!#REF! -> #REF! | C21: =C19*$B21 -> #REF! | D21: =D19*$B21 -> #REF! | E21: =E19*$B21 -> #REF! | F21: =F19*$B21 -> #REF! | G21: =G19*$B21 -> #REF! | H21: =H19*$B21 -> #REF! | I21: =I19*$B21 -> #REF! | J21: =J19*$B21 -> #REF! | ... M21: =M19*$B21 -> #REF!
A22: Net income | C22: =C19-C21 -> #REF! | D22: =D19-D21 -> #REF! | E22: =E19-E21 -> #REF! | F22: =F19-F21 -> #REF! | G22: =G19-G21 -> #REF! | H22: =H19-H21 -> #REF! | I22: =I19-I21 -> #REF! | J22: =J19-J21 -> #REF! | ... M22: =M19-M21 -> #REF!
A24: NPV | B24: 0.1 | C24: =C22/(1+$B24)^C$8 -> #REF! | D24: =D22/(1+$B24)^D$8 -> #REF! | E24: =E22/(1+$B24)^E$8 -> #REF! | F24: =F22/(1+$B24)^F$8 -> #REF! | G24: =G22/(1+$B24)^G$8 -> #REF! | H24: =H22/(1+$B24)^H$8 -> #REF! | I24: =I22/(1+$B24)^I$8 -> #REF! | J24: =J22/(1+$B24)^J$8 -> #REF! | ... M24: =M22/(1+$B24)^M$8 -> #REF!
A26: Actiq Franchise:
A27: Actiq | C27: ='QTR-REV'!#REF! -> #REF! | D27: ='QTR-REV'!#REF! -> #REF! | E27: ='QTR-REV'!#REF! -> #REF! | F27: ='QTR-REV'!#REF! -> #REF! | G27: ='QTR-REV'!#REF! -> #REF! | H27: =#REF! -> #REF! | I27: =#REF! -> #REF! | J27: =#REF! -> #REF! | K27: =#REF! -> #REF! | L27: =#REF! -> #REF! | M27: =#REF! -> #REF!
A28: OraVescent Fentanyl | C28: ='QTR-REV'!#REF! -> #REF! | D28: ='QTR-REV'!#REF! -> #REF! | E28: ='QTR-REV'!#REF! -> #REF! | F28: ='QTR-REV'!#REF! -> #REF! | G28: ='QTR-REV'!#REF! -> #REF! | H28: =#REF! -> #REF! | I28: =#REF! -> #REF! | J28: =#REF! -> #REF! | K28: =#REF! -> #REF! | L28: =#REF! -> #REF! | M28: =#REF! -> #REF!
A29: Total Actiq Franchise | C29: =SUM(C27:C28) -> #REF! | D29: =SUM(D27:D28) -> #REF! | E29: =SUM(E27:E28) -> #REF! | F29: =SUM(F27:F28) -> #REF! | G29: =SUM(G27:G28) -> #REF! | H29: =SUM(H27:H28) -> #REF! | I29: =SUM(I27:I28) -> #REF! | J29: =SUM(J27:J28) -> #REF! | ... M29: =SUM(M27:M28) -> #REF!
A31: Gross profit - Actiq | B31: ='QTR-REV'!#REF! -> #REF! | C31: =C27*$B$31 -> #REF! | D31: =D27*$B$31 -> #REF! | E31: =E27*$B$31 -> #REF! | F31: =F27*$B$31 -> #REF! | G31: =G27*$B$31 -> #REF! | H31: =H27*$B$31 -> #REF! | I31: =I27*$B$31 -> #REF! | J31: =J27*$B$31 -> #REF! | ... M31: =M27*$B$31 -> #REF!
A32: Gross profit - OVF | B32: ='QTR-REV'!#REF! -> #REF! | C32: =C28*$B$32 -> #REF! | D32: =D28*$B$32 -> #REF! | E32: =E28*$B$32 -> #REF! | F32: =F28*$B$32 -> #REF! | G32: =G28*$B$32 -> #REF! | H32: =H28*$B$32 -> #REF! | I32: =I28*$B$32 -> #REF! | J32: =J28*$B$32 -> #REF! | ... M32: =M28*$B$32 -> #REF!
A33: SG&A expense | B33: 0.35 | C33: ='QTR-EPS'!#REF!*$B$33 -> #REF! | D33: ='QTR-EPS'!#REF!*$B$33 -> #REF! | E33: ='QTR-EPS'!#REF!*$B$33 -> #REF! | F33: ='QTR-EPS'!F12*$B$33 -> 0 | G33: ='QTR-EPS'!K12*$B$33 -> 0 | H33: =G33*1.03 -> 0 | I33: =H33*1.03 -> 0 | J33: =I33*1.03 -> 0 | K33: =J33*1.03 -> 0 | L33: =K33*1.03 -> 0 | M33: =L33*1.03 -> 0
A34: R&D expense | B34: 0.35 | C34: ='QTR-EPS'!#REF!*$B$34 -> #REF! | D34: ='QTR-EPS'!#REF!*$B$34 -> #REF! | E34: ='QTR-EPS'!#REF!*$B$34 -> #REF! | F34: ='QTR-EPS'!F13*$B$34 -> 0 | G34: ='QTR-EPS'!K13*$B$34 -> 0 | H34: =G34*1.03 -> 0 | I34: =H34*1.03 -> 0 | J34: =I34*1.03 -> 0 | K34: =J34*1.03 -> 0 | L34: =K34*1.03 -> 0 | M34: =L34*1.03 -> 0
A35: Other expense | C35: 0 | D35: =C35*1.03 -> 0 | E35: =D35*1.03 -> 0 | F35: =E35*1.03 -> 0 | G35: =F35*1.03 -> 0 | H35: =G35*1.03 -> 0 | I35: =H35*1.03 -> 0 | J35: =I35*1.03 -> 0 | K35: =J35*1.03 -> 0 | ... M35: =L35*1.03 -> 0
A36: Operating profit | C36: =SUM(C31,C32)-SUM(C33:C35) -> #REF! | D36: =SUM(D31,D32)-SUM(D33:D35) -> #REF! | E36: =SUM(E31,E32)-SUM(E33:E35) -> #REF! | F36: =SUM(F31,F32)-SUM(F33:F35) -> #REF! | G36: =SUM(G31,G32)-SUM(G33:G35) -> #REF! | H36: =SUM(H31,H32)-SUM(H33:H35) -> #REF! | I36: =SUM(I31,I32)-SUM(I33:I35) -> #REF! | J36: =SUM(J31,J32)-SUM(J33:J35) -> #REF! | ... M36: =SUM(M31,M32)-SUM(M33:M35) -> #REF!
A38: Taxes | B38: ='QTR-EPS'!#REF! -> #REF! | C38: =C36*$B38 -> #REF! | D38: =D36*$B38 -> #REF! | E38: =E36*$B38 -> #REF! | F38: =F36*$B38 -> #REF! | G38: =G36*$B38 -> #REF! | H38: =H36*$B38 -> #REF! | I38: =I36*$B38 -> #REF! | J38: =J36*$B38 -> #REF! | ... M38: =M36*$B38 -> #REF!
A39: Net income | C39: =C36-C38 -> #REF! | D39: =D36-D38 -> #REF! | E39: =E36-E38 -> #REF! | F39: =F36-F38 -> #REF! | G39: =G36-G38 -> #REF! | H39: =H36-H38 -> #REF! | I39: =I36-I38 -> #REF! | J39: =J36-J38 -> #REF! | ... M39: =M36-M38 -> #REF!
A41: NPV | B41: 0.1 | C41: =C39/(1+$B41)^C$8 -> #REF! | D41: =D39/(1+$B41)^D$8 -> #REF! | E41: =E39/(1+$B41)^E$8 -> #REF! | F41: =F39/(1+$B41)^F$8 -> #REF! | G41: =G39/(1+$B41)^G$8 -> #REF! | H41: =H39/(1+$B41)^H$8 -> #REF! | I41: =I39/(1+$B41)^I$8 -> #REF! | J41: =J39/(1+$B41)^J$8 -> #REF! | ... M41: =M39/(1+$B41)^M$8 -> #REF!
A43: Gabitril:
A44: Gabitril sales | C44: ='QTR-REV'!#REF! -> #REF! | D44: ='QTR-REV'!#REF! -> #REF! | E44: ='QTR-REV'!#REF! -> #REF! | F44: ='QTR-REV'!#REF! -> #REF! | G44: ='QTR-REV'!#REF! -> #REF! | H44: =#REF! -> #REF! | I44: =#REF! -> #REF! | J44: =#REF! -> #REF! | K44: =#REF! -> #REF! | L44: =#REF! -> #REF! | M44: =#REF! -> #REF!
A46: Gross profit | B46: ='QTR-REV'!#REF! -> #REF! | C46: =C44*$B$46 -> #REF! | D46: =D44*$B$46 -> #REF! | E46: =E44*$B$46 -> #REF! | F46: =F44*$B$46 -> #REF! | G46: =G44*$B$46 -> #REF! | H46: =H44*$B$15 -> #REF! | I46: =I44*$B$15 -> #REF! | J46: =J44*$B$15 -> #REF! | K46: =K44*$B$15 -> #REF! | L46: =L44*$B$15 -> #REF! | M46: =M44*$B$15 -> #REF!
A47: SG&A expense | B47: 0.1 | C47: ='QTR-EPS'!#REF!*$B$47 -> #REF! | D47: ='QTR-EPS'!#REF!*$B$47 -> #REF! | E47: ='QTR-EPS'!#REF!*$B$47 -> #REF! | F47: ='QTR-EPS'!F12*$B$47 -> 0 | G47: ='QTR-EPS'!K12*$B$47 -> 0 | H47: =G47*1.03 -> 0 | I47: =H47*1.03 -> 0 | J47: =I47*1.03 -> 0 | K47: =J47*1.03 -> 0 | L47: =K47*1.03 -> 0 | M47: =L47*1.03 -> 0
A48: R&D expense | B48: =1-B17-B34 -> 0.15 | C48: ='QTR-EPS'!#REF!*$B$48 -> #REF! | D48: ='QTR-EPS'!#REF!*$B$48 -> #REF! | E48: ='QTR-EPS'!#REF!*$B$48 -> #REF! | F48: ='QTR-EPS'!F13*$B$48 -> 0 | G48: ='QTR-EPS'!K13*$B$48 -> 0 | H48: =G48*1.03 -> 0 | I48: =H48*1.03 -> 0 | J48: =I48*1.03 -> 0 | K48: =J48*1.03 -> 0 | L48: =K48*1.03 -> 0 | M48: =L48*1.03 -> 0
A49: Other expense | C49: 0 | D49: =C49*1.03 -> 0 | E49: =D49*1.03 -> 0 | F49: =E49*1.03 -> 0 | G49: =F49*1.03 -> 0 | H49: =G49*1.03 -> 0 | I49: =H49*1.03 -> 0 | J49: =I49*1.03 -> 0 | K49: =J49*1.03 -> 0 | ... M49: =L49*1.03 -> 0
A50: Operating profit | C50: =C46-SUM(C47:C49) -> #REF! | D50: =D46-SUM(D47:D49) -> #REF! | E50: =E46-SUM(E47:E49) -> #REF! | F50: =F46-SUM(F47:F49) -> #REF! | G50: =G46-SUM(G47:G49) -> #REF! | H50: =H46-SUM(H47:H49) -> #REF! | I50: =I46-SUM(I47:I49) -> #REF! | J50: =J46-SUM(J47:J49) -> #REF! | ... M50: =M46-SUM(M47:M49) -> #REF!
A52: Taxes | B52: ='QTR-EPS'!#REF! -> #REF! | C52: =C50*$B52 -> #REF! | D52: =D50*$B52 -> #REF! | E52: =E50*$B52 -> #REF! | F52: =F50*$B52 -> #REF! | G52: =G50*$B52 -> #REF! | H52: =H50*$B52 -> #REF! | I52: =I50*$B52 -> #REF! | J52: =J50*$B52 -> #REF! | ... M52: =M50*$B52 -> #REF!
A53: Net income | C53: =C50-C52 -> #REF! | D53: =D50-D52 -> #REF! | E53: =E50-E52 -> #REF! | F53: =F50-F52 -> #REF! | G53: =G50-G52 -> #REF! | H53: =H50-H52 -> #REF! | I53: =I50-I52 -> #REF! | J53: =J50-J52 -> #REF! | ... M53: =M50-M52 -> #REF!
A55: NPV | B55: 0.1 | C55: =C53/(1+$B55)^C$8 -> #REF! | D55: =D53/(1+$B55)^D$8 -> #REF! | E55: =E53/(1+$B55)^E$8 -> #REF! | F55: =F53/(1+$B55)^F$8 -> #REF! | G55: =G53/(1+$B55)^G$8 -> #REF! | H55: =H53/(1+$B55)^H$8 -> #REF! | I55: =I53/(1+$B55)^I$8 -> #REF! | J55: =J53/(1+$B55)^J$8 -> #REF! | ... M55: =M53/(1+$B55)^M$8 -> #REF!
A57: Other Sales (Group Lafon, CIMA): | H57: 0 | I57: 0 | J57: 0 | K57: 0 | L57: 0 | M57: 0
A58: Other Sales | C58: ='QTR-REV'!#REF! -> #REF! | D58: ='QTR-REV'!#REF! -> #REF! | E58: ='QTR-REV'!#REF! -> #REF! | F58: ='QTR-REV'!#REF! -> #REF! | G58: ='QTR-REV'!#REF! -> #REF! | H58: =G58*(1+H57) -> #REF! | I58: =H58*(1+I57) -> #REF! | J58: =I58*(1+J57) -> #REF! | K58: =J58*(1+K57) -> #REF! | L58: =K58*(1+L57) -> #REF! | M58: =L58*(1+M57) -> #REF!
A59: Gross profit | B59: ='QTR-REV'!#REF! -> #REF! | C59: =C58*$B$59 -> #REF! | D59: =D58*$B$59 -> #REF! | E59: =E58*$B$59 -> #REF! | F59: =F58*$B$59 -> #REF! | G59: =G58*$B$59 -> #REF! | H59: =H58*$B$59 -> #REF! | I59: =I58*$B$59 -> #REF! | J59: =J58*$B$59 -> #REF! | ... M59: =M58*$B$59 -> #REF!
A60: SG&A expense | B60: 0.05 | C60: ='QTR-EPS'!#REF!*$B$60 -> #REF! | D60: ='QTR-EPS'!#REF!*$B$60 -> #REF! | E60: ='QTR-EPS'!#REF!*$B$60 -> #REF! | F60: ='QTR-EPS'!F12*$B$60 -> 0 | G60: ='QTR-EPS'!K12*$B$60 -> 0 | H60: =G60*1.03 -> 0 | I60: =H60*1.03 -> 0 | J60: =I60*1.03 -> 0 | K60: =J60*1.03 -> 0 | L60: =K60*1.03 -> 0 | M60: =L60*1.03 -> 0
A61: Other expense | C61: 0 | D61: =C61*1.03 -> 0 | E61: =D61*1.03 -> 0 | F61: =E61*1.03 -> 0 | G61: =F61*1.03 -> 0 | H61: =G61*1.03 -> 0 | I61: =H61*1.03 -> 0 | J61: =I61*1.03 -> 0 | K61: =J61*1.03 -> 0 | ... M61: =L61*1.03 -> 0
A62: Operating profit | C62: =C59-SUM(C60:C61) -> #REF! | D62: =D59-SUM(D60:D61) -> #REF! | E62: =E59-SUM(E60:E61) -> #REF! | F62: =F59-SUM(F60:F61) -> #REF! | G62: =G59-SUM(G60:G61) -> #REF! | H62: =H59-SUM(H60:H61) -> #REF! | I62: =I59-SUM(I60:I61) -> #REF! | J62: =J59-SUM(J60:J61) -> #REF! | ... M62: =M59-SUM(M60:M61) -> #REF!
H63: 0 | I63: 0 | J63: 0 | K63: 0 | L63: 0 | M63: 0
A64: Taxes | B64: ='QTR-EPS'!#REF! -> #REF! | C64: =C62*$B64 -> #REF! | D64: =D62*$B64 -> #REF! | E64: =E62*$B64 -> #REF! | F64: =F62*$B64 -> #REF! | G64: =G62*$B64 -> #REF! | H64: =H62*$B64 -> #REF! | I64: =I62*$B64 -> #REF! | J64: =J62*$B64 -> #REF! | ... M64: =M62*$B64 -> #REF!
A65: Net income | C65: =C62-C64 -> #REF! | D65: =D62-D64 -> #REF! | E65: =E62-E64 -> #REF! | F65: =F62-F64 -> #REF! | G65: =G62-G64 -> #REF! | H65: =H62-H64 -> #REF! | I65: =I62-I64 -> #REF! | J65: =J62-J64 -> #REF! | ... M65: =M62-M64 -> #REF!
A67: NPV | B67: 0.1 | C67: =C65/(1+$B67)^C$8 -> #REF! | D67: =D65/(1+$B67)^D$8 -> #REF! | E67: =E65/(1+$B67)^E$8 -> #REF! | F67: =F65/(1+$B67)^F$8 -> #REF! | G67: =G65/(1+$B67)^G$8 -> #REF! | H67: =H65/(1+$B67)^H$8 -> #REF! | I67: =I65/(1+$B67)^I$8 -> #REF! | J67: =J65/(1+$B67)^J$8 -> #REF! | ... M67: =M65/(1+$B67)^M$8 -> #REF!
A69: Royalties & Other Revenue:
A70: Revenue | C70: ='QTR-REV'!#REF! -> #REF! | D70: ='QTR-REV'!#REF! -> #REF! | E70: ='QTR-REV'!#REF! -> #REF! | F70: ='QTR-REV'!#REF! -> #REF! | G70: ='QTR-REV'!#REF! -> #REF! | H70: =G70*(1+H63) -> #REF! | I70: =H70*(1+I63) -> #REF! | J70: =I70*(1+J63) -> #REF! | K70: =J70*(1+K63) -> #REF! | L70: =K70*(1+L63) -> #REF! | M70: =L70*(1+M63) -> #REF!
A71: Gross profit | B71: ='QTR-REV'!#REF! -> #REF! | C71: =C70*$B$71 -> #REF! | D71: =D70*$B$71 -> #REF! | E71: =E70*$B$71 -> #REF! | F71: =F70*$B$71 -> #REF! | G71: =G70*$B$71 -> #REF! | H71: =H70*$B$71 -> #REF! | I71: =I70*$B$71 -> #REF! | J71: =J70*$B$71 -> #REF! | ... M71: =M70*$B$71 -> #REF!
A72: SG&A expense | B72: =1-B16-B33-B47-B60 -> 0.05 | C72: ='QTR-EPS'!#REF!*$B$72 -> #REF! | D72: ='QTR-EPS'!#REF!*$B$72 -> #REF! | E72: ='QTR-EPS'!#REF!*$B$72 -> #REF! | F72: ='QTR-EPS'!F12*$B$72 -> 0 | G72: ='QTR-EPS'!K12*$B$72 -> 0 | H72: =G72*1.03 -> 0 | I72: =H72*1.03 -> 0 | J72: =I72*1.03 -> 0 | K72: =J72*1.03 -> 0 | L72: =K72*1.03 -> 0 | M72: =L72*1.03 -> 0
A73: Other expense | C73: 0 | D73: =C73*1.03 -> 0 | E73: =D73*1.03 -> 0 | F73: =E73*1.03 -> 0 | G73: =F73*1.03 -> 0 | H73: =G73*1.03 -> 0 | I73: =H73*1.03 -> 0 | J73: =I73*1.03 -> 0 | K73: =J73*1.03 -> 0 | ... M73: =L73*1.03 -> 0
A74: Operating profit | C74: =C71-SUM(C72:C73) -> #REF! | D74: =D71-SUM(D72:D73) -> #REF! | E74: =E71-SUM(E72:E73) -> #REF! | F74: =F71-SUM(F72:F73) -> #REF! | G74: =G71-SUM(G72:G73) -> #REF! | H74: =H71-SUM(H72:H73) -> #REF! | I74: =I71-SUM(I72:I73) -> #REF! | J74: =J71-SUM(J72:J73) -> #REF! | ... M74: =M71-SUM(M72:M73) -> #REF!
A76: Taxes | B76: ='QTR-EPS'!#REF! -> #REF! | C76: =C74*$B76 -> #REF! | D76: =D74*$B76 -> #REF! | E76: =E74*$B76 -> #REF! | F76: =F74*$B76 -> #REF! | G76: =G74*$B76 -> #REF! | H76: =H74*$B76 -> #REF! | I76: =I74*$B76 -> #REF! | J76: =J74*$B76 -> #REF! | ... M76: =M74*$B76 -> #REF!
A77: Net income | C77: =C74-C76 -> #REF! | D77: =D74-D76 -> #REF! | E77: =E74-E76 -> #REF! | F77: =F74-F76 -> #REF! | G77: =G74-G76 -> #REF! | H77: =H74-H76 -> #REF! | I77: =I74-I76 -> #REF! | J77: =J74-J76 -> #REF! | ... M77: =M74-M76 -> #REF!
A79: NPV | B79: 0.1 | C79: =C77/(1+$B79)^C$8 -> #REF! | D79: =D77/(1+$B79)^D$8 -> #REF! | E79: =E77/(1+$B79)^E$8 -> #REF! | F79: =F77/(1+$B79)^F$8 -> #REF! | G79: =G77/(1+$B79)^G$8 -> #REF! | H79: =H77/(1+$B79)^H$8 -> #REF! | I79: =I77/(1+$B79)^I$8 -> #REF! | J79: =J77/(1+$B79)^J$8 -> #REF! | ... M79: =M77/(1+$B79)^M$8 -> #REF!
E81: Prob Adj | F81: NPV per
C82: NPV | D82: Probability | E82: NPV | F82: Share | I82: Shares | J82: ='QTR-EPS'!#REF! -> #REF!
J83: 38352
A84: Provigil Franchise | C84: =SUM(C24:M24) -> #REF! | D84: 1 | E84: =C84*D84 -> #REF! | F84: =E84/$J$82 -> #REF!
A85: Actiq Franchise | C85: =SUM(C41:M41) -> #REF! | D85: 1 | E85: =C85*D85 -> #REF! | F85: =E85/$J$82 -> #REF!
A86: Gabitril | C86: =SUM(C55:M55) -> #REF! | D86: 1 | E86: =C86*D86 -> #REF! | F86: =E86/$J$82 -> #REF!
A87: Other Sales (Group Lafon, CIMA) | C87: =SUM(C67:M67) -> #REF! | D87: 1 | E87: =C87*D87 -> #REF! | F87: =E87/$J$82 -> #REF!
A88: Royalties & Other Revenue | C88: =SUM(C79:M79) -> #REF! | D88: 0.8 | E88: =C88*D88 -> #REF! | F88: =E88/$J$82 -> #REF!
A89: Total | C89: =SUM(C84:C88) -> #REF! | E89: =SUM(E84:E88) -> #REF! | F89: =SUM(F84:F88) -> #REF!
A96: Checks:
A97: Revenue from NPV | C97: =SUM(C13,C29,C44,C58,C70) -> #REF! | D97: =SUM(D13,D29,D44,D58,D70) -> #REF! | E97: =SUM(E13,E29,E44,E58,E70) -> #REF! | F97: =SUM(F13,F29,F44,F58,F70) -> #REF! | G97: =SUM(G13,G29,G44,G58,G70) -> #REF!
A98: Revenue from model | C98: ='QTR-EPS'!#REF! -> #REF! | D98: ='QTR-EPS'!#REF! -> #REF! | E98: ='QTR-EPS'!#REF! -> #REF! | F98: ='QTR-EPS'!F8 -> 0 | G98: ='QTR-EPS'!K8 -> 0
A100: COGS from NPV | C100: =(C13-C15)+(C29-C31-C32)+(C44-C46)+(C58-C59)+(C70-C71) -> #REF! | D100: =(D13-D15)+(D29-D31-D32)+(D44-D46)+(D58-D59)+(D70-D71) -> #REF! | E100: =(E13-E15)+(E29-E31-E32)+(E44-E46)+(E58-E59)+(E70-E71) -> #REF! | F100: =(F13-F15)+(F29-F31-F32)+(F44-F46)+(F58-F59)+(F70-F71) -> #REF! | G100: =(G13-G15)+(G29-G31-G32)+(G44-G46)+(G58-G59)+(G70-G71) -> #REF!
A101: COGS from model | C101: ='QTR-EPS'!#REF! -> #REF! | D101: ='QTR-EPS'!#REF! -> #REF! | E101: ='QTR-EPS'!#REF! -> #REF! | F101: ='QTR-EPS'!F9 -> 0 | G101: ='QTR-EPS'!K9 -> 0
A103: SG&A from NPV | C103: =SUM(C16,C33,C47,C60,C72) -> #REF! | D103: =SUM(D16,D33,D47,D60,D72) -> #REF! | E103: =SUM(E16,E33,E47,E60,E72) -> #REF! | F103: =SUM(F16,F33,F47,F60,F72) -> 0 | G103: =SUM(G16,G33,G47,G60,G72) -> 0
A104: SG&A from model | C104: ='QTR-EPS'!#REF! -> #REF! | D104: ='QTR-EPS'!#REF! -> #REF! | E104: ='QTR-EPS'!#REF! -> #REF! | F104: ='QTR-EPS'!F12 -> 0 | G104: ='QTR-EPS'!K12 -> 0
A106: R&D from NPV | C106: =SUM(C17,C34,C48) -> #REF! | D106: =SUM(D17,D34,D48) -> #REF! | E106: =SUM(E17,E34,E48) -> #REF! | F106: =SUM(F17,F34,F48) -> 0 | G106: =SUM(G17,G34,G48) -> 0
A107: R&D from model | C107: ='QTR-EPS'!#REF! -> #REF! | D107: ='QTR-EPS'!#REF! -> #REF! | E107: ='QTR-EPS'!#REF! -> #REF! | F107: ='QTR-EPS'!F13 -> 0 | G107: ='QTR-EPS'!K13 -> 0
A109: EBIT from NPV | C109: =SUM(C19,C36,C50,C62,C74) -> #REF! | D109: =SUM(D19,D36,D50,D62,D74) -> #REF! | E109: =SUM(E19,E36,E50,E62,E74) -> #REF! | F109: =SUM(F19,F36,F50,F62,F74) -> #REF! | G109: =SUM(G19,G36,G50,G62,G74) -> #REF!
A110: Adjusted EBIT from model | C110: =SUM(C112:C113) -> #REF! | D110: =SUM(D112:D113) -> #REF! | E110: =SUM(E112:E113) -> #REF! | F110: =SUM(F112:F113) -> 0 | G110: =SUM(G112:G113) -> 0
A112: EBIT from model | C112: ='QTR-EPS'!#REF! -> #REF! | D112: ='QTR-EPS'!#REF! -> #REF! | E112: ='QTR-EPS'!#REF! -> #REF! | F112: ='QTR-EPS'!F17 -> 0 | G112: ='QTR-EPS'!K17 -> 0
A113: D&A Adjustment | C113: ='QTR-EPS'!#REF! -> #REF! | D113: ='QTR-EPS'!#REF! -> #REF! | E113: ='QTR-EPS'!#REF! -> #REF! | F113: ='QTR-EPS'!F16 -> 0 | G113: ='QTR-EPS'!K16 -> 0

Sheet __APW_ACTIVE_FIELD_RESTORE__
A65536: 8 | B65536: 0
